Workbook

Sheet 4.1ЧНП25
A1: № п.п | B1: Наименование | D1: Описание | E1: Ед. изм. | F1: Объем:
A2: 2 | B2: Облицовка стен по системе Knauf / С-626 / в 2 слоя / А-10, А-27 | D2: Облицовка поэлементной сборки Кнауф С626, профили оцинкованные; Плиты из каменной ваты; КНАУФ-лист; Тип: ЧН-25 | E2: м2 | F2: =C5+C6 -> 383.867
A4: № п.п | B4: пом | C4: объем
A5: 1 | B5: 0.005 | C5: =43.18*3.15-2.1*1.6-1 -> 131.657
A6: 2 | B6: 0.015 | C6: =81.9*3.15-1.2*2.1-2.1*1.55 -> 252.21

Sheet КП
A1: Указать название организации (на бланке организации) | D1: {"estimateId":5150255,"estimateVersionId":7054632} | E1: GgAM2FBpWmhyGMfZ9Tf1NMFQ/DyspR4qZ2otftkkqNv2yla3zlQjb/blsiN2pwjuAdlC7VVga3/2oaNB1nYRUHySUe+1/a6iIWG1885s5p9yZTDQhAlICQE6+uskosxBc78CWR1P9cdQfRKseE33QA1QOxblQVhztfLkGiv5gBM= | F1: 7 | G1: eF7s/ftzJMeR54v+K2UyWzMJQNbmK/LRa/NDAwR7q9VAVSNRe2xnekxWBRR2aSuSuiR19mVjxmaLEmcpiXrOzKFEUpQ0M/vDvcea/RCb/aLZ/Qdu1r9w/5ITkZVVQBUiIt290qOg2dVMg90AGu0fj0z3b4R7RPz3b7zzX783+ca1b7w++t43dr7xf46++/3JcfWZN77/3e/ufGPyX04m35194htvz79B/v6/3/nGyZuvv/7mG3e+ce2v5B/UT5G/Pf/szp3zH3an/ml3zn9c9b1vn39b9efyD+XT8n75ZXl/+t70x53yRfWHB/Lji/JJ+bhTvpy+Wz6s/6i+64fyv08631Tf2Cm/KJ9VX3pq/M5vVf/eyZtvvnX62hujd2b/6PWg+uzk7Xdee11+7ujN/9w7vWDwG++89s5/vfH91+af+5udZdo3zl77DzTa/37nzvk/K/9N+adrIhB+KMTOxS/9u8lbb7/25hv1d6S+iJMo/BsdyivroMgHgMahs+TVdSx5+7X/QHyAdKbsr2PKWk/z78tfl/9YflL+Q/lx+amnPpS/lf/36/J35T/Lj59Xn/l1p/xMfuLX5a/K38g//p38nfobv5ZP9e/lN3ymf2bDa8NwU1gPux1J8XJ6V75p8t3c6YRe+VVHWn1fvXHT9+Sb9qL64hP16a+n73rlo52O/NZn3U4of/O5xPyf1cvdSVLRKZ+Xj6d3p+9pOaNrw2hTnJ9LlJcS4rliVQFppzO9Nw9Q0nwJMP1IclWM5ePykYw/L8s/yd+poPOkQn5aPpv+dPoj+f2Pp++p75WOeVx+Uf099Vvlhsfyb30xfV9+fKT+temH6tOzGPhu9fHDmbPk3/iw/Fp+27PqL9Uhcf6Jl9L5LzvyH3wpDf5afupx+VT+C/c76ofI2PhS/qC7apR+VX7eCcN/pXV3fG0Yb8rdn9VOfCxd9uPaucrvy2Mwc/bLKqo/UC6rvuXBEqd8dT6TT5l8rbQvz01xrS82Rfnb8o+etO338pX/tPy/OvKD/D+dlQNx7WhTVuapH4RBmCWpzrJCXBtuyjL5/L6sAsa78kGQ+fBfy4+6B1lcu55uysSP1WOpQsWXSpB0ZDD/vPydzspdcW13Y1aqcK3eq8dV7LigsS5EHp3Re+La3saM/rga/cpo+dbfl1bOcoyKfEY3vyKuvXIFLZah693pR/Ljj+SnZFbRmb4vru1vzPRfl49kpleB9nlXZ9yr4tqrGzNO+nX6k+kPutWDerfOnlof3hDXbmzSzPKZpzJVp/y5PtD/W3Ht327Mvk+l8vhb+XA+nimHmak6K3viWm9jVv5TFaWk0pRvzL3yi26jkLmZXPt2silrf1uJ4MfVq35fipkPVZ66c+cNJfPUvFQiPLoYcrUAG/P159L+3+2oSckn+nD67Y2Zhn4MbiXXbm3MWt30AWj3QXLt8M/68T3YnNebHt/DjZk2i7X6ac2OdDD06egn1/obg0C/g4Pk2u0/62d5sDFfNz7LtzdmGvoxOEquHW3M2jVCcZFcO/6zfnyLzXm96fE93phpbYXiYXJtuA7EO2++M/ruJYY733hj9Ppk9mPpHBcWxOCP+ysi4+D53tvfe+tYfe1A/si3Xht9d///9f3Xvve6/GkayrMVyr8ohgffPMi0a3kHzPYWr781eOMtqJGHeiMPmY0cvPXaie5xuWSj8tb2wppVWcFj5TtrDXuh92jBaCtuyI/1Bh4zGggebuWl7WPDcA95LPyPr52eTt5Y713/93qf/nt2i3FD/5d6M/+S3UzwA6A8tv2Xhgfg+vX1DF0rAX9ciZZn5ZPpD2arn1WB/uV5Ve3JbEGqWjQtn8qP88/LT/2gqu4/n/2l6UdaOJFl1+Qjnm0K8Gc6q3ZFlm/KoE9qf/9otsp/f6Yap3flp94915B6b+5t0O5H5f3ON//VtzpVseeFKqPqLHxlcxbqzPm30hz1+G3KpvLn+scv9zdl0C+VDq2esxfLpdwn1R/ulV/L31WffHpBuNYFblVMe1AVh1Ux5dms+D39qf5R3RyjelSbHtONWad/THNfPqYbs6n8heEx3VjLjvExrR6+apKlImf9qH5R95u9rJo5nk7vTX/aqXpg3q1i63vqIe18c/aYz7rZ5hH4ycUIfF+rI/Y26Ab5JH9zTtccejdmp+GZDtQzvSmbyl8anumN9Wt9XiX4px0Vapf7h5Sgmj/cqqniPdVG8171tUfVspO2oLq3QZaqV6xreAw3ZZXhMQzVY7gpm8pfGR7DaFMG/fJiXCy/kv/9sPxKrVvNnk7RUYnd1HOyObNBSX1T1hmevEg9eZuyad/w4MUbsqf8h8tTxo7qx/i66mF9XPU/vJjlZNWI+T+qzkkVCmUKlM+oTNnz8e/MP/Gtqrnz5awXUT7CH9YyVYXSL6VYfTb9cdXto9TC80v/kmmStTkXmThVrUG11TQ9/5sy3PD8x+r535RN5d8ZXgCxKYN+IR/uR/IZvVgQqFqEZ1N+VRp4PO87fqppM5YiVj7j9+RfvdC2VsXv59VLc3mrhfwG+SXDU74xPzxQfrjgBa+S5JomSMNTvinDDU+5asPdmE3l3xue8o0VS/VTt6ov8OtK+tabitQiwsPq+16qLuIHnVoAq2XG2X6i8u/VH+SvL229mXsbZIXE5E0ZZ3haE/W0bsqm8h8MT+vGFsBXlmM/V/sBDE/Zxmysll6ryK86mO8DFgI2ZarhmUvVM7cpm8qPDc/cxmoSn0q9+uH0vYs7gqQouNuRofNj1abxD/I/htWqalVALXD9rfzU+/NNODOhLEOpd2FnVBVl/9UsqlY/omH/5d4GPXJB76tnu3NJIqjP/iudJNJK+Fc2h2J4A1QRbGM2lb8xvAEbK4tceAMuPZxzsaB6q6S2VU959TSo5/vi5jL1N+ZTumeVcphtnAm9qFMJi1nYXH4f6llV9QipbnvRWWwNfKyeLvWvXZx8qn9TmVS9bF+uyBH5RdObtDHPrrxJqzZXn6ucY3hvNmW44b1R1buN2VT+VvveJP7G6jT/XAnoWeHtXF1fqNPdl49ynRqqfa3VZtQqpKrxv/x3dRPQWYH/kXwtPtJGXNJa9QaddmFDjXr67ftrXtmcodpXQJpzbbg5m8pPDK/Axso6v5ot581Sx8O6bP3uefKYb7yeLSHo1z42aP4jGXnVUyiVfB2LHxoew02ZaHgMA/UYbsom/ZxMPoYbK+t8Ouv8tioRmw55eeHvf7NSHjL6yhgttf236o20j6pnuFreUwvB96bvV8t7z2at6NXJDi/VHlY1f/hRFYnrsK5eA2VS6Aexesjkf0X936Q2Sa9bNujPyirvfJJ7LlSaPil9O2uqlh59XH5ZN1ZrAV/ZHKAaA+/OnTfUGNT/TT3DqxaqV21ThpafGV61aFMGfS4f+q/UawYL7ZuyUz6Rd6tqjWGd8pXNmWZ4ziL1nG3KJsNRDIkfb8qgX1YitpKws6NPqsK4DMNPKq1RTQen73audco/dst/6Jafdi+c+jKT09Of7szE8LPuTmfivT567buGp3RTlIZHIVaPwqZsKj83PApiUwap4wIutjy/VKsGahXuh+XLdsZ/U2iG8Rdq/DdlU/l7w/hvrEyhzkCq6pHVkVH1gSxPO7OTwOr57/mkd/aoGAZ6UwyGgU7UQCNt+uvqJ51OBqN3/qP8nLQwGZ+E4/HI9ybxmfDizD/zsiw980Zx5I8iEQenp6PZd7715n+e/Saf/WfBNvnuZLEX5SIceNNdIF+/X9Szv5fzVQ01Tk80n/cu9DivfLs6/k3bpn09u9aDL9lCnfI38i8GEdgZLezYy/U79pjQYjwabrvPoZ7nkIlH4HnA+4IUTl+P02fCgb+Ga24Y1GMVPFihj8PCPXHHepZjJpYAx4J62oZ6lCEDimJJ7iwngVW0tycn77ymyXAyCXz/9fFEN0KX00CgI7quLxpEQeDHcZgEq1iz5Cu9D7ZQZcTvfK9KiY1GJjoTd4kmrr7CFifCMqnqs1k95HKRKZ/M9KzUtrMDHrWr5nv5tR6R5lIuNOO0kAsDf+cgEPKXn+qzIpViNe0BKHBB6FCafihNPzSZfkg1XeBNR8WcvrS8Ly3vmyzvUy2HvwlrJjNJUEiCwkRQEAku5a0GAtwjcyzNPpZmH5vMPqaaDY/jhBQlrR5Kq4cmq4cUq6vn5Y6LbGTIR4G+hDe3OjT6GmwkKiHprdylWgl/E6E56bOqcvJw0Uz61JaU9JPvwL/WowI5TkuBPhuRrXeQjvQmH5JNFniTUXGlb7C4T7YY/tCvm370lhdUy7nTjt7cY7K58EBNSTd6a4ckay9EbPY0Y0o0+iL93O7I6GWwmchE0w11du5S7YS/ddBU86lu44wm2VQrhl/NOqZeqvO+ZIJ6aqhDBoHMPURCx7knNOQeqvUOco/e5EOyyQJvMirI9A0W98kWw9+CdXOP3vKCajl37tGbe0w2Fx69KblHb+2QZK0yt373HOQeU/bR963MLY+NfgYbis4+3Vhn6S7VUvibB80/v6j6C2a7H1/Mr515VDflVmdwTe/KzDM7aPRPto0Pe0Eo0w4RzHHaiQxph2q9g7SjN/mQbLLAm4yKL32DxX2yxfCHf920o7e8oFrOnXb05h6TzYUHbkra0Vs7JFl7ISY6STumxKNvZJvbLoyeBptKSDzdXGfrLtVW+NsHTT2/XTQ6/akz/ajqQb4733U1O/exmgWp7uWqwf6r+caQixux5peiqSyl5ko65r0gkpmJyO04M8WGzES13kFm0pt8SDZZ4E1GhaC+weI+2WL4u7FuZtJbXlAt585MenOPyebCYzslM+mtHZKsrZ6LO4uE9Fe2DPWf33zrP2kQKOnJlKBiK0JqdDjMUlJ2Mhm7SzV2NVCb3IpPTzudqtXy+dJn7lczpxfVFhvdet0skanzzNQE6oEOdY+KuhrVjePyugov33ntbchjpLPwFaqFAmUh0bp9qnUJzLrXJ6O3v/8W6Gl5rl1ofpVqYAozcPJfvjd5422dgW+sGBh0/Xoj54qJN6gmZjAT/883v/t90AunM+7fUo1bzcgG46osAfFelncjnYE9qoHBauY1WKgkTpXGIKJh1Wy/qx/zm2SrgalrYbVRMKyaGqXCYOy3ycYCs9fCWI2Zl5SCdN32UX94+Mo3pV07Hf0a6i2yycAchpppQJ+KA7LVMdJquIycuVq+ZVtLTjc5/pCMIJAI4AdGenV7btalCQfVWmD++l7bgWNAthiY0L6HChoiCbtCa+htsqHAtPY96PgPFgHjtjlgHJHNxSS6Np+EgmrxpSmnzWJ6oLhtDxTHZPOBGRA5/5QPybE+SAxJlv7N3/z136j/7ThrCdHq3+sqrlqMz4xuBhuJm3tqrdylWglf94FOOqv78qrlTzmd/LpaEb3fmR8uoBY41Tz0mbnzQ1zrUWEcL3QmOweRqfuDShDjCeARZrbYmewcGsw+JJst8GbDI0u14Jns9A1W98lWwx9+cPIxLHomO4XB+oJqPffCZ7JzbDD5mGwyPHAjk0+1+JnsDA0WD0kWX1gAZU89plXPxGp3bvQ02Exk8jEteBLthL+ByPQzOwTxy2rJc9Z3qPaiz4/3WUpOOqC9IJFpiAjlOA0ZtmKRrXeQggxbsMgmC7zJqNjSN1jcJ1sMf/DXTT2GLVdUy7nTjmGrFdlceMCmpBzDFiuStRdWpB2kG1PC0Z8zXVue+kY/gw1FJ5xuprN0l2op/M2DppzPqoPo6iPQv1zeDFwdRQfISTrEvSCVSYiI6TgJGe61JlvvIAkZbrkmmyzwJqOiTd9gcZ9sMfxVWDcJGe6/plrOnYQMt2GTzYWHcUoS0ls7JFnrds5jTkP6EzXmtrs+f2KWhkxzH6Kt8LcPmoh+Ub6QU5r36q6O2blbVXpRZ2x92JkdDv+4Pvq3Oj51tgWLkpoymZqI4I5TU75zEApDeqISOEhP+c6hwexDstkCbzYqFvWl1X2D1X2y1fAXZd00le8UBusLqvXcqSrfOTaYfEw2GR7wKekq3xkaLB6SLHafskxJK7daHxr9DTaWlLRMaYtoLfxthKatPyx6D7+an5KkLi1ZyWXT9xe5jJKvcpmviMRu81XoG3IV1Xr+XGUw+ZBsssCbjApCfYPFfbLF8LdizRxlsLygWs6cnwzmHpPNhUd2Qm4yWDskWXshtDvpn18kJ0N6Cq0ncqTgvcWtdNAvcpOxpEQ1F9h/CE1OH1f3+zyqDlBqSEpPVIfDF+p0i9ntVmpLmLoYqzo3t6yu66waIao/vDjvilBlqJUEeP98pvZ8+mH1U55WlzXPr9uqLhlS/fvPq/PVL9z6uqP7eS9npy4/qe7HfVp/61c6v+9R/b6aZlpp6C9/Ie19WO/cvq9cJ4E+ql398/LTeoF16cLr8nlnt3fgyZH7Jx3gK1RAgQKEwM0O6VIj96zbKf9YTcnV4Dyvbij5sON1os70g+l7XXV09ks58n8rwdWD43VC3++oCzy6OsR9KmICQ8RsKtD2nL9KNRDYg9nGpgKqicDuy/U2FVCNW5Upa24qyLuhth2tR7WPZU/BpVzfe3X/6Kh/9M1Zn+VMdQc7B2Eof0XyV/wtdVWOhKj6L/Wa4CYZEZj78RsQ0jT3u742m36bbC0w++N2IIT+fAfCzMc6k2+RTQYqgPXmajP7JclWz8xwQGYAZlPCjK1uM5aGLw2BcT8CGUEgEcCPj/Tq9tys1Qkc2Vpg6gPvRwAEnUIGnUIGnUIGnQIUdAZkPGDixG1eCIIkE4aIc5tsKjCBwrcvLKLNbfObekQ2F5NSSQ/OzPaBPdIUVPt5NzMsosxte5Q5JpsPzKbIxQD5yBzrI8yQZKky1Y/FmQjHgXeWn8VePBqn3ijJAi9ORpN4NIon4mw8gzEuE7xePz8aQOpSgWmxIMBRQvF0CwoWKsyigo5jl5NjVWfYRge42vDb6nrWx9VUXV2j9uHiJuFL03f5ydnNxPfqEzXfK19MP5pdYKwOmvmTnDffm763U13RLefGX9UnzehnZHucjhJwR8FnzzqKfU6KVYVgoUBMkOe3Mj6bLV/oqF7lpFoVBhYqxKxah3GDE2NVNFgw1px5M0KsSgkLxPozdEaOS7N4CwhqJn/pOUuzbqJtD73JyoeI/G3MMudzzUDJJ6kCA/N8k5MaEQDB0yT4iA5Y2bCvHoTNOpqD5tEs2IgrPXoaZHEYjCZeFIvUi8engZcJceZFaSgCMUp8IU7uuNej2nB1vY5iCFfA8JzrUUYORFSC6tGl1vbnRnH6dFEkezITpbMCzcPqyvaXSzWv6svz6oXORXucLhJwF62rRBkpEIG4bSXKSOVSiTJiuFOijBDYdAgYCbMSZeRwpkSjKOyGsY7vJisfIua3qUTDWruEZiXKSY0IgGQlah7RASsb9tWDsDUo0cbRLNiIZ9cu+MnJJDnxvSgKhBfnUeLlJ9HES8NsfJaOotPTvH7OnSpR7ULZ9TDCugKG51yJMnIgohJUiX48X8SsGn4uKcvpPXXCqRKXtdJUW/w/qPqi6muHLmjU7+gcssfpEAF3yLq6k5ECEXZRuvOhjuRVThIWrRkKHccNTg53YpMRApvxIEMR+V3taPQ4QZypzaSbaYuTN1npEFG9Ta0Z1eokMmtNTmpE0CNrTdN4DljJsO8dhKxBaTaOZcFGXCnNSZyOx/ko9QIhQi8IJpmX+ae55/vCF0mWBbmoNZhTpRnrXHG9nn0gXAHDc640GTkQMQmqNH8+6+DXLV+q68W+6ryS+H4nCcX0/VD48oPvm9cyGdEFHH1dTclIgQivCE1pajtnBGGRlEHXFzqSG5wk7kQlIwQ2uQEGI+8mmXY9uccJ4kxUxmkWdX1DNZ0TEBHD29SVca1FjEdaH7BSIwIfWVdahnTACod9+yBwDdKycTgLNuLZWdU77g6qtpfKhRXT+VV+862eWmt3qdauPmEOjyHQHKJT6UX0oQShuNaj8js+lCAxREiq9THeenjz+exQAr3Jh2STBd5keMN5dSiB3uI+2WL4O0IPwrONLHrLC6rl3IcS6M09JpsLj/PIfQjVoQR6a4cka6vnYmativfODiUwHXAdJlYIt9f6LTKVOVsRzV0N1m0eSmDIRlUH1tPqdICv5ccf8Z03UD6t/uKsc2h26pw0YH4ugtrPvlOdizq/+WF6T3saweybZv929Tn1jdMPVB4uH9R7Hd6bbYPvdoLQ1kFGHKXVpHR1jzAgAgoUIARu+QiD5VMKFidjeIvhkt/z8fkjqf7wO2/6rle5oFpMk984fT8RarSD8pPyj9VvwurP4Y6v/iOqj+Uvy0/Lz8vfd0Tke6EfaF/XfaqfVudmLZyDoDXwVaqBwO2cqIUm0zkIRBOB2zjXXEEiGofZtAnwXhKm+oTRoxq4uYMQ0p2DMJO/8p2DyJe/gnpfcmI9DIGKCdQc+MMQgjyPTdcxkq0Fqg7kYQjJ4jCExHwYAtVkoPJYb444X1JLtnpmhgMyAzAvE2aK823KydbSEJgPQ6AiCCQC+PGRXt2em3Vp4ki1Fpj/wOuSgMBTyMBTyMBTyMBTyMBTgALPgIwIzKC4AxHCPA8MQec22VJgIkWch5AszkMwvqxHZHMxqZX07MwXfK3BpqDaz3weQrK15HrzeQhU84EJFbkOIR+ZY32QGZIsrebEZ0kcRNGZF5+mgfxwGnl5NBZefBKNT6J8dBLG9UtqXKF4fdRuL4b5XpTQfpj+JUoonm4tw0KFWc/QcexyciDqeNCFjs+rs/DuTn+sJpP3pu9X6xDTH1ZL7OpQ+/fUQrtXrV3cVasUat6pDkbQoO9xogs4OnxyraPY56RYTfsWCsTU19jfy0jC0owRx91M6FBucKK468ZghMDWgwGjEWZBmHdzw7SbkcVZQ0bSjQzdGJx0iCjexqRxPnVM6/J9ap4+clIjQh941gMdzwErGfbVg5BZx3LQPJYFG3GlLMej8HQcjyaeH6WhF0fhqZel8YkXnchvzfKTcXRaP+VOlaWhXcN+54XGFTA858qSkQMRk6DK0sVJW9oB3+N0lIA7al0dykiBCMYoHQo434CRikWTGs43YMRwp0cZIbBJETASlhoQI4g7MSq6SarDu8mKh4j8barRrFYwmVmNclIjAiBdjZoGdMCKhn3zIGgNcrRxMAs24tnxBmdhJPIw8yZnY6lf83zsZacT4Y3TE5GnZ2d5cja6416ORjpXXA9zrCtgeM7lKCMHIihB5Sj1oC1tn1f1lUR0vCC0bE1jdJCAO2hdGcpIgYjCbctQRiqXMpQRw50MZYTAJkPASFhkKCOIMxkaBFk3z3V8N1n5ECG/TR2a19IlN+tQTmpEBCTrUPOIDljZsO8ehK1BiDaOZsFGPGv8n+SJOMki+cUg9mL/dOzlIz/3xNkkOA1OzvJgVI+4UyEa61xxPbLfs6BxBQzPtRDl5EBEJagQ/bw67EBtLJj+pHxWHah1t3zwnZmmFP6W/H/teO1xcgo455p6kpMCEU0RetLQWc4JwiIh/a7wtU/WDU4UZzKSEwKbygCjEQVJN/C1abnHieJMSIZJ3o2105abrHyIkN2ikIz8mfSIzFfVsVIjQh9ZSJpHdMDKhn37IGx2Idk8mgUbcSUkU5FmwZmfeCfCH3txGIReFp+eeiej09MgOT0RIhzfcS8khc4V16MA6woYnnMhyciBiEpQIbm0z08djfBM9WpWOwKfVcdoTd+dflRtVlUbPL+qFWb53AuEtoF+j5NfwPnXFZiMFIgoCxeY6gJqHcmrnCQsClP4+qnmDU4SdwKTEQKb4gCDIQVm4HczbUNcj5PFncKMu7H+lFZWPEQob1Ng1rcZRea7qVipEaGPLjBNAzpgRcO+fBC0Bn3ZOJgFG/HsLK2/cXuclnYJ5XoUWhmzVUb+g7S0du5S7Vx9sNY/Quvz8rfl76ruR+NBWJ3qZH4pDNUpJOX9zjfrQ0kqaVgfEFI+0T50e1F4rUeFdXteVhTtHAR+YAiEVIQYjwDfoVgdmiXtPjTZfUi2W+Dthm9NVCdnSbP7JrP7ZLPh7wc97lZbn6X5hcn8gmo+8xla0uZjk83HZJvhER65gVUdpCVNHppMHpJMVjbXL6WDJGXYmhpFVstzo7PBhqLTlH6etUu1FP4iQhPVL1aPdSwfL44rUu1WT3THaj01HOMYRTItEdEcp6V45yCWqSmV/81zQ3aikjjITvHOoTT/UJp/aDD/kGy+wJuPCj99aX1fWt+X1vcN1vfJ1sNfkXVzVbxTSIpCUhQGioJKwZ2y4p1jafqxNP3YYPox2XR42KdkrnhnKC0fSsuHBsuHJMurZ+eOuwRmSmGxzfbMN3odbCohhelt3aXaCn9DoUlMd2DxPInpTN+LYpmoiOY7TlRCJir9kT8HZAIHCUrIBKU3+5BstsCbjYoufWl132B1n2w1/HFfNyEJmZD01hdU67kTkZCJSG/yMdlkeNimJCAhE5De4iHJ4gvRWxnu4BziulCsQ7geCStCaHQ6zFJS8jHN93apxq4G8DbPINYdk784/nW2ReWL2bVK1WG+04+qY36fVN/yUk2xOkuXxDMdVKz5eS+1RxHr/L5H9ftq2rmypwpTAQUKEAAXeHFn+pPK5D+VTy6dK+x1Qr8+TljHsU/lWK0htXDqb6Qz8FWqgatVccZTf6kmAg8rXLPUTTRuVZOseepvmMh8oo3RPaqFGzv2N0p2DqJU/srkr3x28qZM+pYjf8mIwPSOP/I3TXO/62sH5Ntka4EpHnfkbyTmR/7OfKwz+RbZZGCiX2+aNq/7i62emeGAzABMmoSJWn0SpzR8aQiMR/6SEQQSAfz4SK9uz826NF+jWgtMfuDmCUDQKWTQKWTQKWTQKUBBZ0DGA6ZO3HG/QZBkwhBxbpNNBaZQ+Hm/i2hz2/ymHpHNxSRV0oMzb0qxRpqCaj/veb+LKHPbHmWOyeYDsylyzi8fmWN9hBmSLFWm+rE4E+E48M7ys9iLR+PUGyWZ1PrJaBKPRvFEnI1nMMaVgNdHbTWNL25f1jFejxIcIxROt2ZgYcKsG+g4djk5VlWGbWyASwouzmTTzsj2OB0l4I6CT5F1FPucFKv6wEKBmCBDDsPgpGLpM9fGlBucGO6azBkhVoWEBaKNGTojibMW8yDNuon+jGBWPkTsb2OWOZ9rJnVbsvmKGVZqRAgET5PgIzpgZcO+fBA262gOmkezYCOu9OhpkMVhMJp4USxSLx6fBl4mxJkXpaEIxCjxhTi541qPhjpHXI+sxyXrHAGDc65HGTkQMQmqR6mHss2qMA/lJ79UFZgLha3qy/Pqhc5Fe5wuEnAXratEGSkQYbhtJcpI5VKJMmK4U6KMENhkCBgJmxJlJHGmRKNI5rBYx3eTlQ8R9dtUovUNB5H5tgpWakQIJCtR84gOWNmwLx+ErUGJNo5mwUY820LiJyeT5MT3oigQXpxHiZefRBMvDbPxWTqKTk/z+jl3qES1C2XXI+tJyTpHwOCcK1FGDkRMgirRj+eLmFVXzyVlOb23I9VodVjbTGmqPZYfVM1Ps/2XFzXqd3QO2eN0iIA7ZF3dyUiBCLoo3flQR/IqJwmL1gyFjuMGJ4c7sckIgc13gKFIRJh2U+149DhRnKnNpJsZTtbgpEPE9Ta1Zn19QWS+i4KVGhH2yFrTNJ4DVjLsmwcha1CajWNZsBFXSnMSp+NxPkq9QIjQC4JJ5mX+ae75vvBFkmVBLmoV5lBpxjpHXI9yrCNgcM6VJiMHIiJBlebPZ236uuXLF9Wxba8kvt9JQjF9PxS+/OCbr5jgRBdw9HU1JSMFIrgiNKWp7ZwRhEVSBl1f6EhucJK4E5WMENjUBhiMMI27QZLoUHqcKM5EZZxmUdc3VNM5ARFRvE1dWd9GEJnvlmClRoQ+sq60DOmAFQ77/kHgGqRl43AWbMTVmW07i5zsdEOnvmAeW48/zuJVVCcbOoVhQyfV2NW4seaGzr+vFghnB7CpTkmp++5O35v1Xr6cvi8l4J+qr8+6L6u9eH+q/qhq4lIbTt/v1FXU59N71T5K+XOmP5z1Y87XH1U5XenI55cK6upv6tyzR3VPDHMPbt+lzsJXqBYKlIVE6/ap1q0GaLbtkFQDgXs6UHrTsB2SaiJwL8d6QpJqHGbnBsB7Qmdcj2rcxnZCxsHOQRzONiPFvm0HJBkNmA/xOyCzXCRd/SP8bbK1wJyI2wEZ+/MdkLHxEoNbZJOBmbENNS1JtnpmhgMyAzB90XdASsOXhsC4A5KMIJAI4MdHenV7btaKtX2ytcB8B56MAIJNIYNNAQo2AzIWMEsidz5GcRQbIs1tsqnAbAnf+biIMrfNb+gR2VxM/iQ9MPXUzh5hCqr9vDsfF9Hltj26HJPNB2ZR5M5H+cgc6yPLkGRpNVE7S+Igis68+DQN5IfTyMujsfDik2h8EuWjkzCu31LjlNmygECbNht2PtYXKIEZoXC6ybWFCTPB1nHscnIg1uugc+/P6+n2j9WpSffkZFsdYyTnzuoEdXUk7Xuqj8erjj66qw45Us3kagukBn2PE13A0dedtTJSIJYeEbNbUycPJwlL2SUW2lX+G5wgzqounBDYVV/AWIShvjOix8nhrOSSdCN9vYWVDhG/25ghzueJ9aUqsfmGHFZqRNADT3Gg4zlgJcO+dhAye7GleSwLNuJZH0+aZkl4lnlxPIoWhZnRJvt4TLfoxCHWETA454qSkQMRkaCKcun6xd9dvGlxR38dY9XNE4TyQyJUDacTlJ+Uf+yUvw2E33lV/prVcKT+vKtE6rtdtVmuG3bKX5afSv36+46IfC/0A+1TsMfpPQH33rqilJECEZ/hotR4eSMnCYsojXKhA7nBCeJOlDJCYLMjYCyC3NBczsnhTJSGQVd/9NVNVjxEDmhTlYa1kgnNqpSTGhH1yKrUOKADVjTsiwdBa5CljYNZsBHP7m3ccXlpo7n7J7JCilVIU/dPu9eJaG3dpdq6+nTxXCeiuQXrZflUB7IXR9d6VBi3l4vE8c6BCOSv1BDwqBQxngJeV6kuGJGmH0rTDw2mH5JNF3jT4TUVdcmItLwvLe8bLO+TLYe/CPQoO6vVxjuFJCgMBAWVgPmyEWn2sTT72GD2MdlseGBHluDUhSPS6qG0emiwekiyunpe7rhMT6YqW2y1PjH6HGwsKUGZ+lOJ1sLfzPZTVH0G09PzVRDV0/pk6RoSHexeHMs0RgR2nMaEIX1RrXeQvvQmH5JNFniTUXGob7C4T7YY/lKsm670lhdUy7nTlN7cY7K58MBOSU96a4ckay+kJRXgHW2dMN/GGAsrBPje+xY3T1j2euxSzV0N1mtun1i6DwuRk3iuuiqfVn9xdp7d7H5jacD8Si51F5T8ni/Pd3xM72kvwpp90+zfrj6nvnH6QVVIeFCfwP3e7HKmbicILecaUkdpNSm1souD4/YsKqBAAQLgGm7PWlzL5i0GTH7PUrno4/J33vRdr3LCxbKQGu+qKlT9Jqz+HO746j+i+giqBe1TPQVs0IVXR8rnWgNfpRoIbLWFFz0sG1KIJgJbbNcsZxCNwzTUQryXJ7HpGByqiZvblpLsHMSp/JXJX/nOgfDrrnHrJV1kTKDuwG9RCfLc1Dj+bbK1QOWB3KKyuKQrNl/SRTYZqD7WmyfOizxiq2dmOCAzAHMzYbY4byJfXNIV2y/pIiMIJAL48ZFe3Z6bdWnySLUWmAHBlTJA4Clk4Clk4Clk4Clk4ClAgWdARgTmUNx2lTDPA+NuFaqlwFSK2K2yuKfL/LIekc3FJFfSszMvQlqDTUG1n3m3yuKeLnugOSabD0yoyLUI+cgc64PMkGRpNS8G9SEqGOMqxeujNnsLbTd3xwmOEoqnW8+wUGHWNHQcu5wciM4S6GJHq/tVGNEFHB0+wdZR7HNSIJpkEJNf434VRhKW1sA47mZCh3KDE8VdcyAjBLZHCTAaWRYEedfXbwToccI46xA0b1vhpEOE8TZmjfO5Y31NU2y+dIuVGhH7wNMe6HgOWMmw7x6EzDqWg+axLNiIK2k5HoWn43g08fwoDb04Ck+9LI1PvOhEfmuWn4yj0/opdyotDV2EKdYVMDzn0pKRAxGToNLSxSWw2gHf43SUgDtqXSHKSIEIxigh2nz1FicViyjVTldvcGK4E6SMENikCBkJWxmIEcWdHBXdJNXh3WTFQ8T+NvVofVlTbL56i5UaEQLpetQ0oANWNOy7B0FrEKSNg1mwEc9u3joLI5GHmTc5G0sFm+djLzudCG+cnog8PTvLk7PRHfeCNNK54npsvxpC4woYnnNBysiBCEpQQUq9BVbb7lV9JREdLwjN9yZwOkjAHbSuEGWkQEThtoUoI5VLIcqI4U6IMkJgkyFkJGxClBHFmRANgqyb5zq+m6x8iKDfphKtL3OKzRdzsVIjYiBZiZpHdMDKhn37IGwNUrRxNAs24tkOgEmeiJMskl8MYi/2T8dePvJzT5xNgtPg5CwPRvWIO5Wisc4V1+Mc6woYnnMpysiBiEpQKfp5dReX2mEw/Un5rLrv9W754DszVSn8Lfn/2vHa4+QUcM51FSUjBSKaIhSlqcGcEYRFRPpd4WufrBucKO6EJCMENpUBRiPP/W4Yacejx4niTEiGSd6NtROXm6x8iJDdppCsr26KzTdxsVIjQh9ZSJpHdMDKhn37IGwNQrJxNAs24kpIpiLNgjM/8U6EP/biMAi9LD499U5Gp6dBcnoiRDi+415ICp0rrgv7meoaV8DwXAtJTg5EVIIKyaXtfrrTIKfvXjwyslaY5XMvENou+j1OfgHnX1NgclIgoixcYBrPd+QkYVGYwtdPNW9wkjgTmJwQ2BQHGAwpMMNIPx49ThR3AjPu6i/5uMmKh4jkLepL4c8UiTDfUsVKjYh8dH1pGtABKxr23YOg2eVl82AWbMQbOuPR0J8pAitmvorp6hAtrbW7VGtXn7ANHKL1dXm//FL++WH1HV+oG1/LB7P7XlWt9IleguyJ4FqPSu32JC1hiopU62O89fAti9VJWgaTD8kmC7zJ8G2K6iQtg8V9ssXwN4Meeqsd0AbLC6rlzCdpGcw9JpsLj+7I3avqJC2DtUOStdVzcWeRkpydpGU651GENog8MLocZisxP5k20+5SzV0N1muepIVOUJ+Vvyw/W/skreqe8/lOgdlBV/fkP/esOupKu/ng/PAt+Y+qXQfVFoNn9Q7Y6qqN89OxlMWdIBDmI7Ko7l/NNlf2iCwqoEABAuAuHZH1mV7iqI6/WuKoTr/P5G9/WX4SeEmSTt8XvjoZy/e196k83umc70mRH9Uj+ePpT9UGlMfqSX1ZPSaP1RFc1c0qD6vjs55HHW9xhlYiw5w6REu7NW2f6svVyRjbIVpUA1dXlxgP0aKaCDz5Y80lI6Jxq7Jo3UO0RKDt/+lR7dvYCVoi2jkQ6uh3IX8ls0NsRGg7PYuMCNQahNOzkjgznZ5FthaoNnCnZ4lwfnqWMN5GcYtsMlBxrDc3nC+fhVs9M8MBmQGYtgkzxPpQG2n40hAYT88iIwgkAvjxkV7dnpt1acJItRaY+sBrkICgU8igUwh1cYCQvyBBZ0DGAyZO5MlZcRqaTs4iWwrMn/CTsxbB5rb5RT0im4vJqKTnZr60aw00BdV+3pOzFkHmtj3IHJPNByZT5NqDfGSO9QFmSLK0kq6neZaI8cgT6WnmxUkcedlJ5ntplp+ejMbBODs7m8EYVyVeH7XbeWE+5VtEOEoonm79wkKFWcPQcexyciDqddDFjfPdZF9d2k2m3UsGWPn45vRutXfpi/L+Tmf6wfReNW3/Wk5BH01/Wi2LPJv+uJqQVmd/1xPWR9XSxp/Ueob2jd3j9KyAexY+rddR7HNSICqbiAk1ZBsaJxVLf4d+GxonhrvmDkYIbIEZMhLGGT0jh7POjiANupm+dZiVD5Eq2piVzuemUd0NEJnnp5zUiAAInlbBR3TAyoZ99SBs1tEcNI9mwUZcCdjTcRKHZ+nEC5PTZHHXZ765a+Vtt3yKGOsKGJ5zAcvIgYhKYAE7q4eootpDKUK/ltqzunmmKqHpyiizL/2ikrQPZ6UQVRtTunP60eXiSfXtSwUWc8GM0XMC7rl1BSojBSI+IwSqqeLDCMKjSbu+luQGJ4k7WcoIgc2NkMEQcW44h7PHieJOmfoi7CZCB3iTFRCRBNqUpnEtZmKzNOWkRoQ+ujQ1D+mAFQ77/kHgGrRp43AWbMQzbTrxT0WutsCJRJ0zm515o2QSeiejSRj6sfxRo8kd99o00rniuhBoV4DwnGtTRg5EWIJqU8LZsap/a3Yq7IPqL89WUN+b3qv06XtqLbW+vEAK3fmlB6YTZDndJeDuWleQMlIgojJCkIJWTBmpeNSpDuMGJ4Y7acoIgU2NkJEwrpgycrjTpTKlafFusuIhwn+bqlTUMsZ8HR4rNSL+0VWpaUAHrGjYFw+C1qBJGwezYCOuNGkWnZ6JWIRelo0SLw5PAi+L47F3mozHJ2fBqR+ntQZ1qkljnSuuiwTrChiec03KyIEISlBN+vH86oFaiVYl++8o7amj2+OkE3C6dSUkIwUihKIk5EMdyaucJCyy0bCiyYjhTjYyQmCzF2AkItMlWJwczmRjbmgLvclKhwjQbarG+uIkYb4Ei5UaEfLIqtE0ngNWMuxrByFrEI2NY1mwES8OUIjv2FVhywcoGBYprVcr5OEqpqsDFGKdtbtUa1efMMcHKHTKL8v70w/KJ9V20/udeq3q+fSeWoWsFhl/OGsG/aWUir/Roe+J9FqPiu/4JIVs5yCJ5a/cECWpFDGeAt7KPjtRIds5lKYfGkw/JJsu8KbD29irkxWynb60vG+wvE+2HP7q0GPzbJdMtlNIgsJAUFAJuE9ayHaOpdnHBrOPyWbD0wFy10N14kK2M5RWDw1WD0lWX8gL6lV1dvJCZNrdYD2rPY+NrofZSkxs5uRGNHc1uK958sKn5RdVd9cPq5au6pzxu1VX1ovZdv/pXfnF2Weel487335j9P2zuoz2uZeESf37B51Qfava/T6vsv3MC9RG+Z95ofZiqz2qA1bzwtU9+4AIKFCAELjLg6xw1IHy5dL17eoU0LvqqAKpZ6qNKB9XhdB70x/I0ZaDvVMfmTH9gXTMM/UNLysp86KSOA+qMuuL2RkKn5WfdALVzRerh+Cz8vPZn4Qv/4WOFEdVY6D0YKIOQ5Di6N905m2GqoRbX6N0f2ZcbdqsXKu+/Pvy1+U/lp9Irp9JE/+gzk4o/6H8uOOpf2T+4z6W3/Az+cU/etXPlc+whJA/8mtl/fTdzjel/Pq8/Mx75dV/G/WOvrXTeecvgnBndliH/Ennz/O/Uf/gk/Lra53yn8tPvFDoRnufOtqrEz2+0xmIBgI3mcKXqyynMxBNBO4uXXMpimgcZi8pwHuJr01/Pap5mzucIZeTBl/+CuSvUP6K6r3SmfWABiomUJIQDmgIQ2E8oIFqLVCUIA9oyBYHNBivvLlFNhkoTNabcs5X57KtnpnhgMwA1BaECed873S2tTQE5gMaqAgCiQB+fKRXt+dmXZpvUq0FZj/wEicg8BQy8BQy8BQy8BQy8BSgwDMgIwLzJ+6QhiCL0q7+YPbbZEuBaRRxSEO2OKTB+LIekc3FJFbSszNfPrYGm4JqP/MhDdnWkuvNhzRQzQcmVORyhXxkjvVBZkiyVJnqR2GcTE4CLzxV1wOHeeCNo8T3RlGSiMQXeTSunyXjAsbro3Z7NiLzIQ05jhKKp1vqsFBhljt0HLucHIiSIHQdBHjl78uVmfSTC8sl1aS1WtKXc8v5kZBVc7HaJSd//6zaG/e0Oo5httYwOzSy/pzpGIeqpCDn3d1v1ZdyXFhqqf+92YrLhbm5+ltyCl4dMagm36ntEErGkRLwkYKvZ+go9jkpEMVYxDwd1MLMSMXSi2JoYWbEcNeLwgixqmUsEGsvFDBiOGtFCYKoq+e7ycqHyDxtTHTn0936gjFhvi6OlRoR/8AzNfiIDljZsG8ehK2hHaVxNAs24lnVbjSKwyg6806SKPDiKDnzRuJs7E2iMEvOojM/GtfPuVM9rF22vp5YrzbRuQKG51oPc3IgohJUD/9WlXW6i7OwVcno91IRv1/VYu6rs9Ir4fukfNrR4e5x4go47pqikpMCEVQRovK5tvHrVU4QFh3pd339WY03OFGcaUlOCGxGA4xGJKOzfjh6nCTO5GTs51E31wLeZAVERO4W9WRS3yiWmK+HY6VGhD6ynrQM6YAVDvv6QeDsgrJ5OAs24tlBDSM/mpyenHnj+DT3Yl9kXp6nkZfJv3Hmj/zUP6294lRQalPh9STAugKG51xQMnIgwhJUUH52cXGy2gyneouqNcv75QO1ulrdp/Ok/Ep9LRVbsb/l78jnVv4pMqxccrpAwF0AF5kX26J0RPucRIioixCc6iy3h3KioB2hVzl5mHRnluhIbnCSuJOdjBDYvAcYDBEkhuHocZI4k51JYtpRx4qHiO5tis6gVimBWXRyUiPCH1l0Ggd0wIqGffUgaA2Ss3EwCzbiSnJORC5G2elEftGX3xuc5N5o4gdePknTUZhO4klwese95Ix1rriehFhXwPCcS05GDkRQoknOWZG8Pov28fRHVaf6V53Zp6XeFJXerCvsseqju+yBPU4PCLgHUIpz0XqvI9rnJEKE3PYUJyMPi+I03CR7gxPEneBkhMBmPcBYBGFiGI4eJ4kzwZkn3USrp2+y4iFie5uCM6w1ivkmP1ZqRPQjC07jgA5Y0bCvHgStQXA2DmbBRlwJThGK8SjOhBfFwakXj5PUG6W+VKix8KOx8JOzyckd94JT6FxxPYmwroDhORecjByIoAQVnL+Z7zM8vyZBnfbwbiU5Z1sjv6p16GLzoerT/E35h/Lj2ecXWxB1/tjj9IeA+wMuP3UU+5wUiKCLkJyGLZWcIExa01BTZwRxpzUZIbAJDzAWQRQahqPHSeJMawZ+2g0Mq5ucfIi43qbYrC9ySszXcrFSI+IeWWyaR3TAyoZ9+SBsDWqzcTQLNmJ1Yth8RB0eqqKNRNeT2EopVimdHaoSaGc9u1R7V4PGFT5VJakOVcl1+HtU/BiGv/kzVaiAAgUIgeMY4tlurvIX1SygOodk5esvZsfJ3a/OZ7kvP/945s7qp3tLh7NUBxCrxV9Rrf1O3498dTbKk9nRLKJqQZh9snt+vsnfl//TC+7ceUPn+32q71dTE9sJJ1QDgTu04TLbfMIJ1UTg1uw1BTTRuNX8vOYJJ2luWoIl2rexI04SsXOQJPJXKn9ls1MGkth2vAkZESgOCMebxL7pnNhvk60FygPc8SZJPD/eJDHeWHWLbDJQIbQxpZAkWz0zwwGZIUYyoE8dkIYvDYHxeBMygkAigB8f6dXtuVkr1vbJ1gJTH3hGBgg6hQw6hQw6hQw6BSjoDMh4wMSJO9okVDsBDUebkC0F5k/40SaLYHPb/KIekc3FZFTSczOf51oDTUG1n/dok0WQuW0PMsdk84HJFHm0iXxkjvUBZkiyVJkK2/apYIzLCJbVFOpSguFok/raTDAlFE+34GChwiw66Dh2OTkQq5fQxYj/hY824RwpAR8p+LKCjmKfkwKxboyYoEOONuGkYimeGdq0GDHclc4YIbCr94CRMK8QMHK4K5yZzzZh5UOknjZmufO5bn2jX2K+npGVGhEAwdM0+IgOWNmwrx6EraFw1jiaBRtxJYhHo9Oz8SQZeaNxoFq6wrE3iseJl8RinIzP8jxI4zvuBbGhupZgXQHDcy6IGTkQUQkniC9uRV3dFaA+J/x6S4B9CyojuoCjr6swGSkQARahMBs2ATDysGhL4yYARhB36pIRApviAGMRJEk3MOhLRhJn+lLiZdorWW6y4iECeZvysr77LzHf48hKjYh+ZHlpHNABKxr21YOgNajLxsEs2IgrdXl2cpKcpeMTL0tPTrw4l5p0HI9OvLNkFIaj8TjL0jqqOlWXkc4V1xP7rV4aV8DwnKtLRg5EUKKrS9tBJ1JiQg46YXSBgLtgXZXJSIGIs+2pTEYeFpXpd7Un69/gBHGnMhkhsKkOMBaJDNza0ehxgjgTmSLqxgaRyYmHiOdtisy01iWpWWRyUiOCH1lkGgd0wIqGffMgaA0is3EwCzbiq7vT1HCN6fUkw7oChudcZDJyIIISVGTy7zRl9IeA+2NdxclIgQi6CMVpam1nBGGRmsadpowg7qQmIwQ24QHGIkjjrq8djh4niTOtadtpysmHiOttis2s1ifm+y9ZqRFxjyw2bTtNOdmwLx+ErUFtNo5mwUas5KZNRba7wdSwSJlb4OIgWoXb+AZTor2rseLPdYMpET+G4V+BDaZEQIEChMBxDHHdU7vJ7aWhcXsp0fOr+YhveynRQOAuGbi2tmwvJZq4qpx5tpcSjVtNymtuL40SY/co0cCN7S9N/Z2DNJC/QvmrvsU6ya37S6mIQG3Q8v5SqrVAdYDcX5ov9pcab267RTYZKBDamEhIkq2emeGAzADM8mvsL823lobAvL+UiiCQCODHR3p1e27WirV9srXA3AeehwGCTiGDTiGDTiGDTgEKOgMyHjBztri/lGopMIEi9pfmi/2lxhf1iGwuJqWSnpv57NYaaAqq/cz7S/OtJdeb95dSzQcmU+z+0nz7WB9ghiRLK2EozpI8ioSXjrPAi0+iU2/si9w7G/vJZJKF8v/ql9S4imBZQ6GuJBj2l6a2S640lFA817UoTg7EmiV0LQJfiyp/hqpFcfpDwP0Bn7vrKPY5KRBrsuvPgzlBnNaiOEGc1aI4IVZlggUCOvvOgtBUi+IkuQq1KFY+RFxvYwpZTyTT+ubJ1HyRKCs1Iu6B50DwER2wsmFfPgibvRbVPJoFG/HV3bxpOho1td1vpXUFDM+52mTkQEQlqNpsc/MmJ7qAo68rLBkpEAEWISztbfWcPEz6Ur95kxPEnb5khMCmOMBYpKkwbd7kJHGmL82bN1nxEIG8TXlZ3zKZmq8MZaVGRD+yvDRv3mRFw756ELQGddk4mAUb8dXdvGnqi0pDrCtgeM7VJSMHIijR1eX6mzc5XSDgLlhXZTJSIOJseyqTkYdFZZo2b3KCuFOZjBDYVAcYizAXpt2bnCTOVKZ59yYrHiKgt6ky66slU/M9oazUiOhHVpnm3ZusaNhXD4LWoDIbB7NgI766JzJHht2baYR1BQzPucpk5EAEJZzK/F/yRGbOkRLwkVpXDDNSINIBQgxDTmTmpGKRxIZlV0YMd4KYEQKblQEjYW6q5wRxpoctRzKz8iFyT5uCuL79MjXfZcpKjYiAZEFsOZKZlQ377kHYGhRx42gWbMTqLtOZLK6fZKPmfXty8s5rb76hcQNB8hqWVGMLZZgnq5SmraZmUzE6dr7bVGvrLtXW1cfL4lagVv2D0pxK65VfVerzgdpS+XWlVx+Xz6cfShkrFYWSjVIM3p++L7/hcbV/UEpNHdpeGl/rUfEuBUQz33rxcLa9SuwcpNnOQRbKX8nOQe7LX5H8JT+fp4bASCWL8WTwznaFcyhxDiXOocQ5lDiHEudQ4hxKnEMDziEZR+Bx4J3ukqYvafqSpi9p+pKmL2n6kqYvafoGmj6ZBv5a0YP2bHON2CkkVSGpCklVSKpCUhWSqjBQFVSqS7soGqhwj9uxRDmWKMcS5ViiHEuUY4lyLFGODSjHZBR4OkFuqpAkQ0kylCRDSTKUJENJMpQkQ0kyNJAMSSTVs3ZnkR8d3f5t3E4hrAiZcTBglpKSpTRXa+wu1djVhLLmuQzgbKmWb9Q++2r1p1qK+bAzvavWfFYXa16qnfZP1Feeqirk9O7sczov7FG9sJp8ruzxDFRAgQKEwKnq4iM5QPfLZ56/44di+t6/6QRe3Jn+pAL5kxwzryO/EgfT97o6mH0qDHDXJ3x1yLQeRLQPuG0Tsc5jPPCAaiJwv+aaazhE41bVxpoHHvhd+XTqDOxRDdzcgQdShafpbM9xKmwHHZDRgHkWf9BBHPqxbzrpgGwuMNniTjpIxfykg9R4j9MtssnAlLveBG6+lCW2emaGAzIDMGESpmr1JmRp+NIQGE86ICMIJAL48ZFe3Z6bdWkGRrUWmPPA64GAaFPIaFOAos2AjAVMlbgTDpLIT0yR5jbZVGDKhB9xsIgyt81v6BHZXEwSJT0w8+VVa4QpqPbzHnGwiC637dHlmGw+MI0iZ+PykTnWR5YhydJKraaRHyf5iTeJg9CL8zz2xifBmXdymo1HWZCeZPnpDMY4F3991GbDhnGSez1NcIxQON2s3cKEmbnrOHY5ORAlM+ik/rxd46tL7RqLZo3Lk/xvyol6dVDexQ6Mb9XtE/XfWlkC0Hlrj9NbAu4t+NxYR7HPSYEoGMInxbCWCUYqly0TjBjuWiYYIbBlW8BIWKbljCDOWiayNAi7WawDvMkKiEgAbUwx5xPN+mq61HzPICs1IgSC50iIIR2wwmHfPgicdTgHzcNZsBHP+iX8k8l4kp14eX428uJgFHh5Ks68JDmNg5PRaRTO32SHqjTUOeJ6mmIdAYNzrkoZORBBCapKf3ZROpb3dUh7nEgCjrSudGSkQMRNuHQ0iUVGDpdikRHDnVhkhMCmK8BIWMQiI4gzsRj7oXHF8iYrISIwt6kW6zvmUvOFgazUiKhHVou2MR2w0mHfPwhdg1xsHM+Cjbjqsd1ZSCWnjUMGQZhZUCPfX0V10jhkOKRnl2ossIoJVXPQxqHnqo9GLTxWO8PkJ6t+oCfT99voHiK6Ioa5Atk99NkSvNr9Nl80fVGdLqu6il7Ir71/YVfcC/kf1U/0ftWc80R66+Vsp5r6rdoj95F08o9nLUjVkQ5fym97LF15vzN7UoRanv1G+cnFf6F8vPgXph+qL9+58wZLbxPR/QLlfpjrF71N3U75x6DjyY+xzuh9qtHAeu76mptoH7Awi9DS5h4moonAguyaOploHKb8CvCe340i7QPYoxq4uR6mfOcg8+WvoO4syKx9TFQ8YNrH9zElvi8yYx8T1Vxg7kf2MWWLPibj9Xq3yCYDFUAb0wZJstUzMxyQGYCpe40+pmxraQjMfUxUBIFEAD8+0qvbc7NWrO2TrQXmPfCsCxBxChlxChlxClDEGZDRgCkT18uU+36WGnuZqKYCUyeilylb9DIZ39IjsrmYZEp6aObTWGuUKaj2M/cyZVtLrjf3MlHNB6ZSbC9Ttn2sjy5DkqWV6gpCfzJJzrxxnI28eBIJL8tOJl4wOclFPD49SeYR37g8YFksoS0RmHqZchwjFE63kGBhwiwm6Dh2OTkQi5PQdQY1tVOnudyd3yeqjpz5cTWl/sjcy6Qj3+MkF3By1Lz2mVoCkdRPqrtOq2tKdWz7nGyIxdf1p7+MHDwlp64f6UhucJK4qzoxQmBXvQGD4Xf9WOhAepwgzqpOuR+r08ITHeFNVkJEYG9j+jifROZ1lcJ89ScrNSLwgec/mDEdsNJh3z8IXUPVqXE8Czbi2Ynavjg5GZ+deafJWebFJ2LsZUkaeOloFGaTeCK/Xksxh3JTX5PKfKwjYHCu5SYnByIqQeXmH8qHM8FZPl2Wm1VdCiU3OckFnBwhNy/CK6kpvCBPd0TUKZ+WD1UR6eI3JNH0/cQLUj8zfUcmf0TqRUHi70Sh9jvy6jtEkOxk2q8HvvyG+h9KRLITJfpvC8X0ffWvSadlOwtjdKOyzzkqiHyxtlDm5HArlDlJnAllTghsogYMht8N81wH0uMEcSaUsziJ/W6ub89iJUSkpBaFclZfhJeZrzVkpUYEPrJQto3pgJUO+/5B6OxCuXk8Czbi2bpsmsufkQUyn6Zn8nulvM6i8Vgm8/gsO4n87OTEvVDWpo/rme0OHv2MAQTnXCgzciCiElQoM+4x/Xq+5KuOFn+i+sY68vtmcu+pYeMAp/cE3Htwsa2j2OekQMRouDgF7TnlpOKRqjqMG5wY7nQqIwQ2TwJGwtxGxQniTKeGeSQTmzav3WQFRCSENmVqfaNeZr4ekZUaEQLJMtUypANWOOzbB4FrUKmNw1mwESuZalOfbW4aMOjO0IIWB/Eq2kY3DVCNXY0T/wI2DVBdEcNc8b83Ddg3DVDdL1Duh7n+4qaBz8rfedW+geo32rdon2o7sIcSLrtNQptoH7AREiGgjXsHqCYCGyDXFMdE4zDtjgDvSdGbCJ2BPaqBG9s7kEU7B1ksf4lZJ28W2vYOkPGA2b/lvQNkc4ESALd3IAvnewcy41WCt8gmA4VAG5MFSbLVMzMckBmAGZy+d0AavjQExr0DZASBRAA/PtKr23OzVqztk60F5j3wXAsQcQoZcQoZcQpQxBmQ0YAps8W9A2RTgakTvndgEWlum9/SI7K5mGRKemjms1drlCmo9vPuHVhEmNv2CHNMNh+YSpF7B+Qjc6yPLkOSpVe0RmW6mSSLcIxQOOc1KkYOxJIkdLnhqtWoGL0n4N6DT5F1FPucFIgFWvhkGVajYqRyWaNixHBXo2KEwK6SA0bCMl1nBLkaNSpOQERCaGPaOZ981rePZua7ZFmpESEQPG9CDOmAFQ779kHgGmpUjcNZsBFf1S0HpmOw6pNyEY6AwTlXqYwciKAEValtbjlgJBdw8nUVJiMFIrzCFaZJUzJy8GhKY4s+I4k7WckIgU1sgMHwu6H2sIUeJ4czVWnv0OckRETwNmVlXOuQ2CwrOakRcY8sK+0d+px02NcPQtegKxvHs2Ajvqonpxg7pQTWETA457qSkQMRlaC6ssWTUzjJBZx8XV3JSIGIr+vrSkYOx7qSkcSdrmSEwCY2wGD4XT/XnjbR4wRxJiytZ6SwEiJCeJvCUtRCxHxpMCs1IvCRhaX1jBRWOuz7B6FrEJaN41mwEbtsqo91aNezxIomVtE221RPNHY1UPxLaKonuiKGueJ/N9U3NNUT3S9Q7ge4PvDizvQnlcl/Kp/obN2n2gpsJlxfXRPtA3YEolSzqYmeaCKwE3BNOUw0DtP3B/BeKL2nnXT0qAZurok+3TnIMvkrr1taE2sTPRUPmO3bbqKnmgtM+cgm+mTRRG+8SPMW2WRg4m9jdiBJtnpmhgMyAzBjr9FEn2wtDYG5iZ6KIJAI4MdHenV7btaKtX2ytcC8B55cASJOISNOISNOAYo4AzIaMGW22URPNRWYOhFN9Mmiid74lh6RzcUkU9JDM5+tWqNMQbWfuYk+2VpyvbmJnmo+MJVim+iT7WN9dBmSLL2iZaTY1ERvu5BQwwiFc15GYuRArEFClxfaLCMxkgs4OXw6q6PY56RYTfYWivUnuowcjstIjCTuykiMENhlbMBg+N3YVEZiBLkiZSROQkQIb2OiOJ8u1hcCZ+YLnlmpEYEPPNPBjOmAlQ77/kHorOM5aB7Pgo34qva9x6a+d9vtVVpHwOCcC0tGDkRUggrLNvveGckFnHxdYclIgYiv6wtLRg7HwpKRxJ2wZITAJjbQYIgk14H0OEGcCUt74zsnISKEtykss1qImC8DZqVGBD6ysLQ3vnPSYd8/CF2DsGwcz4KN+Koe+xGbGt9zrCNgcM6FJSMHIipBheVVO/aD0XsC7r11xSkjBSJGw8Up7NgPRioeqarDuMGJ4U6nMkJg8yRgJCwNRowgznSq9dgPTkBEQmhTptZXU2bmq0ZZqREhkCxTrcd+cMJh3z4IXINKbRzOgo1Y/u+vLygbJT7/yqZG2+yqFzrU67n9rqhwFdVJV73hrLxdqrGrcYOjq/5iC/3LSmC8mH2bFIFPpz+sFOf0B1Jxvi+/X+lL9S0PdmbLmy+VDtmZNY8/lxrzi+oHvVSfkx+lspRfmXWlG35yJTandyvd+bh8MfvX7qrP/aiyS8qdTtWr/7hWPfJbph/t6Hr7nyx19n8gf5Q6B736ft2g7FEHJYYNCrK//49LHr5C3f0a171CdZ1AuQ7kNi/oll97QTb9QMrhO2+oT3hJfOFP3cALLv4xXP5j5IXnfwzVz7rwl0MvvPDNkfqquPBnL8wuflX+wxf/uPQPxZWVF/7sBcnFrwYX/1lx0SYhv3bhj4kXXfiLqZdf/JP81uziH8OLfzPzkvz8T7k0/qKbfC+MLvwxuAgahEv/aBB52cWvLrMEoubUPDj71AcH2DAKn0kZ5k5U+4Bdn4g5kXGjBNVEYLfnevMdqnGY3k6A99Juaji+kGrgxjZK5MHOQR7OWpZz37ZJgowGFG/4TRKBFJZBaNolQbYXKOFwuyRyf75LIjdeUHqLbDJQyLUx+ZMkWz0zwwGZAah76LskpOFLQ2DcJUFGEEgE8OMjvbo9N2vF2j7ZWmDSA8+dAeGmkOGmAIWbARkLmCtxOySCJAwS04as22RbgUkTvkViEWZum1/RI7K5mDRKemLqpQh7iCmo9vNukViEl9v28HJMNh+YSJFbJOQjc6wPLUOSpZVeHfn56SSTKj+bnHhxOo68/PQk804mY5EHIyEyvx4L4xKPZcGLtsxj2CKR269bvMQIhdMtBlmYMAtCOo5dTg7E+jJ0rei3jctCTzrfrP/8RXl/Z7b08HL6A7WUM/3xpe63+TeokuL0PbUcpFZnHlVrNe9VKw+XvkUd6XC3Xt6pfsKiLDlbYLovv7kqhU7vqR9TLf/IH9jVvtV7nP4XcP/D1zZ0FPucFIj1+vUn2owcDouUnBjOipScENgyCWAkLJN7RhBnRco0FLlvELI3WQkRWaSNiep8ulrfuJybL9BmpUZEPfBMCzOmA1Y67PsHobOXKZvHs2AjrrRtdpb74fgs9qI0GHvxRH7vOI1PvWAUJqdBHMb53CsOtW2oc8T1PMQ6AgbnXNsyciCiElTb/kxK0qeq0vadWSdcXR1TldB3lch8Wv3x/qx89uBCUW36o1lFUX8M1B6nGwTcDXCJWX6sRHYl0B/Mtqjcn7umc/Dt485uJ1OVIWmDdFMqvKgq+3RVoafpb/5l53vf/f7bHfW3fS/y1Q/I5e+T1Ef/iPD8RwS+8FKRJLOfoRmDfc4xQKQKhEA21Mpe5SRxKZEZMdxJZEYIbIoGjEQYJvp9zJwczhSyWR1z0iHyUJvqOKzVlPnuaFZqRMgjq+NQREZtzMmGffEgbA3auHE0CzbieQtffGcheZ218GmD0fU8sqJeOvPXSQuf4aSeXaqxwMovVLr+YalX7vF81bVu2Zr15lULobOV1MeqK0x9ZrnL78Iyq+qw0wHvUYFjGDCuPU5n4StUCwXKQoB15cfLDYpqXNQpxO/KT6lTiesOyPn2nIdVW6Rq2pNjYFCxRDRgyRihTg3alGgfsPaL0JzmPimiicCS75p6kmgcpsAL8p7Idfb1qPZtrk0qrnsWImuLFBULmBzxLVJ5kofmDimqucAMieyQihYdUsaLR2+RTQbmyTaktSTZ6pkZDsgMwNS3RodUtLU0BOYOKSqCQCKAHx/p1e25WSvW9snWAtMdeGYCiDQFKNIMyEjADInsjopFlJkmWbfJtgJTJaI7Klp0RxlfzyOyuZjkSXpa5rM8a3gpqPYzd0dFW0uuN3dHUc0H5lBsd1S0fawPK0OSpcrU0/g0jUfBiRcm45EXj5OJl4/SxAvPktP0NArPYuG6OyoxdUfFOEYonG6ebWHCzLV1HLucHKvSwjY2wGk4rDtquV1pcc5C1S21qHVMP9zpTD9QO7+qn6aqH/X8vYu7xEb7uu5xOlbAHQufTOso9jkpEEuc68+bGTlc1nQYMdzVdBghsEvLkJEwztUZOa5ATYeTDpEZ2ph4zqef9T3LufnebFZqRMADz5wuPa2hnHKYW5448bDvHgSvoazTOKAFG7HL+w1THdr1XFjQ4iBZRdtsGYdoLHB5CqofHZZxiMAxDLiNMg7RQoGyEGCdroyjrdnUFxs+rNrEXpZf1CdVvCjvG6o5RELg8tb6qpRoH3CtCqE2zdUcoonAJao1lSTROMyCFMh7QaBdCelRDdxcOSepF1mFtZxDxQImybbLOVRzgZkSWc4Ri3KO8VrmW2STgfmyDVUtSbZ6ZoYDMgMwBa5RzhFbS0NgLudQEQQSAfz4SK9uz81asbZPthaY78CTEkCkKUCRZkBGAqbIVss5VFuBuRJRzhGLco7x9Twim4vJnqSnZT67s4aXgmo/czlHbC253lzOoZoPzKHYco7YPtaHlSHJ0itazklN5ZwExwiFc17OYeRALNpBp+N/RuUcRscKuGPhk2odxT4nBWJ1c/2JMyOHy3IOI4a7cg4jBHZJGTIS5sk6I8gVqOdw0iFSQxszz/n8M6mX/81X07NSIyIeeOqErOdw4mFfPgheQz2ncUALNmKX9ZxMh3Y9t9+hmK6ibbaeQzQWuD4FFZAO6zlE4BgG3EY9h2ihQFkIsK78tPyi2tr/fHljjuYcch3IPhUEuIy1vvok2gdck0KoSnPZhmgicClqTcVINA6z8ATwnt+NEm1lvUc1cHNlm6xeTE2tZRsqFjAXtl22oZoLTIjIsk26KNsYr0G+RTYZmBbbEM+SZKtnZjggMwAz3Rplm3RraQjMZRsqgkAigB8f6dXtuVkr1vbJ1gLzHXjuAYg0BSjSDMhIwBTZatmGaiswVyLKNumibGN8PY/I5mKyJ+lpmU/irOGloNrPXLZJt5Zcby7bUM0H5lBs2SbdPtaHlSHJ0itatslMZRv77bCXGKFwzss2jByItTnorPvPqGzD6FgBdyx87qyj2OekQCxirj9xZuRwWbZhxHBXtmGEwK4cA0bCMllnBLkCZRtOOkRqaGPmOZ9/1re+58Zb3w9YqRERDzx1QpZtOPGwLx8Er6Fs0zigBRtxdbpaFXNqbqMmfXty8s5rb76hcQNBksY6yuvKBiNl5F+6BtZUwTGbilGa8yJObdUlzUk0dvX5svgVKCc/q2o2P6rKBFXd4Av5x/emH+rM3svzaz2q6ZcCntn29eJdtSgb+PrVkQOy+THefPhMWNl8aLL5kGyzwNsMn/5Kk/smk/tkk+FPOD2AVotpJtMLqumXFkkaTMc9Hccme4/J9sKDNHJhRJo7NJk7JJl7YS7t8AxPQ/39elBLCxODeSEKZiot0Rgv4iabCyyMQFON7ibu6b3yy2qZ4vzE+emH1Vn01R3W9RqE/OOfykfl/elPp38rP227WHu52UDnjz2yP1ZTAF87AdlEgTIRYF4lEOrLtaXrVWtHfb3VtU61SfRLNVqd+uby6irv6pu+qi4RON8tOluserwzv+N7erdaUlK9IH87v+G8ugR9+dZ19S8/WWw9fTG9Vy1FPVRPztLClTQhDP3p+0L+imfPgfzC/eo5e1K+6EiHTt8PhF/9Ex9Iq9Ty2POO8H3Vj/JcfTqcXzQ+2/T6Qr+tlTwywIIRfJ2nWtV72O3oe2ZeJRsKLAMhFnKMnRJkG4Hln/VWacjWYao9AP+JrCtEqDOxRzaRpVsCvLBCNxuY7PHdECZbv023FZjtca0Q0px5L4T8rbEZgm41MOmj5mhQZx/QzQbmZsLcrK5SStO2lh1vbIGgUwgkBfi5UZ7dXhi2OlujGwzMauS1POMyHt1kYH7DtTnEwmTpbbqlwCwHb3I4Dx63LcHjiG4xJvO1+TgUZJN5WxvOg8bc4cbmBjoBMCciJ/HqWVkYtTqJpxlbLRdfkG8ulou1uknO4AOr/ZnR2WBL8ZN47c6EXbKp8JU06AT+42pi9EDN33Smyol1cK1Httf1ArGh/EW3f1WCAOyHB5R6hdioOKhGC7zR8BgyWyLW29yn2wx/ssGJxrRGbCipkW1nXyQ2ZheqwfDYjEwws1Vivb1Dmr1V2KufDifJxbhAHFqtz43eBttKSC+mYiTZWvh7CM0wqGqktFulG6LxrtNNZEo3VPtdpBu90Yd0owXeaFRE6Zts7tNthj/ma6cbve0F2Xb2dKM3+JhuMDxak9KN3t4hzV5lcL0A4qwqqeqSpqQT2RiCwOhzmKm0jGO6xGGXbC5wgRKacnRVyeWL7GZdz09VPal8pL7UUaeedqoW6Go6VD7WEe6RCVcjeyt1xvIX0w/rfu4/SZDHEvquKrBWpbWfl59WXeKq3vrF9H+UjyWcajJ/3tntHXjlx+U/6QhfIRMKFCGE7uPF8MiRUYXBFxLwA1VLnL53eby6nfL3qidelZOrL3qdIJyVAnc68mctRl/94Xfe9F2v8k6oyouBqjMmorqZu/yk/GP1m7D6c7hTXdgtqo/lL8tPy8/L33dE5HuhH2hXIvbJLgSuvCLqic8jnYWvki0ELrS2U0gk2ghcYl23kEi0DrOcCvBfLkNyorOwR7aQpY54KXlrdl1Lu3bkB6E+1KdZSgjbDmw6IzCX44uOSWDsU/423VxgPsfWHaPzuqP5KkS61cC0vt5crO6Cl1Zu9SwYB3QMYO4mTMkWJYVoa3kgLHVIKoVAUoCfI+XZ7YVhl+doVIOB2RBchwSEoEKFoEKFoAIYggZ0PmAuxRUt8yAX5qol1VRgSsVULaPzqqX5ikS6xZg0S3p46r0aTWGnICNwVzGjreUBsFQxqQTAJIuc9atnZ2HU5Vk/xdjqkZnkiTjJIm+cBrEX+6djLx/5uSfOJsFpcHKWB6M6IhkXBF4ftbdNu1oUMC4LxDhIKJ1u6cAChVk+0IHssoKsqg/b6AAXFj6vOmKr5tiflM9UepjeLR98p6N+1xH+lvz/WAe6xwoq4KDw2bcOY58VYzXfWzAwM2DtHP1VVhKWvdOxvu/hBiuJs+3TrBSrYsBCAZ13R7mc5enXf3qsLM62UIdJ3o21+ecmLyAibrcxc1zMH+vL7+rf6MAPeMERARA86YGP6oAXDvsOQuCsIzqAjGjBB12JyjDLJn5yEnt5niVeEExSL/NPM8/3hS+SLJOztVpvORSV2qglRaXAegJG515UMoIgghNcVKodU3enP+5Mf1htcqsKHapG5VXX9t2d/qjaO3dflXZ+Gwjt5H6PlVrAqddWmIwYiACLUJhPy4c6lFdZUXgkZix0JDdYSRxKTEYKbHqDjEYQhaH+rtoeK4sziZl0Qy3eTV48RAxvVWCKuRwx3/HHC46If2SBaRrTAS8a9v2DoDXJy+bxLPigK3mZijQLzvzEOxH+2IvDIPSy+PTUOxmdngbJ6YkQ4fiOa3mpXZiV8jLBegJG515eMoIgQhNUXi51vsxOjXyhOnCrXf8fll91pu9OP6rug36guqLqxczyuWdWmowOEHAHrK00GTEQkRauNKcfGM6BZEVhUZqR/m7EG6wkDpUmIwU200FGI0nS3Kg0GVmcKc0w7sbaaHaTlw8Rz1uVmslcmpiv8uIFRwRAstQ0DuqAlw37BkLYmrRm84AWfND1Lt+LR3YZ9WRLW7FMItJ2CHsUhKuI3JuwtGbuks2Eb0uBqr9PpdB7VJ2p9FQdFD47DEnt9pWa8IWUf8t7snaqm7zkn6oToepjwdXXVIv5TCLen90/peOWyjBVu7eI8K53b2WmuEi1P8bbD+/bqXdv6Y0+pBst8EbDW3Vmu7f0NvfpNsNfE3r8rdsB9bYXZNvZd2/pDT6mGwwP8Mg+rtnuLb29Q5q91dNxx02CMvZm2Y5mjoLI6GiwncgUZdysRTQU/vaRkpTa2fO4/JO6hnL6oToXUq1ZXDhTUH/Jocw9mco9RCbXuSc35R6q/S5yj97oQ7rRAm80Krz0TTb36TbDn/61c4/e9oJsO3vu0Rt8TDcYHrtJuUdv75Bm74XVSwe5x5h9cqvpsdHVYEvR2acrdKbukk2Fv4HE/PN5+XH5c53NMsnkKskQDXecZAJ/5yDMsp2DOI13DkSkPmSxKfFQmRwkHglyqEAOFcihAjk0gRzSQQQeBBVv+oqjrzj6iqOvOPomjj6dA/56rJugJE+heArFUyiewsRTkHm4k5aEOFYQxwriWEEcmyCO6RDwREBJZJJhqBiGimGoGIYmhiGNwe3EypzeAusZhYHzG2Gq9GaaYFGNhb/B0AT3WbXm96HOzD1pjcxpVFtd57Rg5yDII5nYgkRlN2FIZ2QcF+ks2DlUDIeK4dDEcEhnEHgGVMDpK4S+QugrhL4JoU9HgL8CayexYKdQKIVC | H1: AQxDAzokMKu2t3eVbCkwtyL2robnV8Ka39sjusWYfEt6gBYzP3voKcgIzHtXw/MrYe1h55hOAMyz2L2roboSVh9yhjRjlbWn8Sgd5enEC4IkkHPt8NQbhaMTL5qcZaNsNMlOJiczHuM827LQQJ1rm/auhhEOE8rnvmbECIJY34NO19uoGZV/J7/vmZz5NlSN/v3+rVv9/6OlupH8z2P5T96tqkeqBavai/DIuHbAOCwCPizw6fncQeWnF3x5og6wq3x58uZb9T9wedrOiIpYaG1jes9I4rjUxEjisNTESIFd5IaMRhZ00yTWsfRYWa5IqYmTEJGK2pgSLybG81tRQ8tFt6zgiAgIns0hhnXAS4d9CyF0TaWm5iEt+KArqXw2ivLwLBVeME5CLxYikN+bn3onQog0i0+zbFynC6dSWZsVpVSOsb6A8bmXyowgiPgElcrNmwPcbUPQ/EvlZ+Uvyn9UMni25eCZ1MRe3c8136Vg2HsgE6U22OyxDpGADxFcNusw9lkxEAkBIYmbthswAvEoYx3HDVYOh7qYkQKbkQFjkUU6jB4rhjNJbNttwMmHSDitCuJ4rp4sl9WygiPiH1kQ23YbcLJhXz4IW5Mcbh7Qgg/66h4QExp35QqsL2B87uUwIwgiOkHlsOMDYji9I+DeWVuJMmIgIjFCiRoPiOFEYdGg5gNiOFEcylBGCmwmBAxHGHfTLNGh9FhRnElRywExrHyIYN+qFJ1flhhaLr9kBUcEQLIUtRwQw8qGfQEhbE1StHlACz7oq3sAd2jc+JpgfQHjcy9FGUEQ0QkqRYkHcHNSCjglXFIyHcCt884+q3cQgboVpcqIwqRUtZPdG6wkDoUqIwU2TwJGI5YpP9UW43qsKM6Equ1YbVZARC5oVakmc2GTWJQqJzgiANKVquVYbVY47CsIgWuSqs0jWvBBVxe1K/L4zkKCOrx8VZsrpBpNLbhRnK/iOtrAGsTGHaxEg1ejyAZ2sD6dVeyr8/6eVMufz2ZHAP7rjlrUVN+gxOhPdeB7ZPAYBo7b2Koz8RWyiQJlIsC8C9tWg67O1n2yratBmXHfKtFC4A4buNC07Vsl2gjcW7OuhCRah9lHA/Bf5ofCIJ16ZBs3uHFVXboaqktXI3++Wcx+3yqZEZgS8XtWkyQw71mlWgvMidg9q+f3rYaW+1bJVgMTYxvSWsFs9SwYB3QMYJpbZ8/q+X2rYcN9q2QKgaQAP0fKs9sLw1YM7tMNBqZD8PwEEIEKFYEKFYEKYAQa0PmAyRS3XTWPLdtVqZYCUypmu+r5VavmV/aIbjEmzZKencXEzx51CjIC93bV86tW7RHnmE4ATLHo7arqqlV9tBnSjFXWnsWTcZ4kI28s/+sFwWTsZf7Z2PN94Ysky4Jc1EnYOKu2rDNQZ9bG7ar2G7ouYUL5dPNvCxZmDq4D2WUFQazuQefmi0rPbPr9RPXEV93u96uCz4PZltFH8jf3pu9XXe7Pq299If+WalWq95T+alYnkjPz2Q9SDUpyav++qpm8LB9N7138VNVX7y2vAJRfffPWvzveOZ/3e+cTf/kql39SywLqX63vC7ir+v+VidXawo87gRfsiOmPdma9/nW7vie/5bH8q49nHDudeCcKTFWNPdahE/ChQ0zdl8pX3v5bZ99/652OCLPO/vCoXxxfP+ocXR/0XllUr7qQ6lVHzcF2kuTi9bF/0YmSQHpYWMpbjN5DrO7CFxOmH0zf06G8yorCUt4ybQZg5HBY3GKkwK6sA8Yii9JuHgsdS4+VxVl1yzcsB9zkxUNkvzYm4Itp+PyC0dByZSwrOCL6geeOlyqWaWwa1gEvHfYVhNA1Fbeah7Tgg67UuZjk6STOhHcyOQu8eDxOvHwUTzzhT05FGCZn49N62J2qc+3yulTnOdYXMD736pwRBBGf4Or8shqudgfcn1XMlGB/r9oqUFXGisFe59/1/t31TiH/4cnbnendC8eoVlL9udq/qn7EY/lbfydSolDnqT1WTwm4pxBieLZdV22DUNDlV+WLJRdJ7ftZVYRUX55tm1BfUQft/Pha3QBW/qw+LOepmrFc6+yfnU3+0zujzuCtN88mb7/92ptvjL4r5XHid447t177D//xnTt33th7842TtybvTDqDo35H+P70fflB/mN/v+T4r+aO/6rjdzOdy/dZXY7IIXAFbS7HMZLwCOiub2oQY0RxqKEZKbAJHDAcWZgk3Vg7Ij1WlqugoTnxEDmqVQ09vxk1tFx1ywqOiH9kDR0kvkVDc9JhX0EIXZOGbh7Sgg/66m6rNXaPRT7WFzA+5xqaEwQRn6Aa2vG2Wk7vCLh34LpZh7HPioGIxQgtatyswInCIkbN22o5UdyJUU4KbCYEDEcQ+lE3i7U9CD1WGGdq1LKxlpUPEe7blKPR/ALSyHKjLCs4IgSS5ahlYy0rG/YVhLA1iFHAgBZ80G5v19IOqZSXtrvD4ihbpdv45gSqwasx489ucwIVPIaBt7E5gWqiQJkIMO/C5gTtUuM+2VRgMyZCgJoWQ6kWAtsp4brSsjeBaiOwkXJdwUi0DtM0CfCfKuwnOgt7ZAs3tzMhCtWmBHWvVhTXfcFRYN2ZQGYE5sN2dyaQrQUmROTOhChY7EyIjDeA3qJbDcyKbahoBbPVs2Ac0DGAOW6NnQnS9uWBMO9MIFMIJAX4OVKe3V4YtmJwn24wMBmCpyKACFSoCFSoCFQAI9CAzgdMpe3tTCBbCkyoiJ0Ji8hz2/LKHtEtxiRZ0rOzmOTZo05BRmDembCIOPMBMO9MIBMAUyx2Z4J8dhZGrRg7pBl7Zes2hnmqnFiHOEwon/u6DSMIYiEPOjF3Xbdh9I6Aewc+NdZh7LNiIBYtEdNmc92GEcV13YYRxWHdhpECu2gMGA7RTfJYR9JjJbkSRRtOPkSsb2O6uZh0hvM1fss1zqzgiPgHnimBB3XAy4Z9/yBsTUWb5gEt+KCvbhd+bOrCjyKsL2B87pUoIwgiOkGV6Aa78Dk9JeCegqvSP/8ufE6XIzIIQkEbC0+MJCwC2tyFz4niUEAzUmATOGA4orzr56a2J0YUZwra3ITPiodIUa0K6Pm9oJHlqldWcET4IwtoaxM+Kx32DYTQNUno5iEt+KCv7jEzsbEJP8b6AsbnXkIzgiDiE1xC/+9jZmau2GMdOgEfOoSm5zlmJkp38uVDZoJ0x8/MJ8xwOg6RmuDK3HzCDCcKjzTXcdxg5XCoyxkpsKoAMBZRN0+0+a3HSnIVZDknHiLttSrL5/eTRpYLZ1nBEbGPLMut58uw0mFfQAhdkyxvHtKCD3pxeUI9rkpuO7w8QehwpfIWFtxIBKu4rvYnJMb9CUSDV8NIG/sT5jK5WmRelr/yvw9nWxaqS7qkSr2nmiLq3QgP5ee+qPR09U3nwvrL2Zqo4W/rPLJH9kgM80grGxeIJgqUiQDzFhsXPit/48U6Y/fJxgK7NeE6tXoiHkrV/lxn6KtkQ4FtlwgVatnBQLQR2HC5rsIkWodprgT4Lwu6iTbc9cgWbnAHQ6I2L6Tz1mFh37xAxQMmS/zmhSBJu/rV9W/TrQVmS+zmBXG+ecF4c+ktutXAlNmG6lYwWz0LxgEdA5jn1tm8ILaWB8KyeYFKIZAU4OdIeXZ7YdiKwX26wcB0CJ66AIJPoYJPAQw+AzoaMIHi9i2EUW4IPLfplgLTKGbfgjjft2B8W4/oFmNSK+mxWcwG7QGnICNw71sQW8sDYNm3QCUAZlf0vgWxvTBqxdghzdhKKp6cjqJExF6YjBMvTs5Gcv6dTLzsxB/5WRb6p+nZjMc41bYsPlCn28Z9CwkOE8qnm5RbsDATcx3ILisIYs0POmH/7OJU+lKtSlWxfl0+qFqg1KRbFUfe+47KIklXyFH1E50T9lidIOBOQEyAV/zwtFrDUH1eP5XwlSdUL5janjEv/32tvDL9garFnTtLNZFVfWLyuz+uli++mBXsKhc+qH5q/a2zf2LlH1n5sarE97haUnmqqoGdQLoi6naOrt/qpH6snVvuszofsfja4oSeEYin/KSPcjdYSRwWoBgpsOvfgNHI8m6amtYRGFGcVaCCJOom2v7Qm7yAiHzUxmx4MSee3/YcWe7vZgVHhEHwRA4+qgNeOOwrCIGzjugAMqIFH3Qll6MozU7SQHjB+CTwYv9MeNmpn3uBGOVBOPHjk/z0jnu5HOp8IeWy9Z41nS9gfO7lMiMIIjxB5fLfSRn2qBJjj1W56kFVm3pUPjFs85WS7nEll3Xwe6zwAg4Pl8k6jH1WDESkhQtOS6cTIwqL1PS7vnZx7AYrikOtyUiBTXSA4Ui7kekyLU4Sd1LTDwz3nd/kBUTE8lalZjoXJpabrVnBEQGQLjWNozrghcO+gRC4JqnZPKIFH7TqdtqZ9Zg4bHLSDq0UkdY7w0S4SumuySnWGbxLNhhYsYWKwPWanOo9BeXzajFx8c2Ak1iJ9DGMvpWGJqKJAmUiwLylhqawq7N2n2ztakjm72giGgosyMLVpq2jiWgjsBS7rowkWocpuwL8Fwdh0g21izo9so0b7GnK5x0Fmb2diUoGTIv4dqYwMPV3f5tuLTAvYtuZsvN2JuMFoLfoVgOTYxuqWsFs9SwYB3QMYJZbp50p21oeCEs7E5VCICnAz5Hy7PbCsBWD+3SDgbkQPDUBxJ0CGHcGdCpg4sR1MkXGrd636ZYC0yemkyk772QyvqhHdIsxKZX0xCxmevZYU5ARuDuZsq3lAbB0MlEJgIkV3cmUbS+MWjF2SDNWWXs6kbLp9OzMi8JTX+0kmnijwA+90yBJgtGJPx7ndRIzzqctCwvUObWxkynHYUL5dDNvCxZm9q0D2WUFQSznQWflKx08j2ab76vPVTPux9N7cs59v/PN+Zdell9M/0f5uHw6O7RVbZL/uPz5tzqB71f7wjv/x63q96+M3vpPnRtvjf5rxw/ipPPKm9/97n+avNEB/4PzrzxSO/Cndxf7m6oy0aPqmpbO9IPq0890I7HHOhICPhKI6feKb+Ybu55g26h2Vtw8Pzn3WX3Swv1rnZu31CDJL52fcCD/8Ljayv+RapPSrn7tszoVsWjb4ioBIxBL7crcJsVI4rB0xUiBXTgHjEYsoqyb+6bFCUYYZ9WrSPhd/c2IN3kBEemujXn2YrY9v/U4slxkzQqOCITgKSJ8VAe8cNiXEALXVL1qHtGCD3qxV78Ooo736qc63OthbL0pUcSruK7KWJlprz7VYOBKHVQwfyolmTrc6oeLMlZ1bNQ9dQtB1Zf+VS2JVV2q0lPVuVUPq9+9WOzI/+riiakvq0NLZyfIvld1vdef+6DScw90DtkjOySGOaSNyhbVRIEyEWDeorL1cfk7L5Rq8PMLY/akU2/iqBTwj6o9Bs/lZ8v6Ikj9KN7vfHv/6PrB9c7B9aPrf/mXvZ3Z3oVnlcp+Kp+PJ9OPrtUn4XbK36qhlb9VB97evXPnjdXzb195JfSDLPSP1BLdjSP5w/4oBf67aio0fe9aJ1Kn3SbqQz4/feufZtL9Wmem2+cn39Z6vt578fcXnqj7nb3JW5O3X3uns7cfRR0/Vg+qYnssp3Tvqps01JTOO/9xujHdJ48pcM0ToexNZ+JSLQSuX2KkurHwR7URuHK5pginWodZpQT4LwxFV79Zqkc2cXN1vzjYkR/UlYyxupIxnl+IFvvWMiAZFCgrCGXAyFIHJJsLFBbIOmDsL+qAsfHe6Ft0q4Hqoo35iYLZ6lkwDugYQE2wRh1Q2r48EOY6IJlCICnAz5Hy7PbCsBWD+3SDgTkRPMkDxKFCxaFCxaFCxaECGIcGdEhgWkWWBW11QbKpwOyKqAsu4s9ty4t7RLcYk3FJT9B8Dt0QewoyAnNdcBF35gNgrguSCYCZFlsXlM/OwqgVY4c0YysF6YssGI98b3QWhV4cxL6X+3nmnY1ORXYS5GLsj2Y8xgUKy5INdZHCVBeMbRdQajChfLqlDAsWZjlDB7LLCoJYKIUuc1Dmx0/k1x5fKNWtTJdllvlG+Qs15a2KfQ/Vn6ttXsWNxBdycns0u/rxfP4p/3g+8Q0C8xU6nM4VcOfC1yOWlw70qwSrawKXFgF0vthn9QViYRo+jzfvK+NEYanNxTqOG6wc7ipznBTYogBgLHIpEEPtgPRYUZzV5YIgyLqplvAmLyEi37Qx8V1Mf4O6jBMbLwg/4AVHxD/wnA0xrANeOuxLCKFrqMwBhrTgg6708Dg/jSbBSeAlfhx4cZxNvDzKci8/EVE6SUU8jus32qke1q5tSz0cYn0B43OvhxlBEPEJqocvXG4zq9q9lGL3xVylln+oVO4Pqrqg5tSqr5W4+6z8h/Jjr/y8/H35s/KT8lfy4+/K3+u8s8fqHQH3DlzQ6jD2WTEQsRiuRU0X07zKisKiRQN9CLnBSuJQjTJSYBMhZDRUv01kqmUxsriTo0lX38N+k5cPEexbFaPzm61jy1XlrOCIAEgXo6ZBHfCyYd9ACFuTFG0e0IIPupKi4WkY+WIUen4enM2+d3R2knpBNh5FQZLE47M6wDqVopHOF1KKRlhfwPjcS1FGEER0gkrR5Z6e8p+kLv2yWoOVsrRTfr4fRd+ZHZrQCaotGVKHTt+vuoIely+0m/r3WF0g4C5YW28yYiDCbSt6kxGFRW/63VDoUG6wojgUnIwU2HQHGA6RdMNEOyA9VhRnejP2u3ms47vJy4eI6K3qzfk10LHlZm9WcEQAJOtN46AOeNmwLyCErUlvNg9owQc9W/ocn0xGZ1HuiTg+8eI0O/NGiS+8OBhnp8F4dConrXfc603tAyD1Zoz1BYzPvd5kBEFEJ6je/OX0XXVO62y/72zHg+nY1q865W/Kn1VLnP9Q/lb++qSWouUfyk/Kj8tP5cffq+/5v+UfPu/cGoigU/5M56U9Vi8JuJfWlqSMGIiI3IokZURhkqSqJfQyyg1WFIeSlJECmxEBwxHJ4C60Ww57rCjOJGnuG44pu8nLhwj6rUrS+RXIseVWa1ZwRAAkS1LjoA542bAvIIStSZI2D2jBB600qU1qtrstVjukUmQKC10c5at0m98WSzR4NWb8y9kWS3RIDHNIK9tiiSYKlIkA85a2xUbVITMvy0dLI/cUvRH2wj5Y/C7YxA/9Wcfrndi8s3V2DNG71cr34rFZtfxl+bQz6xyOxX/J612za22INZyISx1O4O4fhHQ37oglWgjcugNX5LYdsUQbgXt21pXaROsw+3Mg/vPTbhbrTOyRTdzgjlh1u3ecqg+Z+jA/oDK23/NNBgUqirZ3xFLNBWoK7I7Y84u+Y8tF32SrgcKijYmIgtnqWTAO6BhAObDOjtjzi77jhou+yRQCSQF+jpRntxeGrRjcpxsMzIng2RwgDhUqDhUqDhUqDhXAODSgQwLTaps7YqmmArMrZkfs+Z3f5hf3iG4xJuOSnqDFbNkeewoyAveO2PM7v+1x55hOAMy06B2x6s5vfcwZ0oy9smUww4T/elifzAnGhPK5L4MxgiBWRKErHJsqgzF6ScC9BF9T0GHss2IgVoERc2lzGYwRxXUZjBHFYRmMkQK7Cg8YjiDpBqlpJwAjypUog3HyIYJ+G7PPxRx0fg1zbLlYmxUcEQDBEyfwoA542bAvIIStqQzWPKAFH/TV3QmQGTel2i5+1PoCxudekjKCIKITVJKy7ARgdIGAu2BtvcmIgQi3rehNRhQmvWncCcCI4lBvMlJg0x1gOMKkm5vkJiOJM7lp2wjAyYcI6K3KzflVzLHlcm1WcET8I8tN20YATjbs+wdha5KbzQNa8EFf3TNQMuPG0wzrCxife7nJCIKITlC56foMFEbvCLh31laijBiISNyKEmVEYVGi5jNQGEkcClFGCmwiBIxGEqddX5vUe6wozpSo7QgUTj5ErG9ViWZz4WK5mpoVHBH/yErUdgQKJxv2BYSwNSnR5gEt+KBnC5/j0yhK5LeNT86EF4/ikTcahb534ifhWRpl/uRkdMe9EtVGLalEc6wvYHzulSgjCCI6QZUorE2deh51Z+lA6uXzqAMBOo+a0Z0C7k64dAWeR73UnX/eW287jZrRE4joD1e/ltOoGVFY1K82aN1g5XCofRkpsKkXMhZRYD7+jxHFmfaNkrDrCx3gTV5ARHppVfzO7xSNLbfEsoIjwh9Z/JpHdcALh30FIXBN6rd5RAs+aLe7X3Md3fVQNSCY6WJ/lW7ju1+pBq8GjX8xu1+pDolhDmlj9yvVRIEyEWDe0u5X0VX/1Y5N59uTt0avjzoHo7dG/+2/vbbTWd22Wv6x2jT6UI2U0sKPy0dqhKp17+JG6gepnEusXumaKfkczmYSlYDufHO5oePaYnuqfHZ+3YmiHbVFdTYdMW5RVbfQqi9XX5AGXuuE1Q/XhrN98lis5h6+ratUC4F7bOBq2rJ1lWrjqlrm2bpKtW41Ba+7dTVNjQqYauLmtq4KdZmrUJe5CnWZq5hfoijsl7mSQYFyoOWtq2RzgYIAuXVVnF/mKiyXuZKtBqqCNqYRCmarZ8E4oGMAc/kaW1fF+WWuouEyVzKFQFKAnyPl2e2FYSsG9+kGA3MieC4GiEOFikOFikOFikMFMA4N6JDAtNri1lWyqcDsiti6Ks4vczW/uEd0izEZl/QEzae6DbGnICMwb10V55e52uPOMZ0AmGmxW1eFusxVH3OGNGMrBQm66ErxGBcWLCsr1MUF09ZVEeAwoXzOy2WcIIj1TOjyxJ/XZa6czhVw58LXEZaXB2CrAUvTf50f9ln9gFg7hs/hzaUzThSXpTNODnelM04K7Lo9YCxSP+/G2gHpsaI4K51ZL3JlJUTkmjYmvYup7/zWT2G5yJUVHBH/wPM1xLAOeOmwLyGErqF4BhjSgg/66m5iyE17ZkWI9QWMz70WZgRBxCeoFna8iYHTOwLuHbiY1WHss2IgYjFci5o3MXCisGhR4yYGThKHapSRApsIIaPhJ3E3MNWxGFncyVHzLgZWPkSwb1WMzu/9FJaLXFnBEQGQLkbNuxhY2bBvIIStSYo2D2jBB311j2/JTftpRYT1BYzPvRRlBEFEJ6gU5Ti+hdMFAu6CtfUmIwYi3LaiNxlRWPSm+fgWThSHgpORApvuAMMRx90o1pH0WEmcyU3L8S2sfIiA3qrcnF/7KSz3uLKCI+IfWW5ajm9hZcO+fxC2JrnZPKAFH/TVPcA6N22aFTHWFzA+93KTEQQRnaByc0MHWHN6ScC9tLYiZcRARORWFCkjCpMiNR1gzYniUJEyUmAzImA4wqSbmM5x4URxJkktB1iz8iGCfquSdH7tp7Dc48oKjgiAZElqOcCalQ37AkLYmiRp84AWfNBud7IGvg5PqkxhxQtW8Ta/lZVo8GrQ+JezlZXokBjmkFa2shJNFCgTAeYttrL+xgv+19zIShwJ4KYdhOw2bmQlWgjccQNX07aNrEQbgVtt1pXJROsw22oA/guzbqw9P6FHtnCD+1jVFaxCXcEq1BWsYn71obBfwUoGBYqBtvexUs0FqgHsPtbzK1iF5QpWstVASdDGHELBbPUsGAd0DGAiX2cf6/kVrKLhClYyhUBSgJ8j5dnthWErBvfpBgNTIngiBohDhYpDhYpDhYpDBTAODeiQwKza5j5WqqnA5IrZx3p+Bav5xT2iW4xJuKQnaDHRtceegozAvY/1/ApWe9w5phMAMy16H6u6glUfc4Y0Y69sBUsKCu1c/bqMVjhOKKD7EhYjCGI1E7o4sakSFqOXBNxL8OUAHcY+KwZiBRcxlzaXsBhRXJewGFEclrAYKbAr6IDhiLuhfmdej5XkSlSwOPkQMb+N2ediDjq/sVNYrmBlBUfEP/DECTyoA1427PsHYWuqYDUPaMEHfXV7+KUk1S4vS0lqvSBM5wwYoHtJygiCCE9QScrSxM/oAgF3wdp6kxEDEW9b0ZuMKEx609jEz4jiUG8yUmDzHWA40m4QRjqSHiuJM71pa+Ln5EME9Fb15vzKTmG5g5UVHBH/yHrT1sTPyYZ9/yBsTXqzeUALPuire3yJ1JvasCX1ZoZ1BgzQvd5kBEGEJ6jedH1+CaN3BNw7a0tRRgxEKG5FijKisEhR8/kljCQOlSgjBTYTQkYjNWX1HiuKMylqO76Ekw8R61uVovM7O4XlElZWcET8I0tR2/ElnGzYFxDC1iRFmwe04IO+upewSimqDVtSiuZYZ8AA3UtRRhBEeIJK0at+CyunOwXcnXDtynWQNKMfEMEfLn4tB0kzorCIX23IusHK4VD6MlJgMy9gLIIg6uaJDqXHiuJM+truYGUFRCSXVrXv/MZOYbmDlRUcEf7I2td2BysrHPYVhMA1id/mES34oOX//voiuRK1f2VTuS1vZTV0mya+hTcSySqvq62shntedskGr4aRNbey/qHSpmoN9KtqF+EDpT6rZVPVQjq9p/pFL8nVhq2sT+rdrzrwPTJ4DANvY8sq1USBMhFg3mLL6mf1ptXPLo5Mw7jc73x7/+j6wfXOwfWj63/5lz21W1R+y7Nqcfxptfb9kfrRavQ75W+VglYtGfJLdy/ven3llcQPw3qikewer25wrSYauZC/qh2oO6rLQzUcv6f2sFa/kf/sywt33XS+ubx3tRPWf+/LpWaR+a7Yvf0oUjti5ZNl2xH7LW23yD55RFdz1/pbX79WoyRH8rnO0FfJhgL36sBFuWUHLNXGVdHNswOWah1mQw7Ef0Gc6GN/j2zi5rbAJuoq10Rd5Zqoq1yT+RWKif0qVzIoUETgt8DGadjNc52136ZbCxQRyB2wyflNronlJley1UAl0cZkRMFs9SwYB3QMoC5YYwdscn6Ta9JwkyuZQiApwM+R8uz2wrAVg/t0g4GZETyjA4ShQoWhQoWhQoWhAhiGBnRIYFbF7YBNUtFNtcNxm24pMLciNsAm5xe5mt/bI7rFmHxLeoDm8+WG0FOQEZg3wCbnF7naw84xnQCYZ7EbYBN1kas+5Axpxs5CvS/ESSq8NItPvXh0lnqj+HTk5UkS+1mciMSvc5pxMcKyPENekDBtgE0CHCcUULdsYeHCLF3oQHZZQRCrotAlDfscmVJq66zc09qZ196CcF57S+Rf+v3s82oW3Fh34/SpgPsUvhShw9hnxUCsG8Pn3+ayGScKS9ks6GaxDuUGK4q7yhknBXbZHjAcYeBn3SzUDkmPFcZZ7SyIfEmoA7zJC4jIEm1MVxeT1vmFnYnlDlZWcEQMBM+04KM64IXDvoQQuIbaGWBECz7o2R6GSZqM0zPfO83CwIvDIPJG/lh4p/FpPvazLMjOatXqVsVqnwCpYkOsM2CA7lUsIwgiPqFU7MWtC0rEVtsazs9oaXcbA6eDBNxBa0tSRgxEOIZLUvM2Bk4UFknqd1MdyQ1WEoeKlJECmwwBo5H5YTfUDkiPFcWdHjVvY2DlQ4T7VuXo/NLOxHILKys4Iv7R5ah5GwMrG/YFhLA1qdHmAS34oK/wCS6BaUdtEmGdAQN0r0YZQRDhCapGOU5w4XSBgLtgbb3JiIGIt63oTUYUJr2pv2PpBiuKQ8HJSIHNd4DhiEU3i7UD0mNFcSY4LUe4sPIhInqrgnN+bWdiuYeVFRwRAMmC03KECysb9gWEsDUJzuYBLfigK8GZnGV+cnbqe2ehL7/3JMm97DTPvZPJJPaT6Gzkx3WqcCs4tU+AFJwx1hkwQPeCkxEEEZ6ggrONU6xvDTzLgdWcDhFwh6wtPxkxENG3FfnJiMIlP00nVnOyONSfjBTY9AcYjyDtBrm2jtVjRXGmPy1HVrPyIQJ8q/pzfkdnYrl0lRUcEQHJ+tNyZDUrG/YFhLA16c/mAS34oB1fumoqqAsLXhyHq3ib36lKNHg1aPz57VQlgscw8FZ2qhJNFCgTAeYt7VRNeHaqzj73pPprLy9vUS1u5EHk+/7h6t7UqGrGVR8yxs2pQdSplr3VM3q/svk9425U4qgB99wgtHjTblSiocB9M3ClbduNSrQRuGNmXQVNtA6zOwbivzhMukGss7FHtnGD21HVjayJupE1UTeyJvObEBP7jaxkUKBSaHk7KtVaoFLAbkc9v5A1sVzISrYaKBfamF8omK2eBeOAjgFM/utsRz2/kDVpuJCVTCGQFODnSHl2e2HYisF9usHA1AiepAHCUKHCUKHCUKHCUAEMQwM6JDCttrgdlWopMLlitqOe38dqfm+P6BZjEi7pAVrMge2hpyAjcG9HPb+P1R52jukEwDyL3o6q7mPVh5whzdirW8kKjdtRExwnFNB9JYsRBLHQCV23cFDJYnSIgDsEvligw9hnxUCs4yJmz+ZKFiOK80oWI4vDShYjBXYhHTAeoYzlxkoWI8qVqGRx8iECfBszzcV8c35XZ2K5fJUVHBEBwZMk8KAOeNmwLyCEramS1TygBR/0rHVfiEk4nggvPxkHXjwWoZfFp6EX51EchFlwkuUbaN0PjRtJU6wzYIDu9ScjCCI8QfUnoHW/ui5AlS8uFi908Hus8AIOv7bWZMRARNpWtCYjCpfWjHUoN1hRHEpNRgpspgMMh0jleCQ6lB4rijOpGWdd/b2yN3n5ELG8Vak5v6Yzsdy7ygqOCIBkqWkc1AEvG/YFhLA1Sc3mAS34oK/wmSWhcZdohnUGDNC91GQEQYQnqNTcwJkljA4ScAetLUcZMRDRuBU5yojCJEdTHckNVhKHapSRApsMAaOR5zKx59pFpB4rizM5aju0hJMPEe9blaPzqzoTy92rrOCIAEiWo7ZDSzjZsG8ghK1JjjYPaMEHXcnR08mJyNJR5iVn8UQdtzf2xqfyQz5KUj/ITkZpeHJnA3I01jlDytEc6wwYoHs5ygiCCE9QOfqx5tDn+9OPLm4AuH/eaV73lc+V6uerhz3XzeWzP8rfbqlfmeWEZ0ZnCbiz1pamjBiIyIyQps+1BYhXWUmYlKn+trsbrCgOpSkjBTYxAoYjEEk3S4WOpcfK4kyaxiLuZtql4Ju8gIjg36o2nd+kmVjuRmUFR0RAsjY1j+qAFw77DkLgmsRp84gWfNDzu1HnnbhKdLq8G9WwHJraL1zJVnkd7TgNfdOOU6rBq2GEZ8fpy/KpUoZVUf2j2SeeKSFZ7STtqM2OF3cJVjtOn6iez8XfKh+Xzzvlr8pflJ/VYhO9a/WRNMXfCZXWkT/AdKnFHtmTMcyTbWxhpZooUCYCzFtsYf24/J0XdzsX5g9LA+Jgs2p0vlkVuxV1sSW1E0U7mE2p1HFYTWHrb0o1CXiqhavinHM3KtXGVdXNsxuVah1mcwzEf2GQdiOhs7FHtnFzu1FTdTlqqi5HTdXlqOn8VsLUfjkqGRSoIvC7UYNEiK7+yf423VygjEBuR03Pb0dNLbejkq0Gaok2piMKZqtnwTigYwAT+RrbUdPz21HThttRyRQCSQF+jpRntxeGrRjcpxsMTIrgOR0gDhUqDhUqDhUqDhXAODSgQwLzKm47ahglcTfMdabeppsKTK+I/ajp+fWo5hf3iG4xJuWSnqD5lLkh9hRkBOb9qOn59aj2uHNMJwBmWux+1FRdj6qPOUOasZW1+Wic+37kiXEceXE+Sr1sPFJdXUkSZr6IT9PJjMe4HmFZoSGvSZj2o6YBjhMKqFu5sHBhVi90ILusIIiFUeiqxsezjqzzBYVFtxZPixanewTcPfB1AB3GPisGYhUYMY02tmhxorAUwgwNWpwc7qpgnBTYFXjAWGQiDLqx0LH0WFmcVcEsDVqsfIhY38asczH3nF+JmVouOWUFR4Q/8IQJPKgDXjbsGwhha6iBAQa04IO+wg1akWlrahpinQEDdC9FGUEQ4QkuRTfZoMXpLAF31trClBEDEZkRwtRY32EkYdGlQdc3SVNGFIfSlJECmxghwxH5YVfoz/nqscI406a2Di1WQET0b1Wczm/ITC1XnrKCI0IgWZzaOrRY4bAvIQSuSZ02j2jBB32FD06JTLtZ0wjrDBige3XKCIKIT1B12u7BKZzwAg6/ttpkxECEWoTaNC+DMqKwyE2/Gwodyg1WFIdyk5ECm+kAwxH5cTfSLyr1WFncqU3zySmsfIhg3qrYnN+OmVquO2UFR0RAutg0n5zCyoZ9AyFsTVqzeUALPugrfEh0ZNqqmsZYZ8AA3WtNRhBEeIJqTf5DojkdIuAOWVt/MmIgom8r+pMRhUl/ms6I5kRxqD8ZKbDZDzAcQRZ2E1+bynusLM70p+WQaFY+RIBvVX/Ob8dMLdedsoIjIiBZf1oOiWZlw76BELYm/dk8oAUftNqNujOTXS43ocY6TKkshRUzX8V0twlVW43cJRu8Gjz+5W5CfTl9D7YJlejJGObJVjahEk0UKBMB5i1tQg3W3YT6mXpwOnKWMFugVrtP717ei/rKK4kfyv87unPnjeXNqInah1p9yFUfRXdxceq1i5elnl+iSr071Y/rfg5p/RfVCrv6yy+983/EuGuVOHDADToInW/saiBaCNxdA5fvtl2rRBuB22rW1eVE6zBbaAD+C9XuSKFNbz2yjRvctaruUE3VHaqpukM1nV9emNrvUCWDAmUHfteqtN+ya5VqLlB3YHetnl+imlouUSVbDRQfbcxaFMxWz4JxQMcAZv51dq2eX6KaNlyiSqYQSArwc6Q8u70wbMXgPt1gYFIET/0AcahQcahQcahQcagAxqEBHRKYV3G7VqM8zbpC2wx4m24qML1idq2e36JqfnGP6BZjUi7pCVpMre2xpyAjcO9aPb9F1R53jukEwEyL3rWqblHVx5whzVhl7Tg/FaM4yrxwFORenGRn3liobQVJnJ2eBqenodhAM1Zs3LWa4DihgLqlDgsXZrlDB7LLCoJYP4UugzReLcCwcZXRQwLuIfjagQ5jnxUDsV6MmEmbK2aMKCwVs0C/uHiDlcRhwYyRArtcDxkNkUdRN4x1MD1WGGcVM9veVU4+RMRvY+65mIHOb+FMLdeqsoIjIiB42gQe1AEvG/YVhLA1VcyaB7Tgg64EaTQ6ybNJlHji5FR48egk9fIgSLwsT0+Ck5NgfJqM7mxAkGoziRSkKdYZMED3gpQRBBGeoIJUt3f1idKZS0WayVuj10ed10dvjf7bf3vt8s7VlcpJvZE1CeLMV9WYO/9aatT7s+LevPur+uzHVZHmZSWAH5xvm31Uf/pheX/2sxLf31K/9OfI77H6XMB9vrbEZcRABHiExDUWixhJHCtcRhKHCpeRApteAaMRBVnSlTlNB9NjhXGncLMo70baeHaTlxCRRFrVuPPrP1PLfa6s4IgQSNe45mEd8NJhX0MIXZPKbR7Sgg+6UrknYR6FYTD2TvPoxIvjMPay0Pe9STDO83EaJOmkft7dqlxtO6tUuRnWGTBA9yqXEQQRoKAqF7gH1o/rfiBj/47OG3us3hBwb6ytPxkxEMEXoT/NS6yMKCwC1LIplhHFoQJlpMCmPsBwJEnUzTLtiPRYWZwJ0Njv5rGO7yYvHyK6tyo/59d9ppb7W1nBERGQLD+NgzrgZcO+gRC2JvHZPKAFH/QV3hQbGzfF5lhnwADdi09GEER4gopPB5tiGR0i4A5ZW38yYiCibyv6kxGFSX8aN8UyojjUn4wU2OwHGI4oz7qRfh2px8riTH/aNsVy8iECfKv6c36jZ2q5o5UVHBEByfrTtimWkw37BkLYmvRn84AWfNBKgNp0ZcubYYUO73qY2e54kYCreBvfDEs1eDVo/O/NsFRPxjBPtrEZlmqiQJkIMG9pM2yy7mbYX5V/kj/uufz1Yvrj6Uf6e1lfeSWJw7CtvbCVJfJRlA/rXfWll+XX6umt/sEHlXkvqke2auGYNXn8qf7kTztHQeB2Ly113FcTJN9eWqqFq8qfcy8t1cZVSc+zl5ZqHWZjD8B/kVTpic7C/4e9v++RJLnOPNGvErjAAmRkRsDfzF840B9dpWQhipWZUemZM8NWC4N8vUtAIhcUB9g7wABsNilSlxw1XyQMt8lmq1uzIwF3sFvdzRKr34H9AHsjv8L9JNfNI9yj0tPM/Dkn/FgESWmG0VWVWVnnd8z92GN2HnebsSPc3pO0uT7/Ndfnv+b6/Ne8OXcxd5//ygYFNcvAT9KywwVFC/FJ2nx9/mvuOP+VHTWoXIZY6miY8cyBccjHAGXDBk/S5uvzX/Oe81/ZFIpIAV9HOrN7bWCdgI/5AYNTIrxeBOpQqetQqetQqetQCdahOR8SnFUHfJKWHSo4uRKepM3X57/ab9wTfsSUCZd1BTXr8Z7aU7IRhJ+kzdfnv7rrzimfAJxpqU/S5vr8V3PNOeMFu7tdNWV7kjYPaZwooPeumiQIYdMV3UOR76pJJkThCcH3GUwYB6IYhD1lwrLZ2lWTRPHcVZNE8ddVk6Sg7ukDw6Gmme3FV5Iku9BTE+UjlPchFprtcrM5ITR3HPkqCk6of/AaCR7UuSwb9f5D2Hp6asCAlnLQO/xAgbI9NptH1GRggP7VpyAIoTyh6lP4gQLJbCg8GxtLT0EMQukdRHoKoghJT9sDBZIoHqWnIAV16gOGo5iqwgQyEwXxpjwdTxOI8hFK+6DKszn9M3ec5yoKTih/bOXpeJpAlI16+yFsfcqzf0BLOegdfmGLsj3KmsfUZGCA/pWnIAihPKHK8w/ihS2SOVd4zjfWt4IYhAJP0LdWR5IgiYi8tb6wRZLEo7oVpKBOr8BoJOk0iI0DMhNF8aZvna9rESUkTCGDKtzmzNHccYisKDihALIVrvN1LaJ01JsQoevTuP1DWspB7/BbspXtidk8oSYDA/SvcQVBCAUK1bhbeEu2ZIYUnqGNFakgBqEgExSpfcdVEMWzJBUk8ShJBSmosyEwGlEcTEObN18QxZ8ktb8jW5SPUO8HFaTNIaS541RZUXBC/eMLUvs7skXZqDcgwtYnR/sHtJSD1qfK1pI0ec2tN//q+vI73/jWNw2JYMnNxMRZKU3l4IzToMtpe5LWHi1FRK4fpjWG+4AdbvcycyQXlYp1V/3Nxad6G3Rfb2wue+zPF5/e/rjeFK2++Lu6Pf/s9m+0qrz9sYmpUoDqKzM22L2qaCfbrCiuHtVKbQWQG39Cjx/3uuugj2xBH/GDVvSgcXt7FfOxLeZjfsz4LcAvtKvnaMyxl+zY7z0J0RM77QI5tQV8yg8YL+bEZx+qeM9s8Z7x4q2vjtfaOcjbWefWM8Ly1EkRWbOOBcuckHTMpngfsOPtlu5NX+5Q71U8W/x2+VDCSxOSZToaLT7THrK622Yie8gm6xZ1yZctMENUpBCB8NqXLfxi8Q8T44L8gB1sdwUg+IYAZoTgs4yUTQ37GwKYMYIPMW66XcGMjvLAIpC/KJmmiSnCGTvCLb4hIGsexU3drwTgkoHzHP2VAHmcTgPjvPE1frTgREd9I0C6fiOA9fSoJ/yowelus2VKu2uTjmcOjEM+Bji3MVYr7ZO56fjuQDjeCMClUEQK+DrSmd1rA7u/fOEGDE6B8AYYUHdKsO7M+VTgtEl7BUAYFsk0Nk6eT/mhgrMn5RUA6foVANY79YQfMWVGZV0y7Y6iu9iUbATpVwCk47sD4HgFAJcAnFmJy2B97bRB3V8Gc4LV0d5kNxeXWXA1CZPzy0mSXoWTvPppkzBOr26iizQ7j6+XPNYV8l+e27vQzFWydZ2c0TBRPtNa2oFFWU+bQB6IghC6RuhC+xf3F9N6JX375mhUr7hXLwCo/6R++9yPasvrx41JdfFu803L3+dBHMSrL/20+mP9CoEPtbPVlK2HotlSeLbwlbEJ40AUoysWHBhDrJkFSWQMAyaOR6IcHu0CghTUbiUwFq51uiCJN7dAkap8GhsJH8sSEir/EGvOduXZHE6XO84bFAUnVD94uUQY1rksHfUeROicQzpHhrSUg146Bl4SZVbtOahlwDjZVaIzd2LeM0b4MQwYg33ADhbvlaKa8d26E/OZ1QOQaw8AM1rfHoBi/zDOYltl40IkdAh8xbsyAhT7R7bIj/iRK3rk+Ep36QYo9o9tgR/zA8cvc34lXW2kFfulDaBkA4j7Aor9U1vUp/yo8bJN3BVZmgOK/TNb0Ge8oOuL5TWfc491y6Nwhp9Ycw5Hy5p9rM4AZrj4jYnOP/9UP72rD1744PbHi+ej+pnd9/Wr9LUP4IvmHIjlOwx/oL9x+c780cpD8JkJsJq3Cj1vMSk9z1tFsF996DeMF1k1gwWB/kj0R159hJH+SPWHnt+iWH/o38b6+2L921j/tSTUH0p/6O9T+gtKfyHVX0j1F9LCNjdyE+Vhbqyyc6Szc6Szc6Szc6Szc6Szc6Szc6Szc6Szc6Szc6Szc6Szc6Szc6Szc6Szc6Szc6Szc6Szc6Szc6Szc6Szc2TLzhE/O4qeHVJNPdbJOdbJOdbJOdbJOdbJOdbJOdbJOdbJOdbJOdbJOdbJOdbJOdbJOdbJOdbJOdbJOdbJOdbJOdbJOdbJOdbJObYl55ifHLyUbDrHV0kqdZJKnaRSJ6nUSSp1kkqdpFInqdRJKnWSSp2kUiep1EkqdZJKnaRSJ6nUSSp1kkqdpFInqdRJKm1JKtlJktYRVWZOdWZOdWZOdWZOdWZOdWZOdWZOdWZOdWZOdWZOdWZOdWZOdWZOdWZOdWZOdWZOdWZOdWZOdWZOdWZOdWZObZk55WcGn+Y5WqVKzJlOzJlOzJlOzJlOzJlOzJlOzJlOzJlOzJlOzJlOzJlOzJlOzJlOzJlOzJlOzJlOzJlOzJlOzJlOzJlOzJktMWe8xLykhzw6JiN7J6hwvfM6TlPr8GLBMjWR3THJjRe0kKCi6DfN051Lx+SP9HlYiw/ag4Zu32xPE3pzVIml5/U7n+tHPW9/oI/AWvy2fhf0h9U3/MCsn57X7zxZKqh9/S3LV/J9uHpvyW/10VujL+n3lyx+V/26/Tf29UOkv1i8U/8d/Xjpc/1kqm4PvVVF/d7i7xdvNQFMv9z8Cxrm8+of1y9PqV/3t/jUlP6H7PR3ZYigrZMboiKFCIRXjcNyzH470oeS6VPP9CsYb99Yn4VWn0m1upS0sfYn9aVU6WrjhVQr79/VV8jyElhdTrbL50t3rop7V0rz4PH7evAXH+/rJ5b1c8lf6Nf0NJfRl1cHtn2o37uzfDPk91bR37l26ibl8ni2fQ2hf9CLl1zCOqy7vB/Vp7eFKtir/vcnVQUfLU/Yuv2hDq/OwKon+kH1b7+p/+FRFPxPy/Pe6lf5PG+Ogvv89m9q93J9GFw31S/qx6yf1yeXfWRZq0xNl9IB+1ICHUeEBqKO+sPpyHxbfpUdKGgiIvQH7d5bboyge2jD3h83OopTCMhfFOah9Rlgbozbc98W+nyuIlpZ4Qr3qVxsPFA40S24UW49k4sdLCiciA7cYn0mV+E4k4sdNSifNttsafqghT4Xx45xyMcAZQhjK6QxxhXrM7mKnjO52BSKSAFfRzqze21g93YS2AGD8yHcUgZqT6lrTwnWnjkfDZxBaTbcJLDUnaf8QMFplGDCLdbncNlv1hN+xJSplXXVNE36nnpTshGETbjF+hwud6055ROAcytxC0dfO21Q93ZWWMHqaC8CVYRBfj1J08vrSXKu0kmRpWpyWUTJdXIZXOQXq/vVuunyl+dDmnAdWxmvVAWKhonymbZnHFiULRoTyANREIIVC927+ed7a/FnenX8olqdvr58Kdftm837Z63v7Fq+Rdbxzq79URzY3hT1UDRlCk8Zvplx+73p4uNpZ2X/rPrlp9Pladp1O7BZxY++tFrXf3mkdxxu/9/1s8SGXZAXoz/RS579MB1H42A/CP+kot+P4khvRnxoW5YLJo/ggCMs361vDJNEETEAB+Zq9kiUxJ8FWJKiq2ccFOh2QRXSNLK9xVaSxZsJOJsWRrzHsniEaWeINW+78m1Okyocx4OJghPqH7xcQ8d0LotGvf8QtB77LzCepRx0rYmvz6/jq4sinKRFcjlJYn2eQ5xdTNTlRXQepnkSZNev+dfEFo/w6sIg5ALj86+JBUEIxQnVxL9aSrhW1GmVV0m0v9WNlUrofqk5E+yL2zcr6VcpuC/Xh4VVCk/LPVMKHoqmQOEpwDVutxdlwjoQxSJUX4L67GseCQKJaFDLivqRKIlHDSpIQZ0DgdFIsiKfKmUToYIwHkWo+VSYx7J4hDo/qAhtDpYqHCeFiYITyuAGItQ8pnNZNOoNiKD1idD+8SzloOtn0PZb0eLZ9WaTmbGTNu/SenK9xVbXGzNesG2LqkTjzukHlXB8o/qD79Y+pc9qR1tjXFvukOovV7/7YnVEwvPFJ7d/u/qKyUL0vDbTfbQ2Gz1fbsbWrqVPbv9mWp/eNQpd0pOZrwTL1yA2NWaIihQiEN7ivfpotvf1iN7+uEquaZTvbd1+tvh8sjJyvTRen+rT3W5/oof3veqXtcNKXxK1Y+yT259MojAYfan6fW1J1IP9rDaffThavLX46eLni79f/MPinWo18svq9++OTh+GYfZl10X04uWrxH01vaHfa7ncq1761EbV4uZ5/b31oXT15fXRyts2WV1e/2bUvpzxnxZvT8J8f/WLwjSqB+xRBTvkBNFve+UEN0Kw0U1R8XarGDNGsMe9qT5nRkfpZwP5U9lUmQKcsQPcok8s0T4xpT/SxrARu81iXEZQb9DNYlmYTQtjWfgaP1pQcFDdYvHaLWY9WOsJP2pQdgyxaNEw45kD45CPAaqBTdxi8fjuQDjcYlwKRaSAryOd2b02sE7Ax/yAwbkQXvkBFajUFajUFagEK9CczwfOpDTLWBhEaprZTGPcUMEJlWIai9emMes9e8KPmDLJsi6edlXtLjslG0HaNBaP7w6AwzTGJQDnWLJpLN5rg+oEe8YLVkd7kV9cqavr68n5xXU4SZLifJKnlxeT86ssv1Lq4urq5mrJY92zcGzicPctrKaxhIaJ8pl2NxxYlB0OE8gDUZCu/nCND3Pro7P+rV/Y2K5/G/fYbxbvLt6uPn9erWffcyxxTRl6KJohhWcI30kwYRyIYhA2iglLZ7tbSxBFqFOmTCSPREk8dsoEKagb9cBo5GlkXbILknhrk8XxNDHyPZblI5T7IZac7cKzOQ2wcBzvKApOKH/wagke1LksG/X+Q9j6GmX9A1rKQS/fDRHeZJdXN+kkvIyiSRheF5M8uM4mQaACleZ5WKiVSvMqRm1tNEXNBcbnX4wKghCqEypG323fCm5teWhBGsZBpWQqJbr4NNof3b6p+xyrN1aEwe0PnA00wYQoPCEba09BDELxJWhPa9tGkERIetpMWoIkHqWnIAV16gNGI42nkTKRzERJvEnPqJqnchPfY1k+QnEfVHqqRqkoh/SUBCdUP7b0tA7qXJaNev8hbH3Ss39ASzno5T5ofHEe5mEwicP0epKEYT4pguuLyeV1VFypyzwOstWge5Wexu3eSnqm1FxgfP6lpyAIoTqh0lMfXv65fiC2PoSmEpDPal2pXTP69bAf1Y8FLN5Z/Do14T4UxVU47sbCUhCDUFoJwrLvIQBBICF9GSgTyiNRFI8CU5CCOsEBw5EG0zgzDshMFMWbwgzTaWBcmz2W5SPU8EEVZtoIEsdJqKLghDLIVpjWQZ3LslFvQIStT2H2D2gpB908BaBea4Wjx6cAbBoyc9FmQZfW01MAyvoUADPebgnZ8CmAf9SbjvW7UD6qtx8/0O7sxpv9+WTxu0oJvlErwhf1C0c/qRTiX1e/Xp8IsGqPfzAKddNcG8A/MhE/ZBMnGPEgPn5miIoUIhBeNS7NINQvjF08H9XW998tfnv7Rv1uX/07/d7gD/QXlq9s+VGl339w+71KF/66fqnL8/ods5+sXoPzvdUrYg3e+5+MvvS//EmYqPo9Lcs95uni42rc35/uL9/z+rz6t6rvXL30tVojrE+GWL49Rp8g8d3q538w+v/9zf8e1j/pncWzL4++vD/6zp+EqnkfbP3O4v+99lG8XZsmfrP41eJ/6Evo//HSl/7b4qeLd/Wf2d4Zwxym7iwkaMxnRgjaCUnK2mrMZ8YI+gg3lczM6CieQSB/UZJMg9Ro6pmxY9yiNz/XtvyiMcVmbls+Fw8UAHRbvkoTuy2fGy2oAKi2/Gxty7ceF/iEHzWoA4ZYRmiY8cyBccjHACf3TWz52fjuQDhs+VwKRaSAryOd2b02sE7Ax/yAwZkQXosBxafUxacEi8+cjwZOoTRHfh5k09C48njKjxScSCmG/GxtyLferSf8iCmTK+uyaRe47oJTshGkDfnZ+O4AOAz5XAJwdiUb8rO9NqhOsGe8YGs5VoTn11EWT87TPJ4k11kxyfPrq0l8ERZxcXF9kzS3gXX7wLGfwt1CsBryncci3sdE+UwbDQ4symaDCeSBKAhhExPdhXhntRh99tLeQ2fD4fP1i1o/Na9uX37V6/qB9dXiWPv3v9DrVd3lMuXsoWjOFJ4zfJPAhHEgikHYxqUsoo0T61dFSaTaWEaUR6IoHttYghTUXXRgOOJsmgVGz8lMFMVbG0ulcTFNbW+zkiQkzAFDrEDbdWje9D1yx1pUEpxQAeHFE2FY57J01JsQoetrZfUPaSkHXWvUOE9VfpOpyWX9vfH15eQ8OU8m12F0c14ElxfV52v+Napxa7nSqAU1Fxiff40qCEKoT6hG/bvbv9XH7S2tUr+tuyTdltjs1SeT09Ht67WKrd+8+rk+43ElUuuXES3ftBroz8i8Mf9QNDEKT8zGQlQQg1CGcSGq34tlQvmqKIqIEjUu4x+JcniUoYIU1BkQGIuwEqHTJDW2LWaiMN6EaCVXUhPeY1k8QpUfVIUWjWQpHCpUEpxQ/tgq1Damc1k06g2IoPVJ0P7xLOWgtQZ1Scth3VOJie6VOHCd0lX9X5duy+4pdrxg1xTVhP7cU2ziBCMewD3FDlGRQgTCW+4QT0etyenZSzvCt99fPNPHV7+0HzwyvcT0S//f1/8kDMJJGLxki4r3R//3J38S7AdJOFr8vJKL9Z/+X8++PFoenrByQ5nfpar/BeKbVCfmF8288rB+l6qq/0kN83Ht0XrJLqZD+bA+3Ov9+kHiKiP7zUHb1ZJkpJTxjaimgT1gDyzYZcYVus1vxY4QbBbjwtvut2LH2BXWIn4rdnTd+XpTv1VgeasKO8Ctma3iINyvPiL9ES9NDxWEy3HFZwRFw6COK360oGqgOa6qcBrH1SrNpqif8KMGtcMQKw0NM545MA75GKAg4DuudOx3B8LquOJTKCIFfB3pzO61gXUCPuYHDM6F8HINqEClrkClrkAlWIHmfD5wJh3MdsWPFJxPcdvVuvI8ddyyJ/yIKXMs69pZrYT7qk7JRpC1Xa0rTjMAVtsVnwCcYom2K33ttEF1gj3jBVsr78voRuVFMclvLotJktwEk/Pr4KL67XkRRdfXmYpXI2Ldd3BsvHD3Hiy2q6pM0TBRPt8tLVEQwmYnun0xeEsrjMwtLdHEKDwx+BaCCeNAFIOwp4svmK0tLVEUjy0tUQ5vLS1RCuqOOjAWYRJbl+mCJN76Wfk0Skx4j2XxCCV+iFVmu9ZcHWy8+oUJ/FAWnFD74AUSOqZzWTTq3YeguftZyHiWctC1/ry8jK+vzqObSfWlbJKcp+kkT6KLyXV0nl+oICjOL1d606v+NFuq4tVrIwi5wPj8609BEEJxQvXnW5u/cr/uhJiS8VA0GQpPxsaaUxCDUHdxzWl95b4oiojmNBogHolyeNScghTUWQ8YizAybgTORDm8Kc4omMY2ySnJR6jqg0rOqJEo9mOpZcEJpY8tOa2DOpdlo959CFuf5uwf0FIOencfNU0s76uKV0+KEXKB8fnXnIIghOqEas5deNRUNGcKz9nG0lQQg1CfCdLU8qipKImIMrU+aiqK4lGcClJQp0dsOJRxsTATJfEmT11PmsoSEqaAQQVq3OgZ+2HEsuCEAsgWqK4nTWXpqPcgQtcnUfuHtJSD9mvzVya6SnQmTjrVpdu6zZ8Zb7do/B7Z/JnECUY8iM2fGaIihQiEtw2bf/h75vMPaUZ/5tCC5kaKUDe2ar7KjhC0J5IEuNXoz4wRNCZuqqyZ0VFMiED+YmPXZsYOb4s2f6Ud/qn+yBqTbeK2+XMZQdEwsM2fGy2oGqg2/2Rt87ce7fmEHzWoHYZYbGiY8cyBccjHSIgYDNNtMr47EA6bP5dCESng60hndq8NrBPwMT9gcCaEV2xABSp1BSp1BSrBCjTn84Hz6IA2f26k4GxKsfkna5u/9ZY94UdMmWFZ1067EnZXnZKNIG3zT8Z3B8Bh8+cSgFMs2eaf7LVBdYI94wW7sy0vy2r+lXh1xheMifL5b3kJghD2O9Hti91oeQnmTOE5w3cXTBgHohiEHV/KStrW8hIk8d3yEkTx2PISpKButwPDoaaZ2Xk5EyXZkZaXJCFhChhiFdquRVXTH7GfQy0LTiiA8AKKMKxzWTrqPYjQ9bW8+oe0lIPe3ScBlPVJgJSaC4zPv0QVBCHUJ1SiCj8JIJgMhSdjY+0piEEovQTtaX8SQBBFRHzangQQ5PCoPAUpqLMeMBZRZKzeM1EOb7rT9SSAJB+hqg+qOtNGotjPppYFJ5Q+tup0PQkgyUa9+xC2Ps3ZP6ClHHStOa+C6zA7D5JJfHkVTBKln1RNb/LJxXmWnl/mSfWxmiS8ak7j7kWlOV1naxlzgfH515yCIITqhGrOwd9+ElnffiKYGIUnZmP9KYhBKMK4/nS8/UQQRUR/2t5+IsjhUX8KUlBnQGAsImV0ysxEObzpzzCcms8qeCzLR6jwg+rPrJEr9uONZcEJpY+tP62DOpdlo959CFuf/uwf0FIOuvq/P3+peCbVf/7MpTOHtf0bdykqhZk7aOMs6tJ6sv3n5tMIHrDjBa17qEB8p9J3v9V6r1J/S733THvN66737XdXNnNt8H8xWry7eGvxs+VmZcfz/4vqK7/aH1U/7ReLd5Z/FmlLtgn9IRs9wdAH8f8zQ1SkEIHwVgP0gTYqTEeLf67G5tnKkr8arLdq38Ibt9+fLP7b7RvVUOphqcbhxeK3+nEObbt/v/o7WvR/cPvjpYW/fjhjetcvH6nXXvumKRsH7GyARkFc7Not88wIuzpW1DLPjBE0+W2qT5nRUQx9QP7SwNi2nLHj26Jnvtg/jMNAf4SNYzV3e+a5jOCMS/fM60ay+Xr+Gj9acMqleubztWfeeszmE37U4MQ7hG7XMOOZA+OQjwFOopt45vPx3YFweOa5FIpIAV9HOrN7bWCdgI/5AYNTIbz4ASpQqStQqStQCVagOZ8PnEhpnvkijKa5Ue8/5UcKTqcUz3y+9sxbb9kTfsSUKZZ17bTLSnfVKdkI0p75fHx3AByeeS4BOMWSPfP5XhtUJ9gzXrD1MiRUN9lVEk/i4jqcJHGaTs6Lq2ISXVzHV0kYXFa/W/JYF+2OXQzuwt3qmS9omCifaXnvwKIs8U0gD0RBCFuH6Nq/XkxW6/j1YvL2r/XT1ku/+9IObwJ9KAqqcFDCMrpnlWzCPBDFJOyIEtbHdjOSIIpIM8i40H8kyuGxGSRIQd2OBsYijAKbG0kQxFs3KIqnsa0bJMlHKOlDrCrbtWXRNA/sRzvLghNqH7wgggd1LstGvf0Qtr5uUP+AlnLQteBM8uCmuEzSSZKreJJk1V84v4yDSZwEV1l0fRMkWziLKbU54MOAmguMz7vglAQhVCdUcP5jayz6WD+D+ax2IX23Eps/XnmMKkGqu07fX3yuX/dTv43qg/odQvW31P4jNa7+fxwEgb2/JJkVhWcFV6cmjANRDEIFxtWn3YokiSKiPgOzkfGRKIk//SlJQZ0AgdEIc8t4zERJvAnQLJnGxqnqsSwfocQPKUDDYKVXQsfZv6LghPLHFqDWQZ3LslHvP4StR4ACA1rKQS8PA73Jg/TmKpjcRMHNJLlMi0l+VRSTy+vrJEjjm/MgWU0UXgWosWpVAjSk5gLj8y9ABUEI1QkVoL+oxOUb9eZm43XSv128WLmdXq8l6U+WanO0+NXip4t3F+8tfrn4dfW/t1fPaT6ZT1Q4WvzUlJCHoglReEI21p6CGITii2tP+86nJIqQ9tTt7fsoj0RRPIpPQQrq5AcMR2Ebj5koiTfxWfFFxv7jY1k+QnkfVHw2B0eGjoNARcEJ9Y8tPq2DOpdlo95/CFuf+Owf0FIO2u8r7zMTXSUnIwddkqRdum1737nxghY8VA1uw/vORU8w9CG879wQFSlEILxwkoxu/4t+qd/iX8ze9w+1f72S7Z+vXqqydrrr33YM7mGyv3K6R1anO5cdtPcR9KzN6c6NEDTo4TLV4XTnxgha8zbVn8zoKDY8IH/J6p1U91UlM77tOd3DWJvcE/2hVj7TMHI63dmM4Pw6rNOdHS04wRKd7mHUOt1D60mUT/hRg9PsEKpcw4xnDoxDPgY4ZW7gdK9ivzsQdqc7m0IRKeDrSGd2rw2sE/AxP2BwKoSXNkAFKnUFKnUFKsEKNOfzgRPpcE53dqTgdEpwureV56njlj3hR0yZYlnXTrtodFedko0g7HRvK04zAHanO5sAnGKpTvfq2mmD6gR7xgt2Z/s+mc3pvjoAAsZE+fz3fQRBCBuD6ErfQ99HMCEKTwi+uDZhHIhiEPY9Cetke99HEMV330cQxWPfR5CCuu8MDEcaTDPjeMxESXai7yPJRyjvQ6ww23VmczJu6DjsWBScUP/gxRE8qHNZNur9h7D19X36B7SUg95d13tmdb0n1FxgfP7FpyAIoTqh4tOX610wKwrPysYKVBCDUIFxBepwvQuiCCnQ2ETySJTEowAVpKBOgMBohJHljPuZKIk3AepyvUvyEUr8oAI0afSK4yhcUXBC+WMLUJfrXZKNev8hbH0CtH9ASzno5cFD6vqqCPJicnGt1CS5uM4rsXoRT4KbKE/Po6uLi3P1mn8BapxFKgGqqLnA+PwLUEEQQnVCBej993x0jTPNEUT1q+JrJ83y9/+oN0krYfpCvyv+ZWG6dNt8sfhc+55+uXhrUm+Y/nTx9uLvqs9/WLy3P4oD297cQ9EEKjyBG2tVQQxCsca1qmO3VBBFRKtatNEjURKPWlWQgjpXAqORBplVqwqSeNOqYTSNjO35x7J8hNlgUK3anKkYOo7JFAUnlD+2VrUO6lyWjXr/IWx9WrV/QEs5aL8meeP+d6U+Uydd1qXbukmeGW+3ZPw+muSZ6AmGPohJnhmiIoUIhEc3yWs9X+v6Hy11vMMmb0A/YKODxkCCmrV65JkRgtY+iki1e+SZMYKmvk3lJzM6ioEPyJ/dI8+Mb4se+Uzb4/PGnJq67fFcPHBmHdgez40WnFqp9vh0bY+3Hs/4hB81OMEOocc1zHjmwDjkY4CT5Sb2+HR8dyAc9nguhSJSwNeRzuxeG1gn4GN+wOAsCC9qgOJT6uJTgsVnzkcDp88BnfHcSMFJlOKMT9fOeOvdesKPmDKxsi6bdqXoLjglG0HaGZ+O7w6AwxnPJQBnV7IzPt1rg+oEe8YLdmd7Q7nVGZ/RMFE+/70hQRDCbiC6vN/B3pBgAhWeQHwFbsI4EMXoaggHBmE1be8NCaJ47g0JknjsDQlSUPemgdFw9YYESXaiNyTJR5gNhliLtivS5uzZ0HGYsCg4ofzByyh4UOeybNT7D2FzDugcGdBSDnp3n+LMrUZ617FMxlxgfP61qiAIoTqhWtXDU5yCCVF4QjbWnoIYhOI7iPYURBHRno6nOAVRPIpPQQrq5AcMh+spTkESb+LT9RSnJB+hvA8qPvNGqzjOxhUFJ9Q/tvh0PcUpyUa9/xC2PvHZP6ClHHT1f3++v5ya/8wlLoc1KBUmykpWFg7KOIu7lN4MSsb6+YAdL9g/RVXhMAYlvV2pn+SrFOXHekP09o3b71a/et7vVWJmIcGyMIhXiRmiIoUIhEf3Kjlf6KlWRqV09d989d/Q2GM4YOcBbNkS5K7VuMSMEOy84irWZVxixgj2XDeVp8zoKP1VJH8qKGLz/sGMHeP2zEtRsF99hPojakwEhdvBxGUEp166g0kFud3BxI0WnHupDqZi7WCyHun4hB81OAMPIdw1zHjmwDjkY4BT6CYOpmJ8dyAcDiYuhSJSwNeRzuxeG1gn4GN+wOB0CK9+gApU6gpU6gpUghVozucDJ1OajSmL1DQz6pKn/EjBKZViYyrWNibrLXvCj5gyzbKunXZd6a46JRtB2sZUjO8OgMPGxCUAp1iyjanYa4PqBHvGC1ZHexHm52laXE6UuigmyXl8MSkuri8neRJf31wXcXATXy55rKt3xzYGdwVvszFFAQ0T5TOt8x1YlLW+CeSBKAhh7xDdBNg9G5NkAhWeQHxxbsI4EMUgbKUS1tbWVpIkikgryfIo4yNREn+dJEmKrs5wUKBL+igL02yaGU0hM1EYb80kh5NJlI8wIQyxJm1WplFzbG3kOIdYFJxQAeHlFDyoc1k26i2IsPU0k4ABLeWgl06m8/P8Iq6+LUvjZJIEN8XkXF1WH0EUXl7H6iZrFvxe5arFyRS5j8Uz5ALj8y9XBUEI1QmVq85Xgq6MSn8SLz4dLV/+efuDSI3sLShJeIXDbyw1BTEIhRaXmvY3f0qiiEhN65s/JUk8Sk1BCuo8B4xGoqJsWtiUpiCLN6XpePenKB+hlg+qNJszaiPHocOi4IQCyFaajnd/irJR70CErU9p9g9oKQe9u575wvbuz9XLZCi5gPj8K01BEEJ1QpWmvGdeMiEKT8jG6lMQg1B8cfXp2OgURBFSnzbPvCSKR/kpSEGd/IDhiKI0nhbGveeZKIs3+elwzYvyEQr8oPIzatSK45xdUXBCBWTLT4drXpSNegcibH3ys39ASzlov6/zDI2evUpRxg68JMm7eNu2y3Pj7daM32+7PDcLCZaFIezy3BAVKUQgPLpdvufVnlTDPDcToEOQoHVthnluhKDHD5ewDsM8N0bQ3bepNmVGR3HyIflzGea5MW7RMJ9or3xzFH0UO73ybDxw4h3WK8+OFpx4iV75KG698pH1IMgn/KjB6XcIua5hxjMHxiEfA5w/N/DKV7HfHQi7V55NoYgU8HWkM7vXBtYJ+JgfMDgTwmseoPiUuviUYPGZ89HAKXQ4mzw7UnAiJdjk26Lz1HG3nvAjpkyurMumXUi6C07JRhC2ybfFphkAu02eTQDOrlSbfHXttEF1gj3jBbuz3aAwsPrkExonCui/HSQI0pUergECV/8e2kGCCVF4QvBVtgnjQBSDsBlKWCLb20GCKL7bQYIoHttBghTUzWhgONztIEGWnWgHSfIRCvwQ68t2ldkcXBs5TiIWBSdUQHhpBA/qXJaNegcibH3toP4BLeWgd/cxzUp/GncUK/2pqMnAAP3rT0EQQnlC9ecOPqcpmECFJ3BjvSqIQajWg+hVQRQRvWp/TlOQxKNcFaSgTpbAaPQ8pykI402vup7TlOQjTAiD6tXm8NrIcRqxKDihArL1qus5TUk26i2IsPXp1f4BLeWgPduXbDugqROv6OJt3b7EjLdbM37P7UvMLCRYFgaxLzFDVKQQgfB67UuVkn9epfp5vR/9Wf/7PrPGrtT4l8wvGzpgpwDs1hJErtW3xIwQbLpStKvdt8SMEWy3bqpKmdFRWqtA/uKiiMwnuM/YIW7RtqQPKY5y/VE09gH3ScVsRnDWHdi7xI0WnHWp3qX1ScWR46RidtTg3DuEVtcw45kD45CPAU6em3iX1icVRz0nFbMpFJECvo50ZvfawDoBH/MDBmdDeMEDVKBSV6BSV6ASrEBzPh84lw5oYOJGCs6oFAPT+rhi+y17wo+YMsuyrp12KemuOiUbQdrAtD6u2F1xTvkE4BRLNjDp44rN1eaMF2y9/AjVTXaVxJO4uK5WDnGaTs6Lq2ISXVzHV0kYXFa/W/JYF+6OnQv24t1qYMponCig/waSIAhhvxBd/99vIN1fRZpAH4qCKhwUXz+bMA5EMbozvgODsAa2N3oEUUQaPcbF/CNRDo9tHkEK6h4zMBZZkSfmvttMFMVbkyeKp7Fxf+uxLB+haA+xcGyXj80ptJHjWGFRcEL1g9c88KDOZdmoNyDC5hzQOTKgpRz07r6Ms9KUNlOS+5g7QzIwQP+aUhCEUJ5QTTnw2zgF4RUOv7HOFMQgVFpcZzreximIIqIz7W/jFCTxqDQFKagTHTAaYVhk08xYs2eiLN6kputtnJJ8hFo+qNRszpyNHIcIi4ITCiBbarrexinJRr0DEbY+qdk/oKUc9A4/fxlaX8dZkJMBAfqXmoIghPKESk0Pz18KJkThCdlYfgpiEKovLj8d25yCKELy0/r8pSCKR/0pSEGd/YDhUEU+zY3ttpkoijf56Xr8UpKPUN8HlZ9Fo1Ych+KKghMKIFt+uh6/lGSj3oAIW5/87B/QUg7as53dsncZu05VSlTQxdu2nZ0bL2ipQ/Xglu3s3CwkWBaGsLNzQ1SkEIHwOHb2nvdxwoZ2bhJACx9B5doM7dwIuwJW0tDOjRG0322oSrnRUax2QP5chnZuiNsztMfhfvXRnBgfB04vOxsPnHKH9bKzowWnXKKXPQ5aL3tsPX3xCT9qcOIdQqhrmPHMgXHIxwBnzg287FXsdwfC7mVnUygiBXwd6czutYF1Aj7mBwxOhPBqByg+pS4+JVh85nw0cAYdzsbOjhScRwk29rboPHXcrSf8iClzK+uyaZaQPQWnZCMI29jbYtMMgN3GziYAZ1eqjb26dtqgOsGe8YLd3T5QZLOxx64j6gycKKD3PpAkCGGfEF33y/eBJBOi8ITg62sTxoEoBmEblLBCtvaBJFE894EkUfz1gSQpqNvQwHC4+kCSKLvQBxLlI9T3IZaX7SKzOUM2dhwKLApOKIDwygge1LksG/UGRNh6+kDAgJZy0Dv8FGVkc7yvDGqEZGCA/uWnIAihPKHyk/8UpSSowkE3lpWCGISqOoisFEQRkZXGWvBIlMOjphSkoE5pwFi4nqKURPGmKR1PUYryEYr2oJqyORg2dpz0KwpOqH5sTel4ilKUjXoDImx9mrJ/QEs56Or//vzl21VrxT9ziceBzUaxibeSjbGDN85Ul9eT2ch23NEDdsBg0xOWffcsQs/WVqK7CvD2x4tP97uq8PNJpRufV3/jh/rV6/pbRtVPeVb/iA8Wn9dvZa/+6PXR4ovq188Xv61f4/jdxYv6n6g3NKvv+GhUfXzY2QDVf7y0Nuk/+eT2b6aj6q9/PoqC+lHLldHpg9sf6zfF19/z0fIbEv315xVQ/Up4U/ofstOfYOkfxObEDFGRQgTCe9nmtHihjU6Gi6Z53f4vFu8s7Wq/1WP6frWe0K/nr0f09g39lU/qsV8ObzVyn9ZXz09u/3b0tW+e/8ebm8nt9/W3LH5XX4Hhaqz1BWS6Ppq/8z19EED1N6u/03zf4rcda1W0clTZDFXMdIN9ZIKutxqqmBGC7WBcrrsMVcwYwUbwplKcGR2l6YvkL8hj87wwY4e4RUOVPtg4VvojbYwN7tON2YygtqC7qvIstruquNGC2oLqqlqfbhw7TjdmRw0KjCGWKBpmPHNgHPIxwIl6E1fV+nTjuOd0YzaFIlLA15HO7F4bWCfgY37A4GwIr/OAClTqClTqClSCFWjO5wPnUpq1KoySbKqv2PuhPuWHCk6pFG/V+oxj+z17wo+YMs2yLp52Ce0uOyUbQdpbtT7j2F1yTvkE4BxL9lbpM47N5eaMF2wtvmP9DH4RT/IguZokKj2fnAcX15P4IgqK5OIqzm5WF5V1f8KxY8Peo7B6qxIaJwpo2slwcFF2M0wgD0RBugLENUCb7HKg7S1BVIWj4st1wzraRHYgSkbY8yWsjO0dL0EUkY6X5TUcj0RJPPa8BCmoW+7IaCRBbnnD1kyUxVvTK59myoT3WBaPUMuHWFC2y8rm9NvYcZyxKDih/sFrIXRM57Jo1PsPQetrefWPZykHvTzNOL44D/MwmMRhej1JwjCfFMH1xeTyOiqu1GUeB9lqzP0qTeNecaU0FTUZGKB/pSkIQqhOqNJ8Rzed6me8P7n9Sf3q0Ns3b39Ydys+qF8eqrcnFu8s
A2: ТЕХНИКО-КОММЕРЧЕСКОЕ ПРЕДЛОЖЕНИЕ (ТКП)
A3: г. Москва, 2-й Нагатинский пр-д, вл. 2, СОШ на 675 мест
A4: Стоимость, указанная в предложении, включает в себя все необходимые затраты на выполнение полного комплекса работс НДС 22%
A5: Номер п/п | B5: Код узла ИСР | C5: Наименование затрат | D5: Комментарий по ИСР | E5: Комментарий подрядчика | F5: Ед. изм. | G5: Коэф.расхода | H5: Общее кол-во | I5: Сумма | J5: 1.1-Ст | K5: 1.2-Ст | L5: 1.3-Ст | M5: 1.4-Ст | N5: 1.5-Ст | O5: 2.1-Ст2 | P5: 2.2-Ст | Q5: 2.3-Ст | R5: 2.4-Ст | S5: 2.5-Ст
A6: 1.1.1.1.1.1 | B6: 6.1.2.4.9 | C6: Монтаж ярусных конструкций для работ на высоте
A7: 1.1.1.1.1.1.1 | B7: 6.1.2.4.9.1.1 | C7: Монтаж, демонтаж, аренда строительных лесов | F7: м2 | G7: 1 | H7: 189.3
A8: 1.1.2.1.1.1 | B8: 6.2.1.8.1 | C8: Внутренние стены и перегородки подземной части
A9: 1.1.2.1.1.1.1 | B9: 6.2.1.8.1.1 | C9: Устройство внутренних стен подземной части
A10: 1.1.2.1.1.1.1.1 | B10: 6.2.1.8.1.1.2.1 | C10: Кладка внутренних стен из блоков ячеистого бетона без устройства перемычек, включая армирование, устройство примыканий | E10: Подвал. Форкамеры - 3 шт. Толщина - 200 мм. | F10: м3 | G10: 1 | H10: 9.22 | I10: =SUM(Таблица1[[#This Row],[1.1-Ст]:[2.5-Ст]]) -> 11.014 | M10: ='1.4-Бл'!D6 -> 11.014
A11: 1.1.2.1.1.1.1.1.1 | C11: Материалы для примыкания / уплотняющий жгут, клей на м3 | F11: комплект | G11: 1 | H11: 9.22
A12: 1.1.2.1.1.1.1.1.2 | C12: Прочие материалы для кладки / из газобетона / 200 мм | F12: комплект | G12: 1 | H12: 9.22
A13: 1.1.2.1.1.1.1.1.3 | C13: Клей по газобетону, д/тонкошовной кладки_ | F13: кг | G13: 25 | H13: 230.5
A14: 1.1.2.1.1.1.1.1.4 | C14: Блок газобетонный D600 625х250х200мм | F14: м3 | G14: 1.05 | H14: 9.681
A15: 1.1.2.1.1.1.2 | B15: 6.2.1.8.1.2 | C15: Устройство внутренних перегородок подземной части
A16: 1.1.2.1.1.1.2.1 | B16: 6.2.1.8.1.2.1.2 | C16: Кладка перегородок из кирпича без устройства перемычек, включая армирование, крепление к стенам, заделку примыканий, зачеканку швов / толщ. 120 мм | E16: Подвал. Толщина стен - 120 мм. Кирпич КР-р-по 250х120х65/1НФ/125/2,0/50/ГОСТ 530-2012 | F16: м2 | G16: 1 | H16: 627.2 | I16: =SUM(Таблица1[[#This Row],[1.1-Ст]:[2.5-Ст]]) -> 496.33125 | L16: ='1.3-Кирп'!D7 -> 496.33125
A17: 1.1.2.1.1.1.2.1.1 | C17: Смесь сухая цементно-песчаная | F17: кг | G17: 44.85 | H17: 28129.92
A18: 1.1.2.1.1.1.2.1.2 | C18: Материалы для примыкания / уплотняющий жгут, клей на м2 | F18: комплект | G18: 1 | H18: 627.2
A19: 1.1.2.1.1.1.2.1.3 | C19: Прочие материалы для кладки / из кирпича / 65 -120мм | F19: комплект | G19: 1 | H19: 627.2
A20: 1.1.2.1.1.1.2.1.4 | C20: Сетка эл/св_ / 50*50*4 | F20: м2 | G20: 0.504 | H20: 316.109
A21: 1.1.2.1.1.1.2.1.5 | C21: Кирпич полнотелый рядовой_ / м-150 | F21: шт | G21: 50.4 | H21: 31610.88
A22: 1.1.2.2 | B22: 6.2.2 | C22: СМР надземной части корпуса (без отделки)
A23: 1.1.2.2.1 | B23: 6.2.2.4 | C23: Внутренние стены и перегородки
A24: 1.1.2.2.1.1 | B24: 6.2.2.4.1 | C24: Устройство стен
A25: 1.1.2.2.1.1.1 | B25: 6.2.2.4.1.2.1 | C25: Кладка внутренних стен из блоков ячеистого бетона без устройства перемычек, включая армирование, устройство примыканий | E25: 1-4 этажи. Толщина - 200 мм. | F25: м3 | G25: 1 | H25: 261.11 | I25: =SUM(Таблица1[[#This Row],[1.1-Ст]:[2.5-Ст]]) -> 204.49 | K25: 123.72 | M25: ='1.4-Бл'!D13 -> 80.77
A26: 1.1.2.2.1.1.1.1 | C26: Материалы для примыкания / уплотняющий жгут, клей на м3 | F26: комплект | G26: 1 | H26: 261.11
A27: 1.1.2.2.1.1.1.2 | C27: Прочие материалы для кладки / из газобетона / 200 мм | F27: комплект | G27: 1 | H27: 261.11
A28: 1.1.2.2.1.1.1.3 | C28: Клей по газобетону, д/тонкошовной кладки_ | F28: кг | G28: 25 | H28: 6527.75
A29: 1.1.2.2.1.1.1.4 | C29: Блок газобетонный D600 625х250х200мм | F29: м3 | G29: 1.05 | H29: 274.166
A30: 1.1.2.2.1.1.2 | B30: 6.2.2.4.1.5.1 | C30: Заделка мест прохождения инженерных коммуникаций кладочным материалом | F30: м3 | G30: 1 | H30: 5
A31: 1.1.2.2.1.1.2.1 | C31: Смесь сухая цементно-песчаная | F31: кг | G31: 456 | H31: 2280
A32: 1.1.2.2.1.1.2.2 | C32: Кирпич Рядовой, полнотелый 250х120х65мм 1НФ М150 F50 класс ср.пл.2 ГОСТ 530-2012 | F32: шт | G32: 395 | H32: 1975
A33: 1.1.2.2.1.2 | B33: 6.2.2.4.2 | C33: Устройство перегородок
A34: 1.1.2.2.1.2.1 | B34: 6.2.2.4.2.1 | C34: Устройство перегородок из кирпича и блоков
A35: 1.1.2.2.1.2.1.1 | B35: 6.2.2.4.2.1.1.2 | C35: Кладка перегородок из кирпича без устройства перемычек, включая армирование, крепление к стенам, заделку примыканий, зачеканку швов / толщ. 120 мм | E35: 1-4 этажи. Толщина стен - 120 мм. Кирпич КР-р-по 250х120х65/1НФ/125/2,0/50/ГОСТ 530-2012 | F35: м2 | G35: 1 | H35: 1964.75 | I35: =SUM(Таблица1[[#This Row],[1.1-Ст]:[2.5-Ст]]) -> 855.51 | J35: 728.15 | L35: ='1.3-Кирп'!D15 -> 127.36
A36: 1.1.2.2.1.2.1.1.1 | C36: Смесь сухая цементно-песчаная | E36: 227.92 | F36: кг | G36: 44.85 | H36: 88119.038
A37: 1.1.2.2.1.2.1.1.2 | C37: Материалы для примыкания / уплотняющий жгут, клей на м2 | F37: комплект | G37: 1 | H37: 1964.75
A38: 1.1.2.2.1.2.1.1.3 | C38: Прочие материалы для кладки / из кирпича / 65 -120мм | F38: комплект | G38: 1 | H38: 1964.75
A39: 1.1.2.2.1.2.1.1.4 | C39: Сетка эл/св_ / 50*50*4 | F39: м2 | G39: 0.504 | H39: 990.234
A40: 1.1.2.2.1.2.1.1.5 | C40: Кирпич полнотелый рядовой_ / м-150 | F40: шт | G40: 50.4 | H40: 99023.4
A41: 1.1.2.2.1.2.2 | B41: 6.2.2.4.2.2 | C41: Устройство перегородок из пазогребневых плит
A42: 1.1.2.2.1.2.2.1 | B42: 6.2.2.4.2.2.1.1 | C42: Устройство перегородок из ПГП без устройства перемычек, включая проклейку углов примыкания армирующей лентой, толщ. до 115 мм | E42: 1-4 этажи. Пазогребневые плиты ПлГН1-667х500х100, полнотелые, плотностью не более 1200 кг/м3 -ГОСТ 6428-2018 | F42: м2 | G42: 1 | H42: 1519
A43: 1.1.2.2.1.2.2.1.1 | C43: Прочий материал для кладки перегородок из ПГП (скоба, шуруп, дюбель, пена, подложка) | F43: комплект | G43: 1 | H43: 1519
A44: 1.1.2.2.1.2.2.1.2 | C44: Плита гипсовая пазогребневая Влагостойкая, полнотелая 667х500х100мм | F44: м2 | G44: 1.02 | H44: 1549.38
A45: 1.1.2.2.1.2.2.1.3 | C45: Материалы для примыкания / мина вата, штукатурная смесь м2 | F45: комплект | G45: 1 | H45: 1519
A46: 1.1.2.2.1.2.2.1.4 | C46: Клей для ПГП_/ | E46: 12.6 | F46: кг | G46: 2 | H46: 3038
A47: 1.1.2.2.1.2.3 | B47: 6.2.2.4.2.4 | C47: Устройство перегородок и зашивка коммуникаций ГКЛ
A48: 1.1.2.2.1.2.3.1 | B48: 6.2.2.4.2.4.2.4 | C48: Облицовка стен по системе Knauf / С-626 / в 2 слоя / А-10, А-27 | E48: Облицовка поэлементной сборки Кнауф С626, профили оцинкованные ПН 100х40, ПС 100х50 с шагом 600 мм; Плиты из каменной ваты ТЕХНОАКУСТИК - 100 мм; КНАУФ-лист Сапфир (ГСП-DFH3IR), t=12,5 мм - 2 слоя; Тип: ЧН-25 | F48: м2 | G48: 1 | H48: 601
A49: 1.1.2.2.1.2.3.1.1 | C49: Прочие материалы для облицовки стен из ГКЛ (лента, шпатлевка, грунтовка, шуруп, дюбель и пр.)_ / 2 слоя ГКЛ / профиль ПН/ПС 75 мм | F49: комплект | G49: 1 | H49: 601
A50: 1.1.2.2.1.2.3.1.2 | C50: Мин. плита Техноакустик | F50: м3 | G50: 0.052 | H50: 31.252
A51: 1.1.2.2.1.2.3.1.3 | C51: Профиль_/направляющий/75*40*0,60/3м | E51: ПН 100х40 | F51: пог. м | G51: 0.86 | H51: 516.86
A52: 1.1.2.2.1.2.3.1.4 | C52: Профиль_ / стоечный / 75*50*0,6 / 2415 | E52: ПС 100х50 | F52: пог. м | G52: 2.1 | H52: 1262.1
A53: 1.1.2.2.1.2.3.1.5 | C53: Лист гипсокартонный_ / ГСП-DF ПЛУК / 12,5 мм | F53: м2 | G53: 2.2 | H53: 1322.2
A54: 1.1.2.2.1.2.3.2 | B54: 6.2.2.4.2.4.2.16 | C54: Облицовка стен по системе Knauf / С-626 / в 2 слоя / А-6, А-9 | E54: Облицовка стен по системе Knauf / С-626 / в 2 слоя ГКЛВ 12,5мм в 2 слоя на каркасе из Knauf-профилей ПС 50х50х3000 и ПН 50х40х3000. Тип: ЗШ-1 | F54: м2 | G54: 1 | H54: 79.1
A55: 1.1.2.2.1.2.3.2.1 | C55: Прочие материалы для облицовки стен из ГКЛ (лента, шпатлевка, грунтовка, шуруп, дюбель и пр.)_ / 2 слоя ГКЛ / профиль ПН/ПС 75 мм | F55: комплект | G55: 1 | H55: 79.1
A56: 1.1.2.2.1.2.3.2.2 | C56: Профиль_/стоечный/50*50*0,60/3м | F56: пог. м | G56: 2.1 | H56: 166.11
A57: 1.1.2.2.1.2.3.2.3 | C57: Профиль_/направляющий/50*40*0,60/3м | F57: пог. м | G57: 0.8 | H57: 63.28
A58: 1.1.2.2.1.2.3.2.4 | C58: Лист гипсокартонный_ / ГСП-DF ПЛУК / 12,5 мм | F58: м2 | G58: 2.2 | H58: 174.02
A59: 1.1.2.2.1.2.3.3 | B59: 6.2.2.4.2.4.2.16 | C59: Облицовка стен по системе Knauf / С-626 / в 2 слоя / А-6, А-9 | E59: Облицовка стен по системе Knauf / С-626 / в 2 слоя ГКЛ 12,5мм в 2 слоя на каркасе из Knauf-профилей ПС 50х50х3000 и ПН 50х40х3000. Тип: ЗШ-2 | F59: м2 | G59: 1 | H59: 369.1
A60: 1.1.2.2.1.2.3.3.1 | C60: Лист гипсокартонный_ / ГСП-А ПЛУК / 12,5 мм | F60: м2 | G60: 2.2 | H60: 812.02
A61: 1.1.2.2.1.2.3.3.2 | C61: Профиль_/стоечный/50*50*0,60/3м | F61: пог. м | G61: 2.1 | H61: 775.11
A62: 1.1.2.2.1.2.3.3.3 | C62: Профиль_/направляющий/50*40*0,60/3м | F62: пог. м | G62: 0.8 | H62: 295.28
A63: 1.1.2.2.1.2.3.3.4 | C63: Прочие материалы для облицовки стен из ГКЛ (лента, шпатлевка, грунтовка, шуруп, дюбель и пр.)_ / 2 слоя ГКЛ / профиль ПН/ПС 75 мм | F63: комплект | G63: 1 | H63: 369.1
A64: 1.1.2.2.1.3 | B64: 6.2.2.4.3 | C64: Устройство перемычек и фахверков
A65: 1.1.2.2.1.3.1 | B65: 6.2.2.4.3.1.1 | C65: Устройство перемычек из арматуры с огрунтовкой и окраской | E65: подвал-0,025т; 1-4 этажи - 0,041т. | F65: т | G65: 1 | H65: 0.025
A66: 1.1.2.2.1.3.1.1 | C66: Прочий материал для перемычек (клей, грунт) / для арматуры | F66: комплект | G66: 1 | H66: 0.025
A67: 1.1.2.2.1.3.1.2 | C67: Арматура | F67: т | G67: 1 | H67: 0.025
A68: 1.1.2.2.1.3.2 | B68: 6.2.2.4.3.2.1 | C68: Устройство перемычек металлических с огрунтовкой и окраской | D68: Перемычки для наружных стен необходимо применять из раздела 6.2.2.5 "Наружные стены" | E68: Подвал. Ф1 - Ф4 | F68: т | G68: 1 | H68: 0.334
A69: 1.1.2.2.1.3.2.1 | C69: Полоса стальная для перемычек | E69: Пластина 50х4 | F69: т | G69: 1.03 | H69: 0.045
A70: 1.1.2.2.1.3.2.2 | C70: Уголок стальной для перемычек | E70: Уголок 50х5-197,53 кг Уголок 63х6-1708,53 кг Уголок 80х7-3160,32 кг Уголок 90х7-516,8 кг Уголок 100х63х6-1656,36 кг Уголок 125х80х8-48,3 кг | F70: т | G70: 1.03 | H70: 0.299
A71: 1.1.2.2.1.3.2.3 | C71: Прочий материал для перемычек (клей, грунт) / для полосы или уголка | F71: комплект | G71: 1 | H71: 0.334
A72: 1.1.2.2.1.3.3 | B72: 6.2.2.4.3.2.1 | C72: Устройство перемычек металлических с огрунтовкой и окраской | D72: Перемычки для наружных стен необходимо применять из раздела 6.2.2.5 "Наружные стены" | E72: Подвал. ПР-1 - ПР-11 | F72: т | G72: 1 | H72: 0.365 | S72: ='2.6-Пер -1'!H29 -> 0.3379252
A73: 1.1.2.2.1.3.3.1 | C73: Прочий материал для перемычек (клей, грунт) / для полосы или уголка | F73: комплект | G73: 1 | H73: 0.365
A74: 1.1.2.2.1.3.3.2 | C74: Уголок стальной для перемычек | F74: т | G74: 1.03 | H74: 0.28
A75: 1.1.2.2.1.3.3.3 | C75: Полоса стальная для перемычек | F75: т | G75: 1.03 | H75: 0.096
A76: 1.1.2.2.1.3.4 | B76: 6.2.2.4.3.2.1 | C76: Устройство перемычек металлических с огрунтовкой и окраской | D76: Перемычки для наружных стен необходимо применять из раздела 6.2.2.5 "Наружные стены" | E76: 1-4 этажи | F76: т | G76: 1 | H76: 2.003 | P76: ='2.2-Пер'!H42 -> 2.4501313
A77: 1.1.2.2.1.3.4.1 | C77: Полоса стальная для перемычек | F77: т | G77: 1.03 | H77: 0.496
A78: 1.1.2.2.1.3.4.2 | C78: Уголок стальной для перемычек | F78: т | G78: 1.03 | H78: 1.569
A79: 1.1.2.2.1.3.4.3 | C79: Прочий материал для перемычек (клей, грунт) / для полосы или уголка | F79: комплект | G79: 1 | H79: 2.003
A80: 1.1.2.2.1.3.5 | B80: 6.2.2.4.3.3.1 | C80: Устройство металлоконструкций фахверков, стоек, рам, балок, опорных конструкций и усилений с учетом крепления, огрунтовки и окрашивания | D80: Фахверки для наружных стен необходимо применять из раздела 6.2.2.5 "Наружные стены" | E80: Ф-1.п-18шт Ф-1-64шт Ф-1.1-1шт Ф-1.2-1шт Ф-1.3-2шт Ф-2.п-4шт Ф-2-21шт Ф-3.п-5шт Ф-3-28шт Ф-3.1-6шт Ф-3.2-1шт Ф-4.п-1шт Ф-4-16шт Ф-4.1-4шт Ф-5-2шт Ф-5.1-2шт Ф-6-36шт Ф-7-96шт Ф-7.1-8шт Ф-7.2-2шт Ф-8-69шт Ф-9-284шт Ф-10-23шт Ф-11-5шт Ф-12-36шт Ф-13-85шт Ф-14-16шт Ф-15-1шт | F80: т | G80: 1 | H80: 7.765 | O80: ='2.1-Ст'!H23 -> 8.14427 | Q80: ='2.3-Ст'!H13 -> 1.13448 | R80: ='2.4-Ст'!H26 -> 2.86178
A81: 1.1.2.2.1.3.5.1 | C81: Металлоконструкции (труба, профиль стальной, прокат квадратный, прокат листовой, уголок, арматура и др.) | F81: т | G81: 1 | H81: 7.765
A82: 1.1.2.2.1.3.5.2 | C82: Анкер_ / размер указать в примечании | E82: Клиновой анкер MKT B 8-10-19/75-35шт. Клиновой анкер MKT BZ plus 10-10-30/90-1670шт. Клиновой анкер MKT BZ plus 12-10-30/105-7566шт. | F82: шт | G82: 1 | H82: 2266
A83: 1.1.2.2.1.3.6 | B83: 6.2.2.4.3.4.1 | C83: Усиление простенков и проемов металлопрокатом | E83: Крепление кирпичных перегородок. | F83: т | G83: 1 | H83: 1.59
A84: 1.1.2.2.1.3.6.1 | C84: Металлоконструкции (уголок, полоса, анкеры, швеллер и пр. с огрунтовкой и окраской) | F84: т | G84: 1 | H84: 1.59
A85: 1.1.2.2.1.3.7 | B85: 6.2.2.4.3.4.1 | C85: Усиление простенков и проемов металлопрокатом | E85: Крепление перегородок из газобетона. | F85: т | G85: 1 | H85: 1.113
A86: 1.1.2.2.1.3.7.1 | C86: Металлоконструкции (уголок, полоса, анкеры, швеллер и пр. с огрунтовкой и окраской) | F86: т | G86: 1 | H86: 1.113
A87: 1.1.2.2.1.3.8 | B87: 6.2.2.4.3.4.1 | C87: Усиление простенков и проемов металлопрокатом | E87: Обрамление конструкций | F87: т | G87: 1 | H87: 0.367
A88: 1.1.2.2.1.3.8.1 | C88: Металлоконструкции (уголок, полоса, анкеры, швеллер и пр. с огрунтовкой и окраской) | F88: т | G88: 1 | H88: 0.367
A89: 1.1.2.2.1.4 | B89: 6.2.2.4.99 | C89: Прочие работы
A90: 1.1.2.2.1.4.1 | B90: 6.2.2.4.99.3.1 | C90: Устройство узлов примыкания ограждающих конструкций и проемов | E90: Применительно: резка четвертей в газоблоке, для совмещения с фахверкими из гнутого швеллера 220х50х4 и пластин 100х150 с шагом 500 мм с 2х сторон. | F90: пог. м | G90: 1 | H90: 58.552
A91: 1.1.2.2.2 | B91: 6.2.2.8 | C91: Кровля
A92: 1.1.2.2.2.1 | B92: 6.2.2.8.99 | C92: Прочие работы
A93: 1.1.2.2.2.1.1 | B93: 6.2.2.8.99.6.1 | C93: Устройство кирпичной кладки на кровле | E93: Кладка вентшахт на кровле. Толщина - 120 мм, Кирпич КР-р-по 250х120х65/1НФ/125/2,0/50/ГОСТ 530-2012 | F93: м3 | G93: 1 | H93: 92.86
A94: 1.1.2.2.2.1.1.1 | C94: Сетка эл/св_ / 50*50*4 | F94: м2 | G94: 4.2 | H94: 390.012
A95: 1.1.2.2.2.1.1.2 | C95: Смесь цементно-песчаная М150 | F95: кг | G95: 445 | H95: 41322.7
A96: 1.1.2.2.2.1.1.3 | C96: Кирпич полнотелый рядовой_ / м-150 | F96: шт | G96: 395 | H96: 36679.7
A97: 1.1.3.1.1.2 | B97: 6.3.1.5.2 | C97: Стены
A98: 1.1.3.1.1.2.1 | B98: 6.3.1.5.2.1 | C98: Черновые работы по поверхности стен
A99: 1.1.3.1.1.2.1.1 | B99: 6.3.1.5.2.1.1.1 | C99: Оклейка швов сопряжения бетонных и других поверхностей стен, перегородок (газобетон, ПГП, панели АКОТЕК и др.) стеклохолстом | E99: Перед штукатуркой проклеить швы сопряжения разнородных поверхностей (бетон, газобетонный блок, кирпич, ПГП) и углы сеткой стеклотканой, ширина полос проклейки 150+150=300 мм, что составляет 20% от всей площади оштукатуриваемой поверхности. | F99: пог. м | G99: 1 | I99: 2181.16
A100: 1.1.3.1.1.2.1.1.1 | C100: Штукатурка гипсовая_ / Унифицированная по ПИК-СТАНДАРТ, 30кг | E100: т.к. ширина арм.ленты 300 мм (150+150) объем штукатурки =2181,16*2*0,01=436,232 кг. | F100: кг | G100: 0.1 | I100: 436.232
...

Sheet 3.2Шт3в
A1: № п.п | B1: Наименование | C1: Описание | D1: Ед. изм. | E1: Объем:
A2: 1 | B2: Оклейка швов сопряжения бетонных и других поверхностей стен, перегородок (газобетон, ПГП, панели АКОТЕК и др.) стеклохолстом | C2: Перед штукатуркой проклеить швы сопряжения разнородных поверхностей (бетон, газобетонный блок, кирпич, ПГП) и углы сеткой стеклотканой, ширина полос проклейки 150+150=300 мм, что составляет 20% от всей площади оштукатуриваемой поверхности. | D2: пог. м | E2: =SUM(E3:E9)/7.61406957765593 -> 439.09502
A3: 2 | B3: Штукатурка стен цементным, цементно-песчаным раствором с предварительной огрунтовкой / толщ. от 21 до 40 мм / высотой до 4 метров | C3: Штукатурка по ж/б. Тип: ЧН-1, ЧН-7, ЧН-10 | D3: м2 | E3: 166.4
A4: 3 | B4: Штукатурка стен цементным, цементно-песчаным раствором с предварительной огрунтовкой / толщ. от 21 до 40 мм / высотой до 4 метров | C4: Штукатурка по блоку и кирпичу. Тип: ЧН-4, ЧН-12, ЧН-13, ЧН-15, ЧН-16, ЧН-20, ЧН-21, ЧН-23 | D4: м2 | E4: 1095.4
A5: 4 | B5: Штукатурка стен гипсовыми смесями с предварительной огрунтовкой СКБ / толщ. от 21 до 40 мм / высотой от 4,01 до 8 метров | C5: Штукатурка гипсовая по блоку. Тип: ЧН-6, ЧН-11 | D5: м2 | E5: 1579
A6: 5 | B6: Штукатурка стен гипсовыми смесями с предварительной огрунтовкой СКБ / толщ. от 21 до 40 мм / высотой от 4,01 до 8 метров | C6: Штукатурка гипсовая по ж/б. Тип: ЧН-5 | D6: м2 | E6: 348.5
A7: 6 | B7: Штукатурка стен гипсовыми смесями с предварительной огрунтовкой СКБ / до 20 мм / высотой от 4,01 до 8 метров | C7: Штукатурка гипсовая по ПГП. Тип: ЧН-8 | D7: м2 | E7: 26.3
A8: 7 | B8: Штукатурка стен цементным, цементно-песчаным раствором с предварительной огрунтовкой / толщ. до 20 мм / высотой до 4 метров | C8: Штукатурка по ПГП под облицовку плиткой смесью Knauff-флизен 10 мм с грунтовкой Knauff-тиффенгрунд. Тип: ЧН-2, ЧН-9 | D8: м2 | E8: 107.2
A9: 8 | B9: Штукатурка внутренних стен по утеплителю по стеклотканевой сетке / толщ. до 10мм | C9: Тамбуры. Штукатурка штукатурно-клеевой смесью Технониколь-210 (или аналог КАВЕРПЛИКС TC117) по утеплителю и сетке стеклотканевой усиленной щелочестойкой - 10мм; Тип: ЧН-18, ЧН-19 | D9: м2 | E9: 20.5
D10: Сумма | E10: =SUM(E3:E9) -> 3343.3

Sheet 3.2.1Шт
A1: Этаж | B1: Секция | C1: № помеще ния | D1: Марка | E1: Площадь | F1: Примечание
A2: 1 | B2: 2 | C2: 1025 | D2: ЧН-6 | E2: 269.8 | F2: Отделка перегородок и стен из газобетона
A3: 1 | B3: 2 | C3: 1025 | D3: ЧН-14 | E3: 16.4 | F3: Отделка перегородок ГКЛ
A4: 1 | B4: 2 | C4: 1025 | D4: ЧН-5 | E4: 79.5 | F4: Отделка стен из железобетона
A5: 1 | B5: 2 | C5: 1036 | D5: ЧН-11 | E5: 39.8 | F5: Отделка перегородок и стен из кирпича
A6: 1 | B6: 2 | C6: 1036 | D6: ЧН-6 | E6: 24.4 | F6: Отделка перегородок и стен из газобетона
A7: 1 | B7: 2 | C7: 1036 | D7: ЧН-14 | E7: 9.5 | F7: Отделка перегородок ГКЛ
A8: 1 | B8: 2 | C8: 1036 | D8: ЧН-5 | E8: 0.8 | F8: Отделка стен из железобетона
A9: 1 | B9: 2 | C9: 1038 | D9: ЧН-11 | E9: 47.1 | F9: Отделка перегородок и стен из кирпича
A10: 1 | B10: 2 | C10: 1038 | D10: ЧН-6 | E10: 81.8 | F10: Отделка перегородок и стен из газобетона
A11: 1 | B11: 2 | C11: 1038 | D11: ЧН-14 | E11: 1.9 | F11: Отделка перегородок ГКЛ
A12: 1 | B12: 2 | C12: 1038 | D12: ЧН-5 | E12: 11.8 | F12: Отделка стен из железобетона
A13: 1 | B13: 2 | C13: 1043 | D13: ЧН-12 | E13: 83 | F13: Отделка перегородок и стен из кирпича
... A102: 1 | B102: 3 | C102: 1098 | D102: ЧН-18 | E102: 20.5 | F102: Отделка перегородок ГКЛ
A103: 1 | B103: 3 | C103: 1.094а | D103: ЧН-11 | E103: 10.8 | F103: Отделка перегородок и стен из кирпича
A104: 1 | B104: 3 | C104: 1.094а | D104: ЧН-6 | E104: 88.1 | F104: Отделка перегородок и стен из газобетона
A105: 1 | B105: 3 | C105: 1.094а | D105: ЧН-14 | E105: 8.3 | F105: Отделка перегородок ГКЛ
A106: 1 | B106: 3 | C106: 1.094а | D106: ЧН-5 | E106: 48.3 | F106: Отделка стен из железобетона
A107: 1 | B107: 3 | C107: 1094 | D107: ЧН-11 | E107: 39.5 | F107: Отделка перегородок и стен из кирпича
A108: 1 | B108: 3 | C108: 1094 | D108: ЧН-6 | E108: 220.4 | F108: Отделка перегородок и стен из газобетона
A109: 1 | B109: 3 | C109: 1094 | D109: ЧН-14 | E109: 9.3 | F109: Отделка перегородок ГКЛ
A110: 1 | B110: 3 | C110: 1094 | D110: ЧН-5 | E110: 52.3 | F110: Отделка стен из железобетона
A111: 1 | B111: 3 | C111: 1084 | D111: ЧН-11 | E111: 8 | F111: Отделка перегородок и стен из кирпича
A112: 1 | B112: 3 | C112: 1084 | D112: ЧН-6 | E112: 83.4 | F112: Отделка перегородок и стен из газобетона
A113: 1 | B113: 3 | C113: 1084 | D113: ЧН-14 | E113: 3.5 | F113: Отделка перегородок ГКЛ
A114: 1 | B114: 3 | C114: 1084 | D114: ЧН-5 | E114: 5.7 | F114: Отделка стен из железобетона
A115: 1 | B115: 3 | C115: 1084 | D115: ЧН-8 | E115: 5.2 | F115: Отделка перегородок ПГП
A116: 1 | B116: 3 | C116: 1085 | D116: ЧН-11 | E116: 8 | F116: Отделка перегородок и стен из кирпича
A117: 1 | B117: 3 | C117: 1085 | D117: ЧН-6 | E117: 86.1 | F117: Отделка перегородок и стен из газобетона
A118: 1 | B118: 3 | C118: 1085 | D118: ЧН-14 | E118: 3.7 | F118: Отделка перегородок ГКЛ
... A125: 2 | B125: 3 | C125: 2044 | D125: ЧН-5 | E125: 27.5 | F125: Отделка стен из железобетона
D127: ЧН-7 | E127: =SUMIF($D$120:$D$125,D127,$E$120:$E$125) -> 97.9
D128: ЧН-10 | E128: =SUMIF($D$120:$D$125,D128,$E$120:$E$125) -> 0
E129: =SUMIF($D$120:$D$125,D129,$E$120:$E$125) -> 0
D130: ЧН-4 | E130: =SUMIF($D$120:$D$125,D130,$E$120:$E$125) -> 0
D131: ЧН-12 | E131: =SUMIF($D$120:$D$125,D131,$E$120:$E$125) -> 0 | H131: =E123+E121 -> 97.9
D132: ЧН-13 | E132: =SUMIF($D$120:$D$125,D132,$E$120:$E$125) -> 0
D133: ЧН-15 | E133: =SUMIF($D$120:$D$125,D133,$E$120:$E$125) -> 0 | F133: ЧН-1, ЧН-7, ЧН-10
D134: ЧН-20 | E134: =SUMIF($D$120:$D$125,D134,$E$120:$E$125) -> 0
D135: ЧН-21 | E135: =SUMIF($D$120:$D$125,D135,$E$120:$E$125) -> 0 | F135: ЧН-4, ЧН-12, ЧН-13, ЧН-15, ЧН-16, ЧН-20, ЧН-21, ЧН-23
D136: ЧН-23 | E136: =SUMIF($D$120:$D$125,D136,$E$120:$E$125) -> 0
E137: =SUMIF($D$120:$D$125,D137,$E$120:$E$125) -> 0
D138: ЧН-6 | E138: =SUMIF($D$120:$D$125,D138,$E$120:$E$125) -> 26.5
D139: ЧН-11 | E139: =SUMIF($D$120:$D$125,D139,$E$120:$E$125) -> 0
E140: =SUMIF($D$120:$D$125,D140,$E$120:$E$125) -> 0
E141: =SUMIF($D$120:$D$125,D141,$E$120:$E$125) -> 0
D142: ЧН-5 | E142: =SUMIF($D$120:$D$125,D142,$E$120:$E$125) -> 27.5
E143: =SUMIF($D$120:$D$125,D143,$E$120:$E$125) -> 0
D144: ЧН-2 | E144: =SUMIF($D$120:$D$125,D144,$E$120:$E$125) -> 0
D145: ЧН-9 | E145: =SUMIF($D$120:$D$125,D145,$E$120:$E$125) -> 0
E146: =SUMIF($D$120:$D$125,D146,$E$120:$E$125) -> 0
D147: ЧН-8 | E147: =SUMIF($D$120:$D$125,D147,$E$120:$E$125) -> 0
E148: =SUMIF($D$120:$D$125,D148,$E$120:$E$125) -> 0
E149: =SUMIF($D$120:$D$125,D149,$E$120:$E$125) -> 0
D150: ЧН-14 | E150: =SUMIF($D$120:$D$125,D150,$E$120:$E$125) -> 4.4
E151: =SUMIF($D$120:$D$125,D151,$E$120:$E$125) -> 0
D152: ЧН-17 | E152: =SUMIF($D$120:$D$125,D152,$E$120:$E$125) -> 0
D153: ЧН-18 | E153: =SUMIF($D$120:$D$125,D153,$E$120:$E$125) -> 0
A155: 1 | B155: 2 | C155: 1025 | D155: ЧН-6 | E155: 269.8
A156: 1 | B156: 2 | C156: 1025 | D156: ЧН-14 | E156: 16.4
A157: 1 | B157: 2 | C157: 1025 | D157: ЧН-5 | E157: 79.5
A158: 1 | B158: 2 | C158: 1036 | D158: ЧН-11 | E158: 39.8
A159: 1 | B159: 2 | C159: 1036 | D159: ЧН-6 | E159: 24.4
A160: 1 | B160: 2 | C160: 1036 | D160: ЧН-14 | E160: 9.5
A161: 1 | B161: 2 | C161: 1036 | D161: ЧН-5 | E161: 0.8
A162: 1 | B162: 2 | C162: 1038 | D162: ЧН-11 | E162: 47.1
A163: 1 | B163: 2 | C163: 1038 | D163: ЧН-6 | E163: 81.8
A164: 1 | B164: 2 | C164: 1038 | D164: ЧН-14 | E164: 1.9
A165: 1 | B165: 2 | C165: 1038 | D165: ЧН-5 | E165: 11.8
A166: 1 | B166: 2 | C166: 1043 | D166: ЧН-12 | E166: 83
... A199: 1 | B199: 2 | C199: 1069 | D199: ЧН-6 | E199: 22.5
D201: ЧН-7 | E201: =SUMIF($D$155:$D$199,D201,$E$155:$E$199) -> 0
D202: ЧН-10 | E202: =SUMIF($D$155:$D$199,D202,$E$155:$E$199) -> 41
E203: =SUMIF($D$155:$D$199,D203,$E$155:$E$199) -> 0
D204: ЧН-4 | E204: =SUMIF($D$155:$D$199,D204,$E$155:$E$199) -> 0
D205: ЧН-12 | E205: =SUMIF($D$155:$D$199,D205,$E$155:$E$199) -> 624.6
D206: ЧН-13 | E206: =SUMIF($D$155:$D$199,D206,$E$155:$E$199) -> 91.6
D207: ЧН-15 | E207: =SUMIF($D$155:$D$199,D207,$E$155:$E$199) -> 0
D208: ЧН-20 | E208: =SUMIF($D$155:$D$199,D208,$E$155:$E$199) -> 0
D209: ЧН-21 | E209: =SUMIF($D$155:$D$199,D209,$E$155:$E$199) -> 0
D210: ЧН-23 | E210: =SUMIF($D$155:$D$199,D210,$E$155:$E$199) -> 0
E211: =SUM(E205:E206) -> 716.2
D212: ЧН-6 | E212: =SUMIF($D$155:$D$199,D212,$E$155:$E$199) -> 398.5
D213: ЧН-11 | E213: =SUMIF($D$155:$D$199,D213,$E$155:$E$199) -> 86.9
E214: =SUM(E212:E213) -> 485.4
E215: =SUMIF($D$155:$D$199,D215,$E$155:$E$199) -> 0
D216: ЧН-5 | E216: =SUMIF($D$155:$D$199,D216,$E$155:$E$199) -> 92.1
E217: =SUMIF($D$155:$D$199,D217,$E$155:$E$199) -> 0
D218: ЧН-2 | E218: =SUMIF($D$155:$D$199,D218,$E$155:$E$199) -> 0
D219: ЧН-9 | E219: =SUMIF($D$155:$D$199,D219,$E$155:$E$199) -> 33.9
E220: =SUMIF($D$155:$D$199,D220,$E$155:$E$199) -> 0
D221: ЧН-8 | E221: =SUMIF($D$155:$D$199,D221,$E$155:$E$199) -> 0
E222: =SUMIF($D$155:$D$199,D222,$E$155:$E$199) -> 0
E223: =SUMIF($D$155:$D$199,D223,$E$155:$E$199) -> 0
D224: ЧН-14 | E224: =SUMIF($D$155:$D$199,D224,$E$155:$E$199) -> 27.8
E225: =SUMIF($D$155:$D$199,D225,$E$155:$E$199) -> 0
D226: ЧН-17 | E226: =SUMIF($D$155:$D$199,D226,$E$155:$E$199) -> 11.9
D227: ЧН-18 | E227: =SUMIF($D$155:$D$199,D227,$E$155:$E$199) -> 0
C229: 1048 | D229: ЧН-12 | E229: 68.1
C230: 1048 | D230: ЧН-13 | E230: 22.4
...

Sheet 1.9КирпКровля3вып
A1: Устройство кирпичной кладки на кровле
A2: Описание: Кладка вентшахт на кровле. Толщина - 120 мм, Кирпич КР-р-по 250х120х65
A3: Номер п/п | B3: Описание | C3: Ед. изм. | D3: Общее кол-во
A4: 1 | B4: ВШ-51 | C4: м3 | D4: =1.17*1.895-0.36*2*0.225 -> 2.05515
A5: 2 | B5: ВШ-43 | C5: м3 | D5: =1.04*1.82-0.328*2*0.225 -> 1.7452
A6: 3 | B6: ВШ-42 | C6: м3 | D6: =0.2496*1.6-0.3*0.4*0.12 -> 0.38496
A7: 4 | B7: ВШ-41 | C7: м3 | D7: =1.95*2.4+0.53*0.9-0.3*0.3*0.25*8 -> 4.977
A8: 5 | B8: ВШ-40 | C8: м3 | D8: =1.575*1.435 -> 2.260125
A9: 6 | B9: ВШ-35 | C9: м3 | D9: =1.125*0.442 -> 0.49725
A10: 7 | B10: Люк на кровлю, лестница Л-1 | C10: м3 | D10: =1.85*0.675 -> 1.24875
A11: Сумма: | B11: Кровля. 3 секция. | C11: м3 | D11: =SUM(D4:D10) -> 13.168435

Sheet 1.8КирпПодвал3вып
A1: Кладка перегородок из кирпича без устройства перемычек, включая армирование, крепление к стенам, заделку примыканий, зачеканку швов / толщ. 120 мм (Толщина стен - 120 мм.)
A2: Описание: Подвал
A3: Номер п/п | B3: Описание | C3: Ед. изм. | D3: Общее кол-во
A4: 1 | B4: Подвал. 1 секция. | C4: м2 | D4: =2.5*3.15 -> 7.875
A5: 2 | B5: Подвал. 2 секция. | C5: м2 | D5: =6.3 * 3.15 -> 19.845
A6: 3 | B6: Подвал. 3 секция. | C6: м2 | D6: =6 * 3.15 -> 18.9
B7: Итог: | C7: м2 | D7: =SUM(D4:D6) -> 46.62

Sheet 1.7Кирп3вып
A1: Кладка перегородок из кирпича без устройства перемычек, включая армирование, крепление к стенам, заделку примыканий, зачеканку швов / толщ. 120 мм (Толщина стен - 120 мм.)
A2: Номер п/п | B2: Описание | C2: Ед. изм. | D2: Общее кол-во
A3: 1 | B3: 1 этаж. 1 секция. | C3: м2 | D3: =((((0.79*3)+3.7)*4)*2- 0.65*1.86*5) -> 42.515
A4: 2 | B4: 2 этаж. 1 секция. | C4: м2 | D4: =((((0.79*3)+3.7)*4)*2- 0.65*1.87*5) -> 42.4825
A5: 3 | B5: 3 этаж. 1 секция. | C5: м2 | D5: =(3.7+0.85+0.85+0.75)*4 * 0 + (0.79+0.79+0.79+3.7)*4 - 0.65*1.86*3 -> 20.653
A6: 4 | B6: 1 этаж. 2 секция. | C6: м2 | D6: =(1.7+4.23+2.4)*4-1.1*2.1 -> 31.01
A7: 5 | B7: 3 этаж. 2 секция. | C7: м2 | D7: =(1.98+9.15)*4-1*2.1*2 -> 40.32
A8: 6 | B8: 1 этаж. 3 секция. | C8: м2 | D8: =(3.2+4.2)*4+2.7*2 -> 35
A9: 7 | B9: 2 этаж. 3 секция. | C9: м2 | D9: =(4.165+4.96+8.7+1.42+1.9+2.22+0.455+5.4+3.6+6.15+5.6+0.48)*4-1.2*2.1*4 -> 170.12
B10: Итог: | C10: м2 | D10: =SUM(D3:D9) -> 382.1005

Sheet 1.6Блок3вып
A1: Кладка внутренних стен из блоков ячеистого бетона без устройства перемычек, включая армирование, устройство примыканий. (Толщина - 200 мм.)
A2: Номер п/п | B2: Описание | C2: Ед. изм. | D2: Общее кол-во
A3: 1 | B3: 1 этаж. 2 секция. | C3: м3 | D3: =2.51*4-0.688*3+(0.79-0.56)*4+0.806*4+1.654*4-0.25*2*4 -> 16.736
A4: 2 | B4: 1 этаж. 3 секция. | C4: м3 | D4: =1.44*4+0.215*4+3.593*4-0.22*2 -> 20.552
A5: 3 | B5: 2 этаж. 3 секция. | C5: м3 | D5: =0.951*4-0.3*2.2 -> 3.144
A6: 4 | B6: 3 этаж. 2 секция. | C6: м3 | D6: =4.832*4-0.5*2.3-0.28*2.1*2 -> 17.002
A7: 5 | B7: 3 этаж. 3 секция. | C7: м3 | D7: =5.693*4-0.3*2.3*2-0.22*2*2 -> 20.512
B8: Итог: | C8: м3 | D8: =SUM(D3:D7) -> 77.946

Sheet 1.5-ПГП 3 вып
A1: Устройство перегородок из ПГП без устройства перемычек, включая проклейку углов примыкания армирующей лентой, толщ. до 115 мм
A2: Номер п/п | B2: Описание | C2: Ед. изм. | D2: Общее кол-во
A3: 1 | B3: 1 этаж. 3 секция. | C3: м2 | D3: =(2.505*2+2.225*2+1.86) * 4 -> 45.28
B4: Итог: | C4: м2 | D4: =SUM(D3:D3) -> 45.28

Sheet 2.7-Фар 3 вып
A1: Устройство металлоконструкций фахверков, стоек, рам, балок, опорных конструкций и усилений с учетом крепления, огрунтовки и окрашивания
A2: Номер п/п | B2: Этаж | C2: Секция | D2: Тип | E2: шт. | F2: кг/1шт | G2: Ед. изм. | H2: Общее кол-во
B3: 1 | C3: 2 | D3: Ф-1 | E3: 7 | F3: =35.8+2+3.1 -> 40.9 | G3: т | H3: =E3*F3/1000 -> 0.2863
B4: 1 | C4: 2 | D4: Ф-2 | E4: 3 | F4: =35.8+3.1+2.15 -> 41.05 | G4: т | H4: =E4*F4/1000 -> 0.12315
B6: 1 | C6: 3 | D6: Ф-1 | E6: 4 | F6: =35.8+2+3.1 -> 40.9 | G6: т | H6: =E6*F6/1000 -> 0.1636
B7: 1 | C7: 3 | D7: Ф-2 | E7: 2 | F7: =35.8+3.1+2.15 -> 41.05 | G7: т | H7: =E7*F7/1000 -> 0.0821
B8: 1 | C8: 3 | D8: Ф-5 | E8: 1 | F8: =32.9+1.4+0.48 -> 34.78 | G8: т | H8: =E8*F8/1000 -> 0.03478
B10: 2 | C10: 3 | D10: Ф-14 | E10: 4 | F10: =29.99+2.1+1.05 -> 33.14 | G10: т | H10: =E10*F10/1000 -> 0.13256
B12: 3 | C12: 2 | D12: Ф-12 | E12: 2 | F12: =35.4+1.7+3.1 -> 40.2 | G12: т | H12: =E12*F12/1000 -> 0.0804
B13: 3 | C13: 2 | D13: Ф-13 | E13: 7 | F13: =35.4+2.15+3.1 -> 40.65 | G13: т | H13: =E13*F13/1000 -> 0.28455
E14: =SUM(E3:E13) -> 30 | F14: Итог: | G14: т | H14: =SUM(H3:H13) -> 1.18744

Sheet 2.6-Пер 3 вып
A1: Устройство перемычек металлических с огрунтовкой и окраской. 1-4 этажи.
A2: Номер п/п | B2: Этаж | C2: Секция | D2: Тип | E2: шт. | F2: кг/1шт | G2: Ед. изм. | H2: Общее кол-во
A3: 1 | B3: 1 | C3: 1 | D3: ПР-К3 | E3: 6 | F3: =VLOOKUP(D3,'2.2-Пер2'!$A$2:$C$13,3) -> 8.81 | G3: т | H3: =E3*F3/1000 -> 0.05286
A5: 2 | B5: 1 | C5: 2 | D5: ПР-Г2 | E5: 3 | F5: =VLOOKUP(D5,'2.2-Пер2'!$A$2:$C$13,3) -> 22.4 | G5: т | H5: =E5*F5/1000 -> 0.0672
A6: 3 | B6: 1 | C6: 2 | D6: ПР-Г4 | E6: 2 | F6: =VLOOKUP(D6,'2.2-Пер2'!$A$2:$C$13,3) -> 21.307692 | G6: т | H6: =E6*F6/1000 -> 0.042615385
A7: 4 | B7: 1 | C7: 2 | D7: ПР-Г5 | E7: 2 | F7: =VLOOKUP(D7,'2.2-Пер2'!$A$2:$C$13,3) -> 56.63 | G7: т | H7: =E7*F7/1000 -> 0.11326
A8: 5 | B8: 1 | C8: 2 | D8: ПР-Г6 | E8: 1 | F8: =VLOOKUP(D8,'2.2-Пер2'!$A$2:$C$13,3) -> 18.69 | G8: т | H8: =E8*F8/1000 -> 0.01869
A10: 6 | B10: 1 | C10: 3 | D10: ПР-К1 | E10: 1 | F10: =VLOOKUP(D10,'2.2-Пер2'!$A$2:$C$13,3) -> 12.170909 | G10: т | H10: =E10*F10/1000 -> 0.012170909
A11: 7 | B11: 1 | C11: 3 | D11: ПР-Г4 | E11: 1 | F11: =VLOOKUP(D11,'2.2-Пер2'!$A$2:$C$13,3) -> 21.307692 | G11: т | H11: =E11*F11/1000 -> 0.021307692
A12: 8 | B12: 2 | C12: 1 | D12: ПР-К3 | E12: 6 | F12: =VLOOKUP(D12,'2.2-Пер2'!$A$2:$C$13,3) -> 8.81 | G12: т | H12: =E12*F12/1000 -> 0.05286
A14: 9 | B14: 2 | C14: 3 | D14: ПР-К2 | E14: 3 | F14: =VLOOKUP(D14,'2.2-Пер2'!$A$2:$C$13,3) -> 6.93 | G14: т | H14: =E14*F14/1000 -> 0.02079
A15: 10 | B15: 2 | C15: 3 | D15: ПР-К3 | E15: 1 | F15: =VLOOKUP(D15,'2.2-Пер2'!$A$2:$C$13,3) -> 8.81 | G15: т | H15: =E15*F15/1000 -> 0.00881
A16: 11 | B16: 2 | C16: 3 | D16: ПР-К9 | E16: 2 | F16: =VLOOKUP(D16,'2.2-Пер2'!$A$2:$C$13,3) -> 5.85 | G16: т | H16: =E16*F16/1000 -> 0.0117
A18: 12 | B18: 3 | C18: 1 | D18: ПР-К3 | E18: 3 | F18: =VLOOKUP(D18,'2.2-Пер2'!$A$2:$C$13,3) -> 8.81 | G18: т | H18: =E18*F18/1000 -> 0.02643
... A22: 15 | B22: 3 | C22: 2 | D22: ПР-Г2 | E22: 1 | F22: =VLOOKUP(D22,'2.2-Пер2'!$A$2:$C$13,3) -> 22.4 | G22: т | H22: =E22*F22/1000 -> 0.0224
A23: 16 | B23: 3 | C23: 2 | D23: ПР-Г7 | E23: 1 | F23: 21.47 | G23: т | H23: =E23*F23/1000 -> 0.02147
A24: 17 | B24: 3 | C24: 3 | D24: ПР-Г6 | E24: 2 | F24: =VLOOKUP(D24,'2.2-Пер2'!$A$2:$C$13,3) -> 18.69 | G24: т | H24: =E24*F24/1000 -> 0.03738
E25: =SUM(E3:E24) -> 39 | F25: Итог: | G25: т | H25: =SUM(H3:H24) -> 0.64124399
A27: Содержимое | B27: Количество | C27: кг/шт | D27: Итог, кг:
A28: ПР-Г1 | B28: =SUMIF($D$3:$D$24,A28,$E$3:$E$24) -> 2 | C28: 46.84 | D28: =B28*C28 -> 93.68
A29: ПР-Г2 | B29: =SUMIF($D$3:$D$24,A29,$E$3:$E$24) -> 4 | C29: 22.4 | D29: =B29*C29 -> 89.6
A30: ПР-Г4 | B30: =SUMIF($D$3:$D$24,A30,$E$3:$E$24) -> 3 | C30: 21.307692 | D30: =B30*C30 -> 63.923077
A31: ПР-Г5 | B31: =SUMIF($D$3:$D$24,A31,$E$3:$E$24) -> 2 | C31: 56.63 | D31: =B31*C31 -> 113.26
A32: ПР-Г6 | B32: =SUMIF($D$3:$D$24,A32,$E$3:$E$24) -> 3 | C32: 18.69 | D32: =B32*C32 -> 56.07
A33: ПР-Г7 | B33: =SUMIF($D$3:$D$24,A33,$E$3:$E$24) -> 1 | C33: =18.69+1.7*2-0.31*2 -> 21.47 | D33: =B33*C33 -> 21.47
A34: ПР-К1 | B34: =SUMIF($D$3:$D$24,A34,$E$3:$E$24) -> 1 | C34: 12.170909 | D34: =B34*C34 -> 12.170909
A35: ПР-К2 | B35: =SUMIF($D$3:$D$24,A35,$E$3:$E$24) -> 3 | C35: 6.93 | D35: =B35*C35 -> 20.79
A36: ПР-К3 | B36: =SUMIF($D$3:$D$24,A36,$E$3:$E$24) -> 18 | C36: 8.81 | D36: =B36*C36 -> 158.58
A37: ПР-К9 | B37: =SUMIF($D$3:$D$24,A37,$E$3:$E$24) -> 2 | C37: 5.85 | D37: =B37*C37 -> 11.7
B38: =SUM(B28:B37) -> 39 | C38: Сумма, кг: | D38: =SUM(D28:D37) -> 641.24399

Sheet 1.1-Ст
A1: Кладка перегородок из кирпича без устройства перемычек, включая армирование, крепление к стенам, заделку примыканий, зачеканку швов / толщ. 120 мм (Толщина стен - 120 мм.)
A2: Номер п/п | B2: Описание | C2: Ед. изм. | D2: Общее кол-во
A3: 1 | B3: 1 этаж. 1 секция. | C3: м2 | D3: 128.9
A4: 2 | B4: 1 этаж. 2, 3 секция. | C4: м2 | D4: 571.25
A5: 3 | B5: 4 этаж. 3 секция. | C5: м2 | D5: 28
B6: Итог: | C6: м2 | D6: =SUM(D3:D5) -> 728.15

Sheet 1.2-Ст
A1: Кладка внутренних стен из блоков ячеистого бетона без устройства перемычек, включая армирование, устройство примыканий. (Толщина - 200 мм.)
A2: Номер п/п | B2: Описание | C2: Ед. изм. | D2: Общее кол-во
A3: 1 | B3: 1 этаж. 1 секция. | C3: м3 | D3: 33.86
A4: 2 | B4: 2 этаж. 1 секция. | C4: м3 | D4: 26.36
A5: 3 | B5: 3 этаж. 1 секция. | C5: м3 | D5: 25.2
A6: 4 | B6: 4 этаж. 3 секция. | C6: м3 | D6: 38.3
B7: Итог: | C7: м3 | D7: =SUM(D3:D6) -> 123.72

Sheet 1.3-Кирп
A1: Кладка перегородок из кирпича без устройства перемычек, включая армирование, крепление к стенам, заделку примыканий, зачеканку швов / толщ. 120 мм (Толщина стен - 120 мм.)
A2: Подвал
A3: Номер п/п | B3: Описание | C3: Ед. изм. | D3: Общее кол-во
A4: 1 | B4: Подвал. 1 секция. | C4: м2 | D4: =31.275*3.15 - 4 -> 94.51625
A5: 1 | B5: Подвал. 2 секция. | C5: м2 | D5: =64.3 * 3.15 -4 -> 198.545
A6: 2 | B6: Подвал. 3 секция. | C6: м2 | D6: =65.8 * 3.15 -4 -> 203.27
B7: Итог: | C7: м2 | D7: =SUM(D4:D6) -> 496.33125
A9: 1-3 этаж
A10: Номер п/п | B10: Описание | C10: Ед. изм. | D10: Общее кол-во
A11: 1 | B11: 1 этаж. 3 секция. | C11: м2 | D11: =3.55*4 -> 14.2
A12: 2 | B12: 2 этаж. 1 секция. | C12: м2 | D12: =(3.75+3.58)*4-2 -> 27.32
A13: 3 | B13: 3 этаж. 1 секция. | C13: м2 | D13: =(3.58+3.75+4.45+3.58)*4-4 -> 57.44
A14: 4 | B14: 3 этаж. 3 секция. | C14: м2 | D14: =3.55*2*4 -> 28.4
B15: Итог: | C15: м2 | D15: =SUM(D11:D14) -> 127.36

Sheet 1.4-Бл
A1: Кладка внутренних стен из блоков ячеистого бетона без устройства перемычек, включая армирование, устройство примыканий. (Толщина - 200 мм.)
A2: Номер п/п | B2: Описание | C2: Ед. изм. | D2: Общее кол-во
A3: 1 | B3: Подвал. 1 секция. | C3: м3 | D3: =3.96-0.2*1.15*0.4 -> 3.868
A4: 2 | B4: Подвал. 2 секция. | C4: м3 | D4: =2.83-0.2*1.15*0.4 -> 2.738
A5: 2 | B5: Подвал. 3 секция. | C5: м3 | D5: =4.5-0.2*1.15*0.4 -> 4.408
B6: Итог: | C6: м3 | D6: =SUM(D3:D5) -> 11.014
A8: 1-3 этаж
A9: 2 | B9: 1 этаж. 1 секция. | C9: м3 | D9: 8.45
A10: 1 | B10: 1 этаж. 3 секция. | C10: м3 | D10: 8.18
A11: 2 | B11: 2 этаж. 3 секция. | C11: м3 | D11: 18.24
A12: 3 | B12: 3 этаж. 3 секция. | C12: м3 | D12: 45.9
B13: Итог: | C13: м3 | D13: =SUM(D9:D12) -> 80.77

Sheet 2.1-Ст
A1: Устройство металлоконструкций фахверков, стоек, рам, балок, опорных конструкций и усилений с учетом крепления, огрунтовки и окрашивания
A2: Номер п/п | B2: Этаж | C2: Секция | D2: Тип | E2: шт. | F2: кг/1шт | G2: Ед. изм. | H2: Общее кол-во
A3: 1 | B3: 1 | C3: 1 | D3: Ф-1 | E3: 19 | F3: =35.8+2+3.1 -> 40.9 | G3: т | H3: =E3*F3/1000 -> 0.7771
A4: 2 | B4: 1 | C4: 1 | D4: Ф-2 | E4: 4 | F4: =35.8+3.1+2.15 -> 41.05 | G4: т | H4: =E4*F4/1000 -> 0.1642
A5: 3 | B5: 1 | C5: 2 | D5: Ф-3 | E5: =23-9 -> 14 | F5: =30.36+2.1+1.05 -> 33.51 | G5: т | H5: =E5*F5/1000 -> 0.46914
A6: 4 | B6: 1 | C6: 2 | D6: Ф-3.1 | E6: 4 | F6: =49.2+9.8 -> 59 | G6: т | H6: =E6*F6/1000 -> 0.236
A7: 5 | B7: 1 | C7: 2 | D7: Ф-4 | E7: 15 | F7: =30.36+2.1+1.47 -> 33.93 | G7: т | H7: =E7*F7/1000 -> 0.50895
A8: 6 | B8: 1 | C8: 2 | D8: Ф-4.1 | E8: 2 | F8: =29.07+2.1+1.47 -> 32.64 | G8: т | H8: =E8*F8/1000 -> 0.06528
A9: 7 | B9: 1 | C9: 3 | D9: Ф-1 | E9: 8 | F9: =35.8+2+3.1 -> 40.9 | G9: т | H9: =E9*F9/1000 -> 0.3272
A10: 8 | B10: 1 | C10: 3 | D10: Ф-3.1 | E10: 4 | F10: =49.2+9.8 -> 59 | G10: т | H10: =E10*F10/1000 -> 0.236
A11: 9 | B11: 1 | C11: 3 | D11: Ф-3.2 | E11: 1 | F11: =29.07+2.1+1.05 -> 32.22 | G11: т | H11: =E11*F11/1000 -> 0.03222
A12: 10 | B12: 1 | C12: 3 | D12: Ф-4.1 | E12: 2 | F12: =29.07+2.1+1.47 -> 32.64 | G12: т | H12: =E12*F12/1000 -> 0.06528
A13: 11 | B13: 2 | C13: 1 | D13: Ф-12 | E13: 8 | F13: =35.4+1.7+3.1 -> 40.2 | G13: т | H13: =E13*F13/1000 -> 0.3216
A14: 12 | B14: 2 | C14: 1 | D14: Ф-13 | E14: 12 | F14: =35.4+2.15+3.1 -> 40.65 | G14: т | H14: =E14*F14/1000 -> 0.4878
A15: 13 | B15: 2 | C15: 3 | D15: Ф-12 | E15: 16 | F15: =35.4+1.7+3.1 -> 40.2 | G15: т | H15: =E15*F15/1000 -> 0.6432
A16: 14 | B16: 2 | C16: 3 | D16: Ф-13 | E16: 21 | F16: =35.4+2.15+3.1 -> 40.65 | G16: т | H16: =E16*F16/1000 -> 0.85365
A17: 15 | B17: 3 | C17: 1 | D17: Ф-12 | E17: 4 | F17: =35.4+1.7+3.1 -> 40.2 | G17: т | H17: =E17*F17/1000 -> 0.1608
A18: 16 | B18: 3 | C18: 1 | D18: Ф-13 | E18: 6 | F18: =35.4+2.15+3.1 -> 40.65 | G18: т | H18: =E18*F18/1000 -> 0.2439
A19: 17 | B19: 3 | C19: 3 | D19: Ф-12 | E19: 12 | F19: =35.4+1.7+3.1 -> 40.2 | G19: т | H19: =E19*F19/1000 -> 0.4824
A20: 18 | B20: 3 | C20: 3 | D20: Ф-13 | E20: 24 | F20: =35.4+2.15+3.1 -> 40.65 | G20: т | H20: =E20*F20/1000 -> 0.9756
A21: 19 | B21: 4 | C21: 3 | D21: Ф-12 | E21: 8 | F21: =35.4+1.7+3.1 -> 40.2 | G21: т | H21: =E21*F21/1000 -> 0.3216
A22: 20 | B22: 4 | C22: 3 | D22: Ф-13 | E22: 19 | F22: =35.4+2.15+3.1 -> 40.65 | G22: т | H22: =E22*F22/1000 -> 0.77235
F23: Итог: | G23: т | H23: =SUM(H3:H22) -> 8.14427

Sheet 2.3-Ст
A1: Устройство металлоконструкций фахверков, стоек, рам, балок, опорных конструкций и усилений с учетом крепления, огрунтовки и окрашивания
A2: Номер п/п | B2: Этаж | C2: Секция | D2: Тип | E2: шт. | F2: кг/1шт | G2: Ед. изм. | H2: Общее кол-во
A3: 1 | B3: -1 | C3: 1 | D3: Ф-1 | E3: 3 | F3: =35.8+3.5+2+3.1 -> 44.4 | G3: т | H3: =E3*F3/1000 -> 0.1332
A4: 2 | B4: -1 | C4: 1 | D4: Ф-2 | E4: 1 | F4: =35.8+3.5+3.1+2.15 -> 44.55 | G4: т | H4: =E4*F4/1000 -> 0.04455
A5: 3 | B5: -1 | C5: 1 | D5: Ф-3 | E5: 1 | F5: =30.36+2.1+1.05 -> 33.51 | G5: т | H5: =E5*F5/1000 -> 0.03351
A6: 4 | B6: -1 | C6: 1 | D6: Ф-4 | E6: 1 | F6: =30.36+2.1+1.47 -> 33.93 | G6: т | H6: =E6*F6/1000 -> 0.03393
A7: 5 | B7: -1 | C7: 2 | D7: Ф-1 | E7: 7 | F7: =35.8+3.5+2+3.1 -> 44.4 | G7: т | H7: =E7*F7/1000 -> 0.3108
A8: 6 | B8: -1 | C8: 2 | D8: Ф-2 | E8: 1 | F8: =35.8+3.5+3.1+2.15 -> 44.55 | G8: т | H8: =E8*F8/1000 -> 0.04455
A9: 7 | B9: -1 | C9: 2 | D9: Ф-3 | E9: 2 | F9: =30.36+2.1+1.05 -> 33.51 | G9: т | H9: =E9*F9/1000 -> 0.06702
A10: 8 | B10: -1 | C10: 3 | D10: Ф-1 | E10: 7 | F10: =35.8+3.5+2+3.1 -> 44.4 | G10: т | H10: =E10*F10/1000 -> 0.3108
A11: 9 | B11: -1 | C11: 3 | D11: Ф-2 | E11: 2 | F11: =35.8+3.5+3.1+2.15 -> 44.55 | G11: т | H11: =E11*F11/1000 -> 0.0891
A12: 10 | B12: -1 | C12: 3 | D12: Ф-3 | E12: 2 | F12: =30.36+2.1+1.05 -> 33.51 | G12: т | H12: =E12*F12/1000 -> 0.06702
F13: Итог: | G13: т | H13: =SUM(H3:H12) -> 1.13448

Sheet 2.4-Ст
A1: Устройство металлоконструкций фахверков, стоек, рам, балок, опорных конструкций и усилений с учетом крепления, огрунтовки и окрашивания
A2: Номер п/п | B2: Этаж | C2: Секция | D2: Тип | E2: шт. | F2: кг/1шт | G2: Ед. изм. | H2: Общее кол-во
A3: 1 | B3: 1 | C3: 1 | D3: Ф-7 | E3: 2 | F3: =30.7+3+2.15+3.1 -> 38.95 | G3: т | H3: =E3*F3/1000 -> 0.0779
A4: 2 | B4: 1 | C4: 2 | D4: Ф-1 | E4: 7 | F4: =35.8+3.5+2+3.1 -> 44.4 | G4: т | H4: =E4*F4/1000 -> 0.3108
A5: 3 | B5: 1 | C5: 2 | D5: Ф-2 | E5: 3 | F5: =35.8+3.5+3.1+2.15 -> 44.55 | G5: т | H5: =E5*F5/1000 -> 0.13365
A6: 4 | B6: 1 | C6: 2 | D6: Ф-5.1 | E6: 2 | F6: =34.4+1.4+0.48 -> 36.28 | G6: т | H6: =E6*F6/1000 -> 0.07256
A7: 5 | B7: 1 | C7: 3 | D7: Ф-1 | E7: 2 | F7: =35.8+2+3.1 -> 40.9 | G7: т | H7: =E7*F7/1000 -> 0.0818
A8: 6 | B8: 1 | C8: 3 | D8: Ф-4 | E8: 1 | F8: =30.36+2.1+1.47 -> 33.93 | G8: т | H8: =E8*F8/1000 -> 0.03393
A9: 7 | B9: 2 | C9: 1 | D9: Ф-14 | E9: 1 | F9: =29.99+2.1+1.05 -> 33.14 | G9: т | H9: =E9*F9/1000 -> 0.03314
A10: 8 | B10: 2 | C10: 1 | D10: Ф-15 | E10: 1 | F10: =29.99+2.1+1.47 -> 33.56 | G10: т | H10: =E10*F10/1000 -> 0.03356
A11: 9 | B11: 2 | C11: 2 | D11: Ф-13 | E11: 5 | F11: =35.4+3.5+2.15+3.1 -> 44.15 | G11: т | H11: =E11*F11/1000 -> 0.22075
A12: 10 | B12: 2 | C12: 2 | D12: Ф-14 | E12: 8 | F12: =29.99+2.1+1.05 -> 33.14 | G12: т | H12: =E12*F12/1000 -> 0.26512
A13: 11 | B13: 2 | C13: 3 | D13: Ф-12 | E13: 1 | F13: =35.4+3.5+1.7+3.1 -> 43.7 | G13: т | H13: =E13*F13/1000 -> 0.0437
A14: 12 | B14: 2 | C14: 3 | D14: Ф-13 | E14: 3 | F14: =35.4+3.5+2.15+3.1 -> 44.15 | G14: т | H14: =E14*F14/1000 -> 0.13245
A15: 13 | B15: 2 | C15: 3 | D15: Ф-14 | E15: 6 | F15: =29.99+2.1+1.05 -> 33.14 | G15: т | H15: =E15*F15/1000 -> 0.19884
A16: 14 | B16: 3 | C16: 1 | D16: Ф-14 | E16: 1 | F16: =29.99+2.1+1.05 -> 33.14 | G16: т | H16: =E16*F16/1000 -> 0.03314
A17: 15 | B17: 3 | C17: 1 | D17: Ф-15 | E17: 1 | F17: =29.99+2.1+1.47 -> 33.56 | G17: т | H17: =E17*F17/1000 -> 0.03356
A18: 16 | B18: 3 | C18: 2 | D18: Ф-12 | E18: 3 | F18: =35.4+3.5+1.7+3.1 -> 43.7 | G18: т | H18: =E18*F18/1000 -> 0.1311
A19: 17 | B19: 3 | C19: 2 | D19: Ф-13 | E19: 12 | F19: =35.4+3.5+2.15+3.1 -> 44.15 | G19: т | H19: =E19*F19/1000 -> 0.5298
A20: 18 | B20: 3 | C20: 2 | D20: Ф-14 | E20: 1 | F20: =29.99+2.1+1.05 -> 33.14 | G20: т | H20: =E20*F20/1000 -> 0.03314
A21: 19 | B21: 3 | C21: 3 | D21: Ф-12 | E21: 2 | F21: =35.4+3.5+1.7+3.1 -> 43.7 | G21: т | H21: =E21*F21/1000 -> 0.0874
A22: 20 | B22: 3 | C22: 3 | D22: Ф-13 | E22: 2 | F22: =35.4+3.5+2.15+3.1 -> 44.15 | G22: т | H22: =E22*F22/1000 -> 0.0883
A23: 21 | B23: 3 | C23: 3 | D23: Ф-14 | E23: 5 | F23: =29.99+2.1+1.05 -> 33.14 | G23: т | H23: =E23*F23/1000 -> 0.1657
A24: 22 | B24: 4 | C24: 3 | D24: Ф-13 | E24: 2 | F24: =35.4+3.5+2.15+3.1 -> 44.15 | G24: т | H24: =E24*F24/1000 -> 0.0883
A25: 23 | B25: 4 | C25: 3 | D25: Ф-14 | E25: 1 | F25: =29.99+2.1+1.05 -> 33.14 | G25: т | H25: =E25*F25/1000 -> 0.03314
F26: Итог: | G26: т | H26: =SUM(H3:H25) -> 2.86178

Sheet Лист2
A1: Устройство металлоконструкций фахверков, стоек, рам, балок, опорных конструкций и усилений с учетом крепления, огрунтовки и окрашивания
A2: Номер п/п | B2: Секция | C2: Этаж | D2: Тип | E2: шт. | F2: кг/1шт | G2: Ед. изм. | H2: Общее кол-во
A3: 1 | B3: 1 | C3: 1 | D3: Ф-7 | E3: 2 | F3: =30.7+3+2.15+3.1 -> 38.95 | G3: т | H3: =E3*F3/1000 -> 0.0779
A4: 2 | B4: 1 | C4: 2 | D4: Ф-14 | E4: 1 | F4: =29.99+2.1+1.05 -> 33.14 | G4: т | H4: =E4*F4/1000 -> 0.03314
A5: 3 | B5: 1 | C5: 2 | D5: Ф-15 | E5: 1 | F5: =29.99+2.1+1.47 -> 33.56 | G5: т | H5: =E5*F5/1000 -> 0.03356
A6: 4 | B6: 1 | C6: 3 | D6: Ф-14 | E6: 1 | F6: =29.99+2.1+1.05 -> 33.14 | G6: т | H6: =E6*F6/1000 -> 0.03314
A7: 5 | B7: 1 | C7: 3 | D7: Ф-15 | E7: 1 | F7: =29.99+2.1+1.47 -> 33.56 | G7: т | H7: =E7*F7/1000 -> 0.03356
A8: 6 | B8: 2 | C8: 1 | D8: Ф-1 | E8: 7 | F8: =35.8+3.5+2+3.1 -> 44.4 | G8: т | H8: =E8*F8/1000 -> 0.3108
A9: 7 | B9: 2 | C9: 1 | D9: Ф-2 | E9: 3 | F9: =35.8+3.5+3.1+2.15 -> 44.55 | G9: т | H9: =E9*F9/1000 -> 0.13365
A10: 8 | B10: 2 | C10: 1 | D10: Ф-5.1 | E10: 2 | F10: =34.4+1.4+0.48 -> 36.28 | G10: т | H10: =E10*F10/1000 -> 0.07256
A11: 9 | B11: 2 | C11: 2 | D11: Ф-13 | E11: 5 | F11: =35.4+3.5+2.15+3.1 -> 44.15 | G11: т | H11: =E11*F11/1000 -> 0.22075
A12: 10 | B12: 2 | C12: 2 | D12: Ф-14 | E12: 8 | F12: =29.99+2.1+1.05 -> 33.14 | G12: т | H12: =E12*F12/1000 -> 0.26512
A13: 11 | B13: 2 | C13: 3 | D13: Ф-12 | E13: 3 | F13: =35.4+3.5+1.7+3.1 -> 43.7 | G13: т | H13: =E13*F13/1000 -> 0.1311
A14: 12 | B14: 2 | C14: 3 | D14: Ф-13 | E14: 12 | F14: =35.4+3.5+2.15+3.1 -> 44.15 | G14: т | H14: =E14*F14/1000 -> 0.5298
A15: 13 | B15: 2 | C15: 3 | D15: Ф-14 | E15: 1 | F15: =29.99+2.1+1.05 -> 33.14 | G15: т | H15: =E15*F15/1000 -> 0.03314
A16: 14 | B16: 3 | C16: 1 | D16: Ф-1 | E16: 2 | F16: =35.8+2+3.1 -> 40.9 | G16: т | H16: =E16*F16/1000 -> 0.0818
A17: 15 | B17: 3 | C17: 1 | D17: Ф-4 | E17: 1 | F17: =30.36+2.1+1.47 -> 33.93 | G17: т | H17: =E17*F17/1000 -> 0.03393
A18: 16 | B18: 3 | C18: 2 | D18: Ф-12 | E18: 1 | F18: =35.4+3.5+1.7+3.1 -> 43.7 | G18: т | H18: =E18*F18/1000 -> 0.0437
A19: 17 | B19: 3 | C19: 2 | D19: Ф-13 | E19: 3 | F19: =35.4+3.5+2.15+3.1 -> 44.15 | G19: т | H19: =E19*F19/1000 -> 0.13245
A20: 18 | B20: 3 | C20: 2 | D20: Ф-14 | E20: 6 | F20: =29.99+2.1+1.05 -> 33.14 | G20: т | H20: =E20*F20/1000 -> 0.19884
A21: 19 | B21: 3 | C21: 3 | D21: Ф-12 | E21: 2 | F21: =35.4+3.5+1.7+3.1 -> 43.7 | G21: т | H21: =E21*F21/1000 -> 0.0874
A22: 20 | B22: 3 | C22: 3 | D22: Ф-13 | E22: 2 | F22: =35.4+3.5+2.15+3.1 -> 44.15 | G22: т | H22: =E22*F22/1000 -> 0.0883
A23: 21 | B23: 3 | C23: 3 | D23: Ф-14 | E23: 5 | F23: =29.99+2.1+1.05 -> 33.14 | G23: т | H23: =E23*F23/1000 -> 0.1657
A24: 22 | B24: 3 | C24: 4 | D24: Ф-13 | E24: 2 | F24: =35.4+3.5+2.15+3.1 -> 44.15 | G24: т | H24: =E24*F24/1000 -> 0.0883
A25: 23 | B25: 3 | C25: 4 | D25: Ф-14 | E25: 1 | F25: =29.99+2.1+1.05 -> 33.14 | G25: т | H25: =E25*F25/1000 -> 0.03314
F26: Итог: | G26: т | H26: =SUM(H3:H25) -> 2.86178

Sheet 2.2-Пер
A1: Устройство перемычек металлических с огрунтовкой и окраской. 1-4 этажи.
A2: Номер п/п | B2: Этаж | C2: Секция | D2: Тип | E2: шт. | F2: кг/1шт | G2: Ед. изм. | H2: Общее кол-во
A3: 1 | B3: 1 | C3: 1 | D3: ПР-Г1 | E3: 5 | F3: =VLOOKUP(D3,'2.2-Пер2'!$A$2:$C$13,3) -> 46.84 | G3: т | H3: =E3*F3/1000 -> 0.2342
A4: 2 | B4: 1 | C4: 1 | D4: ПР-Г2 | E4: 1 | F4: =VLOOKUP(D4,'2.2-Пер2'!$A$2:$C$13,3) -> 22.4 | G4: т | H4: =E4*F4/1000 -> 0.0224
A5: 3 | B5: 1 | C5: 1 | D5: ПР-Г4 | E5: 1 | F5: =VLOOKUP(D5,'2.2-Пер2'!$A$2:$C$13,3) -> 21.307692 | G5: т | H5: =E5*F5/1000 -> 0.021307692
A6: 4 | B6: 1 | C6: 1 | D6: ПР-Г6 | E6: 1 | F6: =VLOOKUP(D6,'2.2-Пер2'!$A$2:$C$13,3) -> 18.69 | G6: т | H6: =E6*F6/1000 -> 0.01869
A7: 5 | B7: 1 | C7: 1 | D7: ПР-К2 | E7: 1 | F7: =VLOOKUP(D7,'2.2-Пер2'!$A$2:$C$13,3) -> 6.93 | G7: т | H7: =E7*F7/1000 -> 0.00693
A8: 6 | B8: 1 | C8: 1 | D8: ПР-К3 | E8: 3 | F8: =VLOOKUP(D8,'2.2-Пер2'!$A$2:$C$13,3) -> 8.81 | G8: т | H8: =E8*F8/1000 -> 0.02643
A10: 7 | B10: 1 | C10: 2 | D10: ПР-Г4 | E10: 1 | F10: =VLOOKUP(D10,'2.2-Пер2'!$A$2:$C$13,3) -> 21.307692 | G10: т | H10: =E10*F10/1000 -> 0.021307692
A11: 8 | B11: 1 | C11: 2 | D11: ПР-К1 | E11: 9 | F11: =VLOOKUP(D11,'2.2-Пер2'!$A$2:$C$13,3) -> 12.170909 | G11: т | H11: =E11*F11/1000 -> 0.10953818
A12: 9 | B12: 1 | C12: 2 | D12: ПР-К2 | E12: 6 | F12: =VLOOKUP(D12,'2.2-Пер2'!$A$2:$C$13,3) -> 6.93 | G12: т | H12: =E12*F12/1000 -> 0.04158
A13: 10 | B13: 1 | C13: 2 | D13: ПР-К3 | E13: 8 | F13: =VLOOKUP(D13,'2.2-Пер2'!$A$2:$C$13,3) -> 8.81 | G13: т | H13: =E13*F13/1000 -> 0.07048
A14: 11 | B14: 1 | C14: 2 | D14: ПР-К6 | E14: 1 | F14: =VLOOKUP(D14,'2.2-Пер2'!$A$2:$C$13,3) -> 27.95 | G14: т | H14: =E14*F14/1000 -> 0.02795
A15: 12 | B15: 1 | C15: 2 | D15: ПР-К9 | E15: 3 | F15: =VLOOKUP(D15,'2.2-Пер2'!$A$2:$C$13,3) -> 5.85 | G15: т | H15: =E15*F15/1000 -> 0.01755
... A41: 32 | B41: 4 | C41: 3 | D41: ПР-К13 | E41: 1 | F41: =VLOOKUP(D41,'2.2-Пер2'!$A$2:$C$13,3) -> 5.44 | G41: т | H41: =E41*F41/1000 -> 0.00544
E42: =SUM(E3:E41) -> 96 | F42: Итог: | G42: т | H42: =SUM(H3:H41) -> 2.4501313

Sheet 2.2-Пер2
A1: Содержимое | B1: Количество | C1: кг/шт | D1: Итог:
A2: ПР-Г1 | B2: 30 | C2: 46.84 | D2: =B2*C2 -> 1405.2
A3: ПР-Г2 | B3: 16 | C3: 22.4 | D3: =B3*C3 -> 358.4
A4: ПР-Г4 | B4: 3 | C4: 21.307692 | D4: =B4*C4 -> 63.923077
A5: ПР-Г5 | B5: 2 | C5: 56.63 | D5: =B5*C5 -> 113.26
A6: ПР-Г6 | B6: 8 | C6: 18.69 | D6: =B6*C6 -> 149.52
A7: ПР-Г6* | B7: 1 | C7: 18.69 | D7: =B7*C7 -> 18.69
A8: ПР-К1 | B8: 9 | C8: 12.170909 | D8: =B8*C8 -> 109.53818
A9: ПР-К13 | B9: 1 | C9: 5.44 | D9: =B9*C9 -> 5.44
A10: ПР-К2 | B10: 7 | C10: 6.93 | D10: =B10*C10 -> 48.51
A11: ПР-К3 | B11: 15 | C11: 8.81 | D11: =B11*C11 -> 132.15
A12: ПР-К6 | B12: 1 | C12: 27.95 | D12: =B12*C12 -> 27.95
A13: ПР-К9 | B13: 3 | C13: 5.85 | D13: =B13*C13 -> 17.55
B14: =SUM(B2:B13) -> 96 | C14: Сумма: | D14: =SUM(D2:D13) -> 2450.1313

Sheet 3-Ст
A1: Номер п/п | B1: Наименование затрат | C1: Описание | D1: Ед. изм. | E1: Общее кол-во
A2: 1 | B2: Кладка внутренних стен из блоков ячеистого бетона без устройства перемычек, включая армирование, устройство примыканий | C2: 2 этаж. 1 секция. Толщина - 200 мм. | D2: м3 | E2: 26.36
A3: 2 | B3: Кладка внутренних стен из блоков ячеистого бетона без устройства перемычек, включая армирование, устройство примыканий | C3: 3 этаж. 1 секция. Толщина - 200 мм. | D3: м3 | E3: 23.04

Sheet Ведомость
A1: Этаж | B1: Секция | C1: № помеще ния | D1: Марка | E1: Площадь | F1: Примечание | G1: Состав отделки
A2: 1 | B2: 1 | C2: 1001 | D2: ЧН-11 | E2: 12.6 | F2: Отделка перегородок и стен из кирпича | G2: - грунтование грунтом глубокого проникновения; - штукатурка гипсовыми смесями до 25 мм; - грунтование грунтом глубокого проникновения; - шпаклевка гипсовая базовая т.2 мм; - грунтование грунтом глубокого проникновения; - шпаклевка гипсовая финишная т.2 мм; - грунтованиеие грунтом глубокого проникновения по типу краски.
A3: 1 | B3: 1 | C3: 1001 | D3: ЧН-6 | E3: 55.1 | F3: Отделка перегородок и стен из газобетона | G3: - грунтование грунтом глубокого проникновения; - штукатурка гипсовыми смесями до 25 мм; - грунтование грунтом глубокого проникновения; - шпаклевка гипсовая базовая т.2 мм; - грунтование грунтом глубокого проникновения; - шпаклевка гипсовая финишная т.2 мм; - окраска в 2 слоя с предварительным грунтованием по типу краски.
A4: 1 | B4: 1 | C4: 1001 | D4: ЧН-14 | E4: 5.7 | F4: Отделка перегородок ГКЛ | G4: - заделка швов шпаклевкой и серпянкой; - грунтование грунтовкой Knauff-тиффенгрунд; - шпаклевка гипсовая базовая т.2 мм; - грунтование грунтом глубокого проникновения; - шпаклевка гипсовая финишная т.2 мм; - грунтование по типу краски.
A5: 1 | B5: 1 | C5: 1001 | D5: ЧН-5 | E5: 40.4 | F5: Отделка стен из железобетона | G5: - грунтование Бетонконтактом; - штукатурка гипсовыми смесями до 25 мм; - грунтование грунтом глубокого проникновения; - шпаклевка гипсовая базовая т.2 мм; - грунтование грунтом глубокого проникновения; - шпаклевка гипсовая финишная т.2 мм; - окраска в 2 слоя с предварительным грунтованием по типу краски.
A6: 1 | B6: 1 | C6: 1001 | D6: ЧН-8 | E6: 15 | F6: Отделка перегородок ПГП | G6: - грунтование грунтом глубокого проникновения; - штукатурка гипсовыми смесями до 10 мм; - грунтование грунтом глубокого проникновения; - шпаклевка гипсовая базовая т.2 мм; - грунтование грунтом глубокого проникновения; - шпаклевка гипсовая финишная т.2 мм; - окраска в 2 слоя с предварительным грунтованием по типу краски.
A7: 1 | B7: 1 | C7: 1002 | D7: ЧН-11 | E7: 6.2 | F7: Отделка перегородок и стен из кирпича | G7: - грунтование грунтом глубокого проникновения; - штукатурка гипсовыми смесями до 25 мм; - грунтование грунтом глубокого проникновения; - шпаклевка гипсовая базовая т.2 мм; - грунтование грунтом глубокого проникновения; - шпаклевка гипсовая финишная т.2 мм; - грунтованиеие грунтом глубокого проникновения по типу краски.
A8: 1 | B8: 1 | C8: 1002 | D8: ЧН-6 | E8: 81.3 | F8: Отделка перегородок и стен из газобетона | G8: - грунтование грунтом глубокого проникновения; - штукатурка гипсовыми смесями до 25 мм; - грунтование грунтом глубокого проникновения; - шпаклевка гипсовая базовая т.2 мм; - грунтование грунтом глубокого проникновения; - шпаклевка гипсовая финишная т.2 мм; - окраска в 2 слоя с предварительным грунтованием по типу краски.
A9: 1 | B9: 1 | C9: 1002 | D9: ЧН-14 | E9: 2.9 | F9: Отделка перегородок ГКЛ | G9: - заделка швов шпаклевкой и серпянкой; - грунтование грунтовкой Knauff-тиффенгрунд; - шпаклевка гипсовая базовая т.2 мм; - грунтование грунтом глубокого проникновения; - шпаклевка гипсовая финишная т.2 мм; - грунтование по типу краски.
A10: 1 | B10: 1 | C10: 1002 | D10: ЧН-5 | E10: 10 | F10: Отделка стен из железобетона | G10: - грунтование Бетонконтактом; - штукатурка гипсовыми смесями до 25 мм; - грунтование грунтом глубокого проникновения; - шпаклевка гипсовая базовая т.2 мм; - грунтование грунтом глубокого проникновения; - шпаклевка гипсовая финишная т.2 мм; - окраска в 2 слоя с предварительным грунтованием по типу краски.
A11: 1 | B11: 1 | C11: 1002 | D11: ЧН-8 | E11: 3.8 | F11: Отделка перегородок ПГП | G11: - грунтование грунтом глубокого проникновения; - штукатурка гипсовыми смесями до 10 мм; - грунтование грунтом глубокого проникновения; - шпаклевка гипсовая базовая т.2 мм; - грунтование грунтом глубокого проникновения; - шпаклевка гипсовая финишная т.2 мм; - окраска в 2 слоя с предварительным грунтованием по типу краски.
A12: 1 | B12: 1 | C12: 1003 | D12: ЧН-11 | E12: 7.8 | F12: Отделка перегородок и стен из кирпича | G12: - грунтование грунтом глубокого проникновения; - штукатурка гипсовыми смесями до 25 мм; - грунтование грунтом глубокого проникновения; - шпаклевка гипсовая базовая т.2 мм; - грунтование грунтом глубокого проникновения; - шпаклевка гипсовая финишная т.2 мм; - грунтованиеие грунтом глубокого проникновения по типу краски.
A13: 1 | B13: 1 | C13: 1003 | D13: ЧН-6 | E13: 59.9 | F13: Отделка перегородок и стен из газобетона | G13: - грунтование грунтом глубокого проникновения; - штукатурка гипсовыми смесями до 25 мм; - грунтование грунтом глубокого проникновения; - шпаклевка гипсовая базовая т.2 мм; - грунтование грунтом глубокого проникновения; - шпаклевка гипсовая финишная т.2 мм; - окраска в 2 слоя с предварительным грунтованием по типу краски.
... A359: 1 | B359: 3 | C359: 1094 | D359: ЧН-5 | E359: 52.3 | F359: Отделка стен из железобетона | G359: - грунтование Бетонконтактом; - штукатурка гипсовыми смесями до 25 мм; - грунтование грунтом глубокого проникновения; - шпаклевка гипсовая базовая т.2 мм; - грунтование грунтом глубокого проникновения; - шпаклевка гипсовая финишная т.2 мм; - окраска в 2 слоя с предварительным грунтованием по типу краски.
A360: 1 | B360: 3 | C360: 1.094а | D360: ЧН-11 | E360: 10.8 | F360: Отделка перегородок и стен из кирпича | G360: - грунтование грунтом глубокого проникновения; - штукатурка гипсовыми смесями до 25 мм; - грунтование грунтом глубокого проникновения; - шпаклевка гипсовая базовая т.2 мм; - грунтование грунтом глубокого проникновения; - шпаклевка гипсовая финишная т.2 мм; - грунтованиеие грунтом глубокого проникновения по типу краски.
A361: 1 | B361: 3 | C361: 1.094а | D361: ЧН-6 | E361: 88.1 | F361: Отделка перегородок и стен из газобетона | G361: - грунтование грунтом глубокого проникновения; - штукатурка гипсовыми смесями до 25 мм; - грунтование грунтом глубокого проникновения; - шпаклевка гипсовая базовая т.2 мм; - грунтование грунтом глубокого проникновения; - шпаклевка гипсовая финишная т.2 мм; - окраска в 2 слоя с предварительным грунтованием по типу краски.
A362: 1 | B362: 3 | C362: 1.094а | D362: ЧН-14 | E362: 8.3 | F362: Отделка перегородок ГКЛ | G362: - заделка швов шпаклевкой и серпянкой; - грунтование грунтовкой Knauff-тиффенгрунд; - шпаклевка гипсовая базовая т.2 мм; - грунтование грунтом глубокого проникновения; - шпаклевка гипсовая финишная т.2 мм; - грунтование по типу краски.
A363: 1 | B363: 3 | C363: 1.094а | D363: ЧН-5 | E363: 48.3 | F363: Отделка стен из железобетона | G363: - грунтование Бетонконтактом; - штукатурка гипсовыми смесями до 25 мм; - грунтование грунтом глубокого проникновения; - шпаклевка гипсовая базовая т.2 мм; - грунтование грунтом глубокого проникновения; - шпаклевка гипсовая финишная т.2 мм; - окраска в 2 слоя с предварительным грунтованием по типу краски.
A364: 1 | B364: 3 | C364: 1095 | D364: ЧН-14 | E364: 3.8 | F364: Отделка перегородок ГКЛ | G364: - заделка швов шпаклевкой и серпянкой; - грунтование грунтовкой Knauff-тиффенгрунд; - шпаклевка гипсовая базовая т.2 мм; - грунтование грунтом глубокого проникновения; - шпаклевка гипсовая финишная т.2 мм; - грунтование по типу краски.
A365: 1 | B365: 3 | C365: 1095 | D365: ЧН-7 | E365: 57.3 | F365: Отделка стен из железобетона | G365: - Грунтовка глубокого проникновения; - Штукатурка цементными штукатурными смесями - до 25 мм; - Грунтовка глубокого проникновения; - Шпаклевка цементная базовая т.2 мм; - Грунтовка глубокого проникновения; - Шпаклевка цементная финишная т.2 мм; - Грунтовка глубокого проникновения по типу краски
A366: 1 | B366: 3 | C366: 1095 | D366: ЧН-16 | E366: 17 | F366: Отделка перегородок и стен из кирпича | G366: - Грунтовка глубокого проникновения; - Штукатурка цементными штукатурными смесями - до 25 мм; - Грунтовка глубокого проникновения; - Шпаклевка цементная базовая т.2 мм; - Грунтовка глубокого проникновения; - Шпаклевка цементная финишная т.2 мм; - Грунтовка глубокого проникновения по типу краски
A367: 1 | B367: 3 | C367: 1097 | D367: ЧН-11 | E367: 14.5 | F367: Отделка перегородок и стен из кирпича | G367: - грунтование грунтом глубокого проникновения; - штукатурка гипсовыми смесями до 25 мм; - грунтование грунтом глубокого проникновения; - шпаклевка гипсовая базовая т.2 мм; - грунтование грунтом глубокого проникновения; - шпаклевка гипсовая финишная т.2 мм; - грунтованиеие грунтом глубокого проникновения по типу краски.
A368: 1 | B368: 3 | C368: 1097 | D368: ЧН-12 | E368: 3 | F368: Отделка перегородок и стен из кирпича | G368: - грунтование грунтом глубокого проникновения; - выравнивание штукатуркой цементными смесями до 25 мм; - грунтование грунтом глубокого проникновения; - клей плиточный
A369: 1 | B369: 3 | C369: 1097 | D369: ЧН-20 | E369: 5.2 | F369: Отделка перегородок и стен из Газобетона, Кирпича | G369: - Грунтовка глубокого проникновения; - Штукатурка цементными штукатурными смесями - до 25 мм; - Грунтовка глубокого проникновения; - Шпаклёвка цементная базовая - 2 мм; - Грунтовка глубокого проникновения; - Шпаклёвка цементная финишная - 2 мм; - Грунтовка глубокого проникновения по типу краски
A370: 1 | B370: 3 | C370: 1097 | D370: ЧН-6 | E370: 21.4 | F370: Отделка перегородок и стен из газобетона | G370: - грунтование грунтом глубокого проникновения; - штукатурка гипсовыми смесями до 25 мм; - грунтование грунтом глубокого проникновения; - шпаклевка гипсовая базовая т.2 мм; - грунтование грунтом глубокого проникновения; - шпаклевка гипсовая финишная т.2 мм; - окраска в 2 слоя с предварительным грунтованием по типу краски.
A371: 1 | B371: 3 | C371: 1097 | D371: ЧН-15 | E371: 4.2 | F371: Отделка перегородок и стен из Газобетона, Кирпича | G371: - грунтование мастикой KNAUF Флихендихт, разведенной 1:4; - гидроизоляция полимерной мастикой KNAUF Флихендихт и при необходимости с использованием в углах Plitonit ГидроЛента; - выравнивание штукатуркой цементными смесями - до 25 мм; - грунтование грунтом глубокого проникновения; - плиточный клей.
A372: 1 | B372: 3 | C372: 1097 | D372: ЧН-23 | E372: 0.8 | F372: Отделка перегородок и стен из Газобетона, Кирпича. Мокрые помещения | G372: - грунтование грунтом глубокого проникновения; - штукатурка цементными смесями до 25 мм; - грунтование грунтом глубокого проникновения; - шпаклевка цементная базовая т.2 мм; - грунтование грунтом глубокого проникновения; - шпаклевка цементная финишная т.2 мм; - окраска в 2 слоя с предварительным грунтованием по типу краски.
A373: 1 | B373: 3 | C373: 1097 | D373: ЧН-8 | E373: 12.6 | F373: Отделка перегородок ПГП | G373: - грунтование грунтом глубокого проникновения; - штукатурка гипсовыми смесями до 10 мм; - грунтование грунтом глубокого проникновения; - шпаклевка гипсовая базовая т.2 мм; - грунтование грунтом глубокого проникновения; - шпаклевка гипсовая финишная т.2 мм; - окраска в 2 слоя с предварительным грунтованием по типу краски.
A374: 1 | B374: 3 | C374: 1097 | D374: ЧН-2 | E374: 14.1 | F374: Отделка перегородок ПГП | G374: - грунтование мастикой KNAUF Флихендихт, разведенной 1:4; - гидроизоляция полимерной мастикой KNAUF Флихендихт и при необходимости с использованием в углах Plitonit ГидроЛента; - выравнивание смесью Knauf-Флизен до 10 мм; - грунтование грунтовкой Knauf-тиффенгрунд; - клей Knauf-Флизен
A375: 1 | B375: 3 | C375: 1097 | D375: ЧН-9 | E375: 12.6 | F375: Отделка перегородок ПГП | G375: - грунтование грунтовкой Knauff-тиффенгрунд; - выравнивание штукатуркой смесью Knauff-флизен до 10 мм; - грунтование грунтовкой Knauff-тиффенгрунд; - смесь Knauff-флизен
... A560: 2 | B560: 3 | C560: 2047 | D560: ЧН-6 | E560: 75.6 | F560: Отделка перегородок и стен из газобетона | G560: 1) Грунтовка; 2) Шпаклевка на цементной основе; 3) Штукатурка ЦПР М100 - 20 мм
A561: 2 | B561: 3 | C561: 2.047а | D561: ЧН-11 | E561: 30.2 | F561: Отделка перегородок и стен из кирпича | G561: 1) Клей плиточный; 2) Мастика гидроизоляционная на высоту 1800 мм; 3) Шпаклевка на цементной основе; 4) Штукатурка ЦПР М100 - 20 мм.
A562: 2 | B562: 3 | C562: 2.047а | D562: ЧН-6 | E562: 189.4 | F562: Отделка перегородок и стен из газобетона | G562: 1) Грунтовка; 2) Шпаклевка на цементной основе; 3) Штукатурка ЦПР М100 - 20 мм
A563: 2 | B563: 3 | C563: 2.047а | D563: ЧН-14 | E563: 6.2 | F563: Отделка перегородок ГКЛ | G563: 1) Грунтовка; 2) Шпаклевка на гисповой основе; 3) Грунтовка по ГКЛ
A564: 2 | B564: 3 | C564: 2.047а | D564: ЧН-5 | E564: 29.8 | F564: Отделка стен из железобетона | G564: 1) Грунтовка; 2) Шпаклевка на цементной основе; 3) Штукатурка ЦПР М100 - 10 мм
A565: 2 | B565: 3 | C565: 2.047б | D565: ЧН-11 | E565: 14.6 | F565: Отделка перегородок и стен из кирпича | G565: 1) Клей плиточный; 2) Мастика гидроизоляционная на высоту 1800 мм; 3) Шпаклевка на цементной основе; 4) Штукатурка ЦПР М100 - 20 мм.
A566: 2 | B566: 3 | C566: 2.047б | D566: ЧН-6 | E566: 42.6 | F566: Отделка перегородок и стен из газобетона | G566: 1) Грунтовка; 2) Шпаклевка на цементной основе; 3) Штукатурка ЦПР М100 - 20 мм
A567: 2 | B567: 3 | C567: 2.047б | D567: ЧН-14 | E567: 6.6 | F567: Отделка перегородок ГКЛ | G567: 1) Грунтовка; 2) Шпаклевка на гисповой основе; 3) Грунтовка по ГКЛ
A568: 2 | B568: 3 | C568: 2.047б | D568: ЧН-5 | E568: 53.7 | F568: Отделка стен из железобетона | G568: 1) Грунтовка; 2) Шпаклевка на цементной основе; 3) Штукатурка ЦПР М100 - 10 мм
A569: 2 | B569: 3 | C569: 2048 | D569: ЧН-13 | E569: 3.1 | F569: Отделка перегородок и стен из газобетона | G569: 1) Клей плиточный; 2) Мастика гидроизоляционная на высоту 1800 мм; 3) Шпаклевка на цементной основе; 4) Штукатурка ЦПР М100 - 20 мм.
A570: 2 | B570: 3 | C570: 2048 | D570: ЧН-17 | E570: 1.9 | F570: Отделка перегородок ГКЛВ | G570: 1) Клей плиточный; 2) Мастика гидроизоляционная на высоту 1800 мм; 3) Грунтовка
A571: 2 | B571: 3 | C571: 2048 | D571: ЧН-10 | E571: 11 | F571: Отделка стен из железобетона | G571: 1) Клей плиточный; 2) Шпаклевка на цементной основе; 3) Штукатурка ЦПР М100 - 10 мм.
A572: 2 | B572: 3 | C572: 2048 | D572: ЧН-9 | E572: 18.3 | F572: Отделка перегородок ПГП | G572: 1) Клей плиточный; 2) Мастика гидроизоляционная на высоту 1800 мм; 3) Грунтовка
A573: 2 | B573: 3 | C573: 2049 | D573: ЧН-12 | E573: 10.4 | F573: Отделка перегородок и стен из кирпича | G573: 1) Клей плиточный; 2) Мастика гидроизоляционная на высоту 1800 мм; 3) Шпаклевка на цементной основе; 4) Штукатурка ЦПР М100 - 20 мм.
A574: 2 | B574: 3 | C574: 2049 | D574: ЧН-6 | E574: 5.2 | F574: Отделка перегородок и стен из газобетона | G574: 1) Грунтовка; 2) Шпаклевка на цементной основе; 3) Штукатурка ЦПР М100 - 20 мм
A575: 2 | B575: 3 | C575: 2049 | D575: ЧН-7 | E575: 1.9 | F575: Отделка стен из железобетона | G575: 1) Грунтовка; 2) Шпаклевка на цементной основе; 3) Штукатурка ЦПР М100 - 10 мм
A576: 2 | B576: 3 | C576: 2049 | D576: ЧН-10 | E576: 8.1 | F576: Отделка стен из железобетона | G576: 1) Клей плиточный; 2) Шпаклевка на цементной основе; 3) Штукатурка ЦПР М100 - 10 мм.
A577: 2 | B577: 3 | C577: 2049 | D577: ЧН-9 | E577: 5.2 | F577: Отделка перегородок ПГП | G577: 1) Клей плиточный; 2) Мастика гидроизоляционная на высоту 1800 мм; 3) Грунтовка
A578: 2 | B578: 3 | C578: 2050 | D578: ЧН-14 | E578: 3.9 | F578: Отделка перегородок ГКЛ | G578: 1) Грунтовка; 2) Шпаклевка на гисповой основе; 3) Грунтовка по ГКЛ
A579: 2 | B579: 3 | C579: 2050 | D579: ЧН-7 | E579: 88.6 | F579: Отделка стен из железобетона | G579: 1) Грунтовка; 2) Шпаклевка на цементной основе; 3) Штукатурка ЦПР М100 - 10 мм
A580: 2 | B580: 3 | C580: 2051 | D580: ЧН-11 | E580: 59.6 | F580: Отделка перегородок и стен из кирпича | G580: 1) Клей плиточный; 2) Мастика гидроизоляционная на высоту 1800 мм; 3) Шпаклевка на цементной основе; 4) Штукатурка ЦПР М100 - 20 мм.
... A583: 2 | B583: 3 | C583: 2051 | D583: ЧН-5 | E583: 40.5 | F583: Отделка стен из железобетона | G583: 1) Грунтовка; 2) Шпаклевка на цементной основе; 3) Штукатурка ЦПР М100 - 10 мм
A584: 2 | B584: 3 | C584: 2.051.1 | D584: ЧН-11 | E584: 54.3 | F584: Отделка перегородок и стен из кирпича | G584: 1) Клей плиточный; 2) Мастика гидроизоляционная на высоту 1800 мм; 3) Шпаклевка на цементной основе; 4) Штукатурка ЦПР М100 - 20 мм.
A585: 2 | B585: 3 | C585: 2.051.1 | D585: ЧН-6 | E585: 104.2 | F585: Отделка перегородок и стен из газобетона | G585: 1) Грунтовка; 2) Шпаклевка на цементной основе; 3) Штукатурка ЦПР М100 - 20 мм
A586: 2 | B586: 3 | C586: 2.051.1 | D586: ЧН-14 | E586: 4.5 | F586: Отделка перегородок ГКЛ | G586: 1) Грунтовка; 2) Шпаклевка на гисповой основе; 3) Грунтовка по ГКЛ
A587: 2 | B587: 3 | C587: 2.051.1 | D587: ЧН-5 | E587: 12.7 | F587: Отделка стен из железобетона | G587: 1) Грунтовка; 2) Шпаклевка на цементной основе; 3) Штукатурка ЦПР М100 - 10 мм
A588: 2 | B588: 2 | C588: 2052 | D588: ЧН-11 | E588: 23 | F588: Отделка перегородок и стен из кирпича | G588: 1) Клей плиточный; 2) Мастика гидроизоляционная на высоту 1800 мм; 3) Шпаклевка на цементной основе; 4) Штукатурка ЦПР М100 - 20 мм.
A589: 2 | B589: 2 | C589: 2052 | D589: ЧН-6 | E589: 233.9 | F589: Отделка перегородок и стен из газобетона | G589: 1) Грунтовка; 2) Шпаклевка на цементной основе; 3) Штукатурка ЦПР М100 - 20 мм
A590: 2 | B590: 2 | C590: 2052 | D590: ЧН-5 | E590: 58.5 | F590: Отделка стен из железобетона | G590: 1) Грунтовка; 2) Шпаклевка на цементной основе; 3) Штукатурка ЦПР М100 - 10 мм
A591: 2 | B591: 2 | C591: 2052 | D591: ЧН-8 | E591: 3.6 | F591: Отделка перегородок ПГП | G591: 1) Грунтовка; 2) Шпаклевка на гисповой основе
A592: 2 | B592: 3 | C592: 2053 | D592: ЧН-12 | E592: 11.5 | F592: Отделка перегородок и стен из кирпича | G592: 1) Клей плиточный; 2) Мастика гидроизоляционная на высоту 1800 мм; 3) Шпаклевка на цементной основе; 4) Штукатурка ЦПР М100 - 20 мм.
A593: 2 | B593: 3 | C593: 2053 | D593: ЧН-21 | E593: 2.1 | F593: Отделка перегородок и стен из кирпича. Выше уровня плитки | G593: 1) Клей плиточный; 2) Мастика гидроизоляционная на высоту 1800 мм; 3) Шпаклевка на цементной основе; 4) Штукатурка ЦПР М100 - 20 мм.
A594: 2 | B594: 3 | C594: 2053 | D594: ЧН-20 | E594: 0.6 | F594: Отделка перегородок и стен из Газобетона, Кирпича | G594: 1) Клей плиточный; 2) Мастика гидроизоляционная на высоту 1800 мм; 3) Шпаклевка на цементной основе; 4) Штукатурка ЦПР М100 - 20 мм.
A595: 2 | B595: 3 | C595: 2053 | D595: ЧН-13 | E595: 9.2 | F595: Отделка перегородок и стен из газобетона | G595: 1) Клей плиточный; 2) Мастика гидроизоляционная на высоту 1800 мм; 3) Шпаклевка на цементной основе; 4) Штукатурка ЦПР М100 - 20 мм.
A596: 2 | B596: 3 | C596: 2053 | D596: ЧН-23 | E596: 2.1 | F596: Отделка перегородок и стен из Газобетона, Кирпича. Мокрые помещения | G596: 1) Грунтовка; 2) Шпаклевка на цементной основе; 3) Штукатурка ЦПР М100 - 20 мм
A597: 2 | B597: 3 | C597: 2053 | D597: ЧН-10 | E597: 3.5 | F597: Отделка стен из железобетона | G597: 1) Клей плиточный; 2) Шпаклевка на цементной основе; 3) Штукатурка ЦПР М100 - 10 мм.
A598: 2 | B598: 3 | C598: 2053 | D598: ЧН-9 | E598: 3.5 | F598: Отделка перегородок ПГП | G598: 1) Клей плиточный; 2) Мастика гидроизоляционная на высоту 1800 мм; 3) Грунтовка
A599: 3 | B599: 1 | C599: 3001 | D599: ЧН-11 | E599: 13.7 | F599: Отделка перегородок и стен из кирпича | G599: 1) Клей плиточный; 2) Мастика гидроизоляционная на высоту 1800 мм; 3) Шпаклевка на цементной основе; 4) Штукатурка ЦПР М100 - 20 мм.
... A767: 3 | B767: 3 | C767: 3047 | D767: ЧН-5 | E767: 43.3 | F767: Отделка стен из железобетона | G767: 1) Грунтовка; 2) Шпаклевка на цементной основе; 3) Штукатурка ЦПР М100 - 10 мм
A768: 3 | B768: 3 | C768: 3.047а | D768: ЧН-11 | E768: 34.2 | F768: Отделка перегородок и стен из кирпича | G768: 1) Клей плиточный; 2) Мастика гидроизоляционная на высоту 1800 мм; 3) Шпаклевка на цементной основе; 4) Штукатурка ЦПР М100 - 20 мм.
A769: 3 | B769: 3 | C769: 3.047а | D769: ЧН-6 | E769: 11.6 | F769: Отделка перегородок и стен из газобетона | G769: 1) Грунтовка; 2) Шпаклевка на цементной основе; 3) Штукатурка ЦПР М100 - 20 мм
A770: 3 | B770: 3 | C770: 3.047а | D770: ЧН-14 | E770: 6.7 | F770: Отделка перегородок ГКЛ | G770: 1) Грунтовка; 2) Шпаклевка на гисповой основе; 3) Грунтовка по ГКЛ
A771: 3 | B771: 3 | C771: 3.047а | D771: ЧН-5 | E771: 40 | F771: Отделка стен из железобетона | G771: 1) Грунтовка; 2) Шпаклевка на цементной основе; 3) Штукатурка ЦПР М100 - 10 мм
A772: 3 | B772: 3 | C772: 3.047б | D772: ЧН-11 | E772: 14.6 | F772: Отделка перегородок и стен из кирпича | G772: 1) Клей плиточный; 2) Мастика гидроизоляционная на высоту 1800 мм; 3) Шпаклевка на цементной основе; 4) Штукатурка ЦПР М100 - 20 мм.
A773: 3 | B773: 3 | C773: 3.047б | D773: ЧН-6 | E773: 17.2 | F773: Отделка перегородок и стен из газобетона | G773: 1) Грунтовка; 2) Шпаклевка на цементной основе; 3) Штукатурка ЦПР М100 - 20 мм
A774: 3 | B774: 3 | C774: 3.047б | D774: ЧН-14 | E774: 6.6 | F774: Отделка перегородок ГКЛ | G774: 1) Грунтовка; 2) Шпаклевка на гисповой основе; 3) Грунтовка по ГКЛ
A775: 3 | B775: 3 | C775: 3.047б | D775: ЧН-5 | E775: 55.8 | F775: Отделка стен из железобетона | G775: 1) Грунтовка; 2) Шпаклевка на цементной основе; 3) Штукатурка ЦПР М100 - 10 мм
A776: 3 | B776: 3 | C776: 3048 | D776: ЧН-7 | E776: 94.2 | F776: Отделка стен из железобетона | G776: 1) Грунтовка; 2) Шпаклевка на цементной основе; 3) Штукатурка ЦПР М100 - 10 мм
A777: 3 | B777: 3 | C777: 3049 | D777: ЧН-11 | E777: 22.5 | F777: Отделка перегородок и стен из кирпича | G777: 1) Клей плиточный; 2) Мастика гидроизоляционная на высоту 1800 мм; 3) Шпаклевка на цементной основе; 4) Штукатурка ЦПР М100 - 20 мм.
A778: 3 | B778: 3 | C778: 3049 | D778: ЧН-6 | E778: 214.6 | F778: Отделка перегородок и стен из газобетона | G778: 1) Грунтовка; 2) Шпаклевка на цементной основе; 3) Штукатурка ЦПР М100 - 20 мм
A779: 3 | B779: 3 | C779: 3049 | D779: ЧН-14 | E779: 2.1 | F779: Отделка перегородок ГКЛ | G779: 1) Грунтовка; 2) Шпаклевка на гисповой основе; 3) Грунтовка по ГКЛ
A780: 3 | B780: 3 | C780: 3049 | D780: ЧН-5 | E780: 65.3 | F780: Отделка стен из железобетона | G780: 1) Грунтовка; 2) Шпаклевка на цементной основе; 3) Штукатурка ЦПР М100 - 10 мм
A781: 3 | B781: 3 | C781: 3049 | D781: ЧН-8 | E781: 2.9 | F781: Отделка перегородок ПГП | G781: 1) Грунтовка; 2) Шпаклевка на гисповой основе
A782: 3 | B782: 3 | C782: 3050 | D782: ЧН-13 | E782: 18.6 | F782: Отделка перегородок и стен из газобетона | G782: 1) Клей плиточный; 2) Мастика гидроизоляционная на высоту 1800 мм; 3) Шпаклевка на цементной основе; 4) Штукатурка ЦПР М100 - 20 мм.
A783: 3 | B783: 3 | C783: 3050 | D783: ЧН-17 | E783: 2 | F783: Отделка перегородок ГКЛВ | G783: 1) Клей плиточный; 2) Мастика гидроизоляционная на высоту 1800 мм; 3) Грунтовка
A784: 3 | B784: 3 | C784: 3050 | D784: ЧН-10 | E784: 9.2 | F784: Отделка стен из железобетона | G784: 1) Клей плиточный; 2) Шпаклевка на цементной основе; 3) Штукатурка ЦПР М100 - 10 мм.
A785: 3 | B785: 3 | C785: 3050 | D785: ЧН-2 | E785: 24.6 | F785: Отделка перегородок ПГП | G785: 1) Клей плиточный; 2) Мастика гидроизоляционная на высоту 1800 мм; 3) Грунтовка
A786: 3 | B786: 3 | C786: 3051 | D786: ЧН-12 | E786: 10.4 | F786: Отделка перегородок и стен из кирпича | G786: 1) Клей плиточный; 2) Мастика гидроизоляционная на высоту 1800 мм; 3) Шпаклевка на цементной основе; 4) Штукатурка ЦПР М100 - 20 мм.
A787: 3 | B787: 3 | C787: 3051 | D787: ЧН-13 | E787: 5.2 | F787: Отделка перегородок и стен из газобетона | G787: 1) Клей плиточный; 2) Мастика гидроизоляционная на высоту 1800 мм; 3) Шпаклевка на цементной основе; 4) Штукатурка ЦПР М100 - 20 мм.
... A850: 4 | B850: 3 | C850: 4010 | D850: ЧН-5 | E850: 117.4 | F850: Отделка стен из железобетона | G850: 1) Грунтовка; 2) Шпаклевка на цементной основе; 3) Штукатурка ЦПР М100 - 10 мм
A851: 4 | B851: 3 | C851: 4.010а | D851: ЧН-11 | E851: 10.9 | F851: Отделка перегородок и стен из кирпича | G851: 1) Клей плиточный; 2) Мастика гидроизоляционная на высоту 1800 мм; 3) Шпаклевка на цементной основе; 4) Штукатурка ЦПР М100 - 20 мм.
A852: 4 | B852: 3 | C852: 4.010а | D852: ЧН-6 | E852: 17.4 | F852: Отделка перегородок и стен из газобетона | G852: 1) Грунтовка; 2) Шпаклевка на цементной основе; 3) Штукатурка ЦПР М100 - 20 мм
A853: 4 | B853: 3 | C853: 4.010а | D853: ЧН-5 | E853: 51.3 | F853: Отделка стен из железобетона | G853: 1) Грунтовка; 2) Шпаклевка на цементной основе; 3) Штукатурка ЦПР М100 - 10 мм
A854: 4 | B854: 3 | C854: 4011 | D854: ЧН-20 | E854: 2.1 | F854: Отделка перегородок и стен из Газобетона, Кирпича | G854: 1) Клей плиточный; 2) Мастика гидроизоляционная на высоту 1800 мм; 3) Шпаклевка на цементной основе; 4) Штукатурка ЦПР М100 - 20 мм.
A855: 4 | B855: 3 | C855: 4011 | D855: ЧО-2 | E855: 26.7 | F855: Отделка перегородок и стен из кирпича | G855: 1) Клей плиточный; 2) Мастика гидроизоляционная на высоту 1800 мм; 3) Шпаклевка на цементной основе; 4) Штукатурка ЦПР М100 - 20 мм.
A856: 4 | B856: 3 | C856: 4011 | D856: ЧН-13 | E856: 3.1 | F856: Отделка перегородок и стен из газобетона | G856: 1) Клей плиточный; 2) Мастика гидроизоляционная на высоту 1800 мм; 3) Шпаклевка на цементной основе; 4) Штукатурка ЦПР М100 - 20 мм.
A857: 4 | B857: 3 | C857: 4011 | D857: ЧН-10 | E857: 26.8 | F857: Отделка стен из железобетона | G857: 1) Клей плиточный; 2) Шпаклевка на цементной основе; 3) Штукатурка ЦПР М100 - 10 мм.
A858: 4 | B858: 3 | C858: 4011 | D858: ЧН-2 | E858: 54.5 | F858: Отделка перегородок ПГП | G858: 1) Клей плиточный; 2) Мастика гидроизоляционная на высоту 1800 мм; 3) Грунтовка
A859: 4 | B859: 3 | C859: 4012 | D859: ЧН-12 | E859: 10 | F859: Отделка перегородок и стен из кирпича | G859: 1) Клей плиточный; 2) Мастика гидроизоляционная на высоту 1800 мм; 3) Шпаклевка на цементной основе; 4) Штукатурка ЦПР М100 - 20 мм.
A860: 4 | B860: 3 | C860: 4012 | D860: ЧН-21 | E860: 1.8 | F860: Отделка перегородок и стен из кирпича. Выше уровня плитки | G860: 1) Клей плиточный; 2) Мастика гидроизоляционная на высоту 1800 мм; 3) Шпаклевка на цементной основе; 4) Штукатурка ЦПР М100 - 20 мм.
...

Sheet 2.6-Пер -1
A1: Устройство перемычек металлических с огрунтовкой и окраской. Повдал.
A2: Номер п/п | B2: Этаж | C2: Секция | D2: Тип | E2: шт. | F2: кг/1шт | G2: Ед. изм. | H2: Общее кол-во
A3: 1 | B3: -1 | C3: 1 | D3: ПР-1 | E3: 1 | F3: =0.632+10.367 -> 10.999 | G3: т | H3: =E3*F3/1000 -> 0.010999
A4: 2 | B4: -1 | C4: 1 | D4: ПР-2 | E4: 3 | F4: =15.587 -> 15.587 | G4: т | H4: =E4*F4/1000 -> 0.046761
A5: 3 | B5: -1 | C5: 1 | D5: ПР-4 | E5: 1 | F5: 9.713 | G5: т | H5: =E5*F5/1000 -> 0.009713
A6: 4 | B6: -1 | C6: 1 | D6: ПР-5 | E6: 2 | F6: 11.671 | G6: т | H6: =E6*F6/1000 -> 0.023342
A7: 5 | B7: -1 | C7: 1 | D7: ПР-6 | E7: 1 | F7: =9.789+0.883 -> 10.672 | G7: т | H7: =E7*F7/1000 -> 0.010672
A8: 6 | B8: -1 | C8: 1 | D8: ПР-А1 | E8: 1 | F8: =1.8012+0.883 -> 2.6842 | G8: т | H8: =E8*F8/1000 -> 0.0026842
A9: 7 | B9: -1 | C9: 1 | D9: ПР-А4 | E9: 2 | F9: 0.805 | G9: т | H9: =E9*F9/1000 -> 0.00161
A10: 8 | B10: -1 | C10: 1 | D10: ПР-А6 | E10: 1 | F10: =1.216 -> 1.216 | G10: т | H10: =E10*F10/1000 -> 0.001216
A12: 9 | B12: -1 | C12: 1 | D12: ПР-1 | E12: 1 | F12: =0.632+10.367 -> 10.999 | G12: т | H12: =E12*F12/1000 -> 0.010999
A13: 10 | B13: -1 | C13: 2 | D13: ПР-2 | E13: 3 | F13: =15.587 -> 15.587 | G13: т | H13: =E13*F13/1000 -> 0.046761
A14: 11 | B14: -1 | C14: 2 | D14: ПР-4 | E14: 1 | F14: 9.713 | G14: т | H14: =E14*F14/1000 -> 0.009713
A15: 12 | B15: -1 | C15: 2 | D15: ПР-А2 | E15: 1 | F15: =2.464+0.883 -> 3.347 | G15: т | H15: =E15*F15/1000 -> 0.003347
A16: 13 | B16: -1 | C16: 2 | D16: ПР-А4 | E16: 2 | F16: 0.805 | G16: т | H16: =E16*F16/1000 -> 0.00161
A17: 14 | B17: -1 | C17: 2 | D17: ПР-А6 | E17: 2 | F17: =1.216 -> 1.216 | G17: т | H17: =E17*F17/1000 -> 0.002432
A19: 15 | B19: -1 | C19: 3 | D19: ПР-1 | E19: 1 | F19: =0.632+10.367 -> 10.999 | G19: т | H19: =E19*F19/1000 -> 0.010999
A20: 16 | B20: -1 | C20: 3 | D20: ПР-2 | E20: 3 | F20: =15.587 -> 15.587 | G20: т | H20: =E20*F20/1000 -> 0.046761
A21: 17 | B21: -1 | C21: 3 | D21: ПР-4 | E21: 2 | F21: 9.713 | G21: т | H21: =E21*F21/1000 -> 0.019426
A22: 18 | B22: -1 | C22: 3 | D22: ПР-5 | E22: 2 | F22: 11.671 | G22: т | H22: =E22*F22/1000 -> 0.023342
A23: 19 | B23: -1 | C23: 3 | D23: ПР-6 | E23: 1 | F23: =9.789+0.883 -> 10.672 | G23: т | H23: =E23*F23/1000 -> 0.010672
A24: 20 | B24: -1 | C24: 3 | D24: ПР-8 | E24: 2 | F24: 12.65 | G24: т | H24: =E24*F24/1000 -> 0.0253
A25: 21 | B25: -1 | C25: 3 | D25: ПР-9 | E25: 1 | F25: 13.629 | G25: т | H25: =E25*F25/1000 -> 0.013629
A26: 22 | B26: -1 | C26: 3 | D26: ПР-А3 | E26: 1 | F26: =3.033+0.883 -> 3.916 | G26: т | H26: =E26*F26/1000 -> 0.003916
A27: 23 | B27: -1 | C27: 3 | D27: ПР-А4 | E27: 1 | F27: 0.805 | G27: т | H27: =E27*F27/1000 -> 0.000805
A28: 24 | B28: -1 | C28: 3 | D28: ПР-А6 | E28: 1 | F28: =1.216 -> 1.216 | G28: т | H28: =E28*F28/1000 -> 0.001216
E29: =SUM(E3:E28) -> 37 | F29: Итог: | G29: т | H29: =SUM(H3:H28) -> 0.3379252

Sheet 3.1-Шт
A1: № п.п | B1: Наименование | C1: Описание | D1: Ед. изм. | E1: Объем:
A2: 1 | B2: Оклейка швов сопряжения бетонных и других поверхностей стен, перегородок (газобетон, ПГП, панели АКОТЕК и др.) стеклохолстом | C2: Перед штукатуркой проклеить швы сопряжения разнородных поверхностей (бетон, газобетонный блок, кирпич, ПГП) и углы сеткой стеклотканой, ширина полос проклейки 150+150=300 мм, что составляет 20% от всей площади оштукатуриваемой поверхности. | D2: пог. м | E2: 742.98
A3: 2 | B3: Штукатурка стен цементным, цементно-песчаным раствором с предварительной огрунтовкой / толщ. от 21 до 40 мм / высотой до 4 метров | C3: 1-4 этажи. Штукатурка по ж/б. Тип: ЧН-1, ЧН-7, ЧН-10 | D3: м2 | E3: ='3.1.1'!I3+'3.1.1'!I7+'3.1.1'!I8 -> 346.8
A4: 3 | B4: Штукатурка стен цементным, цементно-песчаным раствором с предварительной огрунтовкой / толщ. от 21 до 40 мм / высотой до 4 метров | C4: 1-4 этажи. Штукатурка по блоку и кирпичу. Тип: ЧН-4, ЧН-12, ЧН-13, ЧН-15, ЧН-16, ЧН-20, ЧН-21, ЧН-23 | D4: м2 | E4: ='3.1.1'!I4+SUM('3.1.1'!I10:I16) -> 446.9
A5: 4 | B5: Штукатурка стен гипсовыми смесями с предварительной огрунтовкой СКБ / толщ. от 21 до 40 мм / высотой от 4,01 до 8 метров | C5: 1-4 этажи. Штукатурка гипсовая по блоку. Тип: ЧН-6, ЧН-11 | D5: м2 | E5: ='3.1.1'!I6+'3.1.1'!I9 -> 3098.9
A6: 5 | B6: Штукатурка стен гипсовыми смесями с предварительной огрунтовкой СКБ / толщ. от 21 до 40 мм / высотой от 4,01 до 8 метров | C6: 1-4 этажи. Штукатурка гипсовая по ж/б. Тип: ЧН-5 | D6: м2 | E6: ='3.1.1'!I5 -> 1231.1
D7: Сумма | E7: =SUM(E3:E6) -> 5123.7

Sheet 3.1.1
A1: Этаж | B1: 1 | C1: 1 | D1: 2 | E1: 2 | F1: 3 | G1: 3 | H1: 4
A2: Секция | B2: 1 | C2: 3 | D2: 1с | E2: 3с | F2: 1 с | G2: 3 с | H2: 3 с | I2: Итог:
A3: ЧН-1 | B3: =SUMIF(Таблица4[Марка],A3,Таблица4[Площадь]) -> 15 | C3: =SUMIF(Таблица46[Марка],A3,Таблица46[Площадь]) -> 19.8 | D3: =SUMIF(Таблица467[Марка],A3,Таблица467[Площадь]) -> 14.9 | E3: =SUMIF(Таблица4678[Марка],A3,Таблица4678[Площадь]) -> 10.7 | F3: =SUMIF(Таблица46789[Марка],A3,Таблица46789[Площадь]) -> 14.9 | G3: =SUMIF(Таблица4678910[Марка],A3,Таблица4678910[Площадь]) -> 0 | H3: =SUMIF(Таблица467891011[Марка],A3,Таблица467891011[Площадь]) -> 11.7 | I3: =SUM(B3:H3) -> 87
A4: ЧН-4 | B4: =SUMIF(Таблица4[Марка],A4,Таблица4[Площадь]) -> 6.1 | C4: =SUMIF(Таблица46[Марка],A4,Таблица46[Площадь]) -> 0 | D4: =SUMIF(Таблица467[Марка],A4,Таблица467[Площадь]) -> 6.1 | E4: =SUMIF(Таблица4678[Марка],A4,Таблица4678[Площадь]) -> 0 | F4: =SUMIF(Таблица46789[Марка],A4,Таблица46789[Площадь]) -> 0 | G4: =SUMIF(Таблица4678910[Марка],A4,Таблица4678910[Площадь]) -> 0 | H4: =SUMIF(Таблица467891011[Марка],A4,Таблица467891011[Площадь]) -> 0 | I4: =SUM(B4:H4) -> 12.2
A5: ЧН-5 | B5: =SUMIF(Таблица4[Марка],A5,Таблица4[Площадь]) -> 261.3 | C5: =SUMIF(Таблица46[Марка],A5,Таблица46[Площадь]) -> 0 | D5: =SUMIF(Таблица467[Марка],A5,Таблица467[Площадь]) -> 352.5 | E5: =SUMIF(Таблица4678[Марка],A5,Таблица4678[Площадь]) -> 93.2 | F5: =SUMIF(Таблица46789[Марка],A5,Таблица46789[Площадь]) -> 143.2 | G5: =SUMIF(Таблица4678910[Марка],A5,Таблица4678910[Площадь]) -> 155.8 | H5: =SUMIF(Таблица467891011[Марка],A5,Таблица467891011[Площадь]) -> 225.1 | I5: =SUM(B5:H5) -> 1231.1
A6: ЧН-6 | B6: =SUMIF(Таблица4[Марка],A6,Таблица4[Площадь]) -> 622.4 | C6: =SUMIF(Таблица46[Марка],A6,Таблица46[Площадь]) -> 10.6 | D6: =SUMIF(Таблица467[Марка],A6,Таблица467[Площадь]) -> 554.8 | E6: =SUMIF(Таблица4678[Марка],A6,Таблица4678[Площадь]) -> 483.4 | F6: =SUMIF(Таблица46789[Марка],A6,Таблица46789[Площадь]) -> 92.8 | G6: =SUMIF(Таблица4678910[Марка],A6,Таблица4678910[Площадь]) -> 344 | H6: =SUMIF(Таблица467891011[Марка],A6,Таблица467891011[Площадь]) -> 152.3 | I6: =SUM(B6:H6) -> 2260.3
A7: ЧН-7 | B7: =SUMIF(Таблица4[Марка],A7,Таблица4[Площадь]) -> 55.6 | C7: =SUMIF(Таблица46[Марка],A7,Таблица46[Площадь]) -> 30.9 | D7: =SUMIF(Таблица467[Марка],A7,Таблица467[Площадь]) -> 0 | E7: =SUMIF(Таблица4678[Марка],A7,Таблица4678[Площадь]) -> 26.7 | F7: =SUMIF(Таблица46789[Марка],A7,Таблица46789[Площадь]) -> 0 | G7: =SUMIF(Таблица4678910[Марка],A7,Таблица4678910[Площадь]) -> 1.8 | H7: =SUMIF(Таблица467891011[Марка],A7,Таблица467891011[Площадь]) -> 6.7 | I7: =SUM(B7:H7) -> 121.7
A8: ЧН-10 | B8: =SUMIF(Таблица4[Марка],A8,Таблица4[Площадь]) -> 3.1 | C8: =SUMIF(Таблица46[Марка],A8,Таблица46[Площадь]) -> 31.4 | D8: =SUMIF(Таблица467[Марка],A8,Таблица467[Площадь]) -> 3.1 | E8: =SUMIF(Таблица4678[Марка],A8,Таблица4678[Площадь]) -> 28.4 | F8: =SUMIF(Таблица46789[Марка],A8,Таблица46789[Площадь]) -> 0 | G8: =SUMIF(Таблица4678910[Марка],A8,Таблица4678910[Площадь]) -> 9.9 | H8: =SUMIF(Таблица467891011[Марка],A8,Таблица467891011[Площадь]) -> 62.2 | I8: =SUM(B8:H8) -> 138.1
A9: ЧН-11 | B9: =SUMIF(Таблица4[Марка],A9,Таблица4[Площадь]) -> 189.9 | C9: =SUMIF(Таблица46[Марка],A9,Таблица46[Площадь]) -> 5.7 | D9: =SUMIF(Таблица467[Марка],A9,Таблица467[Площадь]) -> 216.7 | E9: =SUMIF(Таблица4678[Марка],A9,Таблица4678[Площадь]) -> 86.4 | F9: =SUMIF(Таблица46789[Марка],A9,Таблица46789[Площадь]) -> 153.6 | G9: =SUMIF(Таблица4678910[Марка],A9,Таблица4678910[Площадь]) -> 132.1 | H9: =SUMIF(Таблица467891011[Марка],A9,Таблица467891011[Площадь]) -> 54.2 | I9: =SUM(B9:H9) -> 838.6
A10: ЧН-12 | B10: =SUMIF(Таблица4[Марка],A10,Таблица4[Площадь]) -> 53.7 | C10: =SUMIF(Таблица46[Марка],A10,Таблица46[Площадь]) -> 19.3 | D10: =SUMIF(Таблица467[Марка],A10,Таблица467[Площадь]) -> 18.6 | E10: =SUMIF(Таблица4678[Марка],A10,Таблица4678[Площадь]) -> 19.3 | F10: =SUMIF(Таблица46789[Марка],A10,Таблица46789[Площадь]) -> 16.1 | G10: =SUMIF(Таблица4678910[Марка],A10,Таблица4678910[Площадь]) -> 18.9 | H10: =SUMIF(Таблица467891011[Марка],A10,Таблица467891011[Площадь]) -> 30.4 | I10: =SUM(B10:H10) -> 176.3
A11: ЧН-13 | B11: =SUMIF(Таблица4[Марка],A11,Таблица4[Площадь]) -> 19.5 | C11: =SUMIF(Таблица46[Марка],A11,Таблица46[Площадь]) -> 38 | D11: =SUMIF(Таблица467[Марка],A11,Таблица467[Площадь]) -> 19.5 | E11: =SUMIF(Таблица4678[Марка],A11,Таблица4678[Площадь]) -> 7.4 | F11: =SUMIF(Таблица46789[Марка],A11,Таблица46789[Площадь]) -> 0 | G11: =SUMIF(Таблица4678910[Марка],A11,Таблица4678910[Площадь]) -> 8 | H11: =SUMIF(Таблица467891011[Марка],A11,Таблица467891011[Площадь]) -> 37.2 | I11: =SUM(B11:H11) -> 129.6
A12: ЧН-15 | B12: =SUMIF(Таблица4[Марка],A12,Таблица4[Площадь]) -> 0 | C12: =SUMIF(Таблица46[Марка],A12,Таблица46[Площадь]) -> 40.3 | D12: =SUMIF(Таблица467[Марка],A12,Таблица467[Площадь]) -> 0 | E12: =SUMIF(Таблица4678[Марка],A12,Таблица4678[Площадь]) -> 22.7 | F12: =SUMIF(Таблица46789[Марка],A12,Таблица46789[Площадь]) -> 0 | G12: =SUMIF(Таблица4678910[Марка],A12,Таблица4678910[Площадь]) -> 0 | H12: =SUMIF(Таблица467891011[Марка],A12,Таблица467891011[Площадь]) -> 0 | I12: =SUM(B12:H12) -> 63
A13: ЧН-16 | B13: =SUMIF(Таблица4[Марка],A13,Таблица4[Площадь]) -> 19.9 | C13: =SUMIF(Таблица46[Марка],A13,Таблица46[Площадь]) -> 0 | D13: =SUMIF(Таблица467[Марка],A13,Таблица467[Площадь]) -> 0 | E13: =SUMIF(Таблица4678[Марка],A13,Таблица4678[Площадь]) -> 0 | F13: =SUMIF(Таблица46789[Марка],A13,Таблица46789[Площадь]) -> 0 | G13: =SUMIF(Таблица4678910[Марка],A13,Таблица4678910[Площадь]) -> 0 | H13: =SUMIF(Таблица467891011[Марка],A13,Таблица467891011[Площадь]) -> 0 | I13: =SUM(B13:H13) -> 19.9
A14: ЧН-20 | B14: =SUMIF(Таблица4[Марка],A14,Таблица4[Площадь]) -> 5.7 | C14: =SUMIF(Таблица46[Марка],A14,Таблица46[Площадь]) -> 6.3 | D14: =SUMIF(Таблица467[Марка],A14,Таблица467[Площадь]) -> 0 | E14: =SUMIF(Таблица4678[Марка],A14,Таблица4678[Площадь]) -> 0 | F14: =SUMIF(Таблица46789[Марка],A14,Таблица46789[Площадь]) -> 0 | G14: =SUMIF(Таблица4678910[Марка],A14,Таблица4678910[Площадь]) -> 0 | H14: =SUMIF(Таблица467891011[Марка],A14,Таблица467891011[Площадь]) -> 7 | I14: =SUM(B14:H14) -> 19
... A16: ЧН-23 | B16: =SUMIF(Таблица4[Марка],A16,Таблица4[Площадь]) -> 0 | C16: =SUMIF(Таблица46[Марка],A16,Таблица46[Площадь]) -> 6.9 | D16: =SUMIF(Таблица467[Марка],A16,Таблица467[Площадь]) -> 0 | E16: =SUMIF(Таблица4678[Марка],A16,Таблица4678[Площадь]) -> 1.2 | F16: =SUMIF(Таблица46789[Марка],A16,Таблица46789[Площадь]) -> 0 | G16: =SUMIF(Таблица4678910[Марка],A16,Таблица4678910[Площадь]) -> 0 | H16: =SUMIF(Таблица467891011[Марка],A16,Таблица467891011[Площадь]) -> 2.2 | I16: =SUM(B16:H16) -> 10.3
H17: Сумма: | I17: =SUM(I3:I16) -> 5123.7

Sheet 3.2-Шт Оста
A1: № п.п | B1: Наименование | C1: Описание | D1: Ед. изм. | E1: Объем:
A2: 1 | B2: Оклейка швов сопряжения бетонных и других поверхностей стен, перегородок (газобетон, ПГП, панели АКОТЕК и др.) стеклохолстом | C2: Перед штукатуркой проклеить швы сопряжения разнородных поверхностей (бетон, газобетонный блок, кирпич, ПГП) и углы сеткой стеклотканой, ширина полос проклейки 150+150=300 мм, что составляет 20% от всей площади оштукатуриваемой поверхности. | D2: пог. м | E2: =SUM(E3:E8)/7.61406957765593 -> #REF!
A3: 2 | B3: Штукатурка стен цементным, цементно-песчаным раствором с предварительной огрунтовкой / толщ. до 20 мм / высотой до 4 метров | C3: 1-4 этажи. Штукатурка по ПГП под облицовку плиткой смесью Knauff-флизен 10 мм с грунтовкой Knauff-тиффенгрунд. Тип: ЧН-2, ЧН-9 | D3: м2 | E3: ='3.1.1'!#REF!+'3.1.1'!#REF! -> #REF!
A4: 3 | B4: Штукатурка стен цементным, цементно-песчаным раствором с предварительной огрунтовкой / толщ. от 21 до 40 мм / высотой до 4 метров | C4: 1-4 этажи. Штукатурка по ж/б. Тип: ЧН-1, ЧН-7, ЧН-10 | D4: м2 | E4: ='3.1.1'!I3+'3.1.1'!I7+'3.1.1'!I8 -> 346.8
A5: 4 | B5: Штукатурка стен цементным, цементно-песчаным раствором с предварительной огрунтовкой / толщ. от 21 до 40 мм / высотой до 4 метров | C5: 1-4 этажи. Штукатурка по блоку и кирпичу. Тип: ЧН-4, ЧН-12, ЧН-13, ЧН-15, ЧН-16, ЧН-20, ЧН-21, ЧН-23 | D5: м2 | E5: ='3.1.1'!I4+SUM('3.1.1'!I10:I16) -> 446.9
A6: 5 | B6: Штукатурка стен гипсовыми смесями с предварительной огрунтовкой СКБ / до 20 мм / высотой от 4,01 до 8 метров | C6: 1-4 этажи. Штукатурка гипсовая по ПГП. Тип: ЧН-8 | D6: м2 | E6: ='3.1.1'!#REF! -> #REF!
A7: 6 | B7: Штукатурка стен гипсовыми смесями с предварительной огрунтовкой СКБ / толщ. от 21 до 40 мм / высотой от 4,01 до 8 метров | C7: 1-4 этажи. Штукатурка гипсовая по блоку. Тип: ЧН-6, ЧН-11 | D7: м2 | E7: ='3.1.1'!I6+'3.1.1'!I9 -> 3098.9
A8: 7 | B8: Штукатурка стен гипсовыми смесями с предварительной огрунтовкой СКБ / толщ. от 21 до 40 мм / высотой от 4,01 до 8 метров | C8: 1-4 этажи. Штукатурка гипсовая по ж/б. Тип: ЧН-5 | D8: м2 | E8: ='3.1.1'!I5 -> 1231.1
D9: Сумма | E9: =SUM(E3:E8) -> #REF!

Sheet 3.2.1 Ост
A1: Этаж | B1: 1 | C1: 1 | D1: 2 | E1: 2 | F1: 3 | G1: 3 | H1: 4
A2: Секция | B2: 1 | C2: 3 | D2: 12 | E2: 33 | F2: 14 | G2: 35 | H2: 36 | I2: Итог:
A3: ЧН-1 | B3: =SUMIF(Таблица4[Марка],A3,Таблица4[Площадь]) -> 15 | C3: =SUMIF(Таблица46[Марка],A3,Таблица46[Площадь]) -> 19.8 | D3: =SUMIF(Таблица467[Марка],A3,Таблица467[Площадь]) -> 14.9 | E3: =SUMIF(Таблица4678[Марка],A3,Таблица4678[Площадь]) -> 10.7 | F3: =SUMIF(Таблица46789[Марка],A3,Таблица46789[Площадь]) -> 14.9 | G3: =SUMIF(Таблица4678910[Марка],A3,Таблица4678910[Площадь]) -> 0 | H3: =SUMIF(Таблица467891011[Марка],A3,Таблица467891011[Площадь]) -> 11.7 | I3: =SUM(B3:H3) -> 87
A4: ЧН-2 | B4: =SUMIF(Таблица4[Марка],A4,Таблица4[Площадь]) -> 0 | C4: =SUMIF(Таблица46[Марка],A4,Таблица46[Площадь]) -> 0 | D4: =SUMIF(Таблица467[Марка],A4,Таблица467[Площадь]) -> 0 | E4: =SUMIF(Таблица4678[Марка],A4,Таблица4678[Площадь]) -> 0 | F4: =SUMIF(Таблица46789[Марка],A4,Таблица46789[Площадь]) -> 0 | G4: =SUMIF(Таблица4678910[Марка],A4,Таблица4678910[Площадь]) -> 0 | H4: =SUMIF(Таблица467891011[Марка],A4,Таблица467891011[Площадь]) -> 0 | I4: =SUM(B4:H4) -> 0
A5: ЧН-4 | B5: =SUMIF(Таблица4[Марка],A5,Таблица4[Площадь]) -> 6.1 | C5: =SUMIF(Таблица46[Марка],A5,Таблица46[Площадь]) -> 0 | D5: =SUMIF(Таблица467[Марка],A5,Таблица467[Площадь]) -> 6.1 | E5: =SUMIF(Таблица4678[Марка],A5,Таблица4678[Площадь]) -> 0 | F5: =SUMIF(Таблица46789[Марка],A5,Таблица46789[Площадь]) -> 0 | G5: =SUMIF(Таблица4678910[Марка],A5,Таблица4678910[Площадь]) -> 0 | H5: =SUMIF(Таблица467891011[Марка],A5,Таблица467891011[Площадь]) -> 0 | I5: =SUM(B5:H5) -> 12.2
A6: ЧН-5 | B6: =SUMIF(Таблица4[Марка],A6,Таблица4[Площадь]) -> 261.3 | C6: =SUMIF(Таблица46[Марка],A6,Таблица46[Площадь]) -> 0 | D6: =SUMIF(Таблица467[Марка],A6,Таблица467[Площадь]) -> 352.5 | E6: =SUMIF(Таблица4678[Марка],A6,Таблица4678[Площадь]) -> 93.2 | F6: =SUMIF(Таблица46789[Марка],A6,Таблица46789[Площадь]) -> 143.2 | G6: =SUMIF(Таблица4678910[Марка],A6,Таблица4678910[Площадь]) -> 155.8 | H6: =SUMIF(Таблица467891011[Марка],A6,Таблица467891011[Площадь]) -> 225.1 | I6: =SUM(B6:H6) -> 1231.1
A7: ЧН-6 | B7: =SUMIF(Таблица4[Марка],A7,Таблица4[Площадь]) -> 622.4 | C7: =SUMIF(Таблица46[Марка],A7,Таблица46[Площадь]) -> 10.6 | D7: =SUMIF(Таблица467[Марка],A7,Таблица467[Площадь]) -> 554.8 | E7: =SUMIF(Таблица4678[Марка],A7,Таблица4678[Площадь]) -> 483.4 | F7: =SUMIF(Таблица46789[Марка],A7,Таблица46789[Площадь]) -> 92.8 | G7: =SUMIF(Таблица4678910[Марка],A7,Таблица4678910[Площадь]) -> 344 | H7: =SUMIF(Таблица467891011[Марка],A7,Таблица467891011[Площадь]) -> 152.3 | I7: =SUM(B7:H7) -> 2260.3
A8: ЧН-7 | B8: =SUMIF(Таблица4[Марка],A8,Таблица4[Площадь]) -> 55.6 | C8: =SUMIF(Таблица46[Марка],A8,Таблица46[Площадь]) -> 30.9 | D8: =SUMIF(Таблица467[Марка],A8,Таблица467[Площадь]) -> 0 | E8: =SUMIF(Таблица4678[Марка],A8,Таблица4678[Площадь]) -> 26.7 | F8: =SUMIF(Таблица46789[Марка],A8,Таблица46789[Площадь]) -> 0 | G8: =SUMIF(Таблица4678910[Марка],A8,Таблица4678910[Площадь]) -> 1.8 | H8: =SUMIF(Таблица467891011[Марка],A8,Таблица467891011[Площадь]) -> 6.7 | I8: =SUM(B8:H8) -> 121.7
A9: ЧН-8 | B9: =SUMIF(Таблица4[Марка],A9,Таблица4[Площадь]) -> 0 | C9: =SUMIF(Таблица46[Марка],A9,Таблица46[Площадь]) -> 0 | D9: =SUMIF(Таблица467[Марка],A9,Таблица467[Площадь]) -> 0 | E9: =SUMIF(Таблица4678[Марка],A9,Таблица4678[Площадь]) -> 0 | F9: =SUMIF(Таблица46789[Марка],A9,Таблица46789[Площадь]) -> 0 | G9: =SUMIF(Таблица4678910[Марка],A9,Таблица4678910[Площадь]) -> 0 | H9: =SUMIF(Таблица467891011[Марка],A9,Таблица467891011[Площадь]) -> 0 | I9: =SUM(B9:H9) -> 0
A10: ЧН-9 | B10: =SUMIF(Таблица4[Марка],A10,Таблица4[Площадь]) -> 0 | C10: =SUMIF(Таблица46[Марка],A10,Таблица46[Площадь]) -> 0 | D10: =SUMIF(Таблица467[Марка],A10,Таблица467[Площадь]) -> 0 | E10: =SUMIF(Таблица4678[Марка],A10,Таблица4678[Площадь]) -> 0 | F10: =SUMIF(Таблица46789[Марка],A10,Таблица46789[Площадь]) -> 0 | G10: =SUMIF(Таблица4678910[Марка],A10,Таблица4678910[Площадь]) -> 0 | H10: =SUMIF(Таблица467891011[Марка],A10,Таблица467891011[Площадь]) -> 0 | I10: =SUM(B10:H10) -> 0
A11: ЧН-10 | B11: =SUMIF(Таблица4[Марка],A11,Таблица4[Площадь]) -> 3.1 | C11: =SUMIF(Таблица46[Марка],A11,Таблица46[Площадь]) -> 31.4 | D11: =SUMIF(Таблица467[Марка],A11,Таблица467[Площадь]) -> 3.1 | E11: =SUMIF(Таблица4678[Марка],A11,Таблица4678[Площадь]) -> 28.4 | F11: =SUMIF(Таблица46789[Марка],A11,Таблица46789[Площадь]) -> 0 | G11: =SUMIF(Таблица4678910[Марка],A11,Таблица4678910[Площадь]) -> 9.9 | H11: =SUMIF(Таблица467891011[Марка],A11,Таблица467891011[Площадь]) -> 62.2 | I11: =SUM(B11:H11) -> 138.1
A12: ЧН-11 | B12: =SUMIF(Таблица4[Марка],A12,Таблица4[Площадь]) -> 189.9 | C12: =SUMIF(Таблица46[Марка],A12,Таблица46[Площадь]) -> 5.7 | D12: =SUMIF(Таблица467[Марка],A12,Таблица467[Площадь]) -> 216.7 | E12: =SUMIF(Таблица4678[Марка],A12,Таблица4678[Площадь]) -> 86.4 | F12: =SUMIF(Таблица46789[Марка],A12,Таблица46789[Площадь]) -> 153.6 | G12: =SUMIF(Таблица4678910[Марка],A12,Таблица4678910[Площадь]) -> 132.1 | H12: =SUMIF(Таблица467891011[Марка],A12,Таблица467891011[Площадь]) -> 54.2 | I12: =SUM(B12:H12) -> 838.6
A13: ЧН-12 | B13: =SUMIF(Таблица4[Марка],A13,Таблица4[Площадь]) -> 53.7 | C13: =SUMIF(Таблица46[Марка],A13,Таблица46[Площадь]) -> 19.3 | D13: =SUMIF(Таблица467[Марка],A13,Таблица467[Площадь]) -> 18.6 | E13: =SUMIF(Таблица4678[Марка],A13,Таблица4678[Площадь]) -> 19.3 | F13: =SUMIF(Таблица46789[Марка],A13,Таблица46789[Площадь]) -> 16.1 | G13: =SUMIF(Таблица4678910[Марка],A13,Таблица4678910[Площадь]) -> 18.9 | H13: =SUMIF(Таблица467891011[Марка],A13,Таблица467891011[Площадь]) -> 30.4 | I13: =SUM(B13:H13) -> 176.3
A14: ЧН-13 | B14: =SUMIF(Таблица4[Марка],A14,Таблица4[Площадь]) -> 19.5 | C14: =SUMIF(Таблица46[Марка],A14,Таблица46[Площадь]) -> 38 | D14: =SUMIF(Таблица467[Марка],A14,Таблица467[Площадь]) -> 19.5 | E14: =SUMIF(Таблица4678[Марка],A14,Таблица4678[Площадь]) -> 7.4 | F14: =SUMIF(Таблица46789[Марка],A14,Таблица46789[Площадь]) -> 0 | G14: =SUMIF(Таблица4678910[Марка],A14,Таблица4678910[Площадь]) -> 8 | H14: =SUMIF(Таблица467891011[Марка],A14,Таблица467891011[Площадь]) -> 37.2 | I14: =SUM(B14:H14) -> 129.6
... A19: ЧН-23 | B19: =SUMIF(Таблица4[Марка],A19,Таблица4[Площадь]) -> 0 | C19: =SUMIF(Таблица46[Марка],A19,Таблица46[Площадь]) -> 6.9 | D19: =SUMIF(Таблица467[Марка],A19,Таблица467[Площадь]) -> 0 | E19: =SUMIF(Таблица4678[Марка],A19,Таблица4678[Площадь]) -> 1.2 | F19: =SUMIF(Таблица46789[Марка],A19,Таблица46789[Площадь]) -> 0 | G19: =SUMIF(Таблица4678910[Марка],A19,Таблица4678910[Площадь]) -> 0 | H19: =SUMIF(Таблица467891011[Марка],A19,Таблица467891011[Площадь]) -> 2.2 | I19: =SUM(B19:H19) -> 10.3
H20: Сумма: | I20: =SUM(I3:I19) -> 5123.7
K22: Этаж | L22: Секция | M22: № помеще ния | N22: Марка | O22: Площадь | P22: Примечание
K23: 1 | L23: 1 | M23: 1001 | N23: ЧН-8 | O23: 15 | P23: Отделка перегородок ПГП
K24: 1 | L24: 1 | M24: 1002 | N24: ЧН-8 | O24: 3.8 | P24: Отделка перегородок ПГП
K25: 1 | L25: 1 | M25: 1003 | N25: ЧН-8 | O25: 3.8 | P25: Отделка перегородок ПГП
K26: 1 | L26: 1 | M26: 1005 | N26: ЧН-8 | O26: 3.6 | P26: Отделка перегородок ПГП
K27: 1 | L27: 1 | M27: 1007 | N27: ЧН-8 | O27: 7.3 | P27: Отделка перегородок ПГП
K28: 1 | L28: 1 | M28: 1010 | N28: ЧН-2 | O28: 7.9 | P28: Отделка перегородок ПГП
K29: 1 | L29: 1 | M29: 1012 | N29: ЧН-2 | O29: 39.8 | P29: Отделка перегородок ПГП
K30: 1 | L30: 1 | M30: 1013 | N30: ЧН-9 | O30: 5.9 | P30: Отделка перегородок ПГП
K31: 1 | L31: 1 | M31: 1014 | N31: ЧН-2 | O31: 18 | P31: Отделка перегородок ПГП
K32: 2 | L32: 1 | M32: 2001 | N32: ЧН-8 | O32: 13.8 | P32: Отделка перегородок ПГП
K33: 2 | L33: 1 | M33: 2002 | N33: ЧН-8 | O33: 3.9 | P33: Отделка перегородок ПГП
K34: 2 | L34: 1 | M34: 2003 | N34: ЧН-8 | O34: 3.9 | P34: Отделка перегородок ПГП
... K62: 4 | L62: 3 | M62: 4017 | N62: ЧН-9 | O62: 5.2 | P62: Отделка перегородок ПГП

Sheet 3.1.2-Шт1э1с
A1: Этаж | B1: Секция | C1: № помеще ния | D1: Марка | E1: Площадь | F1: Примечание
A2: 1 | B2: 1 | C2: 1001 | D2: ЧН-11 | E2: 12.6 | F2: Штукатурка гипсовая по кирпичу
A3: 1 | B3: 1 | C3: 1001 | D3: ЧН-6 | E3: 55.1 | F3: Штукатурка гипсовая по блоку
A4: 1 | B4: 1 | C4: 1001 | D4: ЧН-5 | E4: 40.4 | F4: Штукатурка гипсовая по ж/б
A5: 1 | B5: 1 | C5: 1002 | D5: ЧН-11 | E5: 6.2 | F5: Штукатурка гипсовая по кирпичу
A6: 1 | B6: 1 | C6: 1002 | D6: ЧН-6 | E6: 81.3 | F6: Штукатурка гипсовая по блоку
A7: 1 | B7: 1 | C7: 1002 | D7: ЧН-5 | E7: 10 | F7: Штукатурка гипсовая по ж/б
A8: 1 | B8: 1 | C8: 1003 | D8: ЧН-11 | E8: 7.8 | F8: Штукатурка гипсовая по кирпичу
A9: 1 | B9: 1 | C9: 1003 | D9: ЧН-6 | E9: 59.9 | F9: Штукатурка гипсовая по блоку
A10: 1 | B10: 1 | C10: 1003 | D10: ЧН-5 | E10: 31.7 | F10: Штукатурка гипсовая по ж/б
A11: 1 | B11: 1 | C11: 1005 | D11: ЧН-11 | E11: 3.4 | F11: Штукатурка гипсовая по кирпичу
A12: 1 | B12: 1 | C12: 1005 | D12: ЧН-6 | E12: 73 | F12: Штукатурка гипсовая по блоку
A13: 1 | B13: 1 | C13: 1005 | D13: ЧН-5 | E13: 8.5 | F13: Штукатурка гипсовая по ж/б
... A37: 1 | B37: 1 | C37: 1016 | D37: ЧН-5 | E37: 45.5 | F37: Штукатурка гипсовая по ж/б

Sheet 3.1.3-Шт1э3с
A1: Этаж | B1: Секция | C1: № помеще ния | D1: Марка | E1: Площадь | F1: Примечание
A2: 1 | B2: 3 | C2: 1087 | D2: ЧН-20 | E2: 2.1 | F2: Штукатурка по блоку, Кирпича
A3: 1 | B3: 3 | C3: 1087 | D3: ЧН-13 | E3: 3.2 | F3: Штукатурка по блоку
A4: 1 | B4: 3 | C4: 1087 | D4: ЧН-15 | E4: 14.5 | F4: Штукатурка по блоку, Кирпича
A5: 1 | B5: 3 | C5: 1087 | D5: ЧН-1 | E5: 9.2 | F5: Штукатурка по ж/б
A6: 1 | B6: 3 | C6: 1088 | D6: ЧН-13 | E6: 24.2 | F6: Штукатурка по блоку
A7: 1 | B7: 3 | C7: 1088 | D7: ЧН-23 | E7: 4.8 | F7: Штукатурка по блоку, Кирпича. Мокрые помещения
A8: 1 | B8: 3 | C8: 1088 | D8: ЧН-7 | E8: 4.2 | F8: Штукатурка по ж/б
A9: 1 | B9: 3 | C9: 1088 | D9: ЧН-10 | E9: 23.3 | F9: Штукатурка по ж/б
A10: 1 | B10: 3 | C10: 1089 | D10: ЧН-12 | E10: 8.9 | F10: Штукатурка по кирпичу
A11: 1 | B11: 3 | C11: 1089 | D11: ЧН-21 | E11: 1.6 | F11: Штукатурка по кирпичу. Выше уровня плитки
A12: 1 | B12: 3 | C12: 1089 | D12: ЧН-20 | E12: 3.2 | F12: Штукатурка по блоку, Кирпича
A13: 1 | B13: 3 | C13: 1089 | D13: ЧН-13 | E13: 4.3 | F13: Штукатурка по блоку
... A29: 1 | B29: 3 | C29: 1092 | D29: ЧН-10 | E29: 8.1 | F29: Штукатурка по ж/б

Sheet 3.1.4-Шт2э1с
A1: Этаж | B1: Секция | C1: № помеще ния | D1: Марка | E1: Площадь | F1: Примечание
A2: 2 | B2: 1 | C2: 2001 | D2: ЧН-11 | E2: 20 | F2: Штукатурка по кирпичу
A3: 2 | B3: 1 | C3: 2001 | D3: ЧН-6 | E3: 45.3 | F3: Штукатурка по блоку
A4: 2 | B4: 1 | C4: 2001 | D4: ЧН-5 | E4: 36.4 | F4: Штукатурка гипсовая по ж/б
A5: 2 | B5: 1 | C5: 2002 | D5: ЧН-11 | E5: 10.9 | F5: Штукатурка по кирпичу
A6: 2 | B6: 1 | C6: 2002 | D6: ЧН-6 | E6: 82.6 | F6: Штукатурка по блоку
A7: 2 | B7: 1 | C7: 2002 | D7: ЧН-5 | E7: 8.6 | F7: Штукатурка гипсовая по ж/б
A8: 2 | B8: 1 | C8: 2003 | D8: ЧН-11 | E8: 12.3 | F8: Штукатурка по кирпичу
A9: 2 | B9: 1 | C9: 2003 | D9: ЧН-6 | E9: 26.2 | F9: Штукатурка по блоку
A10: 2 | B10: 1 | C10: 2003 | D10: ЧН-5 | E10: 31.5 | F10: Штукатурка гипсовая по ж/б
A11: 2 | B11: 1 | C11: 2004 | D11: ЧН-11 | E11: 10.9 | F11: Штукатурка по кирпичу
A12: 2 | B12: 1 | C12: 2004 | D12: ЧН-6 | E12: 55.5 | F12: Штукатурка по блоку
A13: 2 | B13: 1 | C13: 2004 | D13: ЧН-5 | E13: 33.8 | F13: Штукатурка гипсовая по ж/б
... A31: 2 | B31: 1 | C31: 2015 | D31: ЧН-5 | E31: 45.8 | F31: Штукатурка гипсовая по ж/б

Sheet 3.1.5-Шт2э3с
A1: Этаж | B1: Секция | C1: № помеще ния | D1: Марка | E1: Площадь | F1: Примечание
A2: 2 | B2: 3 | C2: 2034 | D2: ЧН-11 | E2: 15.6 | F2: Штукатурка по кирпичу
A3: 2 | B3: 3 | C3: 2034 | D3: ЧН-6 | E3: 95.5 | F3: Штукатурка по блоку
A4: 2 | B4: 3 | C4: 2034 | D4: ЧН-5 | E4: 8.3 | F4: Штукатурка гипсовая по ж/б
A5: 2 | B5: 3 | C5: 2035 | D5: ЧН-11 | E5: 20.3 | F5: Штукатурка по кирпичу
A6: 2 | B6: 3 | C6: 2035 | D6: ЧН-6 | E6: 42.6 | F6: Штукатурка по блоку
A7: 2 | B7: 3 | C7: 2035 | D7: ЧН-5 | E7: 1.4 | F7: Штукатурка гипсовая по ж/б
A8: 2 | B8: 3 | C8: 2042 | D8: ЧН-15 | E8: 22.7 | F8: Штукатурка по блоку, Кирпича
A9: 2 | B9: 3 | C9: 2042 | D9: ЧН-7 | E9: 1.9 | F9: Штукатурка по ж/б.
A10: 2 | B10: 3 | C10: 2042 | D10: ЧН-1 | E10: 10.7 | F10: Штукатурка по ж/б.
A11: 2 | B11: 3 | C11: 2043 | D11: ЧН-6 | E11: 17.8 | F11: Штукатурка по блоку
A12: 2 | B12: 3 | C12: 2043 | D12: ЧН-10 | E12: 9.3 | F12: Штукатурка по ж/б.
A13: 2 | B13: 3 | C13: 2045 | D13: ЧН-12 | E13: 8.9 | F13: Штукатурка по кирпичу
... A25: 2 | B25: 3 | C25: 2049 | D25: ЧН-10 | E25: 8.1 | F25: Штукатурка по ж/б.
A26: 2 | B26: 3 | C26: 2.047а | D26: ЧН-11 | E26: 30.2 | F26: Штукатурка по кирпичу
A27: 2 | B27: 3 | C27: 2.047а | D27: ЧН-6 | E27: 189.4 | F27: Штукатурка по блоку
A28: 2 | B28: 3 | C28: 2.047а | D28: ЧН-5 | E28: 29.8 | F28: Штукатурка гипсовая по ж/б
A29: 2 | B29: 3 | C29: 2.047б | D29: ЧН-11 | E29: 14.6 | F29: Штукатурка по кирпичу
A30: 2 | B30: 3 | C30: 2.047б | D30: ЧН-6 | E30: 42.6 | F30: Штукатурка по блоку
A31: 2 | B31: 3 | C31: 2.047б | D31: ЧН-5 | E31: 53.7 | F31: Штукатурка гипсовая по ж/б

Sheet 3.1.6-Шт3э1с
A1: Этаж | B1: Секция | C1: № помеще ния | D1: Марка | E1: Площадь | F1: Примечание
A2: 3 | B2: 1 | C2: 3011 | D2: ЧН-12 | E2: 16.1 | F2: Штукатурка по кирпичу
A3: 3 | B3: 1 | C3: 3011 | D3: ЧН-1 | E3: 14.9 | F3: Штукатурка по ж/б.
A4: 3 | B4: 1 | C4: 3016 | D4: ЧН-11 | E4: 54.6 | F4: Штукатурка по кирпичу
A5: 3 | B5: 1 | C5: 3016 | D5: ЧН-6 | E5: 25.8 | F5: Штукатурка по блоку
A6: 3 | B6: 1 | C6: 3016 | D6: ЧН-5 | E6: 97 | F6: Штукатурка гипсовая по ж/б
A7: 3 | B7: 1 | C7: 3017 | D7: ЧН-11 | E7: 99 | F7: Штукатурка по кирпичу
A8: 3 | B8: 1 | C8: 3017 | D8: ЧН-6 | E8: 67 | F8: Штукатурка по блоку
A9: 3 | B9: 1 | C9: 3017 | D9: ЧН-5 | E9: 46.2 | F9: Штукатурка гипсовая по ж/б

Sheet 3.1.7-Шт3э3с
A1: Этаж | B1: Секция | C1: № помеще ния | D1: Марка | E1: Площадь | F1: Примечание
A2: 3 | B2: 3 | C2: 3040 | D2: ЧН-11 | E2: 19.9 | F2: Штукатурка гипсовая по кирпичу
A3: 3 | B3: 3 | C3: 3040 | D3: ЧН-6 | E3: 82.3 | F3: Штукатурка гипсовая по блоку
A4: 3 | B4: 3 | C4: 3040 | D4: ЧН-5 | E4: 4.5 | F4: Штукатурка гипсовая по ж/б
A5: 3 | B5: 3 | C5: 3041 | D5: ЧН-11 | E5: 25.1 | F5: Штукатурка гипсовая по кирпичу
A6: 3 | B6: 3 | C6: 3041 | D6: ЧН-6 | E6: 36 | F6: Штукатурка гипсовая по блоку
A7: 3 | B7: 3 | C7: 3041 | D7: ЧН-5 | E7: 1.5 | F7: Штукатурка гипсовая по ж/б
A8: 3 | B8: 3 | C8: 3046 | D8: ЧН-11 | E8: 21.8 | F8: Штукатурка гипсовая по кирпичу
A9: 3 | B9: 3 | C9: 3046 | D9: ЧН-6 | E9: 91.8 | F9: Штукатурка гипсовая по блоку
A10: 3 | B10: 3 | C10: 3046 | D10: ЧН-5 | E10: 10.7 | F10: Штукатурка гипсовая по ж/б
A11: 3 | B11: 3 | C11: 3047 | D11: ЧН-11 | E11: 16.5 | F11: Штукатурка гипсовая по кирпичу
A12: 3 | B12: 3 | C12: 3047 | D12: ЧН-6 | E12: 105.1 | F12: Штукатурка гипсовая по блоку
A13: 3 | B13: 3 | C13: 3047 | D13: ЧН-5 | E13: 43.3 | F13: Штукатурка гипсовая по ж/б
... A19: 3 | B19: 3 | C19: 3053 | D19: ЧН-13 | E19: 4.3 | F19: Штукатурка по блоку
A20: 3 | B20: 3 | C20: 3.047а | D20: ЧН-11 | E20: 34.2 | F20: Штукатурка гипсовая по кирпичу
A21: 3 | B21: 3 | C21: 3.047а | D21: ЧН-6 | E21: 11.6 | F21: Штукатурка гипсовая по блоку
A22: 3 | B22: 3 | C22: 3.047а | D22: ЧН-5 | E22: 40 | F22: Штукатурка гипсовая по ж/б
A23: 3 | B23: 3 | C23: 3.047б | D23: ЧН-11 | E23: 14.6 | F23: Штукатурка гипсовая по кирпичу
A24: 3 | B24: 3 | C24: 3.047б | D24: ЧН-6 | E24: 17.2 | F24: Штукатурка гипсовая по блоку
A25: 3 | B25: 3 | C25: 3.047б | D25: ЧН-5 | E25: 55.8 | F25: Штукатурка гипсовая по ж/б

Sheet 3.1.8-Шт4э3с
A1: Этаж | B1: Секция | C1: № помеще ния | D1: Марка | E1: Площадь | F1: Примечание
A2: 4 | B2: 3 | C2: 4010 | D2: ЧН-11 | E2: 31 | F2: Штукатурка гипсовая по кирпичу
A3: 4 | B3: 3 | C3: 4010 | D3: ЧН-6 | E3: 107 | F3: Штукатурка гипсовая по блоку
A4: 4 | B4: 3 | C4: 4010 | D4: ЧН-5 | E4: 117.4 | F4: Штукатурка гипсовая по ж/б
A5: 4 | B5: 3 | C5: 4011 | D5: ЧН-20 | E5: 2.1 | F5: Штукатурка по блоку, Кирпича
A6: 4 | B6: 3 | C6: 4011 | D6: ЧН-13 | E6: 3.1 | F6: Штукатурка по блоку
A7: 4 | B7: 3 | C7: 4011 | D7: ЧН-10 | E7: 26.8 | F7: Штукатурка по ж/б
A8: 4 | B8: 3 | C8: 4012 | D8: ЧН-12 | E8: 10 | F8: Штукатурка по кирпичу
A9: 4 | B9: 3 | C9: 4012 | D9: ЧН-21 | E9: 1.8 | F9: Штукатурка по кирпичу. Выше уровня плитки
A10: 4 | B10: 3 | C10: 4012 | D10: ЧН-20 | E10: 0.9 | F10: Штукатурка по блоку, Кирпича
A11: 4 | B11: 3 | C11: 4012 | D11: ЧН-13 | E11: 2.4 | F11: Штукатурка по блоку
A12: 4 | B12: 3 | C12: 4012 | D12: ЧН-23 | E12: 0.9 | F12: Штукатурка по блоку, Кирпича. Мокрые помещения
A13: 4 | B13: 3 | C13: 4012 | D13: ЧН-7 | E13: 1.8 | F13: Штукатурка по ж/б
... A32: 4 | B32: 3 | C32: 4017 | D32: ЧН-10 | E32: 13.2 | F32: Штукатурка по ж/б
A33: 4 | B33: 3 | C33: 4.010а | D33: ЧН-11 | E33: 10.9 | F33: Штукатурка гипсовая по кирпичу
A34: 4 | B34: 3 | C34: 4.010а | D34: ЧН-6 | E34: 17.4 | F34: Штукатурка гипсовая по блоку
A35: 4 | B35: 3 | C35: 4.010а | D35: ЧН-5 | E35: 51.3 | F35: Штукатурка гипсовая по ж/б
