Workbook

Sheet Table 1
A1: Ведомость отделки помещений подвала
A2: Ном ер пом еще ния | B2: Наименование помещения | C2: СТЕНЫ ИЛИ ПЕРЕГОРОДКИ | M2: Основной тип потолка | O2: ПЛИНТУС | Q2: Примечание
C3: Железобетон | E3: Кирпич | G3: Газобетон | I3: Утеплитель | K3: Финишный слой | M3: Вид отделки | N3: Площадь, м² | O3: Вид отделки | P3: м.п.
C4: Вид отделки | D4: Площадь, м² | E4: Вид отделки | F4: Площадь, м² | G4: Вид отделки | H4: Площадь, м² | I4: Вид отделки | J4: Площадь, м² | K4: Вид отделки | L4: Площадь, м²
A5: 0.01 | B5: Лестничная клетка №1 | C5: - грунтовка "Бетоноконтакт"; - штукатурка цементно-песчаным раствором М100 (армированная стекловолоконной или пластиковой сеткой); - грунтовка глубокого проникновения; - шпатлёвка; - грунтовка глубокого проникновения δ = 25 мм | D5: 64 | E5: - грунтовка глубокого проникновения; - штукатурка цементно-песчаным раствором М100 (армированная стекловолоконной или пластиковой сеткой); - грунтовка глубокого проникновения; - шпатлёвка; - грунтовка глубокого проникновения δ = 25 мм | F5: 25.4 | G5: - | H5: 0 | I5: - | J5: 0 | K5: см. раздел АИ | L5: 89.4 | M5: - затирка; - грунтовка "Бетоноконтакт "; - шпатлёвка; - грунтовка глубокого проникновения δ = 5 мм | N5: 10.7 | O5: см. раздел АИ | P5: 28.8 | Q5: -
A6: 0.02 | B6: Венткамера | C6: - грунтовка "Бетоноконтакт"; - штукатурка цементно-песчаным раствором М100 (армированная стекловолоконной или пластиковой сеткой); - грунтовка глубокого проникновения; - шпатлёвка; - грунтовка глубокого проникновения δ = 25 мм | D6: 21.9 | E6: - грунтовка глубокого проникновения; - штукатурка цементно-песчаным раствором М100 (армированная стекловолоконной или пластиковой сеткой); - грунтовка глубокого проникновения; - шпатлёвка; - грунтовка глубокого проникновения δ = 25 мм | F6: 31.9 | G6: - | H6: 0 | I6: - штукатурка цементно-песчаным раствором М100 (армированная стекловолоконной или пластиковой сеткой); - грунтовка глубокого проникновения; - шпатлёвка; - грунтовка глубокого проникновения δ = 25 мм | J6: 79.7 | K6: см. раздел АИ | L6: 133.5 | M6: - затирка; - грунтовка "Бетоноконтакт "; - шпатлёвка; - грунтовка глубокого проникновения δ = 5 мм | N6: 57.6 | O6: см. раздел АИ | P6: 42.8 | Q6: -
A7: 0.03 | B7: Коридор | C7: - грунтовка "Бетоноконтакт"; - штукатурка цементно-песчаным раствором М100 (армированная стекловолоконной или пластиковой сеткой); - грунтовка глубокого проникновения; - шпатлёвка; - грунтовка глубокого проникновения δ = 25 мм | D7: 140.9 | E7: - грунтовка глубокого проникновения; - штукатурка цементно-песчаным раствором М100 (армированная стекловолоконной или пластиковой сеткой); - грунтовка глубокого проникновения; - шпатлёвка; - грунтовка глубокого проникновения δ = 25 мм | F7: 221.4 | G7: - пропитка гидрофобизирующим составом BOSTIK SMP; - грунтовка глубокого проникновения; - штукатурка цементно-песчаным раствором М100 (армированная стекловолоконной или пластиковой сеткой); - грунтовка глубокого проникновения; - шпатлёвка; - грунтовка глубокого проникновения δ = 25 мм | H7: 5.2 | I7: - | J7: 0 | K7: см. раздел АИ | L7: 367.5 | M7: - затирка; - грунтовка "Бетоноконтакт "; - шпатлёвка; - грунтовка глубокого проникновения δ = 5 мм | N7: 164.4 | O7: см. раздел АИ | P7: 116.4 | Q7: -
A8: 0.04 | B8: Насосная | C8: - грунтовка "Бетоноконтакт"; - штукатурка цементно-песчаным раствором М100 (армированная стекловолоконной или пластиковой сеткой); - грунтовка глубокого проникновения; - шпатлёвка; - грунтовка глубокого проникновения δ = 25 мм | D8: 126.5 | E8: - грунтовка глубокого проникновения; - штукатурка цементно-песчаным раствором М100 (армированная стекловолоконной или пластиковой сеткой); - грунтовка глубокого проникновения; - шпатлёвка; - грунтовка глубокого проникновения δ = 25 мм | F8: 4.9 | G8: - | H8: 0 | I8: - | J8: 0 | K8: см. раздел АИ | L8: 131.3 | M8: - затирка; - грунтовка "Бетоноконтакт "; - шпатлёвка; - грунтовка глубокого проникновения δ = 5 мм | N8: 58.2 | O8: см. раздел АИ | P8: 42.1 | Q8: -
A9: 0.05 | B9: Венткамера | C9: - грунтовка "Бетоноконтакт"; - штукатурка цементно-песчаным раствором М100 (армированная стекловолоконной или пластиковой сеткой); - грунтовка глубокого проникновения; - шпатлёвка; - грунтовка глубокого проникновения δ = 25 мм | D9: 37.7 | E9: - грунтовка глубокого проникновения; - штукатурка цементно-песчаным раствором М100 (армированная стекловолоконной или пластиковой сеткой); - грунтовка глубокого проникновения; - шпатлёвка; - грунтовка глубокого проникновения δ = 25 мм | F9: 29.7 | G9: - | H9: 0 | I9: - | J9: 0 | K9: см. раздел АИ | L9: 67.4 | M9: - затирка; - грунтовка "Бетоноконтакт "; - шпатлёвка; - грунтовка глубокого проникновения δ = 5 мм | N9: 54.2 | O9: см. раздел АИ | P9: 30.1 | Q9: -
A10: 0.06 | B10: ИТП | C10: - грунтовка "Бетоноконтакт"; - штукатурка цементно-песчаным раствором М100 (армированная стекловолоконной или пластиковой сеткой); - грунтовка глубокого проникновения; - шпатлёвка; - грунтовка глубокого проникновения δ = 25 мм | D10: 57.5 | E10: - грунтовка глубокого проникновения; - штукатурка цементно-песчаным раствором М100 (армированная стекловолоконной или пластиковой сеткой); - грунтовка глубокого проникновения; - шпатлёвка; - грунтовка глубокого проникновения δ = 25 мм | F10: 72.2 | G10: - | H10: 0 | I10: - | J10: 0 | K10: см. раздел АИ | L10: 129.7 | M10: - затирка; - грунтовка "Бетоноконтакт "; - шпатлёвка; - грунтовка глубокого проникновения δ = 5 мм | N10: 99.5 | O10: см. раздел АИ | P10: 41.7 | Q10: -
A11: 0.07 | B11: Венткамера | C11: - | D11: 0 | E11: - грунтовка глубокого проникновения; - штукатурка цементно-песчаным раствором М100 (армированная стекловолоконной или пластиковой сеткой); - грунтовка глубокого проникновения; - шпатлёвка; - грунтовка глубокого проникновения δ = 25 мм | F11: 31.4 | G11: - | H11: 0 | I11: - штукатурка цементно-песчаным раствором М100 (армированная стекловолоконной или пластиковой сеткой); - грунтовка глубокого проникновения; - шпатлёвка; - грунтовка глубокого проникновения δ = 25 мм | J11: 64.4 | K11: см. раздел АИ | L11: 95.8 | M11: - затирка; - грунтовка "Бетоноконтакт "; - шпатлёвка; - грунтовка глубокого проникновения δ = 5 мм | N11: 40.7 | O11: см. раздел АИ | P11: 31.4 | Q11: -
A12: 0.08 | B12: Помещение CC1 | C12: - грунтовка "Бетоноконтакт"; - штукатурка цементно-песчаным раствором М100 (армированная стекловолоконной или пластиковой сеткой); - грунтовка глубокого проникновения; - шпатлёвка; - грунтовка глубокого проникновения δ = 25 мм | D12: 44.3 | E12: - грунтовка глубокого проникновения; - штукатурка цементно-песчаным раствором М100 (армированная стекловолоконной или пластиковой сеткой); - грунтовка глубокого проникновения; - шпатлёвка; - грунтовка глубокого проникновения δ = 25 мм | F12: 23.1 | G12: см. раздел АИ | H12: 67.4 | M12: - затирка; - грунтовка "Бетоноконтакт "; - шпатлёвка; - грунтовка глубокого проникновения δ = 5 мм | N12: 24.5 | O12: см. раздел АИ | P12: 21.4 | Q12: -
A13: 0.09 | B13: Помещение для прокладки коммуникаций | C13: - обеспыливание поверхности ж/б грунтовкой глубокого проникновения Политакс 88PU 2/50 (или аналог) | D13: 233.1 | E13: - грунтовка глубокого проникновения; - штукатурка цементно-песчаным раствором М100 (армированная стекловолоконной или пластиковой сеткой); - грунтовка глубокого проникновения; - шпатлёвка; - грунтовка глубокого проникновения δ = 25 мм | F13: 72.4 | G13: - | H13: 305.5 | M13: - обеспыливание | N13: 156.9 | O13: - | P13: 98.5 | Q13: -
A14: 0.10 | B14: Помещение для прокладки коммуникаций | C14: - обеспыливание поверхности ж/б грунтовкой глубокого проникновения Политакс 88PU 2/50 (или аналог) | D14: 387.1 | E14: - грунтовка глубокого проникновения; - штукатурка цементно-песчаным раствором М100 (армированная стекловолоконной или пластиковой сеткой); - грунтовка глубокого проникновения; - шпатлёвка; - грунтовка глубокого проникновения δ = 25 мм | F14: 31.8 | G14: - | H14: 419 | M14: - обеспыливание | N14: 243.4 | O14: - | P14: 135.5 | Q14: -
A15: 0.11 | B15: Помещение для прокладки коммуникаций | C15: - обеспыливание поверхности ж/б грунтовкой глубокого проникновения Политакс 88PU 2/50 (или аналог) | D15: 87.2 | E15: - грунтовка глубокого проникновения; - штукатурка цементно-песчаным раствором М100 (армированная стекловолоконной или пластиковой сеткой); - грунтовка глубокого проникновения; - шпатлёвка; - грунтовка глубокого проникновения δ = 25 мм | F15: 11.1 | G15: - | H15: 98.3 | M15: - обеспыливание | N15: 64.3 | O15: - | P15: 32.3 | Q15: -
A16: 0.12 | B16: Лестничная клетка №5 | C16: - грунтовка "Бетоноконтакт"; - штукатурка цементно-песчаным раствором М100 (армированная стекловолоконной или пластиковой сеткой); - грунтовка глубокого проникновения; - шпатлёвка; - грунтовка глубокого проникновения δ = 25 мм | D16: 89.2 | E16: - грунтовка глубокого проникновения; - штукатурка цементно-песчаным раствором М100 (армированная стекловолоконной или пластиковой сеткой); - грунтовка глубокого проникновения; - шпатлёвка; - грунтовка глубокого проникновения δ = 25 мм | F16: 26.1 | G16: см. раздел АИ | H16: 115.3 | M16: - затирка; - грунтовка "Бетоноконтакт "; - шпатлёвка; - грунтовка глубокого проникновения δ = 5 мм | N16: 17 | O16: см. раздел АИ | P16: 37.3 | Q16: -
A17: 0.13 | B17: Помещение для прокладки коммуникаций | C17: - обеспыливание поверхности ж/б грунтовкой глубокого проникновения Политакс 88PU 2/50 (или аналог) | D17: 49.8 | E17: - грунтовка глубокого проникновения; - штукатурка цементно-песчаным раствором М100 (армированная стекловолоконной или пластиковой сеткой); - грунтовка глубокого проникновения; - шпатлёвка; - грунтовка глубокого проникновения δ = 25 мм | F17: 16.5 | G17: - | H17: 70.4 | M17: - обеспыливание | N17: 16.6 | O17: - | P17: 22.3 | Q17: -
A18: 0.14 | B18: Помещение для прокладки коммуникаций | C18: - обеспыливание поверхности ж/б грунтовкой глубокого проникновения Политакс 88PU 2/50 (или аналог) | D18: 197.8 | E18: - грунтовка глубокого проникновения; - штукатурка цементно-песчаным раствором М100 (армированная стекловолоконной или пластиковой сеткой); - грунтовка глубокого проникновения; - шпатлёвка; - грунтовка глубокого проникновения δ = 25 мм | F18: 25.9 | G18: - | H18: 223.7 | M18: - обеспыливание | N18: 176.6 | O18: - | P18: 68.6 | Q18: -

Sheet Table 2
A1: Ведомость отделки помещений подвала
A2: Ном ер пом еще ния | B2: Наименование помещения | C2: СТЕНЫ ИЛИ ПЕРЕГОРОДКИ | M2: Основной тип потолка | O2: ПЛИНТУС | Q2: Примечание
C3: Железобетон | E3: Кирпич | G3: Газобетон | I3: Утеплитель | K3: Финишный слой | M3: Вид отделки | N3: Площадь, м² | O3: Вид отделки | P3: м.п.
C4: Вид отделки | D4: Площадь, м² | E4: Вид отделки | F4: Площадь, м² | G4: Вид отделки | H4: Площадь, м² | I4: Вид отделки | J4: Площадь, м² | K4: Вид отделки | L4: Площадь, м²
A5: 0.15 | B5: Помещение CC2 | C5: - грунтовка "Бетоноконтакт"; - штукатурка цементно-песчаным раствором М100 (армированная стекловолоконной или пластиковой сеткой); - грунтовка глубокого проникновения; - шпатлёвка; - грунтовка глубокого проникновения δ = 25 мм | D5: 26.3 | E5: - грунтовка глубокого проникновения; - штукатурка цементно-песчаным раствором М100 (армированная стекловолоконной или пластиковой сеткой); - грунтовка глубокого проникновения; - шпатлёвка; - грунтовка глубокого проникновения δ = 25 мм | F5: 18.9 | G5: - | H5: 0 | K5: см. раздел АИ | L5: 45.2 | M5: - затирка; - грунтовка "Бетоноконтакт "; - шпатлёвка; - грунтовка глубокого проникновения δ = 5 мм | N5: 11.8 | O5: см. раздел АИ | P5: 14.3 | Q5: -
A6: 0.16 | B6: Помещение для хранения отработанных ламп | C6: - грунтовка "Бетоноконтакт"; - штукатурка цементно-песчаным раствором М100 (армированная стекловолоконной или пластиковой сеткой); - грунтовка глубокого проникновения; - шпатлёвка; - грунтовка глубокого проникновения δ = 25 мм | D6: 30.7 | E6: - грунтовка глубокого проникновения; - штукатурка цементно-песчаным раствором М100 (армированная стекловолоконной или пластиковой сеткой); - грунтовка глубокого проникновения; - шпатлёвка; - грунтовка глубокого проникновения δ = 25 мм | F6: 11.7 | G6: - | H6: 0 | K6: см. раздел АИ | L6: 42.4 | M6: - затирка; - грунтовка "Бетоноконтакт "; - шпатлёвка; - грунтовка глубокого проникновения δ = 5 мм | N6: 12.4 | O6: см. раздел АИ | P6: 13.4 | Q6: -
A7: 0.17 | B7: Коридор | C7: - грунтовка "Бетоноконтакт"; - штукатурка цементно-песчаным раствором М100 (армированная стекловолоконной или пластиковой сеткой); - грунтовка глубокого проникновения; - шпатлёвка; - грунтовка глубокого проникновения δ = 25 мм | D7: 33.7 | E7: - грунтовка глубокого проникновения; - штукатурка цементно-песчаным раствором М100 (армированная стекловолоконной или пластиковой сеткой); - грунтовка глубокого проникновения; - шпатлёвка; - грунтовка глубокого проникновения δ = 25 мм | F7: 45.4 | G7: - | H7: 0 | K7: см. раздел АИ | L7: 79.1 | M7: - затирка; - грунтовка "Бетоноконтакт "; - шпатлёвка; - грунтовка глубокого проникновения δ = 5 мм | N7: 30.4 | O7: см. раздел АИ | P7: 24.3 | Q7: -
A8: 0.18 | B8: Лестничная клетка №6 | C8: - грунтовка "Бетоноконтакт"; - штукатурка цементно-песчаным раствором М100 (армированная стекловолоконной или пластиковой сеткой); - грунтовка глубокого проникновения; - шпатлёвка; - грунтовка глубокого проникновения δ = 25 мм | D8: 69.9 | E8: - грунтовка глубокого проникновения; - штукатурка цементно-песчаным раствором М100 (армированная стекловолоконной или пластиковой сеткой); - грунтовка глубокого проникновения; - шпатлёвка; - грунтовка глубокого проникновения δ = 25 мм | F8: 24.3 | G8: - | H8: 0 | K8: см. раздел АИ | L8: 94.2 | M8: - затирка; - грунтовка "Бетоноконтакт "; - шпатлёвка; - грунтовка глубокого проникновения δ = 5 мм | N8: 13 | O8: см. раздел АИ | P8: 29.8 | Q8: -
A9: 0.19 | B9: Помещение для прокладки коммуникаций | C9: - обеспыливание поверхности ж/б грунтовкой глубокого проникновения Политакс 88PU 2/50 (или аналог) | D9: 60.3 | E9: - грунтовка глубокого проникновения; - штукатурка цементно-песчаным раствором М100 (армированная стекловолоконной или пластиковой сеткой); - грунтовка глубокого проникновения; - шпатлёвка; - грунтовка глубокого проникновения δ = 25 мм | F9: 29.4 | G9: - | H9: 0 | K9: - | L9: 89.7 | M9: - обеспыливание | N9: 31.4 | O9: - | P9: 28.9 | Q9: -
A10: 0.20 | B10: Помещение для прокладки коммуникаций | C10: - обеспыливание поверхности ж/б грунтовкой глубокого проникновения Политакс 88PU 2/50 (или аналог) | D10: 337.9 | E10: - грунтовка глубокого проникновения; - штукатурка цементно-песчаным раствором М100 (армированная стекловолоконной или пластиковой сеткой); - грунтовка глубокого проникновения; - шпатлёвка; - грунтовка глубокого проникновения δ = 25 мм | F10: 126.9 | G10: - | H10: 0 | K10: - | L10: 464.7 | M10: - обеспыливание | N10: 289.1 | O10: - | P10: 162 | Q10: -
A11: 0.21 | B11: Помещение для прокладки коммуникаций | C11: - обеспыливание поверхности ж/б грунтовкой глубокого проникновения Политакс 88PU 2/50 (или аналог) | D11: 278.8 | E11: - грунтовка глубокого проникновения; - штукатурка цементно-песчаным раствором М100 (армированная стекловолоконной или пластиковой сеткой); - грунтовка глубокого проникновения; - шпатлёвка; - грунтовка глубокого проникновения δ = 25 мм | F11: 64 | G11: - | H11: 0 | K11: - | L11: 342.8 | M11: - обеспыливание | N11: 259.2 | O11: - | P11: 111.1 | Q11: -
A12: 0.22 | B12: Помещение для прокладки коммуникаций | C12: - обеспыливание поверхности ж/б грунтовкой глубокого проникновения Политакс 88PU 2/50 (или аналог) | D12: 32.8 | E12: - грунтовка глубокого проникновения; - штукатурка цементно-песчаным раствором М100 (армированная стекловолоконной или пластиковой сеткой); - грунтовка глубокого проникновения; - шпатлёвка; - грунтовка глубокого проникновения δ = 25 мм | F12: 40.7 | G12: - | H12: 0 | K12: - | L12: 73.5 | M12: - обеспыливание | N12: 26.4 | O12: - | P12: 24.1 | Q12: -
A13: 0.23 | B13: Венткамера | C13: - грунтовка "Бетоноконтакт"; - штукатурка цементно-песчаным раствором М100 (армированная стекловолоконной или пластиковой сеткой); - грунтовка глубокого проникновения; - шпатлёвка; - грунтовка глубокого проникновения δ = 25 мм | D13: 89.7 | E13: - грунтовка глубокого проникновения; - штукатурка цементно-песчаным раствором М100 (армированная стекловолоконной или пластиковой сеткой); - грунтовка глубокого проникновения; - шпатлёвка; - грунтовка глубокого проникновения δ = 25 мм | F13: 52.7 | G13: - | H13: 0 | K13: см. раздел АИ | L13: 142.3 | M13: - затирка; - грунтовка "Бетоноконтакт "; - шпатлёвка; - грунтовка глубокого проникновения δ = 5 мм | N13: 126 | O13: см. раздел АИ | P13: 56.4 | Q13: -
A14: 0.24 | B14: Венткамера | C14: - грунтовка "Бетоноконтакт"; - штукатурка цементно-песчаным раствором М100 (армированная стекловолоконной или пластиковой сеткой); - грунтовка глубокого проникновения; - шпатлёвка; - грунтовка глубокого проникновения δ = 25 мм | D14: 26.4 | E14: - грунтовка глубокого проникновения; - штукатурка цементно-песчаным раствором М100 (армированная стекловолоконной или пластиковой сеткой); - грунтовка глубокого проникновения; - шпатлёвка; - грунтовка глубокого проникновения δ = 25 мм | F14: 92.5 | G14: - | H14: 0 | K14: см. раздел АИ | L14: 118.9 | M14: - затирка; - грунтовка "Бетоноконтакт "; - шпатлёвка; - грунтовка глубокого проникновения δ = 5 мм | N14: 70.7 | O14: см. раздел АИ | P14: 38.8 | Q14: -
A15: 0.25 | B15: Помещение для прокладки коммуникаций | C15: - обеспыливание поверхности ж/б грунтовкой глубокого проникновения Политакс 88PU 2/50 (или аналог) | D15: 210.2 | E15: - грунтовка глубокого проникновения; - штукатурка цементно-песчаным раствором М100 (армированная стекловолоконной или пластиковой сеткой); - грунтовка глубокого проникновения; - шпатлёвка; - грунтовка глубокого проникновения δ = 25 мм | F15: 94.2 | G15: - | H15: 0 | K15: - | L15: 304.3 | M15: - обеспыливание | N15: 242 | O15: - | P15: 99.1 | Q15: -
A16: 0.26 | B16: Коридор | C16: - грунтовка "Бетоноконтакт"; - штукатурка цементно-песчаным раствором М100 (армированная стекловолоконной или пластиковой сеткой); - грунтовка глубокого проникновения; - шпатлёвка; - грунтовка глубокого проникновения δ = 25 мм | D16: 261.6 | E16: - грунтовка глубокого проникновения; - штукатурка цементно-песчаным раствором М100 (армированная стекловолоконной или пластиковой сеткой); - грунтовка глубокого проникновения; - шпатлёвка; - грунтовка глубокого проникновения δ = 25 мм | F16: 130.3 | G16: - пропитка гидрофобизирующим составом BOSTIK SMP; - грунтовка глубокого проникновения; - штукатурка цементно-песчаным раствором М100 (армированная стекловолоконной или пластиковой сеткой); - грунтовка глубокого проникновения; - шпатлёвка; - грунтовка глубокого проникновения δ = 25 мм | H16: 3.8 | K16: см. раздел АИ | L16: 395.7 | M16: - затирка; - грунтовка "Бетоноконтакт "; - шпатлёвка; - грунтовка глубокого проникновения δ = 5 мм | N16: 180.7 | O16: см. раздел АИ | P16: 123.9 | Q16: -
... A19: 0.28 | B19: Помещение для прокладки коммуникаций | C19: - обеспыливание поверхности ж/б грунтовкой глубокого проникновения Политакс 88PU 2/50 (или аналог) | D19: 185.8 | E19: - грунтовка глубокого проникновения; - штукатурка цементно-песчаным раствором М100 (армированная стекловолоконной или пластиковой сеткой); - грунтовка глубокого проникновения; - шпатлёвка; - грунтовка глубокого проникновения δ = 25 мм | F19: 41.3 | G19: - | H19: 0 | K19: - | L19: 227.1 | M19: - обеспыливание | N19: 181.1 | O19: - | P19: 71 | Q19: -

Sheet Table 3
A1: Ведомость отделки помещений подвала
A2: Ном ер пом еще ния | B2: Наименование помещения | C2: СТЕНЫ ИЛИ ПЕРЕГОРОДКИ | Q2: Основной тип потолка | S2: ПЛИНТУС | U2: Примечание
C3: Железобетон | E3: Кирпич | G3: Газобетон | I3: ГСП | K3: ПГП | M3: Утеплитель | O3: Финишный слой | Q3: Вид отделки | R3: Площадь, м² | S3: Вид отделки | T3: м.п.
C4: Вид отделки | D4: Площадь, м² | E4: Вид отделки | F4: Площадь, м² | G4: Вид отделки | H4: Площадь, м² | I4: Вид отделки | J4: Площадь, м² | K4: Вид отделки | L4: Площадь, м² | M4: Вид отделки | N4: Площадь, м² | O4: Вид отделки | P4: Площадь, м²
A5: 1.01 | B5: Тамбур | C5: - грунтовка "Бетоноконтакт"; - гипсовая штукатурка; - грунтовка глубокого проникновения; - шпатлёвка; - грунтовка глубокого проникновения δ = 25 мм | D5: 5.6 | G5: - | H5: 0 | I5: - | J5: 0 | K5: - | L5: 0 | M5: - штукатурка цементно-песчаным раствором М100 (армированная стекловолоконной или пластиковой сеткой); - грунтовка глубокого проникновения; - шпатлёвка; - грунтовка глубокого проникновения δ = 25 мм | N5: 5.4 | O5: см. раздел АИ | P5: 11 | Q5: - затирка; - грунтовка "Бетоноконтакт "; - шпатлёвка; - грунтовка глубокого проникновения δ = 5 мм | R5: 13.4 | S5: см. раздел АИ | T5: 7.7 | U5: Работы по черновой отделке выполнять при необходимост и выравнивания стен
A6: 1.02 | B6: Зона ожидания родителей со стойкой для зарядки мобильных устройств | C6: - грунтовка "Бетоноконтакт"; - гипсовая штукатурка; - грунтовка глубокого проникновения; - шпатлёвка; - грунтовка глубокого проникновения δ = 25 мм | D6: 11.6 | G6: - грунтовка глубокого проникновения; - гипсовая штукатурка; - грунтовка глубокого проникновения; - шпатлёвка; - грунтовка глубокого проникновения δ = 25 мм | H6: 6.3 | I6: - | J6: 0 | K6: - грунтовка глубокого проникновения; - гипсовая штукатурка; - грунтовка глубокого проникновения; - шпатлёвка; - грунтовка глубокого проникновения δ = 25 мм | L6: 15.1 | M6: - | N6: 0 | O6: см. раздел АИ | P6: 32.9 | Q6: - обеспыливание | R6: 17.6 | S6: см. раздел АИ | T6: 14 | U6: Работы по черновой отделке выполнять при необходимост и выравнивания стен
A7: 1.03 | B7: Санузел для посетителей | C7: - | D7: 0 | G7: - | H7: 0 | I7: - | J7: 0 | K7: - грунтовка глубокого проникновения; - штукатурка цементно-песчаным раствором М100 (армированная стекловолоконной или пластиковой сеткой); - грунтовка глубокого проникновения δ = 20 мм | L7: 27.1 | M7: - | N7: 0 | O7: см. раздел АИ | P7: 27.1 | Q7: - затирка; - грунтовка "Бетоноконтакт "; - шпатлёвка; - грунтовка глубокого проникновения δ = 5 мм | R7: 5.8 | S7: см. раздел АИ | T7: 8.5 | U7: Работы по черновой отделке выполнять при необходимост и выравнивания стен
A8: 1.04 | B8: Вестибюль с многофункциональн ым двухсветным пространством с возможностью проведения общественных мероприятий на 200 мест (с эстрадой в уровне пола) | C8: - грунтовка "Бетоноконтакт"; - гипсовая штукатурка; - грунтовка глубокого проникновения; - шпатлёвка; - грунтовка глубокого проникновения δ = 25 мм | D8: 266.7 | G8: - грунтовка глубокого проникновения; - гипсовая штукатурка; - грунтовка глубокого проникновения; - шпатлёвка; - грунтовка глубокого проникновения δ = 25 мм | H8: 166.5 | I8: - грунтовка глубокого проникновения; - шпатлёвка; - грунтовка глубокого проникновения δ = 5 мм | J8: 4.3 | K8: - грунтовка глубокого проникновения; - гипсовая штукатурка; - грунтовка глубокого проникновения; - шпатлёвка; - грунтовка глубокого проникновения δ = 25 мм | L8: 7.1 | M8: - | N8: 0 | O8: см. раздел АИ | P8: 444.7 | Q8: - затирка; - грунтовка "Бетоноконтакт "; - шпатлёвка; - грунтовка глубокого проникновения δ = 5 мм | R8: 357.2 | S8: см. раздел АИ | T8: 88.6 | U8: Работы по черновой отделке выполнять при необходимост и выравнивания стен
A9: 1.05 | B9: Комната охраны с диспетчерским пультом | C9: - грунтовка "Бетоноконтакт"; - гипсовая штукатурка; - грунтовка глубокого проникновения; - шпатлёвка; - грунтовка глубокого проникновения δ = 25 мм | D9: 26.5 | G9: - грунтовка глубокого проникновения; - гипсовая штукатурка; - грунтовка глубокого проникновения; - шпатлёвка; - грунтовка глубокого проникновения δ = 25 мм | H9: 28.2 | I9: - | J9: 0 | K9: - грунтовка глубокого проникновения; - гипсовая штукатурка; - грунтовка глубокого проникновения; - шпатлёвка; - грунтовка глубокого проникновения δ = 25 мм | L9: 14 | M9: - | N9: 0 | O9: см. раздел АИ | P9: 68.7 | Q9: - обеспыливание | R9: 22.1 | S9: см. раздел АИ | T9: 19 | U9: Работы по черновой отделке выполнять при необходимост и выравнивания стен
A10: 1.06 | B10: Санузел для МГН | C10: - | D10: 0 | G10: - грунтовка глубокого проникновения; - штукатурка цементно-песчаным раствором М100 (армированная стекловолоконной или пластиковой сеткой); - грунтовка глубокого проникновения δ = 20 мм | H10: 15 | I10: - | J10: 0 | K10: - грунтовка глубокого проникновения; - штукатурка цементно-песчаным раствором М100 (армированная стекловолоконной или пластиковой сеткой); - грунтовка глубокого проникновения δ = 20 мм | L10: 21.5 | M10: - | N10: 0 | O10: см. раздел АИ | P10: 36.5 | Q10: - затирка; - грунтовка "Бетоноконтакт "; - шпатлёвка; - грунтовка глубокого проникновения δ = 5 мм | R10: 5.9 | S10: см. раздел АИ | T10: 9 | U10: Работы по черновой отделке выполнять при необходимост и выравнивания стен
A11: 1.07 | B11: Гардероб для учителей | C11: - грунтовка "Бетоноконтакт"; - гипсовая штукатурка; - грунтовка глубокого проникновения; - шпатлёвка; - грунтовка глубокого проникновения δ = 25 мм | D11: 12.4 | G11: - грунтовка глубокого проникновения; - гипсовая штукатурка; - грунтовка глубокого проникновения; - шпатлёвка; - грунтовка глубокого проникновения δ = 25 мм | H11: 34.3 | I11: - | J11: 0 | K11: - | L11: 0 | M11: - | N11: 0 | O11: см. раздел АИ | P11: 46.7 | Q11: - обеспыливание | R11: 10 | S11: см. раздел АИ | T11: 11.7 | U11: Работы по черновой отделке выполнять при необходимост и выравнивания стен
A12: 1.08 | B12: Гардероб для начальной школы | C12: - грунтовка "Бетоноконтакт"; - гипсовая штукатурка; - грунтовка глубокого проникновения; - шпатлёвка; - грунтовка глубокого проникновения δ = 25 мм | D12: 72.9 | G12: - грунтовка глубокого проникновения; - гипсовая штукатурка; - грунтовка глубокого проникновения; - шпатлёвка; - грунтовка глубокого проникновения δ = 25 мм | H12: 66.1 | I12: - | J12: 0 | K12: - грунтовка глубокого проникновения; - гипсовая штукатурка; - грунтовка глубокого проникновения; - шпатлёвка; - грунтовка глубокого проникновения δ = 25 мм | L12: 16.5 | M12: - | N12: 0 | O12: см. раздел АИ | P12: 155.5 | Q12: - обеспыливание | R12: 105.4 | S12: см. раздел АИ | T12: 48.2 | U12: Работы по черновой отделке выполнять при необходимост и выравнивания стен
A13: 1.09 | B13: Учебный кабинет 1 класс | C13: - грунтовка "Бетоноконтакт"; - гипсовая штукатурка; - грунтовка глубокого проникновения; - шпатлёвка; - грунтовка глубокого проникновения δ = 25 мм | D13: 40.1 | G13: - грунтовка глубокого проникновения; - гипсовая штукатурка; - грунтовка глубокого проникновения; - шпатлёвка; - грунтовка глубокого проникновения δ = 25 мм | H13: 70.1 | I13: - | J13: 0 | K13: - грунтовка глубокого проникновения; - гипсовая штукатурка; - грунтовка глубокого проникновения; - шпатлёвка; - грунтовка глубокого проникновения δ = 25 мм | L13: 8.4 | M13: - | N13: 0 | O13: см. раздел АИ | P13: 118.6 | Q13: - обеспыливание | R13: 62.9 | S13: см. раздел АИ | T13: 34.6 | U13: Работы по черновой отделке выполнять при необходимост и выравнивания стен

Sheet Table 4
A1: Ведомость отделки помещений подвала
A2: Ном ер пом еще ния | B2: Наименование помещения | C2: СТЕНЫ ИЛИ ПЕРЕГОРОДКИ | Q2: Основной тип потолка | S2: ПЛИНТУС | U2: Примечание
C3: Железобетон | E3: Кирпич | G3: Газобетон | I3: ГСП | K3: ПГП | M3: Утеплитель | O3: Финишный слой | Q3: Вид отделки | R3: Площадь, м² | S3: Вид отделки | T3: м.п.
C4: Вид отделки | D4: Площадь, м² | E4: Вид отделки | F4: Площадь, м² | G4: Вид отделки | H4: Площадь, м² | I4: Вид отделки | J4: Площадь, м² | K4: Вид отделки | L4: Площадь, м² | M4: Вид отделки | N4: Площадь, м² | O4: Вид отделки | P4: Площадь, м²
A5: 1.10 | B5: Учебный кабинет 1 класс | C5: - грунтовка "Бетоноконтакт"; - гипсовая штукатурка; - грунтовка глубокого проникновения; - шпатлёвка; - грунтовка глубокого проникновения δ = 25 мм | D5: 55.6 | G5: - грунтовка глубокого проникновения; - гипсовая штукатурка; - грунтовка глубокого проникновения; - шпатлёвка; - грунтовка глубокого проникновения δ = 25 мм | H5: 47.3 | K5: - грунтовка глубокого проникновения; - гипсовая штукатурка; - грунтовка глубокого проникновения; - шпатлёвка; - грунтовка глубокого проникновения δ = 25 мм | L5: 6.6 | O5: см. раздел АИ | P5: 109.5 | Q5: - обеспыливание | R5: 64.3 | S5: см. раздел АИ | T5: 32.4 | U5: Работы по черновой отделке выполнять при необходимост и выравнивания стен
A6: 1.11 | B6: Учебный кабинет 1 класс | C6: - грунтовка "Бетоноконтакт"; - гипсовая штукатурка; - грунтовка глубокого проникновения; - шпатлёвка; - грунтовка глубокого проникновения δ = 25 мм | D6: 92.6 | G6: - грунтовка глубокого проникновения; - гипсовая штукатурка; - грунтовка глубокого проникновения; - шпатлёвка; - грунтовка глубокого проникновения δ = 25 мм | H6: 11.6 | K6: - грунтовка глубокого проникновения; - гипсовая штукатурка; - грунтовка глубокого проникновения; - шпатлёвка; - грунтовка глубокого проникновения δ = 25 мм | L6: 8.5 | O6: см. раздел АИ | P6: 112.7 | Q6: - обеспыливание | R6: 64.4 | S6: см. раздел АИ | T6: 32.6 | U6: Работы по черновой отделке выполнять при необходимост и выравнивания стен
A7: 1.12 | B7: Игровая с возможностью организации спальных мест | C7: - грунтовка "Бетоноконтакт"; - гипсовая штукатурка; - грунтовка глубокого проникновения; - шпатлёвка; - грунтовка глубокого проникновения δ = 25 мм | D7: 121.5 | G7: - грунтовка глубокого проникновения; - гипсовая штукатурка; - грунтовка глубокого проникновения; - шпатлёвка; - грунтовка глубокого проникновения δ = 25 мм | H7: 24.2 | K7: - грунтовка глубокого проникновения; - гипсовая штукатурка; - грунтовка глубокого проникновения; - шпатлёвка; - грунтовка глубокого проникновения δ = 25 мм | L7: 28.6 | O7: см. раздел АИ | P7: 174.2 | Q7: - обеспыливание | R7: 131.2 | S7: см. раздел АИ | T7: 46 | U7: Работы по черновой отделке выполнять при необходимост и выравнивания стен
A8: 1.13 | B8: Санузел для девочек | C8: - грунтовка "Бетоноконтакт"; - штукатурка цементно-песчаным раствором М100 (армированная стекловолоконной или пластиковой сеткой); - грунтовка глубокого проникновения δ = 20 мм | D8: 50.1 | G8: - | H8: 0 | K8: - грунтовка глубокого проникновения; - штукатурка цементно-песчаным раствором М100 (армированная стекловолоконной или пластиковой сеткой); - грунтовка глубокого проникновения δ = 20 мм | L8: 30.1 | O8: см. раздел АИ | P8: 80.2 | Q8: - затирка; - грунтовка "Бетоноконтакт "; - шпатлёвка; - грунтовка глубокого проникновения δ = 5 мм | R8: 15.8 | S8: см. раздел АИ | T8: 20.3 | U8: Работы по черновой отделке выполнять при необходимост и выравнивания стен
A9: 1.14 | B9: Санузел для МГН | C9: - грунтовка "Бетоноконтакт"; - штукатурка цементно-песчаным раствором М100 (армированная стекловолоконной или пластиковой сеткой); - грунтовка глубокого проникновения δ = 20 мм | D9: 7.2 | G9: - | H9: 0 | K9: - грунтовка глубокого проникновения; - штукатурка цементно-песчаным раствором М100 (армированная стекловолоконной или пластиковой сеткой); - грунтовка глубокого проникновения δ = 20 мм | L9: 27.6 | O9: см. раздел АИ | P9: 34.8 | Q9: - затирка; - грунтовка "Бетоноконтакт "; - шпатлёвка; - грунтовка глубокого проникновения δ = 5 мм | R9: 5.4 | S9: см. раздел АИ | T9: 8.2 | U9: Работы по черновой отделке выполнять при необходимост и выравнивания стен
A10: 1.15 | B10: Санузел для мальчиков | C10: - грунтовка "Бетоноконтакт"; - штукатурка цементно-песчаным раствором М100 (армированная стекловолоконной или пластиковой сеткой); - грунтовка глубокого проникновения δ = 20 мм | D10: 49.9 | G10: - | H10: 0 | K10: - грунтовка глубокого проникновения; - штукатурка цементно-песчаным раствором М100 (армированная стекловолоконной или пластиковой сеткой); - грунтовка глубокого проникновения δ = 20 мм | L10: 30.4 | O10: см. раздел АИ | P10: 80.3 | Q10: - затирка; - грунтовка "Бетоноконтакт "; - шпатлёвка; - грунтовка глубокого проникновения δ = 5 мм | R10: 15.8 | S10: см. раздел АИ | T10: 20.2 | U10: Работы по черновой отделке выполнять при необходимост и выравнивания стен
A11: 1.16 | B11: С/у (медблок) | C11: - грунтовка "Бетоноконтакт"; - штукатурка цементно-песчаным раствором М100 (армированная стекловолоконной или пластиковой сеткой); - грунтовка глубокого проникновения δ = 20 мм | D11: 1.1 | G11: - грунтовка глубокого проникновения; - штукатурка цементно-песчаным раствором М100 (армированная стекловолоконной или пластиковой сеткой); - грунтовка глубокого проникновения δ = 20 мм | H11: 4.8 | K11: - грунтовка глубокого проникновения; - штукатурка цементно-песчаным раствором М100 (армированная стекловолоконной или пластиковой сеткой); - грунтовка глубокого проникновения δ = 20 мм | L11: 16.7 | O11: см. раздел АИ | P11: 22.7 | Q11: - обеспыливание | R11: 2.4 | S11: см. раздел АИ | T11: 5.3 | U11: Работы по черновой отделке выполнять при необходимост и выравнивания стен
A12: 1.17 | B12: Процедурный кабинет | C12: - грунтовка "Бетоноконтакт"; - штукатурка цементно-песчаным раствором М100 (армированная стекловолоконной или пластиковой сеткой); - грунтовка глубокого проникновения δ = 20 мм | D12: 18.6 | G12: - | H12: 0 | K12: - грунтовка глубокого проникновения; - штукатурка цементно-песчаным раствором М100 (армированная стекловолоконной или пластиковой сеткой); - грунтовка глубокого проникновения δ = 20 мм | L12: 40.8 | O12: см. раздел АИ | P12: 59.4 | Q12: - затирка; - грунтовка "Бетоноконтакт "; - шпатлёвка; - грунтовка глубокого проникновения δ = 5 мм | R12: 13.9 | S12: см. раздел АИ | T12: 16.2 | U12: Работы по черновой отделке выполнять при необходимост и выравнивания стен
A13: 1.18 | B13: Прививочный кабинет | C13: - грунтовка "Бетоноконтакт"; - штукатурка цементно-песчаным раствором М100 (армированная стекловолоконной или пластиковой сеткой); - грунтовка глубокого проникновения δ = 20 мм | D13: 7.2 | G13: - | H13: 0 | K13: - грунтовка глубокого проникновения; - штукатурка цементно-песчаным раствором М100 (армированная стекловолоконной или пластиковой сеткой); - грунтовка глубокого проникновения δ = 20 мм | L13: 50.8 | O13: см. раздел АИ | P13: 58 | Q13: - затирка; - грунтовка "Бетоноконтакт "; - шпатлёвка; - грунтовка глубокого проникновения δ = 5 мм | R13: 13.9 | S13: см. раздел АИ | T13: 15.4 | U13: Работы по черновой отделке выполнять при необходимост и выравнивания стен
A14: 1.20 | B14: Холл | C14: - грунтовка "Бетоноконтакт"; - гипсовая штукатурка; - грунтовка глубокого проникновения; - шпатлёвка; - грунтовка глубокого проникновения δ = 25 мм | D14: 7.4 | G14: - грунтовка глубокого проникновения; - гипсовая штукатурка; - грунтовка глубокого проникновения; - шпатлёвка; - грунтовка глубокого проникновения δ = 25 мм | H14: 24.1 | K14: - грунтовка глубокого проникновения; - гипсовая штукатурка; - грунтовка глубокого проникновения; - шпатлёвка; - грунтовка глубокого проникновения δ = 25 мм | L14: 35.7 | O14: см. раздел АИ | P14: 67.2 | Q14: - обеспыливание | R14: 20.4 | S14: см. раздел АИ | T14: 15.9 | U14: Работы по черновой отделке выполнять при необходимост и выравнивания стен
A15: 1.21 | B15: Помещение для приготовления дезинфицирующих растворов | C15: - грунтовка "Бетоноконтакт"; - штукатурка цементно-песчаным раствором М100 (армированная стекловолоконной или пластиковой сеткой); - грунтовка глубокого проникновения δ = 20 мм | D15: 7.7 | G15: - грунтовка глубокого проникновения; - штукатурка цементно-песчаным раствором М100 (армированная стекловолоконной или пластиковой сеткой); - грунтовка глубокого проникновения δ = 20 мм | H15: 14.3 | K15: - грунтовка глубокого проникновения; - штукатурка цементно-песчаным раствором М100 (армированная стекловолоконной или пластиковой сеткой); - грунтовка глубокого проникновения δ = 20 мм | L15: 21.7 | O15: см. раздел АИ | P15: 43.7 | Q15: - затирка; - грунтовка "Бетоноконтакт "; - шпатлёвка; - грунтовка глубокого проникновения δ = 5 мм | R15: 6 | S15: см. раздел АИ | T15: 10.7 | U15: Работы по черновой отделке выполнять при необходимост и выравнивания стен
A16: 1.22 | B16: Санузел персонала | C16: - грунтовка "Бетоноконтакт"; - штукатурка цементно-песчаным раствором М100 (армированная стекловолоконной или пластиковой сеткой); - грунтовка глубокого проникновения δ = 20 мм | D16: 3.2 | G16: - грунтовка глубокого проникновения; - штукатурка цементно-песчаным раствором М100 (армированная стекловолоконной или пластиковой сеткой); - грунтовка глубокого проникновения δ = 20 мм | H16: 9 | K16: - грунтовка глубокого проникновения; - штукатурка цементно-песчаным раствором М100 (армированная стекловолоконной или пластиковой сеткой); - грунтовка глубокого проникновения δ = 20 мм | L16: 20.9 | O16: см. раздел АИ | P16: 33 | Q16: - затирка; - грунтовка "Бетоноконтакт "; - шпатлёвка; - грунтовка глубокого проникновения δ = 5 мм | R16: 4.7 | S16: см. раздел АИ | T16: 8 | U16: Работы по черновой отделке выполнять при необходимост и выравнивания стен
... A22: 1.28 | B22: Серверная | C22: - грунтовка "Бетоноконтакт"; - гипсовая штукатурка; - грунтовка глубокого проникновения; - шпатлёвка; - грунтовка глубокого проникновения δ = 25 мм | D22: 42.4 | G22: - грунтовка глубокого проникновения; - гипсовая штукатурка; - грунтовка глубокого проникновения; - шпатлёвка; - грунтовка глубокого проникновения δ = 25 мм | H22: 39.3 | K22: - | L22: 0 | O22: см. раздел АИ | P22: 81.7 | Q22: - обеспыливание | R22: 35.8 | S22: см. раздел АИ | T22: 22 | U22: Работы по черновой отделке выполнять при необходимост и выравнивания стен

Sheet Table 5
A1: Ведомость отделки помещений подвала
A2: Ном ер пом еще ния | B2: Наименование помещения | C2: СТЕНЫ ИЛИ ПЕРЕГОРОДКИ | Q2: Основной тип потолка | S2: ПЛИНТУС | U2: Примечание
C3: Железобетон | E3: Кирпич | G3: Газобетон | I3: ГСП | K3: ПГП | M3: Утеплитель | O3: Финишный слой | Q3: Вид отделки | R3: Площадь, м² | S3: Вид отделки | T3: м.п.
C4: Вид отделки | D4: Площадь, м² | E4: Вид отделки | F4: Площадь, м² | G4: Вид отделки | H4: Площадь, м² | I4: Вид отделки | J4: Площадь, м² | K4: Вид отделки | L4: Площадь, м² | M4: Вид отделки | N4: Площадь, м² | O4: Вид отделки | P4: Площадь, м²
A5: 1.29 | B5: Электрощитовая | C5: - грунтовка "Бетоноконтакт"; - гипсовая штукатурка; - грунтовка глубокого проникновения; - шпатлёвка; - грунтовка глубокого проникновения δ = 25 мм | D5: 31.2 | E5: - | F5: 0 | G5: - грунтовка глубокого проникновения; - гипсовая штукатурка; - грунтовка глубокого проникновения; - шпатлёвка; - грунтовка глубокого проникновения δ = 25 мм | H5: 59.7 | K5: - | L5: 0 | O5: см. раздел АИ | P5: 90.9 | Q5: - затирка; - грунтовка "Бетоноконтакт "; - шпатлёвка; - грунтовка глубокого проникновения δ = 5 мм | R5: 45.9 | S5: см. раздел АИ | T5: 24.9 | U5: Работы по черновой отделке выполнять при необходимост и выравнивания стен
A6: 1.30 | B6: Рекреация коридорного типа | C6: - грунтовка "Бетоноконтакт"; - гипсовая штукатурка; - грунтовка глубокого проникновения; - шпатлёвка; - грунтовка глубокого проникновения δ = 25 мм | D6: 64.9 | E6: - | F6: 0 | G6: - грунтовка глубокого проникновения; - гипсовая штукатурка; - грунтовка глубокого проникновения; - шпатлёвка; - грунтовка глубокого проникновения δ = 25 мм | H6: 88.7 | K6: - грунтовка глубокого проникновения; - гипсовая штукатурка; - грунтовка глубокого проникновения; - шпатлёвка; - грунтовка глубокого проникновения δ = 25 мм | L6: 23.7 | O6: см. раздел АИ | P6: 177.2 | Q6: - затирка; - грунтовка "Бетоноконтакт "; - шпатлёвка; - грунтовка глубокого проникновения δ = 5 мм | R6: 180.7 | S6: см. раздел АИ | T6: 38.3 | U6: Работы по черновой отделке выполнять при необходимост и выравнивания стен
A7: 1.31 | B7: Коридор | C7: - грунтовка "Бетоноконтакт"; - гипсовая штукатурка; - грунтовка глубокого проникновения; - шпатлёвка; - грунтовка глубокого проникновения δ = 25 мм | D7: 130.2 | E7: - | F7: 0 | G7: - грунтовка глубокого проникновения; - гипсовая штукатурка; - грунтовка глубокого проникновения; - шпатлёвка; - грунтовка глубокого проникновения δ = 25 мм | H7: 128.2 | K7: - грунтовка глубокого проникновения; - гипсовая штукатурка; - грунтовка глубокого проникновения; - шпатлёвка; - грунтовка глубокого проникновения δ = 25 мм | L7: 4.6 | O7: см. раздел АИ | P7: 263.1 | Q7: - затирка; - грунтовка "Бетоноконтакт "; - шпатлёвка; - грунтовка глубокого проникновения δ = 5 мм | R7: 113 | S7: см. раздел АИ | T7: 51.4 | U7: Работы по черновой отделке выполнять при необходимост и выравнивания стен
A8: 1.32 | B8: Лестничная клетка №1 (Тип Н2) | C8: - грунтовка "Бетоноконтакт"; - гипсовая штукатурка; - грунтовка глубокого проникновения; - шпатлёвка; - грунтовка глубокого проникновения δ = 25 мм | D8: 73.9 | E8: - грунтовка глубокого проникновения; - гипсовая штукатурка; - грунтовка глубокого проникновения; - шпатлёвка; - грунтовка глубокого проникновения δ = 25 мм | F8: 36.8 | G8: - | H8: 0 | K8: - | L8: 0 | O8: см. раздел АИ | P8: 110.6 | Q8: - затирка; - грунтовка "Бетоноконтакт "; - шпатлёвка; - грунтовка глубокого проникновения δ = 5 мм | R8: 14.4 | S8: см. раздел АИ | T8: 26.9 | U8: Работы по черновой отделке выполнять при необходимост и выравнивания стен
A9: 1.33 | B9: Лестничная клетка №2 (Тип Н2) | C9: - грунтовка "Бетоноконтакт"; - гипсовая штукатурка; - грунтовка глубокого проникновения; - шпатлёвка; - грунтовка глубокого проникновения δ = 25 мм | D9: 82.3 | E9: - | F9: 0 | G9: - | H9: 0 | K9: - | L9: 0 | O9: см. раздел АИ | P9: 82.3 | Q9: - затирка; - грунтовка "Бетоноконтакт "; - шпатлёвка; - грунтовка глубокого проникновения δ = 5 мм | R9: 17.9 | S9: см. раздел АИ | T9: 20 | U9: Работы по черновой отделке выполнять при необходимост и выравнивания стен
A10: 1.34 | B10: Лестничная клетка №3 (Тип Н2) | C10: - грунтовка "Бетоноконтакт"; - гипсовая штукатурка; - грунтовка глубокого проникновения; - шпатлёвка; - грунтовка глубокого проникновения δ = 25 мм | D10: 78.4 | E10: - | F10: 0 | G10: - | H10: 0 | K10: - | L10: 0 | O10: см. раздел АИ | P10: 78.4 | Q10: - затирка; - грунтовка "Бетоноконтакт "; - шпатлёвка; - грунтовка глубокого проникновения δ = 5 мм | R10: 15.5 | S10: см. раздел АИ | T10: 18.8 | U10: Работы по черновой отделке выполнять при необходимост и выравнивания стен
A11: 1.35 | B11: Лестничная клетка №4 (Тип Н2) | C11: - грунтовка "Бетоноконтакт"; - гипсовая штукатурка; - грунтовка глубокого проникновения; - шпатлёвка; - грунтовка глубокого проникновения δ = 25 мм | D11: 82.6 | E11: - | F11: 0 | G11: - | H11: 0 | K11: - грунтовка глубокого проникновения; - гипсовая штукатурка; - грунтовка глубокого проникновения; - шпатлёвка; - грунтовка глубокого проникновения δ = 25 мм | L11: 13.7 | O11: см. раздел АИ | P11: 96.3 | Q11: - затирка; - грунтовка "Бетоноконтакт "; - шпатлёвка; - грунтовка глубокого проникновения δ = 5 мм | R11: 23.4 | S11: см. раздел АИ | T11: 23.1 | U11: Работы по черновой отделке выполнять при необходимост и выравнивания стен
A12: 1.36 | B12: Лифтовой холл | C12: - грунтовка "Бетоноконтакт"; - гипсовая штукатурка; - грунтовка глубокого проникновения; - шпатлёвка; - грунтовка глубокого проникновения δ = 25 мм | D12: 32.8 | E12: - | F12: 0 | G12: - грунтовка глубокого проникновения; - гипсовая штукатурка; - грунтовка глубокого проникновения; - шпатлёвка; - грунтовка глубокого проникновения δ = 25 мм | H12: 22 | K12: - | L12: 0 | O12: см. раздел АИ | P12: 54.8 | Q12: - затирка; - грунтовка "Бетоноконтакт "; - шпатлёвка; - грунтовка глубокого проникновения δ = 5 мм | R12: 25.9 | S12: см. раздел АИ | T12: 15.2 | U12: Работы по черновой отделке выполнять при необходимост и выравнивания стен
A13: 1.37 | B13: Умывальная | C13: - грунтовка "Бетоноконтакт"; - штукатурка цементно-песчаным раствором М100 (армированная стекловолоконной или пластиковой сеткой); - грунтовка глубокого проникновения δ = 20 мм | D13: 11 | E13: - | F13: 0 | G13: - | H13: 0 | K13: - грунтовка глубокого проникновения; - штукатурка цементно-песчаным раствором М100 (армированная стекловолоконной или пластиковой сеткой); - грунтовка глубокого проникновения δ = 20 мм | L13: 38.9 | O13: см. раздел АИ | P13: 49.9 | Q13: - затирка; - грунтовка "Бетоноконтакт "; - шпатлёвка; - грунтовка глубокого проникновения δ = 5 мм | R13: 11.8 | S13: см. раздел АИ | T13: 12.2 | U13: Работы по черновой отделке выполнять при необходимост и выравнивания стен
A14: 1.38 | B14: Обеденный зал на 150 мест | C14: - грунтовка "Бетоноконтакт"; - гипсовая штукатурка; - грунтовка глубокого проникновения; - шпатлёвка; - грунтовка глубокого проникновения δ = 25 мм | D14: 116.4 | E14: - | F14: 0 | G14: - грунтовка глубокого проникновения; - гипсовая штукатурка; - грунтовка глубокого проникновения; - шпатлёвка; - грунтовка глубокого проникновения δ = 25 мм | H14: 87.3 | K14: - грунтовка глубокого проникновения; - гипсовая штукатурка; - грунтовка глубокого проникновения; - шпатлёвка; - грунтовка глубокого проникновения δ = 25 мм | L14: 22.5 | O14: см. раздел АИ | P14: 226.1 | Q14: - затирка; - грунтовка "Бетоноконтакт "; - шпатлёвка; - грунтовка глубокого проникновения δ = 5 мм | R14: 170.4 | S14: см. раздел АИ | T14: 62.7 | U14: Работы по черновой отделке выполнять при необходимост и выравнивания стен

Sheet Table 6
A1: Ведомость отделки помещений подвала
A2: Ном ер пом еще ния | B2: Наименование помещения | C2: СТЕНЫ ИЛИ ПЕРЕГОРОДКИ | Q2: Основной тип потолка | S2: ПЛИНТУС | U2: Примечание
C3: Железобетон | E3: Кирпич | G3: Газобетон | I3: ГСП | K3: ПГП | M3: Утеплитель | O3: Финишный слой | Q3: Вид отделки | R3: Площадь, м² | S3: Вид отделки | T3: м.п.
C4: Вид отделки | D4: Площадь, м² | E4: Вид отделки | F4: Площадь, м² | G4: Вид отделки | H4: Площадь, м² | I4: Вид отделки | J4: Площадь, м² | K4: Вид отделки | L4: Площадь, м² | M4: Вид отделки | N4: Площадь, м² | O4: Вид отделки | P4: Площадь, м²
A5: 1.39 | B5: Моечная столовой посуды | C5: - грунтовка "Бетоноконтакт"; - штукатурка цементно-песчаным раствором М100 (армированная стекловолоконной или пластиковой сеткой); - грунтовка глубокого проникновения δ = 20 мм | D5: 20.5 | E5: - | F5: 0 | G5: - грунтовка глубокого проникновения; - штукатурка цементно-песчаным раствором М100 (армированная стекловолоконной или пластиковой сеткой); - грунтовка глубокого проникновения δ = 20 мм | H5: 102.4 | K5: - грунтовка глубокого проникновения; - штукатурка цементно-песчаным раствором М100 (армированная стекловолоконной или пластиковой сеткой); - грунтовка глубокого проникновения δ = 20 мм | L5: 2 | O5: см. раздел АИ | P5: 125 | Q5: - затирка; - грунтовка "Бетоноконтакт "; - шпатлёвка; - грунтовка глубокого проникновения δ = 5 мм | R5: 36.4 | S5: см. раздел АИ | T5: 32.2 | U5: Работы по черновой отделке выполнять при необходимост и выравнивания стен
A6: 1.40 | B6: Холодный цех | C6: - грунтовка "Бетоноконтакт"; - штукатурка цементно-песчаным раствором М100 (армированная стекловолоконной или пластиковой сеткой); - грунтовка глубокого проникновения δ = 20 мм | D6: 5 | E6: - грунтовка глубокого проникновения; - штукатурка цементно-песчаным раствором М100 (армированная стекловолоконной или пластиковой сеткой); - грунтовка глубокого проникновения δ = 20 мм | F6: 1.4 | G6: - грунтовка глубокого проникновения; - штукатурка цементно-песчаным раствором М100 (армированная стекловолоконной или пластиковой сеткой); - грунтовка глубокого проникновения δ = 20 мм | H6: 22.3 | K6: - грунтовка глубокого проникновения; - штукатурка цементно-песчаным раствором М100 (армированная стекловолоконной или пластиковой сеткой); - грунтовка глубокого проникновения δ = 20 мм | L6: 27.9 | O6: см. раздел АИ | P6: 56.7 | Q6: - затирка; - грунтовка "Бетоноконтакт "; - шпатлёвка; - грунтовка глубокого проникновения δ = 5 мм | R6: 15 | S6: см. раздел АИ | T6: 12.6 | U6: Работы по черновой отделке выполнять при необходимост и выравнивания стен
A7: 1.41 | B7: Горячий цех | C7: - грунтовка "Бетоноконтакт"; - штукатурка цементно-песчаным раствором М100 (армированная стекловолоконной или пластиковой сеткой); - грунтовка глубокого проникновения δ = 20 мм | D7: 53.6 | E7: - грунтовка глубокого проникновения; - штукатурка цементно-песчаным раствором М100 (армированная стекловолоконной или пластиковой сеткой); - грунтовка глубокого проникновения δ = 20 мм | F7: 5.5 | G7: - грунтовка глубокого проникновения; - штукатурка цементно-песчаным раствором М100 (армированная стекловолоконной или пластиковой сеткой); - грунтовка глубокого проникновения δ = 20 мм | H7: 62.9 | K7: - грунтовка глубокого проникновения; - штукатурка цементно-песчаным раствором М100 (армированная стекловолоконной или пластиковой сеткой); - грунтовка глубокого проникновения δ = 20 мм | L7: 69.3 | O7: см. раздел АИ | P7: 191.3 | Q7: - затирка; - грунтовка "Бетоноконтакт "; - шпатлёвка; - грунтовка глубокого проникновения δ = 5 мм | R7: 89.2 | S7: см. раздел АИ | T7: 44 | U7: Работы по черновой отделке выполнять при необходимост и выравнивания стен
A8: 1.42 | B8: Моечная кухонной посуды | C8: - грунтовка "Бетоноконтакт"; - штукатурка цементно-песчаным раствором М100 (армированная стекловолоконной или пластиковой сеткой); - грунтовка глубокого проникновения δ = 20 мм | D8: 6.7 | E8: - | F8: 0 | G8: - | H8: 0 | K8: - грунтовка глубокого проникновения; - штукатурка цементно-песчаным раствором М100 (армированная стекловолоконной или пластиковой сеткой); - грунтовка глубокого проникновения δ = 20 мм | L8: 61.5 | O8: см. раздел АИ | P8: 68.2 | Q8: - затирка; - грунтовка "Бетоноконтакт "; - шпатлёвка; - грунтовка глубокого проникновения δ = 5 мм | R8: 13.6 | S8: см. раздел АИ | T8: 16.2 | U8: Работы по черновой отделке выполнять при необходимост и выравнивания стен
A9: 1.43 | B9: Кладовая сухих продуктов | C9: - грунтовка "Бетоноконтакт"; - штукатурка цементно-песчаным раствором М100 (армированная стекловолоконной или пластиковой сеткой); - грунтовка глубокого проникновения δ = 20 мм | D9: 5.2 | E9: - | F9: 0 | G9: - | H9: 0 | K9: - грунтовка глубокого проникновения; - штукатурка цементно-песчаным раствором М100 (армированная стекловолоконной или пластиковой сеткой); - грунтовка глубокого проникновения δ = 20 мм | L9: 51.6 | O9: см. раздел АИ | P9: 56.8 | Q9: - затирка; - грунтовка "Бетоноконтакт "; - шпатлёвка; - грунтовка глубокого проникновения δ = 5 мм | R9: 12.1 | S9: см. раздел АИ | T9: 14.2 | U9: Работы по черновой отделке выполнять при необходимост и выравнивания стен
A10: 1.44 | B10: Помещение с холодильным оборудованием | C10: - грунтовка "Бетоноконтакт"; - штукатурка цементно-песчаным раствором М100 (армированная стекловолоконной или пластиковой сеткой); - грунтовка глубокого проникновения δ = 20 мм | D10: 11.2 | E10: - | F10: 0 | G10: - | H10: 0 | K10: - грунтовка глубокого проникновения; - штукатурка цементно-песчаным раствором М100 (армированная стекловолоконной или пластиковой сеткой); - грунтовка глубокого проникновения δ = 20 мм | L10: 86.5 | O10: см. раздел АИ | P10: 97.6 | Q10: - затирка; - грунтовка "Бетоноконтакт "; - шпатлёвка; - грунтовка глубокого проникновения δ = 5 мм | R10: 29.7 | S10: см. раздел АИ | T10: 23.8 | U10: Работы по черновой отделке выполнять при необходимост и выравнивания стен
A11: 1.45 | B11: Кладовая овощей | C11: - грунтовка "Бетоноконтакт"; - штукатурка цементно-песчаным раствором М100 (армированная стекловолоконной или пластиковой сеткой); - грунтовка глубокого проникновения δ = 20 мм | D11: 2 | E11: - | F11: 0 | G11: - | H11: 0 | K11: - грунтовка глубокого проникновения; - штукатурка цементно-песчаным раствором М100 (армированная стекловолоконной или пластиковой сеткой); - грунтовка глубокого проникновения δ = 20 мм | L11: 52.8 | O11: см. раздел АИ | P11: 54.8 | Q11: - затирка; - грунтовка "Бетоноконтакт "; - шпатлёвка; - грунтовка глубокого проникновения δ = 5 мм | R11: 10.8 | S11: см. раздел АИ | T11: 13.4 | U11: Работы по черновой отделке выполнять при необходимост и выравнивания стен
A12: 1.46 | B12: Помещение персонала | C12: - грунтовка "Бетоноконтакт"; - штукатурка цементно-песчаным раствором М100 (армированная стекловолоконной или пластиковой сеткой); - грунтовка глубокого проникновения δ = 20 мм | D12: 6.5 | E12: - | F12: 0 | G12: - | H12: 0 | K12: - грунтовка глубокого проникновения; - штукатурка цементно-песчаным раствором М100 (армированная стекловолоконной или пластиковой сеткой); - грунтовка глубокого проникновения δ = 20 мм | L12: 48.2 | O12: см. раздел АИ | P12: 54.7 | Q12: - затирка; - грунтовка "Бетоноконтакт "; - шпатлёвка; - грунтовка глубокого проникновения δ = 5 мм | R12: 9.3 | S12: см. раздел АИ | T12: 13.5 | U12: Работы по черновой отделке выполнять при необходимост и выравнивания стен
A13: 1.47 | B13: Помещение временного хранения отходов | C13: - | D13: 0 | E13: - | F13: 0 | G13: - | H13: 0 | K13: - грунтовка глубокого проникновения; - штукатурка цементно-песчаным раствором М100 (армированная стекловолоконной или пластиковой сеткой); - грунтовка глубокого проникновения δ = 20 мм | L13: 54.7 | O13: см. раздел АИ | P13: 54.7 | Q13: - затирка; - грунтовка "Бетоноконтакт "; - шпатлёвка; - грунтовка глубокого проникновения δ = 5 мм | R13: 9.7 | S13: см. раздел АИ | T13: 13.1 | U13: Работы по черновой отделке выполнять при необходимост и выравнивания стен
A14: 1.48 | B14: Раздаточная | C14: - грунтовка "Бетоноконтакт"; - гипсовая штукатурка; - грунтовка глубокого проникновения; - шпатлёвка; - грунтовка глубокого проникновения δ = 25 мм | D14: 10.6 | E14: - | F14: 0 | G14: - грунтовка глубокого проникновения; - гипсовая штукатурка; - грунтовка глубокого проникновения; - шпатлёвка; - грунтовка глубокого проникновения δ = 25 мм | H14: 8.5 | K14: - грунтовка глубокого проникновения; - гипсовая штукатурка; - грунтовка глубокого проникновения; - шпатлёвка; - грунтовка глубокого проникновения δ = 25 мм | L14: 22.5 | O14: см. раздел АИ | P14: 41.6 | Q14: - затирка; - грунтовка "Бетоноконтакт "; - шпатлёвка; - грунтовка глубокого проникновения δ = 5 мм | R14: 7.7 | S14: см. раздел АИ | T14: 9.8 | U14: Работы по черновой отделке выполнять при необходимост и выравнивания стен | AF14: 0,000 = 163,65

Sheet Table 7
A1: Ведомость отделки помещений подвала
A2: Ном ер пом еще ния | B2: Наименование помещения | C2: СТЕНЫ ИЛИ ПЕРЕГОРОДКИ | Q2: Основной тип потолка | S2: ПЛИНТУС | U2: Примечание
C3: Железобетон | E3: Кирпич | G3: Газобетон | I3: ГСП | K3: ПГП | M3: Утеплитель | O3: Финишный слой | Q3: Вид отделки | R3: Площадь, м² | S3: Вид отделки | T3: м.п.
C4: Вид отделки | D4: Площадь, м² | E4: Вид отделки | F4: Площадь, м² | G4: Вид отделки | H4: Площадь, м² | I4: Вид отделки | J4: Площадь, м² | K4: Вид отделки | L4: Площадь, м² | M4: Вид отделки | N4: Площадь, м² | O4: Вид отделки | P4: Площадь, м²
A5: 1.49 | B5: Санузел персонала | C5: - грунтовка "Бетоноконтакт"; - штукатурка цементно-песчаным раствором М100 (армированная стекловолоконной или пластиковой сеткой); - грунтовка глубокого проникновения δ = 20 мм | D5: 11.7 | E5: - | F5: 0 | G5: - | H5: 0 | K5: - грунтовка глубокого проникновения; - штукатурка цементно-песчаным раствором М100 (армированная стекловолоконной или пластиковой сеткой); - грунтовка глубокого проникновения δ = 20 мм | L5: 18.8 | M5: - | N5: 0 | O5: см. раздел АИ | P5: 30.5 | Q5: - затирка; - грунтовка "Бетоноконтакт "; - шпатлёвка; - грунтовка глубокого проникновения δ = 5 мм | R5: 3.3 | S5: см. раздел АИ | T5: 7.2 | U5: Работы по черновой отделке выполнять при необходимост и выравнивания стен
A6: 1.50 | B6: Моечная оборотной тары | C6: - грунтовка "Бетоноконтакт"; - штукатурка цементно-песчаным раствором М100 (армированная стекловолоконной или пластиковой сеткой); - грунтовка глубокого проникновения δ = 20 мм | D6: 26.2 | E6: - | F6: 0 | G6: - | H6: 0 | K6: - грунтовка глубокого проникновения; - штукатурка цементно-песчаным раствором М100 (армированная стекловолоконной или пластиковой сеткой); - грунтовка глубокого проникновения δ = 20 мм | L6: 23.8 | M6: - | N6: 0 | O6: см. раздел АИ | P6: 50 | Q6: - затирка; - грунтовка "Бетоноконтакт "; - шпатлёвка; - грунтовка глубокого проникновения δ = 5 мм | R6: 8.7 | S6: см. раздел АИ | T6: 11.9 | U6: Работы по черновой отделке выполнять при необходимост и выравнивания стен
A7: 1.51 | B7: Загрузочная | C7: - | D7: 0 | E7: - | F7: 0 | G7: - | H7: 0 | K7: - | L7: 0 | M7: - штукатурка цементно-песчаным раствором М100 по сетке δ = 20 мм | N7: 42.1 | O7: см. раздел АИ | P7: 42.1 | Q7: - затирка; - грунтовка "Бетоноконтакт "; - шпатлёвка; - грунтовка глубокого проникновения δ = 5 мм | R7: 8.3 | S7: см. раздел АИ | T7: 10.7 | U7: Работы по черновой отделке выполнять при необходимост и выравнивания стен
A8: 1.52 | B8: Тамбур | C8: - | D8: 0 | E8: - | F8: 0 | G8: - | H8: 0 | K8: - | L8: 0 | M8: - штукатурка цементно-песчаным раствором М100 по сетке δ = 20 мм | N8: 19.7 | O8: см. раздел АИ | P8: 19.7 | Q8: - затирка; - грунтовка "Бетоноконтакт "; - шпатлёвка; - грунтовка глубокого проникновения δ = 5 мм | R8: 2.2 | S8: см. раздел АИ | T8: 5.1 | U8: -
A9: 1.53 | B9: Помещение уборочного инвентаря | C9: - | D9: 0 | E9: - | F9: 0 | G9: - | H9: 0 | K9: - грунтовка глубокого проникновения; - штукатурка цементно-песчаным раствором М100 (армированная стекловолоконной или пластиковой сеткой); - грунтовка глубокого проникновения δ = 20 мм | L9: 26.5 | M9: - | N9: 0 | O9: см. раздел АИ | P9: 26.5 | Q9: - затирка; - грунтовка "Бетоноконтакт "; - шпатлёвка; - грунтовка глубокого проникновения δ = 5 мм | R9: 3.3 | S9: см. раздел АИ | T9: 6.3 | U9: Работы по черновой отделке выполнять при необходимост и выравнивания стен
A10: 1.54 | B10: Гардероб персонала с душем | C10: - грунтовка "Бетоноконтакт"; - гипсовая штукатурка; - грунтовка глубокого проникновения; - шпатлёвка; - грунтовка глубокого проникновения δ = 25 мм | D10: 8.3 | E10: - | F10: 0 | G10: - | H10: 0 | K10: - грунтовка глубокого проникновения; - гипсовая штукатурка; - грунтовка глубокого проникновения; - шпатлёвка; - грунтовка глубокого проникновения δ = 25 мм | L10: 40 | M10: - | N10: 0 | O10: см. раздел АИ | P10: 48.4 | Q10: - затирка; - грунтовка "Бетоноконтакт "; - шпатлёвка; - грунтовка глубокого проникновения δ = 5 мм | R10: 10.2 | S10: см. раздел АИ | T10: 12.8 | U10: Работы по черновой отделке выполнять при необходимост и выравнивания стен
A11: 1.55 | B11: Цех первичной обработки | C11: - грунтовка "Бетоноконтакт"; - штукатурка цементно-песчаным раствором М100 (армированная стекловолоконной или пластиковой сеткой); - грунтовка глубокого проникновения δ = 20 мм | D11: 10.6 | E11: - | F11: 0 | G11: - | H11: 0 | K11: - грунтовка глубокого проникновения; - штукатурка цементно-песчаным раствором М100 (армированная стекловолоконной или пластиковой сеткой); - грунтовка глубокого проникновения δ = 20 мм | L11: 35.3 | M11: - | N11: 0 | O11: см. раздел АИ | P11: 45.9 | Q11: - затирка; - грунтовка "Бетоноконтакт "; - шпатлёвка; - грунтовка глубокого проникновения δ = 5 мм | R11: 13.9 | S11: см. раздел АИ | T11: 13.2 | U11: Работы по черновой отделке выполнять при необходимост и выравнивания стен
A12: 1.56 | B12: Цех вторичной обработки | C12: - грунтовка "Бетоноконтакт"; - штукатурка цементно-песчаным раствором М100 (армированная стекловолоконной или пластиковой сеткой); - грунтовка глубокого проникновения δ = 20 мм | D12: 10.8 | E12: - | F12: 0 | G12: - | H12: 0 | K12: - грунтовка глубокого проникновения; - штукатурка цементно-песчаным раствором М100 (армированная стекловолоконной или пластиковой сеткой); - грунтовка глубокого проникновения δ = 20 мм | L12: 34.2 | M12: - | N12: 0 | O12: см. раздел АИ | P12: 45 | Q12: - затирка; - грунтовка "Бетоноконтакт "; - шпатлёвка; - грунтовка глубокого проникновения δ = 5 мм | R12: 12.2 | S12: см. раздел АИ | T12: 12.6 | U12: Работы по черновой отделке выполнять при необходимост и выравнивания стен
A13: 1.57 | B13: Мясо-рыбный цех | C13: - грунтовка "Бетоноконтакт"; - штукатурка цементно-песчаным раствором М100 (армированная стекловолоконной или пластиковой сеткой); - грунтовка глубокого проникновения δ = 20 мм | D13: 15.4 | E13: - | F13: 0 | G13: - | H13: 0 | K13: - грунтовка глубокого проникновения; - штукатурка цементно-песчаным раствором М100 (армированная стекловолоконной или пластиковой сеткой); - грунтовка глубокого проникновения δ = 20 мм | L13: 51.8 | M13: - | N13: 0 | O13: см. раздел АИ | P13: 67.2 | Q13: - затирка; - грунтовка "Бетоноконтакт "; - шпатлёвка; - грунтовка глубокого проникновения δ = 5 мм | R13: 21.4 | S13: см. раздел АИ | T13: 19.5 | U13: Работы по черновой отделке выполнять при необходимост и выравнивания стен
A14: 1.58 | B14: Коридор | C14: - грунтовка "Бетоноконтакт"; - штукатурка цементно-песчаным раствором М100 (армированная стекловолоконной или пластиковой сеткой); - грунтовка глубокого проникновения δ = 20 мм | D14: 41.9 | E14: - грунтовка глубокого проникновения; - штукатурка цементно-песчаным раствором М100 (армированная стекловолоконной или пластиковой сеткой); - грунтовка глубокого проникновения δ = 20 мм | F14: 7 | G14: - грунтовка глубокого проникновения; - штукатурка цементно-песчаным раствором М100 (армированная стекловолоконной или пластиковой сеткой); - грунтовка глубокого проникновения δ = 20 мм | H14: 4.2 | K14: - грунтовка глубокого проникновения; - штукатурка цементно-песчаным раствором М100 (армированная стекловолоконной или пластиковой сеткой); - грунтовка глубокого проникновения δ = 20 мм | L14: 150.7 | M14: - | N14: 0 | O14: см. раздел АИ | P14: 203.8 | Q14: - затирка; - грунтовка "Бетоноконтакт "; - шпатлёвка; - грунтовка глубокого проникновения δ = 5 мм | R14: 58.8 | S14: см. раздел АИ | T14: 43.1 | U14: -

Sheet Table 8
A1: Ведомость отделки помещений подвала
A2: Ном ер пом еще ния | B2: Наименование помещения | C2: СТЕНЫ ИЛИ ПЕРЕГОРОДКИ | Q2: Основной тип потолка | S2: ПЛИНТУС | U2: Примечание
C3: Железобетон | E3: Кирпич | G3: Газобетон | I3: ГСП | K3: ПГП | M3: Утеплитель | O3: Финишный слой | Q3: Вид отделки | R3: Площадь, м² | S3: Вид отделки | T3: м.п.
C4: Вид отделки | D4: Площадь, м² | E4: Вид отделки | F4: Площадь, м² | G4: Вид отделки | H4: Площадь, м² | I4: Вид отделки | J4: Площадь, м² | K4: Вид отделки | L4: Площадь, м² | M4: Вид отделки | N4: Площадь, м² | O4: Вид отделки | P4: Площадь, м²
A5: 1.59 | B5: Тамбур | C5: - грунтовка "Бетоноконтакт"; - гипсовая штукатурка; - грунтовка глубокого проникновения; - шпатлёвка; - грунтовка глубокого проникновения δ = 25 мм | D5: 0.1 | G5: - | H5: 0 | K5: - | L5: 0 | M5: - штукатурка цементно-песчаным раствором М100 по сетке δ = 20 мм | N5: 37 | O5: см. раздел АИ | P5: 37.1 | Q5: - грунтовка глубокого проникновения | R5: 27.4 | S5: см. раздел АИ | T5: 10.6 | U5: Работы по черновой отделке выполнять при необходимост и выравнивания стен
A6: 1.60 | B6: Вестибюль с зоной для посетителей | C6: - грунтовка "Бетоноконтакт"; - штукатурка цементно-песчаным раствором М100 (армированная стекловолоконной или пластиковой сеткой); - грунтовка глубокого проникновения; - шпатлёвка; - грунтовка глубокого проникновения δ = 25 мм | D6: 62.4 | G6: - грунтовка глубокого проникновения; - штукатурка цементно-песчаным раствором М100 (армированная стекловолоконной или пластиковой сеткой); - грунтовка глубокого проникновения; - шпатлёвка; - грунтовка глубокого проникновения δ = 25 мм | H6: 43 | K6: - грунтовка глубокого проникновения; - штукатурка цементно-песчаным раствором М100 (армированная стекловолоконной или пластиковой сеткой); - грунтовка глубокого проникновения; - шпатлёвка; - грунтовка глубокого проникновения δ = 25 мм | L6: 6.7 | M6: - | N6: 0 | O6: см. раздел АИ | P6: 112.1 | Q6: - грунтовка глубокого проникновения | R6: 92.5 | S6: см. раздел АИ | T6: 31.1 | U6: -
A7: 1.61 | B7: Пост охраны | C7: - грунтовка "Бетоноконтакт"; - штукатурка цементно-песчаным раствором М100 (армированная стекловолоконной или пластиковой сеткой); - грунтовка глубокого проникновения; - шпатлёвка; - грунтовка глубокого проникновения δ = 25 мм | D7: 25.4 | G7: - грунтовка глубокого проникновения; - штукатурка цементно-песчаным раствором М100 (армированная стекловолоконной или пластиковой сеткой); - грунтовка глубокого проникновения; - шпатлёвка; - грунтовка глубокого проникновения δ = 25 мм | H7: 29.6 | K7: - | L7: 0 | M7: - | N7: 0 | O7: см. раздел АИ | P7: 55 | Q7: - грунтовка глубокого проникновения | R7: 21.6 | S7: см. раздел АИ | T7: 15.1 | U7: -
A8: 1.62 | B8: Туалет для МГН (для посетителей) | C8: - | D8: 0 | G8: - грунтовка глубокого проникновения; - штукатурка цементно-песчаным раствором М100 (армированная стекловолоконной или пластиковой сеткой); - грунтовка глубокого проникновения δ = 20 мм | H8: 8.8 | K8: - грунтовка глубокого проникновения; - штукатурка цементно-песчаным раствором М100 (армированная стекловолоконной или пластиковой сеткой); - грунтовка глубокого проникновения δ = 20 мм | L8: 28.9 | M8: - | N8: 0 | O8: см. раздел АИ | P8: 37.7 | Q8: - грунтовка глубокого проникновения | R8: 6.2 | S8: см. раздел АИ | T8: 8.9 | U8: Работы по черновой отделке выполнять при необходимост и выравнивания стен
A9: 1.63 | B9: Тамбур | C9: - | D9: 0 | G9: - | H9: 0 | K9: - | L9: 0 | M9: - штукатурка цементно-песчаным раствором М100 по сетке δ = 20 мм | N9: 19.6 | O9: см. раздел АИ | P9: 19.6 | Q9: - грунтовка глубокого проникновения | R9: 10.9 | S9: см. раздел АИ | T9: 8.7 | U9: Работы по черновой отделке выполнять при необходимост и выравнивания стен
A10: 1.64 | B10: Раздевальная комната | C10: - грунтовка "Бетоноконтакт"; - штукатурка цементно-песчаным раствором М100 (армированная стекловолоконной или пластиковой сеткой); - грунтовка глубокого проникновения; - шпатлёвка; - грунтовка глубокого проникновения δ = 25 мм | D10: 45.4 | G10: - грунтовка глубокого проникновения; - штукатурка цементно-песчаным раствором М100 (армированная стекловолоконной или пластиковой сеткой); - грунтовка глубокого проникновения; - шпатлёвка; - грунтовка глубокого проникновения δ = 25 мм | H10: 6.4 | K10: - грунтовка глубокого проникновения; - штукатурка цементно-песчаным раствором М100 (армированная стекловолоконной или пластиковой сеткой); - грунтовка глубокого проникновения; - шпатлёвка; - грунтовка глубокого проникновения δ = 25 мм | L10: 38.3 | M10: - | N10: 0 | O10: см. раздел АИ | P10: 90 | Q10: - грунтовка глубокого проникновения | R10: 24 | S10: см. раздел АИ | T10: 20.8 | U10: -
A11: 1.65 | B11: Буфет | C11: - грунтовка "Бетоноконтакт"; - штукатурка цементно-песчаным раствором М100 (армированная стекловолоконной или пластиковой сеткой); - грунтовка глубокого проникновения; - шпатлёвка; - грунтовка глубокого проникновения δ = 25 мм | D11: 0.1 | G11: - грунтовка глубокого проникновения; - штукатурка цементно-песчаным раствором М100 (армированная стекловолоконной или пластиковой сеткой); - грунтовка глубокого проникновения; - шпатлёвка; - грунтовка глубокого проникновения δ = 25 мм | H11: 5.2 | K11: - грунтовка глубокого проникновения; - штукатурка цементно-песчаным раствором М100 (армированная стекловолоконной или пластиковой сеткой); - грунтовка глубокого проникновения; - шпатлёвка; - грунтовка глубокого проникновения δ = 25 мм | L11: 35 | M11: - | N11: 0 | O11: см. раздел АИ | P11: 40.2 | Q11: - грунтовка глубокого проникновения | R11: 6.7 | S11: см. раздел АИ | T11: 9 | U11: Шпатлевание стен выполнять выше отм. +2,200 от ур. ч. п.
A12: 1.66 | B12: Туалет (в т.ч. МГН) | C12: - грунтовка "Бетоноконтакт"; - штукатурка цементно-песчаным раствором М100 (армированная стекловолоконной или пластиковой сеткой); - грунтовка глубокого проникновения δ = 20 мм | D12: 8.6 | G12: - | H12: 0 | K12: - грунтовка глубокого проникновения; - штукатурка цементно-песчаным раствором М100 (армированная стекловолоконной или пластиковой сеткой); - грунтовка глубокого проникновения δ = 20 мм | L12: 79.9 | M12: - | N12: 0 | O12: см. раздел АИ | P12: 88.5 | Q12: - грунтовка глубокого проникновения | R12: 29.6 | S12: см. раздел АИ | T12: 21.7 | U12: Работы по черновой отделке выполнять при необходимост и выравнивания стен
A13: 1.67 | B13: Групповая | C13: - грунтовка "Бетоноконтакт"; - штукатурка цементно-песчаным раствором М100 (армированная стекловолоконной или пластиковой сеткой); - грунтовка глубокого проникновения; - шпатлёвка; - грунтовка глубокого проникновения δ = 25 мм | D13: 49.4 | G13: - | H13: 0 | K13: - грунтовка глубокого проникновения; - штукатурка цементно-песчаным раствором М100 (армированная стекловолоконной или пластиковой сеткой); - грунтовка глубокого проникновения; - шпатлёвка; - грунтовка глубокого проникновения δ = 25 мм | L13: 34.8 | M13: - | N13: 0 | O13: см. раздел АИ | P13: 84.2 | Q13: - грунтовка глубокого проникновения | R13: 51.3 | S13: см. раздел АИ | T13: 23.6 | U13: -

Sheet Table 9
A1: Ведомость отделки помещений подвала
A2: Ном ер пом еще ния | B2: Наименование помещения | C2: СТЕНЫ ИЛИ ПЕРЕГОРОДКИ | Q2: Основной тип потолка | S2: ПЛИНТУС | U2: Примечание
C3: Железобетон | E3: Кирпич | G3: Газобетон | I3: ГСП | K3: ПГП | M3: Утеплитель | O3: Финишный слой | Q3: Вид отделки | R3: Площадь, м² | S3: Вид отделки | T3: м.п.
C4: Вид отделки | D4: Площадь, м² | E4: Вид отделки | F4: Площадь, м² | G4: Вид отделки | H4: Площадь, м² | I4: Вид отделки | J4: Площадь, м² | K4: Вид отделки | L4: Площадь, м² | M4: Вид отделки | N4: Площадь, м² | O4: Вид отделки | P4: Площадь, м²
A5: 1.68 | B5: Спальная | C5: - грунтовка "Бетоноконтакт"; - штукатурка цементно-песчаным раствором М100 (армированная стекловолоконной или пластиковой сеткой); - грунтовка глубокого проникновения; - шпатлёвка; - грунтовка глубокого проникновения δ = 25 мм | D5: 44.5 | G5: - грунтовка глубокого проникновения; - штукатурка цементно-песчаным раствором М100 (армированная стекловолоконной или пластиковой сеткой); - грунтовка глубокого проникновения; - шпатлёвка; - грунтовка глубокого проникновения δ = 25 мм | H5: 28.3 | K5: - грунтовка глубокого проникновения; - штукатурка цементно-песчаным раствором М100 (армированная стекловолоконной или пластиковой сеткой); - грунтовка глубокого проникновения; - шпатлёвка; - грунтовка глубокого проникновения δ = 25 мм | L5: 20.1 | M5: - | N5: 0 | O5: см. раздел АИ | P5: 92.9 | Q5: - грунтовка глубокого проникновения | R5: 56.6 | S5: см. раздел АИ | T5: 25 | U5: -
A6: 1.69 | B6: Раздевальная комната | C6: - грунтовка "Бетоноконтакт"; - штукатурка цементно-песчаным раствором М100 (армированная стекловолоконной или пластиковой сеткой); - грунтовка глубокого проникновения; - шпатлёвка; - грунтовка глубокого проникновения δ = 25 мм | D6: 32.1 | G6: - грунтовка глубокого проникновения; - штукатурка цементно-песчаным раствором М100 (армированная стекловолоконной или пластиковой сеткой); - грунтовка глубокого проникновения; - шпатлёвка; - грунтовка глубокого проникновения δ = 25 мм | H6: 6.3 | K6: - грунтовка глубокого проникновения; - штукатурка цементно-песчаным раствором М100 (армированная стекловолоконной или пластиковой сеткой); - грунтовка глубокого проникновения; - шпатлёвка; - грунтовка глубокого проникновения δ = 25 мм | L6: 29 | M6: - | N6: 0 | O6: см. раздел АИ | P6: 67.4 | Q6: - грунтовка глубокого проникновения | R6: 18.5 | S6: см. раздел АИ | T6: 15.3 | U6: -
A7: 1.70 | B7: Тамбур | C7: - | D7: 0 | G7: - | H7: 0 | K7: - | L7: 0 | M7: - штукатурка цементно-песчаным раствором М100 по сетке δ = 20 мм | N7: 21.5 | O7: см. раздел АИ | P7: 21.5 | Q7: - грунтовка глубокого проникновения | R7: 4.8 | S7: см. раздел АИ | T7: 6.6 | U7: Работы по черновой отделке выполнять при необходимост и выравнивания стен
A8: 1.71 | B8: Буфет | C8: - грунтовка "Бетоноконтакт"; - штукатурка цементно-песчаным раствором М100 (армированная стекловолоконной или пластиковой сеткой); - грунтовка глубокого проникновения; - шпатлёвка; - грунтовка глубокого проникновения δ = 25 мм | D8: 0.1 | G8: - грунтовка глубокого проникновения; - штукатурка цементно-песчаным раствором М100 (армированная стекловолоконной или пластиковой сеткой); - грунтовка глубокого проникновения; - шпатлёвка; - грунтовка глубокого проникновения δ = 25 мм | H8: 5.1 | K8: - грунтовка глубокого проникновения; - штукатурка цементно-песчаным раствором М100 (армированная стекловолоконной или пластиковой сеткой); - грунтовка глубокого проникновения; - шпатлёвка; - грунтовка глубокого проникновения δ = 25 мм | L8: 35 | M8: - | N8: 0 | O8: см. раздел АИ | P8: 40.2 | Q8: - грунтовка глубокого проникновения | R8: 6.7 | S8: см. раздел АИ | T8: 9 | U8: Шпатлевание стен выполнять выше отм. +2,200 от ур. ч. п.
A9: 1.72 | B9: Туалет (в т.ч. МГН) | C9: - грунтовка "Бетоноконтакт"; - штукатурка цементно-песчаным раствором М100 (армированная стекловолоконной или пластиковой сеткой); - грунтовка глубокого проникновения δ = 20 мм | D9: 8.9 | G9: - | H9: 0 | K9: - грунтовка глубокого проникновения; - штукатурка цементно-песчаным раствором М100 (армированная стекловолоконной или пластиковой сеткой); - грунтовка глубокого проникновения δ = 20 мм | L9: 80.2 | M9: - | N9: 0 | O9: см. раздел АИ | P9: 89.1 | Q9: - грунтовка глубокого проникновения | R9: 29.9 | S9: см. раздел АИ | T9: 21.9 | U9: Работы по черновой отделке выполнять при необходимост и выравнивания стен
A10: 1.73 | B10: Групповая | C10: - грунтовка "Бетоноконтакт"; - штукатурка цементно-песчаным раствором М100 (армированная стекловолоконной или пластиковой сеткой); - грунтовка глубокого проникновения; - шпатлёвка; - грунтовка глубокого проникновения δ = 25 мм | D10: 47.9 | G10: - | H10: 0 | K10: - грунтовка глубокого проникновения; - штукатурка цементно-песчаным раствором М100 (армированная стекловолоконной или пластиковой сеткой); - грунтовка глубокого проникновения; - шпатлёвка; - грунтовка глубокого проникновения δ = 25 мм | L10: 37.5 | M10: - | N10: 0 | O10: см. раздел АИ | P10: 85.4 | Q10: - грунтовка глубокого проникновения | R10: 51.2 | S10: см. раздел АИ | T10: 23.8 | U10: -
A11: 1.74 | B11: Спальная | C11: - грунтовка "Бетоноконтакт"; - штукатурка цементно-песчаным раствором М100 (армированная стекловолоконной или пластиковой сеткой); - грунтовка глубокого проникновения; - шпатлёвка; - грунтовка глубокого проникновения δ = 25 мм | D11: 61.1 | G11: - грунтовка глубокого проникновения; - штукатурка цементно-песчаным раствором М100 (армированная стекловолоконной или пластиковой сеткой); - грунтовка глубокого проникновения; - шпатлёвка; - грунтовка глубокого проникновения δ = 25 мм | H11: 7.6 | K11: - грунтовка глубокого проникновения; - штукатурка цементно-песчаным раствором М100 (армированная стекловолоконной или пластиковой сеткой); - грунтовка глубокого проникновения; - шпатлёвка; - грунтовка глубокого проникновения δ = 25 мм | L11: 20.8 | M11: - | N11: 0 | O11: см. раздел АИ | P11: 89.5 | Q11: - грунтовка глубокого проникновения | R11: 56.3 | S11: см. раздел АИ | T11: 25.2 | U11: -
A12: 1.75 | B12: Помещение уборочного инвентаря | C12: - грунтовка "Бетоноконтакт"; - штукатурка цементно-песчаным раствором М100 (армированная стекловолоконной или пластиковой сеткой); - грунтовка глубокого проникновения δ = 20 мм | D12: 0.8 | G12: - грунтовка глубокого проникновения; - штукатурка цементно-песчаным раствором М100 (армированная стекловолоконной или пластиковой сеткой); - грунтовка глубокого проникновения δ = 20 мм | H12: 2.2 | K12: - грунтовка глубокого проникновения; - штукатурка цементно-песчаным раствором М100 (армированная стекловолоконной или пластиковой сеткой); - грунтовка глубокого проникновения δ = 20 мм | L12: 36.5 | M12: - | N12: 0 | O12: см. раздел АИ | P12: 39.4 | Q12: - грунтовка глубокого проникновения | R12: 5.7 | S12: см. раздел АИ | T12: 9.4 | U12: Работы по черновой отделке выполнять при необходимост и выравнивания стен

Sheet Table 10
A1: Ведомость отделки помещений подвала
A2: Ном ер пом еще ния | B2: Наименование помещения | C2: СТЕНЫ ИЛИ ПЕРЕГОРОДКИ | Q2: Основной тип потолка | S2: ПЛИНТУС | U2: Примечание
C3: Железобетон | E3: Кирпич | G3: Газобетон | I3: ГСП | K3: ПГП | M3: Утеплитель | O3: Финишный слой | Q3: Вид отделки | R3: Площадь, м² | S3: Вид отделки | T3: м.п.
C4: Вид отделки | D4: Площадь, м² | E4: Вид отделки | F4: Площадь, м² | G4: Вид отделки | H4: Площадь, м² | I4: Вид отделки | J4: Площадь, м² | K4: Вид отделки | L4: Площадь, м² | M4: Вид отделки | N4: Площадь, м² | O4: Вид отделки | P4: Площадь, м²
A5: 1.76 | B5: Комната персонала с гардеробом, душем и туалетом | C5: - грунтовка "Бетоноконтакт"; - штукатурка цементно-песчаным раствором М100 (армированная стекловолоконной или пластиковой сеткой); - грунтовка глубокого проникновения; - шпатлёвка; - грунтовка глубокого проникновения δ = 25 мм | D5: 36.1 | E5: - | F5: 0 | G5: - | H5: 0 | K5: - грунтовка глубокого проникновения; - штукатурка цементно-песчаным раствором М100 (армированная стекловолоконной или пластиковой сеткой); - грунтовка глубокого проникновения; - шпатлёвка; - грунтовка глубокого проникновения δ = 25 мм | L5: 32.1 | O5: см. раздел АИ | P5: 68.2 | Q5: - грунтовка глубокого проникновения | R5: 10.7 | S5: см. раздел АИ | T5: 15.2 | U5: -
A6: 1.77 | B6: Коридор | C6: - грунтовка "Бетоноконтакт"; - штукатурка цементно-песчаным раствором М100 (армированная стекловолоконной или пластиковой сеткой); - грунтовка глубокого проникновения; - шпатлёвка; - грунтовка глубокого проникновения δ = 25 мм | D6: 41.8 | E6: - | F6: 0 | G6: - грунтовка глубокого проникновения; - штукатурка цементно-песчаным раствором М100 (армированная стекловолоконной или пластиковой сеткой); - грунтовка глубокого проникновения; - шпатлёвка; - грунтовка глубокого проникновения δ = 25 мм | H6: 47.6 | K6: - грунтовка глубокого проникновения; - штукатурка цементно-песчаным раствором М100 (армированная стекловолоконной или пластиковой сеткой); - грунтовка глубокого проникновения; - шпатлёвка; - грунтовка глубокого проникновения δ = 25 мм | L6: 14.6 | O6: см. раздел АИ | P6: 104 | Q6: - грунтовка глубокого проникновения | R6: 41.2 | S6: см. раздел АИ | T6: 18.1 | U6: -
A7: 1.78 | B7: Коридор | C7: - грунтовка "Бетоноконтакт"; - штукатурка цементно-песчаным раствором М100 (армированная стекловолоконной или пластиковой сеткой); - грунтовка глубокого проникновения; - шпатлёвка; - грунтовка глубокого проникновения δ = 25 мм | D7: 56.7 | E7: - | F7: 0 | G7: - грунтовка глубокого проникновения; - штукатурка цементно-песчаным раствором М100 (армированная стекловолоконной или пластиковой сеткой); - грунтовка глубокого проникновения; - шпатлёвка; - грунтовка глубокого проникновения δ = 25 мм | H7: 74 | K7: - грунтовка глубокого проникновения; - штукатурка цементно-песчаным раствором М100 (армированная стекловолоконной или пластиковой сеткой); - грунтовка глубокого проникновения; - шпатлёвка; - грунтовка глубокого проникновения δ = 25 мм | L7: 7.2 | O7: см. раздел АИ | P7: 137.9 | Q7: - грунтовка глубокого проникновения | R7: 60.8 | S7: см. раздел АИ | T7: 42.3 | U7: -
A8: 1.79 | B8: Лестничная клетка №5 (Тип Н2) | C8: - грунтовка "Бетоноконтакт"; - штукатурка цементно-песчаным раствором М100 (армированная стекловолоконной или пластиковой сеткой); - грунтовка глубокого проникновения; - шпатлёвка; - грунтовка глубокого проникновения δ = 25 мм | D8: 105.7 | E8: - грунтовка глубокого проникновения; - штукатурка цементно-песчаным раствором М100 (армированная стекловолоконной или пластиковой сеткой); - грунтовка глубокого проникновения; - шпатлёвка; - грунтовка глубокого проникновения δ = 25 мм | F8: 38.3 | G8: - | H8: 0 | K8: - | L8: 0 | O8: см. раздел АИ | P8: 144 | Q8: - грунтовка "Бетоноконтакт "; - штукатурка цементно-песчан ым раствором М100 (армированная стальной оцинкованной сеткой); - грунтовка глубокого проникновения; - шпатлёвка; - грунтовка глубокого проникновения δ = 25 мм | R8: 26 | S8: см. раздел АИ | T8: 40.4 | U8: -
A9: 1.80 | B9: Лестничная клетка №6 (Тип Л1) | C9: - грунтовка "Бетоноконтакт"; - штукатурка цементно-песчаным раствором М100 (армированная стекловолоконной или пластиковой сеткой); - грунтовка глубокого проникновения; - шпатлёвка; - грунтовка глубокого проникновения δ = 25 мм | D9: 78.8 | E9: - грунтовка глубокого проникновения; - штукатурка цементно-песчаным раствором М100 (армированная стекловолоконной или пластиковой сеткой); - грунтовка глубокого проникновения; - шпатлёвка; - грунтовка глубокого проникновения δ = 25 мм | F9: 36.5 | G9: - | H9: 0 | K9: - | L9: 0 | O9: см. раздел АИ | P9: 115.3 | Q9: - грунтовка "Бетоноконтакт "; - штукатурка цементно-песчан ым раствором М100 (армированная стальной оцинкованной сеткой); - грунтовка глубокого проникновения; - шпатлёвка; - грунтовка глубокого проникновения δ = 25 мм | R9: 19.3 | S9: см. раздел АИ | T9: 30 | U9: -
A10: 1.81 | B10: Лифтовой холл | C10: - грунтовка "Бетоноконтакт"; - штукатурка цементно-песчаным раствором М100 (армированная стекловолоконной или пластиковой сеткой); - грунтовка глубокого проникновения; - шпатлёвка; - грунтовка глубокого проникновения δ = 25 мм | D10: 26.2 | E10: - | F10: 0 | G10: - грунтовка глубокого проникновения; - штукатурка цементно-песчаным раствором М100 (армированная стекловолоконной или пластиковой сеткой); - грунтовка глубокого проникновения; - шпатлёвка; - грунтовка глубокого проникновения δ = 25 мм | H10: 4.8 | K10: - грунтовка глубокого проникновения; - штукатурка цементно-песчаным раствором М100 (армированная стекловолоконной или пластиковой сеткой); - грунтовка глубокого проникновения; - шпатлёвка; - грунтовка глубокого проникновения δ = 25 мм | L10: 9.1 | O10: см. раздел АИ | P10: 40.1 | Q10: - грунтовка глубокого проникновения | R10: 6.5 | S10: см. раздел АИ | T10: 8.6 | U10: -
A11: 1.82 | B11: Коридор | C11: - грунтовка "Бетоноконтакт"; - штукатурка цементно-песчаным раствором М100 (армированная стекловолоконной или пластиковой сеткой); - грунтовка глубокого проникновения δ = 20 мм | D11: 18 | E11: - | F11: 0 | G11: - грунтовка глубокого проникновения; - штукатурка цементно-песчаным раствором М100 (армированная стекловолоконной или пластиковой сеткой); - грунтовка глубокого проникновения δ = 20 мм | H11: 73.9 | K11: - грунтовка глубокого проникновения; - штукатурка цементно-песчаным раствором М100 (армированная стекловолоконной или пластиковой сеткой); - грунтовка глубокого проникновения δ = 20 мм | L11: 36.4 | O11: см. раздел АИ | P11: 128.3 | Q11: - затирка; - грунтовка "Бетоноконтакт "; - шпатлёвка; - грунтовка глубокого проникновения δ = 5 мм | R11: 25.1 | S11: см. раздел АИ | T11: 28 | U11: -

Sheet Table 11
A1: Ведомость отделки помещений
A2: Ном ер пом еще ния | B2: Наименование помещения | C2: СТЕНЫ ИЛИ ПЕРЕГОРОДКИ | Q2: Основной тип потолка | S2: ПЛИНТУС | U2: Примечание
C3: Железобетон | E3: Кирпич | G3: Газобетон | I3: ГСП | K3: ПГП | M3: Утеплитель | O3: Финишный слой | Q3: Вид отделки | R3: Площадь, м² | S3: Вид отделки | T3: м.п.
C4: Вид отделки | D4: Площадь, м² | E4: Вид отделки | F4: Площадь, м² | G4: Вид отделки | H4: Площадь, м² | I4: Вид отделки | J4: Площадь, м² | K4: Вид отделки | L4: Площадь, м² | M4: Вид отделки | N4: Площадь, м² | O4: Вид отделки | P4: Площадь, м²
A5: 1.04 | B5: Вестибюль с многофункциональн ым двухсветным пространством с возможностью проведения общественных мероприятий на 200 мест (с эстрадой в уровне пола) | C5: - грунтовка "Бетоноконтакт"; - гипсовая штукатурка; - грунтовка глубокого проникновения; - шпатлёвка; - грунтовка глубокого проникновения δ = 25 мм | D5: 38.1 | G5: - грунтовка глубокого проникновения; - гипсовая штукатурка; - грунтовка глубокого проникновения; - шпатлёвка; - грунтовка глубокого проникновения δ = 25 мм | H5: 45.7 | K5: - | L5: 0 | O5: см. раздел АИ | P5: 83.8 | Q5: - затирка; - грунтовка "Бетоноконтакт "; - шпатлёвка; - грунтовка глубокого проникновения δ = 5 мм | R5: 43.1 | S5: см. раздел АИ | T5: 22.2 | U5: Работы по черновой отделке выполнять при необходимост и выравнивания стен
A6: 2.01 | B6: Учебный кабинет 2-4 класс | C6: - грунтовка "Бетоноконтакт"; - гипсовая штукатурка; - грунтовка глубокого проникновения; - шпатлёвка; - грунтовка глубокого проникновения δ = 25 мм | D6: 52.2 | G6: - грунтовка глубокого проникновения; - гипсовая штукатурка; - грунтовка глубокого проникновения; - шпатлёвка; - грунтовка глубокого проникновения δ = 25 мм | H6: 47.9 | K6: - грунтовка глубокого проникновения; - гипсовая штукатурка; - грунтовка глубокого проникновения; - шпатлёвка; - грунтовка глубокого проникновения δ = 25 мм | L6: 13.8 | O6: см. раздел АИ | P6: 114 | Q6: - обеспыливание | R6: 63.7 | S6: см. раздел АИ | T6: 34.1 | U6: Работы по черновой отделке выполнять при необходимост и выравнивания стен
A7: 2.02 | B7: Лабораторно-исслед овательский комплекс для изучения естествознания | C7: - грунтовка "Бетоноконтакт"; - гипсовая штукатурка; - грунтовка глубокого проникновения; - шпатлёвка; - грунтовка глубокого проникновения δ = 25 мм | D7: 47.5 | G7: - грунтовка глубокого проникновения; - гипсовая штукатурка; - грунтовка глубокого проникновения; - шпатлёвка; - грунтовка глубокого проникновения δ = 25 мм | H7: 68.6 | K7: - грунтовка глубокого проникновения; - гипсовая штукатурка; - грунтовка глубокого проникновения; - шпатлёвка; - грунтовка глубокого проникновения δ = 25 мм | L7: 16.7 | O7: см. раздел АИ | P7: 132.8 | Q7: - обеспыливание | R7: 90.2 | S7: см. раздел АИ | T7: 40.3 | U7: Работы по черновой отделке выполнять при необходимост и выравнивания стен
A8: 2.03 | B8: Кабинет с рабочим местом для учителей | C8: - грунтовка "Бетоноконтакт"; - гипсовая штукатурка; - грунтовка глубокого проникновения; - шпатлёвка; - грунтовка глубокого проникновения δ = 25 мм | D8: 22.2 | G8: - грунтовка глубокого проникновения; - гипсовая штукатурка; - грунтовка глубокого проникновения; - шпатлёвка; - грунтовка глубокого проникновения δ = 25 мм | H8: 54.5 | K8: - грунтовка глубокого проникновения; - гипсовая штукатурка; - грунтовка глубокого проникновения; - шпатлёвка; - грунтовка глубокого проникновения δ = 25 мм | L8: 19.5 | O8: см. раздел АИ | P8: 96.2 | Q8: - обеспыливание | R8: 39.8 | S8: см. раздел АИ | T8: 26.9 | U8: Работы по черновой отделке выполнять при необходимост и выравнивания стен
A9: 2.04 | B9: Учебный кабинет 2-4 класс | C9: - грунтовка "Бетоноконтакт"; - гипсовая штукатурка; - грунтовка глубокого проникновения; - шпатлёвка; - грунтовка глубокого проникновения δ = 25 мм | D9: 87.3 | G9: - грунтовка глубокого проникновения; - гипсовая штукатурка; - грунтовка глубокого проникновения; - шпатлёвка; - грунтовка глубокого проникновения δ = 25 мм | H9: 11.4 | K9: - грунтовка глубокого проникновения; - гипсовая штукатурка; - грунтовка глубокого проникновения; - шпатлёвка; - грунтовка глубокого проникновения δ = 25 мм | L9: 13.2 | O9: см. раздел АИ | P9: 111.9 | Q9: - обеспыливание | R9: 64 | S9: см. раздел АИ | T9: 32.6 | U9: Работы по черновой отделке выполнять при необходимост и выравнивания стен
A10: 2.05 | B10: Универсальное помещение с возможностью проведения занятий во внеурочное время в том числе для групп продленного дня | C10: - грунтовка "Бетоноконтакт"; - гипсовая штукатурка; - грунтовка глубокого проникновения; - шпатлёвка; - грунтовка глубокого проникновения δ = 25 мм | D10: 56.5 | G10: - грунтовка глубокого проникновения; - гипсовая штукатурка; - грунтовка глубокого проникновения; - шпатлёвка; - грунтовка глубокого проникновения δ = 25 мм | H10: 35.6 | K10: - грунтовка глубокого проникновения; - гипсовая штукатурка; - грунтовка глубокого проникновения; - шпатлёвка; - грунтовка глубокого проникновения δ = 25 мм | L10: 17.9 | O10: см. раздел АИ | P10: 110 | Q10: - затирка; - грунтовка "Бетоноконтакт "; - шпатлёвка; - грунтовка глубокого проникновения δ = 5 мм | R10: 65.4 | S10: см. раздел АИ | T10: 33.1 | U10: Работы по черновой отделке выполнять при необходимост и выравнивания стен
A11: 2.06 | B11: Универсальное помещение с возможностью проведения занятий во внеурочное время в том числе для групп продленного дня | C11: - грунтовка "Бетоноконтакт"; - гипсовая штукатурка; - грунтовка глубокого проникновения; - шпатлёвка; - грунтовка глубокого проникновения δ = 25 мм | D11: 58.7 | G11: - грунтовка глубокого проникновения; - гипсовая штукатурка; - грунтовка глубокого проникновения; - шпатлёвка; - грунтовка глубокого проникновения δ = 25 мм | H11: 36.7 | K11: - грунтовка глубокого проникновения; - гипсовая штукатурка; - грунтовка глубокого проникновения; - шпатлёвка; - грунтовка глубокого проникновения δ = 25 мм | L11: 12.3 | O11: см. раздел АИ | P11: 107.7 | Q11: - затирка; - грунтовка "Бетоноконтакт "; - шпатлёвка; - грунтовка глубокого проникновения δ = 5 мм | R11: 64.1 | S11: см. раздел АИ | T11: 32.6 | U11: Работы по черновой отделке выполнять при необходимост и выравнивания стен
A12: 2.07 | B12: Учебный кабинет 2-4 класс | C12: - грунтовка "Бетоноконтакт"; - гипсовая штукатурка; - грунтовка глубокого проникновения; - шпатлёвка; - грунтовка глубокого проникновения δ = 25 мм | D12: 91 | G12: - грунтовка глубокого проникновения; - гипсовая штукатурка; - грунтовка глубокого проникновения; - шпатлёвка; - грунтовка глубокого проникновения δ = 25 мм | H12: 17.3 | K12: - | L12: 0 | O12: см. раздел АИ | P12: 108.3 | Q12: - обеспыливание | R12: 64.3 | S12: см. раздел АИ | T12: 33.3 | U12: Работы по черновой отделке выполнять при необходимост и выравнивания стен
A13: 2.08 | B13: Коридор | C13: - грунтовка "Бетоноконтакт"; - гипсовая штукатурка; - грунтовка глубокого проникновения; - шпатлёвка; - грунтовка глубокого проникновения δ = 25 мм | D13: 51.5 | G13: - грунтовка глубокого проникновения; - гипсовая штукатурка; - грунтовка глубокого проникновения; - шпатлёвка; - грунтовка глубокого проникновения δ = 25 мм | H13: 81.4 | K13: - грунтовка глубокого проникновения; - гипсовая штукатурка; - грунтовка глубокого проникновения; - шпатлёвка; - грунтовка глубокого проникновения δ = 25 мм | L13: 43.6 | O13: см. раздел АИ | P13: 176.5 | Q13: - затирка; - грунтовка "Бетоноконтакт "; - шпатлёвка; - грунтовка глубокого проникновения δ = 5 мм | R13: 91.5 | S13: см. раздел АИ | T13: 41.9 | U13: Работы по черновой отделке выполнять при необходимост и выравнивания стен
A14: 2.09 | B14: Помещение уборочного инвентаря | C14: - | D14: 0 | G14: - | H14: 0 | K14: - грунтовка глубокого проникновения; - штукатурка цементно-песчаным раствором М100 (армированная стекловолоконной или пластиковой сеткой); - грунтовка глубокого проникновения δ = 20 мм | L14: 36.3 | O14: см. раздел АИ | P14: 36.3 | Q14: - затирка; - грунтовка "Бетоноконтакт "; - шпатлёвка; - грунтовка глубокого проникновения δ = 5 мм | R14: 5.1 | S14: см. раздел АИ | T14: 8.9 | U14: Работы по черновой отделке выполнять при необходимост и выравнивания стен
A15: 2.11 | B15: Раздевальная для мальчиков (МГН) | C15: - грунтовка "Бетоноконтакт"; - гипсовая штукатурка; - грунтовка глубокого проникновения; - шпатлёвка; - грунтовка глубокого проникновения δ = 25 мм | D15: 16 | G15: - | H15: 0 | K15: - грунтовка глубокого проникновения; - гипсовая штукатурка; - грунтовка глубокого проникновения; - шпатлёвка; - грунтовка глубокого проникновения δ = 25 мм | L15: 37.5 | O15: см. раздел АИ | P15: 53.5 | Q15: - затирка; - грунтовка "Бетоноконтакт "; - шпатлёвка; - грунтовка глубокого проникновения δ = 5 мм | R15: 13.1 | S15: см. раздел АИ | T15: 13.5 | U15: Работы по черновой отделке выполнять при необходимост и выравнивания стен
A16: 2.12 | B16: Раздевальная для мальчиков | C16: - грунтовка "Бетоноконтакт"; - гипсовая штукатурка; - грунтовка глубокого проникновения; - шпатлёвка; - грунтовка глубокого проникновения δ = 25 мм | D16: 16.3 | G16: - грунтовка глубокого проникновения; - гипсовая штукатурка; - грунтовка глубокого проникновения; - шпатлёвка; - грунтовка глубокого проникновения δ = 25 мм | H16: 8 | K16: - грунтовка глубокого проникновения; - гипсовая штукатурка; - грунтовка глубокого проникновения; - шпатлёвка; - грунтовка глубокого проникновения δ = 25 мм | L16: 54.6 | O16: см. раздел АИ | P16: 78.9 | Q16: - затирка; - грунтовка "Бетоноконтакт "; - шпатлёвка; - грунтовка глубокого проникновения δ = 5 мм | R16: 27 | S16: см. раздел АИ | T16: 21.1 | U16: Работы по черновой отделке выполнять при необходимост и выравнивания стен
... A23: 2.19 | B23: Спортивный зал 15х24 м | C23: - грунтовка "Бетоноконтакт"; - гипсовая штукатурка; - грунтовка глубокого проникновения; - шпатлёвка; - грунтовка глубокого проникновения δ = 25 мм | D23: 532.7 | G23: - грунтовка глубокого проникновения; - гипсовая штукатурка; - грунтовка глубокого проникновения; - шпатлёвка; - грунтовка глубокого проникновения δ = 25 мм | H23: 63.7 | K23: - | L23: 0 | O23: см. раздел АИ | P23: 596.4 | Q23: - | R23: 703.2 | S23: см. раздел АИ | T23: 81 | U23: Работы по черновой отделке выполнять при необходимост и выравнивания стен

Sheet Table 12
A1: Ведомость отделки помещений
A2: Ном ер пом еще ния | B2: Наименование помещения | C2: СТЕНЫ ИЛИ ПЕРЕГОРОДКИ | Q2: Основной тип потолка | S2: ПЛИНТУС | U2: Примечание
C3: Железобетон | E3: Кирпич | G3: Газобетон | I3: ГСП | K3: ПГП | M3: Утеплитель | O3: Финишный слой | Q3: Вид отделки | R3: Площадь, м² | S3: Вид отделки | T3: м.п.
C4: Вид отделки | D4: Площадь, м² | E4: Вид отделки | F4: Площадь, м² | G4: Вид отделки | H4: Площадь, м² | I4: Вид отделки | J4: Площадь, м² | K4: Вид отделки | L4: Площадь, м² | M4: Вид отделки | N4: Площадь, м² | O4: Вид отделки | P4: Площадь, м²
A5: 2.20 | B5: Комната инструктора (с душем и туалетом) | C5: - грунтовка "Бетоноконтакт"; - гипсовая штукатурка; - грунтовка глубокого проникновения; - шпатлёвка; - грунтовка глубокого проникновения δ = 25 мм | D5: 57.1 | G5: - | H5: 0 | K5: - грунтовка глубокого проникновения; - гипсовая штукатурка; - грунтовка глубокого проникновения; - шпатлёвка; - грунтовка глубокого проникновения δ = 25 мм | L5: 50.3 | O5: см. раздел АИ | P5: 107.3 | Q5: - затирка; - грунтовка "Бетоноконтакт "; - шпатлёвка; - грунтовка глубокого проникновения δ = 5 мм | R5: 23.7 | S5: см. раздел АИ | T5: 25 | U5: Работы по черновой отделке выполнять при необходимост и выравнивания стен
A6: 2.21 | B6: Кабинет для индивидуальных занятий, в т.ч с учителем-логопедо м | C6: - грунтовка "Бетоноконтакт"; - гипсовая штукатурка; - грунтовка глубокого проникновения; - шпатлёвка; - грунтовка глубокого проникновения δ = 25 мм | D6: 21.2 | G6: - грунтовка глубокого проникновения; - гипсовая штукатурка; - грунтовка глубокого проникновения; - шпатлёвка; - грунтовка глубокого проникновения δ = 25 мм | H6: 17.8 | K6: - грунтовка глубокого проникновения; - гипсовая штукатурка; - грунтовка глубокого проникновения; - шпатлёвка; - грунтовка глубокого проникновения δ = 25 мм | L6: 12.8 | O6: см. раздел АИ | P6: 51.7 | Q6: - обеспыливание | R6: 14 | S6: см. раздел АИ | T6: 14 | U6: Работы по черновой отделке выполнять при необходимост и выравнивания стен
A7: 2.22 | B7: Санузел персонала | C7: - грунтовка "Бетоноконтакт"; - штукатурка цементно-песчаным раствором М100 (армированная стекловолоконной или пластиковой сеткой); - грунтовка глубокого проникновения δ = 20 мм | D7: 13.7 | G7: - грунтовка глубокого проникновения; - штукатурка цементно-песчаным раствором М100 (армированная стекловолоконной или пластиковой сеткой); - грунтовка глубокого проникновения δ = 20 мм | H7: 16.3 | K7: - грунтовка глубокого проникновения; - штукатурка цементно-песчаным раствором М100 (армированная стекловолоконной или пластиковой сеткой); - грунтовка глубокого проникновения δ = 20 мм | L7: 6.7 | O7: см. раздел АИ | P7: 36.7 | Q7: - затирка; - грунтовка "Бетоноконтакт "; - шпатлёвка; - грунтовка глубокого проникновения δ = 5 мм | R7: 5.4 | S7: см. раздел АИ | T7: 8.9 | U7: Работы по черновой отделке выполнять при необходимост и выравнивания стен
A8: 2.23 | B8: Помещение уборочного инвентаря | C8: - грунтовка "Бетоноконтакт"; - штукатурка цементно-песчаным раствором М100 (армированная стекловолоконной или пластиковой сеткой); - грунтовка глубокого проникновения δ = 20 мм | D8: 8.8 | G8: - грунтовка глубокого проникновения; - штукатурка цементно-песчаным раствором М100 (армированная стекловолоконной или пластиковой сеткой); - грунтовка глубокого проникновения δ = 20 мм | H8: 15 | K8: - грунтовка глубокого проникновения; - штукатурка цементно-песчаным раствором М100 (армированная стекловолоконной или пластиковой сеткой); - грунтовка глубокого проникновения δ = 20 мм | L8: 27.8 | O8: см. раздел АИ | P8: 51.6 | Q8: - затирка; - грунтовка "Бетоноконтакт "; - шпатлёвка; - грунтовка глубокого проникновения δ = 5 мм | R8: 9.8 | S8: см. раздел АИ | T8: 12.7 | U8: Работы по черновой отделке выполнять при необходимост и выравнивания стен
A9: 2.24 | B9: Санузел для девочек | C9: - грунтовка "Бетоноконтакт"; - штукатурка цементно-песчаным раствором М100 (армированная стекловолоконной или пластиковой сеткой); - грунтовка глубокого проникновения δ = 20 мм | D9: 49.7 | G9: - | H9: 0 | K9: - грунтовка глубокого проникновения; - штукатурка цементно-песчаным раствором М100 (армированная стекловолоконной или пластиковой сеткой); - грунтовка глубокого проникновения δ = 20 мм | L9: 29.9 | O9: см. раздел АИ | P9: 79.6 | Q9: - затирка; - грунтовка "Бетоноконтакт "; - шпатлёвка; - грунтовка глубокого проникновения δ = 5 мм | R9: 15.8 | S9: см. раздел АИ | T9: 20.3 | U9: Работы по черновой отделке выполнять при необходимост и выравнивания стен
A10: 2.25 | B10: Санузел для мальчиков | C10: - грунтовка "Бетоноконтакт"; - штукатурка цементно-песчаным раствором М100 (армированная стекловолоконной или пластиковой сеткой); - грунтовка глубокого проникновения δ = 20 мм | D10: 49.3 | G10: - | H10: 0 | K10: - грунтовка глубокого проникновения; - штукатурка цементно-песчаным раствором М100 (армированная стекловолоконной или пластиковой сеткой); - грунтовка глубокого проникновения δ = 20 мм | L10: 30 | O10: см. раздел АИ | P10: 79.3 | Q10: - затирка; - грунтовка "Бетоноконтакт "; - шпатлёвка; - грунтовка глубокого проникновения δ = 5 мм | R10: 15.8 | S10: см. раздел АИ | T10: 20.2 | U10: Работы по черновой отделке выполнять при необходимост и выравнивания стен
A11: 2.26 | B11: Санузел для МГН | C11: - грунтовка "Бетоноконтакт"; - штукатурка цементно-песчаным раствором М100 (армированная стекловолоконной или пластиковой сеткой); - грунтовка глубокого проникновения δ = 20 мм | D11: 7.1 | G11: - | H11: 0 | K11: - грунтовка глубокого проникновения; - штукатурка цементно-песчаным раствором М100 (армированная стекловолоконной или пластиковой сеткой); - грунтовка глубокого проникновения δ = 20 мм | L11: 27.3 | O11: см. раздел АИ | P11: 34.4 | Q11: - затирка; - грунтовка "Бетоноконтакт "; - шпатлёвка; - грунтовка глубокого проникновения δ = 5 мм | R11: 5.4 | S11: см. раздел АИ | T11: 8.2 | U11: Работы по черновой отделке выполнять при необходимост и выравнивания стен
A12: 2.27 | B12: Коридор | C12: - грунтовка "Бетоноконтакт"; - гипсовая штукатурка; - грунтовка глубокого проникновения; - шпатлёвка; - грунтовка глубокого проникновения δ = 25 мм | D12: 16.3 | G12: - грунтовка глубокого проникновения; - гипсовая штукатурка; - грунтовка глубокого проникновения; - шпатлёвка; - грунтовка глубокого проникновения δ = 25 мм | H12: 30.6 | K12: - | L12: 0 | O12: см. раздел АИ | P12: 46.9 | Q12: - затирка; - грунтовка "Бетоноконтакт "; - шпатлёвка; - грунтовка глубокого проникновения δ = 5 мм | R12: 19.1 | S12: см. раздел АИ | T12: 4.7 | U12: Работы по черновой отделке выполнять при необходимост и выравнивания стен
A13: 2.28 | B13: Рекреация | C13: - грунтовка "Бетоноконтакт"; - гипсовая штукатурка; - грунтовка глубокого проникновения; - шпатлёвка; - грунтовка глубокого проникновения δ = 25 мм | D13: 164.1 | G13: - грунтовка глубокого проникновения; - гипсовая штукатурка; - грунтовка глубокого проникновения; - шпатлёвка; - грунтовка глубокого проникновения δ = 25 мм | H13: 85.3 | K13: - грунтовка глубокого проникновения; - гипсовая штукатурка; - грунтовка глубокого проникновения; - шпатлёвка; - грунтовка глубокого проникновения δ = 25 мм | L13: 42.8 | O13: см. раздел АИ | P13: 292.2 | Q13: - затирка; - грунтовка "Бетоноконтакт "; - шпатлёвка; - грунтовка глубокого проникновения δ = 5 мм | R13: 377.8 | S13: см. раздел АИ | T13: 70.5 | U13: Работы по черновой отделке выполнять при необходимост и выравнивания стен
A14: 2.30 | B14: Коридор | C14: - грунтовка "Бетоноконтакт"; - гипсовая штукатурка; - грунтовка глубокого проникновения; - шпатлёвка; - грунтовка глубокого проникновения δ = 25 мм | D14: 138.9 | G14: - грунтовка глубокого проникновения; - гипсовая штукатурка; - грунтовка глубокого проникновения; - шпатлёвка; - грунтовка глубокого проникновения δ = 25 мм | H14: 123.1 | K14: - грунтовка глубокого проникновения; - гипсовая штукатурка; - грунтовка глубокого проникновения; - шпатлёвка; - грунтовка глубокого проникновения δ = 25 мм | L14: 6.7 | O14: см. раздел АИ | P14: 268.7 | Q14: - затирка; - грунтовка "Бетоноконтакт "; - шпатлёвка; - грунтовка глубокого проникновения δ = 5 мм | R14: 115.5 | S14: см. раздел АИ | T14: 52.7 | U14: Работы по черновой отделке выполнять при необходимост и выравнивания стен
A15: 2.31 | B15: Лестничная клетка №1 (Тип Н2) | C15: - грунтовка "Бетоноконтакт"; - гипсовая штукатурка; - грунтовка глубокого проникновения; - шпатлёвка; - грунтовка глубокого проникновения δ = 25 мм | D15: 78.7 | G15: - | H15: 0 | K15: - | L15: 0 | O15: см. раздел АИ | P15: 78.7 | Q15: - затирка; - грунтовка "Бетоноконтакт "; - шпатлёвка; - грунтовка глубокого проникновения δ = 5 мм | R15: 13.5 | S15: см. раздел АИ | T15: 20.5 | U15: Работы по черновой отделке выполнять при необходимост и выравнивания стен
A16: 2.32 | B16: Лестничная клетка №2 (Тип Н2) | C16: - грунтовка "Бетоноконтакт"; - гипсовая штукатурка; - грунтовка глубокого проникновения; - шпатлёвка; - грунтовка глубокого проникновения δ = 25 мм | D16: 84 | G16: - | H16: 0 | K16: - | L16: 0 | O16: см. раздел АИ | P16: 84 | Q16: - затирка; - грунтовка "Бетоноконтакт "; - шпатлёвка; - грунтовка глубокого проникновения δ = 5 мм | R16: 27.9 | S16: см. раздел АИ | T16: 21.7 | U16: Работы по черновой отделке выполнять при необходимост и выравнивания стен
... A21: 2.37 | B21: Раздевальная комната | C21: - грунтовка "Бетоноконтакт"; - штукатурка цементно-песчаным раствором М100 (армированная стекловолоконной или пластиковой сеткой); - грунтовка глубокого проникновения; - шпатлёвка; - грунтовка глубокого проникновения δ = 25 мм | D21: 43.8 | G21: - грунтовка глубокого проникновения; - штукатурка цементно-песчаным раствором М100 (армированная стекловолоконной или пластиковой сеткой); - грунтовка глубокого проникновения; - шпатлёвка; - грунтовка глубокого проникновения δ = 25 мм | H21: 6.3 | K21: - грунтовка глубокого проникновения; - штукатурка цементно-песчаным раствором М100 (армированная стекловолоконной или пластиковой сеткой); - грунтовка глубокого проникновения; - шпатлёвка; - грунтовка глубокого проникновения δ = 25 мм | L21: 33.8 | O21: см. раздел АИ | P21: 83.9 | Q21: - грунтовка глубокого проникновения | R21: 21.6 | S21: см. раздел АИ | T21: 20.3 | U21: -

Sheet Table 13
A1: Ведомость отделки помещений
A2: Ном ер пом еще ния | B2: Наименование помещения | C2: СТЕНЫ ИЛИ ПЕРЕГОРОДКИ | Q2: Основной тип потолка | S2: ПЛИНТУС | U2: Примечание
C3: Железобетон | E3: Кирпич | G3: Газобетон | I3: ГСП | K3: ПГП | M3: Утеплитель | O3: Финишный слой | Q3: Вид отделки | R3: Площадь, м² | S3: Вид отделки | T3: м.п.
C4: Вид отделки | D4: Площадь, м² | E4: Вид отделки | F4: Площадь, м² | G4: Вид отделки | H4: Площадь, м² | I4: Вид отделки | J4: Площадь, м² | K4: Вид отделки | L4: Площадь, м² | M4: Вид отделки | N4: Площадь, м² | O4: Вид отделки | P4: Площадь, м²
A5: 2.38 | B5: Буфет | C5: - грунтовка "Бетоноконтакт"; - штукатурка цементно-песчаным раствором М100 (армированная стекловолоконной или пластиковой сеткой); - грунтовка глубокого проникновения; - шпатлёвка; - грунтовка глубокого проникновения δ = 25 мм | D5: 0.1 | G5: - грунтовка глубокого проникновения; - штукатурка цементно-песчаным раствором М100 (армированная стекловолоконной или пластиковой сеткой); - грунтовка глубокого проникновения; - шпатлёвка; - грунтовка глубокого проникновения δ = 25 мм | H5: 5.1 | K5: - грунтовка глубокого проникновения; - штукатурка цементно-песчаным раствором М100 (армированная стекловолоконной или пластиковой сеткой); - грунтовка глубокого проникновения; - шпатлёвка; - грунтовка глубокого проникновения δ = 25 мм | L5: 34.5 | O5: см. раздел АИ | P5: 39.7 | Q5: - грунтовка глубокого проникновения | R5: 6.7 | S5: см. раздел АИ | T5: 9 | U5: Шпатлевание стен выполнять выше отм. +2,200 от ур. ч. п.
A6: 2.39 | B6: Туалет (в т.ч. МГН) | C6: - грунтовка "Бетоноконтакт"; - штукатурка цементно-песчаным раствором М100 (армированная стекловолоконной или пластиковой сеткой); - грунтовка глубокого проникновения δ = 20 мм | D6: 8.5 | G6: - | H6: 0 | K6: - грунтовка глубокого проникновения; - штукатурка цементно-песчаным раствором М100 (армированная стекловолоконной или пластиковой сеткой); - грунтовка глубокого проникновения δ = 20 мм | L6: 79.2 | O6: см. раздел АИ | P6: 87.8 | Q6: - грунтовка глубокого проникновения | R6: 29.6 | S6: см. раздел АИ | T6: 21.7 | U6: Работы по черновой отделке выполнять при необходимост и выравнивания стен
A7: 2.40 | B7: Групповая | C7: - грунтовка "Бетоноконтакт"; - штукатурка цементно-песчаным раствором М100 (армированная стекловолоконной или пластиковой сеткой); - грунтовка глубокого проникновения; - шпатлёвка; - грунтовка глубокого проникновения δ = 25 мм | D7: 46.6 | G7: - | H7: 0 | K7: - грунтовка глубокого проникновения; - штукатурка цементно-песчаным раствором М100 (армированная стекловолоконной или пластиковой сеткой); - грунтовка глубокого проникновения; - шпатлёвка; - грунтовка глубокого проникновения δ = 25 мм | L7: 34.3 | O7: см. раздел АИ | P7: 80.9 | Q7: - грунтовка глубокого проникновения | R7: 51.3 | S7: см. раздел АИ | T7: 23.6 | U7: -
A8: 2.41 | B8: Спальная | C8: - грунтовка "Бетоноконтакт"; - штукатурка цементно-песчаным раствором М100 (армированная стекловолоконной или пластиковой сеткой); - грунтовка глубокого проникновения; - шпатлёвка; - грунтовка глубокого проникновения δ = 25 мм | D8: 43.2 | G8: - грунтовка глубокого проникновения; - штукатурка цементно-песчаным раствором М100 (армированная стекловолоконной или пластиковой сеткой); - грунтовка глубокого проникновения; - шпатлёвка; - грунтовка глубокого проникновения δ = 25 мм | H8: 27.9 | K8: - грунтовка глубокого проникновения; - штукатурка цементно-песчаным раствором М100 (армированная стекловолоконной или пластиковой сеткой); - грунтовка глубокого проникновения; - шпатлёвка; - грунтовка глубокого проникновения δ = 25 мм | L8: 19.8 | O8: см. раздел АИ | P8: 90.9 | Q8: - грунтовка глубокого проникновения | R8: 56.6 | S8: см. раздел АИ | T8: 25 | U8: -
A9: 2.42 | B9: Раздевальная комната | C9: - грунтовка "Бетоноконтакт"; - штукатурка цементно-песчаным раствором М100 (армированная стекловолоконной или пластиковой сеткой); - грунтовка глубокого проникновения; - шпатлёвка; - грунтовка глубокого проникновения δ = 25 мм | D9: 33.7 | G9: - грунтовка глубокого проникновения; - штукатурка цементно-песчаным раствором М100 (армированная стекловолоконной или пластиковой сеткой); - грунтовка глубокого проникновения; - шпатлёвка; - грунтовка глубокого проникновения δ = 25 мм | H9: 14.4 | K9: - грунтовка глубокого проникновения; - штукатурка цементно-песчаным раствором М100 (армированная стекловолоконной или пластиковой сеткой); - грунтовка глубокого проникновения; - шпатлёвка; - грунтовка глубокого проникновения δ = 25 мм | L9: 33.8 | O9: см. раздел АИ | P9: 81.8 | Q9: - грунтовка глубокого проникновения | R9: 21.5 | S9: см. раздел АИ | T9: 20.3 | U9: -
A10: 2.43 | B10: Буфет | C10: - грунтовка "Бетоноконтакт"; - штукатурка цементно-песчаным раствором М100 (армированная стекловолоконной или пластиковой сеткой); - грунтовка глубокого проникновения; - шпатлёвка; - грунтовка глубокого проникновения δ = 25 мм | D10: 0.1 | G10: - грунтовка глубокого проникновения; - штукатурка цементно-песчаным раствором М100 (армированная стекловолоконной или пластиковой сеткой); - грунтовка глубокого проникновения; - шпатлёвка; - грунтовка глубокого проникновения δ = 25 мм | H10: 5.1 | K10: - грунтовка глубокого проникновения; - штукатурка цементно-песчаным раствором М100 (армированная стекловолоконной или пластиковой сеткой); - грунтовка глубокого проникновения; - шпатлёвка; - грунтовка глубокого проникновения δ = 25 мм | L10: 34.5 | O10: см. раздел АИ | P10: 39.7 | Q10: - грунтовка глубокого проникновения | R10: 6.7 | S10: см. раздел АИ | T10: 9 | U10: Шпатлевание стен выполнять выше отм. +2,200 от ур. ч. п.
A11: 2.44 | B11: Групповая | C11: - грунтовка "Бетоноконтакт"; - штукатурка цементно-песчаным раствором М100 (армированная стекловолоконной или пластиковой сеткой); - грунтовка глубокого проникновения; - шпатлёвка; - грунтовка глубокого проникновения δ = 25 мм | D11: 46.6 | G11: - | H11: 0 | K11: - грунтовка глубокого проникновения; - штукатурка цементно-песчаным раствором М100 (армированная стекловолоконной или пластиковой сеткой); - грунтовка глубокого проникновения; - шпатлёвка; - грунтовка глубокого проникновения δ = 25 мм | L11: 34.3 | O11: см. раздел АИ | P11: 80.8 | Q11: - грунтовка глубокого проникновения | R11: 51.3 | S11: см. раздел АИ | T11: 23.6 | U11: -
A12: 2.45 | B12: Спальная | C12: - грунтовка "Бетоноконтакт"; - штукатурка цементно-песчаным раствором М100 (армированная стекловолоконной или пластиковой сеткой); - грунтовка глубокого проникновения; - шпатлёвка; - грунтовка глубокого проникновения δ = 25 мм | D12: 59.5 | G12: - грунтовка глубокого проникновения; - штукатурка цементно-песчаным раствором М100 (армированная стекловолоконной или пластиковой сеткой); - грунтовка глубокого проникновения; - шпатлёвка; - грунтовка глубокого проникновения δ = 25 мм | H12: 7.5 | K12: - грунтовка глубокого проникновения; - штукатурка цементно-песчаным раствором М100 (армированная стекловолоконной или пластиковой сеткой); - грунтовка глубокого проникновения; - шпатлёвка; - грунтовка глубокого проникновения δ = 25 мм | L12: 19.8 | O12: см. раздел АИ | P12: 86.8 | Q12: - грунтовка глубокого проникновения | R12: 56.3 | S12: см. раздел АИ | T12: 24.9 | U12: -
A13: 2.46 | B13: Туалет (в т.ч. МГН) | C13: - грунтовка "Бетоноконтакт"; - штукатурка цементно-песчаным раствором М100 (армированная стекловолоконной или пластиковой сеткой); - грунтовка глубокого проникновения δ = 20 мм | D13: 8.5 | G13: - | H13: 0 | K13: - грунтовка глубокого проникновения; - штукатурка цементно-песчаным раствором М100 (армированная стекловолоконной или пластиковой сеткой); - грунтовка глубокого проникновения δ = 20 мм | L13: 79.2 | O13: см. раздел АИ | P13: 87.7 | Q13: - грунтовка глубокого проникновения | R13: 29.6 | S13: см. раздел АИ | T13: 21.7 | U13: Работы по черновой отделке выполнять при необходимост и выравнивания стен
A14: 2.47 | B14: Многофункциональн ый физкультурный зал для проведения активных игр и занятий с детьми | C14: - грунтовка "Бетоноконтакт"; - штукатурка цементно-песчаным раствором М100 (армированная стекловолоконной или пластиковой сеткой); - грунтовка глубокого проникновения; - шпатлёвка; - грунтовка глубокого проникновения δ = 25 мм | D14: 60.7 | G14: - грунтовка глубокого проникновения; - штукатурка цементно-песчаным раствором М100 (армированная стекловолоконной или пластиковой сеткой); - грунтовка глубокого проникновения; - шпатлёвка; - грунтовка глубокого проникновения δ = 25 мм | H14: 42.3 | K14: - грунтовка глубокого проникновения; - штукатурка цементно-песчаным раствором М100 (армированная стекловолоконной или пластиковой сеткой); - грунтовка глубокого проникновения; - шпатлёвка; - грунтовка глубокого проникновения δ = 25 мм | L14: 9.1 | O14: см. раздел АИ | P14: 112.1 | Q14: - грунтовка глубокого проникновения | R14: 81.7 | S14: см. раздел АИ | T14: 31 | U14: -
A15: 2.48 | B15: Помещение хранения для физкультурного зала | C15: - грунтовка "Бетоноконтакт"; - штукатурка цементно-песчаным раствором М100 (армированная стекловолоконной или пластиковой сеткой); - грунтовка глубокого проникновения; - шпатлёвка; - грунтовка глубокого проникновения δ = 25 мм | D15: 35.4 | G15: - грунтовка глубокого проникновения; - штукатурка цементно-песчаным раствором М100 (армированная стекловолоконной или пластиковой сеткой); - грунтовка глубокого проникновения; - шпатлёвка; - грунтовка глубокого проникновения δ = 25 мм | H15: 6 | K15: - | L15: 0 | O15: см. раздел АИ | P15: 41.3 | Q15: - грунтовка глубокого проникновения | R15: 7 | S15: см. раздел АИ | T15: 9.9 | U15: -
A16: 2.49 | B16: Музыкальный зал | C16: - грунтовка "Бетоноконтакт"; - штукатурка цементно-песчаным раствором М100 (армированная стекловолоконной или пластиковой сеткой); - грунтовка глубокого проникновения; - шпатлёвка; - грунтовка глубокого проникновения δ = 25 мм | D16: 47.7 | G16: - грунтовка глубокого проникновения; - штукатурка цементно-песчаным раствором М100 (армированная стекловолоконной или пластиковой сеткой); - грунтовка глубокого проникновения; - шпатлёвка; - грунтовка глубокого проникновения δ = 25 мм | H16: 36.7 | K16: - грунтовка глубокого проникновения; - штукатурка цементно-песчаным раствором М100 (армированная стекловолоконной или пластиковой сеткой); - грунтовка глубокого проникновения; - шпатлёвка; - грунтовка глубокого проникновения δ = 25 мм | L16: 17.5 | O16: см. раздел АИ | P16: 102 | Q16: - грунтовка глубокого проникновения | R16: 75.2 | S16: см. раздел АИ | T16: 29.4 | U16: -
A17: 2.50 | B17: Помещение хранения для музыкального зала | C17: - грунтовка "Бетоноконтакт"; - штукатурка цементно-песчаным раствором М100 (армированная стекловолоконной или пластиковой сеткой); - грунтовка глубокого проникновения; - шпатлёвка; - грунтовка глубокого проникновения δ = 25 мм | D17: 12.5 | G17: - грунтовка глубокого проникновения; - штукатурка цементно-песчаным раствором М100 (армированная стекловолоконной или пластиковой сеткой); - грунтовка глубокого проникновения; - шпатлёвка; - грунтовка глубокого проникновения δ = 25 мм | H17: 4.5 | K17: - грунтовка глубокого проникновения; - штукатурка цементно-песчаным раствором М100 (армированная стекловолоконной или пластиковой сеткой); - грунтовка глубокого проникновения; - шпатлёвка; - грунтовка глубокого проникновения δ = 25 мм | L17: 23.2 | O17: см. раздел АИ | P17: 40.2 | Q17: - грунтовка глубокого проникновения | R17: 6.2 | S17: см. раздел АИ | T17: 9.6 | U17: -

Sheet Table 14
A1: Ведомость отделки помещений
A2: Ном ер пом еще ния | B2: Наименование помещения | C2: СТЕНЫ ИЛИ ПЕРЕГОРОДКИ | Q2: Основной тип потолка | S2: ПЛИНТУС | U2: Примечание
C3: Железобетон | E3: Кирпич | G3: Газобетон | I3: ГСП | K3: ПГП | M3: Утеплитель | O3: Финишный слой | Q3: Вид отделки | R3: Площадь, м² | S3: Вид отделки | T3: м.п.
C4: Вид отделки | D4: Площадь, м² | E4: Вид отделки | F4: Площадь, м² | G4: Вид отделки | H4: Площадь, м² | I4: Вид отделки | J4: Площадь, м² | K4: Вид отделки | L4: Площадь, м² | M4: Вид отделки | N4: Площадь, м² | O4: Вид отделки | P4: Площадь, м²
A5: 2.51 | B5: Коридор | C5: - грунтовка "Бетоноконтакт"; - штукатурка цементно-песчаным раствором М100 (армированная стекловолоконной или пластиковой сеткой); - грунтовка глубокого проникновения; - шпатлёвка; - грунтовка глубокого проникновения δ = 25 мм | D5: 40 | E5: - грунтовка глубокого проникновения; - штукатурка цементно-песчаным раствором М100 (армированная стекловолоконной или пластиковой сеткой); - грунтовка глубокого проникновения; - шпатлёвка; - грунтовка глубокого проникновения δ = 25 мм | F5: 3.7 | G5: - грунтовка глубокого проникновения; - штукатурка цементно-песчаным раствором М100 (армированная стекловолоконной или пластиковой сеткой); - грунтовка глубокого проникновения; - шпатлёвка; - грунтовка глубокого проникновения δ = 25 мм | H5: 39.9 | K5: - грунтовка глубокого проникновения; - штукатурка цементно-песчаным раствором М100 (армированная стекловолоконной или пластиковой сеткой); - грунтовка глубокого проникновения; - шпатлёвка; - грунтовка глубокого проникновения δ = 25 мм | L5: 4.9 | O5: см. раздел АИ | P5: 88.6 | Q5: - грунтовка глубокого проникновения | R5: 38.7 | S5: см. раздел АИ | T5: 14.8 | U5: -
A6: 2.52 | B6: Помещение уборочного инвентаря | C6: - грунтовка "Бетоноконтакт"; - штукатурка цементно-песчаным раствором М100 (армированная стекловолоконной или пластиковой сеткой); - грунтовка глубокого проникновения δ = 20 мм | D6: 7.1 | E6: - | F6: 0 | G6: - грунтовка глубокого проникновения; - штукатурка цементно-песчаным раствором М100 (армированная стекловолоконной или пластиковой сеткой); - грунтовка глубокого проникновения δ = 20 мм | H6: 13.2 | K6: - грунтовка глубокого проникновения; - штукатурка цементно-песчаным раствором М100 (армированная стекловолоконной или пластиковой сеткой); - грунтовка глубокого проникновения δ = 20 мм | L6: 19.5 | O6: см. раздел АИ | P6: 39.8 | Q6: - грунтовка глубокого проникновения | R6: 5.8 | S6: см. раздел АИ | T6: 9.6 | U6: Работы по черновой отделке выполнять при необходимост и выравнивания стен
A7: 2.53 | B7: Хозяйственная кладовая | C7: - грунтовка "Бетоноконтакт"; - штукатурка цементно-песчаным раствором М100 (армированная стекловолоконной или пластиковой сеткой); - грунтовка глубокого проникновения; - шпатлёвка; - грунтовка глубокого проникновения δ = 25 мм | D7: 25.2 | E7: - | F7: 0 | G7: - | H7: 0 | K7: - грунтовка глубокого проникновения; - штукатурка цементно-песчаным раствором М100 (армированная стекловолоконной или пластиковой сеткой); - грунтовка глубокого проникновения; - шпатлёвка; - грунтовка глубокого проникновения δ = 25 мм | L7: 13.7 | O7: см. раздел АИ | P7: 38.9 | Q7: - грунтовка глубокого проникновения | R7: 6.2 | S7: см. раздел АИ | T7: 9.5 | U7: -
A8: 2.54 | B8: Лестничная клетка №5 (Тип Н2) | C8: - грунтовка "Бетоноконтакт"; - штукатурка цементно-песчаным раствором М100 (армированная стекловолоконной или пластиковой сеткой); - грунтовка глубокого проникновения; - шпатлёвка; - грунтовка глубокого проникновения δ = 25 мм | D8: 104 | E8: - | F8: 0 | G8: - | H8: 0 | K8: - | L8: 0 | O8: см. раздел АИ | P8: 104 | Q8: - грунтовка "Бетоноконтакт"; - штукатурка цементно-песчаным раствором М100 (армированная стальной оцинкованной сеткой); - грунтовка глубокого проникновения; - шпатлёвка; - грунтовка глубокого проникновения δ = 25 мм | R8: 26.3 | S8: см. раздел АИ | T8: 28.7 | U8: -
A9: 2.55 | B9: Лифтовой холл (зона безопасности) | C9: - грунтовка "Бетоноконтакт"; - штукатурка цементно-песчаным раствором М100 (армированная стекловолоконной или пластиковой сеткой); - грунтовка глубокого проникновения; - шпатлёвка; - грунтовка глубокого проникновения δ = 25 мм | D9: 25.2 | E9: - | F9: 0 | G9: - грунтовка глубокого проникновения; - штукатурка цементно-песчаным раствором М100 (армированная стекловолоконной или пластиковой сеткой); - грунтовка глубокого проникновения; - шпатлёвка; - грунтовка глубокого проникновения δ = 25 мм | H9: 4.7 | K9: - грунтовка глубокого проникновения; - штукатурка цементно-песчаным раствором М100 (армированная стекловолоконной или пластиковой сеткой); - грунтовка глубокого проникновения; - шпатлёвка; - грунтовка глубокого проникновения δ = 25 мм | L9: 9.1 | O9: см. раздел АИ | P9: 38.9 | Q9: - грунтовка глубокого проникновения | R9: 6.5 | S9: см. раздел АИ | T9: 8.6 | U9: -
A10: 2.56 | B10: Коридор | C10: - грунтовка "Бетоноконтакт"; - штукатурка цементно-песчаным раствором М100 (армированная стекловолоконной или пластиковой сеткой); - грунтовка глубокого проникновения; - шпатлёвка; - грунтовка глубокого проникновения δ = 25 мм | D10: 60.8 | E10: - | F10: 0 | G10: - грунтовка глубокого проникновения; - штукатурка цементно-песчаным раствором М100 (армированная стекловолоконной или пластиковой сеткой); - грунтовка глубокого проникновения; - шпатлёвка; - грунтовка глубокого проникновения δ = 25 мм | H10: 79.1 | K10: - грунтовка глубокого проникновения; - штукатурка цементно-песчаным раствором М100 (армированная стекловолоконной или пластиковой сеткой); - грунтовка глубокого проникновения; - шпатлёвка; - грунтовка глубокого проникновения δ = 25 мм | L10: 7.1 | O10: см. раздел АИ | P10: 147 | Q10: - грунтовка глубокого проникновения | R10: 63.1 | S10: см. раздел АИ | T10: 31.5 | U10: -
A11: 2.57 | B11: Лестничная клетка №6 (Тип Л1) | C11: - грунтовка "Бетоноконтакт"; - штукатурка цементно-песчаным раствором М100 (армированная стекловолоконной или пластиковой сеткой); - грунтовка глубокого проникновения; - шпатлёвка; - грунтовка глубокого проникновения δ = 25 мм | D11: 83.5 | E11: - | F11: 0 | G11: - | H11: 0 | K11: - | L11: 0 | O11: см. раздел АИ | P11: 83.5 | Q11: - грунтовка "Бетоноконтакт"; - штукатурка цементно-песчаным раствором М100 (армированная стальной оцинкованной сеткой); - грунтовка глубокого проникновения; - шпатлёвка; - грунтовка глубокого проникновения δ = 25 мм | R11: 18.4 | S11: см. раздел АИ | T11: 20.4 | U11: -
A12: 2.58 | B12: Рекреация | C12: - грунтовка "Бетоноконтакт"; - гипсовая штукатурка; - грунтовка глубокого проникновения; - шпатлёвка; - грунтовка глубокого проникновения δ = 25 мм | D12: 43.1 | E12: - | F12: 0 | G12: - грунтовка глубокого проникновения; - гипсовая штукатурка; - грунтовка глубокого проникновения; - шпатлёвка; - грунтовка глубокого проникновения δ = 25 мм | H12: 53.7 | K12: - грунтовка глубокого проникновения; - гипсовая штукатурка; - грунтовка глубокого проникновения; - шпатлёвка; - грунтовка глубокого проникновения δ = 25 мм | L12: 19.1 | O12: см. раздел АИ | P12: 116 | Q12: - затирка; - грунтовка "Бетоноконтакт"; - шпатлёвка; - грунтовка глубокого проникновения δ = 5 мм | R12: 79.6 | S12: см. раздел АИ | T12: 27.6 | U12: Работы по черновой отделке выполнять при необходимост и выравнивания стен

Sheet Table 15
A1: Ведомость отделки помещений
A2: Ном ер пом еще ния | B2: Наименование помещения | C2: СТЕНЫ ИЛИ ПЕРЕГОРОДКИ | Q2: Основной тип потолка | S2: ПЛИНТУС | U2: Примечание
C3: Железобетон | E3: Кирпич | G3: Газобетон | I3: ГСП | K3: ПГП | M3: Утеплитель | O3: Финишный слой | Q3: Вид отделки | R3: Площадь, м² | S3: Вид отделки | T3: м.п.
C4: Вид отделки | D4: Площадь, м² | E4: Вид отделки | F4: Площадь, м² | G4: Вид отделки | H4: Площадь, м² | I4: Вид отделки | J4: Площадь, м² | K4: Вид отделки | L4: Площадь, м² | M4: Вид отделки | N4: Площадь, м² | O4: Вид отделки | P4: Площадь, м²
A5: 3.01 | B5: Учебный кабинет 2-4 класс | C5: - грунтовка "Бетоноконтакт"; - гипсовая штукатурка; - грунтовка глубокого проникновения; - шпатлёвка; - грунтовка глубокого проникновения δ = 25 мм | D5: 49.2 | G5: - грунтовка глубокого проникновения; - гипсовая штукатурка; - грунтовка глубокого проникновения; - шпатлёвка; - грунтовка глубокого проникновения δ = 25 мм | H5: 43.5 | K5: - грунтовка глубокого проникновения; - гипсовая штукатурка; - грунтовка глубокого проникновения; - шпатлёвка; - грунтовка глубокого проникновения δ = 25 мм | L5: 16.8 | O5: см. раздел АИ | P5: 109.4 | Q5: - обеспыливание | R5: 62.8 | S5: см. раздел АИ | T5: 25.1 | U5: Работы по черновой отделке выполнять при необходимост и выравнивания стен
A6: 3.02 | B6: Кабинет иностранного языка с возможностью деления трансформируемой перегородкой на два помещения | C6: - грунтовка "Бетоноконтакт"; - гипсовая штукатурка; - грунтовка глубокого проникновения; - шпатлёвка; - грунтовка глубокого проникновения δ = 25 мм | D6: 30.9 | G6: - грунтовка глубокого проникновения; - гипсовая штукатурка; - грунтовка глубокого проникновения; - шпатлёвка; - грунтовка глубокого проникновения δ = 25 мм | H6: 68.1 | K6: - грунтовка глубокого проникновения; - гипсовая штукатурка; - грунтовка глубокого проникновения; - шпатлёвка; - грунтовка глубокого проникновения δ = 25 мм | L6: 27.4 | O6: см. раздел АИ | P6: 126.4 | Q6: - обеспыливание | R6: 89.1 | S6: см. раздел АИ | T6: 22.7 | U6: Работы по черновой отделке выполнять при необходимост и выравнивания стен
A7: 3.03 | B7: Административный кабинет | C7: - грунтовка "Бетоноконтакт"; - гипсовая штукатурка; - грунтовка глубокого проникновения; - шпатлёвка; - грунтовка глубокого проникновения δ = 25 мм | D7: 17.4 | G7: - грунтовка глубокого проникновения; - гипсовая штукатурка; - грунтовка глубокого проникновения; - шпатлёвка; - грунтовка глубокого проникновения δ = 25 мм | H7: 48.7 | K7: - грунтовка глубокого проникновения; - гипсовая штукатурка; - грунтовка глубокого проникновения; - шпатлёвка; - грунтовка глубокого проникновения δ = 25 мм | L7: 16 | O7: см. раздел АИ | P7: 82.2 | Q7: - обеспыливание | R7: 29.7 | S7: см. раздел АИ | T7: 19.8 | U7: Работы по черновой отделке выполнять при необходимост и выравнивания стен
A8: 3.04 | B8: Учебный кабинет 2-4 класс | C8: - грунтовка "Бетоноконтакт"; - гипсовая штукатурка; - грунтовка глубокого проникновения; - шпатлёвка; - грунтовка глубокого проникновения δ = 25 мм | D8: 52.9 | G8: - грунтовка глубокого проникновения; - гипсовая штукатурка; - грунтовка глубокого проникновения; - шпатлёвка; - грунтовка глубокого проникновения δ = 25 мм | H8: 43.2 | K8: - грунтовка глубокого проникновения; - гипсовая штукатурка; - грунтовка глубокого проникновения; - шпатлёвка; - грунтовка глубокого проникновения δ = 25 мм | L8: 12.5 | O8: см. раздел АИ | P8: 108.7 | Q8: - обеспыливание | R8: 64.6 | S8: см. раздел АИ | T8: 25.1 | U8: Работы по черновой отделке выполнять при необходимост и выравнивания стен
A9: 3.05 | B9: Учебный кабинет 2-4 класс | C9: - грунтовка "Бетоноконтакт"; - гипсовая штукатурка; - грунтовка глубокого проникновения; - шпатлёвка; - грунтовка глубокого проникновения δ = 25 мм | D9: 84.1 | G9: - грунтовка глубокого проникновения; - гипсовая штукатурка; - грунтовка глубокого проникновения; - шпатлёвка; - грунтовка глубокого проникновения δ = 25 мм | H9: 11.3 | K9: - грунтовка глубокого проникновения; - гипсовая штукатурка; - грунтовка глубокого проникновения; - шпатлёвка; - грунтовка глубокого проникновения δ = 25 мм | L9: 15.3 | O9: см. раздел АИ | P9: 110.8 | Q9: - обеспыливание | R9: 69.5 | S9: см. раздел АИ | T9: 24.8 | U9: Работы по черновой отделке выполнять при необходимост и выравнивания стен
A10: 3.06 | B10: Учебный кабинет 2-4 класс | C10: - грунтовка "Бетоноконтакт"; - гипсовая штукатурка; - грунтовка глубокого проникновения; - шпатлёвка; - грунтовка глубокого проникновения δ = 25 мм | D10: 55.7 | G10: - грунтовка глубокого проникновения; - гипсовая штукатурка; - грунтовка глубокого проникновения; - шпатлёвка; - грунтовка глубокого проникновения δ = 25 мм | H10: 35.5 | K10: - грунтовка глубокого проникновения; - гипсовая штукатурка; - грунтовка глубокого проникновения; - шпатлёвка; - грунтовка глубокого проникновения δ = 25 мм | L10: 18.8 | O10: см. раздел АИ | P10: 110 | Q10: - обеспыливание | R10: 65.4 | S10: см. раздел АИ | T10: 25.2 | U10: Работы по черновой отделке выполнять при необходимост и выравнивания стен
A11: 3.07 | B11: Учебный кабинет 2-4 класс | C11: - грунтовка "Бетоноконтакт"; - гипсовая штукатурка; - грунтовка глубокого проникновения; - шпатлёвка; - грунтовка глубокого проникновения δ = 25 мм | D11: 55.3 | G11: - грунтовка глубокого проникновения; - гипсовая штукатурка; - грунтовка глубокого проникновения; - шпатлёвка; - грунтовка глубокого проникновения δ = 25 мм | H11: 36.7 | K11: - грунтовка глубокого проникновения; - гипсовая штукатурка; - грунтовка глубокого проникновения; - шпатлёвка; - грунтовка глубокого проникновения δ = 25 мм | L11: 15.3 | O11: см. раздел АИ | P11: 107.3 | Q11: - обеспыливание | R11: 63.7 | S11: см. раздел АИ | T11: 32.6 | U11: Работы по черновой отделке выполнять при необходимост и выравнивания стен
A12: 3.08 | B12: Учебный кабинет 2-4 класс | C12: - грунтовка "Бетоноконтакт"; - гипсовая штукатурка; - грунтовка глубокого проникновения; - шпатлёвка; - грунтовка глубокого проникновения δ = 25 мм | D12: 88.8 | G12: - грунтовка глубокого проникновения; - гипсовая штукатурка; - грунтовка глубокого проникновения; - шпатлёвка; - грунтовка глубокого проникновения δ = 25 мм | H12: 14.9 | K12: - | L12: 0 | O12: см. раздел АИ | P12: 103.7 | Q12: - обеспыливание | R12: 123.1 | S12: см. раздел АИ | T12: 33.3 | U12: Работы по черновой отделке выполнять при необходимост и выравнивания стен
A13: 3.09 | B13: Санузел для МГН | C13: - грунтовка "Бетоноконтакт"; - штукатурка цементно-песчаным раствором М100 (армированная стекловолоконной или пластиковой сеткой); - грунтовка глубокого проникновения δ = 20 мм | D13: 7.1 | G13: - | H13: 0 | K13: - грунтовка глубокого проникновения; - штукатурка цементно-песчаным раствором М100 (армированная стекловолоконной или пластиковой сеткой); - грунтовка глубокого проникновения δ = 20 мм | L13: 27.1 | O13: см. раздел АИ | P13: 34.2 | Q13: - затирка; - грунтовка "Бетоноконтакт "; - шпатлёвка; - грунтовка глубокого проникновения δ = 5 мм | R13: 5.4 | S13: см. раздел АИ | T13: 8.2 | U13: Работы по черновой отделке выполнять при необходимост и выравнивания стен
A14: 3.11 | B14: Санузел для мальчиков | C14: - грунтовка "Бетоноконтакт"; - штукатурка цементно-песчаным раствором М100 (армированная стекловолоконной или пластиковой сеткой); - грунтовка глубокого проникновения δ = 20 мм | D14: 49.2 | G14: - | H14: 0 | K14: - грунтовка глубокого проникновения; - штукатурка цементно-песчаным раствором М100 (армированная стекловолоконной или пластиковой сеткой); - грунтовка глубокого проникновения δ = 20 мм | L14: 29.9 | O14: см. раздел АИ | P14: 79.1 | Q14: - затирка; - грунтовка "Бетоноконтакт "; - шпатлёвка; - грунтовка глубокого проникновения δ = 5 мм | R14: 15.8 | S14: см. раздел АИ | T14: 20.2 | U14: Работы по черновой отделке выполнять при необходимост и выравнивания стен
A15: 3.12 | B15: Многофункциональн ый информационный библиотечный центр с зонами для индивидуальных и групповых занятий, медиатеки, читательских мест и выдачи книг | C15: - грунтовка "Бетоноконтакт"; - гипсовая штукатурка; - грунтовка глубокого проникновения; - шпатлёвка; - грунтовка глубокого проникновения δ = 25 мм | D15: 316.9 | G15: - грунтовка глубокого проникновения; - гипсовая штукатурка; - грунтовка глубокого проникновения; - шпатлёвка; - грунтовка глубокого проникновения δ = 25 мм | H15: 124.2 | K15: - грунтовка глубокого проникновения; - гипсовая штукатурка; - грунтовка глубокого проникновения; - шпатлёвка; - грунтовка глубокого проникновения δ = 25 мм | L15: 26.1 | O15: см. раздел АИ | P15: 467.2 | Q15: - затирка; - грунтовка "Бетоноконтакт "; - шпатлёвка; - грунтовка глубокого проникновения δ = 5 мм | R15: 256.9 | S15: см. раздел АИ | T15: 80.4 | U15: Работы по черновой отделке выполнять при необходимост и выравнивания стен
A16: 3.13 | B16: Книгохранилище | C16: - грунтовка "Бетоноконтакт"; - гипсовая штукатурка; - грунтовка глубокого проникновения; - шпатлёвка; - грунтовка глубокого проникновения δ = 25 мм | D16: 78.7 | G16: - | H16: 0 | K16: - | L16: 0 | O16: см. раздел АИ | P16: 78.7 | Q16: - обеспыливание | R16: 13.3 | S16: см. раздел АИ | T16: 13.8 | U16: Работы по черновой отделке выполнять при необходимост и выравнивания стен
... A22: 3.19 | B22: Коридор | C22: - грунтовка "Бетоноконтакт"; - гипсовая штукатурка; - грунтовка глубокого проникновения; - шпатлёвка; - грунтовка глубокого проникновения δ = 25 мм | D22: 150.9 | G22: - грунтовка глубокого проникновения; - гипсовая штукатурка; - грунтовка глубокого проникновения; - шпатлёвка; - грунтовка глубокого проникновения δ = 25 мм | H22: 117.1 | K22: - грунтовка глубокого проникновения; - гипсовая штукатурка; - грунтовка глубокого проникновения; - шпатлёвка; - грунтовка глубокого проникновения δ = 25 мм | L22: 2.2 | O22: см. раздел АИ | P22: 270.2 | Q22: - затирка; - грунтовка "Бетоноконтакт "; - шпатлёвка; - грунтовка глубокого проникновения δ = 5 мм | R22: 218.4 | S22: см. раздел АИ | T22: 52.4 | U22: Работы по черновой отделке выполнять при необходимост и выравнивания стен

Sheet Table 16
A1: Ведомость отделки помещений
A2: Ном ер пом еще ния | B2: Наименование помещения | C2: СТЕНЫ ИЛИ ПЕРЕГОРОДКИ | Q2: Основной тип потолка | S2: ПЛИНТУС | U2: Примечание
C3: Железобетон | E3: Кирпич | G3: Газобетон | I3: ГСП | K3: ПГП | M3: Утеплитель | O3: Финишный слой | Q3: Вид отделки | R3: Площадь, м² | S3: Вид отделки | T3: м.п.
C4: Вид отделки | D4: Площадь, м² | E4: Вид отделки | F4: Площадь, м² | G4: Вид отделки | H4: Площадь, м² | I4: Вид отделки | J4: Площадь, м² | K4: Вид отделки | L4: Площадь, м² | M4: Вид отделки | N4: Площадь, м² | O4: Вид отделки | P4: Площадь, м²
A5: 3.20 | B5: Лестничная клетка №3 (Тип Н2) | C5: - грунтовка "Бетоноконтакт"; - гипсовая штукатурка; - грунтовка глубокого проникновения; - шпатлёвка; - грунтовка глубокого проникновения δ = 25 мм | D5: 84.5 | G5: - | H5: 0 | K5: - | L5: 0 | O5: см. раздел АИ | P5: 84.5 | Q5: - затирка; - грунтовка "Бетоноконтакт "; - шпатлёвка; - грунтовка глубокого проникновения δ = 5 мм | R5: 48.5 | S5: см. раздел АИ | T5: 20.5 | U5: Работы по черновой отделке выполнять при необходимост и выравнивания стен
A6: 3.21 | B6: Лестничная клетка №4 (Тип Н2) | C6: - грунтовка "Бетоноконтакт"; - гипсовая штукатурка; - грунтовка глубокого проникновения; - шпатлёвка; - грунтовка глубокого проникновения δ = 25 мм | D6: 114.2 | G6: - | H6: 0 | K6: - грунтовка "Бетоноконтакт"; - гипсовая штукатурка; - грунтовка глубокого проникновения; - шпатлёвка; - грунтовка глубокого проникновения δ = 25 мм | L6: 18.6 | O6: см. раздел АИ | P6: 132.8 | Q6: - затирка; - грунтовка "Бетоноконтакт "; - шпатлёвка; - грунтовка глубокого проникновения δ = 5 мм | R6: 29.4 | S6: см. раздел АИ | T6: 23.3 | U6: Работы по черновой отделке выполнять при необходимост и выравнивания стен
A7: 3.23 | B7: Раздевальная комната | C7: - грунтовка "Бетоноконтакт"; - штукатурка цементно-песчаным раствором М100 (армированная стекловолоконной или пластиковой сеткой); - грунтовка глубокого проникновения; - шпатлёвка; - грунтовка глубокого проникновения δ = 25 мм | D7: 43.6 | G7: - грунтовка "Бетоноконтакт"; - штукатурка цементно-песчаным раствором М100 (армированная стекловолоконной или пластиковой сеткой); - грунтовка глубокого проникновения; - шпатлёвка; - грунтовка глубокого проникновения δ = 25 мм | H7: 6.3 | K7: - грунтовка "Бетоноконтакт"; - штукатурка цементно-песчаным раствором М100 (армированная стекловолоконной или пластиковой сеткой); - грунтовка глубокого проникновения; - шпатлёвка; - грунтовка глубокого проникновения δ = 25 мм | L7: 33.6 | O7: см. раздел АИ | P7: 83.5 | Q7: - грунтовка глубокого проникновения | R7: 21.6 | S7: см. раздел АИ | T7: 20.3 | U7: -
A8: 3.24 | B8: Буфет | C8: - грунтовка "Бетоноконтакт"; - штукатурка цементно-песчаным раствором М100 (армированная стекловолоконной или пластиковой сеткой); - грунтовка глубокого проникновения; - шпатлёвка; - грунтовка глубокого проникновения δ = 25 мм | D8: 0.1 | G8: - грунтовка "Бетоноконтакт"; - штукатурка цементно-песчаным раствором М100 (армированная стекловолоконной или пластиковой сеткой); - грунтовка глубокого проникновения; - шпатлёвка; - грунтовка глубокого проникновения δ = 25 мм | H8: 5 | K8: - грунтовка "Бетоноконтакт"; - штукатурка цементно-песчаным раствором М100 (армированная стекловолоконной или пластиковой сеткой); - грунтовка глубокого проникновения; - шпатлёвка; - грунтовка глубокого проникновения δ = 25 мм | L8: 34.3 | O8: см. раздел АИ | P8: 39.5 | Q8: - грунтовка глубокого проникновения | R8: 6.7 | S8: см. раздел АИ | T8: 9 | U8: Шпатлевание стен выполнять выше отм. +2,200 от ур.
A9: 3.25 | B9: Групповая | C9: - грунтовка "Бетоноконтакт"; - штукатурка цементно-песчаным раствором М100 (армированная стекловолоконной или пластиковой сеткой); - грунтовка глубокого проникновения; - шпатлёвка; - грунтовка глубокого проникновения δ = 25 мм | D9: 45.2 | G9: - | H9: 0 | K9: - грунтовка "Бетоноконтакт"; - штукатурка цементно-песчаным раствором М100 (армированная стекловолоконной или пластиковой сеткой); - грунтовка глубокого проникновения; - шпатлёвка; - грунтовка глубокого проникновения δ = 25 мм | L9: 34.1 | O9: см. раздел АИ | P9: 79.3 | Q9: - грунтовка глубокого проникновения | R9: 52.1 | S9: см. раздел АИ | T9: 16.5 | U9: -
A10: 3.26 | B10: Спальная | C10: - грунтовка "Бетоноконтакт"; - штукатурка цементно-песчаным раствором М100 (армированная стекловолоконной или пластиковой сеткой); - грунтовка глубокого проникновения; - шпатлёвка; - грунтовка глубокого проникновения δ = 25 мм | D10: 32.9 | G10: - грунтовка глубокого проникновения; - штукатурка цементно-песчаным раствором М100 (армированная стекловолоконной или пластиковой сеткой); - грунтовка глубокого проникновения; - шпатлёвка; - грунтовка глубокого проникновения δ = 25 мм | H10: 27.7 | K10: - грунтовка глубокого проникновения; - штукатурка цементно-песчаным раствором М100 (армированная стекловолоконной или пластиковой сеткой); - грунтовка глубокого проникновения; - шпатлёвка; - грунтовка глубокого проникновения δ = 25 мм | L10: 19.7 | O10: см. раздел АИ | P10: 80.4 | Q10: - грунтовка глубокого проникновения | R10: 57 | S10: см. раздел АИ | T10: 19.5 | U10: -
A11: 3.27 | B11: Туалет (в т.ч. МГН) | C11: - грунтовка "Бетоноконтакт"; - штукатурка цементно-песчаным раствором М100 (армированная стекловолоконной или пластиковой сеткой); - грунтовка глубокого проникновения δ = 20 мм | D11: 8.3 | G11: - | H11: 0 | K11: - грунтовка глубокого проникновения; - штукатурка цементно-песчаным раствором М100 (армированная стекловолоконной или пластиковой сеткой); - грунтовка глубокого проникновения δ = 20 мм | L11: 78.5 | O11: см. раздел АИ | P11: 86.7 | Q11: - грунтовка глубокого проникновения | R11: 29.6 | S11: см. раздел АИ | T11: 21.7 | U11: Работы по черновой отделке выполнять при необходимост и выравнивания стен
A12: 3.28 | B12: Раздевальная комната | C12: - грунтовка "Бетоноконтакт"; - штукатурка цементно-песчаным раствором М100 (армированная стекловолоконной или пластиковой сеткой); - грунтовка глубокого проникновения; - шпатлёвка; - грунтовка глубокого проникновения δ = 25 мм | D12: 27.9 | G12: - грунтовка "Бетоноконтакт"; - штукатурка цементно-песчаным раствором М100 (армированная стекловолоконной или пластиковой сеткой); - грунтовка глубокого проникновения; - шпатлёвка; - грунтовка глубокого проникновения δ = 25 мм | H12: 15.1 | K12: - грунтовка "Бетоноконтакт"; - штукатурка цементно-песчаным раствором М100 (армированная стекловолоконной или пластиковой сеткой); - грунтовка глубокого проникновения; - шпатлёвка; - грунтовка глубокого проникновения δ = 25 мм | L12: 33.7 | O12: см. раздел АИ | P12: 76.8 | Q12: - грунтовка глубокого проникновения | R12: 21.6 | S12: см. раздел АИ | T12: 18.1 | U12: -
A13: 3.29 | B13: Групповая | C13: - грунтовка "Бетоноконтакт"; - штукатурка цементно-песчаным раствором М100 (армированная стекловолоконной или пластиковой сеткой); - грунтовка глубокого проникновения; - шпатлёвка; - грунтовка глубокого проникновения δ = 25 мм | D13: 27.8 | G13: - | H13: 0 | K13: (армированная стекловолоконной или пластиковой сеткой); - грунтовка глубокого | L13: 34.2 | O13: см. раздел АИ | P13: 62 | Q13: - грунтовка глубокого проникновения | R13: 51.6 | S13: см. раздел АИ | T13: 14.1 | U13: -
A14: 3.31 | B14: Буфет | C14: - грунтовка "Бетоноконтакт"; - штукатурка цементно-песчаным раствором М100 (армированная стекловолоконной или пластиковой сеткой); - грунтовка глубокого проникновения; - шпатлёвка; - грунтовка глубокого проникновения δ = 25 мм | D14: 0.1 | G14: - грунтовка "Бетоноконтакт"; - штукатурка цементно-песчаным раствором М100 (армированная стекловолоконной или пластиковой сеткой); - грунтовка глубокого проникновения; - шпатлёвка; - грунтовка глубокого проникновения δ = 25 мм | H14: 5 | K14: - грунтовка "Бетоноконтакт"; - штукатурка цементно-песчаным раствором М100 (армированная стекловолоконной или пластиковой сеткой); - грунтовка глубокого проникновения; - шпатлёвка; - грунтовка глубокого проникновения δ = 25 мм | L14: 34.4 | O14: см. раздел АИ | P14: 39.5 | Q14: - грунтовка глубокого проникновения | R14: 6.7 | S14: см. раздел АИ | T14: 9 | U14: Шпатлевание стен выполнять выше отм. +2,200 от ур.
A15: 3.32 | B15: Туалет (в т.ч. МГН) | C15: - грунтовка "Бетоноконтакт"; - штукатурка цементно-песчаным раствором М100 (армированная стекловолоконной или пластиковой сеткой); - грунтовка глубокого проникновения; - шпатлёвка; - грунтовка глубокого проникновения δ = 25 мм | D15: 8.5 | G15: - | H15: 0 | K15: - грунтовка "Бетоноконтакт"; - штукатурка цементно-песчаным раствором М100 (армированная стекловолоконной или пластиковой сеткой); - грунтовка глубокого проникновения; - шпатлёвка; - грунтовка глубокого проникновения δ = 25 мм | L15: 78.5 | O15: см. раздел АИ | P15: 87 | Q15: - грунтовка глубокого проникновения | R15: 29.6 | S15: см. раздел АИ | T15: 21.7 | U15: черновой отделке выполнять при
A16: 3.33 | B16: Помещение (open space) для администрации , с рабочими местами для музыкального руководителя , воспитателя | C16: - грунтовка "Бетоноконтакт"; - штукатурка цементно-песчаным раствором М100 (армированная стекловолоконной или пластиковой сеткой); - грунтовка глубокого проникновения; - шпатлёвка; - грунтовка глубокого проникновения δ = 25 мм | D16: 56.3 | G16: - грунтовка "Бетоноконтакт"; - штукатурка цементно-песчаным раствором М100 (армированная стекловолоконной или пластиковой сеткой); - грунтовка глубокого проникновения; - шпатлёвка; - грунтовка глубокого проникновения δ = 25 мм | H16: 59.7 | K16: - грунтовка "Бетоноконтакт"; - штукатурка цементно-песчаным раствором М100 (армированная стекловолоконной или пластиковой сеткой); - грунтовка глубокого проникновения; - шпатлёвка; - грунтовка глубокого проникновения δ = 25 мм | L16: 9.1 | O16: см. раздел АИ | P16: 125.1 | Q16: - грунтовка глубокого проникновения | R16: 78.3 | S16: см. раздел АИ | T16: 35.6 | U16: -
A17: 3.34 | B17: Вспомогательное помещение | C17: - грунтовка "Бетоноконтакт"; - штукатурка цементно-песчаным раствором М100 (армированная стекловолоконной или пластиковой сеткой); - грунтовка глубокого проникновения; - шпатлёвка; - грунтовка глубокого проникновения δ = 25 мм | D17: 33.8 | G17: - грунтовка глубокого проникновения; - штукатурка цементно-песчаным раствором М100 (армированная стекловолоконной или пластиковой сеткой); - грунтовка глубокого проникновения; - шпатлёвка; - грунтовка глубокого проникновения δ = 25 мм | H17: 4.8 | K17: - грунтовка глубокого проникновения; - штукатурка цементно-песчаным раствором М100 (армированная стекловолоконной или пластиковой сеткой); - грунтовка глубокого проникновения; - шпатлёвка; - грунтовка глубокого проникновения δ = 25 мм | L17: 2.6 | O17: см. раздел АИ | P17: 41.2 | Q17: - грунтовка глубокого проникновения | R17: 6.9 | S17: см. раздел АИ | T17: 10 | U17: -

Sheet Table 17
A1: Ведомость отделки помещений
A2: Ном ер пом еще ния | B2: Наименование помещения | C2: СТЕНЫ ИЛИ ПЕРЕГОРОДКИ | Q2: Основной тип потолка | S2: ПЛИНТУС | U2: Примечание
C3: Железобетон | E3: Кирпич | G3: Газобетон | I3: ГСП | K3: ПГП | M3: Утеплитель | O3: Финишный слой | Q3: Вид отделки | R3: Площадь, м² | S3: Вид отделки | T3: м.п.
C4: Вид отделки | D4: Площадь, м² | E4: Вид отделки | F4: Площадь, м² | G4: Вид отделки | H4: Площадь, м² | I4: Вид отделки | J4: Площадь, м² | K4: Вид отделки | L4: Площадь, м² | M4: Вид отделки | N4: Площадь, м² | O4: Вид отделки | P4: Площадь, м²
A5: 3.35 | B5: Кабинет для развивающих занятий с возможностью зонирования раздвижной трансформируемой перегородкой | C5: - грунтовка "Бетоноконтакт"; - штукатурка цементно-песчаным раствором М100 (армированная стекловолоконной или пластиковой сеткой); - грунтовка глубокого проникновения; - шпатлёвка; - грунтовка глубокого проникновения δ = 25 мм | D5: 44.1 | E5: - | F5: 0 | G5: - грунтовка глубокого проникновения; - штукатурка цементно-песчаным раствором М100 (армированная стекловолоконной или пластиковой сеткой); - грунтовка глубокого проникновения; - шпатлёвка; - грунтовка глубокого проникновения δ = 25 мм | H5: 64.4 | K5: - грунтовка глубокого проникновения; - штукатурка цементно-песчаным раствором М100 (армированная стекловолоконной или пластиковой сеткой); - грунтовка глубокого проникновения; - шпатлёвка; - грунтовка глубокого проникновения δ = 25 мм | L5: 5.7 | O5: см. раздел АИ | P5: 114.2 | Q5: - грунтовка глубокого проникновения | R5: 77.8 | S5: см. раздел АИ | T5: 31.9 | U5: -
A6: 3.36 | B6: Помещение приёма и сортировки грязного белья | C6: - грунтовка "Бетоноконтакт"; - штукатурка цементно-песчаным раствором М100 (армированная стекловолоконной или пластиковой сеткой); - грунтовка глубокого проникновения δ = 20 мм | D6: 9.1 | E6: - | F6: 0 | G6: - грунтовка глубокого проникновения; - штукатурка цементно-песчаным раствором М100 (армированная стекловолоконной или пластиковой сеткой); - грунтовка глубокого проникновения δ = 20 мм | H6: 16.4 | K6: - грунтовка глубокого проникновения; - штукатурка цементно-песчаным раствором М100 (армированная стекловолоконной или пластиковой сеткой); - грунтовка глубокого проникновения δ = 20 мм | L6: 13.6 | O6: см. раздел АИ | P6: 39.1 | Q6: - грунтовка глубокого проникновения | R6: 6 | S6: см. раздел АИ | T6: 9.4 | U6: Работы по черновой отделке выполнять при необходимост и выравнивания стен
A7: 3.37 | B7: Комната чистого белья | C7: - грунтовка "Бетоноконтакт"; - штукатурка цементно-песчаным раствором М100 (армированная стекловолоконной или пластиковой сеткой); - грунтовка глубокого проникновения δ = 20 мм | D7: 24.8 | E7: - | F7: 0 | G7: - | H7: 0 | K7: - грунтовка глубокого проникновения; - штукатурка цементно-песчаным раствором М100 (армированная стекловолоконной или пластиковой сеткой); - грунтовка глубокого проникновения δ = 20 мм | L7: 13.6 | O7: см. раздел АИ | P7: 38.5 | Q7: - грунтовка глубокого проникновения | R7: 6.1 | S7: см. раздел АИ | T7: 9.5 | U7: Работы по черновой отделке выполнять при необходимост и выравнивания стен
A8: 3.38 | B8: Лестничная клетка №5 (Тип Н2) | C8: - грунтовка "Бетоноконтакт"; - штукатурка цементно-песчаным раствором М100 (армированная стекловолоконной или пластиковой сеткой); - грунтовка глубокого проникновения; - шпатлёвка; - грунтовка глубокого проникновения δ = 25 мм | D8: 103.5 | E8: - | F8: 0 | G8: - | H8: 0 | K8: - | L8: 0 | O8: см. раздел АИ | P8: 103.5 | Q8: - грунтовка "Бетоноконтакт"; - штукатурка цементно-песчаным раствором М100 (армированная стальной оцинкованной сеткой); - грунтовка глубокого проникновения; - шпатлёвка; - грунтовка глубокого проникновения δ = 25 мм | R8: 32.1 | S8: см. раздел АИ | T8: 28.7 | U8: -
A9: 3.39 | B9: Лифтовой холл (зона безопасности) | C9: - грунтовка "Бетоноконтакт"; - штукатурка цементно-песчаным раствором М100 (армированная стекловолоконной или пластиковой сеткой); - грунтовка глубокого проникновения; - шпатлёвка; - грунтовка глубокого проникновения δ = 25 мм | D9: 19.3 | E9: - | F9: 0 | G9: - грунтовка глубокого проникновения; - штукатурка цементно-песчаным раствором М100 (армированная стекловолоконной или пластиковой сеткой); - грунтовка глубокого проникновения; - шпатлёвка; - грунтовка глубокого проникновения δ = 25 мм | H9: 4.6 | K9: - грунтовка глубокого проникновения; - штукатурка цементно-песчаным раствором М100 (армированная стекловолоконной или пластиковой сеткой); - грунтовка глубокого проникновения; - шпатлёвка; - грунтовка глубокого проникновения δ = 25 мм | L9: 13.1 | O9: см. раздел АИ | P9: 37 | Q9: - грунтовка глубокого проникновения | R9: 5.9 | S9: см. раздел АИ | T9: 7.9 | U9: -
A10: 3.40 | B10: Помещение уборочного инвентаря | C10: - грунтовка "Бетоноконтакт"; - штукатурка цементно-песчаным раствором М100 (армированная стекловолоконной или пластиковой сеткой); - грунтовка глубокого проникновения δ = 20 мм | D10: 10.9 | E10: - грунтовка глубокого проникновения; - штукатурка цементно-песчаным раствором М100 (армированная стекловолоконной или пластиковой сеткой); - грунтовка глубокого проникновения δ = 20 мм | F10: 5.2 | G10: - грунтовка глубокого проникновения; - штукатурка цементно-песчаным раствором М100 (армированная стекловолоконной или пластиковой сеткой); - грунтовка глубокого проникновения δ = 20 мм | H10: 12.8 | K10: - грунтовка глубокого проникновения; - штукатурка цементно-песчаным раствором М100 (армированная стекловолоконной или пластиковой сеткой); - грунтовка глубокого проникновения δ = 20 мм | L10: 11.5 | O10: см. раздел АИ | P10: 40.4 | Q10: - грунтовка глубокого проникновения | R10: 6.3 | S10: см. раздел АИ | T10: 9.8 | U10: Работы по черновой отделке выполнять при необходимост и выравнивания стен
A11: 3.41 | B11: Коридор | C11: - грунтовка "Бетоноконтакт"; - штукатурка цементно-песчаным раствором М100 (армированная стекловолоконной или пластиковой сеткой); - грунтовка глубокого проникновения; - шпатлёвка; - грунтовка глубокого проникновения δ = 25 мм | D11: 40.8 | E11: - грунтовка глубокого проникновения; - штукатурка цементно-песчаным раствором М100 (армированная стекловолоконной или пластиковой сеткой); - грунтовка глубокого проникновения; - шпатлёвка; - грунтовка глубокого проникновения δ = 25 мм | F11: 3.7 | G11: - грунтовка глубокого проникновения; - штукатурка цементно-песчаным раствором М100 (армированная стекловолоконной или пластиковой сеткой); - грунтовка глубокого проникновения; - шпатлёвка; - грунтовка глубокого проникновения δ = 25 мм | H11: 43.9 | K11: - грунтовка глубокого проникновения; - штукатурка цементно-песчаным раствором М100 (армированная стекловолоконной или пластиковой сеткой); - грунтовка глубокого проникновения; - шпатлёвка; - грунтовка глубокого проникновения δ = 25 мм | L11: 4.9 | O11: см. раздел АИ | P11: 93.3 | Q11: - грунтовка глубокого проникновения | R11: 38.7 | S11: см. раздел АИ | T11: 16.9 | U11: -
A12: 3.42 | B12: Коридор | C12: - грунтовка "Бетоноконтакт"; - штукатурка цементно-песчаным раствором М100 (армированная стекловолоконной или пластиковой сеткой); - грунтовка глубокого проникновения; - шпатлёвка; - грунтовка глубокого проникновения δ = 25 мм | D12: 58 | E12: - | F12: 0 | G12: - грунтовка глубокого проникновения; - штукатурка цементно-песчаным раствором М100 (армированная стекловолоконной или пластиковой сеткой); - грунтовка глубокого проникновения; - шпатлёвка; - грунтовка глубокого проникновения δ = 25 мм | H12: 115.9 | K12: - грунтовка глубокого проникновения; - штукатурка цементно-песчаным раствором М100 (армированная стекловолоконной или пластиковой сеткой); - грунтовка глубокого проникновения; - шпатлёвка; - грунтовка глубокого проникновения δ = 25 мм | L12: 7 | O12: см. раздел АИ | P12: 180.9 | Q12: - грунтовка глубокого проникновения | R12: 62.9 | S12: см. раздел АИ | T12: 40.1 | U12: -
A13: 3.43 | B13: Лестничная клетка №6 (Тип Л1) | C13: - грунтовка "Бетоноконтакт"; - штукатурка цементно-песчаным раствором М100 (армированная стекловолоконной или пластиковой сеткой); - грунтовка глубокого проникновения; - шпатлёвка; - грунтовка глубокого проникновения δ = 25 мм | D13: 83.5 | E13: - | F13: 0 | G13: - | H13: 0 | K13: - | L13: 0 | O13: см. раздел АИ | P13: 83.5 | Q13: - грунтовка "Бетоноконтакт"; - штукатурка цементно-песчаным раствором М100 (армированная стальной оцинкованной сеткой); - грунтовка глубокого проникновения; - шпатлёвка; - грунтовка глубокого проникновения δ = 25 мм | R13: 28 | S13: см. раздел АИ | T13: 20.4 | U13: -
A14: 3.44 | B14: Коридор | C14: - грунтовка "Бетоноконтакт"; - гипсовая штукатурка; - грунтовка глубокого проникновения; - шпатлёвка; - грунтовка глубокого проникновения δ = 25 мм | D14: 17.7 | E14: - | F14: 0 | G14: - грунтовка глубокого проникновения; - гипсовая штукатурка; - грунтовка глубокого проникновения; - шпатлёвка; - грунтовка глубокого проникновения δ = 25 мм | H14: 31.5 | K14: - | L14: 0 | O14: см. раздел АИ | P14: 49.2 | Q14: - затирка; - грунтовка "Бетоноконтакт"; - шпатлёвка; - грунтовка глубокого проникновения δ = 5 мм | R14: 21.8 | S14: см. раздел АИ | T14: 9.4 | U14: Работы по черновой отделке выполнять при необходимост и выравнивания стен
A15: 3.45 | B15: Рекреация | C15: - грунтовка "Бетоноконтакт"; - гипсовая штукатурка; - грунтовка глубокого проникновения; - шпатлёвка; - грунтовка глубокого проникновения δ = 25 мм | D15: 51.7 | E15: - | F15: 0 | G15: - грунтовка глубокого проникновения; - гипсовая штукатурка; - грунтовка глубокого проникновения; - шпатлёвка; - грунтовка глубокого проникновения δ = 25 мм | H15: 37.6 | K15: - грунтовка глубокого проникновения; - гипсовая штукатурка; - грунтовка глубокого проникновения; - шпатлёвка; - грунтовка глубокого проникновения δ = 25 мм | L15: 24.6 | O15: см. раздел АИ | P15: 113.8 | Q15: - затирка; - грунтовка "Бетоноконтакт"; - шпатлёвка; - грунтовка глубокого проникновения δ = 5 мм | R15: 87.4 | S15: см. раздел АИ | T15: 32.7 | U15: Работы по черновой отделке выполнять при необходимост и выравнивания стен

Sheet 10.9СС
A1: Ведомость работ
A2: № п.п. | B2: Наименование затрат | E2: Ед. изм. | F2: Объем
A3: 1 | B3: Восстановление шпаклевки стен в нишах ЭОМ и СС / шпаклевка финишная | E3: м2 | F3: =B10 -> 363.445
A4: 2 | B4: Лакокрасочные работы СКБ / окраска стен / в 2 слоя | E4: м2 | F4: =B10 -> 363.445
A6: № | B6: Объем, м2
A7: 1 | B7: =35.1*4-13*0.65*2.1 -> 122.655
A8: 2 | B8: =36.67*4-13*0.65*2.1 -> 128.935
A9: 3 | B9: =32.4*4-13*0.65*2.1 -> 111.855
A10: Итог: | B10: =SUM(B7:B9) -> 363.445

Sheet 10.8Ршт
A1: Ведомость работ
A2: № п.п. | B2: Наименование затрат | E2: Ед. изм. | F2: Объем
A3: 1 | B3: Установка металлических решеток на радиаторы отопления / 5 шт. | E3: м2 | F3: =C11 -> 3.95
A5: № | B5: Размеры | C5: Объем
A6: 1 | B6: 0,5 м х 1,3 м | C6: =0.5*1.3 -> 0.65
A7: 2 | B7: 0,5 м х 1,3 м | C7: =0.5*1.3 -> 0.65
A8: 3 | B8: 0,5 м х 1,7 м | C8: =0.5*1.7 -> 0.85
A9: 4 | B9: 0,5 м х 1,8 м | C9: =0.5*1.8 -> 0.9
A10: 5 | B10: 0,5 м х 1,8 м | C10: =0.5*1.8 -> 0.9
A11: Итог: | C11: =SUM(C6:C10) -> 3.95

Sheet 10.7Люк
A1: Ведомость работ
A2: № п.п. | B2: Наименование затрат | E2: Описание | F2: Ед. изм. | G2: Объем
A3: 1 | B3: Установка люков / в потолке | E3: Люк ревизионный с замком 60х60 см. | F3: шт | G3: 3
A5: Пом. | B5: Объем
A6: 1.38 | B6: 1
A7: 2.32 | B7: 1
A8: 2.28 | B8: 1

Sheet 10.6Люк
A1: Ведомость работ
A2: № п.п. | B2: Наименование затрат | E2: Описание | F2: Ед. изм. | G2: Объем
A3: 1 | B3: Установка люков / в потолке | E3: Люк ревизионный с замком 20х30 см. | F3: шт | G3: 3
A5: Пом. | B5: Объем
A6: 1.58 | B6: 3

Sheet 10.5Люк
A1: Ведомость работ
A2: № п.п. | B2: Наименование затрат | E2: Описание | F2: Ед. изм. | G2: Объем
A3: 1 | B3: Установка люков / в потолке | E3: Люк ревизионный с замком 30х30 см. | F3: шт | G3: 9
A5: Пом. | B5: Объем
A6: 2.47 | B6: 9

Sheet 10.4Люк
A1: Ведомость работ
A2: № п.п. | B2: Наименование затрат | D2: Описание | E2: Ед. изм. | F2: Объем
A3: 1 | B3: Монтаж металлических дверей (в т.ч. монтаж доводчиков, доборов и пр.) / Спец. Помещения | D3: Люк-дверь "Хаммер" 700х2100 мм. | E3: шт | F3: 2
A5: Пом. | B5: Объем
A6: 1.05 | B6: 1
A7: 3.39 | B7: 1

Sheet 10.3Прх
A1: Ведомость работ
A2: № п.п. | B2: Наименование затрат | J2: Ед. изм. | K2: Объем
A3: 1 | B3: Заделка отверстий в стенах в местах прохода коммуникации / до 150 мм | J3: шт | K3: =E23+H33+K21+B26 -> 777
A5: Пом. | B5: Объем | D5: Пом. | E5: Объем | G5: Пом. | H5: Объем | J5: Пом. | K5: Объем
A6: 1.03 | B6: 1 | D6: 1.37 | E6: 4 | G6: 2.01 | H6: 10 | J6: 3.01 | K6: 8
A7: 1.06 | B7: 4 | D7: 1.38 | E7: 9 | G7: 2.02 | H7: 16 | J7: 3.02 | K7: 8
A8: 1.07 | B8: 7 | D8: 1.39 | E8: 8 | G8: 2.03 | H8: 20 | J8: 3.03 | K8: 12
A9: 1.08 | B9: 20 | D9: 1.40 | E9: 20 | G9: 2.04 | H9: 9 | J9: 3.04 | K9: 8
A10: 1.09 | B10: 11 | D10: 1.41 | E10: 21 | G10: 2.05 | H10: 10 | J10: 3.05 | K10: 7
A11: 1.10 | B11: 12 | D11: 1.42 | E11: 12 | G11: 2.06 | H11: 7 | J11: 3.06 | K11: 12
A12: 1.11 | B12: 6 | D12: 1.45 | E12: 8 | G12: 2.07 | H12: 7 | J12: 3.07 | K12: 7
A13: 1.12 | B13: 20 | D13: 1.46 | E13: 4 | G13: 2.08 | H13: 29 | J13: 3.08 | K13: 6
A14: 1.13 | B14: 8 | D14: 1.49 | E14: 6 | G14: 2.09 | H14: 18 | J14: 3.09 | K14: 4
A15: 1.14 | B15: 5 | D15: 1.50 | E15: 10 | G15: 2.10 | H15: 11 | J15: 3.10 | K15: 8
A16: 1.15 | B16: 9 | D16: 1.51 | E16: 9 | G16: 2.11 | H16: 5 | J16: 3.11 | K16: 10
A17: 1.16 | B17: 8 | D17: 1.52 | E17: 6 | G17: 2.12 | H17: 4 | J17: 3.12 | K17: 17
... A20: 1.19 | B20: 8 | D20: 1.55 | E20: 5 | G20: 2.16 | H20: 3 | J20: 3.45 | K20: 6
A21: 1.21 | B21: 4 | D21: 1.56 | E21: 12 | G21: 2.17 | H21: 23 | J21: Итог | K21: =SUM(K6:K20) -> 139
A22: 1.22 | B22: 7 | D22: 1.57 | E22: 10 | G22: 2.20 | H22: 12
A23: 1.25 | B23: 11 | D23: Итог | E23: =SUM(E6:E22) -> 163 | G23: 2.21 | H23: 10
A24: 1.26 | B24: 10 | G24: 2.22 | H24: 4
A25: 1.36 | B25: 12 | G25: 2.23 | H25: 7
A26: Итог | B26: =SUM(B6:B25) -> 188 | G26: 2.24 | H26: 6
G27: 2.25 | H27: 2
G28: 2.26 | H28: 4
G29: 2.27 | H29: 9
G30: 2.28 | H30: 25
G31: 2.33 | H31: 11
G32: 2.58 | H32: 2
G33: Итог | H33: =SUM(H6:H32) -> 287

Sheet 10.2Крс
A1: Ведомость работ
A2: № п.п. | B2: Наименование затрат | E2: Описание | G2: Ед. изм. | H2: Объем
A3: 1 | B3: Лакокрасочные работы СКБ / окраска стен / в 2 слоя | E3: Ремонт (демонтаж/монтаж) окраски стен под радиаторами отопления | G3: м2 | H3: 120.7
A5: Пом. | B5: Объем | D5: Пом. | E5: Объем | G5: Пом. | H5: Объем
A6: 1.04 | B6: 2.7 | D6: 2.07 | E6: 4.74 | G6: 3.08 | H6: 4.8
A7: 1.05 | B7: 1.98 | D7: 2.12 | E7: 2.04 | G7: 3.18 | H7: 3.71
A8: 1.08 | B8: 9.18 | D8: 2.15 | E8: 2.04 | G8: 3.23 | H8: 1.45
A9: 1.19 | B9: 2.1 | D9: 2.21 | E9: 1.98 | G9: 3.25 | H9: 5.75
A10: 1.60 | B10: 5.64 | D10: 2.28 | E10: 7.56 | G10: 3.28 | H10: 1.45
A11: 1.61 | B11: 1.63 | D11: 2.37 | E11: 1.45 | G11: 3.29 | H11: 5.75
A12: 1.67 | B12: 5.75 | D12: 2.40 | E12: 5.75 | G12: 3.33 | H12: 5.28
A13: 1.73 | B13: 5.75 | D13: 2.42 | E13: 1.45 | G13: 3.35 | H13: 5.4
A14: Итог | B14: =SUM(B6:B13) -> 34.73 | D14: 2.44 | E14: 5.75 | G14: 3.45 | H14: 7.26
D15: 2.47 | E15: 5.28 | G15: Итог | H15: =SUM(H6:H14) -> 40.85
D16: 2.49 | E16: 5.28
D17: 2.58 | E17: 1.8
D18: Итог | E18: =SUM(E6:E17) -> 45.12

Sheet 10.1Шт
A1: Ведомость работ
A2: № п.п. | B2: Наименование затрат | K2: Ед. изм. | M2: Объем
A3: 1 | B3: Штукатурка стен сухими смесями с установкой маяков с предварительной огрунтовкой / толщ. от 21,5 до 26 мм / по бетону | K3: м2 | M3: =B36+E35 -> 2168.08
A4: 2 | B4: Штукатурка стен сухими смесями с установкой маяков с предварительной огрунтовкой / толщ. от 21,5 до 26 мм / по блоку ячеистому, кирпичу и ПГП | K4: м2 | M4: =H36+K26 -> 1279.31
A5: 3 | B5: Штукатурка стен цементным, цементно-песчаным раствором с предварительной огрунтовкой / толщ. от 21 до 40 мм / высотой до 4 метров / Блок, Кирпич, ПГП | K5: м2 | M5: =N19 -> 163.92
A7: Пункт №1. | D7: Пункт №1. | G7: Пункт №2. | J7: Пункт №2. | M7: Пункт №3.
A8: Пом. | B8: Объем | D8: Пом. | E8: Объем | G8: Пом. | H8: Объем | J8: Пом. | K8: Объем | M8: Пом. | N8: Объем
A9: 1.04 | B9: 9.71 | D9: 2.35 | E9: 9.5 | G9: 1.04 | H9: 19.4 | J9: 2.51 | K9: 3.6 | M9: 1.49 | N9: 6
A10: 1.27 | B10: 2.1 | D10: 2.37 | E10: 9.27 | G10: 1.20 | H10: 25.6 | J10: 2.53 | K10: 1.7 | M10: 1.52 | N10: 10.14
A11: 1.30 | B11: 20.75 | D11: 2.42 | E11: 9.27 | G11: 1.25 | H11: 30.23 | J11: 2.55 | K11: 7.8 | M11: 1.58 | N11: 17.19
A12: 1.31 | B12: 46.34 | D12: 2.49 | E12: 5.25 | G12: 1.26 | H12: 18.85 | J12: 2.58 | K12: 15.6 | M12: 1.65 | N12: 19.76
A13: 1.32 | B13: 74.61 | D13: 2.51 | E13: 33.54 | G13: 1.27 | H13: 14.43 | J13: 3.12 | K13: 52.64 | M13: 1.71 | N13: 19.76
A14: 1.33 | B14: 78.49 | D14: 2.53 | E14: 7.02 | G14: 1.31 | H14: 21.54 | J14: 3.21 | K14: 1.7 | M14: 1.75 | N14: 12.03
A15: 1.34 | B15: 78.74 | D15: 2.54 | E15: 100.77 | G15: 1.35 | H15: 13.26 | J15: 3.22 | K15: 11.54 | M15: 2.38 | N15: 19.76
A16: 1.35 | B16: 67.17 | D16: 2.55 | E16: 15.6 | G16: 1.38 | H16: 166.63 | J16: 3.23 | K16: 33.03 | M16: 2.43 | N16: 19.76
A17: 1.38 | B17: 52.67 | D17: 2.56 | E17: 22.35 | G17: 1.60 | H17: 53.32 | J17: 3.25 | K17: 33.13 | M17: 3.24 | N17: 19.76
A18: 1.60 | B18: 21.06 | D18: 2.57 | E18: 78.06 | G18: 1.67 | H18: 33.13 | J18: 3.28 | K18: 33.03 | M18: 3.31 | N18: 19.76
A19: 1.69 | B19: 10.14 | D19: 3.08 | E19: 31.59 | G19: 1.69 | H19: 36.93 | J19: 3.29 | K19: 33.11 | M19: Итог | N19: =SUM(N9:N18) -> 163.92
A20: 1.76 | B20: 7.37 | D20: 3.12 | E20: 31 | G20: 1.73 | H20: 33.13 | J20: 3.33 | K20: 10.5
A21: 1.77 | B21: 15.4 | D21: 3.17 | E21: 61.8 | G21: 1.76 | H21: 3.35 | J21: 3.37 | K21: 1.7
A22: 1.78 | B22: 22.34 | D22: 3.18 | E22: 53.46 | G22: 1.77 | H22: 15.4 | J22: 3.39 | K22: 7.8
A23: 1.79 | B23: 100.77 | D23: 3.19 | E23: 47.4 | G23: 1.81 | H23: 9.05 | J23: 3.41 | K23: 3.6
A24: 1.80 | B24: 68.28 | D24: 3.20 | E24: 81.96 | G24: 2.08 | H24: 107.54 | J24: 3.44 | K24: 11.7
A25: 1.81 | B25: 7.02 | D25: 3.21 | E25: 8.75 | G25: 2.12 | H25: 28.16 | J25: 3.45 | K25: 15.6
A26: 2.07 | B26: 31.59 | D26: 3.23 | E26: 9.27 | G26: 2.19 | H26: 202.19 | J26: Итог | K26: =SUM(K9:K25) -> 277.78
A27: 2.08 | B27: 19.67 | D27: 3.28 | E27: 9.27 | G27: 2.27 | H27: 11.7
A28: 2.12 | B28: 6.27 | D28: 3.35 | E28: 5.25 | G28: 2.33 | H28: 1.63
A29: 2.19 | B29: 191.85 | D29: 3.37 | E29: 7.03 | G29: 2.35 | H29: 1.7
A30: 2.20 | B30: 28.05 | D30: 3.38 | E30: 100.77 | G30: 2.36 | H30: 11.54
A31: 2.28 | B31: 53.46 | D31: 3.39 | E31: 15.6 | G31: 2.37 | H31: 33.03
A32: 2.30 | B32: 47.4 | D32: 3.41 | E32: 33.54 | G32: 2.40 | H32: 33.13
A33: 2.31 | B33: 61.8 | D33: 3.42 | E33: 22.35 | G33: 2.42 | H33: 33.03
A34: 2.32 | B34: 79.84 | D34: 3.43 | E34: 73.56 | G34: 2.44 | H34: 33.13
A35: 2.34 | B35: 81.96 | D35: Итог | E35: =SUM(E9:E34) -> 883.23 | G35: 2.47 | H35: 10.5
A36: Итог | B36: =SUM(B9:B35) -> 1284.85 | G36: Итог | H36: =SUM(H9:H35) -> 1001.53

Sheet 9.10Грб
A1: Спецификация выполненных работ
A2: № п.п. | B2: Наименование | I2: Ед. изм. | J2: Объем
A3: 1 | B3: Обработка поверхностей антигрибковым составом / стены | I3: м2 | J3: =C38+G44+K41 -> 3850.15
A5: № п.п. | B5: Пом.: | C5: Объем, м² | E5: № п.п. | F5: Пом.: | G5: Объем, м² | I5: № п.п. | J5: Пом.: | K5: Объем, м²
A6: 1 | B6: 1.04 | C6: =1.35*2 -> 2.7 | E6: 33 | F6: 2.01 | G6: 39.22 | I6: 71 | J6: 3.01 | K6: 39.735
A7: 2 | B7: 1.05 | C7: 44.165 | E7: 34 | F7: 2.02 | G7: 57.45 | I7: 72 | J7: 3.02 | K7: 52.485
A8: 3 | B8: 1.07 | C8: 23.35 | E8: 35 | F8: 2.03 | G8: 41.79 | I8: 73 | J8: 3.03 | K8: 26.6
A9: 4 | B9: 1.08 | C9: 76.86 | E9: 36 | F9: 2.04 | G9: 41.195 | I9: 74 | J9: 3.04 | K9: 39.505
A10: 5 | B10: 1.09 | C10: =2*2 -> 4 | E10: 37 | F10: 2.05 | G10: 37.565 | I10: 75 | J10: 3.05 | K10: 39.61
A11: 6 | B11: 1.11 | C11: =2*2.5 -> 5 | E11: 38 | F11: 2.06 | G11: 38.795 | I11: 76 | J11: 3.06 | K11: 34.18
A12: 7 | B12: 1.19 | C12: 36.12 | E12: 39 | F12: 2.07 | G12: 50.22 | I12: 77 | J12: 3.07 | K12: 33.925
A13: 8 | B13: 1.20 | C13: =16.545*2 -> 33.09 | E13: 40 | F13: 2.08 | G13: 88.25 | I13: 78 | J13: 3.08 | K13: 48.61
A14: 9 | B14: 1.25 | C14: 23.73 | E14: 41 | F14: 2.10 | G14: 15.325 | I14: 79 | J14: 3.12 | K14: 101.905
A15: 10 | B15: 1.26 | C15: 28.23 | E15: 42 | F15: 2.12 | G15: 38.75 | I15: 80 | J15: 3.13 | K15: 27.79
A16: 11 | B16: 1.32 | C16: 36.95 | E16: 43 | F16: 2.15 | G16: 40.3 | I16: 81 | J16: 3.16 | K16: 24.45
A17: 12 | B17: 1.33 | C17: 41.15 | E17: 44 | F17: 2.16 | G17: 9.365 | I17: 82 | J17: 3.17 | K17: 39.2
A18: 13 | B18: 1.34 | C18: 39.2 | E18: 45 | F18: 2.20 | G18: 27.35 | I18: 83 | J18: 3.18 | K18: 54.9
A19: 14 | B19: 1.35 | C19: 48.15 | E19: 46 | F19: 2.21 | G19: 27.1 | I19: 84 | J19: 3.19 | K19: 73.06
A20: 15 | B20: 1.59 | C20: 15.02 | E20: 47 | F20: 2.27 | G20: 17.185 | I20: 85 | J20: 3.20 | K20: 42.25
A21: 16 | B21: 1.60 | C21: 40.87 | E21: 48 | F21: 2.28 | G21: 76.29 | I21: 86 | J21: 3.21 | K21: 66.4
A22: 17 | B22: 1.61 | C22: 12.42 | E22: 49 | F22: 2.29 | G22: 30.25 | I22: 87 | J22: 3.22 | K22: 15.47
A23: 18 | B23: 1.63 | C23: 9.8 | E23: 50 | F23: 2.30 | G23: 40.46 | I23: 88 | J23: 3.23 | K23: 38.63
A24: 19 | B24: 1.64 | C24: 42.87 | E24: 51 | F24: 2.31 | G24: 39.35 | I24: 89 | J24: 3.25 | K24: 42.25
A25: 20 | B25: 1.65 | C25: =2*5.69-4.04 -> 7.34 | E25: 52 | F25: 2.33 | G25: 20.5 | I25: 90 | J25: 3.26 | K25: 35.25
A26: 21 | B26: 1.67 | C26: 34.31 | E26: 53 | F26: 2.34 | G26: 41.05 | I26: 91 | J26: 3.28 | K26: 37.18
A27: 22 | B27: 1.68 | C27: 36.89 | E27: 54 | F27: 2.35 | G27: 49.3 | I27: 92 | J27: 3.29 | K27: 41
A28: 23 | B28: 1.69 | C28: 29.25 | E28: 55 | F28: 2.36 | G28: 15.59 | I28: 93 | J28: 3.30 | K28: 33.65
A29: 24 | B29: 1.70 | C29: =4.99*2 -> 9.98 | E29: 56 | F29: 2.37 | G29: 38.79 | I29: 94 | J29: 3.33 | K29: 55.255
A30: 25 | B30: 1.71 | C30: =2*5.825 -> 11.65 | E30: 57 | F30: 2.40 | G30: 42.9 | I30: 95 | J30: 3.34 | K30: 20.6
A31: 26 | B31: 1.73 | C31: 32.06 | E31: 58 | F31: 2.41 | G31: 41.98 | I31: 96 | J31: 3.35 | K31: 41.51
A32: 27 | B32: 1.74 | C32: 34.6 | E32: 59 | F32: 2.42 | G32: 37.69 | I32: 97 | J32: 3.36 | K32: 17.845
A33: 28 | B33: 1.76 | C33: 18.225 | E33: 60 | F33: 2.44 | G33: 42.25 | I33: 98 | J33: 3.37 | K33: 19.2
A34: 29 | B34: 1.77 | C34: 46.075 | E34: 61 | F34: 2.45 | G34: 43.7 | I34: 99 | J34: 3.38 | K34: 51.75
A35: 30 | B35: 1.78 | C35: 47.41 | E35: 62 | F35: 2.47 | G35: 51.67 | I35: 100 | J35: 3.39 | K35: 18.5
A36: 31 | B36: 1.79 | C36: 52.85 | E36: 63 | F36: 2.49 | G36: 50.35 | I36: 101 | J36: 3.41 | K36: 43.16
A37: 32 | B37: 1.80 | C37: 39 | E37: 64 | F37: 2.51 | G37: 16.55 | I37: 102 | J37: 3.42 | K37: 50.86
B38: сумма: | C38: =SUM(C6:C37) -> 963.315 | E38: 65 | F38: 2.53 | G38: 19.45 | I38: 103 | J38: 3.43 | K38: 41.75
E39: 66 | F39: 2.54 | G39: 51.4 | I39: 104 | J39: 3.44 | K39: 18.335
E40: 67 | F40: 2.55 | G40: 19.5 | I40: 105 | J40: 3.45 | K40: 30.895
E41: 68 | F41: 2.56 | G41: 58.125 | J41: сумма: | K41: =SUM(K6:K40) -> 1397.695
E42: 69 | F42: 2.57 | G42: 41.75
E43: 70 | F43: 2.58 | G43: 50.385
F44: сумма: | G44: =SUM(G6:G43) -> 1489.14

Sheet 9.9Дм
A1: Ведомость работ
A2: № п.п. | B2: Наименование затрат | G2: Ед. изм. | H2: Объем
A3: 1 | B3: Демонтаж шпатлевки и/или штукатурки на поверхности стен | G3: м2 | H3: =H15+E14+B12 -> 2901.22
A5: Пом. | B5: Объем | D5: Пом. | E5: Объем | G5: Пом. | H5: Объем
A6: 1.09 | B6: 14.28 | D6: 2.01 | E6: 168.87 | G6: 3.01 | H6: 169.2
A7: 1.11 | B7: 30.4 | D7: 2.02 | E7: 181.59 | G7: 3.02 | H7: 199.44
A8: 1.12 | B8: 31.43 | D8: 2.03 | E8: 159.15 | G8: 3.03 | H8: 123.89
A9: 1.64 | B9: 134.49 | D9: 2.04 | E9: 203.64 | G9: 3.04 | H9: 158.88
A10: 1.68 | B10: 85.25 | D10: 2.05 | E10: 158.56 | G10: 3.05 | H10: 167.2
A11: 1.74 | B11: 82.29 | D11: 2.06 | E11: 160.41 | G11: 3.06 | H11: 151.98
A12: Итог: | B12: 378.14 | D12: 2.41 | E12: 95.47 | G12: 3.07 | H12: 140.79
D13: 2.45 | E13: 90.49 | G13: 3.26 | H13: 102.08
D14: Итог: | E14: 1218.18 | G14: 3.30 | H14: 91.44
G15: Итог: | H15: 1304.9

Sheet 9.8ШтрШп
A1: Ведомость работ
A2: № п.п. | B2: Наименование затрат | L2: Ед. изм. | O2: Объем
A3: 1 | B3: Подготовка поверхности СКБ / стен / по штукатурке / 2мм Шпаклевка стен. Гипсовыми смесями базовая + грунт глубокого проникновения, м2. / Заделка штроб | L3: м2 | O3: =Q22+N30+K28+H30+E30+B30 -> 1801
A4: 2 | B4: Подготовка поверхности СКБ / стен / по штукатурке / 2мм / Шпаклевка стен. Гипсовыми смесями финишная + грунт глубокого проникновения, м2. / Заделка штроб | L4: м2 | O4: =O3 -> 1801
A6: Пом. | B6: Об. | D6: Пом. | E6: Об. | G6: Пом. | H6: Об. | J6: Пом. | K6: Об. | M6: Пом. | N6: Об. | P6: Пом. | Q6: Об.
A7: 1.04 | B7: 64 | D7: 1.52 | E7: 10.5 | G7: 2.01 | H7: 14 | J7: 2.35 | K7: 5 | M7: 3.01 | N7: 16 | P7: 3.30 | Q7: 7
A8: 1.05 | B8: 11 | D8: 1.58 | E8: 38.5 | G8: 2.02 | H8: 10 | J8: 2.36 | K8: 6 | M8: 3.02 | N8: 12 | P8: 3.31 | Q8: 15
A9: 1.07 | B9: 15.5 | D9: 1.59 | E9: 12 | G9: 2.03 | H9: 12 | J9: 2.37 | K9: 8 | M9: 3.03 | N9: 14 | P9: 3.33 | Q9: 5
A10: 1.08 | B10: 16.5 | D10: 1.60 | E10: 20.5 | G10: 2.04 | H10: 13 | J10: 2.38 | K10: 13 | M10: 3.04 | N10: 14 | P10: 3.34 | Q10: 17
A11: 1.09 | B11: 6.5 | D11: 1.61 | E11: 11.5 | G11: 2.05 | H11: 12 | J11: 2.40 | K11: 7 | M11: 3.05 | N11: 14 | P11: 3.35 | Q11: 5
A12: 1.11 | B12: 10.5 | D12: 1.63 | E12: 8.5 | G12: 2.06 | H12: 3 | J12: 2.41 | K12: 10 | M12: 3.06 | N12: 14 | P12: 3.36 | Q12: 5
A13: 1.12 | B13: 16.5 | D13: 1.64 | E13: 13.5 | G13: 2.07 | H13: 21 | J13: 2.42 | K13: 7 | M13: 3.07 | N13: 13 | P13: 3.37 | Q13: 6
A14: 1.19 | B14: 17.5 | D14: 1.65 | E14: 12.5 | G14: 2.08 | H14: 7 | J14: 2.43 | K14: 12 | M14: 3.08 | N14: 43 | P14: 3.38 | Q14: 11
A15: 1.20 | B15: 17.5 | D15: 1.67 | E15: 13.5 | G15: 2.10 | H15: 9 | J15: 2.44 | K15: 10 | M15: 3.12 | N15: 6 | P15: 3.39 | Q15: 5
A16: 1.21 | B16: 15.5 | D16: 1.68 | E16: 3.5 | G16: 2.12 | H16: 7 | J16: 2.45 | K16: 20 | M16: 3.13 | N16: 11 | P16: 3.40 | Q16: 21
A17: 1.23 | B17: 11 | D17: 1.69 | E17: 11.5 | G17: 2.15 | H17: 5 | J17: 2.47 | K17: 4 | M17: 3.16 | N17: 8 | P17: 3.41 | Q17: 22
A18: 1.25 | B18: 12.5 | D18: 1.70 | E18: 8.5 | G18: 2.16 | H18: 57 | J18: 2.48 | K18: 27 | M18: 3.17 | N18: 24 | P18: 3.42 | Q18: 6
... A21: 1.30 | B21: 24.5 | D21: 1.74 | E21: 10.5 | G21: 2.21 | H21: 3 | J21: 2.52 | K21: 4 | M21: 3.20 | N21: 12 | P21: 3.45 | Q21: 33
A22: 1.31 | B22: 33.5 | D22: 1.75 | E22: 6.5 | G22: 2.27 | H22: 40 | J22: 2.53 | K22: 5 | M22: 3.21 | N22: 7 | P22: Итог: | Q22: =SUM(Q7:Q21) -> 200
A23: 1.32 | B23: 11.5 | D23: 1.76 | E23: 7.5 | G23: 2.28 | H23: 6 | J23: 2.54 | K23: 6 | M23: 3.22 | N23: 11
A24: 1.33 | B24: 12.5 | D24: 1.77 | E24: 21.5 | G24: 2.29 | H24: 38 | J24: 2.55 | K24: 25 | M24: 3.23 | N24: 8
A25: 1.34 | B25: 12.5 | D25: 1.78 | E25: 16.5 | G25: 2.30 | H25: 7 | J25: 2.56 | K25: 5 | M25: 3.24 | N25: 16
A26: 1.36 | B26: 11.5 | D26: 1.79 | E26: 6.5 | G26: 2.31 | H26: 7 | J26: 2.57 | K26: 29 | M26: 3.25 | N26: 8
A27: 1.35 | B27: 9.5 | D27: 1.80 | E27: 9.5 | G27: 2.32 | H27: 14 | J27: 2.58 | K27: 31 | M27: 3.26 | N27: 11
A28: 1.38 | B28: 34.5 | D28: 1.81 | E28: 10.5 | G28: 2.33 | H28: 7 | J28: Итог: | K28: =SUM(K7:K27) -> 261 | M28: 3.28 | N28: 16
A29: 1.49 | B29: 11.5 | D29: 1.82 | E29: 10.5 | G29: 2.34 | H29: 7 | M29: 3.29 | N29: 11
A30: Итог: | B30: =SUM(B7:B29) -> 401 | D30: Итог: | E30: =SUM(E7:E29) -> 285 | G30: Итог: | H30: =SUM(H7:H29) -> 318 | M30: Итог: | N30: =SUM(N7:N29) -> 336

Sheet 9.7ШтрШТ
A1: Ведомость работ
A2: № п.п. | B2: Наименование затрат | L2: Ед. изм. | O2: Объем
A3: 1 | B3: Штукатурка стен. Гипсовая + Грунт глубокого проникновения, м2. / Заделка штроб | L3: м2 | O3: =Q21+N29+K27+H29+E29+B29 -> 1801
A5: Пом. | B5: Об. | D5: Пом. | E5: Об. | G5: Пом. | H5: Об. | J5: Пом. | K5: Об. | M5: Пом. | N5: Об. | P5: Пом. | Q5: Об.
A6: 1.04 | B6: 64 | D6: 1.52 | E6: 10.5 | G6: 2.01 | H6: 14 | J6: 2.35 | K6: 5 | M6: 3.01 | N6: 16 | P6: 3.30 | Q6: 7
A7: 1.05 | B7: 11 | D7: 1.58 | E7: 38.5 | G7: 2.02 | H7: 10 | J7: 2.36 | K7: 6 | M7: 3.02 | N7: 12 | P7: 3.31 | Q7: 15
A8: 1.07 | B8: 15.5 | D8: 1.59 | E8: 12 | G8: 2.03 | H8: 12 | J8: 2.37 | K8: 8 | M8: 3.03 | N8: 14 | P8: 3.33 | Q8: 5
A9: 1.08 | B9: 16.5 | D9: 1.60 | E9: 20.5 | G9: 2.04 | H9: 13 | J9: 2.38 | K9: 13 | M9: 3.04 | N9: 14 | P9: 3.34 | Q9: 17
A10: 1.09 | B10: 6.5 | D10: 1.61 | E10: 11.5 | G10: 2.05 | H10: 12 | J10: 2.40 | K10: 7 | M10: 3.05 | N10: 14 | P10: 3.35 | Q10: 5
A11: 1.11 | B11: 10.5 | D11: 1.63 | E11: 8.5 | G11: 2.06 | H11: 3 | J11: 2.41 | K11: 10 | M11: 3.06 | N11: 14 | P11: 3.36 | Q11: 5
A12: 1.12 | B12: 16.5 | D12: 1.64 | E12: 13.5 | G12: 2.07 | H12: 21 | J12: 2.42 | K12: 7 | M12: 3.07 | N12: 13 | P12: 3.37 | Q12: 6
A13: 1.19 | B13: 17.5 | D13: 1.65 | E13: 12.5 | G13: 2.08 | H13: 7 | J13: 2.43 | K13: 12 | M13: 3.08 | N13: 43 | P13: 3.38 | Q13: 11
A14: 1.20 | B14: 17.5 | D14: 1.67 | E14: 13.5 | G14: 2.10 | H14: 9 | J14: 2.44 | K14: 10 | M14: 3.12 | N14: 6 | P14: 3.39 | Q14: 5
A15: 1.21 | B15: 15.5 | D15: 1.68 | E15: 3.5 | G15: 2.12 | H15: 7 | J15: 2.45 | K15: 20 | M15: 3.13 | N15: 11 | P15: 3.40 | Q15: 21
A16: 1.23 | B16: 11 | D16: 1.69 | E16: 11.5 | G16: 2.15 | H16: 5 | J16: 2.47 | K16: 4 | M16: 3.16 | N16: 8 | P16: 3.41 | Q16: 22
A17: 1.25 | B17: 12.5 | D17: 1.70 | E17: 8.5 | G17: 2.16 | H17: 57 | J17: 2.48 | K17: 27 | M17: 3.17 | N17: 24 | P17: 3.42 | Q17: 6
... A20: 1.30 | B20: 24.5 | D20: 1.74 | E20: 10.5 | G20: 2.21 | H20: 3 | J20: 2.52 | K20: 4 | M20: 3.20 | N20: 12 | P20: 3.45 | Q20: 33
A21: 1.31 | B21: 33.5 | D21: 1.75 | E21: 6.5 | G21: 2.27 | H21: 40 | J21: 2.53 | K21: 5 | M21: 3.21 | N21: 7 | P21: Итог: | Q21: =SUM(Q6:Q20) -> 200
A22: 1.32 | B22: 11.5 | D22: 1.76 | E22: 7.5 | G22: 2.28 | H22: 6 | J22: 2.54 | K22: 6 | M22: 3.22 | N22: 11
A23: 1.33 | B23: 12.5 | D23: 1.77 | E23: 21.5 | G23: 2.29 | H23: 38 | J23: 2.55 | K23: 25 | M23: 3.23 | N23: 8
A24: 1.34 | B24: 12.5 | D24: 1.78 | E24: 16.5 | G24: 2.30 | H24: 7 | J24: 2.56 | K24: 5 | M24: 3.24 | N24: 16
A25: 1.36 | B25: 11.5 | D25: 1.79 | E25: 6.5 | G25: 2.31 | H25: 7 | J25: 2.57 | K25: 29 | M25: 3.25 | N25: 8
A26: 1.35 | B26: 9.5 | D26: 1.80 | E26: 9.5 | G26: 2.32 | H26: 14 | J26: 2.58 | K26: 31 | M26: 3.26 | N26: 11
A27: 1.38 | B27: 34.5 | D27: 1.81 | E27: 10.5 | G27: 2.33 | H27: 7 | J27: Итог: | K27: =SUM(K6:K26) -> 261 | M27: 3.28 | N27: 16
A28: 1.49 | B28: 11.5 | D28: 1.82 | E28: 10.5 | G28: 2.34 | H28: 7 | M28: 3.29 | N28: 11
A29: Итог: | B29: =SUM(B6:B28) -> 401 | D29: Итог: | E29: =SUM(E6:E28) -> 285 | G29: Итог: | H29: =SUM(H6:H28) -> 318 | M29: Итог: | N29: =SUM(N6:N28) -> 336

Sheet 9.6Штр
A1: Ведомость работ
A2: № п.п. | B2: Наименование затрат | L2: Ед. изм. | O2: Объем
A3: 1 | B3: Устройство штроб | L3: пог.м. | O3: =B29+E29+H29+K27+N29+Q21 -> 3602
A5: Пом. | B5: Об. | D5: Пом. | E5: Об. | G5: Пом. | H5: Об. | J5: Пом. | K5: Об. | M5: Пом. | N5: Об. | P5: Пом. | Q5: Об.
A6: 1.04 | B6: 128 | D6: 1.52 | E6: 21 | G6: 2.01 | H6: 28 | J6: 2.35 | K6: 10 | M6: 3.01 | N6: 32 | P6: 3.30 | Q6: 14
A7: 1.05 | B7: 22 | D7: 1.58 | E7: 77 | G7: 2.02 | H7: 20 | J7: 2.36 | K7: 12 | M7: 3.02 | N7: 24 | P7: 3.31 | Q7: 30
A8: 1.07 | B8: 31 | D8: 1.59 | E8: 24 | G8: 2.03 | H8: 24 | J8: 2.37 | K8: 16 | M8: 3.03 | N8: 28 | P8: 3.33 | Q8: 10
A9: 1.08 | B9: 33 | D9: 1.60 | E9: 41 | G9: 2.04 | H9: 26 | J9: 2.38 | K9: 26 | M9: 3.04 | N9: 28 | P9: 3.34 | Q9: 34
A10: 1.09 | B10: 13 | D10: 1.61 | E10: 23 | G10: 2.05 | H10: 24 | J10: 2.40 | K10: 14 | M10: 3.05 | N10: 28 | P10: 3.35 | Q10: 10
A11: 1.11 | B11: 21 | D11: 1.63 | E11: 17 | G11: 2.06 | H11: 6 | J11: 2.41 | K11: 20 | M11: 3.06 | N11: 28 | P11: 3.36 | Q11: 10
A12: 1.12 | B12: 33 | D12: 1.64 | E12: 27 | G12: 2.07 | H12: 42 | J12: 2.42 | K12: 14 | M12: 3.07 | N12: 26 | P12: 3.37 | Q12: 12
A13: 1.19 | B13: 35 | D13: 1.65 | E13: 25 | G13: 2.08 | H13: 14 | J13: 2.43 | K13: 24 | M13: 3.08 | N13: 86 | P13: 3.38 | Q13: 22
A14: 1.20 | B14: 35 | D14: 1.67 | E14: 27 | G14: 2.10 | H14: 18 | J14: 2.44 | K14: 20 | M14: 3.12 | N14: 12 | P14: 3.39 | Q14: 10
A15: 1.21 | B15: 31 | D15: 1.68 | E15: 7 | G15: 2.12 | H15: 14 | J15: 2.45 | K15: 40 | M15: 3.13 | N15: 22 | P15: 3.40 | Q15: 42
A16: 1.23 | B16: 22 | D16: 1.69 | E16: 23 | G16: 2.15 | H16: 10 | J16: 2.47 | K16: 8 | M16: 3.16 | N16: 16 | P16: 3.41 | Q16: 44
A17: 1.25 | B17: 25 | D17: 1.70 | E17: 17 | G17: 2.16 | H17: 114 | J17: 2.48 | K17: 54 | M17: 3.17 | N17: 48 | P17: 3.42 | Q17: 12
... A20: 1.30 | B20: 49 | D20: 1.74 | E20: 21 | G20: 2.21 | H20: 6 | J20: 2.52 | K20: 8 | M20: 3.20 | N20: 24 | P20: 3.45 | Q20: 66
A21: 1.31 | B21: 67 | D21: 1.75 | E21: 13 | G21: 2.27 | H21: 80 | J21: 2.53 | K21: 10 | M21: 3.21 | N21: 14 | P21: Итог: | Q21: =SUM(Q6:Q20) -> 400
A22: 1.32 | B22: 23 | D22: 1.76 | E22: 15 | G22: 2.28 | H22: 12 | J22: 2.54 | K22: 12 | M22: 3.22 | N22: 22
A23: 1.33 | B23: 25 | D23: 1.77 | E23: 43 | G23: 2.29 | H23: 76 | J23: 2.55 | K23: 50 | M23: 3.23 | N23: 16
A24: 1.34 | B24: 25 | D24: 1.78 | E24: 33 | G24: 2.30 | H24: 14 | J24: 2.56 | K24: 10 | M24: 3.24 | N24: 32
A25: 1.36 | B25: 23 | D25: 1.79 | E25: 13 | G25: 2.31 | H25: 14 | J25: 2.57 | K25: 58 | M25: 3.25 | N25: 16
A26: 1.35 | B26: 19 | D26: 1.80 | E26: 19 | G26: 2.32 | H26: 28 | J26: 2.58 | K26: 62 | M26: 3.26 | N26: 22
A27: 1.38 | B27: 69 | D27: 1.81 | E27: 21 | G27: 2.33 | H27: 14 | J27: Итог: | K27: =SUM(K6:K26) -> 522 | M27: 3.28 | N27: 32
A28: 1.49 | B28: 23 | D28: 1.82 | E28: 21 | G28: 2.34 | H28: 14 | M28: 3.29 | N28: 22
A29: Итог: | B29: =SUM(B6:B28) -> 802 | D29: Итог: | E29: =SUM(E6:E28) -> 570 | G29: Итог: | H29: =SUM(H6:H28) -> 636 | M29: Итог: | N29: =SUM(N6:N28) -> 672

Sheet 9.4Подъ
A1: Ведомость работ
A2: № п.п. | B2: Наименование затрат | E2: Ед. изм. | F2: Объем
A3: 1 | B3: Подъем материалов на 2-й и 3-й этажи в отсутствие подъемника | E3: тн | F3: 21

Sheet 9.3Крск
A1: Ведомость работ
A2: № п.п. | B2: Наименование затрат | E2: Описание | F2: Ед. изм. | G2: Объем
A3: 1 | B3: Лакокрасочные работы СКБ / окраска стен / в 2 слоя | E3: Ремонт (демонтаж/монтаж) окраски стен под радиаторами отопления | F3: м2 | G3: 108.07

Sheet 9.2Шп
A1: Ведомость работ
A2: № п.п. | B2: Наименование затрат | H2: Ед. изм. | I2: Объем
A3: 1 | B3: Ремонт (демонтаж и монтаж) шпаклевки гипсовой. Базовый слой 2 мм. 1-й, 2-й и 3-й этаж стены, колонны и простенки шириной до 500 мм. | H3: м2 | I3: =B33 -> 1612.46
A4: 2 | B4: Ремонт (демонтаж и монтаж) шпаклевки гипсовой. Финишный слой 2 мм. 1-й, 2-й и 3-й этаж стены, колонны и простенки шириной до 500 мм. | H4: м2 | I4: =C33 -> 964.47
A5: 3 | B5: Ремонт (демонтаж/монтаж) шпаклевки гипсовой базовой. Откосы оконные, витражные и дверные (этажи 1, 2, 3). | H5: м2 | I5: =F26 -> 57.34
A6: 4 | B6: Ремонт (демонтаж/монтаж) шпаклевки гипсовой финишной. Откосы оконные, витражные и дверные (этажи 1, 2, 3). | H6: м2 | I6: =G26 -> 57.34
A8: Пункт №1, 2. | E8: Пункт №3, 4.
A9: Пом. | B9: Объем | C9: Объем | E9: Пом. | F9: Объем | G9: Объем
A10: 1.09 | B10: 4.59 | C10: 4.59 | E10: 1.09 | F10: 5.1 | G10: 5.1
A11: 1.11 | B11: 5.1 | C11: 5.1
A12: 1.12 | B12: 1.27 | C12: 9.96 | E12: 2.01 | F12: 4.22 | G12: 4.22
A13: 1.64 | B13: 85.82 | C13: 1.45 | E13: 2.02 | F13: 5.78 | G13: 5.78
A14: 1.68 | B14: 73.78 | C14: 3.27 | E14: 2.03 | F14: 1.56 | G14: 1.56
A15: 1.74 | B15: 69.2 | C15: 4.89 | E15: 2.04 | F15: 4.22 | G15: 4.22
A16: 2.01 | B16: 80.53 | C16: 71.56 | E16: 2.05 | F16: 3.24 | G16: 3.24
A17: 2.02 | B17: 95.12 | C17: 80.69 | E17: 2.06 | F17: 4.22 | G17: 4.22
A18: 2.03 | B18: 83.67 | C18: 73.92
A19: 2.04 | B19: 84.29 | C19: 74.15 | E19: 3.01 | F19: 4.22 | G19: 4.22
A20: 2.05 | B20: 76.63 | C20: 64.73 | E20: 3.02 | F20: 6.62 | G20: 6.62
A21: 2.06 | B21: 79.09 | C21: 70.12 | E21: 3.03 | F21: 1.56 | G21: 1.56
A22: 2.41 | B22: 84 | C22: 3.27 | E22: 3.04 | F22: 3.96 | G22: 3.96
A23: 2.45 | B23: 77.4 | C23: 4.89 | E23: 3.05 | F23: 4.22 | G23: 4.22
A24: 3.01 | B24: 81.85 | C24: 75.8 | E24: 3.06 | F24: 4.2 | G24: 4.2
A25: 3.02 | B25: 103.04 | C25: 89.78 | E25: 3.07 | F25: 4.22 | G25: 4.22
A26: 3.03 | B26: 53.99 | C26: 47.94 | E26: Итог: | F26: =SUM(F10:F25) -> 57.34 | G26: =SUM(G10:G25) -> 57.34
A27: 3.04 | B27: 83.7 | C27: 71.22
A28: 3.05 | B28: 81.12 | C28: 74.88
A29: 3.06 | B29: 70.03 | C29: 63.79
A30: 3.07 | B30: 69.28 | C30: 60.31
A31: 3.26 | B31: 90.61 | C31: 3.27
A32: 3.30 | B32: 78.35 | C32: 4.89
A33: Итог: | B33: =SUM(B10:B32) -> 1612.46 | C33: =SUM(C10:C32) -> 964.47

Sheet 9.1Шт
A1: Ведомость работ
A2: № п.п. | B2: Наименование затрат | I2: Ед. изм. | J2: Объем
A3: 1 | B3: Ремонт (демонтаж/монтаж) штукатурки стен 25 мм гипсовая по бетону + Бетонконтакт | I3: м2 | J3: =B28 -> 167.29
A4: 2 | B4: Ремонт (демонтаж/монтаж) штукатурки стен 25 мм гипсовая по блоку ячеистому, кирпичу и ПГП + Грунт глубокого проникновения | I4: м2 | J4: =E18 -> 98.31
A5: 3 | B5: Ремонт (демонтаж/монтаж) штукатурки 25 мм гипсовая по бетону + Бетонконтакт. Колонны и простенки ш. до 500 мм. | I5: м2 | J5: =E23 -> 1.35
A6: 4 | B6: Штукатурка откосов | I6: м2 | J6: =H19 -> 10.97
A7: 5 | B7: Обработка поверхности стен антиграбовым составом | I7: м2 | J7: 277.92
A9: Пункт №1. | D9: Пункт №2. | G9: Пункт №4.
A10: Пом. | B10: Объем | D10: Пом. | E10: Объем | G10: Пом. | H10: Объем
A11: 1.11 | B11: 20.2 | D11: 1.64 | E11: 36.93 | G11: 1.11 | H11: 2.11
A12: 1.12 | B12: 20.2 | G12: 1.12 | H12: 2.83
A13: 1.64 | B13: 8.94 | D13: 2.04 | E13: 34 | G13: 2.01 | H13: 0.63
A14: 1.68 | B14: 8.2 | D14: 2.06 | E14: 3.49 | G14: 2.03 | H14: 0.23
A15: 1.74 | B15: 8.2 | G15: 2.04 | H15: 2.11
A16: 2.01 | B16: 12.56 | D16: 3.03 | E16: 20.4 | G16: 2.05 | H16: 0.49
A17: 2.04 | B17: 6.98 | D17: 3.07 | E17: 3.49 | G17: 2.06 | H17: 0.63
A18: 2.05 | B18: 13.96 | D18: Итог: | E18: =SUM(E11:E17) -> 98.31 | G18: 3.30 | H18: 1.94
A19: 2.06 | B19: 3.49 | G19: Итог: | H19: =SUM(H11:H18) -> 10.97
A20: 2.41 | B20: 8.2 | D20: Пункт №3.
A21: 2.45 | B21: 8.2 | D21: Пом. | E21: Объем
A22: 3.01 | B22: 7.33 | D22: 1.64 | E22: 1.35
A23: 3.05 | B23: 6.98 | D23: Итог: | E23: =SUM(E22:E22) -> 1.35
A24: 3.06 | B24: 13.96
A25: 3.07 | B25: 3.49
A26: 3.26 | B26: 8.2
A27: 3.30 | B27: 8.2
A28: Итог: | B28: =SUM(B11:B27) -> 167.29

Sheet 8.4_НЗ
A1: Ведомость работ
A2: № п.п. | B2: Наименование затрат | M2: Ед. изм. | N2: Объем
A3: 1 | B3: Ремонт (демонтаж/монтаж) штукатурки стен 25 мм гипсовая по бетону + Бетонконтакт | M3: м2 | N3: =B38 -> 167.29 | O3: 167.29
A4: 2 | B4: Ремонт (демонтаж/монтаж) штукатурки стен 25 мм гипсовая по блоку ячеистому, кирпичу и ПГП + Грунт глубокого проникновения | M4: м2 | N4: =E26 -> 98.31 | O4: 98.31
A5: 3 | B5: Ремонт (демонтаж/монтаж) штукатурки 25 мм гипсовая по бетону + Бетонконтакт. Колонны и простенки ш. до 500 мм. | M5: м2 | N5: =E31 -> 1.35 | O5: 1.35
A6: 4 | B6: Штукатурка откосов | M6: м2 | N6: =E43 -> 10.97 | O6: 10.97
A7: 5 | B7: Ремонт (демонтаж и монтаж) шпаклевки гипсовой. Базовый слой 2 мм. 1-й, 2-й и 3-й этаж стены, колонны и простенки шириной до 500 мм. | M7: м2 | N7: =H42 -> 1612.46 | O7: 1612.46
A8: 6 | B8: Ремонт (демонтаж и монтаж) шпаклевки гипсовой. Финишный слой 2 мм. 1-й, 2-й и 3-й этаж стены, колонны и простенки шириной до 500 мм. | M8: м2 | N8: =I42 -> 964.47 | O8: 964.47
A9: 7 | B9: Ремонт (демонтаж/монтаж) шпаклевки гипсовой базовой. Откосы оконные, витражные и дверные (этажи 1, 2, 3). | M9: м2 | N9: =M35 -> 57.34 | O9: 57.34
A10: 8 | B10: Ремонт (демонтаж/монтаж) шпаклевки гипсовой финишной. Откосы оконные, витражные и дверные (этажи 1, 2, 3). | M10: м2 | N10: =N35 -> 57.34 | O10: 57.34
A11: 9 | B11: Ремонт (демонтаж/монтаж) окраски стен под радиаторами отопления | M11: м2 | N11: =J42 -> 108.07 | O11: 108.07
A12: 10 | B12: Подъем материалов на 2-й и 3-й этажи в отсутствие подъемника | M12: тн | O12: 21
A13: 11 | B13: Обработка поверхности стен антиграбовым составом | M13: м2 | O13: 277.92
A14: 12 | B14: Уборка и вынос мусора после демонтажных работ | M14: тн | O14: 21
A15: 13 | B15: Вывоз мусора контейнерами по 8м3, исходя из грузоподъемности контейнера 3,19 тн/шт | M15: шт | O15: 3
A17: Пункт №1. | D17: Пункт №2. | G17: Пункт №5, 6, 9. | L17: Пункт №7, 8.
A18: Пом. | B18: Объем | D18: Пом. | E18: Объем | G18: Пом. | H18: Объем | I18: Объем | J18: Объем | L18: Пом. | M18: Объем | N18: Объем
A19: 1.11 | B19: 20.2 | D19: 1.64 | E19: 36.93 | G19: 1.09 | H19: 4.59 | I19: 4.59 | J19: 4.59 | L19: 1.09 | M19: 5.1 | N19: 5.1
A20: 1.12 | B20: 20.2 | G20: 1.11 | H20: 5.1 | I20: 5.1 | J20: 5.1
A21: 1.64 | B21: 8.94 | D21: 2.04 | E21: 34 | G21: 1.12 | H21: 1.27 | I21: 9.96 | J21: 9.96 | L21: 2.01 | M21: 4.22 | N21: 4.22
A22: 1.68 | B22: 8.2 | D22: 2.06 | E22: 3.49 | G22: 1.64 | H22: 85.82 | I22: 1.45 | J22: 1.45 | L22: 2.02 | M22: 5.78 | N22: 5.78
A23: 1.74 | B23: 8.2 | G23: 1.68 | H23: 73.78 | I23: 3.27 | J23: 3.27 | L23: 2.03 | M23: 1.56 | N23: 1.56
D24: 3.03 | E24: 20.4 | G24: 1.74 | H24: 69.2 | I24: 4.89 | J24: 4.89 | L24: 2.04 | M24: 4.22 | N24: 4.22
A25: 2.01 | B25: 12.56 | D25: 3.07 | E25: 3.49 | G25: 2.01 | H25: 80.53 | I25: 71.56 | J25: 4.8 | L25: 2.05 | M25: 3.24 | N25: 3.24
A26: 2.04 | B26: 6.98 | D26: Итог: | E26: =SUM(E19:E25) -> 98.31 | G26: 2.02 | H26: 95.12 | I26: 80.69 | J26: 7.35 | L26: 2.06 | M26: 4.22 | N26: 4.22
A27: 2.05 | B27: 13.96 | G27: 2.03 | H27: 83.67 | I27: 73.92 | J27: 1.8
A28: 2.06 | B28: 3.49 | D28: Пункт №3. | G28: 2.04 | H28: 84.29 | I28: 74.15 | J28: 4.98 | L28: 3.01 | M28: 4.22 | N28: 4.22
A29: 2.41 | B29: 8.2 | D29: Пом. | E29: Объем | G29: 2.05 | H29: 76.63 | I29: 64.73 | J29: 4.98 | L29: 3.02 | M29: 6.62 | N29: 6.62
A30: 2.45 | B30: 8.2 | D30: 1.64 | E30: 1.35 | G30: 2.06 | H30: 79.09 | I30: 70.12 | J30: 4.98 | L30: 3.03 | M30: 1.56 | N30: 1.56
D31: Итог: | E31: =SUM(E30:E30) -> 1.35 | G31: 2.41 | H31: 84 | I31: 3.27 | J31: 3.27 | L31: 3.04 | M31: 3.96 | N31: 3.96
A32: 3.01 | B32: 7.33 | G32: 2.45 | H32: 77.4 | I32: 4.89 | J32: 4.89 | L32: 3.05 | M32: 4.22 | N32: 4.22
A33: 3.05 | B33: 6.98 | D33: Пункт №4. | G33: 3.01 | H33: 81.85 | I33: 75.8 | J33: 4.8 | L33: 3.06 | M33: 4.2 | N33: 4.2
A34: 3.06 | B34: 13.96 | D34: Пом. | E34: Объем | G34: 3.02 | H34: 103.04 | I34: 89.78 | J34: 4.8 | L34: 3.07 | M34: 4.22 | N34: 4.22
A35: 3.07 | B35: 3.49 | D35: 1.11 | E35: 2.11 | G35: 3.03 | H35: 53.99 | I35: 47.94 | J35: 4.8 | L35: Итог: | M35: =SUM(M19:M34) -> 57.34 | N35: =SUM(N19:N34) -> 57.34
A36: 3.26 | B36: 8.2 | D36: 1.12 | E36: 2.83 | G36: 3.04 | H36: 83.7 | I36: 71.22 | J36: 4.8
A37: 3.30 | B37: 8.2 | D37: 2.01 | E37: 0.63 | G37: 3.05 | H37: 81.12 | I37: 74.88 | J37: 4.8
A38: Итог: | B38: =SUM(B19:B37) -> 167.29 | D38: 2.03 | E38: 0.23 | G38: 3.06 | H38: 70.03 | I38: 63.79 | J38: 4.8
D39: 2.04 | E39: 2.11 | G39: 3.07 | H39: 69.28 | I39: 60.31 | J39: 4.8
D40: 2.05 | E40: 0.49 | G40: 3.26 | H40: 90.61 | I40: 3.27 | J40: 3.27
D41: 2.06 | E41: 0.63 | G41: 3.30 | H41: 78.35 | I41: 4.89 | J41: 4.89
D42: 3.30 | E42: 1.94 | G42: Итог: | H42: =SUM(H19:H41) -> 1612.46 | I42: =SUM(I19:I41) -> 964.47 | J42: =SUM(J19:J41) -> 108.07
D43: Итог: | E43: =SUM(E35:E42) -> 10.97

Sheet 8.3
A1: Ведомость работ и используемых материалов
A2: № п.п. | B2: Наименование затрат | E2: Описание | F2: Ед. изм. | G2: Объем
A5: Пом. | B5: Объем
A10: Итог: | B10: =SUM(B6:B9) -> 0

Sheet 8.2
A1: Ведомость работ и используемых материалов
A2: № п.п. | B2: Наименование затрат | E2: Ед. изм. | F2: Объем
A3: 1 | B3: Облицовка поверхности стен / керамической, керамогранитной плиткой / 600 х 600 | E3: м2 | F3: =B11 -> 3.42
A4: 2 | B4: Облицовка поверхности стен / керамической, керамогранитной плиткой / 200 х 300 | E4: м2 | F4: =F10 -> 12.547
A5: 3 | B5: Зашивка коммуникации / файерборд | E5: м2 | F5: =F10 -> 12.547
A7: Пом. | B7: Объем | E7: Пом. | F7: Объем
A8: 1.31 | B8: =1.9*0.6 -> 1.14 | E8: 1.39 | F8: =2.3*0.57+2.4*0.86-0.8+2.5*0.45-0.5*0.19+2.5*0.86-0.68 -> 5.075
A9: 2.30 | B9: =1.9*0.6 -> 1.14 | E9: 1.58 | F9: =2.2*0.5+2.4*0.86-0.6*1.7+0.58*5+0.86*5-0.52*1.8*2 -> 7.472
A10: 3.19 | B10: =1.9*0.6 -> 1.14 | E10: Итог: | F10: =SUM(F8:F9) -> 12.547
A11: Итог: | B11: =SUM(B8:B10) -> 3.42

Sheet 8.1
A1: Ведомость работ
A2: № п.п. | B2: Наименование затрат | I2: Описание | J2: Ед. изм. | K2: Объем
A3: 1 | I3: Зашивка витражного остекленния до уровня чистого потолка / файерборд | J3: м2 | K3: =B27 -> 180.8
A4: 2 | I4: Зашивка окон до уровня чистого пола / файерборд | J4: м2 | K4: =E22 -> 219
A5: 3 | I5: Зашивка для монтажа противопожарной шторы / файерборд | J5: м2 | K5: =H19 -> 38.08615
A6: 4 | I6: Зашивка коммуникации до уровня чистого потолка / файерборд | J6: м2 | K6: =B40 -> 35
A7: 5 | I7: Зашивка коммуникации / файерборд | J7: м2 | K7: =E40 -> 358.01
A8: 6 | I8: Зашивка окон второго света до ур. чистого пот. / файерборд | J8: м2 | K8: =H26 -> 94
A9: 7 | I9: ЗашивкаЖБ плиты до ур. чистого пот. / файерборд | J9: м2 | K9: =H33 -> 23.2
A10: 8 | B10: Подготовка поверхности СКБ / стен / ГКЛ / 2мм | I10: Шпаклевка базовая / файерборд | J10: м2 | K10: =SUM(K3:K9) -> 948.09615
A11: 9 | B11: Подготовка поверхности СКБ / стен / ГКЛ / 2мм | I11: Шпаклевка финишная / файерборд | J11: м2 | K11: =K10 -> 948.09615
A12: 10 | B12: Лакокрасочные работы СКБ / окраска стен / в 2 слоя | I12: окраска файерборда | J12: м2 | K12: =K11 -> 948.09615
A14: Пом. | B14: Объем | D14: Пом. | E14: Объем | G14: Пом. | H14: Объем
A15: 1.04 | B15: 18 | D15: 1.04 | E15: 4 | G15: 1.82 | H15: 22
A16: 1.08 | B16: =3.9*1 -> 3.9 | D16: 1.27 | E16: 6 | G16: 1.04 | H16: 2
A17: 1.39 | B17: =2.5*0.6 -> 1.5 | D17: 2.27 | E17: 48 | G17: 1.38 | H17: =10.617*0.95 -> 10.08615
A18: 1.41 | B18: =5.9*0.6 -> 3.54 | D18: 2.28 | E18: 90 | G18: 1.82 | H18: =4*1 -> 4
A19: 1.58 | B19: =(5.3+2.5)*0.6 -> 4.68 | D19: 2.51 | E19: 8 | G19: Итог: | H19: =SUM(H15:H18) -> 38.08615
A20: 1.60 | B20: =(7.3+14.6)*0.6 -> 13.14 | D20: 3.42 | E20: 18
A21: 1.77 | B21: 10 | D21: 3.44 | E21: 45 | G21: Пом. | H21: Объем
A22: 1.78 | B22: 27 | D22: Итог: | E22: =SUM(E15:E21) -> 219 | G22: 2.30 | H22: 40
A23: 2.28 | B23: =2.15+4.66*1 -> 6.81 | G23: 3.19 | H23: 23
A24: 2.56 | B24: 43.5 | D24: Пом. | E24: Объем | G24: 3.44 | H24: 15
A25: 2.58 | B25: =6.95*1 -> 6.95 | D25: 0.18 | E25: =23.3*0.15 -> 3.495 | G25: 3.45 | H25: 16
A26: 3.12 | B26: =27.4*1+14.38 -> 41.78 | D26: 0.12 | E26: =30.1*0.15 -> 4.515 | G26: Итог: | H26: =SUM(H22:H25) -> 94
A27: Итог: | B27: =SUM(B15:B26) -> 180.8 | D27: 1.04 | E27: 115
D28: 1.25 | E28: 15 | G28: Пом. | H28: Объем
A29: Пом. | B29: Объем | D29: 1.26 | E29: 10 | G29: 1.04 | H29: 15
A30: 1.04 | B30: 5 | D30: 1.31 | E30: 36 | G30: 2.08 | H30: 3
A31: 1.26 | B31: 3 | D31: 1.38 | E31: 48 | G31: 2.54 | H31: 2.8
A32: 1.27 | B32: 3 | D32: 2.08 | E32: 3 | G32: 3.38 | H32: 2.4
A33: 1.30 | B33: 6 | D33: 2.27 | E33: 2 | G33: Итог: | H33: =SUM(H29:H32) -> 23.2
A34: 1.31 | B34: 3 | D34: 2.28 | E34: 110
A35: 1.77 | B35: 3 | D35: 2.30 | E35: 2
A36: 2.30 | B36: 3 | D36: 2.51 | E36: 2
A37: 2.56 | B37: 3 | D37: 3.19 | E37: 4
A38: 3.19 | B38: 3 | D38: 3.16 | E38: 2
A39: 3.42 | B39: 3 | D39: 3.44 | E39: 1
A40: Итог: | B40: =SUM(B30:B39) -> 35 | D40: Итог: | E40: =SUM(E25:E39) -> 358.01

Sheet 7.3Крс
A1: Ведомость работ и используемых материалов
A2: № п.п. | B2: Наименование затрат | E2: Описание | F2: Ед. изм. | G2: Объем
A3: 1 | B3: Лакокрасочные работы СКБ / окраска стен / в 2 слоя | E3: Тип: FK13. | F3: м2 | G3: 900
A4: 2 | B4: Лакокрасочные работы СКБ / окраска стен / в 2 слоя | E4: Тип: FK15. | F4: м2 | G4: 90
A5: 3 | B5: Лакокрасочные работы СКБ / окраска стен / в 2 слоя | E5: Тип: FK11. | F5: м2 | G5: 9.8
A6: 4 | B6: Лакокрасочные работы СКБ / окраска стен / в 2 слоя | E6: Тип: FK5.1 | F6: м2 | G6: 150
A7: 5 | B7: Лакокрасочные работы СКБ / окраска стен / в 2 слоя | E7: Тип: FK2 | F7: м2 | G7: 300
A8: 6 | B8: Лакокрасочные работы СКБ / окраска стен / в 2 слоя | E8: Тип: FK2.1 | F8: м2 | G8: 15
A9: 7 | B9: Лакокрасочные работы СКБ / окраска стен / в 2 слоя | E9: Тип: FK6 | F9: м2 | G9: 9.4
A11: Пом. | B11: Объем
A16: Итог: | B16: =SUM(B12:B15) -> 0

Sheet 7.2звукИз
A1: Ведомость работ и используемых материалов
A2: № п.п. | B2: Наименование затрат | E2: Описание | F2: Ед. изм. | G2: Объем
A3: 1 | B3: Устройство тепло-звукоизоляции стен / в 1 слой | E3: Пом: 1.01, 1.59, 1.63, 1,70. Минераловатный утеплитель Rockwool венти баттс 100 мм. | F3: м2 | G3: 83.5
A5: Пом. | B5: Объем
A6: 1.01 | B6: =2.7*4 -> 10.8
A7: 1.59 | B7: =8.8*4 -> 35.2
A8: 1.63 | B8: =4.56*4+1.06 -> 19.3
A9: 1.70 | B9: =4.55*4 -> 18.2
A10: Итог: | B10: =SUM(B6:B9) -> 83.5

Sheet 7.1WD8
A1: Ведомость работ и используемых материалов
A2: № п.п. | B2: Наименование затрат | E2: Описание | F2: Ед. изм. | G2: Объем
A3: 1 | B3: Устройство перегородок на металлическом каркасе по системе Knauf / С-115.1 / А2-16 | E3: Тип: WD8 | F3: м2 | G3: 6.3
A4: 2 | B4: Устройство перегородок на металлическом каркасе по системе Knauf / С-115.1 / А2-16 | E4: Тип: WD10. | F4: м2 | G4: 24.1
A5: 3 | B5: Облицовка стен по системе Knauf / С-625 / в 1 слой / А-13, А-23 | E5: Тип: WD11 | F5: м2 | G5: 0.4
A6: 4 | B6: Облицовка стен по системе Knauf / С-631 / в 1 слой | E6: Тип: WD12 | F6: м2 | G6: 36.7

Sheet Общ (3)
A120: FK1 | B120: =SUM(SUMIF(C$76:C$119,A120,B$76:B$119)) -> 0 | C120: 3000
A121: FK2 | B121: =SUM(SUMIF(C$76:C$119,A121,B$76:B$119)) -> 0 | C121: 65.1
A122: FK3 | B122: =SUM(SUMIF(C$76:C$119,A122,B$76:B$119)) -> 0 | C122: 36.1
A123: FK6 | B123: =SUM(SUMIF(C$76:C$119,A123,B$76:B$119)) -> 0 | C123: 9.4
B124: =SUM(SUMIF(C$76:C$119,A124,B$76:B$119)) -> 0
A125: FK13 | B125: =SUM(SUMIF(C$76:C$119,A125,B$76:B$119)) -> 0 | C125: 314.2
A126: FK14 | B126: =SUM(SUMIF(C$76:C$119,A126,B$76:B$119)) -> 0 | C126: 72.9
A127: FK15 | B127: =SUM(SUMIF(C$76:C$119,A127,B$76:B$119)) -> 0 | C127: 8.6

Sheet Общ (2)
A2: Столбец1 | B2: Столбец2 | C2: Столбец3
A3: 1.04 | B3: =83.8-B4 -> 49.8 | C3: FK1
A4: 1.04 | B4: 34 | C4: FK7.1
A5: 1.04 | B5: 15.2 | C5: FK15
A6: 1.04 | B6: 72 | C6: FK8.1
A7: 2.01 | B7: =115.5-B8 -> 93.1 | C7: FK1
A8: 2.01 | B8: =5.6*4 -> 22.4 | C8: FK13
A9: 2.02 | B9: =134.2-B10 -> 111.4 | C9: FK1
A10: 2.02 | B10: =5.7*4 -> 22.8 | C10: FK13
A12: 2.03 | B12: =100.3-1.8 -> 98.5 | C12: FK1
A13: 2.04 | B13: =112.1-B14 -> 92.9 | C13: FK1
A14: 2.04 | B14: =4.8*4 -> 19.2 | C14: FK13
A16: 2.05 | B16: =110.7-B17 -> 80.7 | C16: FK1
A17: 2.05 | B17: =7.5*4 -> 30 | C17: FK13
A20: 2.06 | B20: =108.9-B21 -> 90.1 | C20: FK1
A21: 2.06 | B21: =4.7*4 -> 18.8 | C21: FK13
A23: 2.07 | B23: =113.1-1.4*1.8 -> 110.58 | C23: FK1
A24: 2.08 | B24: 176.5 | C24: FK1
A26: 2.09 | B26: 36.3 | C26: 0
A28: 2.10 | B28: =57*0.6 -> 34.2 | C28: FK1
A30: 2.11 | B30: =53.5*0.6 -> 32.1 | C30: FK1
A32: 2.12 | B32: 77.5 | C32: FK1
A33: 2.13 | B33: 53.6 | C33: 0
A34: 2.14 | B34: =45.1*0.6 -> 27.06 | C34: FK1
A35: 2.15 | B35: 80.6 | C35: FK1
A36: 2.16 | B36: =40.4*0.6 -> 24.24 | C36: FK1
A37: 2.17 | B37: 53.2 | C37: 0
A38: 2.18 | B38: 89.4 | C38: 0
A39: 2.19 | B39: 626.5 | C39: FK1
A40: 2.20 | B40: =125.7-6*4 -> 101.7 | C40: FK1
A41: 2.21 | B41: 54.2 | C41: FK1
A42: 2.22 | B42: 34.9 | C42: 0
A43: 2.23 | B43: 51.1 | C43: 0
A44: 2.24 | B44: =80.2*0+18.8*2.2 -> 41.36 | C44: FK1
A45: 2.25 | B45: =80.2*0+18.8*2.2 -> 41.36 | C45: FK1
A46: 2.26 | B46: =34.8*0+8.3*2.2 -> 18.26 | C46: FK1
A47: 2.27 | B47: 46.9 | C47: FK1
A48: 2.28 | B48: =291.5-B49-B50 -> 248.7 | C48: FK1
A49: 2.28 | B49: =0.5*5*4 -> 10 | C49: FK3
A50: 2.28 | B50: 32.8 | C50: FK2.1
A51: 2.29 | B51: 60.5 | C51: FK1
A52: 2.30 | B52: =268.7-B53 -> 250.3 | C52: FK1
A53: 2.30 | B53: =4.6*4 -> 18.4 | C53: FK2
A54: 2.31 | B54: =78.7-B55 -> 37.82 | C54: FK1
A55: 2.31 | B55: =3.36*2*4+14 -> 40.88 | C55: FK13
A56: 2.32 | B56: =84-B57 -> 37 | C56: FK1
A57: 2.32 | B57: 47 | C57: FK13
A58: 2.33 | B58: 71.1 | C58: FK1
A60: 2.34 | B60: =82.1-B61 -> 37.1 | C60: FK1
A61: 2.34 | B61: 45 | C61: FK13
A62: 2.35 | B62: =98.7-B63 -> 46.7 | C62: FK1
A63: 2.35 | B63: 52 | C63: FK13
A64: 2.36 | B64: 47.6 | C64: 0
A65: 2.37 | B65: =83.9-B66 -> 80.9 | C65: FK1
A66: 2.37 | B66: 3 | C66: FK3
A69: 2.38 | B69: =40.2*0.6 -> 24.12 | C69: FK1
A70: 2.39 | B70: =88.5*0.6 -> 53.1 | C70: FK1
A71: 2.40 | B71: 85.8 | C71: FK1
A72: 2.41 | B72: =94.9-10.2*4 -> 54.1 | C72: FK1
A73: 2.42 | B73: 81.7 | C73: FK1
A74: 2.43 | B74: =39.7*0.6 -> 23.82 | C74: FK1
A75: 2.44 | B75: 84.5 | C75: FK1
A76: 2.45 | B76: =94.9-10.2*4 -> 54.1 | C76: FK1
A77: 2.46 | B77: =87.7*0.6 -> 52.62 | C77: FK1
A78: 2.47 | B78: 112.1 | C78: FK1
A79: 2.48 | B79: 41.3 | C79: FK1
A80: 2.49 | B80: 103.9 | C80: FK1
A81: 2.50 | B81: 40.2 | C81: FK1
A82: 2.51 | B82: =88.6-B83 -> 76.6 | C82: FK1
A83: 2.51 | B83: =3*4 -> 12 | C83: FK3
A84: 2.52 | B84: 39.8 | C84: 0
A85: 2.53 | B85: 38.9 | C85: FK1
A86: 2.54 | B86: =104-B87 -> 47 | C86: FK1
A87: 2.54 | B87: 57 | C87: FK13
A88: 2.55 | B88: =38.9-B89 -> 22.9 | C88: FK1
A89: 2.55 | B89: =4*4 -> 16 | C89: FK3
A90: 2.56 | B90: =147-B91 -> 135 | C90: FK1
A91: 2.56 | B91: =3*4 -> 12 | C91: FK3
A92: 2.57 | B92: =83.5-B93 -> 47.5 | C92: FK1
A93: 2.57 | B93: 36 | C93: FK13
A94: 2.58 | B94: =113.3-B95 -> 57.3 | C94: FK1
A95: 2.58 | B95: =14*4 -> 56 | C95: FK2

Sheet Общ
A2: Пом. | B2: Объем | C2: Тип
A3: 1.01 | B3: 11 | C3: FK11
A4: 1.02 | B4: =32.9-8 -> 24.9 | C4: FK15
A5: 1.02 | B5: 8 | C5: FK1
A6: 1.03 | B6: =27.1 / 2 *0 + 8.6*2.2 -> 18.92 | C6: FK1
A7: 1.04 | B7: =428.1-B8 -> 366.4 | C7: FK1
A8: 1.04 | B8: =86.6-B4 -> 61.7 | C8: FK15
A9: 1.05 | B9: 70.7 | C9: FK1
A10: 1.06 | B10: =36.5*0.65 -> 23.725 | C10: FK1
A11: 1.07 | B11: 46.7 | C11: FK1
A12: 1.08 | B12: 156.8 | C12: FK1
A13: 1.09 | B13: =118.8-B14-2*1.8 -> 105.6 | C13: FK1
A14: 1.09 | B14: =2.4*4 -> 9.6 | C14: FK2
A15: 1.10 | B15: =114-B16-1.4*1.8 -> 93.88 | C15: FK1
A16: 1.10 | B16: =4.4*4 -> 17.6 | C16: FK2
A17: 1.11 | B17: =113.7-B18-1.6*1.8 -> 93.22 | C17: FK1
A18: 1.11 | B18: =4.4*4 -> 17.6 | C18: FK2
A19: 1.12 | B19: =176.9-B20-3.6*1.8-1.2*1.8 -> 141.1 | C19: FK1
A20: 1.12 | B20: =1.3*4+1.8*2.2+2*4+2.5*4 -> 27.16 | C20: FK3
A21: 1.13 | B21: =80.2*0+18.8*2.2 -> 41.36 | C21: FK1
A22: 1.14 | B22: =34.8*0+8.3*2.2 -> 18.26 | C22: FK1
A23: 1.15 | B23: =80.3*0+18.8*2.2 -> 41.36 | C23: FK1
A24: 1.16 | B24: 22.7 | C24: 0
A25: 1.17 | B25: 62.2 | C25: 0
A26: 1.18 | B26: 58.9 | C26: 0
A27: 1.19 | B27: =74.5-1.8*1 -> 72.7 | C27: FK1
A28: 1.20 | B28: 67.2 | C28: FK1
A29: 1.21 | B29: 43.7 | C29: 0
A30: 1.22 | B30: =33*0+8*2.2 -> 17.6 | C30: FK1
A31: 1.23 | B31: 42.9 | C31: 0
A32: 1.24 | B32: 49.9 | C32: FK1
A33: 1.25 | B33: 50.7 | C33: FK1
A34: 1.26 | B34: =59.7-1.8 -> 57.9 | C34: FK1
A35: 1.27 | B35: 63.5 | C35: FK1
A36: 1.28 | B36: 80 | C36: FK1
A37: 1.29 | B37: 90.9 | C37: FK1
A38: 1.30 | B38: 177.2 | C38: FK1
A39: 1.31 | B39: 253.5 | C39: FK1
A40: 1.32 | B40: =110.6-B41 -> 77.28 | C40: FK1
A41: 1.32 | B41: =22*1+11.32 -> 33.32 | C41: FK13
A42: 1.33 | B42: =8*3*2 -> 48 | C42: FK1
A43: 1.33 | B43: =82.3-B42 -> 34.3 | C43: FK13
A44: 1.34 | B44: =7.5*2*3 -> 45 | C44: FK1
A45: 1.34 | B45: =78.4/4 -> 19.6 | C45: FK13
A46: 1.35 | B46: =9*2*4 -> 72 | C46: FK1
A47: 1.35 | B47: =96.3-B46 -> 24.3 | C47: FK13
A48: 1.36 | B48: 71.4 | C48: FK1
A49: 1.37 | B49: =49.9*0.6 -> 29.94 | C49: FK2
A50: 1.38 | B50: =244.5-B51-B52 -> 189.5 | C50: FK1
A51: 1.38 | B51: =23*2.2 -> 50.6 | C51: FK2
A52: 1.38 | B52: =2*2.2 -> 4.4 | C52: FK3
A53: 1.39 | B53: 121.5 | C53: 0
A54: 1.40 | B54: 56.7 | C54: 0
A55: 1.41 | B55: 191.3 | C55: 0
A56: 1.42 | B56: 68.2 | C56: 0
A57: 1.43 | B57: 56.8 | C57: 0
A58: 1.44 | B58: 97.6 | C58: 0
A59: 1.45 | B59: 54.8 | C59: 0
A60: 1.46 | B60: 54.7 | C60: FK1
A61: 1.47 | B61: 54.7 | C61: 0
A62: 1.48 | B62: 41.6 | C62: 0
A63: 1.49 | B63: =30.5*0.6 -> 18.3 | C63: FK1
A64: 1.50 | B64: 50 | C64: 0
A65: 1.51 | B65: 42.1 | C65: FK1
A66: 1.52 | B66: 19.7 | C66: FK1
A67: 1.53 | B67: 26.5 | C67: 0
A68: 1.54 | B68: 65.4 | C68: FK1
A69: 1.55 | B69: 44.7 | C69: 0
A70: 1.56 | B70: 44.6 | C70: 0
A71: 1.57 | B71: 71.4 | C71: 0
A72: 1.58 | B72: 198.3 | C72: 0
A73: 1.59 | B73: 37.1 | C73: FK1
A74: 1.60 | B74: =106.4-B75 -> 72.4 | C74: FK1
A75: 1.60 | B75: =8.5*4 -> 34 | C75: FK3
A76: 1.60 | B76: =2*4 -> 8 | C76: FK3
A77: 1.60 | C77: FK14
A78: 1.61 | B78: 55 | C78: FK1
A79: 1.62 | B79: =37.7*0.6 -> 22.62 | C79: FK1
A80: 1.63 | B80: 19.6 | C80: FK1
A81: 1.64 | B81: =90-B82 -> 86 | C81: FK1
A82: 1.64 | B82: =1*4 -> 4 | C82: FK3
A83: 1.65 | B83: =40.2*0.6 -> 24.12 | C83: FK1
A84: 1.66 | B84: =88.5*0.6 -> 53.1 | C84: FK1
A85: 1.67 | B85: 92 | C85: FK1
A86: 1.68 | B86: =94.9-10.2*4 -> 54.1 | C86: FK1
A87: 1.69 | B87: =67.4-B88 -> 65.4 | C87: FK1
A88: 1.69 | B88: =0.5*4 -> 2 | C88: FK3
A89: 1.70 | B89: 21.5 | C89: FK1
A90: 1.71 | B90: =40.2*0.6 -> 24.12 | C90: FK1
A91: 1.72 | B91: =89.1*0.6 -> 53.46 | C91: FK1
A92: 1.73 | B92: 87.5 | C92: FK1
A93: 1.74 | B93: =86.5-10.2*4 -> 45.7 | C93: FK1
A94: 1.75 | B94: 39.4 | C94: 0
A95: 1.76 | B95: =75.1*0.8 -> 60.08 | C95: FK1
A96: 1.77 | B96: =104-B97 -> 96.8 | C96: FK1
A97: 1.77 | B97: =1.8*4 -> 7.2 | C97: FK3
A98: 1.78 | B98: =137.9-B99 -> 127.1 | C98: FK1
A99: 1.78 | B99: =2.7*4 -> 10.8 | C99: FK3
A100: 1.79 | B100: =4.5*4*3 -> 54 | C100: FK1
A101: 1.79 | B101: =144-B100 -> 90 | C101: FK13
...

Sheet FK15
A1: Ведомость работ и используемых материалов
A2: № п.п. | B2: Наименование затрат | E2: Описание | F2: Ед. изм. | G2: Объем
A3: 1 | B3: Лакокрасочные работы СКБ / окраска стен / в 2 слоя | E3: 1, 3 этажи. Тип: FK15 | F3: м2 | G3: =B10 -> 115.8
A5: Пом. | B5: Объем
A6: 1.02 | B6: 24.9
A7: 1.04 | B7: 61.7
A8: 1.04 | B8: 15.2
A9: 3.45 | B9: 14
A10: Итог: | B10: =SUM(B6:B9) -> 115.8

Sheet FK13
A1: Ведомость работ и используемых материалов
A2: № п.п. | B2: Наименование затрат | F2: Описание | G2: Ед. изм. | H2: Объем
A3: 1 | B3: Лакокрасочные работы СКБ / окраска стен / в 2 слоя | F3: 3 этажи. Тип: FK6 | G3: м2 | H3: =B14 -> 61.3
A4: 2 | B4: Лакокрасочные работы СКБ / окраска стен / в 2 слоя | F4: 1 этажи. Тип: FK7.1 | G4: м2 | H4: =B10 -> 34.3
A5: 3 | B5: Лакокрасочные работы СКБ / окраска стен / в 2 слоя | F5: 1 этажи. Тип: FK8.1 | G5: м2 | H5: =B11 -> 19.6
A6: 4 | B6: Лакокрасочные работы СКБ / окраска стен / в 2 слоя | F6: 3 этажи. Тип: FK11 | G6: м2 | H6: =B9 -> 33.32
A8: Пом. | B8: Объем | D8: Пом. | E8: Объем | G8: Пом. | H8: Объем
A9: 1.32 | B9: 33.32 | D9: 2.01 | E9: 22.4 | G9: 3.01 | H9: 14
A10: 1.33 | B10: 34.3 | D10: 2.02 | E10: 22.8 | G10: 3.02 | H10: 18
A11: 1.34 | B11: 19.6 | D11: 2.04 | E11: 19.2 | G11: 3.04 | H11: 18
A12: 1.35 | B12: 24.3 | D12: 2.05 | E12: 30 | G12: 3.05 | H12: 16.8
A13: 1.79 | B13: 90 | D13: 2.06 | E13: 18.8 | G13: 3.06 | H13: 17.6
A14: 1.80 | B14: 61.3 | D14: 2.31 | E14: 40.88 | G14: 3.07 | H14: 10
A15: Итог: | B15: =SUM(B9:B14) -> 262.82 | D15: 2.32 | E15: 47 | G15: 3.17
D16: 2.34 | E16: 45 | G16: 3.20 | H16: 46
D17: 2.35 | E17: 52 | G17: 3.21 | H17: 69
D18: 2.54 | E18: 57 | G18: 3.38 | H18: 56
D19: 2.57 | E19: 36 | G19: 3.43 | H19: 43
D20: Итог: | E20: =SUM(E9:E19) -> 391.08 | G20: Итог: | H20: =SUM(H9:H19) -> 308.4

Sheet FK
A1: Ведомость работ и используемых материалов
A2: № п.п. | B2: Наименование затрат | E2: Описание | F2: Ед. изм. | G2: Объем
A3: 1 | B3: Лакокрасочные работы СКБ / окраска стен / в 2 слоя | E3: 3 этажи. Тип: FK6 | F3: м2 | G3: =B14 -> 9.4
A4: 2 | B4: Лакокрасочные работы СКБ / окраска стен / в 2 слоя | E4: 1 этажи. Тип: FK7.1 | F4: м2 | G4: =B10 -> 34
A5: 3 | B5: Лакокрасочные работы СКБ / окраска стен / в 2 слоя | E5: 1 этажи. Тип: FK8.1 | F5: м2 | G5: =B11 -> 72
A6: 4 | B6: Лакокрасочные работы СКБ / окраска стен / в 2 слоя | E6: 3 этажи. Тип: FK11 | F6: м2 | G6: =B9 -> 11
A8: Пом. | B8: Объем | C8: Тип
A9: 1.01 | B9: 11 | C9: FK11
