Workbook

Sheet 10.4ЛкХам
A1: Ведомость работ
A2: № п.п. | B2: Наименование затрат | C2: Описание | D2: Ед. изм. | E2: Объем
A3: 1 | B3: Установка люков / в стене | C3: 1-3 эт. лючок "Хаммер". | D3: шт | E3: 60
A5: № эт | B5: Кол-во люков, шт
A6: 1 | B6: 20
A7: 2 | B7: 18
A8: 3 | B8: 22
A9: Итог: | B9: =SUM(B6:B8) -> 60

Sheet 10.3отк
A1: Ведомость работ
A2: № п.п. | B2: Наименование затрат | G2: Описание | J2: Ед. изм. | K2: Объем
A3: 1 | B3: Устройство откосов из ГКЛ на клеевом составе / в 2 слой | G3: 1-3 эт. Откосы, витражи файерборд | J3: м2 | K3: ='10.3отк1'!F60 -> 195.415
A4: 2 | B4: Устройство откосов из ГКЛ на металлическом каркасе / в 2 слоя | G4: 1-3 эт. Откосы, двери витражнык файерборд | J4: м2 | K4: ='10.3отк3'!G19 -> 106.10325
A5: 3 | B5: Устройство откосов из ГКЛ на металлическом каркасе / в 2 слоя | G5: 1-3 эт. Откосы, окна. Файерборд | J5: м2 | K5: ='10.3отк2'!J16 -> 930.67225
A6: 4 | B6: Устройство откосов из ГКЛ на металлическом каркасе / в 2 слоя | G6: 1-3 эт. Откосы, двери файерборд | J6: м2 | K6: ='10.3отк4'!G18 -> 288.321
A7: 5 | B7: Устройство тепло-звукоизоляции оконных откосов в 1 слой (ТЕХНОФАС ОПТИМА 50 мм) | G7: 1-3 этаж. Оконные откосы | J7: м2 | K7: 930.67225
A8: 6 | B8: Выравнивание поверхностей откосов толщ. до 5 мм с предварительной огрунтовкой поверхности | G8: 1-3 эт. Шпаклевка базовая | J8: м2 | K8: =SUM(K3:K6) -> 1520.5115
A9: 7 | B9: Выравнивание поверхностей откосов толщ. до 5 мм с предварительной огрунтовкой поверхности ( | G9: 1-3 эт. Шпаклевка финишная | J9: м2 | K9: =K8 -> 1520.5115
A10: 8 | B10: Лакокрасочные работы СКБ / окраска откосов / в 2 слоя | G10: 1-3 эт. | J10: м2 | K10: =K8 -> 1520.5115

Sheet 10.3отк1
A1: Витражи
A2: (Ширина + Высота*2) * Кол-во * 2 стороны = Итог
A3: Марка | B3: Ширина, м | C3: Высота, м | D3: Кол-во | E3: Глубина, м | F3: Итог, м2
A4: ВВ-1* | B4: 1.7 | C4: 2.7 | D4: 6 | E4: 0.15 | F4: =(B4+C4*2)*E4*D4*2 -> 12.78
A5: ВВ-2* | B5: 1.8 | C5: 2.7 | D5: 1 | E5: 0.1 | F5: =(B5+C5*2)*E5*D5*2 -> 1.44
A6: ВВ-3* | B6: 2.1 | C6: 2.7 | D6: 2 | E6: 0.2 | F6: =(B6+C6*2)*E6*D6*2 -> 6
A7: ВВ-4* | B7: 2.1 | C7: 2.7 | D7: 2 | E7: 0.2 | F7: =(B7+C7*2)*E7*D7*2 -> 6
A8: ВВ-5* | B8: 2.4 | C8: 2.7 | D8: 1 | E8: 0.1 | F8: =(B8+C8*2)*E8*D8*2 -> 1.56
A9: ВВ-6* | B9: 2.8 | C9: 2.7 | D9: 1 | E9: 0.13 | F9: =(B9+C9*2)*E9*D9*2 -> 2.132
A10: ВВ-7* | B10: 2.7 | C10: 2.7 | D10: 1 | E10: 0.24 | F10: =(B10+C10*2)*E10*D10*2 -> 3.888
A11: ВВ-8* | B11: 2.8 | C11: 2.7 | D11: 1 | E11: 0.1 | F11: =(B11+C11*2)*E11*D11*2 -> 1.64
A12: ВВ-9* | B12: 3 | C12: 2.7 | D12: 1 | E12: 0.1 | F12: =(B12+C12*2)*E12*D12*2 -> 1.68
A13: ВВ-10* | B13: 3.2 | C13: 2.7 | D13: 2 | E13: 0.2 | F13: =(B13+C13*2)*E13*D13*2 -> 6.88
A14: ВВ-11* | B14: 3.7 | C14: 2.7 | D14: 1 | E14: 0.235 | F14: =(B14+C14*2)*E14*D14*2 -> 4.277
A15: ВВ-12* | B15: 4.2 | C15: 2.7 | D15: 1 | E15: 0.1 | F15: =(B15+C15*2)*E15*D15*2 -> 1.92
... A59: УДВВ-2.2* | B59: 5.4 | C59: 2.7 | D59: 1 | E59: 0.08 | F59: =(B59+C59*2)*E59*D59*2 -> 1.728
D60: Итог, м2: | F60: =SUM(F4:F59) -> 195.415

Sheet 10.3отк3
A1: Двери витражные
A2: Марка окна | B2: Размер (ШхВ), м | C2: Всего, шт. | D2: Периметр откоса, м.п. | E2: Глубина откоса, м. | F2: Площадь одного откоса, м2 | G2: Общая площадь откосов, м2
A3: ДВН-1, ДВН-1.1, ДВН-12*, ДВН-12.1*, ДВН-12.2* | B3: 1,4х3,3 | C3: =1+1+2+4+1 -> 9 | D3: =1.4+3.3*2 -> 8 | E3: 0.33 | F3: =D3*E3 -> 2.64 | G3: =F3*C3 -> 23.76
A4: ДВН-2 | B4: 1,75х3,3 | C4: 1 | D4: =1.75+3.3*2 -> 8.35 | E4: =E3 -> 0.33 | F4: =D4*E4 -> 2.7555 | G4: =F4*C4 -> 2.7555
A5: ДВН-3 | B5: 1,875х3,3 | C5: 1 | D5: =1.875+3.3*2 -> 8.475 | E5: =E4 -> 0.33 | F5: =D5*E5 -> 2.79675 | G5: =F5*C5 -> 2.79675
A6: ДВН-4, ДВН-4.1, ДВН-14* | B6: 2,1х3,3 | C6: =1+5+1 -> 7 | D6: =2.1+3.3*2 -> 8.7 | E6: =E5 -> 0.33 | F6: =D6*E6 -> 2.871 | G6: =F6*C6 -> 20.097
A7: ДВН-5 | B7: 2,56х3,88 | C7: 1 | D7: =2.56+3.88*2 -> 10.32 | E7: =E6 -> 0.33 | F7: =D7*E7 -> 3.4056 | G7: =F7*C7 -> 3.4056
A8: ДВН-6 | B8: 3,85х3,3 | C8: 1 | D8: =3.85+3.3*2 -> 10.45 | E8: =E7 -> 0.33 | F8: =D8*E8 -> 3.4485 | G8: =F8*C8 -> 3.4485
A9: ДВН-7 | B9: 4,8х3,3 | C9: 1 | D9: =4.8+3.3*2 -> 11.4 | E9: =E8 -> 0.33 | F9: =D9*E9 -> 3.762 | G9: =F9*C9 -> 3.762
A10: ДВН-8 | B10: 5,095х3,88 | C10: 1 | D10: =5.095+3.88*2 -> 12.855 | E10: =E9 -> 0.33 | F10: =D10*E10 -> 4.24215 | G10: =F10*C10 -> 4.24215
A11: ДВН-9 | B11: 5,245х3,88 | C11: 1 | D11: =5.245+3.88*2 -> 13.005 | E11: =E10 -> 0.33 | F11: =D11*E11 -> 4.29165 | G11: =F11*C11 -> 4.29165
A12: ДВН-10 | B12: 7,8х3,3 | C12: 1 | D12: =7.8+3.3*2 -> 14.4 | E12: =E11 -> 0.33 | F12: =D12*E12 -> 4.752 | G12: =F12*C12 -> 4.752
A13: ДВН-11 | B13: 10,8х3,3 | C13: 1 | D13: =10.8+3.3*2 -> 17.4 | E13: =E12 -> 0.33 | F13: =D13*E13 -> 5.742 | G13: =F13*C13 -> 5.742
A14: ДВН-13* | B14: 1,8х3,3 | C14: 1 | D14: =1.8+3.3*2 -> 8.4 | E14: =E13 -> 0.33 | F14: =D14*E14 -> 2.772 | G14: =F14*C14 -> 2.772
A15: ДВН-15* | B15: 11,95х3,3 | C15: 1 | D15: =11.95+3.3*2 -> 18.55 | E15: =E14 -> 0.33 | F15: =D15*E15 -> 6.1215 | G15: =F15*C15 -> 6.1215
A16: ДВН-16* | B16: 33,2х3,88 | C16: 1 | D16: =33.2+3.3*2 -> 39.8 | E16: =E15 -> 0.33 | F16: =D16*E16 -> 13.134 | G16: =F16*C16 -> 13.134
A17: ДН-1* | B17: 1,3х2,76 | C17: 1 | D17: =1.3+2.76*2 -> 6.82 | E17: =E16 -> 0.33 | F17: =D17*E17 -> 2.2506 | G17: =F17*C17 -> 2.2506
A18: ДН-2* | B18: 1,8х3,3 | C18: 1 | D18: =1.8+3.3*2 -> 8.4 | E18: =E17 -> 0.33 | F18: =D18*E18 -> 2.772 | G18: =F18*C18 -> 2.772
A19: ИТОГО, м2 | G19: =SUM(G3:G18) -> 106.10325

Sheet 10.3отк2
A1: Окна
A2: Размер проема (ШхВ), м | B2: 1 эт., шт. | C2: 2 эт., шт. | D2: 3 эт., шт. | E2: Всего, шт. | F2: Наличие подоконика | G2: Периметр откоса, м.п. | H2: Глубина откоса, м. | I2: Площадь одного откоса, м2 | J2: Общая площадь откосов, м2
A3: 1х2,7 | B3: =2+2 -> 4 | C3: =3+1+1+4+1 -> 10 | D3: =3+1+1+4+1 -> 10 | E3: =SUM(B3:D3) -> 24 | F3: да | G3: =1+2*2.6 -> 6.2 | H3: 0.33 | I3: =G3*H3 -> 2.046 | J3: =I3*E3 -> 49.104
A4: 1,8х2,7 | B4: =17+10+11+20+14+11+4 -> 87 | C4: =18+4+12+20+15+11+11+5 -> 96 | D4: =18+4+10+20+15+13+11+5+8 -> 104 | E4: =SUM(B4:D4) -> 287 | F4: да | G4: =1.8+2*2.6 -> 7 | H4: =H3-0.005 -> 0.325 | I4: =G4*H4 -> 2.275 | J4: =I4*E4-2 -> 650.925
A5: 7,8х2,7 | B5: =2 -> 2 | C5: =1+2 -> 3 | D5: =1+1 -> 2 | E5: =SUM(B5:D5) -> 7 | F5: да | G5: =7.8+2*2.6 -> 13 | H5: =H4 -> 0.325 | I5: =G5*H5 -> 4.225 | J5: =I5*E5 -> 29.575
A6: 4,8х2,7 | B6: =1+1 -> 2 | C6: =1+2+2 -> 5 | D6: =1+1+3+2 -> 7 | E6: =SUM(B6:D6) -> 14 | F6: да | G6: =4.8+2*2.6 -> 10 | H6: =H5 -> 0.325 | I6: =G6*H6 -> 3.25 | J6: =I6*E6 -> 45.5
A7: 4,65х2,7 | C7: =1 -> 1 | E7: =SUM(B7:D7) -> 1 | F7: да | G7: =4.65+2*2.6 -> 9.85 | H7: =H6 -> 0.325 | I7: =G7*H7 -> 3.20125 | J7: =I7*E7 -> 3.20125
A8: 1,8х6,9 | C8: 7 | E8: =SUM(B8:D8) -> 7 | F8: нет | G8: =(1.8+6.8)*2 -> 17.2 | H8: =H7 -> 0.325 | I8: =G8*H8 -> 5.59 | J8: =I8*E8 -> 39.13
A9: 1,8х6,9 | C9: 4 | E9: =SUM(B9:D9) -> 4 | F9: да | G9: =1.8+2*6.8 -> 15.4 | H9: =H8 -> 0.325 | I9: =G9*H9 -> 5.005 | J9: =I9*E9 -> 20.02
A10: 9,5х6,9 | C10: =1 -> 1 | E10: =SUM(B10:D10) -> 1 | F10: да | G10: =9.5+2*6.8 -> 23.1 | H10: =H9 -> 0.325 | I10: =G10*H10 -> 7.5075 | J10: =I10*E10 -> 7.5075
A11: 10,8х2,7 | B11: =1 -> 1 | E11: =SUM(B11:D11) -> 1 | F11: да | G11: =10.8+2*2.6 -> 16 | H11: =H10 -> 0.325 | I11: =G11*H11 -> 5.2 | J11: =I11*E11 -> 5.2
A12: 13,7х6,9 | C12: =1 -> 1 | E12: =SUM(B12:D12) -> 1 | F12: да | G12: =13.7+2*6.8 -> 27.3 | H12: =H11 -> 0.325 | I12: =G12*H12 -> 8.8725 | J12: =I12*E12 -> 8.8725
A13: 1,7х6,9 | C13: =10 -> 10 | E13: =SUM(B13:D13) -> 10 | F13: да | G13: =1.7+2*6.8 -> 15.3 | H13: =H12 -> 0.325 | I13: =G13*H13 -> 4.9725 | J13: =I13*E13 -> 49.725
A14: 1,8х1,5 | C14: 8 | E14: =SUM(B14:D14) -> 8 | F14: нет | G14: =(1.8+1.5)*2 -> 6.6 | H14: =H13 -> 0.325 | I14: =G14*H14 -> 2.145 | J14: =I14*E14 -> 17.16
A15: 7,8х3,3 | B15: 1 | C15: 0 | D15: 0 | E15: 1 | F15: да | G15: 14.4 | H15: 0.33 | I15: 4.752 | J15: 4.752
J16: =SUM(J3:J15) -> 930.67225

Sheet 10.3отк4
A1: Двери
A2: Марка окна | B2: Размер (ШхВ), м | C2: Всего, шт. | D2: Периметр откоса, м.п. | E2: Глубина откоса, м. | F2: Площадь одного откоса, м2 | G2: Общая площадь откосов, м2
A3: Д-1* | B3: 0,7х1,8 | C3: 60 | D3: =0.7+2*1.8 -> 4.3 | E3: 0.13 | F3: =D3*E3 -> 0.559 | G3: =F3*C3 -> 33.54
A4: Д-2*(л) | B4: 0,7х2,1 | C4: 3 | D4: =0.7+2*2.1 -> 4.9 | E4: 0.13 | F4: =D4*E4 -> 0.637 | G4: =F4*C4 -> 1.911
A5: Д-3, Д-3(л), Д-3.1 | B5: 0,9х2,1 | C5: =1+1+1 -> 3 | D5: =0.9+2*2.1 -> 5.1 | E5: 0.13 | F5: =D5*E5 -> 0.663 | G5: =F5*C5 -> 1.989
A6: Д-4, Д-4(л), Д-5, Д-5(л), Д-6(л), Д-7(л), Д-8, Д-8(л) | B6: 1,0х2,1 | C6: =1+1+10+4+1+1+3+1 -> 22 | D6: =1+2*2.1 -> 5.2 | E6: 0.13 | F6: =D6*E6 -> 0.676 | G6: =F6*C6 -> 14.872
A7: Д-9, Д-9(л), Д-10*, Д-10*(л) | B7: 1,1х2,1 | C7: =5+3+4+5 -> 17 | D7: =1.1+2*2.1 -> 5.3 | E7: 0.13 | F7: =D7*E7 -> 0.689 | G7: =F7*C7 -> 11.713
A8: Д-11, Д-11(л), Д-11.1, Д-11.1(л), Д-11.2, Д-11.2(л), Д-12, Д-12(л), Д-13, Д-13(л), Д-14*, Д-15*, Д-15*(л), Д-16, Д-16(л), Д-17*, Д-17*(л), Д-18, Д-19*(л), Д-20*, Д-21, Д-22*, Д-22*(л), Д-23, Д-24, Д-25 | B8: 1,15х2,1 | C8: =5+3+1+1+6+4+10+4+4+4+4+5+1+5+3+15+4+1+1+2+2+2+2+3+2+1 -> 95 | D8: =1.15+2*2.1 -> 5.35 | E8: 0.13 | F8: =D8*E8 -> 0.6955 | G8: =F8*C8 -> 66.0725
A9: Д-26* | B9: 1,2х2,1 | C9: 2 | D9: =1.2+2*2.1 -> 5.4 | E9: 0.13 | F9: =D9*E9 -> 0.702 | G9: =F9*C9 -> 1.404
A10: Д-27*(л) | B10: 1,4х2,1 | C10: 1 | D10: =1.4+2*2.1 -> 5.6 | E10: 0.13 | F10: =D10*E10 -> 0.728 | G10: =F10*C10 -> 0.728
A11: Д-28*, Д-29*, Д-29*(л), Д-30* | B11: 1,45х2,1 | C11: =6+6+2+1 -> 15 | D11: =1.45+2*2.1 -> 5.65 | E11: 0.13 | F11: =D11*E11 -> 0.7345 | G11: =F11*C11 -> 11.0175
A12: Д-31*, Д-31*(л) | B12: 1,6х2,1 | C12: =25+8 -> 33 | D12: =1.6+2*2.1 -> 5.8 | E12: 0.18 | F12: =D12*E12 -> 1.044 | G12: =F12*C12 -> 34.452
A13: Д-32(л), Д-33* | B13: 1,65х2,4 | C13: =1+1 -> 2 | D13: =1.65+2*2.4 -> 6.45 | E13: 0.18 | F13: =D13*E13 -> 1.161 | G13: =F13*C13 -> 2.322
A14: Д-34* | B14: 2,2х2,4 | C14: 2 | D14: =2.2+2*2.4 -> 7 | E14: 0.18 | F14: =D14*E14 -> 1.26 | G14: =F14*C14 -> 2.52
A15: ДО-1, ДО-1(л), ДО-1.1* | B15: 1,7х2,4 | C15: =51+2+17 -> 70 | D15: =1.7+2*2.4 -> 6.5 | E15: 0.18 | F15: =D15*E15 -> 1.17 | G15: =F15*C15 -> 81.9
A16: ДО-2*, ДО-2.1* | B16: 2,0х2,4 | C16: =3+1 -> 4 | D16: =2+2*2.4 -> 6.8 | E16: 0.33 | F16: =D16*E16 -> 2.244 | G16: =F16*C16 -> 8.976
A17: ДО-3*, ДО-3.1*, ДО-3.2*, ДО-3.3*, ДО-3.4*, ДО-3.5* | B17: 2,1х2,4 | C17: =1+3+2+2+2+2 -> 12 | D17: =2.1+2*2.4 -> 6.9 | E17: 0.18 | F17: =D17*E17 -> 1.242 | G17: =F17*C17 -> 14.904
A18: ИТОГО, м2 | C18: =SUM(C3:C17) -> 341 | G18: =SUM(G3:G17) -> 288.321

Sheet Лист1
B1: 1.6 | C1: 1000 | D1: 2700 | G1: 4
B2: 1.7 | C2: 1800 | D2: 2700 | G2: 87
B3: 1.9 | C3: 2060 | D3: 3230 | G3: 1
B4: 1.10 | C4: 2150 | D4: 2700 | G4: 1
B5: 1.11 | C5: 2150 | D5: 3430 | G5: 3
B6: 1.14 | C6: 2800 | D6: 3430 | G6: 1
B7: 1.18 | C7: 3300 | D7: 2700 | G7: 1
B8: 1.27 | C8: 4800 | D8: 2700 | G8: 2
B9: 1.29 | C9: 4800 | D9: 3430 | G9: 1
B10: 1.33 | C10: 5150 | D10: 2700 | G10: 1
B11: 1.34 | C11: 5150 | D11: 3430 | G11: 2
B12: 1.38 | C12: 6550 | D12: 2930 | G12: 1
B13: 1.39 | C13: 6800 | D13: 2300 | G13: 1
A16: Устройство витражных откосов.
A17: эт. | B17: шт | C17: верхняя пл-ть, общая, м2 | F17: боковая пл-тьь, общая, м2 | H17: высота откоса, м. | I17: Глубина откоса, м. | J17: Площадь одного откоса, м2 | K17: Итог, м2
A18: 1 эт | B18: 33 | C18: 35.79 | F18: =B18*2*3.8*0.13 -> 32.604 | H18: 3.85 | I18: 0.13 | K18: =SUM(C18:F18) -> 68.394
A19: 2 эт | B19: 17 | C19: 13.03 | F19: =B19*2*3.8*0.13 -> 16.796 | H19: 3.85 | I19: 0.13 | K19: =SUM(C19:F19) -> 29.826
A20: 3 эт | B20: 25 | C20: 16.06 | F20: =B20*2*3.8*0.13 -> 24.7 | H20: 3.85 | I20: 0.13 | K20: =SUM(C20:F20) -> 40.76
A21: Итог: | K21: =SUM(K18:K20) -> 138.98
B33: 2.4 | C33: 1000 | D33: 2700 | G33: 4
B34: 2.5 | C34: 1500 | D34: 2700 | G34: 1
B35: 2.6 | C35: 1700 | D35: 2700 | G35: 10
B36: 2.7 | C36: 1800 | D36: 1500 | G36: 6
B37: 2.8 | C37: 1800 | D37: 2700 | G37: 108
B38: 2.10 | C38: 1930 | D38: 2700 | G38: 1
B39: 2.13 | C39: 2370 | D39: 2700 | G39: 1
B40: 2.14 | C40: 2800 | D40: 2700 | G40: 1
B41: 2.17 | C41: 3000 | D41: 1200 | G41: 1
B42: 2.18 | C42: 3000 | D42: 1200 | G42: 1
B43: 2.20 | C43: 3300 | D43: 2700 | G43: 1
B44: 2.26 | C44: 4650 | D44: 2700 | G44: 1
... B68: 3.31 | C68: 5350 | D68: 4200 | G68: 1

Sheet 10.2плны
A1: Ведомость работ
A2: № п.п. | B2: Наименование затрат | H2: Ед. изм. | I2: Объем
A3: 1 | B3: Штукатурка поверхностей откосов сухими смесями с предварительной огрунтовкой поверхности | H3: м2 | I3: =C15 -> 1688.585
A4: 2 | B4: Выравнивание поверхностей откосов толщ. до 5 мм с предварительной огрунтовкой поверхности (базовая шпаклевка) | H4: м2 | I4: =I3 -> 1688.585
A5: 3 | B5: Выравнивание поверхностей откосов толщ. до 5 мм с предварительной огрунтовкой поверхности (финишная шпаклевка) | H5: м2 | I5: =I4 -> 1688.585
A6: 4 | B6: Лакокрасочные работы СКБ / окраска откосов / 2 слоя / СТ-2.1 | H6: м2 | I6: =C21 -> 203.451
A7: 5 | B7: Лакокрасочные работы СКБ / окраска откосов / 2 слоя / СТ-2.16 | H7: м2 | I7: =C28 -> 72.609
A8: 6 | B8: Лакокрасочные работы СКБ / окраска откосов / 2 слоя / СТ-1.1 | H8: м2 | I8: =C35 -> 1374.697
A9: 7 | B9: Лакокрасочные работы СКБ / окраска откосов / 2 слоя / СТ-2.3 | H9: м2 | I9: =I21 -> 37.828
A11: № п.п. | B11: № эт. | C11: Объем, м2:
A12: 1 | B12: 1 | C12: =C18+I18+C25+C32 -> 631.9
A13: 2 | B13: 2 | C13: =C19+I19+C26+C33 -> 559.504
A14: 3 | B14: 3 | C14: =C20+I20+C27+C34 -> 497.181
A15: Итог: | C15: =SUM(C12:C14) -> 1688.585
A16: СТ-2.1 | G16: СТ-2.3
A17: № п.п. | B17: № эт. | C17: Объем, м2: | G17: № п.п. | H17: № эт. | I17: Объем, м2:
A18: 1 | B18: 1 | C18: =3.38*8+(1.5*4 + 1.1*4)*3.3+(6.8+9.19)*3.3 -> 114.127 | G18: 1 | H18: 1 | I18: =(1.5*4 + 1.1*4)*0.7 -> 7.28
A19: 2 | B19: 2 | C19: =8*2.8+7.2*3.3 -> 46.16 | G19: 2 | H19: 2 | I19: =7.2*0.7+12.14*0.7 -> 13.538
A20: 3 | B20: 3 | C20: =3.38*7.8+4.2*4 -> 43.164 | G20: 3 | H20: 3 | I20: =24.3*0.7 -> 17.01
A21: Итог: | C21: =SUM(C18:C20) -> 203.451 | G21: Итог: | I21: =SUM(I18:I20) -> 37.828
A23: СТ-2.16
A24: № п.п. | B24: № эт. | C24: Объем, м2:
A25: 1 | B25: 1 | C25: =0.62*8+1.1*4+6.9*0.7+(6.8+9.19)*0.7 -> 25.383
A26: 2 | B26: 2 | C26: =2.2*0.7 -> 1.54
A27: 3 | B27: 3 | C27: =2.16*4+0.62*7.8+0.7*1.8+5*4+4*0.62+12.1*0.7 -> 45.686
A28: Итог: | C28: =SUM(C25:C27) -> 72.609
A30: СТ-1.1
A31: № п.п. | B31: № эт. | C31: Объем, м2:
A32: 1 | B32: 1 | C32: =3.38*3+6.9*3.3+16.25*12.2+7.75*12.2+12.3*8+15.25*4 -> 485.11
A33: 2 | B33: 2 | C33: =4*15.2+1.6*8+1.3*3.38+4.2*4+12.14*3.3+14.35*4+5.6*8+24.13*4+17.3*9.1+2.2*3.3 -> 498.266
A34: 3 | B34: 3 | C34: =6*4+24.77*3.3+24.3*3.3+36.5*4+1.8*3.3+4*3.38+12.1*3.3 -> 391.321
A35: Итог: | C35: =SUM(C32:C34) -> 1374.697

Sheet 8.7штр
A1: Ведомость работ
A2: № п.п. | B2: Наименование затрат | G2: Ед. изм. | H2: Объем
A3: 1 | B3: Заделка штроб | G3: пог. м. | H3: =B39+E19+H41+K39+N39+Q37 -> 5679
A5: Пом. | B5: п.м | D5: Пом. | E5: п.м | G5: Пом. | H5: п.м | J5: Пом. | K5: п.м | M5: Пом. | N5: п.м | P5: Пом. | Q5: п.м
A6: 1006 | B6: 7 | D6: 1112 | E6: 8 | G6: 2001 | H6: 22.8 | J6: 2036 | K6: 88.8 | M6: 3001 | N6: 40 | P6: 3034 | Q6: 6
A7: 1004 | B7: 4 | D7: 1062 | E7: 34 | G7: 2002 | H7: 57.6 | J7: 2037 | K7: 151.2 | M7: 3002 | N7: 40 | P7: 3035 | Q7: 48
A8: 1005 | B8: 3 | D8: 1061 | E8: 24 | G8: 2003 | H8: 112.8 | J8: 2038 | K8: 57.6 | M8: 3003 | N8: 36 | P8: 3036 | Q8: 16
A9: 1007 | B9: 20 | D9: 1067 | E9: 15 | G9: 2004 | H9: 45.6 | J9: 2039 | K9: 50.4 | M9: 3004 | N9: 88 | P9: 3037 | Q9: 77
A10: 1009 | B10: 9 | D10: 1073 | E10: 21 | G10: 2005 | H10: 40.8 | J10: 2040 | K10: 36 | M10: 3005 | N10: 17 | P10: 3038 | Q10: 122
A11: 1052 | B11: 2 | D11: 1070 | E11: 9 | G11: 2006 | H11: 9.6 | J11: 2041 | K11: 48 | M11: 3006 | N11: 39 | P11: 3039 | Q11: 22
A12: 1088 | B12: 7 | D12: 1079 | E12: 8 | G12: 2007 | H12: 14.4 | J12: 2042 | K12: 69.6 | M12: 3007 | N12: 34 | P12: 3040 | Q12: 88
A13: 1011 | B13: 6 | D13: 1084 | E13: 5 | G13: 2008 | H13: 9.6 | J13: 2043 | K13: 31.2 | M13: 3008 | N13: 2 | P13: 3041 | Q13: 132
A14: 1012 | B14: 15 | D14: 1080 | E14: 15 | G14: 2009 | H14: 31.2 | J14: 2044 | K14: 0 | M14: 3009 | N14: 5 | P14: 3042 | Q14: 5
A15: 1002 | B15: 19 | D15: 1068 | E15: 14 | G15: 2010 | H15: 6 | J15: 2045 | K15: 112.8 | M15: 3010 | N15: 82 | P15: 3043 | Q15: 8
A16: 1008 | B16: 9 | D16: 1057 | E16: 25 | G16: 2011 | H16: 2.4 | J16: 2046 | K16: 148.8 | M16: 3011 | N16: 60 | P16: 3044 | Q16: 2
A17: 1016 | B17: 4 | D17: 1048 | E17: 18 | G17: 2012 | H17: 74.4 | J17: 2047 | K17: 14.4 | M17: 3012 | N17: 126 | P17: 3045 | Q17: 20
A18: 1085 | B18: 27 | D18: 1045 | E18: 23 | G18: 2013 | H18: 52.8 | J18: 2048 | K18: 45.6 | M18: 3013 | N18: 40 | P18: 3046 | Q18: 22
A19: 1026 | B19: 3 | D19: Итог: | E19: =SUM(E6:E18) -> 219 | G19: 2014 | H19: 57.6 | J19: 2049 | K19: 96 | M19: 3014 | N19: 56 | P19: 3047 | Q19: 33
A20: 1027 | B20: 3 | G20: 2015 | H20: 52.8 | J20: 2050 | K20: 7.2 | M20: 3015 | N20: 12 | P20: 3048 | Q20: 65
A21: 1024 | B21: 3 | G21: 2016 | H21: 48 | J21: 2053 | K21: 14.4 | M21: 3016 | N21: 35 | P21: 3049 | Q21: 30
A22: 1017 | B22: 3 | G22: 2017 | H22: 151.2 | J22: 2054 | K22: 3.6 | M22: 3017 | N22: 10 | P22: 3050 | Q22: 82
A23: 1022 | B23: 7 | G23: 2018 | H23: 2.4 | J23: 2055 | K23: 18 | M23: 3018 | N23: 12 | P23: 3051 | Q23: 61
A24: 1036 | B24: 21 | G24: 2019 | H24: 2.4 | J24: 2056 | K24: 9.6 | M24: 3019 | N24: 140 | P24: 3052 | Q24: 0
A25: 1015 | B25: 34 | G25: 2020 | H25: 15.6 | J25: 2057 | K25: 9.6 | M25: 3020 | N25: 0 | P25: 3053 | Q25: 88
A26: 1023 | B26: 16 | G26: 2021 | H26: 6 | J26: 2058 | K26: 4.8 | M26: 3021 | N26: 20 | P26: 3054 | Q26: 44
A27: 1028 | B27: 17 | G27: 2022 | H27: 151.2 | J27: 2059 | K27: 2.4 | M27: 3022 | N27: 36 | P27: 3055 | Q27: 5
A28: 1029 | B28: 15 | G28: 2023 | H28: 2.4 | J28: 2060 | K28: 4.8 | M28: 3023 | N28: 83 | P28: 3057 | Q28: 5
A29: 1030 | B29: 10 | G29: 2024 | H29: 0 | J29: 2061 | K29: 57.6 | M29: 3024 | N29: 0 | P29: 3058 | Q29: 54
A30: 1050 | B30: 4 | G30: 2025 | H30: 16.8 | J30: 2062 | K30: 43.2 | M30: 3025 | N30: 5 | P30: 3059 | Q30: 104
A31: 1053 | B31: 8 | G31: 2026 | H31: 2.4 | J31: 2063 | K31: 0 | M31: 3026 | N31: 2 | P31: 3061 | Q31: 2
... A36: 1059 | B36: 11 | G36: 2031 | H36: 21.6 | J36: 2068 | K36: 38.4 | M36: 3031 | N36: 54 | P36: 3067 | Q36: 20
A37: 1087 | B37: 3 | G37: 2032 | H37: 45.6 | J37: 2070 | K37: 52.8 | M37: 3032 | N37: 42 | P37: Итог: | Q37: =SUM(Q6:Q36) -> 1228
A38: 1051 | B38: 4 | G38: 2033 | H38: 7.2 | J38: 2071 | K38: 93.6 | M38: 3033 | N38: 28
A39: Итог: | B39: =SUM(B6:B38) -> 348 | G39: 2034 | H39: 4.8 | J39: Итог: | K39: =SUM(K6:K38) -> 1446 | M39: Итог: | N39: =SUM(N6:N38) -> 1346
G40: 2035 | H40: 2.4
G41: Итог: | H41: =SUM(H6:H40) -> 1092

Sheet 7.5.1лес
A1: Ведомость работ
A2: № п.п. | B2: Наименование затрат | E2: Ед. изм. | F2: Объем
A3: 1 | B3: Монтаж, демонтаж, аренда строительных лесов | E3: м2 | F3: =C9 -> 2292
A5: № п.п. | B5: № эт. | C5: Объем, м2:
A6: 1 | B6: 1 | C6: =252+660 -> 912
A7: 2 | B7: 2 | C7: =378+608+322 -> 1308
A8: 3 | B8: 3 | C8: =12*3*2 -> 72
A9: Итог: | C9: =SUM(C6:C8) -> 2292

Sheet 8.6отв
A1: Ведомость работ
A2: № п.п. | B2: Наименование затрат | J2: Ед. изм. | K2: Объем
A3: 1 | B3: Заделка отверстий в стенах в местах прохода коммуникации / до 500 см2 | J3: шт | K3: 746

Sheet 8.5дфрг
A1: Ведомость работ
A2: № п.п. | B2: Наименование затрат | J2: Ед. изм. | K2: Объем
A3: 1 | B3: Заделка мест прохождения воздуховодов | J3: м3 | K3: =Q35+N36+K36+H37+B37+E21 -> 86.9952
A4: 2 | B4: Заделка стояков отопления | J4: м3 | K4: =292*(0.15*0.15*0.25) -> 1.6425
A5: Итог (м3): | K5: =SUM(K3:K4) -> 88.6377
A7: Пом. | B7: Объем, м3: | D7: Пом. | E7: Объем, м3: | G7: Пом. | H7: Объем, м3: | J7: Пом. | K7: Объем, м3: | M7: Пом. | N7: Объем, м3: | P7: Пом. | Q7: Объем, м3:
A8: 1.005 | B8: 0.09456 | D8: 1.112 | E8: 0.37824 | G8: 2.001 | H8: 0.66192 | J8: 2.036 | K8: 1.13472 | M8: 3.001 | N8: 0.66192 | P8: 3.033 | Q8: 0.4728
A9: 1.007 | B9: 0.37824 | D9: 1.061 | E9: 0.56736 | G9: 2.002 | H9: 0.75648 | J9: 2.038 | K9: 0.56736 | M9: 3.002 | N9: 0.66192 | P9: 3.035 | Q9: 0.66192
A10: 1.009 | B10: 0.18912 | D10: 1.063 | E10: 0.18912 | G10: 2.003 | H10: 0.66192 | J10: 2.039 | K10: 0.56736 | M10: 3.003 | N10: 0.66192 | P10: 3.036 | Q10: 0.56736
A11: 1.015 | B11: 0.09456 | D11: 1.064 | E11: 0.09456 | G11: 2.004 | H11: 0.75648 | J11: 2.040 | K11: 0.56736 | M11: 3.004 | N11: 1.13472 | P11: 3.037 | Q11: 1.60752
A12: 1.024 | B12: 0.18912 | D12: 1.097 | E12: 0.18912 | G12: 2.005 | H12: 0.37824 | J12: 2.041 | K12: 0.56736 | M12: 3.005 | N12: 0.18912 | P12: 3.038 | Q12: 1.70208
A13: 1.027 | B13: 0.09456 | D13: 1.069 | E13: 0.4728 | G13: 2.009 | H13: 0.4728 | J13: 2.042 | K13: 1.70208 | M13: 3.007 | N13: 0.4728 | P13: 3.039 | Q13: 0.18912
A14: 1.031 | B14: 0.18912 | D14: 1.070 | E14: 0.4728 | G14: 2.010 | H14: 0.18912 | J14: 2.043 | K14: 0.4728 | M14: 3.008 | N14: 0.37824 | P14: 3.040 | Q14: 0.9456
A15: 1.032 | B15: 0.18912 | D15: 1.073 | E15: 0.9456 | G15: 2.011 | H15: 0.18912 | J15: 2.045 | K15: 1.70208 | M15: 3.009 | N15: 0.09456 | P15: 3.041 | Q15: 1.8912
A16: 1.028 | B16: 0.09456 | D16: 1.072 | E16: 0.09456 | G16: 2.012 | H16: 0.66192 | J16: 2.046 | K16: 1.60752 | M16: 3.010 | N16: 1.13472 | P16: 3.042 | Q16: 0.18912
A17: 1.044 | B17: 0.09456 | D17: 1.083 | E17: 0.4728 | G17: 2.013 | H17: 0.66192 | J17: 2.047 | K17: 1.04016 | M17: 3.011 | N17: 1.13472 | P17: 3.043 | Q17: 0.18912
A18: 1.043 | B18: 0.09456 | D18: 1.078 | E18: 0.66192 | G18: 2.014 | H18: 0.66192 | J18: 2.048 | K18: 1.4184 | M18: 3.012 | N18: 2.08032 | P18: 3.044 | Q18: 0.18912
A19: 1.092 | B19: 0.09456 | D19: 1.075 | E19: 0.56736 | G19: 2.015 | H19: 0.66192 | J19: 2.049 | K19: 1.04016 | M19: 3.013 | N19: 0.56736 | P19: 3.045 | Q19: 0.18912
A20: 1.042 | B20: 0.37824 | D20: 1.076 | E20: 0.75648 | G20: 2.016 | H20: 0.66192 | J20: 2.050 | K20: 0.56736 | M20: 3.014 | N20: 0.66192 | P20: 3.046 | Q20: 0.4728
A21: 1.050 | B21: 0.28368 | D21: Итог: | E21: =SUM(E8:E20) -> 5.86272 | G21: 2.017 | H21: 1.22928 | J21: 2.051 | K21: 0.28368 | M21: 3.015 | N21: 0.28368 | P21: 3.048 | Q21: 0.56736
A22: 1.105 | B22: 0.09456 | G22: 2.018 | H22: 0.18912 | J22: 2.052 | K22: 0.37824 | M22: 3.017 | N22: 0.09456 | P22: 3.049 | Q22: 0.37824
A23: 1.106 | B23: 0.09456 | G23: 2.020 | H23: 0.18912 | J23: 2.053 | K23: 0.18912 | M23: 3.018 | N23: 0.09456 | P23: 3.050 | Q23: 0.66192
A24: 1.109 | B24: 0.18912 | G24: 2.021 | H24: 0.18912 | J24: 2.054 | K24: 0.28368 | M24: 3.019 | N24: 1.8912 | P24: 3.051 | Q24: 0.66192
A25: 1.046 | B25: 0.28368 | G25: 2.022 | H25: 1.60752 | J25: 2.055 | K25: 0.56736 | M25: 3.021 | N25: 0.18912 | P25: 3.053 | Q25: 1.32384
A26: 1.107 | B26: 0.09456 | G26: 2.025 | H26: 0.75648 | J26: 2.060 | K26: 1.04016 | M26: 3.022 | N26: 0.66192 | P26: 3.054 | Q26: 0.37824
A27: 1.047 | B27: 0.28368 | G27: 2.026 | H27: 0.09456 | J27: 2.061 | K27: 1.98576 | M27: 3.023 | N27: 1.51296 | P27: 3.055 | Q27: 0.18912
A28: 1.049 | B28: 0.28368 | G28: 2.027 | H28: 0.09456 | J28: 2.062 | K28: 1.70208 | M28: 3.025 | N28: 0.09456 | P28: 3.057 | Q28: 0.09456
A29: 1.060 | B29: 0.28368 | G29: 2.028 | H29: 0.18912 | J29: 2.064 | K29: 0.18912 | M29: 3.026 | N29: 0.09456 | P29: 3.058 | Q29: 0.18912
A30: 1.081 | B30: 0.09456 | G30: 2.029 | H30: 0.09456 | J30: 2.065 | K30: 0.28368 | M30: 3.027 | N30: 1.13472 | P30: 3.059 | Q30: 0.09456
A31: 1.082 | B31: 0.18912 | G31: 2.030 | H31: 0.75648 | J31: 2.066 | K31: 1.70208 | M31: 3.028 | N31: 0.66192 | P31: 3.063 | Q31: 0.75648
A32: 1.054 | B32: 0.09456 | G32: 2.031 | H32: 0.37824 | J32: 2.067 | K32: 1.8912 | M32: 3.029 | N32: 0.09456 | P32: 3.064 | Q32: 0.09456
A33: 1.058 | B33: 0.18912 | G33: 2.032 | H33: 0.66192 | J33: 2.068 | K33: 1.60752 | M33: 3.030 | N33: 0.66192 | P33: 3.066 | Q33: 1.4184
A34: 1.059 | B34: 0.28368 | G34: 2.033 | H34: 0.09456 | J34: 2.070 | K34: 0.4728 | M34: 3.031 | N34: 0.66192 | P34: 3.067 | Q34: 0.4728
A35: 1.087 | B35: 0.09456 | G35: 2.034 | H35: 0.09456 | J35: 2.071 | K35: 1.13472 | M35: 3.032 | N35: 0.66192 | P35: Итог: | Q35: =SUM(Q8:Q34) -> 16.548
A36: 1.051 | B36: 0.18912 | G36: 2.035 | H36: 0.09456 | J36: Итог: | K36: =SUM(K8:K35) -> 26.66592 | M36: Итог: | N36: =SUM(N8:N35) -> 18.62832
A37: Итог: | B37: =SUM(B8:B36) -> 5.2008 | G37: Итог: | H37: =SUM(H8:H36) -> 14.08944

Sheet 8.4отк.лк
A1: Ведомость работ
A2: № п.п. | B2: Наименование затрат | F2: Описание | G2: Ед. изм. | H2: Объем
A3: 1 | B3: Устройство проемов из файерборд / в 1 слои | F3: 1-3 эт. Откосы лючков "Хаммер". | G3: м2 | H3: =E12 -> 51.6
A4: 2 | B4: Подготовка поверхности СКБ / 2мм | F4: 1-3 эт. Шпаклевка откосов базовая. Откосы лючков "Хаммер". | G4: м2 | H4: =H3 -> 51.6
A5: 3 | B5: Подготовка поверхности СКБ / 2мм | F5: 1-3 эт. Шпаклевка откосов финишная. Откосы лючков "Хаммер". | G5: м2 | H5: =H4 -> 51.6
A6: 4 | B6: Лакокрасочные работы СКБ / окраска откосов / в 2 слоя | F6: 1-3 эт. Откосы лючков "Хаммер". | G6: м2 | H6: =H5 -> 51.6
A8: № эт | B8: Кол-во люков, шт | C8: Периметр (п.м.). | D8: Ширина, м. | E8: Сумма, м2.
A9: 1 | B9: 20 | C9: 0,7+(1,8*2) | D9: 0.2 | E9: =((0.7+(1.8*2))*0.2)*B9 -> 17.2
A10: 2 | B10: 18 | C10: 0,7+(1,8*2) | D10: 0.2 | E10: =((0.7+(1.8*2))*0.2)*B10 -> 15.48
A11: 3 | B11: 22 | C11: 0,7+(1,8*2) | D11: 0.2 | E11: =((0.7+(1.8*2))*0.2)*B11 -> 18.92
B12: =SUM(B9:B11) -> 60 | D12: Итог: | E12: =SUM(E9:E11) -> 51.6

Sheet 8.3шп.лк
A1: Ведомость работ
A2: № п.п. | B2: Наименование затрат | F2: Описание | G2: Ед. изм. | H2: Объем
A3: 1 | B3: Подготовка поверхности СКБ / 2мм | F3: 1-3 эт. Шпаклевка базовая лючков "Хаммер" | G3: м2 | H3: =D11 -> 65.394
A4: 2 | B4: Подготовка поверхности СКБ / 2мм | F4: 1-3 эт. Шпаклевка финишная лючков "Хаммер" | G4: м2 | H4: =H3 -> 65.394
A5: 3 | B5: Лакокрасочные работы СКБ / окраска стен / в 2 слоя | F5: 1-3 эт. Лючки "Хаммер" | G5: м2 | H5: =H4 -> 65.394
A7: № эт | B7: Кол-во люков, шт | C7: Габариты (м*м). | D7: Сумма, м2.
A8: 1 | B8: 20 | C8: 0,63х1,730 | D8: =0.63*1.73*B8 -> 21.798
A9: 2 | B9: 18 | C9: 0,63х1,730 | D9: =0.63*1.73*B9 -> 19.6182
A10: 3 | B10: 22 | C10: 0,63х1,730 | D10: =0.63*1.73*B10 -> 23.9778
B11: =SUM(B8:B10) -> 60 | C11: Итог: | D11: =SUM(D8:D10) -> 65.394

Sheet 8.2умнь.дв
A1: Ведомость работ
A2: № п.п. | B2: Наименование затрат | D2: Описание | F2: Ед. изм. | G2: Объем
A3: 1 | B3: Устройство проемов из файерборд / в 2 слоя | D3: 1-3 эт. Дверные откосы. Уменьшение дверных проемов. /файерборд | F3: м2 | G3: =E10 -> 12.66696
A5: Расчет
A6: Этаж | B6: Кол-во, шт. | C6: Ср. ширина, м | D6: Ср. длина, м | E6: Сумма, м2
A7: 1 | B7: 20 | C7: 0.155 | D7: 1.13 | E7: =C7*D7*B7 -> 3.503
A8: 2 | B8: 13 | C8: 0.189 | D8: 1.4 | E8: =C8*D8*B8 -> 3.4398
A9: 3 | B9: 26 | C9: 0.172 | D9: 1.28 | E9: =C9*D9*B9 -> 5.72416
A10: Итог, м2: | E10: =SUM(E7:E9) -> 12.66696

Sheet 8.1дврн.откс
A1: Ведомость работ
A2: № п.п. | B2: Наименование затрат | C2: Описание | D2: Ед. изм. | E2: Объем
A3: 1 | B3: Устройство откосов из ГКЛ / в 2 слоя | C3: 1-3 эт. Дверные откосы. Фаиерборд. | D3: м2 | E3: 20.85
A4: 2 | B4: Подготовка поверхности СКБ / стен / по ГКЛ / 2мм | C4: 1-3 эт. Шпаклевка базовая | D4: м2 | E4: =E3 -> 20.85
A5: 3 | B5: Подготовка поверхности СКБ / стен / по ГКЛ / 2мм | C5: 1-3 эт. Шпаклевка финишная | D5: м2 | E5: =E4 -> 20.85

Sheet 7.8фрхв
A1: Ведомость работ
A2: № п.п. | B2: Наименование затрат | F2: Ед. изм. | G2: Объем
A3: 1 | B3: Устройство металлоконструкций фахверков, стоек, рам, балок, опорных конструкций и усилений с учетом крепления, огрунтовки и окрашивания | F3: т | G3: 4.773
A4: 2 | B4: Устройство металлоконструкций фахверков, стоек, рам, балок, опорных конструкций и усилений с учетом крепления, огрунтовки и окрашивания | F4: т | G4: 1.977
A6: № п.п. | B6: № фархверки | C6: Кол-во, шт. | D6: вес, кг | E6: общ. вес, кг.
A7: 1 | B7: Ф-250.3 | C7: 42.64 | D7: 156 | E7: =C7*D7-29.76 -> 6622.08
A8: 2 | B8: Ф-250.3.1 | C8: 42.64 | D8: 3 | E8: =C8*D8 -> 127.92
D9: Итог: | E9: =SUM(E7:E8) -> 6750

Sheet 7.7внеш.блк
A1: Ведомость работ
A2: № п.п. | B2: Наименование затрат | F2: Ед. изм. | G2: Объем
A3: 1 | B3: Кладка наружных стен из блоков ячеистого бетона без устройства перемычек, включая армирование, устройство примыканий | F3: м3 | G3: 11.7
A4: 2 | B4: Кладка наружных стен из блоков ячеистого бетона без устройства перемычек, включая армирование, устройство примыканий | F4: м3 | G4: 9.54
A5: 3 | B5: Кладка наружных стен из блоков ячеистого бетона без устройства перемычек, включая армирование, устройство примыканий | F5: м3 | G5: 11.8

Sheet 7.6прмч
A1: Ведомость работ
A2: № п.п. | B2: Наименование затрат | F2: Ед. изм. | G2: Объем
A3: 1 | B3: Устройство перемычек металлических с огрунтовкой и окраской | F3: т | G3: 0.589
A4: 2 | B4: Устройство перемычек металлических с огрунтовкой и окраской | F4: т | G4: 0.373
A5: 3 | B5: Устройство перемычек металлических с огрунтовкой и окраской | F5: т | G5: 0.484
A6: № п.п. | B6: № перемч | C6: Кол-во, шт. | D6: вес, кг | E6: общ. вес, кг.
A7: 1 | B7: ПР-21 | C7: 1 | D7: =23.43+0.68 -> 24.11 | E7: =C7*D7 -> 24.11
A8: 2 | B8: ПР-27 | C8: 1 | D8: =33.07+1.13+1.38 -> 35.58 | E8: =C8*D8 -> 35.58
A9: 3 | B9: ПР-30 | C9: 1 | D9: =63.7+1.13+2.45 -> 67.28 | E9: =C9*D9-10.8 -> 56.48
A10: 4 | B10: ПР-33 | C10: 3 | D10: =13.79+0.87+3.45 -> 18.11 | E10: =C10*D10 -> 54.33
A11: 5 | B11: ПР-34 | C11: 1 | D11: =17.19+1.16+3.45 -> 21.8 | E11: =C11*D11 -> 21.8
A12: 6 | B12: ПР-35 | C12: 5 | D12: =44.1+1.16+3.45 -> 48.71 | E12: =C12*D12 -> 243.55
A13: 7 | B13: ПР-36 | C13: 2 | D13: =44.1+1.16+3.45 -> 48.71 | E13: =C13*D13 -> 97.42
A14: 8 | B14: ПР-37 | C14: 1 | D14: =50.84+1.44+3.45 -> 55.73 | E14: =C14*D14 -> 55.73
D15: Итог: | E15: =SUM(E7:E14) -> 589
A16: 9 | B16: ПР-5 | C16: 1 | D16: =13.09+0.68+1.38 -> 15.15 | E16: =C16*D16 -> 15.15
A17: 10 | B17: ПР-6 | C17: 3 | D17: =9.65+0.65+2.76 -> 13.06 | E17: =C17*D17 -> 39.18
A18: 11 | B18: ПР-10 | C18: 1 | D18: =20.67+0.68 -> 21.35 | E18: =C18*D18 -> 21.35
A19: 12 | B19: ПР-12 | C19: 1 | D19: =22.74+0.68 -> 23.42 | E19: =C19*D19 -> 23.42
A20: 13 | B20: ПР-13 | C20: 1 | D20: =19.29+0.68+1.38 -> 21.35 | E20: =C20*D20 -> 21.35
A21: 14 | B21: ПР-17 | C21: 4 | D21: =28.25+0.9+1.38 -> 30.53 | E21: =C21*D21-13.44 -> 108.68
A22: 15 | B22: ПР-18 | C22: 1 | D22: =28.25+0.9+1.38 -> 30.53 | E22: =C22*D22 -> 30.53
A23: 16 | B23: ПР-20 | C23: 1 | D23: =23.43+0.9+2.76 -> 27.09 | E23: =C23*D23 -> 27.09
A24: 17 | B24: ПР-30 | C24: 1 | D24: =53.9+1.13+2.76 -> 57.79 | E24: =C24*D24 -> 57.79
A25: 18 | B25: ПР-32 | C25: 1 | D25: =24.8+0.9+2.76 -> 28.46 | E25: =C25*D25 -> 28.46
D26: Итог: | E26: =SUM(E16:E25) -> 373
A27: 19 | B27: ПР-4 | C27: 2 | D27: =13.09+0.68+2.76 -> 16.53 | E27: =C27*D27 -> 33.06
A28: 20 | B28: ПР-5 | C28: 3 | D28: =9.65+0.65+2.76 -> 13.06 | E28: =C28*D28-7.92 -> 31.26
A29: 21 | B29: ПР-7 | C29: 1 | D29: =19.29+0.68 -> 19.97 | E29: =C29*D29 -> 19.97
A30: 22 | B30: ПР-9 | C30: 1 | D30: =20.76+0.68 -> 21.44 | E30: =C30*D30 -> 21.44
A31: 23 | B31: ПР-12 | C31: 1 | D31: =19.29+0.68+1.38 -> 21.35 | E31: =C31*D31 -> 21.35
A32: 24 | B32: ПР-15 | C32: 6 | D32: =28.25+0.9+1.38 -> 30.53 | E32: =C32*D32 -> 183.18
A33: 25 | B33: ПР-16 | C33: 1 | D33: =28.28+0.9+1.38 -> 30.56 | E33: =C33*D33 -> 30.56
A34: 26 | B34: ПР-18 | C34: 1 | D34: =23.43+0.9+2.76 -> 27.09 | E34: =C34*D34 -> 27.09
A35: 27 | B35: ПР-25 | C35: 1 | D35: =24.8+0.9+2.76 -> 28.46 | E35: =C35*D35 -> 28.46
A36: 28 | B36: ПР-27 | C36: 1 | D36: =27.56+0.9+1.38 -> 29.84 | E36: =C36*D36 -> 29.84
A37: 29 | B37: ПР-28 | C37: 1 | D37: =53.9+1.13+2.76 -> 57.79 | E37: =C37*D37 -> 57.79
D38: Итог: | E38: =SUM(E27:E37) -> 484

Sheet КП
A1: Указать название организации (на бланке организации) | D1: {"estimateId":5186302,"estimateVersionId":7249287} | F1: 12 | G1: eF7s/euSXFdyJoi+SpjM2qykRMTZt7UvPDY/ADCJzixkRgI7o8dmijJZXntoqiI1rNJ0t8bajBdRVRpWiyWV1KrDIosi1dPTP461oUhCRBEk+AqRr3Ce5Ky145Jg5PK93T32tyKoVpUhmZlIAN/na2/3by335f5//t5P/sOfXPzeC7/3o5M/+b1bv/d/nPzwTy+Om++8+qc//OGt37v492cXP5x94/d+vPgB+/n/+fLvnb32ox+99urLv/fCD+wX7m+xn15/99bL13/Zy/O/7eXrv6752R9f/1jz9fQfp19OH02/mD66euvq54Pp180Xn9qPX0+fTB8Pps+u3ph+Nv/S/dRf2P8+GXzP/eBg+tvp0+a3viR/8vebf+/stddeP3/l1ZOfzP7R23Hz3Ysf/+SVH9nvPXzt3+2dPwf41Z+88pP/cO9PX1l87z/e+jbbVy9f+bc6tv/nyy9f/7P237RfvWDiMk+j5Nbzv/VvLl7/8SuvvTr/iSLJqqQs/qOPyovrULEPgI6HD8lL6yD58Sv/VvkA+aDsrgNlraf5k+nfTf/v6YfTX03fn/5m6D5MP7D//7vpP0z/H/vx4+Y7fzeYfmS/8XfTv53+2n75n+1n7k/8nX2qP7E/8JH/mU1emCSbovXZaGBZPLt6075p9t28NZj+zfSZffee2a+fNe/gV83vPbPv4dXPRrccQft79oV8Nv108Tv2u59On44GRWyf6v9XbOzXH1v6/22Q3BqUJhpMv5o+vnrz6i0v+/SFSbop9h9fvWXxP7H4njl8Vz+/Nbh6e+G2rLuxrujqPUtuMP3GMn48/byxzD/Zz5wretLw/nL69Oqvrn5qf/7x1VvuZ61VHk9/2/w596nzfI/tn/rt1Tv24+fuX7t613175hnfaD6+O5i5vU/tb33TGP7r+T9if3DxjWfWCT4bNCb/yn7zqf2JL+2/8Gjg/hLrMZ/Zv+jNgX3i/nb68SBJ/pXX3NkLk2xT5v5obsTH1mQ/nxvX2f3bazAz9rPG13/qTNb8yKff4mlfqI/sM2ZfNu8rtW9eGJtNsfxg+l+GFtsn1hH8Zvr/GdgP9v8+lEfmhYebQlkVUZzESZkXPmS1eWGyKWT2+X3WOIw37IPg/In96HuQzQu3i01BfN89ls5VfOFc5MC6+I+n/+BDece8cGdjKD+0b4t7rx43vuM55fWc5/GBvmteuLsx0O83q9+Atm/9I4vyyfR3jQ9sMfOL5oUXtxCxdV1vXL1nP/7UfstGFR/0XfPC7sag/930cxv/naP9auQD95J54aWNgbN2vfpPV38+ah7UN+fR02vDe+aFe5uEOX06dJFqMP1rv6P/1+aFf70xfL+xyuMv7cP5eKYcZlB9KPfMC3sbQ/lfGy9l9ad9Y96e/nbUKWT28xe+n28K7QfOdboQZd+dR1bMvOvi1Msvv+pkntutWgqfP+9yvQQ2ZuuPLf5/aJT8h353+v2NQRM/BvfzF+5vDK1v+8DEfZC/cPidfnwPNmf1rsf3cGPQZr7Wv625ZQ3MfTrG+QvjjZEQv4NH+QsPvtPP8tHGbN35LD/YGDTxY/Awf+HhxtCu4Yrr/IXj7/TjW2/O6l2P7/HGoPXliif5C5N1SPzktZ+c/PAGh5d/79WTH13M/lo9j+cOxPiP+4txEmUAQn/y4z95/dj93oH9K19/5eSHu//7n77yJz+yf5uH5uUKzf+pnhx876D0HuYdoAHXP3r96NXXuSgP/SgP0SiPXn/lzPfE3ADZ2GvnGs+qtgAB/claa1/7rVojwcrW/diP8BiJkL3mjZ12jqk1n4BA/m+vnJ9fvLreW/+/+O36v+Ahy9b/f/Xj/F/xONlPQWOznf+Vegpu314T61oB+f1GxDydPrn689lpaJPGf3adZXsyO6BqDlGnX9qPi+/bb/15UwPw1ewPXb3nZWfJmRfck242RfEXPlx3LKKNycsP5yb/6ezg/9FMSF69ab/1xrWs9Bv07iaBfz59NPjev/r9QZMA+tqlVn0QX9wgRB+ef+3wNM/gplBN/5p6BtcRsWsh+qXTp83D9vW3U7xPmi/enn5jP2u++eVzgnae+HZJtk+bpLFLsjydJcWv/op6XjdG0j2v3c/qpuBRz2rRPKubQjX9G+pZLTeFiHxWmyew2YE5Hzp/Xn87L1Gbl8JcvX31VwNXqNY8xS6O2Sd18L3Zsz4rgFv44ifP++JHXmFxd5N2sI/z9xb0OE54U0CpB7tsHuxNoZr+knqwq00h+riJ918OnNP9doWRk1iLJ9yVXbzlCm3ean7v8+ZgyptyvbtJMk052Yh6FjcFi3oWq+ZZ3BSq6d8Sz2IcbQrRL5/3kNPf2f++O/2dO96aPaJm4OI8UZqySdysGL8xeMTjF0fu8dsYql3q6dtYIe+vbm4nB65245umCvZxUyvx9SxEu6LN/6upsnRO0QZE+6DaCL54BgaLb/x+Uwj6bFa3aJ/jd+fS1TnVL6yAfXr186YyyImHr278S+Tua3M2ooi6xISrwel8CTaFnHoJ4uYl2BSq6X+m3oKN1X3/jX3CP7cP6vMZhKameHYg4HIJjxeFyl966pKtsLUP+tv2jz5X59Z48q+aN+fqxo0N+wP2t6hHfWOG+NQZ4jkzDBud7imbpB71TSGnHvWkedQ3hWr699Sjnm4KkX9P11QTftPI4fkFJXfE8Fnzc89c7fGng7kodoeRs7tJ0793X9hfX7RVdN7dJFmWd94UOuqRTZtHdlOopr+iHtlsU4hWjm0/dlcJqEdtYyCbI9omCLjq50eMY4KNYaUevKx58DaFavo+9eCZTSH6jdWw71699fyNIqsR3hxYJ/q+K/P4lf0PcaDVnBm4M7C/tN96Z3GJZyaerVMdPnezqvG3/2rmX5u/ouNW591NmuS5TYB7wAc3FIP77r/ySSSvrn9xg1yo16BJm20M1fTX1GuwsSTKc6/BjSd0oR1cgZbVu+5Rb54I95A/f0PN/YnFXu9pIyRmt2+SYTpodMbMf377pZjvtprHyJXsm8HyfuFj94S5f+35Xan7Nx2k5o37YkWd2N8kX6eNmXbldVoF3XyvsQ718mwKOfXyNPm+jaGafkC9PBvL6vw/jaiepequFfdzmb1H9nmeB4nmhmxzrbXxre4ZuPlnfTvTWWnA5/bdeM/repVn2puz2nN3c9wr0H5V58UNIqXegyaXuDFU0w+p92BjSaC/nZ34zYLIZ/Ns9xvXYWRxj3t2vkCejGwM/+fWB7tH0ar7uVf+jHoWN4WRehab9N/GUPn3au5Z3FgS6DezavJWYdImS5499+e/1wgR64ett7Z6//fnl3M/bx7k5gTQnRe/ffVOcwL4dFbePm8V8btBs6f4aeOT5w7evQsOUhLZnZh90Ox/zfy/+RwSKWM2ZtAG1vB693utW7q+aY07q9S2Jn08/WJere1l+OIGGbpVGL788qtuFeb/LYbU+9akODcGdfoR8b4lm8p6TT+2T/7v3LvGc/IbA2ofyzeb1A5xlvniBrERD1vSJDQ3horo82ARbSy79MtG2DaydtZYpcmnW4f8pJEezT7x6o3BC4PpfxlNfzWa/mb0XE+ZmcS++qtbM4H8dHRrcDH80ckrP6Qe1U3RpB6HJrW3MVTTj6nHYWMZGNeQ4Pkiate6qTmn+4vps56egU1xo56BJue1MVTTT6hnIN0UItdpqclhNo2p5m1fvhzMupDN98bXG+LZ40It9qZIUIvdZIukqP6w+bvOL45OfvK/2e9ZjPnpWXJ6ehINL7JLM8zK6HJYlsXl8CRLo5PUZPH5+cnsJ19/7d/NPqlm/1myu/jhxfKmy/P02Lf7YvsW/s18X/hscejhluqJ5/vD54qmV37cdZ/zFn7fLl/Y42+DuEb5j/YPunQd0xh/sv7NwOrWQRxXlf9+IIhgJicou1F0WN06JFkdglgZOSv2/SNHalzdGpOkxiBS/BdzzVuK1a2aJFdjyDmlKyEnewaPq1vHJKNjEKNYxkj0/E2qWxOS0ARAyDHKX/52oFgl+OOLs5+84omDNlD86Y9OL3yrdTNUxD5Gt/2b7jQtyrQqsmqV1ixE2zVgI3RR84/+pAmbnSBzH8Q7SoirL3WLEXnR1pXvrHbcXEbTJzPpa2XwrNuk99z9bvXCnpLNjXhJ0+khXsZREzBzf8DUUliNiAwKMm90aHEfkrgPtbiNHLfI54wt7DEJe6yFzX8B1oxqFn5Nwq+V8G/ErQ74sifl2GI+JjEfazHzHbciMlnIExLyRAPZYZ77FXDsIaIPca9gjtpEpKHZIEXhZ5T6UN7RouS/gNwI9BsbW5r+x+7A9daipcvTq/dsDPq6qbZ+vvLqVtM5u8kTPHVZmCfLRAynLdDdOHphT0s9cLiK/YFKjT5ApPJDPlRDNnLIIvczJhCP1Yj5r8e68cmPvNYiR4cmP9xjNVy+S9dEJT/aiQpt81y8HCYgUSHJnwpY4I5JK7NhCkOSH+cdLU7+W6cKSrNxBf9kg8rTWbnhN9NZO/bFvbjf+djcjWMba5SMAseahIg1WvQBYo0f8qEaspFDFjmVMYF4rEbMf+rXjTV+5LUWOTrW+OEeq+HyvbUm1vjRTlRoHdz5gxwg1lDRxp90XCBPSDuzgYqjzcj4kN7RIuW/ecp4Qyav7saJDSpK2IGDSnrrICmzWwdFUd06qIr4lt27lLOsVUbEGy2xAPEmvXXo2Bw6NoeOzWHD5pBkc6hmY+RsRD5nbMmMHZmxIzN2ZMYNmTFJZqwmw39X1o1S6a3akaodqdqRqhtSNUmq1pJCB7D01rFjcuyYHDsmxw2TY5LJsZoJPzpoYlt6a+KITByRiSMyaYhMSCITFZGwWyw68PkLMBbYU3IR2FAVgY/aaimx8l9nbuj7qDnte9eH8m6c2minRBo42mUusOX2gzFEcNPyCBDcMhfHcvuBAH+oBm/k4EU+Zmyxjx32MYV9rMbOf9bXDV2Zi1K5/UBwqLUc0JEqc0Eptx8I4Mdq4Hz/rQlMmYtBuf1A4J6ocIePQ1QkylrRZ6TV2WBVkYiKRUq0/PdTEos+d9dT5t1RvpxfC5q6Gaefzq85D5puze5K5c8WxYbu+19eveEuSDd1pT6ad+PMBjMl1cDBzNg4VtrtW2J/GbeNu3WQRvaX/Tqz/83s1xbrQW4/z23MK+z3C/s9t9ur7OdV6fZ6TUSMiGCotUOAYGhsHCztbi+xv4zb9d06tOQPLflDS/7Qkj+0AA8t+UNL/tCSP7TkD93m0JI/tOQPHflDivyhmryRkxf5RRtDbRwt7eYwsb+M2yTeGlvuY8t9bLmPLfexxTe23MeW+9hyH1vuY7eXtNzHlvvYcR9T3Mdq7vyXfd1gbGwcLu1eMrG/jNtT3qqtDWprg9raoLY2qC3O2tqgtjaorQ1qa4PabT2tDWprg9rZoKZsUGttgA7mxsbx0m49E/vLuC3orWNL/NgSP7bEjy3xYwvu2BI/tsSPLfFjS/zY7VQt8WNL/NgRP6aIH6uJ84OoRgwYqwNKu1NN7C/jdqy3Jpb3xPKeWN4Ty3tisU0s74nlPbG8J5b3xG1sLe+J5T1xvCcU74mKtyM+9/qO/g/aRMW/e+31P/YYQ6coKE1hWknk5OLxsCoFBZ1LVMJdDbSUaZmK4h+X1ZS/W1RRLrsEufZr1wnFmcRwjYWeTT9rylm+XqqQZ4vpuZ82F4ffef6e8JNFX6Evm6vLv1v8+OdNT4hvrFhx1+C+nn3z6fxmi/ti1l5iVmzzl6Om2dsgbibTf0UIGKVJV2M2+QT8yDnqP3rlx5xHdvo306/ng5ub7uNvTpdToGbdFt8azNo624+uQsg3Sd5NkHquO41L6b4zXXRofH4cxDM3cuOp+3s/nd/y/tp1Nh/5zPSi1kxGZCaGiZLB1X9qLr39kw/nrhZnzsP5o4uTH//p66yX5KvEB/AlLcCCB/Di3//Jxas/9gF8dQVgPIqiyAfxnhZiyYP4f7z2wz9l+RkfuH+tBbcqtQhwTahlWM9ruT0tuHhVBBHonAJudABHCd5Y8KIYpbkP974aNzNmL3GT6m0VbFqWI//j+X01WGbQXoL1wLwhtqzpdh6OJ4cvfs/iujXw573vqyEzA7doe3zjUSYMfaBGzYyN3ZtZLtRDNVQjhMp+MKz1dhawbuwXtWiZUepP+ncRR2rMzMD1Jz25hwdqoMzw9SfcJ+Bo6Roe0K7hoRquJKBpngXqXau1iG/s9NsQs58ECuaxGiYzpgk35fZhOPa7g4kKqYN6fpmdl0V8MixjczHMojwflmdn8fAiTavL9DI9qy4vZmTITfaP5k+Gh6B2o01ttXMZSy4933a8hZVkS+7jcQfJYzXct60Oc6/+4fW2/HrH/fSPZhvl6T82O8Y/b5qGPL83nLeWaRp+Nd2Ah9OPp59Mf9E0sfrF9B/8rTDuIm1j+Lbh7yZ9LHaRLFYjeAsLwV7zS3/LvpeQTFbjegsTyabUqz7uIYmsxv0WImtuXYEkVtVAC4k1t7hAEje2wS0s1toKV6O88LHbh7ITeHfRhu6G2JipztlHS8lpzz/Ym/3Xx/oAylrg8dT7Fmo9j6DMpO8ch1nrWh51r2UNY9woztPTs4uTy7Qamiw7G2ZFeTk8ySMzzOLT8jw+PTlPzfwdDqo4vUett4kmxS2m4NELrjiBPAQ+ias4f7mS53nkJkJ83UjQWYPYb3Uv/LWVk05a/mr6gf314bUw/XD6/vQ39uMn7mf+u/3i48H9IxMP/NO37yKNZPhGWld6AlkIHHEf0hPIBCI9o1FijI/KPSSVcOITSEIaCDmr4SOxhyQRTHyW5aj00tuH0hN4+j7VZzFXLAWtPpGsBU5PrT7JBT2CUpO+dRxqHfKzczFrGGOnP9tkZb/VQoSg9LeVm5Er83KV3KarhZRwmUlHrh78blYL+Sx6V2vRjGfRfzbFQkozGZGZGCZKO4qFlDiZaViBiqaKhZQAmTlXvjhuKRZSQmRmW9cUvUpwktwqw3qEmFWCC1QslIyqyod7X42bGbLlxUJZRGWBv68Gy4zZwmKhclksVNLFQlrIzLgtUvfcdPuBGjUzNvZZLKSFaoRQ2Q+Gtd7OAtYK2rEaLTNKqbc9tIs4UmNmBi5ZsRDtHh6ogTLDl6BYqFwWC5Gu4aEariSgaZ4FulhIiTh0sZAWJjOmSYuFyp1jvzuYqJBubeomoYqFKhlLLr3gqRsgD8GBHnervqHUDdBIhm8k/rbSx2IXyUJwiinYdJKpGyCT0KkbIJVwqRsgCekhMmc1fCT2kCS2IXWDpCfw9KLNXUfqppqf9ld06gbJWuD01HuYltQNkpr0reNQ60jddC5mDWPcyM8sviyi4rQaFvFFYX8iiodlfpkMi5PLpDrPzaXZQK16QiR6iKmjLabg0QstP5E8BE6JKz9/vRhROHCNZ6bPmnTGT12u6Oq9m9kc+80/coqz/IM4ihbTy5OISN0gTWH4plhTZCJZCPytQGS6dNNno4F/VV5C8oFITe929R6SRjCZiSQhDXiMlfDLTCSJYDIzjkaZX2ZC6Qk8eo8yM4lmymT2Xx/rAyhrgdtTy0xyQY+g1KRvHYdau8zsXswaxnh7r0Qm/nlVt4lp5i2m4NELLjOBPAROiSszg16JRNrG8G2zru4EshA4YIHupA43kUwwipO4EokkEk5zAklIox9jLQjNCSQRTHNWo8h/JRLKTuDd+5Sc8VylxLTkRLIWeDy15KTW8wjKTPrOcZh1KM7OtaxhjMPWpBMaMmklxx4MHqgmXQuXWdvGlYD/jGrStRbNeBb951KTrjWTEZmJYaKOBpZanMxqP4GCJmrStQCZpX0SYUzVpGshMov61pS8SnCSEj6G9bIkT/3Zrz0twkCF6dHIZD7c+2rczLjda2G6GiwzcMsK05NkUZieJGRhuhoyM3iLFP6qqYukiLJ8FHtV0oEaOjNKyqvT7XNskpKsUVcDNkLA7GfE2nBnAWsF7ViNlhm11LugloaWaszMQCasUc/NKPc+Cg/UQJnhjF+jvvQSD2gv8VANVxLgNM9CYfI4sXsT44Nda2FjCtXjqsyqzIwq7/t2rAbLjHTCcnX7XBz7PcNEhXRrEznErvZ2kspYcukFT+QAeQiO+ri7+LCJHKBtDN82/I2mj8UukoXgWFOwDSUTOUAmYRM5QCLhEjlAEtJDZcZa5GUSE10+9pBUAqZz/AF5H8pO4ONFm72OdE46TwGkdDoHyVrg99QbGbLDJZSZ9M3jMOtI53SuZQ1jvL3XJImTuttJJjUFj15w3QnkIfBJXN25mWuSSCMZvpHWFaBAFgJH3IcABTKBCFD6miSSSjgJCiQhDYSM1YijshjFsXdPsIfkEk6D2gfO28RgH0pP4PD7FKHZXLhktAhFshb4PrUIpW9LQqlJXz4OtQ4V2rmYNYxx2KKizEfudmLayBXRKrlNFxUp4a56in8pKlpqTaVFM55F/9kUFSnNZERmYpioo9GlFiczPSsQ01RRkRIgMxfL18gtRUVKiMws7JraVwlOknNlWC8tsog6VVUi3HhRkRY3M273W1SkBcsM3MKiouVo3IQejauGzAzeIol/I01gUZh0VHhlx4EaOjNKKoqKsiqPWoqKtICNEDD7GbE23FnAWkE7VqNlRi31NqitqEiLmRnIhEVF5KPwQA2UGc4ERUXLKbm0l3iohisJcJpnIc/TNI9HpTc5U2thg4qKisokVU71wFSDZUY6aVGR2Tn2e4aJCunWJncyqqgol7Hk0gue3AHyEJz1cXfxG0ruAI1k+Ebi7zh9LHaRLAQHnIL9KJncATIJndwBUgmX3AGSkJ4vM1ajcrsG4/Xre0gq25DbQdIT+HvRxq8jtzMfu5rQI3ShrAWuT72pacntIKlJ3z0OtY7cTudi1jDG21vZnlEVRm3z3Lym4NELLkKBPAROiStCw1a2A21j+LZZV3sCWQgccB/aE8gEoj3JynYgkXDKE0hCGv0Ya2GqMiMvdgOphFOeZGU7kp3Ax/cpPOcDVxN6ei6UtcDvqYUnXdmOZCZ98zjMOnRn51rWMMb2f3/4nPd3cvIHbfqy3xoj4yN7O2kbZFSYG12ZAtUYFVSNkRIuM03JFYZ/b4XeV1bwfd0Utzy5+mkjEmeFLI9ndS1vugKXpkzo6h37U//UVAfNS2Bcycyzq/eauqFPB65a6ert6W8HPsZ3tYwzHmNZDZAP4YtahEaEkIGua1muV+NzV7zlSoy+nv7TyJUtPbYr8tip9k+dcHflW49d8/urd11x09V7V+8MkuF1dc+twfXnw3mT/E+nT6/e89Yn7WoNxMygCrTuV6kP4EtagMx0qUTCknU/SojMROma4lQJTpIWZVjPa7k9LbgwJT+JqQoiFbqvRs4MpPKiH5NZXU+W/WjhMmOpsOxnOeQ2oYfcqiEz46lIhN/MpRBDbtWomTFRXvFD1/pooRohVPaDYa23s4C1gnasRsuMVOrdSZubOFKjZoYvWbVPm4t4oIbKDGOCep/loFvaPTxUw5UENs3zQA661SLGlPqQg27VMJmRTVrkU+4c+13CRIXUQb24SMzF5UU1PDVxMYzji3JYRhdmGEUmMnlZxpWZxz1y/9tyGqDdA1NFPpWMJZeeb6fcwkqyW/bxuIPkITh7426jP57vlH8+uPqL5u7M7KqM3b4Nm13Ym3YH53ZvzeCxDxL/y3QXSdrwSfP3qT4Wu0gWggNEwWaSTJwAmWASJwW16QQyCZc5AZKQnt8yFoPYxAJJBMuZFKPMG372oewEflu0XevImcwnnSb02Fooa4HLU+9KqPU8gjKTvnMcZh05k861rGGMw97D9ibQb6dRC7myiFfJbThHooXLPNPhiruAORIt44zHuIcciRahESFkoOtalk3lSLQGYp48CWQtkSPRAmQeMgnUKpkj0UJkHi6tJ0O14CRHSQzrJaPSe9Cxp8UXKE1SxiWVJlEjZ8bSntMkarjMcCpLk6TRIk2SksNS76shM0OqSHevGjvNq9iMysyH/ECNnBka5amS2JSpSYmW6odqvEaIl/2EWBPuLGCtoB2r0TKjlnpn0povUaNmhjJZviQ3VRkRlx4eqKEyQxo/X7L0Ew9oP/FQDVcS5DTPQ5onRUXclq+1qDE5k7iKoiQbFd4H4liNlRnrhIkT+1Qc+33DRIV0axMnOZE4SVuHOt5kyaUXOnGC5CE4gOPurftJnCBJGz5p/ubVx2IXyUJwiijYYVKJEySTsIkTJJNgiRMkCekhLmMxsrLyxvc9JI+AuROiMxiUncB1i/Zw7bmTdD5MOaUHY0NZC7yeeodC5k6gzKSvHYdZe+6key1rGOPFfZPFQY97mgNeOPHeJ7qdJi1si/zG7ZpAyZSYmOx9R4uXefTDVXy+rrbNt96b/pMVFE8GVhO+P/3r+dXkR/Ynv/r2peRGC85P8ef9al0P1ixu2s/OetHmEdmKVmuGjGeGPlIsSoRGhJCB7nq09MiuynKJHs2vj1+9bdftbdf31olzYqVuLdsENwkYt1xm1ih49PLLr04/sd/95oXB9KO4vGU/DuPSvz/b1RqFeUAlEL1Ey1ktQOZZlEDL0mkVJUTmGdSaIlUJTnLixLCe13J7WnBBcipUce6+GjUznMrzKVUWk9kULVhmPBVmU5YDrFN6gLUaMjOkipQ496k4UKNmRkB5JoW8dKKGaoRQ2Q+Gtd7OAtYK2rEaLTNGqbcoWZKOUv+leDVmZtiSpVBKY6gLJ2qgzOAlSKAsp1bTruGhGq4knGmeBfLCiRYxJnlCXjhRw2TGNGneJNk59ruDiQppI7eq8ySPsmRoMteE4TI5G1ZFFA3jKKlOqksTJWZOhtz/thwHaPfAVN4klbHk0vPtlFtYSXbLPh53kDwEh2/cXfR/sfumL13z2Ka48I3F9st+aXdkb1y9O5j+vWswO/3CbYevfup2bX/kdtQ2MtqP2dA/J+wu0gqGbwX+FtXHYhfJQnCkyN9TXv3s6i0fk5eQTCCJFG9J2j0kjXBZFCAJ6XEuYyWIjSyQRLAUSjIyxIYXyU7gxUUbt44UynyAcUoPo4ayFvg79f6EWs8jKDPpO8dh1pFC6VzLGsZ4Nq/gPE2iy5NieHqRZcMsTePhiSkvhpUp4/T0tLpIyrnmCqosvfr5dppJTcGjF1xZAnkIfJJEWf52foo/myz4pTu3b9RjMYwTOrEC5Gn4PNfVjkAWAl/K1450EQ6QCUQ7uj2/d5N5D0klnH4EkpDGMs5q+EjsIUmE049ROZoH2hsKEslP4K37VJDz4cMpPUkaylrg9fQKklzRIyg36XvH4dahITtXs4YxnmnIyzK5OLU/dpqdJcMsrs6Gpyfp5TBKYlMmRWxOzdwqQTWkd/Fvp0ZsCha94BoSyEPglbga8uN5cc6jwdV/mj51yvHqzemnswPIKPoD98v4eN5F8jR8nutqSCALgTcVaEiqpgVIBCIhY3+W4h6SSDgBCSQhDWSMtSAEJJBEMAEZuzy190nbh/ITuOo+BaSZSw5ynuoBlLXA5akFJL2iR1Bu0veOw61DQHauZg1j3AjI7CSqqjyKh9XJuRnan4+G5UV+Ory4TM9NchLH+en5y+EFZOYzxe35TVOBKXj0ggtIIA+BV+IKyI9cUttKyKdNIfHnz98NbFTk9ANDXQUEEjV8ousqSCALgTsVKEjyFBLIBCIho5G/nucekkk4DQkkIY1lnMXwkdhDkgimIQsyiY1kJ/DVfSrI+YzMlB54CmUtcHlqBUmt5xGUmfSd4zDr0I+da1nDGDf6MTfm5DQ+y53WtD+bnV8Oy7g4GZo4Tc6z6jwuyrk7Daofjc8Ut9O2EVxeU/DoBdePQB4Cn8TXj4+v3nSp6/mIU9fi7+qn8/tns5uFX7l2f27AqY/vXSRfw+e7rowEshD4VIGMpHoWAomAVCSZywZSCScjgSSkIY2zGj4Se0gSwWRknEf0/T8kQYHX7lNJzqdepvQEUyhrgddTK8mWJT2CkpO+eRxyHWKyczlrGOPZYWR8WUTFaTUs4otimMVWgpb5ZTIsTi6T6jw3l8YNPA0uJnOfKW6npdQUPHrBxSSQh8AtccXkr+dNyR4N5t2fv2qu1Mybkn3eHE1+c/XnTSPp5pvNEWXp0txNsaT9IomookmgKQzfFOvqTCALgccV6EzXwOKz0cC/Ki8h+UDkJiE1gTTCSU0gCWnAY6wEITWBJMJJzWiUEUITSU/g0fsUmuVcmZBDBQ+grAVuTy80qQU9glKTvnUcah0ys3MxaxjjWdHk6dnFyWVaDU2WnQ2zorwcnuSRFafxaXken56cp2b+FgeVmURjs0pqCh694DITyEPglLgy85fNYJivm3ZZn86KJ99uhpl86pSlu+s9fXr1c/sD77qWZ7+e/mL68fST6a+mH9hfH87POaf/OP1w+v70N/bjJ+5n/rv94uPB/SMTD6a/8BnpLtJIhm+kdQUokIXAEwsEKJkvBzKBSM/If33vHpJIOPEJJCENg5y18JHYQ5IIJj7LkhitsA+lJ/DzfYrP+Zy6lJ45CGUtcHlq8Uku6BGUmvSt41DrEJ+di1nDGIcdOlj6yN2ebzH85MoiWSW36T65WryrruI73idXa4aMZ4Ye+uRqERoRQgY6UJ/cfNYn18d9V8t91bPD2uFqATL7CvL1Kd0OVwtxVX1C2uFqwa3GN0g7XC24zbbDVaNmRs1e2+GqwTLDpqwdbrYcLpjRwwXVkJmRUySwuU/FgRo1M9D12A5XDdUIobIfDGu9nQWsFbRjNVpmjFLvPLLcUM0C1JiZYau3drhqoMzgxW+Hu3QND2jX8FANVxLONM8C2Q5XizhwO1w1TGZME7bDtQ/Dsd8dTFRItzZ3QoypuD2fBcRmyaUXOneC5CE4U+NuljeTO0EayfCNxN+o+ljsIlkIDhIFW04qd4JkEjR3giQSLHeCJCE9xeWshY/EHpLEFuROoPQEfl60tWvPnWTzOXUZPXMQylrg8tQ7GDp3AqUmfes41NpzJ92LWcMYb299eEl0zM0SqSl49IKLTyAPgVPiik9kfTjSFIZvinUlJpCFwN8KJGZ7fTiSD0Ro+uvDkTTCyUwgCWnAY6wEITOBJILJTLo+HEpP4NH7lJnJXJmQM8AOoKwFbk8tM+n6cCg16VvHodYhMzsXs4Yx3t6eFiXRVDdLpabg0QsuM4E8BE6JKzPX7mmB5Gv4fNfVkkAWAqcq0JJETwskEYiIpHtaIKmEE5JAEtKQxlkNH4k9JIlwQrKlpwWUoMBr9ykl52OhMnrEF5S1wOvppWRLTwsoOembxyHXISY7l7OGMd7eBrsl0WA3y6Sm4NELLiaBPARuiS8mtQ12kUQNn+i6KhLIQuBPBSqSTHoDmYBkJNFgF8kknIoEkpDGMs5i+EjsIUkEU5Fkg10oO4Gv7lNCzqdCZfSMLyhrgctTS0iywS6UmfSd4zDr0I+da1nDGG/vhK+SaLCbGakpePSC60cgD4FP4upH9YQvJE/D57mufASyEPhSgXykrukBiUDUY0xM+EISCScegSSkgYyxFoR4BJIIJh5bJnxB+QlcdZ/ycT4TKqMnfEFZC1yeWj62TPiCcpO+dxxuHQKyczVrGOOZgGSNkw0uIHOfKW5nudgULHrBBSSQh8ArcQXkf5k+mf523gTh2fSpy2u7VHajIIthnNB9KYA8DZ/nugISyELgTQUCkjx/BDKBKMiWNDaQSjgNCSQhjWWc1fCR2EOSCKYh6aH0+1B+Am/dp4acz4XK6BlfUNYCr6fWkPSKHkG5Sd87DrcODdm5mjWMcaMhy+o8yaMsGZrMXAyzy+RsWBVRNIyjpDqpLk2UmLlmDKoh/R1zs7YZFV5T8OgF15BAHgKvJNGQX7rL3e7e99Ubi95a9surt6/euHp3MP17dwF8+oXrdXb1U3dcOTuhNO5jNoy9O4K7SCsYvhXWVZhAFgJfy1eYVz+7esvH5CUkE4jC9PZBvIekEU5dAklIoxxjJQh1CSQRTl2S6W0kO4EX71NbzsdEZfTULyhrgb/Ta0syvY1kJn3nOMw6lGXnWtYwxmHb4VY+crezspVcukpu4+1wlXhXPcV3ox0u2XH1rtYOGc8OffTDVSI0IoQMdCnVD5dqcWt/7BP7vW9eGEw/GrrGijfZ7WrZrfpuXMdbJUBm60C+/GzpeKuEuCovMR1vleBWQxim460SXJCOt2VRjgoiWa3FzQyN/fa81YJlxkZhz9ty2fOWHBt1Xw2ZGR5FItqX6fChPlCjZgazPnveaqEaIVT2g2Gtt7OAtYJ2rEbLjFLq3QXtIo7UmJmBS9bzlnYPD9RAmeFL0PO2XPa8JV3DQzVcSUDTPAt0z1sl4tA9b7UwmTFN2vO23Dn2u4OJCunWZj8qqudtJWPJpRc8+wHkITg34+6IUdkPoBUM3wr83aaPxS6SheA0kL+rpLMfQCYhsx9AGuGyH0AS0pNYxkoQW1kgiS3IfiDZCby4aOPWkf2YD5DL6GmAUNYCf6fen9DZDyQz6TvHYdaR/ehcyxrGuFGWJ3Gc5SarhnncNJIoi+GpOSuGl6fFeXQelybP51YJqiy9R6q358+EwBQ8eqGVJZKHwCdxleXHrhXE1ZtXPx883xfCHdkPp980v/PTJqcyy6gsRtvN+0bE/hf5LtIGhm+DNXUlkoXAz/J1JVm3jWQC0ZXEfNF7SCLBlCWShDTKMdbCryyRJIIpy3wUe4s896HsBF68R2VpopkaMeTkrgMoa4HHUytLaj2PoMyk7xyHWbuy7F7LGsZ4e9tGVEQPWxNLTcGjF1xZAnkIfBJfWSrbRiB5Gj7PddUjkIXAlwrUI1HrgiQCEo/e3MU9JJFw4hFIQhrIGGtBiEcgiWDisaVtBJSfwFX3KR/n05kMPWoLylrg8tTysaVtBJSb9L3jcOsQkJ2rWcMYb++srYroW2sSqSl49IILSCAPgVfiCkjkrC2kKQzfFOtqTCALgcMVaMz2WVtIPhip6aNxD0kjnNAEkpAGPMZKEEITSCKc0CRnbUHpCTx6nzpzPp7J0LO2oKwFbk+vM8lZW1Bq0reOQ61DZnYuZg1jPDunZI1/DS4zjc8Ut00qNQWPXnCZCeQhcEpcmfnLqzeu3m6Eprs/2JxX2i+nT1xBpf2tN6ePpk+vfm5/4F13j/DX019MP55+Mv3V9AP768P5fK7pP04/nL4//Y39+In7mf9uv/h4cN/uswbTX/iMdBdpJMM30roCFMhC4IkFApRMkQOZQKRn5K+juYckEk58AklIwyBnLXwk9pAkgolPcvz8PpSewM/3KT7n45wMPZ0Lylrg8tTik1zQIyg16VvHodYhPjsXs4YxDtt8Ivau522TtbLLVtltuvuEFu+qr/iud5/Q2iHj2aGH7hNahEaEkIEuUXSfILtOaFkx7/MKRCqViVcCZF7e5WtPuuuEFiLz2u6aqlIJbjV2QbpOaMEF6jpRjVwIv4l7X42bGRN77TqhBsuMibKuEyZbdJ0w5Pyn+2rIzLAoks/ce9sHatSZEDX7qSC7TqihGiFU9oNhrbezgLWCdqxGy4xS+n0F6SKO1JiZgau3rhNqoMzwxe86sXQND2jX8FANVxLQNM8C2XVCizhw1wk1TGZME3adsA/Dsd8dTFRItzYzEkdE2wljZDS5/IKnRoA8BEdm3K3whlIjQCMZvpH4u1Afi10kC8E5oWDXSaZGgEzCpkaARMKlRoAkpIe0nLXwkdhDktiG1AiSnsDPi/Z2HamR+aA5Q48NhLIWuDz9FoZOjSCpSd86DrWO1EjnYtYwxttb/h0TceO2yaW24PELrj6BPAReias+ofXfQFMYvinW1ZhAFgKHK9CYHfXfQD4QpUnUfwNphNOZQBLSiMdYCUJnAkkE05kt9d9IegKP3qfOnA+jM/RoQShrgdtT68yW+m8kNelbx6HWoTM7F7OGMd7ePhV2+b0FMLdN+ywcn+Zm8QuuM4E8BF6JqzP1jSqAPA2f57oiEshC4E0FIpIqjwESwahHqlEFkEg4/QgkIY1kjLUg9COQRDj92NKoAslP4Kr7FJDzmXOGnh8IZS1weXoB2dKoAslN+t5xuHUoyM7VrGGMt7eHrttA+Gxx27QPofDYgscvuIIE8hC4Jb6CRDTRBdrA8G2wrroEshC4WoG6JNPgQCYgeUk00QUSCScvgSSkYY6xFoS8BJIIJi/pJrpIdgIv3qe4LOdyhBwFdgBlLfB4anFJN9FFMpO+cxxmHdKycy1rGOPtHfxlpaXx2eK2k8QyW/D4BZeWQB4Cp8SVlqDJX0grGL4V1hWXQBYCV8sXl+TkLyQTiLgkpCWQRjhpCSQhDXOMlSCkJZBEMGlJTv6CshN48T6l5XxalKEnf0FZC/ydWlqSk7+gzKTvHIdZh7TsXMsaxjhw6wn/fZ08amVnVtltuvWEFu+qq/iut57Q2iHj2aGH1hNahEaEkIGO33rCLFtPfGK/980Lg+lHsd1zukYUpT8DvKtluerEYa0otACZN3r5OpRuRaGFyLzLu57G1IJbjWWQVhRacEFaURR5OUqMD/e+GjczRvbaikINlhkjZa0o8mjRiiInZ0rdV0NmhkmRmuZe5j5Qo2YGtR5bUaihGiFU9oNhrbezgLWCdqxGy4xS6m0G7SKO1JiZgau3VhRqoMzwxW9FsXQND2jX8FANVxLQNM8C2YpCizhwKwo1TGZME7aisA/Dsd8dTFRItzcPQhRn3s5jGU0uv9B5ECQPwQkad2sMyoMgrWD4VuBvO30sdpEsBOeC/G0lmQdBMgmYB0HSCJYHQZKQnskyVoLYywJJbD4PAmUn8OKinVt7HiSfj6bL6UGDUNYCf6feoJB5ECgz6TvHYdaeB+leyxrGeIurt2Oiz0SeSG3B4xdcWgJ5CJwSV1pCqreRNjB8G6wrLIEsBI6WLyzJ6m0kE4iwpKq3kUTCSUsgCWmYY6wFIS2BJIJJS7J6G8pO4MX7lJbzcXQ5PVsQylrg8dTSkqzehjKTvnMcZh3SsnMtaxjjLW4tQRS43M5TqS14/IJLSyAPgVPiS0tlawkkT8Pnua58BLIQOFOBfKTKXYBEQOrRm724hyQSTj0CSUgjGWMtCPUIJBFMPba0loDyE7jqPvXjfKJcTo8HhLIWuDy1fmxpLQHlJn3vONw6FGTnatYwxlvcBDcmWkvkmdQWPH7BFSSQh8AtcRUksgku0hSGb4p1RSaQhcDjCkRmexNcJB+M1vTRuIekEU5pAklIIx5jJQilCSQRTmmSTXCh9AQevU+hmc2lCTn76wDKWuD29EKTbIILpSZ96zjUOnRm52LWMMZbPOorJvpM5EZqCx6/4DoTyEPglbg6czOjvpBGMnwjratAgSwErligQMksOZAJRHtSo76QRMKpTyAJaRzkrIWPxB6SRDD1SY/6gtIT+Pk+1ed8OlROj/qCsha4PLX6pEd9QalJ3zoOtQ712bmYNYxx4FYU3khwO89b2eWr7DbeikKJd9VXfOdbUSjtkPHs0EcrCiVCI0LIQJeyW1HkN1tRDN0955vsdrXsmJd7BWKVyskrATJv8vI1aEsLCiVE5h3eNdWlEtxqDFuzBUWSVqPKB3BPCzBIG4qySkeR983ZV+Nmxsd+21BowTLjo7ANRb5sQ0GOjLqvhswMkSIpfeNxjrMki0ap19oHaujMqCbvRZEkpsjMqPLiPVTjNUK87EfEmnBnAWsF7ViNlhmz9LuNohwVRFGFFjMzjMkaUsRxUo0S77PwQI2UGc0EHSnyZUcK0ks8VMOVxDfNw5DEURklI+OV/7UWNqYtRVJEZWVGkfcqyrEaKzPQSXtT5DvHfs8wUSHd3txJQvWmaB+Fc4Mml1/w3AmQh+BMjbtX3lDuBGgkwzcSf5vqY7GLZCE4SBRsR8ncCZBJ2NwJkEi43AmQhPQUl7EWWTGqvEF2D0kkWP6kss+al94+lJ7A14s2fa1H7pbS/MidnkAIZS1we/odDZ0/QVKTvnkcaq2LedS9mDWM8RZXiSdUC4v2iTkeW/D4BVegQB4Cr8RVoNAqcaApDN8U6+pMIAuBwxXozI4qcSAfiNokqsSBNMJpTSAJacRjrESV+VjsIVkEE5pufBkhNJH0BC69T6E5n2CX09MIoawFfk8tNFvKxJHUpK8dh1qH0OxczBrGeIsbWiRUQ4tKagsev+BCE8hD4JW4QlPf0ALI0/B5rqsigSwE3lSgIqniGSARjHykGloAiYQTkEAS0kjGWIskT0clUbMDZBJORJpi5G9yvw/lJ/DXfarI+bC6nB48CGUt8Ht6FdnS1QLJTfrycbh1yMjO1axhjLe45W5CdLUoIqktePxCy0gkD4Fb4stIQMtdpA0M3wZrSkwkC4GrFUhMKiGOZALSmN6jo3tIIsE0JpKENMwx1iIxVVT5k0x7SCrBRGY+SvyNd6HsBL68R4lZRDNRUpADxA6grAV+Ty0xyca7UGbSN4/DrF1gdq9lDWO8xePCEqKdRdE+38JjCx6/4AITyEPglLgCEzQuDGkFw7fCuhITyELgavkSkxwXhmQCkZiEwATSCCcwgSSkYY6xEnEVk/oSyCSYvrQBKfOx24eyE7jyPvXlfM5UQc8Mg7IWOD21viRnhkGZSV88DrMOfdm5ljWMceCGFf7MdpG0sitW2W26YYUW76qr+K43rNDaIePZoYeGFVqERoSQgS5RNKwgG1VoWTEv/fJVKpVr1wJk3vDli0+6UYUWIvNq75rCUgluNXat2agiTwkPuKcFGKxRBaUEtbiZcbHXRhVqsMy4KGtUUSSLRhUFOYDqvhoyMzSKFPSqqU2eRVVM3OI5UENnRjN5owpTZZFJicYah2q8RoiX/YhYE+4sYK2gHavRMmOWepNRFtUornyYj9SYmWGsv0YVaqTMaMZvVLH0Eg9oL/FQDVcS3zQPgzEmSpPRvD3gjU2YEjamUUURJ2Wejirvse2xGisz0AkbVdjH4tjvGSYqpNubFUmJRhVFKqPJ5Rc8KwLkIThK4+6RUVkRoBUM3wr8/aePxS6SheCAkL/fpLMiQCYhsyJAGuGyIkAS0sNZxkqYyET+Usk9JJMtyIog2QlcuWhP15EVmQ+4K+hxhVDWAqen3rDQWREkM+mLx2HWkRXpXMsaxniLy7pTog1FkUltweMXXF8CeQicEldfYsq6gTYwfBusqy6BLASOlq8u6bJuIBOIuiTLuoFEwulLIAlpmGOsRV7GJSkwgVSCCUy6rBvJTuDL+xSY88l2BT2mEMpa4PfUApMu60Yyk755HGYdArNzLWsY4y1uP5ES7ScKI7UFj19wgQnkIXBKfIGpbD+B5Gn4PNcVkUAWAmcqEJFUSQyQCEhDehMZ95BEwmlIIAlpJGOsRV5lo8zrlveQTIJJyJb2E1B+An/dp4icD6gr6GmDUNYCv6cWkS3tJ6DcpC8fh1uHjOxczRrGeIvb5aZU+4lcagsev+AyEshD4Ja4MhLZLhdpCsM3xbpKE8hC4HEFSrO9XS6SD0Zw+mjcQ9IIJzeBJKQRj7ESSeE9ANpD0ginNcl+uVB6Ap/ep9TM5+KEnBp2AGUtcHx6qUn2y4VSk753HGodSrNzMWsY4y0eDZZSfSjah1T4VDeLX3ClCeQh8EpcpbmZ0WBIIxm+kdbVoEAWAlcs0KBkyhzIBKI+qdFgSCLh9CeQhDQOMtYiTvJR4i283kMyCSZB6dlgUHoCZ9+nBJ2Pkyro2WBQ1gK/p5ag9GwwKDXpq8eh1iFBOxezhjEO3Koi87G7XbQPpChX2W28VYUS76qv+M63qlDaIePZoY9WFUqERoSQgY7fqsIsW1V8Yr/3zQuD6UdxeatpXFH6s8e7WparXhzXukIJkHnnly9IW1pXKCEyL/uuKTWV4FZj2ZqtK9LMfyqwp8UXpHNFUUaEkNhX42aGyX47V2jBMsOksHNFuexcQU6auq+GzIyUIkV940A+r1KqQuJAjZwZ2+SNK9IkyzPimtKhGq4RwmU/INaCOwtYK2jHarTMgKXechR5OUqMD/ORGjMzhvXYt0KLlBnKBH0rymXfCtJHPFTDlQQ3zcOQ5CbKRrl3C1BrUWPaVqRlZQoiYXOshsoMctKuFeXOsd8vTFRItzeHklFdKyoZTS6/4DkUIA/BsRp3u7yhHArQSIZvJP5O1cdiF8lCcJYo2ImSORQgk7A5FCCRcDkUIAnpQS5jLfJR5aOxh6SxDQkUJD2Bpxdt9zoSKPP5dgU9rRDKWuD01LuZlgQKkpr0veNQ60igdC5mDWO8xdXiGdHVYv5QCGzB4xdafyJ5CLwSV38iq8WRpjB8U6ypMpEsBA5XoDLbq8WRfCBa018tjqQRTGkiSUgjHmclzMj4O+juIZkEE5t0wTiUnsCt9yg2y/msu5KeWwhlLfB9arFJF4xDqUlfPQ61drHZvZg1jPEWd7jIiA4XZSy1BY9fcLEJ5CHwSlyxqe5wgeRp+DzXVZJAFgJvKlCSROUMkghGQhIdLpBEwolIIAlpJGOsRVqMKu9bvockEk5D0g0uoPwE7rpPETkfaFfSwwmhrAVuTy8i6QYXUG7Sd4/DrUNFdq5mDWO8xY14M6LBRZlIbcHjF1xFAnkI3BJfRQIa8SJtYPg2WFdhAlkIXK1AYVIZcSQTkMT0nhzdQxIJJzGBJKRhjrEWaRwZH489JI9gCpPswgtlJ3DkferLZK5IyBFjB1DWAqen1pdkF14oM+lrx2HWoS4717KGMd7iMWLE9ZXbZSq1BY9fcHUJ5CFwSlx1CRojhrSC4VthXX0JZCFwtXx9SY4RQzKB6EtCXQJphFOXQBLSMMdYiaTwN6xA0ggmLskZYlB2Aj/ep7icz50q6RliUNYCj6cWl+QMMSgz6VvHYdYhLjvXsoYxtv/7w1uzBgI/aBOPPbetMD6Wt8ushWWRx6ssw7Wt8PqVO1q8qy5jS9tW5PF114oyIptWaK2Q8azQQ9MKLUIjQshARzataOoen1qVvjzzJRfq1s0OF7khW4rsarkzbwbz5SyZkFcCZF4D5qtUupWFFiLz/u+aClQJbjXOrdnKwmu5PS24IH0sIqIxxL4aNTNqyrtYxFGcUW0s1GiZYVPWxqLMFm0sSnJi1X01ZGbkFAlt7mNxoEadCVGzHwsK6qEaqhFCZT8Y1no7C1graMdqtMwgpd6BZKXVgd7TiyM1ZmbckrWvqJKEeBQeqIEyoxe/e8XSNTygXcNDNVxJPNM8C9S7VmsRYzpXUDCP1TCZQU3YtcI+DMd+dzBRIW30FmvP68iQ+9yW3b56r0t0rSiNjCaXn29H3EJLsiv28biD5CE4XOPullFJEqAVDN8K/L2oj8UukoXgyJC/q6STJEAmIZMkQBrhkiRAEtLjWsZKEFtZIImQKRJiy4tkJ/Diop1bR4pkPvKupAcYQlkL/J16g0KnSJDMpO8ch1lHiqRzLWsY49kdwfM0iS5PiuHpRZYNszSNhyemvBhWpozT09PqIinnmiustPSeqd4uc6ktePyCS0sgD4FTkkjL387P659Nn9pfX7oT+kY+FsM4oVMoQJ6Gz3Nd8QhkIXCmfPFIV3ADmUDEo9v1e3eZ95BUwglIIAlpMOOsho/EHpJEOAEZlaM09fHbh/ITeOs+JeR8ll1JDyaEshZ4Pb2EJFf0CMpN+t5xuHWIyM7VrGGMt7jRhKEaTbSNyPHbgsUvuIgE8hC4Ja6I1DeaAPI0fJ7rikggC4E7FYhIqq4FSASiIWOq0QSQSDgFCSQhjWSMtSAUJJBEMAVJtyTYh/ITuOo+FeR8FF1JzxWEsha4PLWCbGsygeQmfe843DoUZOdq1jDGs764J1FV5VE8rE7OzdD+fDQsL/LT4cVlem6SkzjOT89f3oCCzHy2uF22jZ/w2oLHL7iCBPIQuCWugvzI5bWthnzaFA1//nyniXknCeOvEbmLJGr4RNeVkEAWAn8qkJDkOSSQCURDRqPUq4bvIZmEE5FAEtJgxlkMH4k9JIlgIrIg89hIdgJf3aeELOeigxz5dQBlLXB5aglJrecRlJn0neMw6xCQnWtZwxg3AjI35uQ0Psud2LQ/m51fDsu4OBmaOE3Os+o8Lsq5Ow0rII3PFrfLSmoLHr/gAhLIQ+CU+ALy8dWbLns9H9J19Yb9xk/nl81mtwi/unr36i032MvH9y6Sr+HzXVdHAlkInKpAR37lPcl/CUkEJCPJdDaQSjgdCSQhjWmc1fCR2EOSCKYj4zyibwEiCQq8dp9Scj7XqaSHdEFZC7yeWkq2LOkRlJz0zeOQ61CTnctZwxhv8ZguM8p9trhdRVJb8PiFVpNIHgK/xFWTyDFdSFMYvinWFJpIFgKXKxCa7WO6kHwgetOvNZE0gmlNJAlpxGOshF9rIkmE05rUQKd9KD2BR+9RaVbzoU4VPaELylrg9vRKk5zQBaUmfes41Np1Zvdi1jDGs8JJ1ujY8DrT2/v4dhVLbcHjF1xnAnkIvBJXZ/7y6o2rtxul6e7fNAWU9svpE3eb2/7Wm9NH06dXP7c/8K5rcPbr6S+mH08/mf5q+oH99eH8pHP6j9MPp+9Pf2M/fuJ+5r/bLz4e3D8y8WD6C5+R7iKNZPhGWleBAlkIXLFAgVIpcyQTiPaM/Hf47iGJhFOfQBLSOMhZCx+JPSSJYOqTnF2/D6Un8PN9qs/5MKiKHu0FZS1weWr1SS7oEZSa9K3jUOtQn52LWcMYO/nZpip7botLnFsmLezKolplt+m2uFq8q77iO9EWl+y8eldrhoxnhh764moRGhFCBrqU6otLtbq1P/aJ/d43LwymHw3j5Fbzn3T2HzP7Tz7ycd7Vcl516bB+uFqAzL6CfGFK98PVQlyVnZB+uFpwq4EN0g9XCy5IP9wqNdT4VzVuZsDstyOuGi0zYso64lbJoiNuRU6Puq+GzAyaInHtK8fxoT5Qo2bGuB474qqhGiFU9oNhrbezgLWCdqxGywxT6l0H7SOO1JiZkUvWEbfFPzxQI2UGMH5L3KVveED7hodquJKQpnkYyJa4WsSBW+KqYTKjmrAlrn0Yjv3+YKJCur2Zk5xoiVulMppcfsEzJ0AeghM17k55Q5kToJEM30j8XaqPxS6SheAYUbDvJDMnQCZhMydAIuEyJ0AS0jNczlr4SOwhSWxD5gRJT+DnRZu7jszJfBZdRc8VhLIWuDz1HqYlc4KkJn3rONQ6Miedi1nDGG9xfXhOdM2tMqktePyCq08gD4FX4qpPaH040BSGb4p1NSaQhcDhCjRmR304kA9EaRL14UAa4XQmkIQ04jFWgtCZQBLBdGZLfTiSnsCj96kzs7k0ISeBHUBZC9yeWme21IcjqUnfOg61Dp3ZuZg1jPEWN9bNica6lZHagscvuM4E8hB4Ja7OVDfWRfI0fJ7rikggC4E3FYhIqkAGSASjHonGukgi4fQjkIQ0kjHWgtCPQBLh9CPdWBfKT+Cq+xSQ84lQFT3dC8pa4PL0ApJurAvlJn3vONw6FGTnatYwxo2CPInjLDdZNczjputFWQxPzVkxvDwtzqPzuDR5vhEFmflscbvKpbbg8QuuIIE8BG6JryC/cp3Rrn4+eL6nrqtMHk6/aX7np03l+Kxu/Ortq3eWx5XTD2J/h8O7SBsYvg3WVZdAFgJXK1CXZBocyAQkL0sfkXtIIuHkJZCENMwx1oKQl0ASweRlPoq91933oewEXrxPcTmfFFXRc7+grAUeTy0uqfU8gjKTvnMcZh3SsnMtaxjjRlryxsyGl5bGZ4vbVdv8Cq8tePyCS0sgD4FT4kpLNzr2S1dp6Yowr95Y3Ee0X1oZ+cbVu4Pp37tqzOkX7tqhlZlfTh/NTi6N+5gN/VdH7yKtYPhWWFdcAlkIXC1fXF797OotH5OXkEwg4pKQlkAa4aQlkIQ0zDFWgpCWQBLBpCU1xX4fyk7gxfuUlvMRUhU9EAzKWuDv1NKSWs8jKDPpO8dh1iEtO9eyhjEO3JmC6HRWtrEro1V2G+9MocS76iq+650plGbIeGboozOFEqERIWSgSwJ2plByXvXouM4USoDM+718UdrSmUIJkXmxd03BqQS3GtgwnSmU4AJ1pshGhfeh3FfjZgbMnjtTaNEyI6awM0W57ExBzqO6r4bMDJoibc292n2gRs2McX12ptBCNUKo7AfDWm9nAWsF7ViNlhmm1JsO2kccqTEzI1ePnSm0SJkBTNCZolx2piB9w0M1XElI0zwMdGcKJeLQnSm0MJlRTdqZotw59vuDiQrp9qZFCqozRSWjyeUXPC0C5CE4UOPulFFpEaAVDN8K/G2oj8UukoXgmJC/saTTIkAmIdMiQBrh0iJAEtIjWsZKELtZIIktSIsg2Qm8uGjr1pEWmY+yq+jJhFDWAn+n3qHQaREkM+k7x2HWkRbpXMsaxniLi7kLou1EPN8DCIzBIxhaW0KJCNwSV1xCyrmhRjB8I6ypLaE0BM6WLy7Jgm4oFYi6pCq6oUyCCUwoC2m0Y6yGX2FCWQSTmGRRN5aewJn3qDEtp5kwmX/iI36AJS7wfGqZSRZ2Y6lJ3zwOtXadyVnPGkd6iztPFETniXh+m1RgDB7B8FITSETgnfhSU9l7AkrU8ImuLSeBNAROVSAniSIYKBOQmvSmNO5BmQRUk0AW0pjGWA1KTQJZBFOTLR0osAQFHrtXPRkv9Ac9ZxBLXOD61HqypQsFlpz07eOQ61KU3Sta40hvcc/cguhEEUeJ1Bg8guEVJZCIwD9xFSWyay7UFoZvi7VFJ5CGwPMKRGd731woIYz29PG4B+URUHkCWUhjH2MtKOUJZBFOeZK9c7H8BI69V+GZLGQKOTXsAEtc4P70wpPsn4vlJn33ONy6dGf3gtY40ls8Kawg2lTEUSo1Bo9geN0JJCJwT1zduZlZYVArGb6V1lakQBoClyxQpHRWHUgFokWpcWFQJgHVKJCFNCJyVsPHYg/KIpgapSeGYfkJ3H2vajRdiBd6aBiWuMD1qdUoPTUMy0367nG4danR7gWtcaQDd7bwllpZfZm10otX6W26tYUa8KrT+I73tlDbIePZoYfmFmqIRgSRAS8N191CTZp5b1ggacnMvhIh85YwX6nS/S3UGJn3g9fVoEp0qzFuzQ4XqSnzUeWDuKeGGKbPhYlGpffK4r4eODN+9tvoQg+XGUBlnS4snEWrC/sp2etCj5oZRUWy+8ZjncVRnlajIvWBP9CDz4Tg2U9ImqdFbCNC7n1IDvWIjRAx+0lxVtxZAlsBPNYDZkYx9e6kSg1h5SM9aGZgE7a/SOwD4d9JPdBDZcY3fv+La4/xoMVjPNQjlsQ8zRORpsZUUTrKvY9yrQaO6YSRpXlmrG+rvNrsWI+WGf2EDTHc07EEtQJ2ogO7vTmYkuiJEUdGxpNLMHwOBkhEcCjH3WNvKgcDtJLhW4m/vfXR2IXSEBxECjasdA4GSCVwDgbIJGAOBshCeg7MWI3CXRTynn/uQakES8RU9nnz8tvH8hP4fNGOsCsRYxbn9vRQRCxxgf9Tb3XaEjFIbtIXkMOtKxHTvaA1jvQWl6OXZC+NXGoMHsHwkhRIROCeuJIUW44OtIXh22Jt4QmkIXC8AuHZVY4OJASRn1Q5OpBHQPEJZCGNfZy1KAtvpmMPSiSY9IyjkaGkJ5KfwLf3Kj3zhVKhRyZiiQs8oFp6tlWkI7lJXz8Oty7p2b2gNY70FvfWKMneGq2jfrw6nEUwvPQEEhG4J670XKO3BpCo4RNdW1cCaQi8qkBXkhU4QCYYQUn21gAyCSgpgSykMY2xGmmVmZGhCn+AXMKpSlMQaf59LEGB3+5VVhYLFUKPS8QSFzhAvaxs67CBJCd9BznkunRl94rWONJb3B64JDtstE/Y8BiDRzC8rgQSEfgnvq6EtAcGGsHwjbC25gTSELhcgeakk+hAKiDRSbUHBjIJKDqBLKQBj7EaNtbkOdFwcw9KJpjqzEcJ1SUYSU/g03vVnOVCoZCDzw6wxAUOUK05W7oEI6lJX0AOtS7F2b2eNY70Fs86K8neGpXUGDyC4RUnkIjAO3EVJ2jaGdQMhm+GtTUnkIbA5fI1JznvDEoFojkpxQnkEVBxAllIAx5jLZIyr4y/AGoPyiWY4ExGJvPR28fSE7j0XgVntRAo9PAzLHGB91MLTnL6GZaa9P3jUOsSnN3rWeNIB26fUfno3Y7jqJVeskpv4+0ztIBXfcZ3vX2G1g4Zzw59tM/QQjQiiAx4ScD2GVrSq64d1z5Di5B5y5ivVVvaZ2gxMq8Xr6lDtehWY9ya7TOyJM9H3sOhPTXEMO0zsmpUESeVauDM+Nlz+ww1XGYAFbbPiKNl+4yYnLV1X4+aGUVFqvvGYx2ZNEkLwuQHevDM0Cdvn5GlSZ6lKXHd6VCP2AgRs58UZ8WdJbAVwGM9YGYUU29OqjQbFd64dqQHzQxsPbbPUENlxjdB+4ylx3jQ4jEe6hFLYp7miWg2YXk1Kr1PRa0GjmmfYeIqLpJoZLwnwMd6tMzoJ22fYZ+OJagVsBMd2O1Ns1RU+4w4lvHkEgyeZkESEZzJcffYqDQL0gyGbwb+/tVHYxdKQ3DQyN+R0mkWJJWQaRYkj3BpFiQL6TEvYy3SLLbam7ijiOSyBWkWKD2BSxdt+DrSLPFitl/cMq0RSlzg/dQ7GTrNAqUmff841DrSLIz1rHGkt7iSvKKaY8SJ1Bg8guEFJ5CIwDtxBSemkhxpBMM3wtpyE0hD4HD5cpOuJEdSgchNspIcySSg4ASykAY8xmpkVZVEKdW4HEkmmOKkK8mh9AQ+vVfFuZjqF7eMaYQSFzhAteKkK8mh1KQvIIdal+LsXs8aR3qLe2JUVE+MOJUag0cwvOIEEhF4J77i1PbEQBI1fKJrq0ogDYFTFahKsqwGyAQkKr35jntQJgFFJZCFNKYxViPLq3SUUtU8QC7BNGVbTwwoQYHf7lVVLqbzxS3jFqHEBQ5QrSrbemJAyUnfQQ65Ll3ZvaI1jvQWt/mtqJ4YcSY1Bo9geF0JJCLwT1xdCW3zi7SF4dtibekJpCHwvALp2dHmF0kIo0B9PO5BeQTUn0AW0tjHWYvSX1e5ByUSTnzSbX6h/AS+vVftmS2UCjkS7QBLXOAB9dqTbvML5SZ9/TjcuqRn94LWONJbPPSsoppjxEZqDB7B8NITSETgnrjSc0NDz5BWMnwrrS1KgTQELlkgSuksO5AKRI6SQ8+QTAIKUiALaURkrEZp0lGa+ajsQakEk6QtQ8+g/AQ+v1dJupiRFbcMPYMSF/g/tSRtGXoG5SZ9ATncuiRp94LWONL2f3/4H5/TYqTm/PHF2U9eee1VjyFUktMbIqzazFt4FvkNnlQfDRqtREhet9Lwwr2jhrv6mLUYlysXrTL8vDmifDL9ounG8N7VX0yfXL13y3VneDz9ZvrUlV9+Mf3UysgvvT/29vIHHzdC87GPs1WI+Qt7auI3vCbNfD2nWU8Ovmf9YHHrIE4i9yF1H3L3obIf0th9cN9Ljfvgfi51v5G538jcb2TuNzL3G5n7DeN+w6SUw9XaI5Pbg7wl6TXCoTPCoTPCoTPCoTPCoTPCoTPCoTPCoTPCoTPCoTPCoTPCoTPCoTPCoTPCoTPCoTPCIWWEQ70RjNwI/MuX1gZjZ4Oxs8HY2WDsbDB2Nhg7G4ydDcbOBmNng7GzwdjZYOxsMHY2GDsbjJ0Nxs4GY8oGY70N+C5BH3icLWpni9rZona2qJ0tameL2tmidraonS1qZ4va2aJ2tqidLWpni9rZona2qJ0tasoWtdoWN+4Md9hC9kIcOwMcOwMcOwMcOwMcOwMcOwMcOwMcOwMcOwMcOwMcOwMcOwMcOwMcOwMcOwMcOwMcUwY41huAH3yFN5Et/4njP3H8J47/xPGfOP4Tx3/i+E8c/4njP3H8J47/xPGfOP4Tx3/i+E8c/wnFf6Lj37wNM/4uqv+gTZT02dwrIe8tt01nKPKMXEUeWKUgaRElSryroRnQ2st+8Vt39dhpjyaP2jTs+syvXaZPBldvDqbfNL/zZSNLnszbfj1xmdfB1c/cXzr91N8YrPmrn84TuM0X9m9vmovZ77m/7lnzp582f/nX00fzI7NPB4nrJ2a/ffWez7531fZdDfXIlmFKiEYEkQHvumWYD+iuGujqHhTY5kuJkNkNhX+s1tbmS4mR2QZl3QMzJbpVRbRmmy+v7fbU6IJ0+ErLfFSmPuD7euDMICrv8JUmLQ2+tGiZUVTa4Ku4bvBFDma6r0fNjKWiPe7Nc3aytZcWNjNEdW9FuVgP9ViNECv76XD221kCu7nD0wJmxiz1mSntLI70oJlhTNbUi3YUD/RImcFM0tOruO7pRTqJh3rEkgCneSCol65WQ8Z086JwHutxMmOccPfsnoglqJu7XQ3YRsyWiYnPzouhOXcX4uLLaljmJ00Jif2zVVWcpuczPuRG+Ecn/VaEuO0ltR1uGx3jocnl59syt9CSbJt9RO5AiQiSg9z99Ed2d/to+rumt8IbA7uPfuIaeNkvmxKQRcXHJ/Z332l2v26X/GWzm/754P/35//Zf7ngLtQKhm8F/pbSR2MXSkOQ8BRsOOmCDyAVVMGH8VG5B6USsOIDyEKacOYsh4/FHpRFsGKPJI5GKXX5DUlQ4NBFm7quao/FMLe4ZTgflLjA+al3LvSqHmHJSd8+Drmuco/uFa1xpBu9eVnmxdnZ5cXw/NLEw6zM8+HJeVYML9Pk9MxEeZZfnL0cXm9SJSGV1BY8fuH1JpCIwD1x9SZRUdIoy/kFONdE1uVTnix7xlr9+XfT/3v6YVNz/Kum9vjX0/+v058ppT+BVjF8q6ytP4E0BC64F/0JpALRn4n/7sI9KJOA8hPIQhoAGatByU8gi2Dy03XILSj5iSQo8O+9ys/FaLe4ZVQflLjA96nlJ72qR1hy0rePQ65LfnavaI0jHXJYX0IJyiRqYVeW6Sq7TdfzaPGu+ox/qefx2feu2r4Zz7591PNoIRoRRAa8tKOeRwuUmRsVyFuqnkeLkJkI5avWlnoeLUZmCnRNPapFJ0l3MuxH6EwtuiD1PFmUjyLispoaODOI9lvPo0bLjKLCep7kemBf0jKwT42aGUtF2pubBj/Qw2aGqD7redRYjRAr++lw9ttZAlsBPNYDZsYs9baEdhZHetDMMNZfPY8aKTOYCep5kusZfbSTeKhHLAlwmgeCrufRQg5dz6PGyYxx0nqexM3l8zuGiQ7s1uZXyOstSfvImBs0ufyC51eQRATnb9z9dKD8CtIqhm8V/hbTR2MXSkNwxijYgJL5FSSVsPkVJJNw+RUkC+kJL2M1qH0vkEW4/EoWE63o9rEEBf5dtMfryK8ki5luScuMPihxge9Tb2ToVT3CkpO+fRxyHfkVxorWONLbW05OZ2MSqS14/MLLTyARgXviyk9QOTnSCoZvhbXlJpCGwOX2IjeBVCByky4nR1IJqDeBLKQRj7McPhZ7UBbB9GZbOTmUoMCh96o3FxPdkpYJfVDiAuen1ptt5eRQctK3j0OuS292r2iNIx22nif1sbMKMm1lR18S5YGVKENePY8S76rP+Jd6Hp9976rtm/Hs20s9jxKiEUFkwOvqz6MFysyNCvQtWc+jRMhMhPJla1s9jxIjMwW6rh5VopOkOxn2S9J85L1Zv6dGGKamJ07IHj1q4MxA2nNNjxYtM5JKa3rS65oeclDcfT1qZjwV6e9Vc1dFEeejMvdBP9BDZ4YqeV1PkedVRLTePtTjNUK87KfE2XBnCWwF8FgPmBm/1FuUprbH6+2O9KCZIU1Y20O2Yn+gR8oMbJLanvS6tod0Fg/1iCXBTvNAVHlsHUXhfSRqNWxMfU+VREk5qrxO7ViPlRnzxDU+6c4S1ArYiQ7s1iZZUrLGJ5PR5PILn2QBElnVA23rw9xjo5IsQCsYvhX420wfjV0oDcE5o2ATSidZgFRCJ1mAVAImWYAspMe8jOUw1SguvAuyB6USMNOSjkqvO9vHEhR4ddFOryvTshg0mbRMDoUSF3hA9TamNdOCJCd9BTnkujIt3Sta40hvb2F5Slb2GKktePzCi04gEYF74orOUIXlQKsYvlXWFqFAGgIX3IsIBVKBiFC6sBzIJKAGBbKQBkDGapgqHpEaFEglmAaNs5QguI8lKHDyvWrQxWTJpGVUKJS4wAGqNWhrdTmSnPQV5JDr0qDdK1rjSIet9sl87KyqzFvZmVV2G6/2UeJd9Rn/Uu3js+9dtX0znn17qfZRQjQiiAx4nd17lECZ2VKBxiWrfZQImalRvnRtq/ZRYmQmRdcVpUp0kgQox34mGnkTiHtqhJuv9tECZwbSnqt9tGiZkVRa7ZNfV/vkLdU+WtTMeCrS36vmzpO4SEb+fhIHeujMUCWv9snKosoI8Xyox2uEeNlPibPhzhLYCuCxHjAzfqm3KK2dfLSgmSGtx2ofLVJmYJNU++TX1T6ks3ioRywJdpoHIo9jY0a58cGu1bAx1T6mNCYdJd7H91iPlRnzxNU++c4S1ArYiQ7s1iZeMrLap20QmYcml1/4xAuQiOBMjrvHDpV4AVrF8K3C33b6aOxCaawG9BYagk0pnXgBUgmceAEyCZh4AbKQnvoyViMtcv967EGZbEfeBUlQ4ONF+74bumMl71IsTunJqbEHWOIC/6fe1LTmXZDkpG8gh1zrih5xVrTGkd7egvOMrP1pG2DmtQWPX3gJCiQicE9cCYoqOAdawfCtsLbkBNIQuNxeJCeQCkRythScA6kE1JxAFtKIx1iOtCCOn/agTIJpztZ6cyRBgVPvVXMuxoomLYNiocQFDlCtOVvrzZHkpG8gh1yX5uxe0RpH2v7vDx3zbEbcuooXftCmLfut/fF6Jqsqqxa2RZ6vsg1U+5P58d5R4131IYDan6bu5htXWDOcfjH91GrELz0VP/YnZjU5n86V4z/YH3w6O9B0gnJ2oPmWE5v25x9Nny7LduJ52c70dz7T3FWbJuOZppeyHSVEI4LIgNfZpEcJlJn2FMhVsmxHiZCZ4+Sr0LayHSVGZnZzXXmpRCfJZDLsRzWDVKILUrITF+ko92YE9/XAmfFPXrJjcrpiRwuWGf+kFTvVdcUOOUz0vh41MwqKVPTNXSk5c0sLmxmh5NU6LTO3tFiNECv76XD221kCWwE81gNmhiz1BoP2FUd60MwoJqvUIf3EAz1QZiiTFOpU14U6pI94qEcsCW+a56Fl5JYSMqZIp2XklhYnM8KJC3SqnSWoFbATHdhmxxSX52cn58kwzk7yYZZUZ8PT5KIaZnlemNOzrCiKyxkfcgfbsqXX7mKpAp35EQabJpefb6/bQkuy3/URuQMlIjhI426EP7L70c+bXek/ufqb2R2U+R73yawup9kmP13cP3nlx6/98LVXByaKBrGJvJubu1AjGL4R+PvJ6/zP1X9yXB3zwfQX0y+v3l4UJw2GA2P39l/5GO9CGQuOEXvYmCKZQNIodgOb+qjcg1IJl0ZBspAe4jKWg9gPI1kES6HEeTnKvQT3sQQFnl+0+etIoaTR/MA9JYfDHmCJC3yffodDruoRlpz07eOQ60ihMFa0xpEOe13au2m1UrN91Bgt/3lgJRKSlTLR4mUeFnGV4jamTLSmyXim6SNlooVoRBAZ8LpuOmuBMs+f+lCmSoTMwyaR4qRSJlqMzHOmdaWkEp3kTIlhP0oiKtFtPGWiBs6Mf72mTNRgmfFPmDJJ42XKJCXng97Xo2ZGQZFq5h41HuhhMyNUnykTNVYjxMp+Opz9dpbAVgCP9YCZIUu/oWhJmahBM6NYbykTNVBmKBOkTJY+4kGLj3ioRywJb5rngU6ZaCGHTpmocTIjnDRlYp+IJagVsBMd2K1NmeRkyiSR0eTyC58yARIRHJxxN8KglAnQCIZvBP5+kpMyaUuYAPkKDg372JYCmYROmACpBEyYAFlIj2wZy0HthoEstiNhgiQo8PuirV9XwmQxezhtmSYNJS7wffr9TVvCBElO+vZxyHUlTLpXtMaRDpswKXzsrNBMW9kVq+w2njBR4mUeFXF14lYmTJSmyXim6SVh | H1: ooRoRBAZ8LrumGiBMk+f+lCmSoTMoyaR4iQTJkqMzFOmdaWkEp3kRIlhvzyNR17JvqdGGChpko+M8QHf1wNnxsB+kyZasMwYKE2aXM+BTlvmQKtRMyOhSDnfeDbiOHMW9/quAz12ZqiSZ05Sk5qEHAStxmuEeNmPibPhzhLYCuCxHjAzful3F23ZEy1oZkiTZU/yguhs/EAPlBnXJNmT6znQtLN4qEcsiXWq5yGqXPwz3keiVuPGpFCyJEvSUerFeqzHyox54jSKGwTtdxATHditTaMUZBolk9Hk8gufRgESWRUEbevD3B6D0ihAIxi+Efi7TE4apf3mCZCx4DCxj+0qkEnoRAqQSsBECpCF9CiXsRy5iUZJ6r1HuQflEi6dUsSjzBvH9rEEBf5ftCnsSqcsBgynLSOjocQFHlC/4WlLpyDJSd9BDrmudEr3itY40mHTKd75EFZwmlZ25Sq7jadTlHiZh0hcvbiV6RSlaTKeaXpJpyghGhFEBrzO+ydKoMzjqD70qRIh8+xJpDvJdIoSI/PYaV1BqUQnOWJi2C/JSr9z3lMj3Hw6RQucGQP7TadowTJjoDSdYq7TKeQU4ft61MxIKFLONw4e0yoxozzzQT/QQ2dGKnk2JU6rtCWbosVrhHjZT4mz4c4S2ArgsR4wM3zpNxdt2RQtaGZE6y+bogXKDGuSbIq5zqaQvuKhHrEk1GmehyxNonyUew8RajVsTDIlzou4opMpWqzMiCdOppidJagVsBMd2K1NppRkMiWX0eTyC59MARIRHKZxN8egZArQCIZvBP4ec/1kCpCx4Cixj80qkEnoZAqQSsBkCpCF9CCXsRyJ3b4l/u3EHpTLdiRTkAQF/l+0JWw9enecFkfv5HzoAyxxgQfU73fakilIctJ3kEOudUWPOCta40gv5qGYl5eqM+A8FG+a1wrQtomDRU5vCnhgJcLy+eQK0ff2jhov80iJqx//cZlJedwMwHv8fNLEKsrHzRC9r6ZfuOl59ptf+djcVbPJeGx6yYcoIRoRRAa8zuslSqCrTraHfIhXl72kRsg8PRJJRzIfosTIPDhaVxMq0UkOiRj2o24gK9EFyYVQvUr29bCZAUueCUliU9C5EC1cZsiS5kKK61wIOdn3vh41M3CJhC/32TjQw2ZGKHkepKUflxarEWJlPx3OfjtLYCuAx3rAzJCl3hMkeRSNKuNDfaRHzQxjsiRIi6t4oIfKjGaSNEhxnQYh3cRDPWJJhNM8Ei0tuZSQMSmQlpZcWpzMMCdOfxQ7S1ArYCc6sLN4EWe5uYyHSZHZHWgSnQxPT9LL4Wl1Ep/GcXlZFvM4SO47Wzbi2r0nmf5omz3qocnl59uhttCS7FJ9RO5AiQiOv7jb1/e/vUGdD3W/+vOrNwZxNPRnle9CSRo+Sf6W0UdjF0pDcGLXx4YSyASVs/CmX+5BqQTMWQBZSM9LGctB7WOBLIJlKxJjWra8SIYCfy3atXWlKxbDvtOW8e1Q4gLnp9+a0Mt6hGUnff847LryFd1LWuNIh738EXvX1ErEqoVeWVar9DaeoFDiZZ7zcBVeXwkKJZuMx6aXBIUSohFBZMBLBtMng+dubbz8albcyv8guhWbndj9N3eflLeM/TQtjI/NrpoN80ioD9GpRMg8/hGJSTKLocTIPPdZVyUq0UnOeBj2o9SfEl2QLMbsZDL3Id/XI2dGtr4TGVq4zNAmTWRcz2JPW2axq1EzA5xIEnNP/w70sJmRrNdEhharEWJlPx3OfjtLYCuAx3rAzKil3y3Q7uJIj5oZyfpMZGihMgOaJJFxPY6ddhMP9YglQU7zSLQkMpSQgycytDiZYU6cyHDj2P2uYaIDu7WJjDiiMhlZJOPJJRg8k4EkIjgZ4+5zdZkMJEnDJ8nfW/po7EJpCA7zethUIpkEzmQgqYTLZCBZSE9SGctB7GWRLLYjkwFlKPDXom1bRyYjW8zczlqmqEOJC5yffm/SlsmAspO+fxx2HZkMxpLWONKBMxmURGwds1dFq/Q2ncnQ4mUe9HAVXk+ZDC2bjMemj0yGFqIRQWTA6yWToWXDPBPqQ3QqETLPf0RikspkaDEyD37WVYlKdJJDHob9knRUxUSDKi3EQOmMLBv5x7Lu65Ezw1vP6Qw1XGZ8E6Yzsus56VnLnHQ1amaUE+niVXvnaZJRvWcO9NCZIU2e0jCxqawG8rrbQz1eI8TLfkqcDXeWwFYAj/WAmSFMv3VoS2uoUTPDmjCtYcpylBFpDTVUZnQTpDWy65HptLt4qEcsiXiaRyJPkqgaFd5nolbDxqQ28riyWP2dn471WJlhT5reyNzodL+LmOjAbm96IybTG4mMJ5dg+PQGkIjguIy7+VWmN4AkDZ8kf8Ppo7ELpSE44etjpwlkEjq9AaQSML0BZCE9XmUsR2J3iX69twelEjDHUSUjQ+U4kAwFTlu0l+vKcSzGZGctg8+hxAUeUL9Rac1xINlJX0IOu64cR/eS1jjSi+5S83DgxGLA7lKxN1pY3Zi20C0KWszz0Er04PM5D2K43R01XuZpEFf2+WZ3TD+3WvDPp8/st934DTeqo5nIYT9+5kZ7/Mz+1CMfq7tqVhmPVS+5DyVEI4LIgLeS+5g+GQ2mfzv9b8Ns8L1Z3un3Rz4Gu2oGzMMigQp1MD+zsL/yAX1JDZR5PiQSmWTaQ4mReTC0rnpUopMcAjHsZyr/CKI9NcAwSY+sikZl5kO+r0fOjG/ypEcc5fRgDjVcZoCTJj2u55xnLXPO1aiZYU4klG/YOyuTKBtV3nzegR47M5jJsx55miVUWuxQj9cI8bIfE2fDnSWwFcBjPWBmINNvJmi/caRHzYxqsqxHnBQVOZxDDZUZ3CRZj+tR57S/eKhHLAl4mkei1VfUatyYtEeRx3FC5MKO9ViZgU+c9nCjzv0+YqID28j1s7NLc3JxMcyNORlmlxfZ8OQkPxueXSZRVJbF5dn53E+TG9eWnbx680qmPTIZTy5B3xa3hZdkm+sjcgdKZFUUtC0Qc//732bFfcSO182gnGdCmq3Z9MPpx4MkjmbfMtFg+rHPCnehVjB8K/A3o5bZo+mXbjKHtYXb6f9uMP3GnQtYszyZPr36ubPR06v3BvY3H822p1c/Xx4JsE4MBtNf2u9/3hw2uGGgX1+9dfX21Rtzy/5i+uuhiZxdo1sDN+rz6q/s3/WkKcT83a0ZmCfub3rSzAL92lVnNv/qaPHXm4ieHoJcD8HxZo9bayAhTJ7Hx+MelEfAJA+QhfR8mbEWLdt5IJFwKZ7WbT+SoSBAiXauXSmexejurGUYO5S4wAeCdmVIdtJXkMOuK8XTvaQ1jnTgayxe7W81sWmhV1bxKr2Np3SUeJlnXVxJ23dKR8kq47HqJaWjhGhEEBnwqJRO3pnSUTJgnoT1qDuVQJmHXwI92ZLSUWJknnqtqxWV6CQnXAz7JSOqykeJbwsyOlrkzPDWd0ZHC5cZ36QZnetR61nLqHU1amaUE+niGwmSrMhH/vtZB3rkzEgmz+ckRRETI/EO9XCNEC77GXEm3FkCWwE81gNmBjHQxkGLmhnR+kznaKEyA5sknXM9a512Fg/1iCXBTvNItDiKWo0ak8xJ08SMKm/V27EeKjPkiXM5btK630FMdGC3N5eTkrmcXMaTSzB8LgdIRHBUxt34onI5QCsYvhX4u9BtyuUMpv9of/TXiJQOcFkEx5k9bq2BhIKmdIA8AqZ0gCyk58mMtaC380AeW5LRQTIUhCnRzrUro7OYH561TISHEhe4QNDGDMlO+gZy2HVldLqXtMaRDpzR8a6pVcZtwwbLKlmlt/GMjhIv86yLK2z7zugoWWU8Vr1kdJQQjQgiAx6V0bHP+K3FZ8ksu9P0hHPN4r4kszxKVswDsh6lqBIo80xMIDFbsjxKjMzDsHXloxKd5OCLYT9TjqhuZUqAW5Dm0SJnxry+0zxauMygJ03zXE+Rz1qmyKtRM0OfSCzfLMbPszwe+ScBHOixMwOcPNGTJ3lpH2gq06PFa4R42Y+Js+HOEtgK4LEeMDOQgTYUWtTMqNZnpkcLlRncJJme63HytL94qEcsCXiaR6LVV9Rq3JhcT2GSOCf67R3rsTIDnzjZ4+bK+33ERAd2e5M9GZnsaRuK6uHJJRg+2QMkIjhF4+6JUckeoBUM3wr8DSo/2cM5MCDzOh9NP55+OIyj6IXBw9v3B1UUpYPhII3tPzaafjX6fzffLaI4t99Nilvl/Ps+I+9CjSw4t+xxvwwkFDR1A+QRMHUDZCE9OGasRcseHUhkS3I3SIaCqCPajnblbhaz1DNylvoBlrjAB4K2Wkh20leQw64rd9O9pDWOdODcjfHRs0K3aqWXrtLbeO5GiZd5gMXVqX3nbpSsMh6rXnI3SohGBJEBj8rdpMvcTSrI3ShZMY+8etSiSqDMUy6BxmzJ3SgxMo+31tWPSnSSoyyG/RKiWcieGuAW5G60yJkxr+/cjRYuM+hJczfVde6GnIh9X4+aGfpEYvnGbsdEWTEy3iPOAz10ZnyTp26S1NgNGnlJR4vXCPGynxJnw50lsBXAYz1gZhwD7Se0qJlBrc/UjRYqM7ZJUjfVdeqGdBcP9Ygl8U7zSLS5iloNG5O5ScqkiEYpdU1Hi5UZ9sSZm2pnCWoF7EQHdnszN8TU0dvxfAgAmyeXYPDMDZKI4AyNuyMGZW6QVjB8K/C3p2EzN/HiKs63EjjFLW8GJzat+RukqQVnl/3tmZGEQuZvkDzC5W+QLKSHx4y1oPfpSCLbkb+BMhTEHtGWtCN/YxYT5A05Qf4AS1zgAzH7LSg76SvIYdeRv2EsaY0jHTh/490vWbkbt9LLVultOn+jxcs8xOKq1Z7zN1pWGY9VH/kbLUQjgsiAR969GXyvWYrHbrdA5Wu0LJjnXD1qTyVQ5tGWQFPS+RotRuaZ1rp6UYlOcn7FsV/qtd6eGt/m0zVq5MwQ13O6Rg2XGeOE6RoTL9M1hpz0fV+PmhnpRNp41d5pkpYRddp9oMfOjGfyfE2clqakRkEe6gEbIWD2c+KMuLMEtgJ4rAfMDGSgDYQWNTOq9ZiwUUNlBjdBwmbpMB60OIyHesSSgKd5JFqdRa3GjcnYxHmeVFQsOdaDZYY+acrGPhtLUCtgJzqw25uyycmUTSLjySUYPmUDJCI4NuNuglEpG6AVDN8K/B1p2JRNZC33W7vLfeoM7LPgLtSCglPIHnfDQEJBMzFAHgEzMUAW0mNgzlqQO3Agjy1JxCAZCiKKaLPZlYhZjLk35Jj7AyxxgQsE7aOQ7KRvIIddVyKme0lrHOnAiRjvzXgrYtNWemaV3sYTMUq8zOMprgbtOxGjZJXxWPWSiFFCNCKIDHjkRRpWIkbJgnl+1aP0VAJlHlkJJGVLIkaJkXlWta5cVKKTnEsx7GcMdaFaC3ALMjFa5MwY13cmRguXGeSkmZj0OhNDTh+/r0fNDHUicexJbFRlOSq9quJAj50Z0OSZGFNlZUI2PVPjNUK87MfE2XBnCWwF8FgPmBnIQBsILWpmVOszEaOFygxukkRMep2IIf3FQz1iScDTPBKtvqJW48YkYoo4tU9F6i1bO9ZjZQY+cR4m3VmCWgE70YHd3jwMsSW0W9hMxpNLMHweBkhkVRS0LRBzD4zKwwCtYPhW4G9IPXmYq7ftlt91cPgUnZZZ3qS5tbxJ4zPrLtSsgpPJHnfIQEJBkzNAHgGTM0AW0qNhxlq07MqBRLYkO4NkKIgzog1oV3ZmMaHekBPqD7DEBT4QtLlCspO+ghx2XdmZ7iWtcaTt//7wPz4nnEil++OLs5+88tqrHkOohK43eluNa1p4FgU9WpONViJfrzM1Xrh31HBXH7MW4zJFqjdR45TFl1dvXL1rv/HEKbFm7KCTaz46VpKaF/bUnG64RJrUeh6xnhx8zzq5/NZBnCfuQ2E/FO6zwrgPlf1Qui9L92Xpvqzcl5X7sipvHSRR4j7k7oP7Mo7cB/e9OHMf7J9IEvdZ4j5L3Wep+yxzn2XuM+M+M+6z3H2Wu88K91lRUT5Za9VMblXyEMBrykNnykNnykNnykNnykNnykNnykNnykNnykNnykNnykNnykNnykNnykNnykNnykNnykNnykNnykNnykNnykNnykNnykNnykNnykNnykNnykNnykNnykNnykNnykPKlId6Uxq5KflnFNaSY2fJsbPk2Fly7Cw5dpYcO0uOnSXHzpJjZ8mxs+TYWXLsLDl2lhw7S46dJcfOkmNnybGz5NhZcuwsOXaWHDtLjp0lx86SY2fJsbPk2Fly7Cw5dpYcO0uOKUuO9Zbk+y99lHQWrZ1Fa2fR2lm0dhatnUVrZ9HaWbR2Fq2dRWtn0dpZtHYWrZ1Fa2fR2lm0dhatnUVrZ9HaWbR2Fq2dRWtn0dpZtHYWrZ1Fa2fR2lm0dhatnUVrZ9GasmittuiNQ74Oi8pe8WNnxmNnxmNnxmNnxmNnxmNnxmNnxmNnxmNnxmNnxmNnxmNnxmNnxmNnxmNnxmNnxmNnxmNnxmNnxmNnxmNnxmNnxmNnxmNnxmNnxmNnxmNnxmNnxmNnxmNnxmPKjMd6M/JVi/AI0lpx4qw4cVacOCtOnBUnzooTZ8WJs+LEWXHirDhxVpw4K06cFSfOihNnxYmz4sRZceKsOHFWnDgrTpwVJ86KE2fFibPixFlx4qw4cVacOCtOnBUnzooTZ8UJZcWJzorN+/3yUgL+oE0T9lm6Qw72nreioljQbZx4YJV60GH24b2jxstMZyIE4aPB1Zuzw7vH08/daZwbDd2UmCxmVP9u4A6p7J98253MNQd+X86P/JovHtvfesf9ZPNvPZmfhz6ZfjGwP2d/c/po+tXsb7Cffd385YtKbvvvuy+/dFOpLYov7L/+VjOcevYPNMeDtGJVGntVVSELipQQjQgiA16yrCUaDaaf2MX55oXB9P3pPwxdY173X28yaFdNgJmCFZyUfpX4EL6kRshMtwqOPluKiJQYmXnWdY81legkOVWG/ahKciW6IBVE1LXXfT1sZpxVlA9laUWXD2nhMiOttHwovy4fIoc339ejZsZb0VkF99k40MNmRq7uwwAu1kM9ViPEyn46nP12lsBu7mu1gJkhS32wHWeFGUVe4XikR80MY9KqIRMTT8QDPVRmNJNUDeXXVUOkm3ioRyyJcJpHgnrtajVkTMEQhfNYj5MZ5oQ7dfdELEHd3BNrwDZoq5NTV3UwNKdZOsyqk2JYnp4kwzLL86SMTHZeXMz4kNvlH530WyxEbkLtprltEKSHJpefb2PdQkuyufYRuQMlIsjhcnfd79vd7OPnt7XPrn46qxGa7Yj/sdn8/rn99RfNHtftnR8tyoiazbSrePnV9P3h9GO7R/vF9MPp39qP/zD9xGeeu1DzGL55+JvQawvNi4Oe3/9PP14cWUx/644gpp8Npn9t7fOFKzxyhwO/mH4cR4OrN5vzhsZiTT3S1ZvuNz+O7LZ2kBj3zc985tqFmmtVO7SYS7DlJai8BKWCKQsaeXfv96BMAhYGAVlIqxIYq0HttIEsglUFxcko9Sbs97H8BPFEtKu8oXFWaoKKRQEJOSr8AEtc4Pr0WydqUY+w3KTvHodb64IecRa0xpFu1O5lfmnOTy5OhmlyWg3j+OJieBJHyfA8zvP45Cw6Pa26CoYQatcbQazabRsC6bUFj194tQskIvBOfLW7SO08sTL3sdVlVsU5VfZcnmfw/YvXT350Mjg4ef3kz/7sFVck/8ilpNz95UF9L4+jNIoeDvIo+vfuV2X/sq9csum3TTbqi0Wh+ZtNkumtWVue5xSgz453oXY0fDuKZLE3S7ZqvfqeiZI4sQZLoujqndJ9iOOBM9qtl19+dfpfGqt95nJo7psunWe3GDOp7Loa/ZP9Nfvye/YfeDxw/4r7pksAfRB7Xc0u1JqC0CFQzWSiCMgEJJoj73Wye1AqAVUzkIU0cjOWg1LNQBbhVHNcpXQqC8lQEJl61c2L+dKmZWQ4lLjA+el1M72sR1h20vePw65LOXcvaY0j3SjnPCrK07RKhkl6cjbMLk/MsDT5yTBLzqryrLhITy6zl8MrZ+/WySrnSmoLHr/wyhlIROCf1lHOj759HPpocPTKxU9eP3H/efXPTuZ3TK+F8PTZ8PmD0A+auqmF2Gt+9vtVVEVx9DCKovjfHB9F7ptW8D2aVX01lV3u32x+1mrvP3C/SiclfSa+CzWx4Zu4f1E9/cgdOs9N2Jw7u8PmF1/MoyRyUtudTP+t68Dklmv69dXPr95z2xL3E1mS2J+45cx39U7zodnAjHwW3IVaUBBL+hDSQCahhTSQSkAhDWQhDeSM5aCENJBFOCGdFtkoMz6G+1iGgkDVq5CuFqqLHHh8gCUucH56IZ1U0Sjy+sMjLDvp+8dh1yWku5e0xpFuhPRZUqVJEp8Oz6vU/myWZMMyiaLhRXxaVadFnNsffzm8kM58trgdz2fVC2zB4xdcSCOJCPwTV0j//XPXBR4Npv+1OTN+PLu/MJh+vJumf+T0bZTNz4zt7zelBc09hecVtM8ad6HWMHxr8DWvj8YulIbA9wqEJ1n3gKQCUZ7RKDE+KvegVMIpTyQLaeTjLIePxR6URTDlmdlnzbvL2cfyE/j1PnVnvhgwm7fMDIYSF/g+te4kF/UIy0367nG4dahOxoLWONKz49vLMsovz6PhZRJdDrOzvBqW51U1PLu4yKI8vTyJsnmUCKo6jc8WVnW2jaDyK3AWv/CqE0hE4J24qvOXKzdhH7lOeC6VPrsJ++b00ex8dXY0+2tXtzr9ZPqr6Qf214fzk9z7R0MTD6a/8BnkLtQghm+QtYUnkIbA+fYiPIFUQMIz9rqNe1AqAYUnkIU0+HGWw8diD8oimPB0bY+JygEoP4Fr71V4xgudQg4MPcASF/g+tfAkF/UIy0367nG4dQnP7gWtcaSbHny3loorcNsVoqY2T1rZ0i3AeWAlkvH5tisJ1XZFi3fVhQRtuzLrkPLUZZWb7zy2MvIraniSlmHGYyjrdTL9G3f16uqvrn46q1twbVv+0h26Xr3tkuV/M/3IR+JFNQkjIsEgcN0NxQd0Vw2UeYVcoEipHLwW4arYRHY90WJk3hNfV0Eq0a1GKEzXEy26IF1PYlOkoyjzId/XI2dGOnnjkyxOyL4narTMUCfse5Iny74nOTmv8b4eNTPgifQyt1nAgR42M4r12fdEjdUIsbKfDme/nSWwFcBjPWBm0FJvJVq8xZEeNTOQyfqe0J7igR4pM5wJ2p4svcSDFi/xUI9YEuI0TwTd9kQLOXTbEzVOZpCTtj2xT8QS1ArYiQ5s8yCcpBdpYszQnJ7kw6y6KIanp2flMCmqi/g0TsrqZG53crvasn/Xblmptid5KqPJ5efb2LbQkmxufUTuQIkIDs24u97Vph7cHS2QpeGz5G8ar4m6hiSuUvzp9f3KOffP7Hd/6y7CXr0z+Ha1vd3/v7NyGGD/3Pct/dcGRz/80x8PspbWJUhbCU4TBftWOpMCpALKpKQ+JvegTAImUoAspIe5nNXwsdiDsgiWSEkSup0olKAgKIh2hl2ZlHRx8E5O/DzAEhf4PvX2h17VIyw56dvHIdeVSule0RpHelbDk50XxdlFOjyNy3KY5SYZ2j996lqenMen+cl5ac5eDq9ZvdLcatZMagsev/CaFUhE4J64mvVmDc/iiqW3lGeW5nCt6Jvhl0P7nyf2d7+Z/9RipqX9KZ917kKtY/jWEWjdpYFai5s8Lft+3XTke2txX3Jw/8jEg9sDn112oXYR+PZedC2QCkjXkhVCQCoBhS2QhTS0cpbDx2IPyiKYsM3LUUbpWiQ/QeDoVdcuhjrmLXM6ocQFvk+ta8lFPcJyk757HG5dsrZ7QWsc6UbWlqdRfmnOomF2EsX2JxL7p/LzYliaqoouy7MLs0g8BZW1qc8WVtYaqS14/MLLWiARgXfiytqP5/Oblo2n3QSlr2ez1KnT2cH3Fr/l+u79X9PH0y9nstjKu+n707/+/bkyPj55/Y8vfvKT+XSn7n+p0cfPrGZ8q1GPi4nvHgDzy5nz35//6Z81I6CeXr07+wer2GTePdRd6BoZ/hrxxbWPxi6UhiAeCLRwx+x6JCGIIvbmle5BeQSUw0AW0pDMWAtKDgNZBJPD5GyVfSw/QcDpVQ6bhXoyLXIYSVzg/tRymFzUIyw36bvH4dYlh7sXtMaRbuRwkVwm53lVDvPTOBtmZZUOq+zyYhjl52V2flFF5xuRw5nPFlYO51Jb8PiFl8NAIgLvxJXDv/621OQq3axpqTyYy97d2/dnn41/9OorP/6T117/yY8Ht+8e740PBw+zyKONh0uJ/C39OzsxXVG/Hrl79RfzJn9N82vfOtyFroPhr8PakhdIQ+DzBZKXLMcHMsFoXX8V1T0ok4BqF8hCGnEZq0GpXSCLYGo3Tsmxo/tYhoKI0qvezRfyiBxJeIAlLvB9ar3bsqxHWHbS94/Drkvxdi9pjSPtJG+bku33Sih1pFu0sCurfJXdxq+EKvGuOo0tvhKqZJjxGAa6EqokYUQkGAQ6r4QqgTJv1/ShQZUImTdpJNqSvhKqxMi8Q7OualSik9yXYdjPZKnfq+2pEQa6FlpVo9j7dO7rkTOjnfxaqDE5fS1Ui5YZ7qTXQovra6HkWLj7etTMoCdSyTc6iuRlViZEJ/YDPXZmOJPfDU2juMrTUe59RA71gI0QMPs5cUbcWQJbATzWA2aGMP1WwhTJqPL6jSM9amZYE14QrTKi6uWBHikzuEkuiBbXF0RJf/FQj1gS8DRPRGmyxCSj0vhw12rcmFuiSV6aqBzN639WwB7rwTIDn/iqaLGzBLUCdqIDu7UJGUJG2c1s2xQoD00uv/AJGSARwfEZdzf8zzchA1wHw18H/nbXR2MXSkNwKNnHZhjIJHBCBsgkYEIGyEJ6IMxYDVMVo4zagwOpBMzK5DZCehnuYxkKwopov9mVlVlMh8xbBn5CiQscoH4r1ZqVQbKTvoQcdl1Zme4lrXGkt7csn27rWUltweMXXvYCiQj8E1f2dhfL/3MsyweukeGv0dqSGEhDEBEEkrirLB9ICKOMfTzuQXkE1MVAFtKQzFiLxHjLA/agPIKJYhMTR477WH6CkNOrJF7MecxbRndCiQscoFoStxXmI7lJ3z4Oty5B3L2gNY709rZfIYuaikhqCx6/4IIYSUTgnbiCOHD7FaR1DN86fCnad/sVn1l2oWYReHaBtCW7ryCpQEQt3X0FSSWcrkWykEZWxnKU8SjLvQuyB6USTNrm1chkPn77WH6C4NGntC0WwySLlumgUOICB6iWti0tWKDcpC8gh1uHtGUsaI0jvb3dsFPqzmnRNrDKawsev/DSFkhE4J240lbZDRvJ0vBZCiTq5rphI20lcNu96FYgFZBu9W6l70GZBJStQBbSqMlYjThPRpV3QfagVILJ1iRJR/N7dTd1K5KgIDL0qlsXsyiLluGiUOICB6jWrW0tsaHkpK8gh1yXcO1e0RpHejFddO5BnR4NOF2UkqZJC9uiKFbZBrpKWlJXSbV4V31IH1dJrYj6enlo2twtfbfJyH+6SPk3uqqpAPjzRpM9pkpWtawyHivZ9VEfxBfVEI0IIgPe9eXQ0WD60fQfht4ne1cNmHnDRqA4O4oAtECZl2r4erLlrqgWI/M6zbpKUYlOcnWGYT+v7fbU6ILcE6WnnKhhM+OY/JJoElFov69HywxkwkuixfXs0KJldqgaNTOcieQw99E40MNmxiv5/VB6dqgaqxFiZT8dzn47S2ArgMd6wMzApd4pxFE2Ml7QR3rQzCAmuxlKO4oHeqTMUCa4GVpcjw6lncRDPWJJeNM8EPToUC1kzKVQenSoGiczxknvgxZudKjfMUx0YJtdQhpfnmdRNozOq9QlVvJhVcWx3a5enJ6dXUZxkswfbnIv2rI51+5HqfugRSqjyeXn27W20JLsXH1E7kCJCI7EuFvaj643qlc/HxwPm1r3N+w+64tFictH0w+m/30YxYv6oFlN+uPmx565a6GP5kVEz6aPZz+SFFH0B6n35bsLtY/h24e/8/TR2IXSEBwA9rgfBRKC5EHsvtX4qNyDUgmYCAGykJ7CMpaD2gYDWQTLgVTRqPK2a9jH8hP4e9GerysFspghWbRMBYUSF3hA9caGXNQjLDfpu8fh1pUB6V7QGke6UaPurzkrYjOMT8/iYRZdmmF5HlXD2JxUcXIRZWfV+cvh1ahXdFs1mkltweMXXo0CiQi8E1eN/merQz935SpWSk4/azTlF67UnK7BfvxHTnL6yN+Fkjd88nypeV3R85UrqJ/lOxY63FPk84H99Cv7B1yV+kuv/PvB9B9XrTSY/tb+/tPmx9Mycn/xU5+xdqHGErhzvqC9+tnVWz4qL0GpQKRsNIoqH5V7UCoBpSyQhTSccpbDx2IPyiKYlI3JQ9J9LEFBtOhVyy4GRxYtk0ChxAXOT61l6VU9wpKTvn0ccl1itntFaxzpsJ3gjY+dlaemhV1Z0QfYPLAS2ckr31HiZeY7ueqy7/IdJauMx6qX8h0lRCOCyICXrpbv2I1oaxmPEjgzG8pXmZ3HpkqgzAwoX0O2lfEoMTJzn+uKQyU6SZ6TYT9K9CnRBSnjiatyVHqPMPb1wJkRredCHi1aZkiTFvKY60IecsLifT1qZmATCWFu/vtAD5sZuXot5NFiNUKs7KfD2W9nCWwF8FgPmBm69HsE0lkc6UEzw1iPhTxapMxgJinkMdeFPKSTeKhHLAlwmgeipZBHCTl4IY8WJzPGiQt5zM4S1ArYiQ7s1qZODFnIk8tocvmFT50AiQgOw7ib255TJ0Dyhk+ev8HcaOoEaCzB6SF/U9uSOgFSCZ06AVIJmDoBspAe3nKWw8diD8piO1InSIKCaCHaMXalThYjV4uWKbpQ4gLnp98WtaVOkOSkbx+HXFfqpHtFaxzp7a1KN2QdUPswJo8tePzCi1kgEYF74orZ8FXpQPsYvn0EevcTj1G++ZbZZjYaRPHge4771Ttp5IY4/f6t5TylwbDdcD5b7UJtJfD4fLnbmcMBEoKI3pbSdyCVgKIXyEIadhnLQYleIItgoreKRon3pGcfy08QVHrVvMVCIZFDOw+wxAUeUK15yUU9wnKTvnscbl2St3tBaxzpRvJWVXV6WV6cDs/LPBtmWV64aUbR8MxEeRqfnF5GJ2cvh5e8qc8WVvKWUlvw+IWXvEAiAu+kk7zTX3rknTu6/atZV3F3zDs/ypyNHVroYe+NlrtQYxi+MQT61meAmb6djU16ZpXrl/Nmll9cvXf1l03/SmuHv5n+36tKuD754cm/HXwvTpMoSn5/kCVX78TGaeFvSeEomath9485qz73lceou1CjCsJAj0IYSAgkhL1h7B6USUAdDGQhjcWM1aB0MJBFMB2cJdUooUqtkAQFoaZXIbyY7Fi0DOuEEhd4QLUQplf1CEtO+vZxyHUp4e4VrXGkw9bN5z52VttWrezKVXYbr5tX4l31GVtWN69klfFY9VI3r4RoRBAZ8JLB9Mngunh++mRRPu/DvavGzaw97FFpKoEy6w0lCpIum1diXNWHoLJ5JTpJVSHDflXlz53tqQEGqZw3STLKqXNNLXBmTJNXzsfWypW3zOX7erTMoCatnK+uK+fJEYj39aiZoU0khW88HHGZJaPK+3gc6KEz45e8ej6uSjdz3ov3UI/XCPGynxJnw50lsBXAYz1gZhTT7xaqbJRnPtBHetDMiCasoM9aKui1SJlxTVJBX11X0JPO4qEesSTW6R6IKC9Hifc5rtWwMVX0SVpGJV1Jr8XKjHniSvpqZwlqBexEB3ZrMzE5VUlfRjKaXH7BMzFIIoLjMe52F5uJQRrD8I3B34J+FzIxSKMKziH72x8jCYXNxCCZhMvEIFmsqpQWFtxdeRxVo5jYlyOphEvH5PloflZ9Y/8OJSiIN6I9aEc6plwMXy1bpulCiQvcoH6D1ZKOgZKTvoIcch3pGMaK1jjS23uxNKdq8cv2CW0eW/D4hZfDQCIC98SVw/1eLEWSN3zyAvm7wYulSGMJ/Dlf1tIXS5FUIIKWvliKpBJQ0QJZSMMpYznKUZV49d4elEkwQRtHMTlmF0pQEDF6FbSLoaxly5hdKHGBA1QL2sTQl0uh5KRvIIdcl6DtXtEaRzpsfZH3bM9K1KSVXbXKbtP1RVq8zCQsV2H2XF+kZZXxWPVRX6SFaEQQGfCo+qLMh3tXjZuZmeULzc7zUyVQZjaWLyNb6ou0GJl52HX1oRKdJOfKsF/l1UR7anhBqoviOBnFlJjTAmdGtH6ri9RomSFNWF1UXg/YLVsG7KpRMwObSAjfVPpFXoxS7+NxoIfOjF6a6iL3gETeiHCox2uEeNlPibPhzhLYCuCxHjAzhqn3CnFc0IffWtDMeNZfdZEaKTOqCaqLyutBu7SzeKhHLIl0ugciMSmRxqvVsFHVRRH5UBzrsTJjnrS6qHQDd/0OYqIDu7XplIKsLkplNLn8wqdTgEQEh2PczW7P6RQgecMnz99wbjSdAjSW4DSRv8ttSacAqYROpwCpBEynAFlID3MZy1EShex7UCLbkU1BEhQEDNEmsiubshjwWrZM7IUSF/g/9Q6pNZuCJCd9ATnkurIp3Sta40hvb6vOgiwPyqS24PELr2eBRATuiatng7fqRNrH8O0jkLyba9WJtJXA4/MVb2deB0gIonvpVp1IKgF1L5CFNOxyliOKRlQZEZBJMOFblaOYuNYO5ScILL3q3sUs2LJlui+UuMALqnVvS7tOKDfp+8fh1iV7uxe0xpG2//vD519XJ2d/0KZv+60q8jomq2xNC92ioE/PeWAlivX5qqI4IsuKlICZ2VeuMm3KipxUmv6uKTD61Immb6ZP3a1N+xtvu+PDgf3ii8H0y0ZZPWrOJD9rPvt6+sT+EVeR9Lv5H7JffumOad8cWBXnlNcT+4NfNj9w9bNGhH16q/ndbxqR9rn91iN3mml/8vHsLHf2lzX/gjvsnYu3Lxf/xrP5qeY77icbxE989r2rtm/Gs28vBU5KiEYEkQEv+fbg4V8Pvc/srhowMyvcowJWAmVmgkXKlqxsUmJk5oDXlaxKdJJ8L8N+XtvtqdEFKWyiByCpYTNDqrysKYtjctywGi0zpkrLmq7HDZct44bVqJmBVaTMuY/GgR42M17JS5roccNqrEaIlf10OPvtLIGtAB7rATMDl37Tko+yzIf5SI+ZGcNk1UxpkdHVTFqkzEgmqWa6njZM+4iHesSS6KZ5Huhpw1rImEqmliomLU5miBNXMblpw36/MNGBbVSOOT/L48tkmJnUfshMNTzNTorh6dlpepKf5iar5kGQ3BW3nBNod8ZkFVMuo8nl59s/t9CS7KF9RO5AiQgO57h76/eXG+YnVz+1n7/ZVDTZbexzu+fB9y9eP/nRyeBHJ6+f/NmfvTJP/0w/niU05hU71519Zr89ePHFPIrSKHp4a7DbGGNw/6UoHkxefeUnr/zw4t9YI7w2+LevX/yHwdG9weyP5C5h0nyIm6yJz8B3oQY2fAPzd652t/rcUUXHQcWjhbEPZsYezPJy8yRRU1T15dWbL7/8qjNvkljzOtPld46d9f59Za7eqQYrbZjsyswXavps2NmACWhdwRGrYJv9lTeP/BKUCSTDFBEn/vegVAJmmIAspCfcnOXwsdiDsgiWXSrJApx9LEFBBBNtYrvSS4t5uWXLBGQocYHvU+/U6FU9wpKTvn0ccl35pe4VrXGkG4F9llRpksSnw/MqPbM/m2TD0gbk4UV8WlWnRZwXF/PHPajA9oZDK7DbRuN5bcHjF15gA4kI3BNXYP/9cymmR4Ppf50+nn7RaD8nrKcf76Zpcysgyr5dFvSkyRt16bW7UGsYvjX4athHYxdKQ+B6BbLzy+lnPiovQamAdKf/Tug9KJWAuhPIQhr5OMvhY7EHZRFMd2bRKPG2XNnH8hP49V5l52JmbdkyhBhKXOD71LKTXNQjLDfpu8fh1qU6uxe0xpFuVGd+WUb55Xk0vEyiy2F2llfD8ryqhmcXF1mUp5cnUTaPEkFVZ+qzhVWdpdQWPH7hVSeQiMA7cVXnL1cqkx7Rt1J/N5j+evqL6cfTT6a/mn5gf304P+C9fzQ08WD6C59B7kINYvgGWVt4AmkInG8vwhNIBSU8Xbr9Jpd7UC4BlSeQhTT6cdbDx2IPyiKY8izLUUkdeCL5CXx7r8pzMSO2bJn6CyUucH5q5Uku6hGWm/Td43DrUp7dC1rjSC/r6edSMnA9vbfhgBWXVRvdMl6lG6qePibr6ZWAV51IH/X032rTaT991NQrL8rbP/OW2DeTgG4Nmj/09Oqvrn46fXT13sD97vN/39Xbg6ZY3x1zvuUOOb928vOtRpH+9urdQTNv6Fnztz9ust7v+ax1V22tjGetXqrjlRCNCCID3o3qeG8WYFcNmFlkKJCxXdXxSqCrQhVaHa/EyKwpXFd8KtFJ6gcZ9qNEpRLdpqvjtbCZAVJeHR/nVNXr9/VomRFSWh1/PVK4bBkprEbNDJMinc19NA70sJnxqtfqeC1WI8TKfjqc/XaWwFYAj/WAmYFLvQWJy3hUZD7QR3rQzCAmK4+PTU6Xx2uRMkOZpDz+epQw7SQe6hFLwpvmgWgpj1dCDl4er8XJjHHi8ng3QtjvGCY6sI1QzE2WXGanwzNzFg2z88vz4cllVgzNaXmSpHZbXJr5o0Juclu2/dqNLlUeX0Uymlx+vu1wCy3JlthH5A6UiOCsjbtV/nbp9mIWbn1w++Hx0cPxS3v3dwe3H0xup8W8hL0yf5AW0w+mHwySW8n0A58N7kJtYPg24O8uVyvYP7Nf/HZxUWBmkhdf++EP//ji1cH/fH8QR9EgirO8uwR98PD2/UERuR+dvj/9gNizIs0lOKXsb2+LJARJ1BBl6Uge4ZI0SBarYqOFxZr7aSSLYEmauEgIMb2PJSiIHKLdY0eWplqMjq1ahgFDiQv8n36LRK7qEZac9O3jkOtI0zBWtMaR3t7u9RVVll61zZHz2oLHL7ywBRIRuCeusO23ez2SvOGTFyjaDXavRxpL4M/5epbuXo+kAlGydPd6JJWAYhbIQhpOOcvhY7EHZRFOzEZ0GglKUBAtehWzi7GxVcsgYChxgfPTi1lyVY+w5KRvH4dcl5jtXtEaR3pZc5S9vBSpAWuOYu8iW8GatPJNV/mGKjrKqKIjLWBmNpUrOIkmns+c1rp6t7ki+d7sG0+f6+bZtN5sjhGfNILL/d6s+4grKnJlSFaB/ZWP+F018YxHvI/6IS1EI4LIgHddP+QDuqsGyky/8rUo2e5Di5CZa+VLzJaCIS1GZpZ1Xe2oRCfJqDLsR2lCJboNFwypYTOjm7xgKM/pdppqtMzoJiwYqq6nBFctU4LVqJkhTqSSuY/GgR42M0D1WTCkxmqEWNlPh7PfzhLYCuCxHjAzYqk3EEmUW6nmPYQ40qNmRjFZxRDtKR7okTJjmaBiqLoeD0x7iYd6xJL4pnki6IohLeTQFUNqnMwgJ60YqtxYYL9nmOjAOrSX2cVplecnw1P732EcX5wOy+jydBhFJjJ5WcaVmYdBcovasmlXb1PJkqFUxpNL0LeZbeEl2dD6iNyBEhGclXE3usvMwmwv++TqbdfU5/qCzCyh8Ln95O2rd5qhEV81P/r1LL2wSEL87fSp2xB/62KO3Se/M8tYfH719vPfampwht/eTk9/9737/+b41vUmeni9i/79W4PpP7k9tvtXr950f9B+fDb97WJixdXPB/EwvmWufnrruUaf02fDJsvxT/ZXw+PWILuVxtSV5LvQpTP8pePvg9mr1yzOrPTpW1NFOhf2X7/2o5Pmwx+/9sMfDo5f+eHFIPn+4GjiLDmgLLkLtaTg3JS/UW9JGgGpQJJGVPkTkEfAjBGQhfTMmrEW1OkAkEWwjFHLKQKSniAGinbCXfmixWDcqmXUMZS4wO+pt3tZRl67OMKyk758HHZdCaPuJa1xpBuRbi6q4iIrzfDs4jIeZqen+bA6yS6GJro4N0mSX56ez5c9rEj3bkasSM+kxuARDC/SgUQEDoov0m+K4ub2+qNZFmoh6ObZpvro7uDf7P2b24Pa/sMXP17OjvvL2XA5K+y+cjXu7q94bD+NbqV0/3qkpQzfUgJN/NFz5phr3pdee/30tcHu5eXFH//kZHD0+muXFz/+8SuvvXryw0EZ5dHgeHD/lX/7v/1kcPe1V89ev/jJxeDo4XhgXGv/5kMy71F/bcTFDAFnwt9ZA5bMLvbtNweAphYED75oprNbQCYYzTyKUh+Ve1AqAWUzkIU0cjOWg5LNQBbbIJuR9ARRqVfZvBisW7VMSoYSF3g+tWyOTVudFZKd9OXjsOuSzd1LWuNIO93cJod7LquiTqtNC70qilbpbb6sSgl41W1898qqlMQzHvFeyqqUEI0IIgNe2lVWpQTKTFL3ITyVCJkJaZGgJMuqlBiZqeh1laISnSTtzLAfpQCV6DZdVqWFzYxuPZdVadEyo5u0rOp6SnHVMqVYjZoZ4kSqmPtoHOhhMwNUr2VVWqxGiJX9dDj77SyBrQAe6wEzI5Z6w5CYzNAbBi1qZhTrsaxKi5QZyyRlVddzimkv8VCPWBLfNE9ES1mVEnLwsiotTmaQE5dVuTnFfs8w0YHd3oxNTJZV5TKeXILhMzZAIoKzMe5Gd5MZG6ClDN9S/G1nkIzNvJ6p95wN0NiCk8s+ts5AJqFzNkAqAXM2QBbSY2PGclA7diCLbcjZIOkJ4pJod9p6wO84LQ74W8YPQ4kLPJ96C2YlYEvOBslO+vJx2LUu6RFnSWsc6S2+jxCTpU6F1Bg8guGFM5CIwEHxhTOvov1/iPsIwKUz/KUTKHnu6gW/jwC0pCBY8WV6y30EIBWMTvfxuAflEVCkA1lIdQJjLSiRDmSxDSIdSU8QA3sV6YvZvlXLsGYocYHfU4v0zGQt9xGQ7KQvH4ddl0jvXtIaRzpwYRUlu9tmAlYRPc2Bh1Yip5mFVUrAzKwzVzZvoLBKSTzjEe+lsEoJ0YggMuB1FlYpga66YGBhlRIhMyUtUJMthVVKjMxk9LpKUYlOknhm2C/Nc+P3ZXtqiEGqq+JolHnP+/f1uJkxrufyKi1aZoyTlleV1+VV5LDe+3rUzEAn0sY3HuoySfJR5W1TdKCHzgxV8hKrJLN405jo2nmoR2yEiNnPibPizhLYCuCxHjAzgqk3EIlpu9CsRc2MarJCq6JKRwlVaKVFyoxtkkKr8rrQivQXD/WIJfFO80RUaV5UlRnlVLmVEjim3CqpoiI2xSj16rJjPVpm6BMXXZU7S1ArYCc6sI3Ozc6L4uwiHZ7GZTnMcpMMT1K7j82qk/P4ND85L83ZjA+5fW3Zv6u3sGTRVSXjySUYPncEJCI4N+Nugn/ZDG13yYLFpPg/mm1n/VNCZrVYbpbI5y47MXQDRZpszuynnjTJh+anfNa5C7WO4VuHvw310diF0hCcEQo2qUSa5yUoFUhuJBo5yXaTyj0olYDpESAL6QktYzlMVo2K3Lsie1AuwZIkeTUymY/fPpafwNuLdoJdWZJqcaRODmc+wBIXeED1Jodc1CMsN+kbyOHWlSPpXtAaR3qLC5kSopApmW9+BcbgEQwtRqFEBO6JK0a5pTD/AxQyQZfO8JeOr5TZqxe4kAlqSUGo4ot1spAJSgUi1v2FTFAewZQ6lIVUJzDWIktTH489KI9gKp0sZcLSE0TBHkW65TTTdPNPfMQPsMQFnk8t0ttKmbDspK8fh127TOcsaY0jvcUXdZOR129Zmd42mNBrDB7B8DIdSETgoPgyfVMXdaGWMnxLCVTxd/eiLtTYgvDBF85UKRaUCUY3Uxd1oVQCSmcgC2nsZixHWhRmFBlKPwPJbIN+RtIThKde9XO8EFv0KGsscYEDVOvntvu6WHbSd5DDrks/dy9pjSMd+CoApYiTVnrJKr1NXwVQA151G9+1qwBq4hmPeA9XAdQQjQgiA17H6Go1UGYhZR/6U4mQWTQp0pXEVQA1Rma55LqCUYlOUhrJsF9aJOnI+CDuqSFu+CqAHjczxvV6FUCPlhnjZFcBLJzFVQD7KXkVQI+aGehE2vjmVYAyzYm+7Qd66MxQpbkKkMdJat9D/1UAPWIjRMx+TpwVd5bAVgCP9YCZEUy9gWiuAvjvnR7pUTOjWm9XAfRImbGNfxXg2l88aPEXD/WIJfFO80RUJi6KOBmV3oeiVgNHXQUwaVZGxINxrEfLDH3CqwDu6ViCWgE70YHd3rROSlwFSOYnn2yeXILh0zpAIoJzM+4meJNpHaClDN9S/C3pdzqtAzS24FSzj201kEnotA6QSsC0DpCF9EiZsRxpmRqrDYyPzB6UzDakdZD0BOFJtHXtSuukixwAPXEaS1zgANW7sva0DpKd9B3ksOtK63QvaY0jvcW3F1Ly9kImNQaPYHj9DCQicFB8/cyrf/8f4vYCcOkMf+kEgp67esFvLwAtKQhWfLXecnsBSAUj13087kF5BNTqQBZSncBYiyzzCp49KI9tkOlIeoIo2KtMzxaajp5wjSUu8Hxqmd5+ewHJTvr6cdh1yfTuJa1xpLe4401K3l4wUmPwCIaX6UAiAgfFlelhO95ArWP41uErYR+NXSgNgTPmy1Cy4w2UCkSGkh1voFQCKlEgC2koZCyHMeXIJN4V2YNyCaZG6Y43WH4Cb9+rHDUL7UJOwT3AEhd4QLUcpTveYLlJ30AOty4x2r2gNY60/d8fPr+q1ugv/KBNdfZ8N8C7yFZv5i18i9Ks8g11NyAfeQHfUQNe9SJ93A1YnALO8v3fOpu1//1sdl3gqTtlvXrr6m2nHuc3AeanidOvnF68/mHGBQEl+4zHvpcLAkqIRgSRAe96VsDInc3+ekhVPigBr7rn9S8KuMfiMwv2Kx/Ql9RAmZWVfOnZdl9AiZFZU7muplSik9RPMuxHnVkq0QW5KpAW1SjxHlrs64EzY578rkASU2en39ejZcY86V2B/PquADlT9L4eNTPwiaQz96D6QA+bGbHk9wQorId6rEaIlf10OPvtLIGtAB7rATNDl3pXQTuLIz1oZhiTXRCgHcUDPVJmMJNcEMivLwiQTuKhHrEkwGkeCMrItRoy5moAhfNYj5MZ48SXAvKdJagVsBMdWIf2/CJO8vPLy2GanEcus3IxPImjZHge53l8chadnlbzeELuW1t28uq9K3kpoG2Gn4cnl6Bvh9vCS7LL9RG5AyUiOD/j7n4/en5Xu6x/ab7X7GwfX71t97aPBt9b/Naz6W+v/q/p4+mXswSLKyJ6f/rXvz+Io6gpXh/8z/ebz188ef2PB/deP/kPgyjO8sGLr/3wh3988eqA/Q8ufudzV6RjN9xfzrfWTebm8+aW/uDqZ823n/pW4i50JQx/JfjbXB+NXSgNwblkj5tfICFIfib2O617UCYB0zNAFtLDYcZqUFtuIItgiZk0y0aF8RHcxxIURBbR9rL1IN9xWhzk0xObscQFHlC/hyJX9QhLTvr2cci1rugRZ0VrHOnAXZq8a2q1bPtMr3SV3uYzMUrAzAMprhbdVCZGyT7jse8lE6OEaEQQGfASbiZGCZh5nNWjGFUCZR5hSUQmnYlRYmQeXq0rH5XoJAdVDPtRslCJbvOZGC1wZszrOROjRcuMedJMTHmdiaEHOOtRMwOfSCpzDzAP9LCZEavXTIwWqxFiZT8dzn47S2ArgMd6wMzQpd9FtGVitKCZYazHTIwWKTOYSTIx5XUmhp7arEcsCXCaB6IlE6OEHDwTo8XJjHHiTEy5swS1AnaiA7u9mRhDZmIqGU8uwfCZGCARwXkZd/fLTYx8FzMxwJUw/JXgb3N9NHahNATnkD1ufoGEAmdigEwCZmKALKRnwYzVoLbcQBbbkYlBEhREFtH2sisTUy3O7emp0FjiAg+o30O1ZWKQ5KRvH4dcVyame0VrHOnAmRhv9dTtJI5a6WWr9DaeidECZh5IcbXohjIxWvYZj30fmRgtRCOCyIDHvROjBcw8zupPjGqBMo+wJCKTzMRoMTIPr9aUj1p0koMqjv3yJKNmaGghhknHlIa8F60Gzgx8/aZj1GiZgU+YjomjZTomJoff3tejZkY/kV5eNXee5GlUjQrvCfyBHjszdslzMmkWx5khEzNqwEYImP2cOCPuLIGtAB7rATMjmX5T4RIz3uh7pAfNjGrCxIxJyMSMGikztgkSM0t38aDFXTzUI5bEO80Dkcd5lCWjsvLhrtW4MdmZLKrSIiNTNGqwzLgnTdHYZ2MJagXsRAd2e1M0OZWiidunXN7gySUYPEWDJCI4SONui7kZk+9giga5Eoa/Evz9r4/GLpSG4ICyx10xkFDYFA2SSbgUDZKF9JCYsxpFmY8q4+OyB+USLlFjolHmVVr7WIKC+CLaeHYkauLFGOy4ZbI5lLjAD+r3VC2JGig56TvIIdeRqGGsaI0jHThRU/joWUWbtNKj7+Tz0EqUKjNRowTMPKriKtJNJWqU7DMe+14SNUqIRgSRAY97ZUYLmHm81aMkVQJlHmlJpCadqFFiZB5mrSsilegkB1cc+xW5jbI+iHtqiJtP1GiBMwNfz4kaLVpm4JMmaq6nncct087VqJnRT6SXb5y+llGaJ6PM+3wc6LEzY5ciUVNEpizoRI0WsBECZj8nzog7S2ArgMd6wMxIpt9UtNygUYNmRrUeEzVapMzYJknUXA87p93FQz1iSbzTPBB5XiVJMYq9Nz5qNW5QoibLiigb+cckHevBMuOeOFHjRp37XcREB3Z7EzUFmahJZTy5BMMnaoBEBAdp3G0xN2/yXUzUAFfC8FeCv//10diF0hAcUPa4KwYSCpyoATIJmKgBspAeEnNWo8pi4nR0D8plOxI1SIKC+CLaeHYlahaDreOWWeVQ4gI/qN9TtSVqkOSk7yCHXFeipntFaxzp5diZOXOna0OOnfFukqzEzVr4FmWxyjdU5qbyh7c7asCrbqSPzM3VG1ZU/K7J4XzqS9O4Sd4uFePSM4+a+eCfNZ993YyldtLydytTqhvd6iN+V0084xHvJWmjhGhEEBnwrm/X+IDuqoEyj7h6lKVKoMxjLYncpJM1SozMA611haQSneTwimE/r+321OjC5GkKQzTJ3NcDZ4Y5eZ4mK1I6T6NFywxz0jxNdp2nIecx39ejZsY6kVy+8UCT/c3UsDMhbPajQfc3U2M1Qqzsp8PZb2cJbAXwWA+YGbr0OwnSWRzpQTPDmCw7QzuKB3qkzGAmyc5k19kZ0kk81COWBDjNA0H3N9NCxiRm6P5mapzMGCfOyWQ7S1ArYCc6sA7t6UWRnxaX0fC8TOJhZnfAw5Po1AzPs/PqNCrLuLyc8yG3qi2bd/V2lczJGBlPLkHfpraFl2Rj6yNyB0pEcGbG3fB+NN+mPrv6qd3hvut2rk2N4fR3fzQvR/zHZl/75/bXX9hfbzQljW6vO//pb9wO+aPpr6bvD+0295PpL6YfTv/WfvyH6Sc+A92FGsjwDcTfddq9e2OQZZro21v7xXnB9Lf2v0+mnw2mf23t84X99aVLOv1i+nEcuUzS46s3ru376OpN95sfR4PpJ4PEuG9+5jPXLtRcgqNIwd6XoPISlAokGRP56/DuQZkETMYAWUgPgjmr4WOxB2URLA3jbpV6I+M+lp8gooi2lV1ZmMWo+JgcFX+AJS5wfeq9E7moR1hu0nePw60rCdO9oDWO9KwIKUsKUxTxME3Oyq0pQipH3mIrK3hzqTF4BMMLXiARgXsSCd7rmiAyizPTan9rv/E7J96mXw9qd1s2iaKHThend44HeRRdvVOZphLJ/synrnrI/u3Phtdqz2eyu1CTGb7JBBJ4xWqtCbBHtwbfv3j95Ecng4OT10/+7M9esfsDJ5EH0w+s7n2rUclOGr/4Yh4lC3vmd45vLQxqfzmb3pIYdRdqVEG04Avlq59dveWj8hKUCkQox6My81G5B6USUCkDWUijNWM5KKUMZBFOKVc5cbK3jyUoiEW9SuV8oazIueQHWOIC56eXyuSqHmHJSd8+Drkurdy9ojWOdKOVE2MuktMLM6zOTq2uPjXJsMzOk2FWpVmclPFZWc2da1itnPqMYbVy+2RKjzF4BMNrZSARgX/iauW/d3qtOfRt7rD/VyuDv2hEn5V5g+nHu2n6R067xelgLuweNWfEXlVzF0re8MnzVe/g7sXrFz9+5SeDu5bpIMrmp7jWCs1Rb1Mg9i1d+vKrPua7UOYC78yXpi1nuEAqEGkajSJKmgKpBJSmQBbS4MhZDh+LPSiLYNI0K4j7zftYfgLP36syXQyVjlvGhEOJC3yfWpmSi3qE5SZ99zjcuoRp94LWONKNMM0vyyi/PI+Gl0l0OczO8mpYnlfV8OziIovy9PIkyuZRIqww9T4BVpiWUmPwCIYXpkAiAvfEFaa/tILrbXccuWyw5L6cPmmOC99orm02jZZmh7i/dkn46SfTX00/sL8+nBc23D8amngw/YXPIHehBjF8g/DFqo/GLpSGwPv2ojyBVFDK0185eQ/KJaD0BLKQhj/OevhY7EFZBJOeZTkqqUNRJD+Bb+9VepYLpUKOCD7AEhc4P7X0JBf1CMtN+u5xuHVJz+4FrXGkA3fb9F63tmKyaqFXRfkqvc3f2VQCXnUa3707m0riGY94L3c2lRCNCCIDXuedTSVQ5sUXgfLsurOpBLqqLaF3NpUYVzUj6M6mEp3kSgvDfpQOVKILcmczT0eFt5BsX4+bGeV6vrKpRcuMctIrm9X1lU1yIOt9PWpmqBNpY+5NpwM9bGag6vXKpharEWJlPx3OfjtLYCuAx3rAzMil3jaQvuJIj5kZxHq8salFygxlkhub1fWNTdJHPNQjloQ3zfPQcmNTCTn4jU0tTmaIE9/YrHaWoFbATnRgtzf3Qez+bidJJOPJJRg894EkIjgf42538bkPpEEM3yD8PaaPxi6UhuD4T7ADJXMfSCqhcx9ILuFyH0gW0vNXznr4WOxBWWxD7gPKT+DbRfu7jtxHEs2PyhNyCu8BlrjA+ak3MS25Dyg36bvH4daR+2AsaI0jvcX14BV1dzKJpcbgEQwvPYFEBO6JKz37rQdHkjd88mvLTCANgaftRWYCqaBkZuajcg9KJaDKBLKQRjrOcvhY7EFZBFOZLcXdUH4CN96rylyMP01aBtpCiQt8n1plthR3Q7lJ3z0Oty6V2b2gNY70fEzQmSmLk3KYX2YXw+zk8nR4em4/VCd5EcXl2UmRnL28AZWZ+oxhVWYiNQaPYHiVCSQicE9clfn+skjnydVP7eduHs+jb/dds+Lz/WaCjyvyaebsLrrVfbzss9Z8Xd+r4jSKosPZl/bTP3C/Stdfwmesu1BjGb6x+KpU1pvjRmuOFTteW+yWs9bVO7H7UC77ccyte2vgOtw9txm4vio5SNNBswNoILXuAXah1hYEEIF4/sq7J30JygSknf3Nqe5BqQTUzkAW0vjNWQ4fiz0oi3Da2eksor0dlKAgOvUqnpOF1iLnbx5giQt8n148k6t6hCUnffs45LrUc/eK1jjSW9zQuaKuRs5H+gqMwSMYXj0DiQj8E1c9h2/ojDSQ4RtIoJg32tAZaS6B2xdIXvq8GEgFpHkLH5N7UCYBJS+QhTToclbDx2IPyiKY5G1p6AzlJ4govSrexRDGpGWsJpS4wPWpFW9LQ2coN+m7x+HWJXi7F7TGkQ57ITPxOiIrYbNWejfum278QqYW8KrT+M5dyNQSz3jE+7iQqYVoRBAZ8JLlhcyR0/m/Hnofpl01YOb1FoH+7LiYqQXKvNPCV5ctFzO1GJm3WdbVjUp0kpsrDPtRelCJLsjFzLZhmmrgzHDX781MNVpmuBPezEyuh2kmLcM01aiZMU8kkrk3mg70sDMhbPajQd/MVGM1Qqzsp8PZb2cJbAXwWA+YGbrU+4e2YZpq0Mww1t/VTDVSZjATXM1Mrodp0k7ioR6xJMBpHgj6aqYWcuirmWqczBgnvZqZuGGafscw0YHd2txLEpFXM42MJ5dg+NwLkIjgpIy78d1A7gVoIMM3EH/3GSz3QvViR1pMcAYp2P7S6RcglcDpFyCTgOkXIAvpETBnNXws9qAstiL9guQnCCqinWVX+mUxfjFpmacJJS5wfertU1v6BclN+u5xuHWlX7oXtMaR3t55mlbzeutvrebNpcbgEQyveYFEBO5JpHk3PE8TaTLDN5lIBXvNtJnJmUjzCeICXxLTkzORVCCSmJ6ciaQSUBMDWUjjMmM5KE0MZBFOE7dMzoQSFESdXkXxYs5i0jI5E0pc4Pz0orhlciaUnPTt45DrUsXdK1rjSG9vpxSrilOfMawqLqTG4BEMr4qBRAT+iauKe+6UAiRv+OQF+pa6HMqao3nL3Ur9IKKPcIHmELhsvl5tOcIFUoHo1ZaOK0AqAfUqkIU0YnKWw8diD8oimF5t67iC5CcIB73K1cX0xaRlnCaUuMD3qeVqW8cVJDfpu8fh1qVWuxe0xpHe3pbSVq16nwCrVkupMXgEw6tVIBGBe+Kq1QAtpYEGMXyD8BWsj8YulIbA+/aiPIFUUMqTbCkN5BJQegJZSMMfZz18LPagLIJJz7aW0kh+At/eq/RcTF9MWsZpQokLnJ9aera1lEZyk757HG5d0rN7QWsc6cC3N6ki2KqVXrlKb/O3N5WAV53Gd+/2ppJ4xiPey+1NJUQjgsiAdz1O81b77U0lYOYVGIEC7bq9qQS6qjGhtzeVGFe1I+j2phKd5HILx35R7s9C7akRhrnBWVq3XPmA7+uBM0Oe5gZnMqq8aL+vR8sMedIbnNezNZOW2Zpq1My4JxLKN8wdmSweFbkP+oEeOjNyyW9xmigpSqKk6FCP1wjxsp8SZ8OdJbAVwGM9YGYYU+8lWm9yakEzQ5rsJqfJi1FO3eTUImUGNslNzushm7SzeKhHLAl2qgeiKu2Ll3kfiVoNG3ObM4/S1IzK0of1WI+VGfPENzrdsE2/g5jowG5vZiSmbnSmkYwnl2DwzAiSiOD0jLsZxmdGkAYxfIPwd6A+GrtQGoLDQcG+lMyMIKmEzowguYTLjCBZSE9nGesRj0zlXY89KJNg2ZEqGiVe8bCP5Sfw76JNX0d2JF3MZ0xbBm5CiQscoHpH05IdgXKTvn8cbh3ZEcaC1jjSW1xGHlOXK9NYagwewfDyE0hE4J648rPfMnIkecMnz5ea0sJxH+1dKG2BZ+5FmgKpoKRp5qNyD0oloDIFspBGRsZyZKPEeF38HpRJMGWalaPEm4Pax/ITuP5elelipmPaMqQTSlzg/9TKtKVkHMpN+v5xuHUp0+4FrXGkt7jtR0xdcEwTqTF4BMMrUyARgXviKtNtaPuBNJnhm4yvZ7er7QfSfIK4wNfFdNsPJBWILqbbfiCpBNTFQBbSuMxZjsqMTEUpYyCXYMo4rqpR4i1j2ccSFMSeXqXxYmBj2jKCE0pc4ALV0rit+QeUnPQd5JDr0sbdK1rjSG9xG+iYuk6ZplJj8AiG18ZAIgL/JNLGQdtAIw1k+AbiK2EfjV0oDYE75ivSlpNaIBWIIiV7MyOZBBSkQBbSYMhYjSIjRmvvQZmEk6P5KKVKCJD8BN6+VzW6mKaYtozHhBIXuD+9GqX7M0O5Sd8/DrcuMdq9oDWOdOALllRRQNZKr1qlt/ELllrAq07jO3fBUks84xHv44KlFqIRQWTAu3HBMvMB3lUDZt5MEWjQjguWWqDM2yh8hdlywVKLkXkPZV3tqEQnuXPCsF+ajYwP4J4aYJD7lXk2Kry3N/b1uJkBr9/rlWq0zIAnvF6ZXg/ITFsGZKpRM6OeSCavmjtJUkMcSx/okWdC5OynI87TuBzFXryHerxGiJf9kDgb7iyBrQAe6wEzY5h6I5Gno8IrOo/0mJnhrL/LlWqkzKAmuFyZXo/JpF3FQz1iSaDTPA9JXJUj/1Ncq1Fj7lbGlSmTUeJ9Jo71WJkBT3q3MnXTMv2GnejAbm+aJCHvVhoZTy7B8GkSIBHBwRl3H7yBNAnQQIZvIP5m1EdjF0pDcE4o2KLSaRIglcBpEiCTgGkSIAvpMS1jNZKM6MKxB2WyFWkSJD+Btxft/7rSJIuph2nLGEsocYH7U+9u2tIkSG7S94/DrStN0r2gNY70rJ794syUxUk5zC+zi2F2cnk6PD23H6qTvIji8uykSM5e3oAYpZIqudQYPILhxSiQiMA9ccXodWX2EytHH1+96W5cfns++SM3luaZ/dJlapwMfbbQqR8v55E3X9f3qjiNouhw9qX99A/cr9LVaPuMdRdqLMM3Fl+Yrtb/t2arHt0ob1+x47XFbjlrXb0Tuw/lsqa9vYwdaDtBOBCo4a+87/5LUCYgMewPZPegVAKqYSALaTRmLEc6Ksi+I0AmwdRwZrJRSdWwIwkK4k2vcngx7jBtGWAJJS7wf2o5nLn7nZQeRpKTvoEccl16uHtFaxzpLe48kpD3OwupMXgEw+thIBGBf+Lq4Z47jwDJGz55vr710diF0hC4WoHUpA9egVRAWpPsJAKkElBrAllIIx1jOWLiYHIPSiSc1GxpJILkJ/DkvSrNxajCtGX2JJS4wP3plWZLIxEkN+nrx+HWJTS7F7TGkd7iDssJeVmylBqDRzC80AQSEbgnrtAM0GEZaBDDN8ja4hNIQ+B9exGfQCoo8Ul2WAZyCag+gSyk4Y+1Hiam5CeQSTD52dZhGclP4N97lZ+LcYVpy/xJKHGBA1TLz7YOy0hu0vePw61LfnYvaI0jHfh6JHVyWbXRi6NVepu/HqkEvOo0vnvXI5XEMx7xXq5HKiEaEUQGvGR5PXLUOn9SC5h5tUSgQruuRyqBrupM6PVIJcZV/Qi6HqlEJ7k1wrBfkpf+oqo9NcIg9yPb5k+qgTNDXs8XJLVomSFPekHyev5k2jJ/Uo2aGfdEQvmGU4iShNSNB3rszNCluCJpX0NjRv5eiod6wEYImP2cOCPuLIGtAB7rATMDmXo30TaBUg2aGdR6vCSpRcoMbZJLktcTKGl38VCPWBLuNA9EHEV5bIjtSK3GDbomaZIkjUap100c68Ey4574nqSbQel3ERMd2O3NkKTUPcmsdSLSTZ5cgsEzJEgighM07oYYnyFBGsTwDcLfhfpo7EJpCA4IBXtTMkOCpBI6Q4LkEi5DgmQhPaFlrEc2ivxKYA/KZBsyJFB+Av8u2vh1ZEiyxcjCrGUGJZS4wAGq9zQtGRIoN+n7x+HWkSFhLGiNI73FleApdTNyfkdAYAwewfDyE0hE4J648rPfSnAkecMnz5ealuzz/IUTKW+5u44feH3aLtQWAnfdi14FUkHp1cxH5R6USkC5CmQhDZeM5YijUeHXc3tQKsH0aktBOZSfICD0qlcXgwyzlsmUUOICB6jWqy0F5VBu0heQw61Lr3YvaI0jvcWTKVPq5mKWSI3BIxherwKJCNwTV69uw2RKpMkM32QClbtVkymR5hPEBb4wpidTIqlAhDE9mRJJJaAwBrKQxmXGcthAOMpKShkDuQRTxm2TKaEEBbGnV2m8mGOYtUymhBIXuEC1NG6bTAklJ30HOeS6tHH3itY40lvccjmlLltmqdQYPILhtTGQiMA/ibRx0JbLSAMZvoH4SthHYxdKQ+CO+Yq05agWSAWiSMmWy0gmAQUpkIU0GDJWIy6LUeF163tQKuH0KN1zGcpP4O57laOLSYZZy2hKKHGB/9PLUbrnMpSb9AXkcOtSo90LWuNI2//9YaPC5q+rU5k/aJOdPV/GpARn1sK3KG/cNQ10GTOJqMuYWsCrXgRzGfPZ9Et3ftfkxd+bfeOpKw5oLlkO3LHr81nz5jLmE1e1uvxTVnJ+5Q5f/2b60Vx4ii90fm6hRLcS103X/gXUCdxdtSUzniX7uN2phWhEEBnwvnW78/3pP1DDL7WAmZdiBDKX6qWsRci8AcNXry3XOrUYmXdf1tWlSnSSey4M+3ltt6dGF+RKZ27lRu69LbKvB84MnPIrnXFuDHFW9309XGbkFN7pzK6HXmYtQy/VqJnhUyTAPaVHxHVONexMCJv9bFBYD/VYjRAr++lw9ttZAlsBPNYDZgYt9d6E9hZHetDMOCa7ydniKR7ooTLDmeAqZ3Y975L2Eg/1iCUhTvNEUG9drYaMucVJ4TzW42RGOekFzswNuvR7hokObIO2OjmtoigdmtMsHWbVSTEsT09cCVOeJ2VksvPiYsaH3P62HAiot8DkBU4j48kl6Nsot/CSbJZ9RO5AiQiO4bib6PdnKZbr/esy/QLKuQDNY/jm4W87ry30+fTpt4cuuc5NixOIWY399LPB9K+tfb6wv1ztkbvvGkfPjQma5bQeXb3pfvPjaDD9ZJCYAZUQ2YWaS3C2Kdj00rkdIBVIbofK7AB5BMzsAFlID5YZa0HttIEsQiZ1/Of/+1h+gmgi2lN2JXUWcxezlkGaUOICx6feOLUldZDcpO8eh1tXUqd7QWsc6S3uVpKR10VzqTF4BMOLXSARgXviit0A3UqABjF8g/DlrY/GLpSGwPv2IjuBVCCyMyJap92DUgmoPIEspNGPsxw+FntQFsGUJ9nTYh/LT+Dae1WeiwmHWcvMSihxge9TK8+2RiVIbtJ3j8OtS3l2L2iNI73FI9wz8uJnITUGj2B45QkkInBPXOW52RHuSGMZvrH4qpS68ike1p4uh7X7LLMLtYzA2QuELllUBGQC0bnxKKJOWIFUAupcIAtprGUsB6VzgSyC6Vx6jPc+lqAgkvQqdBcTFrOWkZlQ4gLfpxa6bcPZoeSkbx+HXJfS7V7RGkd6i1vyZeQ1zlJqDB7B8EoXSETgn7hKt+eWfEDyhk+er1x9NHahNASuViAz6fNUIBWIzoxGifFRuQelElBnAllIIx1nOXws9qAswulMqufaPpafwI33KjMXkxSzltGYUOIC36eXmS2N9JDcpO8eh1uXyuxe0BpHOvBoTOOjZ3Vj1UKviuNVepu/jakEvOo0/uU2ptaSGc+SvdzGVEI0IogMeCn3NqYSMPNii0DRkgenSoSrYhV6G1OJcVWFgm5jKtFJrqow7EcpSyW6cLcxSx/wfT1wZuDs+zamFi4zckpvY15P2MxaJmyqUTPDp0hvc+8wHehhM2NVr7cxtViNECv76XD221kCWwE81gNmBi31VoT2Fkd60Mw41udtTC1UZjiT3Ma8HqxJe4mHesSSEKd5IlpuYyohB7+NqcXJjHLi25hunKbfM0x0YLc3eWKo25gmkvHkEgyePEESEZy6cTfR/SZPkOQNnzx/U+mjsQulIThAFGw1yeQJkkrg5AmSSrjkCZKF9ACXsxw+FntQFtuQPIHyE7hx0WauI3liFkMWTcvUTChxge9T71hakidQbtJ3j8OtI3nCWNAaR3qLi9ENdQ3SxFJj8AiGV5lAIgL3xFWZmy1GRxrL8I3FV6W9F50jLSBw6gJBS+VOkEwgepYuOkdSCahngSykMZWxHJSeBbIIp2dbis6hBAURo1dBu5jCaFrGakKJC3yfXtC2FJ1DyUnfPg65LkXbvaI1jvQWN/Yw1PVKk0iNwSMYXtECiQj8E1fR4ht7IA1i+Abhq1YfjV0oDYH7FUhP+iwVSAWiPenGHkgqAbUnkIU0+nGWw8diD8oimPZsaewB5Sdw7b1Kz8WQQ9MythJKXOD71NKzpbEHlJv03eNw61Ke3Qta40hvcf9kQ113NKnUGDyC4ZUnkIjAPXGVZ+j+yUjzGL55+Dp0s/2TkeYS+Pxe9C6QCkTvUgetQB4BxS6QhTTgMtaCErtAFsHEbkv/ZCg/QTTpVewuZiialqGYUOICx6cWuy39k6HcpO8eh1uX2O1e0BpHOvCty9xHz8rXrJVeskpv47cutYBXnca/3LrUWjLjWbKPW5daiEYEkQGPOwNTC5h5gUUgZ8nKASVC5m0VvkptuXWpxci8prKuAlWik1xJYdgv | I1: MaPS6yP31AjD3LxM8lHl3aLs64Ezg2fPNy/VcJnRU3jz0lzPwTQtczDVqJkhVKS5b9o7LpNRTNy+VEPPhNDZz0eWFLEZGePDe6jHa4R42U+Js+HOEtgK4LEeMDOAqbclbfMw1aCZMU14A7Mqc/IGphoqM7QJbmCa63mYtLd4qEcsCXeaJyI2lX0mCm8kqdWwMbcwTZyYcpR792DHeqzMqCe9iWncXEy/h5jowG5vXicnb2IaGU8uwfB5HSARwUkcd2MdPK8DNI/hm4e/FfXR2IXSEBw7CjaodL4FSCVovgXII2C+BchCeubLWIu4jEa5d0H2oFRCJl1Som8RlJ/A1Ys2gF1Jl8WMQ9MytBJKXOD91LubtqQLkpv0BeRw60q6dC9ojSO9xbXtOXlbM5cag0cwvBIFEhG4J64SDVDbDjSI4Rtkbe0JpCHwvr1oTyAViPZsqW0HUgkoP4EspNGPsRzpqCy8bnwPyiSY+qyiUUKpTyQ/gXvvVX0u5hyalsGVUOIC/6dWn2317Uhu0vePw61LfXYvaI0jvcW9QnLyZmUhNQaPYHj1CSQicE9c9bnhXiFAYxm+sfjKNNjgSqRlBM5eIHbJSiAgE4jWbekhAqQSUOsCWUhjLWM5kmKUx9RRK5BKMLGbmWxUenO2+1iCgnDSq9pdzDo0LdMrocQFDlCtdlsbiSDJSV9BDrkuudu9ojWO9BY3YM7J65yl1Bg8guHlLpCIwD9x5W7PDZiB5A2fPF+++mjsQmkIXK1Aa9IHq0AqELHZ0oAZSCWg2ASykEY6xnJYh228JxR7UCbhtGY5Srz89rH8BK68V6m5GHhoWiZYQokL/J9earY0YUZyk75/HG5dSrN7QWsc6cB3Kb2bXqsdq1Z66Sq9zd+lVAJedRr/cpdSa8mMZ8le7lIqIRoRRAY87gRLLeBVzw68S6lEuCpYoXcplRhXlSjoLqUSneRyCcN+JvO7yD01wHBXKakDSi1wZuzs+yqlFi4zeEqvUl4PsTQtQyzVqJkRVCS5b9SipFVcjvz3eA700JkhS36VsqxMakbG+4Ac6vEaIV72U+JsuLMEtgJ4rAfMjF/qXUnbMEs1aGZI6/MqpRYqM7JJrlJeD7OkvcVDPWJJtNM8EWma5sko9T7ItRo25iplHBVZloxy71NxrAfLDHviu5RuqqXfRUx0YLc3qVJQdynz9uFLN3hyCQZPqiCJCE7iuBvrfpMqSPKGT56/0fTR2IXSEBwqCrafZFIFSSVwUgVJJVxSBclCeqjLWI44HRn/guxBqWxDVgXKT+DLRVu8jqxKvpiEmLeMtoQSFzhA9f6lJasC5SZ9ATncOrIqjAWtcaS3uFy9oC5L5u1TkTzG4BEMLzWBRATuiSs1N1uujjSW4RuLL017L0tHWkDg1AWqlkqqIJlARC1dlo6kElDUAllIYypjOUwxKkuiLB1JJZyobSlLhxIUhI1eVe1iGmLeMt8SSlzgAPWqtqUsHUpO+gpyyHXJ2u4VrXGkt7gHSEHdwswTqTF4BMPLWiARgX/iylp8DxCkQQzfIHzp6qOxC6UhcL8C/UmfqgKpQAQo3QMESSWgAAWykEY/xnKUo9i/HntQJsH0Z0sPECg/gXvvVX4uRiLmLTMuocQF/k8tP1t6gEC5Sd8/Drcu9dm9oDWO9Bb3Qi6oS5F5KjUGj2B49QkkInBPXPUZuhcy0jyGb561tSiQhsAX96JFgVQgWpQ6CQXyCChEgSykgZCxFhbWiDoIBTIJJkRbWiFD+Qk8fa9CdDGuMG+ZPwklLnB+aiHa0goZyk36/nG4dQnR7gWtcaTt//7w1kx//aBNaPZ8d9L7wlqJmbXQLKpolWa4u5PeNOUdNeBV5/HP9+7ks6u3WHcntZbMeJbs4+6kFqIRQWTAuzGH0usqd9WAmXdPBNKWTPMrETIvmvAVa8vdSS1G5g2TddWoEp3kNgnDfl7b7anRBbk4mSRpOopSH/J9PXJm5JTfnEyKkr45qYbLDJ3Cm5P59RDKvGUIpRo1M36KhPfNhIrf2Ad62JkQNvvZoLAe6rEaIVb20+Hst7MEtgJ4rAfMjFr6PYlJo1FpfKiP9KiZkUx2ZbLFVTzQQ2UGNMGVyfx6+iTtJh7qEUuCnOaRoF67Wg0Zc12Swnmsx8kMc9KbkrmbOul3DRMdWIf2tDo3J1laDpOTuBpmeXk5PDVuM5xn5fl5fH7eNCVyfMgNcMtJgHoTTN6UNDKeXIK+rXILL8l22UfkDpSI4PyNu43+aDXB4ra6TfJlXsQDSLYALWT4FuLvPa/TUZ9Pn367tN/u9j9eHENMf+sumE4/G0z/2trnC/vrS3fe8Ivpx3E0uHpzWerfGPjR1ZvuNz+OBtNPBokZUJmQXai5BOeagp0vndQBUoEkdWL/Idg9KJOAaR0gC+mxMmM1qA03kEXIlI7/9H8fy08QUkQ7y66UzmIYYt4y3RJKXOD69NunlpQOkpv03eNw60rpdC9ojSO9xZXtJXlhM5cag0cwvOIFEhG4J67iDVDZDjSI4RuEL3B9NHahNATetxfhCaQCEZ4tle1AKgGVJ5CFNPpxlsPHYg/KIpjyJAug97H8BK69V+W5GISYt0y2hBIX+D618myrakdyk757HG5dyrN7QWsc6UZ5pidnVXmR5kNzdm6G2clZMaziOB+WVXEWn53Fp+f5ycsbUJ7ePK9VnoXUGDyC4ZUnkIjAPXGVp69VyBMnMj1jG380649xs1GI/VNOqL5lRepzfUPyOCuj6KH7avqh/buauqeFim2++/70WXNM6U4yP73uUvL5/NufWR3c/F15FP2B++XfuN6F2tzwbc4Xt9SAzFs3WpF85CwxsEJ/1hPwSXN+++KLeZTY/z+85Uxz9U7zoXL9SG49txbTZ8PrE16f4XahhhOEFIGcJiuYgEwgapo+xgUyCSimgSykAZ2xGpSYBrIIJqbjMqqIrds+lqEgXvUqpxeDFvOW0ZlQ4gLfp5bTcZJkRD3BEZad9P3jsOsS1N1LWuNIN4L6LKnSJIlPh+dVejbMsiQblkkUDS/i06o6LeK8uJg/72EFdeYzhhXUpdQYPILhBTWQiMBBcQU1s81zlM3T7/b3mxx9c2GgS7HdhVrD8K3Bl7o+GrtQGgLnKxCe9DkukApEebb0fQZSCSg9gSykoY+zHD4We1AWwaRnFhHz+fax/AR+vVfhuZi7mLcM0oQSF/g+tfAkF/UIy0367nG4dcnO7gWtcaQDD9KsfPSskKxa6FVxtkpv85dBlYBXnca/XAbVWjLjWbKXy6BKiEYEkQHvxiBN6jKoEjDzWo1A0ZJHqUqEq2IVehlUiXFVhYIugyrRSe7JMOxHKUslui24DKpFzoycfV8G1cJlhk7pZdDrMZp5yxhNNWpm/BQJbu4NqgM9bGaw6vUyqBarEWJlPx3OfjtLYCuAx3rAzKil3ou0XwbVomZGsj4vg2qhMgOa5DLo9fxM2k081COWBDnNI9FyGVQJOfhlUC1OZpgTXwZ1YzP9rmGiA7u9+ZSKugxaRDKeXILB8ylIIoJzN+42GpxPQVrD8K3B32f6aOxCaQjOFAW7TzKfgqQSOJ+CpBIun4JkIT3T5SyHj8UelMU25FOg/AR+XbS968inFIuJi0XLCE0ocYHvU+9hWvIpUG7Sd4/DrSOfwljQGkd6i+viK+pGZhFLjcEjGF52AokI3BNXdv6zqItH2tzwbc4Xt9tSF480nCCkCOQ0lcxBMoGoabIuHskkoJgGspAGdMZqUGIayCKYmG6ti4cyFMSrXuX0YtJj0TK7E0pc4PvUcrq1Lh7KTvr+cdh1CeruJa1xpLe4xUlFXTQtEqkxeATDC2ogEYGD4gpqfIsTpEEM3yB8teujsQulIfC/Au1JH+UCqUDEJ93iBEkloPoEspBGP85y+FjsQVkEU58tLU6g/ASuvVftuZjzWLQM7oQSF/g+tfZsaXEC5SZ99zjcupRn94LWONJb3E66om5kFqnUGDyC4ZUnkIjAPXGV5wbaSSMtZPgW4kvRzbaTRppL4PZ7kbxAKhDJS5+3ApkEVLxAFtKoy1gNSvECWQRTvC3tpKH8BCGlV8W7GChZtEwIhRIXuD614m1pJw3lJn33ONy6FG/3gtY40mEvg6ZeR2Q1bNZKz6zS2/hlUC3gVafxL5dBtZbMeJbs4zKoFqIRQWTA404G1QJmXqsRCFqyfkCJkHmFRqJTycugWozMuzPrKlAlOsk9GYb90jSm5s9rEYa5EJq64rjUh3xfj5wZPXu+EKqGywyfwguhxfV00KJlOqgaNTOGikT3qr2LIskjMzLe20kHeuyZEDv7AakS+29nI+N9RA71gI0QMPs5cUbcWQJbATzWA2bGMP3OxLjTeONDfaRHzYxrsquhaZol5NVQNVRmeBNcDS2u54TSDuOhHrEk5GkeCZMUUWL3DN6HolbjxtwPjeOoNFk8yohbomq0zNgnvSVauJGhfi8x0YHd2hxPGpG3RI2MJ5dg+BwPkIjgQI67v95EjgdoIcO3EH9T6qOxC6UhOIAUbFXp3AuQSuDcC5BJwNwLkIX0/JezGlVFHCPuQamETMCkpY/fPpafwN+L9oJdCZjF+MeiZZ4nlLjA/+m3OS0JGCQ36QvI4daVgOle0BpHenuL3VPCbVk5mkuNwSMYXo4CiQjcE1eOBih2BxrE8A2ytvoE0hB4317UJ5AKRH22FLsDqQSUn0AW0ujHWI6sGhX+k6k9KJVg8tOpa0p+IvkJ/Huv8nMxA7JoGeoJJS5wgGr52VbxjuQmfQE53LrkZ/eC1jjS29u8xMpPb3rWys9CagwewfDyE0hE4J648vOfR/MSoM0N3+Z8hbs1zUuAhhOEFIGmJouPgEwgkpo+0AUyCaiogSykAZ2xGmlVjqLMR2UPSiWYoo4t1lFK1dQjGQqCVq+aejEGsmiZ7AklLnCAak3d3sEEyU76EnLYdanq7iWtcaS3txO1VdVe12VVdSk1Bo9geFUNJCJwUFxVje5EDbSG4VuDr3d9NHahNATOV6A+6RNdIBWI/GzpRA2kElB/AllIQx9jOcpkVPkXZA9KJZj+zKJR5Q1S+1h+Aufeq/pcTIMsWsZ7QokLHKBafba1o0Zyk76AHG5d2rN7QWsc6cA3OqmK1aqVXr5Kb/M3OpWAV53Gv9zo1Foy41mylxudSohGBJEBjzveUwuYeRtGIGvJQ1UlwlXFCr3RqcS4KkVBNzqV6CTXWxj2S1OiyemeGuEW3OjUImdGz75vdGrhMsOn9Ebn9YjPomXEpxo1M4aKRPeNG51VlEbFyH+T6ECPnRm1FDc6s6wyEX2jUwvYCAGznxNnxJ0lsBXAYz1gZgxT70zab3RqUTPjWp83OrVQmeFNcqPzetgn7TAe6hFLQp7mkTBpFVX5qPSqsVqNG3Wj04Zsu73OqRudWrTM2Ce+0enmfvq9xEQHdnuzLTF1o3Ne3cbmySUYPNuCJCI4kOPur8HZFqQ1DN8a/A2oj8YulIbgsFGwLSWzLUgqgbMtSCrhsi1IFtLDXsZylNmopLItSCrbkG2B8hM4d9HGryPbUi5mRZYtwz+hxAUOUL2nacm2QLlJX0AOt45sC2NBaxzpLa6fJ6pGrfaMpcbgEQyvPYFEBO6Jqz3/WdTPI21u+DbnK9xtqZ9HGk4QUgSamkr1IJlAJDVZP49kElBRA1lIAzpjNbKoGMW5j8oelEowRd1aPw9lKAhavWrqxbjIsmUCKJS4wAGqNXVr/TyUnfQl5LDrUtXdS1rjSG9xU5SYupVaJlJj8AiGV9VAIgIHxVXV+KYoSIMYvkH4ktdHYxdKQ+B/BQKUPtQFUoEoULopCpJKQAkKZCGNfozlMNGorLwLsgelEkyCtjRFgfIT+PdeBehiamTZMgYUSlzgANUCtKUpCpSb9AXkcOuSn90LWuNIb3GL6Ji6vlmmUmPwCIaXn0AiAvfElZ8baBGNtJDhW2htPQqkIXDHvehRIBWIHqVPRIFMAspRIAtpNGSsRhKlZuSVa3tQKsHkaEuLaCg/gb/vVY4uRjqWLTM6ocQF/k8tR1taREO5SV9ADrcuOdq9oDWOtP3fH8406VyIkYLzxxdnP3nltVc9llDoTap6IGuhWVTxKk3qZieNVaIhF5c7vWDvqMGuPmMthmXqxI+tRnzsJJ8PqNV02Qt7arQ3/BwNdz03V08Ovmc9l7l1kEX2Q27yWwdFEVEeTksnk9Mhq+W9HA4dh0PH4dBxOKQ4HOo5GDkHfg29pTB2FMaOwthRGFMUxnoK/JdA72cdldpRqR2V2lGpKSq1msqNixcdVGRP07HDf+zwHzv8xxT+Yz1+vqMX3saw8CcO/sTBnzj4Ewr+RAe/eZReDhm3yDsXphV+QlqfjVYVufxw76jh8l9bbuz6f5oKKtcT4NOrd6ePB00R1W9dQ4Crd+fnF980pxou4faO+8HmusSTQfMfG/V8BG3MMy7mKVmGjnk20iVlZT9YSPaD/TKNYvchcx8K+yGO3IfUfXC/G9sfTpPEfTDuQ2k/pO53U/dZ5j7L3GfGfWbcZ7n7LHefFe6zwv2lpfs3XMBN3T+eVu43qsLF35iKulqDhoi6NtY6Kx46Kx46Kx46Kx46Kx46Kx46Kx46Kx46Kx46Kx46Kx46Kx46Kx46Kx46Kx46Kx46Kx46Kx46Kx46Kx46Kx46Kx46Kx46Kx46Kx46Kx46Kx46Kx5SVjzUW9HIrSjy1mNnxLEz4tgZceyMOHZGHDsjjp0Rx86IY2fEsTPi2Blx7Iw4dkYcOyOOnRHHzohjZ8SxM+LYGXHsjDh2Rhw7I46dEcfOiGNnxLEz4tgZceyMOHZGHFNGHOuNyHdhaysPqzecMWtnzNoZs3bGrJ0xa2fM2hmzdsasnTFrZ8zaGbN2xqydMWtnzNoZs3bGrJ0xa2fM2hmzdsasnTFrZ8zaGbN2xqydMWtnzNoZs3bGrClj1mpjwrWPVTzOgsfOgsfOgsfOgsfOgsfOgsfOgsfOgsfOgsfOgsfOgsfOgsfOgsfOgsfOgsfOgsfOgsfOgsfOgsfOgsfOgsfOgsfOgsfOgsfOgsfOgsfOgsfOgseUBY/1FuTLFZX6sprLGXDiDDhxBpw4A06cASfOgBNnwIkz4MQZcOIMOHEGnDgDTpwBJ86AE2fAiTPgxBlw4gw4cQacOANOnAEnzoATZ8CJM+DEGXDiDDhxBpw4A04oA050BnxO/7n//KBNB/bXmyoZ0Vdv81YWGfkY8MAqNSCF944a76pAWrMz1W8Wea1ZjdXPXGuq6aeuBv7Z9Bur+96b/pOTerMGVb9tyuKfzZJcV++4blTTz5tCrc/sD7zj14uPm+sNM8V4y/3I7P7tZ/MrCp+7LliD77mrCtMv7OfLf+OWS5/9cvpR82dcYu2xy8kNpr+Yvm9RfzL9u+n7CwCj31/8C47MM/uPu3sSzd3e6Vc+899Vm39VTgHbWWkhGhFEBrzEdbMaDAdxmeS38nj61Wj6zejWIHXfHtnvJ1FmbiVm9v2XX37VR2dXTWf10Hv9ZlfuKf1sNPA/Gi+pgTJ7g0jSeWTPKy1GZlOQdRN1SnSrAnHNnlde2+2p0QXpdxXHo9R76r2vx82Mx4puVyXZ60oNlhmPhb2uynzZ66okBzLd16NmRmXRmcXNalO/sQ/0sJnRrPtkgIv1UI/VCLGynw5nv50lsJvbXS1gZuDSZ2opV3Gkx8yMYbL+VqSbeKAHygxkgu5WSxfxoMVFPNQjlgQ3zeNAvXK1GjKmsRWF81iPkxnghNt490QsQd3cNWvAOrRn5uK8ispqeHphzDA7vSiH5flpOowu7d95kpyfnp6YGR9yQ/2jE7rAUbmpJrfVhYwml59v691CS7L99hG5AyUiKEji7sv/m9v0NnfQH8/vP7k9tt2SvzkrNL16b9FE4LfNxthd+599TdalzloDtNSl2i1dRFVD3oUa0PANyN+2+mjsQmmsRvwWGoLtKl2fCqQCqU8lZn/egzIJWJ8KZCEtj+Osho/FHpRFuNLUZBQVPn77WH6CSCDaC95QJyulqYu5aGXLqDsocYHr0294qEU9wnKTvnscbq0LesRZ0BpHutGpFycX6flpFQ/zKjsbZqlrlZUWp0NzdpqcxHmZRcXFy+F1KlW/WkptweMXXqcCiQi8E1en/ropf33L6dNHVmy6JlhvXL199VdXf9nIze8tGq5+c/WeVaBWx/5+04k1NpFrtuQzwV2oCQzfBGsrTSANgbsVKM2uxAiQEERvErvae1AmAfUmkIU05jFWg9KbQBbB9GZBHGrtY+kJHHqvcnMxCq1smW0HJS7wf2q5Sa3pEZaa9M3jUOtSm93rWeNIhxttl7Tox6qFXRUXq+w2Xj6kxMtMVHLl3/+w5UNK82c88/dSPqSEaEQQGfBk5UMeLrtqLswUbI8SWQmUmXeVSF+6dkiJkZlyXVfUKtFJ0qsM+6WZf5bNnhpgqPIh/2ixfT1uZjzut3xIC5YZj6XlQ9ej8sqWUXlq1MyoLNLwq9bOrEMoiafjQA+dGdHkJURVkcXUWLRDPV4jxMt+SpwNd5bAVgCP9YCZMUy9zWkrI9JiZoYzWRlRmhLD0B7ogTJjmqSM6HpIHu0qHuoRS+Kc5nFIq7RMiDaDtRo2ppQotpvIKhtlVD2RFiwz4onridyIPL9/mOjAbm2ehrytXUUymlx+wfM0SCKCYz3uRh2Rp0GawPBNwN+J+mjsQmkIzin724QiCYXN0yCZhMvTIFlIT4sZq2Hjfz4iNr9IKgGTNf4OZ/tYegKvLtrodSRrqsUktaplNB6UuMAJqncxdLIGSk36+nGodSRrGOtZ40hvbwl7QqV2qvZ5Jh5b8PiFl5xAIgLnxJWc21fCjjSg4RtwbcEKpCHw1QLBSpawI6lApCpZwo5kElCqAllIYyVjNeIoS0fekuA9KJVgUjW2Uc17AW0fy08QDnrVqov5ZFXLyDkocYH/U2vVljp2KDfpC8jh1iVWuxe0xpFuWizfWqo091AHbFTkDRRWjiYtbIvqRkPpQJVGiR/vHTVeZk6TrSav3rp6u5lvbP9rNWFTbzSvC3KfvH31jhWXXzXtKe1/HttvvTf/cmB/0/3ko1mzS/tHn7kJHV85Ndl84QqWBq5eyf5lnzfS9I1m+sfj2Yy52Y83Y4a/NZPu2WJSc/Odp1d/ORq47pmDOL9l3F//VTOIeZDEg5YzVKV1M551+ygk0kI0IogMeMnAlQzZZfwnH9BdNVBmhlWgd6kZy1qEzHwqX8a2lAdpMTJTqesKVCU6SdqUYT+ill2LLkhtENV4YV8PmxlA5aVB7giaqg1So2VGUGFtUJUsa4MqcqzZfT1qZhwVyXDuo3Ggh80MUPK6ILq1kBqrEWJlPx3OfjtLYCuAx3rAzIil36GU6SgxPtBHetDMICYrCqIdxQM9UmYoE1QFLZ3EgxYn8VCPWBLeNA8E3VxICxlTEUQ3F1LjZMY4aTGQfSKWoFbATnRgHdrTyFRxVF4M8/zsYpidmHxYFbkZnlVJdpGdRafl6fw1JDfBLacC2o0wWQyUymhy+fm2yy20JFtmH5E7UCKCo7h19tJUbgaWiwGazPBNxt99sqw2aCZCufODR7PzA3fFaP6tq7esQQaURXahFhEcawq2uXRaB0gFktah6o+APAImdYAspGfKjLWg9tZAFsHyOcXIeCur9rH0BDFEtI/sSucsBixWLRMzocQFfk+9WaLW9AhLTfrmcah1ZXO617PGkW4EbpmXyVlxXgxP0yIaZvnF5bA6y06HaZVG1WV1cpJezB1rUIHr1fFW4GZSW/D4hRe4QCIC58QVuL9cydRYofbX07+z8vQ30w+HzQXwDxut+v70k6bM3Uf6LpS04ZPmS1QfjV0oDYF/7UVXAqlAdGVEHKPdg1IJKC2BLKQBjrMcPhZ7UBbBpGUctSR4kAQF/rtXcZktxEjWIi6RxAXOTy0u6VU9wpKTvn0ccl3ysntFaxzp2flpenoSl3E0TOPcStE4LodVdHE6PLtIqnNzVqZRMV/1oPIy9dnCyksjtQWPX3h5CSQicE9cefmROwd1Z6KuPmheSHT101kp0dW70981mnL60fQDb+nmXShdw6e7trAE0hD4VoGw7Lo4CSQEkZfxKDI+KvegVALKSyALaYBjLAclL4EswslLMyqoSnQkP4H77lVdmoUWMS3qEklc4AH16pJa1CMsN+m7x+HWJS67F7TGkV5Uomcz4k5cBaxEz3xsrXzMW9mWq2wDVaJn/tPUO2q8qy5kzUr0v7l61+V3p5+6zPg8G/5k+vj5avR1islnKfVnVz9bSTc/bpLuzZ/29cl8slqKnrRVnSstmfEs2UvVuRKiEUFkwLuuOrfCcXmn9eqvFwfLv513Hm3y/z4uu2ouqyEAWJiuRMis6RMpWrIwXYmRWc23rlRVopNU7jHsR0lQJbpNF6ZrYTPjqbwwPU0qujBdi5YZUKWF6dczb6uWmbdq1MywKlLl3EfjQA+bGcN6LUzXYjVCrOynw9lvZwlsBfBYD5gZsdQbliwe5ZkP85EeMzOGyerSaT/xQI+UGckkdenXQ29pH/FQj1gS3TTPQ0tduhJy8Lp0LU5miBPXpbuht36/MNGBdWhP4/Ikz6uzoTGn1TA7SU+H1enF2bDM0ovLiyqNLtOzGR9yS9xyRqDdFpN16YWMJpefb/PcQkuygfYRuQMlIjiY4+6st7BjENCAhm9A/m51ZsP5VA6/Db016t/axT5v36S1ZB1onlUp0WIewQaYLi0CUgHlfrw9mu9BmQRM/QBZSI+fGatB7buBLMKlfpKR8T5r+1h+gggj2mS2Zgocp0WmoGWYLpS4wPWpd1Lkoh5huUnfPQ631gU94ixojSPd6N/85KQ8Te2PFXmaDbPoshqemDP7IUris4vUXBaLvX5Q/UuVrZdSW/D4hde/QCIC78TVv//oxpq5EWTTL5uqounTq/esTPu6qSmaKd37/1M6/ar5NDFX7ySmLckDJG/45Pna1UdjF0pD4Gj5GtNl7nxUXoJSgWhMutslkElAjQlkIY1znNXwsdiDsgimMYt0FFNJICQ/gRfvVWMuJq5WLRN0ocQFrk+tMclFPcJyk757HG5dGrN7QWsc6UZjXlbGXKRn6TA25ekwjl1TzOi8GkaRiUxelnFl5uIrqMb0RhCrMSupLXj8wmtMIBGBd+JqTN8goNXj0o+/PQpo0D4FCMjf8PmvLTOBNAS+li8zO4vZgYQgYpPqwQHkEVBqAllIwx1jLSipCWQRTmrS5UZIegJf3qvSrBbChJxGeYAlLvB+eqVJX5JEUpO+eRxqXUKzez1rHOnZYeZlGeWX59HwMokuh9lZXg3L86oanl1cZFGeXp5E2TxABBWamc8Wt9P5gyGwBY9faKEJJSJwTlyhebMHh/uyqZh3letvNsebP58dbg6sLP1Fk5n/1fQD++vDxWnn0dDEg+kvfAa5CzWI4RtkTeUJpSHwvQLlSSXRoVQgmjMauf3zTSr3oFSCyU4oC2nw4yyHj8UelEUw2VmWo9KvO7H8BK69R91pOc10yvwTH/EDLHGB71PrTnJRj7DcpO8eh1u78OQsaI0j7ZRnm6Ds98Kk8bGzUrJ9UNENdhu+MKnGu+oy/oe/MKm2ZMazZA8XJtUQjQgiA17Hhcmmb4qr1v3Z7LjZx2ZXzYZ5AUUgdokrk2qEqzoWeGVSjZF50WRdcapEJ7lUwrAfJTqV6DZ7ZVIPmxlRe70yqUfLDKmyK5MWzuLKpP2UvDKpR80MrCIdzn00DvSwmVGsxyuTeqxGiJX9dDj77SyBrQAe6wEzI5Z6i5Kakf8615EeMzOG9XZlUo+UGcn4VyavfcSDFh/xUI9YEt00zwN5ZVINOfCVST1OZogTXpl0T8QS1ArYiQ7s1mZZDHFlMo0SGU0uv/BZFiARwVEcd28dIMsCNIjhG4S///TR2IXSEJw0CjaedJYFSCV0lgVIJWCWBchCetLLWQ4fiz0oi63IsiD5CVy7aHfXlWVJFofy5FTJAyxxge9Tb2HasixIbtJ3j8OtK8vSvaA1jvT29uowxF3FNEqltuDxCy88gUQE3okrPLeuVwfUgIZvQL5QVfbqWE2gtLbogFpF4Pt70b1AKhDdS7XogDIJKHuBLKShl7EalOwFsggme+kWHVh+gsDSq+xNFyqJHiyJJS5wfWrZS7fowHKTvnscbl2yt3tBaxzpRXf2ues0Lwftzu5Nzlhhm7WwLaNolW2gYqPSXxx1R4131YWsWWz0kZVOn7s+Gs8Pf/TX/1h5+f70r+dlQItapOuSohsFRV9OH89+O2kpFFJaIeNZoZdCISVEI4LIgHezUOhbWviGzrXr+tT959OrdxuF/GXz69HVT+3KuuX79PmSL7f+nzeK+cvpk5HPErtqSzBTtgLNSxYZKREyE7QSKUsXGSkxMlOz64pUJTpJGpZhP0p8KtEFKTIq0lHqfS739biZoVReZWSikq4y0qJlxlJplVF2XWVETjq8r0fNjKgiQc7Nzh/oYWdC2OxHo6XKSIvVCLGynw5nv50lsBXAYz1gZshS71WSfBR5fcWRHjMziMmqjGg/8UCPlBnKJFVG2XWVEekjHuoRS8Kb5nloqTJSQg5eZaTFyQxx4iqjbGcJagXsRAfWob2IT9M0OyuGZ+YsHmZnWTI8yUw8vDzJksqcFSeX+dzu5G645XhAuyMmq4yMjCaXn2/f3EJLsnf2EbkDJSI4k+Nuqm8me25szo53Hz68fXc8+Ne3D1/8X+6Obx8Pbt+/PziaPDwa17sDnxXuQq1g+Fbg71h9NHahNATnjILtJp1iAVLBpFh8PO5BeQRMsABZSA95GWtB7XGBLIIlWPKWGzdIfgJnLtrPdSVYzOI8nh5/iyUucHzqTUucjAqqrgjJTfrucbh1JVi6F7TGkd7egvacrCvKpbbg8QsvNYFEBN6JKzUDFLQDDWL4BllbdQJpCJxvL6oTSAWiOlsK2oFUAgpPIAtp8OMsh4/FHpRFMOHZVtCO5Cdw7b0Kz3yhU8hxlAdY4gLfpxaebQXtSG7Sd4/DrUt4di9ojSMdtm1Q4WNnpWTRwq6Kq1V2G6/kUeJl5h25SnDTlTxKK2Q8K/RSyaOEaEQQGfDSjVfyKC3BTIsKRC5ZyaNEyEyC8rVrWyWPEiMz/bmuKFWik6Q6GfajxKYS3cYrebS4maG050oeLVpmLJVW8hTXlTzkbMH7etTMiCoS4NwM+IEeNjME9lrJo8VqhFjZT4ez384S2ArgsR4wM2Sp9yZtlTxazMwg1mMljxYpM5RJKnmK60oe0kc81COWhDfN89BSyaOEHLySR4uTGeLElTzFzhLUCtiJDuzWplcKspKnbRSahyaXX/j0CpCI4AyOu6kOkF4BGsTwDcLfvPpo7EJpCI4YBTtPOr0CpLIa2Vuo8LeoLekVIJWA6RUgC+kRL2c5fCz2oCy2Ir2C5Cdw7aLdXVd6pVycxtNzZ7HEBb5PvYVpS68guUnfPQ63rvRK94LWONLbW0JekHU9ldQWPH7hhSeQiMA7cYUnqoQcaAXDt8LaahNIQ+Bxe1GbQCoQtUmVkAN5BJSaQBbScMdYC0pqAlkEk5ptJeRIfgJn3qvUrBbKhB48iyUucHxqqdlWQo7kJn33ONy6pGb3gtY40mErebxtl26ncdTGLrlRp7TpSh4tXmbekav9NlzJo7VCxrNCH5U8WohGBJEBr6Mnz/S39htfLLpTEsU4WjLMzKZApFLFOFqEzDymQHvSxThajMwM5pq6UotOkq1k2I/Qi1p0QYpxUjOaX7S6oQPVuJnRsN9iHDVaZjgUFuPE0bIYJyZHlN7Xo2YGRZGG5iaxD/SwmVGsz2IcNVYjxMp+Opz9dpbAVgCP9YCZIUu9vSB9xZEeMzOI9VeMo0bKDGWCYpylj3jQ4iMe6hFLwpvmeaCLcbSQQxfjqHEyQ5y0GMc+EUtQK2AnOrAOLa/xrONDbmhbdvTaTS1VjBO3zii7SZPLL3hOBElEcIzG3Rdv3wwFpAEN34D8/aqPxi6UhuBUUbBTJdMpSCqYdAo19ADJJFxCBclCeqjLWA1qgwxkESyhEicjfxXtPpafIBKINoMdCZU4np+/x+TY2QMscYHrU+94yEU9wnKTvnscbh0JFcaC1jjS21s0XlK1O3EitQWPX3idCiQi8E5cnYovGkcaxPANsrbuBNIQON9edCeQCkR30kXjSCoBhSeQhTT4cZbDx2IPyiKY8GwpGofyE7j2XoXnYiZp3DJkFkpc4PvUwrOlaBzKTfrucbh1Cc/uBa1xpMNW8lQ+dlZKpq3s4lV2G6/kUeJddRnf8UoepRUynhV6qeRRQjQiiAx4HT15eJU8SjLMtKhAp5KVPEqEzCQoX362VfIoMTLTn+vqSiU6SaqTYT9KLyrRbbySR4ubGQ17ruTRomWGQ2klT3pdyUPOA72vR80MiiINzc2AH+hhM6NYr5U8WqxGiJX9dDj77SyBrQAe6wEzQ5Z6e9FWyaPFzAxiPVbyaJEyQ5mkkie9ruQhfcRDPWJJeNM8Dy2VPErIwSt5tDiZIU5cyZPuLEGtgJ3owG5thqQiK3kyGU0uv/AZEiCR1fDftj7MfXGADAnQIIZvEP7+00djF0pDcEoo2HnSGRIgldAZEiCVgBkSIAvpKS1nOXws9qAstiJDguQncO2i3V1XhiRbHKiTs1oPsMQFvk+9hWnLkCC5Sd89DreuDEn3gtY40ttbQl6RpTlGagsev/DCE0hE4J24wnMLS8iBBjR8A64tVIE0BM66F6EKpAIRqnQJOZBJQJ0KZCGNlYzVoHQqkEUwndpWQo7kJ4gEverUxRTQuGWsK5S4wPWpdWpbCTmSm/Td43Dr0qndC1rjSIet5PFf0rTSM2+ll6zS23gpjxLvqs/4jpfyKK2Q8azQSymPEqIRQWTA62jKgx+vpbUEM6kqELlkHZASITOFKtGudB2QEiMzebquKlWikyRKGfYr46QcZT6Ie2qIoYqBcm9Wbl+PmxlQey4G0qJlBlRpMVB+XQxEjhC9r0fNDKsiGb5q7qSsMpMQM9gO9NiZwVBeEZTFif13i1FC1QVpERshYvaD4qy4swS2AnisB8wMYerNSpqPYu9px5EeMzOoyeqC8qga5VRdkBYpM7RJ6oLy67og0l081COWhDvN85BUWVSakfGGklqNG1MclFXGREUyyr0B+1iPlhn4xCVC+c4S1ArYiQ7s1mZq4oisESpkPLkEw6dqgEQEB3TcDfcWpmqABjR8A/I3wj4au1AagvNKwS6WTtUAqQRO1QCZBEzVAFlIj4s5q5HlqXX93m3GHpRMyIxN4g3g+1h+goAg2iq2HvA7TosDfnJ27AGWuMADqjdBLVMUoNykryCHW+uCHnEWtMaR3t6SdqtXqdKi1ullPmPwCIbXq0AiAvfE1asBatqBBjF8g6ytP4E0BN63F/0JpALRny017UAqAQUokIU0+jGWI07iitBne1AuwfRnZeOUd8uzj+UncPC96s/FfNG4ZWAslLjAA6r1Z1tlO5Kb9A3kcOvSn90LWuNIB64Yok5Aq1Z66Sq9jVcMKfGu+ozveMWQ0goZzwq9VAwpIRoRRAa8juY/ASqGlJZgplsFWpesGFIiZCZX+RK2rWJIiZGZVl1XmyrRSVKoDPsVaZH5AO6pAW68XkiLmxlOe64X0qJlhlNpvVB1XS9EDiq9r0fNDKoiEX6jCCBPjNWksfe5PtBjZ4ZCeb2QfQWN/ZfpPkJaxEaImP2gOCvuLIGtAB7rATMDmHqr0lYvpMXMDGk91gtpkTIDm6ReqLquFyLdxUM9Ykmw0zwPSZ4XVUyUFtZq3KB6oawycRWNMqqlkBYtM/CJ64WqnSWoFbATHdjtzb/EVL3QvAaUzZNLMHj+BUlEcDzH3W7j8y9Igxi+QfjbWh+NXSgNwemjYE9K5l+QVALnX5BUwuVfkCykp7+M5YjjKPf78T0olW1Iv0D5Cfy7aOfXkX5JovlpfUJOqz3AEhc4QPWepiX9AuUmfQE53DrSL4wFrXGkt7hcPabKf5L2AWgeY/AIhpefQCIC98SVn9tXro40oOEbcG25CqQh8Na9yFUgFYhcJcvVkUwCqlUgC2mw5KxGmhSp3+/vQbkEk6st1epQfoJ40KtcXUw0TVpG1EKJCxygWq62VKtDuUnfQA63LrnavaA1jnTgaiFKgCat9LJVepuuFtLiXfUZ3+1qIa0VMp4V+qgW0kI0IogMeB39hVijwrRkmPlSgVqlCn60CJnZUYkIJQt+tBiZedF15aUSnSQHyrBfW4sgLcRNl/yocTNjYr8lP2q0zJgoLPlJkmXJT0JONL2vR82MjCIlfSOP394iSI2dGc/kJT9dLYLUiI0QMftBcVbcWQJbATzWA2aGMPV+o6XkR42ZGdT6K/lRI2WGNkHJz9JdPGhxFw/1iCXhTvM8dLQI0uIGlfx0tAhSo2UGPmnJj304lqBWwE50YLc355KQJT+pjCeXYPicC5CI4IyNu2fewpwL0ICGb0D+XtZHYxdKQ3DkKNjF0jkXIJXAORcgk4A5FyAL6YkvZzVaWwQhyWxF0gXJTxAQRFvFrqRLujijJ+fgHmCJCzygehPUlnRBcpO+ghxuXUmX7gWtcaS3uEQ9IWuEMqkxeATD61UgEYF74urVACXqQIMYvkHW1p9AGgLv24v+BFKB6M+WEnUglYACFMhCGv0Yy9HaIgjJJZj+bKtRR/ITOPhe9ediVmrSMvwWSlzgAdX6s61GHclN+gZyuHXpz+4FrXGkAxf9pD56VlGaVnpmld7Gi36UeFd9xne86EdphYxnhV6KfpQQjQgiA15HiyBe0Y+SDDNjKpCrZNGPEiEzP8pXoW1FP0qMzMzouvJSiU6SBWXYj+7yowW48ZIfLW5mROy55EeLlhkRpSU/5rrkhxx9el+PmhkXRTr6Rh6/vcuPGjszmslLfrq6/KgRGyFi9oPirLizBLYCeKwHzAxg6t1GW8mPFjMzpPVY8qNFygxskpIfc13yQ7qLh3rEkmCneR46uvxocYNKfjq6/KjRMgOfuOTH7CxBrYCd6MBubwolJUt+chlPLsHwKRQgEcEJG3fHHCCFAjSI4RuEvzP10diF0hAcIAr2pHQKBUgldAoFSCVgCgXIQnqAy1iO1i4/QCpbkUFB8hP4d9HOryuDki8O3MmJtQdY4gIHqN7TtGVQkNykLyCHW1cGpXtBaxzpLa44J7o9WPlZSI3BIxhefgKJCNwTV35uYcU50ICGb8C15SqQhsBb9yJXgVQgcpWuOAcyCahWgSykwZKzGq1dfoBcgsnVtoJzJD9BPOhVri5GmCYtM2mhxAUOUC1X2wrOkdykbyCHW5dc7V7QGkfa/u8Pn39dnQz9QZsu7bkCKPPxtYq0bQZaGSWrfANVAMWRf+d/Rw141YusWQL0327U7Ty6ru+xWvHx9Cv3qf2GO9P86tbK96bPhlY7uqlTP3Vy0v3IwP4tj+ZjqJ41StN+600rMe3nj6efNzL1DatB3T/RnJXOx1RNP1s5W3XfntUbue88vfrLkRt89WyQRANXUzQXtvMZWM3P/G72A5n7/ceWUCNzfea/qzZ/xjN/L7VHSohGBJEB77rhkA/orhooMy0rEMVkXZESITMJK9G6dF2REiMz/bquilWik6RaGfbz2m5PjS5IUVFEVGDs62EzY6y8pqi02p+sKdKiZcZYaU1ReV1TRA5Hva9HzQy0IqnOfTQO9LCZAUpeTkRhPdRjNUKs7KfD2W9nCWwF8FgPmBmx1LuYpCxG81L9m9sYLWhmEJNVEtGO4oEeKTOUSSqJyutKItJJPNQjloQ3zQNBvXS1GjKmiIjCeazHyYxx4vKhcmcJagXsRAe2kbJpFl1WVToso+x8mJn8ZHgSnV4M09MkqrLT87S4nD8q5D655eRAvVcmy4cqGU8uQd+OuoWXZFftI3IHSkRwXrfWbvvbG+pHV+/5qN6FUjV8qvxtI5PtYPobu4H/utn0P7l6azD9xO7dm6tHg+k/TD9O4sHBIDEDKuGxCzWM4OhSsE2lczdAKqDcTepjcg/KJGDuBshCenLMWA1qdwxkESxrUxKF6/tYeoIgINoJdiVtqsUZPznl9gBLXOD51Nsdak2PsNSkbx6HWlfOpns9axzpRqJWl3EZX6bZsCqLbJhdnCTD0yi6GJ6b7Pzsoigvo8v5uxxWohIlRmkkNQaPYHCJiiQi8E5cifqxy5zMpNrqne5Grv2RS7tMv2mKi5qr4U2mpqk9cr9j/sD4zHAXagbDNwNfvvpo7EJpCFyuQGxSOREkE5DW9O5m70GZhNOaSBbSiMdYDUJrIlkE05pJTqZsoPwE7rxPsZkuppymLWNrocQFnk8tNslFPcJyk757HG4dapOxoDWO9KygPT09sT8dDdM4vxhmcVwOq+jidHh2kVTn5qxMo2K+6GHVpve4wqrNtqFoXmPwCIZXm0AiAvfEVZsfuRodV5buSoFc2Y6VkVc/nUlKd4dypjY/mn7gLdi8C6Vr+HTXVpVAGgLfKlCVrkvUZ6OBv7XTS1BCGHHp43EPyiOgtASykIY3xlpQ0hLIIpi0jM2oIIrPofwEvrtXabmYSJq2jJiFEhe4P7W0JBf1CMtN+u5xuHVJy+4FrXGkG2lZ5mVyVpwXw9O0iIZZfnE5rM6y02FapVF1WZ2cpBdz1xpWWmY+Y1hpmUiNwSMYXloCiQjcE1da3mzV8f9n729/JEmuM1/wX0nsp1llRcDfzF+02A/sUqgQpYqM7PSMueBVC4PMrMwL4t6hAA73ww4wwIgaUhpoIIrizI7AV5Fa3L0fLi6abLbYfGv+C1H/0bpFZkR0e5mZP+eEPxZRo9YMi1XVVc3nd8zdzmN+jpmtv7P+b+ufrn+0/uFk/T37X5uNjt9b/3TjMl3Qz6nQBoc+2GASMQQzrMBgemvkTBSKtUym7tOKXlBRIrpLIoU0wyHD4aKYUyniucvE32xOBRTM36Pay2zrRrw3Qy644ILJT28vvaN6yYWTvn0I3JC/HB7RlgdtNzc+e7RVMfc0Ghdm5xzzIGbex4y3p9FZUnxPLbg/e/zL2tP46ZtvnGXp09bFMfY2aoehwIZhjL2NWolGJBGQl33uXHXHg/N4NMr/Z/2dqe1M3YzZ+hPbCtE9AOvfdIPz7bPN6SsfPXZEfPZglc0j8uP1d6euGMzUMeinHN62Sa1CcMcJbqED2ya1GsG9Jod6Y6W6fublbJvUqouybbIok2np+1SqFQ4mcvnGyTQpK+/OSbVcMJMLd07m+W7nZO69s/CVXjWYzkULAXTD0UIvG0x/Y+6cVGs1Qq3w02Hjd74T1hO81AsGk5Z6jeSfLS71osE8Jts5GZgp3tdLBdOZYOvkbpZ4PzBLXOkVS1Kc5onwb53USo69dVKtE8xy0q2T3ROxE9UTu9KJ3dhZqIfd8niX44HvEuoluW/rZF7IOFFA18I9wCVZvLtA3qOC9B1AaIAOWdSDWyeZqAZHxVelLowZFUPwHVOwsPQXcYgolCKOd6MjkyRiDYdIIf2KDIyGbz1LpIhWw/FvdKTiCaZs0cJtqIKzvb00D1xHSwUXzHzq1Yl/oyMVTfrmIWhD9Zvh8Wx50Ce80dF4NzoaaTAwwPiGkggimJ1QQ0nb6EgMg8HDcLDZJGIIplyB2fRWMYgkJK/p60YnkkT0mkQKacYDRsPnNYkU0bxmaKMjk08wnY9qNs3WnHhvlVxwwQUzn9pshjY6Mtmk7x7CNuQ2hwe05UGf8EZH493oWEqDgQHGd5tEEMH0hLrNgzc6EnENjnuwqyRiCOZWgasc2uhIBOKYSxfHCypHRGtJpJCmN2AsfNaSSBHNWoY2OjL5BHP3qNZye4dgHrgUkgoumP7U1jK00ZHJJn33ELYhazk8oC0P+oQ3OhrvRsfQlUPOYGCA8a0lEUQwPaHWcqSNjkRog0MfbDCJGIIZVmAw/TVyIgrFWgY2OhJRIrpLIoU0wyHD4aKYUyniucvQRkcmoGD+HtVebu/8ywOXOFLBBZOf3l6GNjoy4aRvHwI35C+HR7TlQVuDGfKNI29wdK4ZOsdYB/CarOzjHX+Do1Jwf9b4YoPjYRsclcNQYMMwygZHpUQjkgjIAzc4/szuZVz/+s1fPjtbf3f9k/WPn222Lq5/rN/26ArMTB2Yfv4h7npUKgR3i+B+OrTrUakR3CZyqFFWqpNsCQHi5zPASnVxdj0W9bSpXcJf6oWD2X3sXY9auWB6l+563N8XmQfui1SrBnO8aFWA7hVa6GWDOXHUXY9arUaoFX46bPzOd8J6gpd6wWDSUi+Y/LPFpV40mMfG3PWolQqmM8mux/2Fkf5Z4kqvWJLiNE9EYNejUnL0XY9anWCWE+96tBdGumeGlU7sxs4+1En58DqZPGTJw6S4K5tJ/bppJnf390VS5g83SfH0HnrX6IGPFOp1unfXYyPjRAHj13aIIIJvg+hK/+3ajv1ltxL7ebdG/o/duuvDx+W4bSE6W39//Xfd0u2n639Y/6D7zw//zeMq+9XlxHSr779zBeQ5NSAGDwi+oHVhzKgYgk+fguWnv+5DRCHVfdwnmL2govRzfwDl0OUskUL65RkZDhfFnEoRre5T19PaV/Zh8gmmdtECb6jss702MA9cA0kFF8x96lWMd1AvuWzSdw9hG6r6DA9oy4M+4Yb10rc9skikwcAAoztPJohgekKd56EN60xcg+Me6iuZGIK5VeArBxrWmUAUd+lpWGdyxLOWTAppegPGwmMtmRTRrGWgYZ3KJ5i7x7SWxfaOwCJw6SMVXDD9qa1loGGdyiZ99xC2AWsJDGjLgz7hkzdK317IInRNkTMYGGB8a0kEEUxPqLVknbzBDIPBw3Cw5SRiCOZcgeX0ddIwSThe03fyBpMkotskUkgzHjAaPrdJpIjmNgMnb1D5BNP5qG5ze21gEbgHkgoumPnUbjNw8gaVTfruIWxDbnN4QFse9AkfHFz6tkcWmTQYGGB8t0kEEUxPqNs85OBgJqrBUQ92lEQMwbwqcJTe4jgThWQpnavPF1SSiJaSSCFNa8Bo+CwlkSKapfQfHEzFE0zZozrK7UWBReDqRyq4YOZTO0r/wcFUNOmbh6ANGcrh8Wx50JH3Q1YuvM4i5kG8qo939P2QWsH9OeOL/ZAH7YfUDkOBDcMY+yG1Eo1IIiAvx/ZDMi581Magn2h4Wx+1CsEtIxLX7N36qNUI7hU51A8r1fUzLmfro1ZdnK2PgQsf1cLBRD7y1ke1XDCTC7c+FvsLH4vAhY9q1WA6F9l/dMPQQi8bTH9jbn1UazVCrfDTYeN3vhPWE7zUCwaTlnplFLrwUS0azGMjbn1USwXTmWDrY7G/8NE/S1zpFUtSnOaJ8G991EqOvfVRrRPMctKtj4W98NE9M6x0Yk+3blP5tj4WhYwTBYxftyGC9B1AaIAOWdSjdRsiqsFR8VWpC2NGxRB8vRQsLP11GyJK5LoNkSRi3YZIIf16DIyGbz1LpDiFug0TTzBlixZuQ3Wb7QWBReDCRyq4YOZTr04CdRsmmvTNQ9CG6jbD49nyoE+47bzy7mg00mBggPENJRFEMDuhhpLWdk4Mg8HDcLDZJGIIplyB2fRWMYgkJK/pazsnkkT0mkQKacYDRsPnNYkU0bxmqO2cySeYzkc1m9v7AYvAhY9UcMHMpzabobZzJpv03UPYhtzm8IC2POgTPj+j8m5yLKXBwADju00iiGB6Qt3mwednEHENjnuwqyRiCOZWgascOj+DCMQxly6OF1SOiNaSSCFNb8BY+KwlkSKatQydn8HkE8zdo1rL7f2AReDCRyq4YPpTW8vQ+RlMNum7h7ANWcvhAW150Cd84WPl3dFYSYOBAca3lkQQwfSEWstxLnxkQhsc+mCDScQQzLACg+mvkRNRKNbSf+EjEyWiuyRSSDMcMhwuijmVIp67DFz4SAUUzN+j2svt9YBF4MJHKrhg8tPby8CFj1Q46duHwA35y+ERbXnQkTc41i68zjHWQby6j3f8DY5Kwf1Z44sNjodtcFQOQ4ENwygbHJUSjUgiIA/c4BjtwkdtYPr5h7jrUakQ3C2C++nQrkelRnCbyKFGWalOsiUEiJ/PACvVxdn1GLjwUS0czO5j73rUygXTu3TX4/7CxyJw4aNaNZjjRasCdK/QQi8bzImj7nrUajVCrfDTYeN3vhPWE7zUCwaTlnrBFLrwUS0azGNj7nrUSgXTmWTX4/7CR/8scaVXLElxmicisOtRKTn6rketTjDLiXc92gsf3TPDSid2Y2ehK3osj3eNHvhIoV6ne3c9NjJOFDB+bYcIIvg2iK70+Rc+MgNi8IDgC1oXxoyKIfj0KVh++us+RBRS3cd34SMTpZ/7AyiHLmeJFNIvz8hwuCjmVIpodZ/AhY9UPsHULlrgDZV9tvcDFoELH6nggrlPvYoJXPhIZZO+ewjbUNVneEBbHvQJN6zXvu2RJpEGAwOM7jyZIILpCXWehzasM3ENjnuor2RiCOZWga8caFhnAlHcpadhnckRz1oyKaTpDRgLj7VkUkSzloGGdSqfYO4e01qa7f2AJnDhIxVcMP2prWWgYZ3KJn33ELYBawkMaMuDPuGTN2rfXkgTvo/IEQwMML61JIIIpifUWrJO3mCGweBhONhyEjEEc67Acvo6aZgkHK/pO3mDSRLRbRIppBkPGA2f2yRSRHObgZM3qHyC6XxUt7m9H9AELnykggtmPrXbDJy8QWWTvnsI25DbHB7Qlgd9wgcH177tkSaTBgMDjO82iSCC6Ql1m4ccHMxENTjqwY6SiCGYVwWO0lscZ6KQLKVz9fmCShLRUhIppGkNGA2fpSRSRLOU/oODqXiCKXtUR7m9INAELnykggtmPrWj9B8cTEWTvnkI2pChHB7PlgcdeT9k48LrLGIexGv6eEffD6kV3J8zvtgPedB+SO0wFNgwjLEfUivRiCQC8jJsPyTjwkdtDPqJhrf1UasQ3DIicc3erY9ajeBekUP9sFJdP+MeuPUxrYqpc8vCXK0wzvbHsnM8hUv4S71wMJmPvP1RLRfM5sLtj2Z/6aMJXPqoVg2mdNES4C03nDa2UbBySV/opYNpUL4FMq1Lk6YeC3+hF2yEguHHxAbxfCesJ3ipFwxmMPUyKXT7o1o0mNSE+yCzOpkWzgfifb1UMLcJ9kGa/e2P/uniSq9Yku80T0SdmCyf5s6polXL5uyFzLK8TvNp4zRl13qxYN6Tbog09hpI9xSx0ok93WpO49sQaQoZJwoYv5pDBOl7gtAAHbLUR6s5RFSDo+JrVRfGjIoh+KYpWG76qzlElMjVHCJJxGoOkUL6TRkYjaoxubvcPqeiRCzpVMaF95KLJ5i3Reu5oZLO9u5AE7gLkgoumP7Ua5VASYeJJn39ELShks7weLY86BPuSG+8mx2NNBgYYHxXSQQRzE6oq6R1pBPDYPAwHOw4iRiCKVfgOL0FDiIJyXD6OtKJJBENJ5FCmvGQ0WiyaearqxBRohnOrJw+Xc78tuNk8gnm9FEd5/b+QBO4EJIKLpj+1I4z1JbOZJO+gAjbkOUcHtCWB33C52s03k2QpTQYGGB8y0kEEUxPqOU8+HwNIq7BcQ+2lkQMwdwqsJZD52sQgTgO08XxgsoR0V8SKaTpDRmLQNsOkSSavUw7J+Jcmb3k8gnm71Ht5fYOQRO4FJIKLpgC1fYydMYGk036/iFsQ/ZyeEBbHvQJXwrZeHc9VtJgYIDx7SURRDA9ofZynEshmdAGhz7YZBIxBDOswGT6K+ZEFIq99F8KyUSJ6DCJFNIMBwxHkU+dPXFzKkg8g5mknkbQl1xAwRQ+qsPc3iJoAvdCUsEF85/eYQbuhaTCSV9ABG7IYg6PaMuDjrsPMnOOaWca6xBenvTxjr8PUim4P2t8sQ/ysH2QymEosGEYZR+kUqIRSQTkgfsgo90LqQ1MP/8QN0cqFYL7SHBLHdocqdQIbiA51Csr1Uk2iwDxqxPfN1alvjhbI005rZze/aVeOJjfx94aqZULJnjp1sj9zZAmcDOkWjWY5UXrgn6887JJqmSaOtc+C712MDXK90bWZZbmvsaEC71gIxQMPyc2iOc7YT3BS71gMIGpF0+hOyLVosGcNubeSK1UMLVJ9kbu74j0zxdXesWSdKd5IvIyqyozrQuX7latm7M5Mk3yLvPlnrXitV4tmPrEuyPtdZHuSWKlE7txudAFP5bHu3QPfLtQL9+9uyMbGScKGL/qQwQRfDJEPwDwr4tkBsTgAcHXuS6MGRVD8EVUsCr1V4SIKKSKkO+6SCZK3wYEUA5d5RIppB+kgeFIs9T9WXNOJYlWEmoST8v+Sy6fYHoXrfyGKkLbGwZN4MpIKrhg/lMvagJXRlLZpO8fwjZUEBoe0JYHfbot7ZmnGvOl/Gl/rSAYGGB098kEEUxPqPs8tKWdiWtw3EO9JRNDMLcKvOVASzsTiOIwPS3tTI549pJJIU1vwFh4iy1MjmjmMtDQTuUTzN5jmstye8dgGbg0kgoumADV5jLQ0E5lk759CNuAuQQGtOVBn+4RHZ25zF3B6Mxl8E4jVzAwwPjmkggimJ5Qc8k6ooMZBoOH4WDTScQQzLkC0+lrs2GScNym74gOJklEv0mkkGY8YDRq+2nIRTKnkkRznIETOqh8gil9VMe5vWewDFwcSQUXzH5qxxk4oYPKJn3/ELYhxzk8oC0P+nSPGu4cp/O17hxnJg0GBhjfcRJBBNMT6jgPOWqYiWpw1INdJRFDMK8KXKW3TM5EIdlK5wr0BZUkoq0kUkjTGjAaeVm576WZU0mi2Ur/ScNUPMG0Paqr3F42WAYuj6SCC2Y/tav0nzRMRZO+fQjakKkcHs+WBx1506Sn57LMg3hpH+/omya1gvtzxhebJg/aNKkdhgIbhjE2TWolGpFEQF6ObZpkXB6pjUE/0fD2R2oVgntJJM7Zuz9SqxHcRHKoJ1aq62fcA/dHpqbwdYRqFcbZIRm4PFItHEzmI++QVMsFs7lwh2S5vzyyDFweqVYNpnTREqAf7yrLyu65blzSF3rpYBqUb5BMy8LkqWc/3IVesBEKhh8TG8TznbCe4KVeMJjB1Muk0OWRatFgUhtxg6RaKpjbBBsky/3lkf7p4kqvWJLvNE9ElSZ57tls36plk/ZHNlWRV9PSWfO81osF8550e2RpL490TxErndjTreh4GgO6pXoh40QB41d0iCB9TxAaoEOW+mhFh4hqcFR8rerCmFExBN80BctNf0WHiBK5okMkiVjRIVJIvykDo1ElaemeoOdUlFMo6TDxBPO2aD03VNLZXjZYBi6PpIILpj/1WiVQ0mGiSV8/BG2opDM8ni0P+oQ70z27tTtXaaTBwADju0oiiGB2Ql0lrTOdGAaDh+Fgx0nEEEy5AsfpLXAQSUiG09eZTiSJaDiJFNKMh4xG2UxLX12FiBLNcIZa05l8gjl9VMe5vWuwDFweSQUXTH9qxxlqTWeySV9AhG3Icg4PaMuDPuGTNjwfLjrLWUqDgQHGt5xEEMH0hFrOg0/aIOIaHPdga0nEEMytAms5dNIGEYjjMF0cL6gcEf0lkUKa3pCxCLTtEEmi2cvQWRtMPsH8Paq93N41WAYuj6SCC6ZAtb0MnbXBZJO+fwjbkL0cHtCWB326l0d29rJwBaOzl5U0GBhgfHtJBBFMT6i9HOfySCa0waEPNplEDMEMKzCZ/oo5EYViL/2XRzJRIjpMIoU0wwHDkddT4xyPOZUknsMM3B5JBRTM4aNazO1dg2Xg9kgquGAC1FvMwO2RVDjpG4jADXnM4RFtedCRN0L66uB1EC/r4x1/I6RScH/W+GIj5GEbIZXDUGDDMMpGSKVEI5IIyAM3Qka7PVIbmH7+Ie6OVCoEN5Lgnjq0O1KpEdxBcqhZVqqT7BYB4meqzP29Yq5WGGd3ZOD+SLVwMMOPvTtSKxdM8dLdkfv7I8vA/ZFq1WCeF60M3i7zp4Uxnpt5FnrtYHKUb48s06QyiecWkAu9YCMUDD8nNojnO2E9wUu9YDCFqZdPofsj1aLBrDbm9kitVDC5SbZH7u+P9M8XV3rFkoSneSIyUzZN6ZkrWrVuzv7IKs+aJJk2zs8613qxYOYT74+010e654iVTuzG5kKX/Vge79o98PFCvX737o9sZJwoYPy6DxFE8M0Q/QLAvz6SGRCDBwRf6LowZlQMwSdRwbLUXxMiopBqQr7rI5kofRcQQDl0mUukkH6RBoajNtPamVvnVJJoNaHA9ZFUPsH0Llr4DZWEtrcNloHrI6nggvlPvaYJXB9JZZO+fwjbUEVoeEBbHvQJN7Vnvn2UVSINBgYY3X0yQQTTE+o+D21qZ+IaHPdQb8nEEMytAm850NTOBKI4TE9TO5Mjnr1kUkjTGzAWgWoLkySavQw0tVP5BPP3mPay2t43WAUukKSCC6ZAtb0MNLVT2aTvH8I2YC+BAW150Cd8TEfm2zNZhe82cgQDA4xvL4kggukJtZesYzqYYTB4GA62nUQMwZwrsJ2+ThsmCcdv+o7pYJJEdJxECmnGA0ajzBrPKeJzKko0yxk4poPKJ5jTR7Wc2wsHq8ANklRwwfSntpyBYzqobNIXEGEbspzDA9ryoE/4vGHPSrmznJk0GBhgfMtJBBFMT6jlPOS8YSaqwVEPtpVEDMG8KrCV3ko5E4XkK51L0BdUkoi+kkghTWvAaGRlUngP6GCyRDOW/gOHqXiCiXtUX7m9c7AK3CFJBRfMf2pf6T9wmIomff8QtCFbOTyeLQ+6+78/25A/+Sn7X38a8o8j76X0fazMA7x1Yvq8sfZSeor376kF9ycR5l7K9UfrT9a/f9zeZrdJrj+xu95+u9k7+e2nXyo3Sa5/sv7e+jv6vZL2DxbPkqc/WgO7JrUBL7CAj7FrUivRiCQC8jJs1yTj+khtDPo5hrdBUqsQ3Eoisc3eDZJajeAekkMNsVJdP9keuEHSGbu5Wl2UzZF5mk8L51f4l3rhYMrWbI6scu/mSLVcMGcLN0dW+6sjq8DVkWrVYOIWOf+3W87dwV7oZYPpT74v0qf1Qq/VCLXCT4eN3/lOWE/wUi8YTFrqRZF/trjUiwbzmHBLpH+meF8vFUxngi2R1f7GSP8scaVXLElxmifC99a1asmc3ZA+ndd6nWCWk26ErOxFke6ZYaUTa9XeJqZJk/p+UpZ395PixpSTpirN5K7JivviLrmtb4+wETL3bYSsChknCuhaoge4JMt0F8h7VJC+AwgN0AHL98+u2jf9Qk8r6H+yOyRt2/qbb3X/+Y+fXZN1y7XHFd2P1/+w/t5ks1vy79Y/XP/X7sd/XP/02Vme+MoNz6khM3jI8NWtC2NGxRB8ABUsUP0FICIKpwDk4nhB5YhY/iFSSD8/A2PhWxUTKaIVfqpp1bjwXnLxBBO/aPk3VPjZ3kxYBW6apIIL5j31Gsc3ppdcNOmbh6ANFX6Gx7PlQZ/wDsncu0PSiIMBAca3pUQQweyE2tKDd0gScQ2Oe7ClJGIIplaBpRzaIUkEimosiRwRjSWRQpregLHwGUsiRTRj6d1I95LLJ5i7R3WW2wsIq8CNklRwwfSndpah3ZFMNum7h7ANWcvhAW150Cd85U/u3R1ZSoOBAca3lkQQwfSEWstxrvxhQhsc+mCDScQQzLACg+n/ZklEoVhL/5U/TJSI7pJIIc1wyHC4KOZUinju0nsxzEsuoGD+HtVebi8grAI3SlLBBZOf3l4GrvuhwknfPgRuyF8Oj2jLg4583U/hwuscYxXAa/K8j3f8FnWl4P6s8UWLOtqirgx4gQV8lBZ1pUQjkgjIA1vUdxf7nHWPAudKH21I+jmG2LGuVAh2+uGeOdSxrtQItvgdaoaV6iTtfED8fCZXqS5Ox3qSTt3tcS/1wsEMPnbHulYumMKlHevVvmPde4viK71qMI+LnD/a57nQywaz4agd61qtRqgVfjps/M53wnqCl3rBYNJSL4r8s8WlXjSYx8bsWNdKBdOZpGO92nese2eJK71iSYrTPBGBjnWl5Ogd61qdYJYTd6xX5ztRPbErndiNnYUOWrc83nV44EOEei3u7VivZZwoYPz6DRFE8P0PXc3zr+5hBsTgAcGXsi6MGRVD8HlTsPz013aIKP3cHkDB16n+q3uYKBFrO0QK6ddlZDhcFHMqRbTajveGl5dcPsHULlrgDZV26m0hwHuh5IILLpj71KuYwLU9VDbpu4ewDVV2hge05UGfcFO65wi1znk20mBggPGdJxFEMD2hzvPgpnQirsFxD/aVRAzB3CrwlUNN6UQgirv0NaUTOSJaSyKFNL0BY+GzlkSKaNYy1JTO5BPM3aNay+0FglXgRkgquGD6U1vLUFM6k0367iFsQ9ZyeEBbHvQJH8NR+JrSnxYdkmBAgNGtJRNEMD2h1vIUjuFghszgITvUnjIxBPOzwJ56P3syUWIaUyZHPGPKpJAmR2AsPMaUSRHNmPqP4aDiCSb+MX1pvb15sA5cJUkFF8x7al/qP4aDiiZ98xC0AVsKjGfLg47cy25ceJ3RDN9aVPTxjt7LrhUM9sAdYhT/x+xl1wa8wAI+Ri+7VqIRSQTk5VgvO+O4dW0MwD5AgY32Na9rFfYdMrN5XasR7PY71Pkq1Uk6+4D4+RytUl2c5vXAcetq4WDKHrl5XS0XzNnC5vU63TWv197rEV/pVYOJW2T00ZbPhV42mP7GbF5XazVCrfDTYeN3vhPWE7zUCwaTlnoNFDpuXS0azGMjNq+rpYLpTNC8vpsl3g/MEld6xZIUp3ki/M3rWsmxm9fVOsEsJ21e756Inaie2JVO7OnWeYyveb3OZJwoYPw6DxFE8LnvkOV79DoPMWQGDxm+unVhzKgYgu+dggWqv85DRIla5yFyRKzzECmkX5uBsfCtiokUp1DnYeIJJn7R8m+ozrO9l7UO3LNLBRfMe+o1TqDOw0STvnkI2lCdZ3g8Wx70CXe2G19ne52LgwEBxrelRBDB7ITa0kM725m4Bsc92FISMQRTq8BSDnS2M4GiGksiR0RjSaSQpjdgLHzGkkgRzVgGOtupfIK5e1RnmW+diPfKyQUXXDD9qZ1loLOdyiZ99xC2IWs5PKAtD/qEj1s33s72QhoMDDC+tSSCCKYn1FqOc9w6E9rg0AcbTCKGYIYVGEz/N0siCsVa+o9bZ6JEdJdECmmGQ4bDRTGnUsRzl4Hj1qmAgvl7VHu5vVewDtwTSQUXTH56exk4bp0KJ337ELghfzk8oi0POnKLunPN0DlGE8R76zT547eoKwX3Z40vWtTRFnVlwAss4KO0qCslGpFEQB7Yoh7huHVtSMDmP4G59nasKxWCnX64Zw51rCs1gi1+h5phpTpJOx8QP5/JVaqL07EeOG5dLRzM4GN3rGvlgilc2rFu9h3r3lsSX+lVg3lc5PzRPs+FXjaYDUftWNdqNUKt8NNh43e+E9YTvNQLBpOWelEUOm5dLRrMY2N2rGulgulM0rFu9h3r3lniSq9YkuI0T0SgY10pOXrHulYnmOXEHevmfCeqJ3alE7uxs9ABmZbHuw4PfIhQr8W9HeuljBMFjF+/IYIIvv+hq3n+cevMgBg8IPhS1oUxo2IIPm8Klp/+2g4RhVTb8R23zkSJWNshUki/LiPD4aKYUymi1XYCx61T+QRTu2iBN1Ta2d67Wgdu0qWCC+Y+9SomcNw6lU367iFsQ5Wd4QFtedAn3JReepvSK2kwMMD4zpMIIpieUOd5cFM6EdfguAf7SiKGYG4V+MqhpnQiEMVd+prSiRwRrSWRQpregLHwWUsiRTRrGWpKZ/IJ5u5RrWW1dSLeWyUXXHDB9Ke2lqGmdCab9N1D2Ias5fCAtjzoEz6Go/Q2pdfiYECA8a0lEUQwPaHW8iSO4SCGzOAhO9ieEjEE87PAnvo/exJRohpTIkdEY0qkkCZHYCx8xpRIEc2YBo7hYOIJJv5Rfen2QsI6cMMkFVww76l9aeAYDiaa9M1D0IZs6fB4tjzoyL3slQuvM5pNEK/s4x2/l10pGOyBO8Qo/g/ay64MeIEFfJRedqVEI5IIyMuwXnbKcevKGPRTCrF5Xamw75CpzetKjWC336HOV6lO0tkHxC8v02rq/HQ1V0uM08Ge1tPS+cXlpV44mLfH7mDXygUTt7SDvdl3sHuvVHylVw1mb5HbfyveqcnKykxrp/1d6MWDmVDex96Z07SsC0+LwoVesREqhp8UG8XznbCe4KVeMJjF1Iui4PnrWtFgYhN2s2d1Nzn7utm1UsH8Julmb/bd7N4Z40qvWJLzNE9EmnYammyaON1OqxbO6WkvSlMnWeqpOF3r1YLZT9zZ3pzvRPXErnRiT7cIVPk625tExokCRi8CMUEE3wIPWdvHLgIxQ2bwkOFLXxfGjIoh+BgqWL16i0BMlJhFICZHvCIQk0L6KRoZi6wsU8+SmYkSsRLUOI3QSy6eYPYXrQ0HKkHN9qLWJnDxLhVcMPmpFz3+ShAVTfr6IWgDlSBgPFse9An3vle+3vcmfB+SKxgQYHxvSgQRzE6oNz20952Ja3Dcg30lEUMwtQp85UDvOxMoqrskckR0l0QKaXoDxiJUkGGiRHOXaen5zvaSyyeYwEe1l+nWjnhvplxwwQVzoNpeBhrgqWzSFxBhG/KXwwPa8qBP+FT2ytcA/7SaFAQDA4zvL4kggukJ9ZfjnMrOhDY49MEuk4ghmGEFLtP/9ZKIQvGX/lPZmSgRLSaRQprhgOFokmJauEjmVJJ4DjNJp6XTjbzkAgrm8FEt5vYKwiZwpSQVXDAB6i1m4GR2Kpz0DUTghjzm8Ii2POjI3ey1C69zjXkQr+rjHb2bXSu4P2t80c0OdrNrA15gAR+jm10r0YgkAvLAbvYIJ7NrQ9LPMbzmdq1CsAcQ982B5natRrD571BDrFQnafQD4lcUZTJ1ppe5WmKc5vak9J4SohYOpvGRm9vVcsE8Lmxub/Jdc3vjvVXxlV41mMxF9v+teOdlp8JME2fdZqEXDyZGeXN7UdVlkdfTwtPcrlZshIrhJ8VG8XwnrCd4qRcMZjH1Kil0VLtaNJjYRmxuV0sF85uguX03Y7wfmDGu9IolOU/zRKR5YRpTTVNnImzVwjnN7aYq8iorp4lT7bVeLZj9pM3t3dOxE9UTu9KJ3Xhd6KBNy+NdpAe+UqgX6t7m9kLGiQLGL/AQQfrOIDRA4FKff2w7MyAGDwi+znVhzKgYgm+fgrWpv/hDRCEVf3zHtjNRIhZ/iBTST8/AcJRlM02dHz7mVJRo1Z8m8XxSfsnlE8zvotXfUPFne4lrE7iWlwoumADVy5rA2e1UNukLiLAN1X6GB7TlQZ9w/3rt7V830mBggPHtJxFEMD2h9vPg/nUirsFxDzaXRAzB3Cowl0P960QgisX09a8TOSL6SyKFNL0BYxGsuRBRovnLUP86k08wgY/qL83WjnjvqVxwwQVzoNpfhvrXmWzSFxBhG/KXwwPa8qBP+OyO2tu/XoqDAQHG95dEEMH0hPrLkzi7gxgyg4fsYI9KxBDMzwKP6v8ASkSJ6k6JHBHdKZFCmhyRsTBl6v46OKeiRHOngbM7mHiC2X9Uc7q957AJXFxJBRdMfmpzGji7g4kmff0QtCFvOjyeLQ86ct+7c0w7t1kF8eo+3vH73pWC+3PGF33vaN+7MuAFFvBR+t6VEo1IIiAvx/reGae4a2PQTynERnelwr5Npja6KzWCjYCH2l+lOknTHxC/PM2Me3qeqyXGaXQPnOKuFg7m7bEb3bVywcQtbXSv9o3u3psaX+lVg9lb5PbfauVoTFVn08K5YFvotYOJUN7nnucmz/PG09Z8oVdshIrhB8VG8XwnrCd4qRcMJjH1mih0iLtaNJjXxuxz10oF05ukz73a97l7J4wrvWJJytM8EU3VFGU9dfdit2rdnDb3IsmKJKmmxpm0r/VqwdwnbnOvzneiemJXOrGnWwdqvG3utYwTBYxfByKC
A2: ТЕХНИКО-КОММЕРЧЕСКОЕ ПРЕДЛОЖЕНИЕ (ТКП)
A3: г. Москва, Волоколамское ш., Покровское, вл. 71/15, СОШ 2, 850 мест
A4: Стоимость, указанная в предложении, включает в себя все необходимые затраты на выполнение полного комплекса работс НДС 22%
A5: Номер п/п | B5: Код узла ИСР | C5: Наименование затрат | D5: Комментарий по ИСР | E5: Комментарий подрядчика | F5: Ед. изм. | G5: Коэф.расхода | H5: Кол-во БО | I5: Общее кол-во | J5: Остаток | K5: 5.1-Пликта
A6: 1.1.1.1.1.2 | B6: 6.3.1.5.2 | C6: Стены
A7: 1.1.1.1.1.2.1 | B7: 6.3.1.5.2.1 | C7: Черновые работы по поверхности стен
A8: 1.1.1.1.1.2.1.1 | B8: 6.3.1.5.2.1.1.1 | C8: Оклейка швов сопряжения бетонных и других поверхностей стен, перегородок (газобетон, ПГП, панели АКОТЕК и др.) стеклохолстом | E8: 2эт - 1826,61м.п., 3эт. - 2045,25м.п. | F8: пог. м | G8: 1 | I8: 0
A9: 1.1.1.1.1.2.1.1.1 | C9: Шпатлевка гипсовая_ / белая / Унифицированная по ПИК-СТАНДАРТ, 30кг | F9: кг | G9: 0.3 | I9: 0
A10: 1.1.1.1.1.2.1.1.2 | C10: Лента армирующая ( серпянка)_/150мм | F10: пог. м | G10: 1.1 | I10: 0
A11: 1.1.1.1.1.2.1.2 | B11: 6.3.1.5.2.1.1.1 | C11: Оклейка швов сопряжения бетонных и других поверхностей стен, перегородок (газобетон, ПГП, панели АКОТЕК и др.) стеклохолстом | E11: 2эт - 1826,61м.п., 3эт. - 2045,25м.п. | F11: пог. м | G11: 1 | I11: 3479
A12: 1.1.1.1.1.2.1.2.1 | C12: Лента армирующая ( серпянка)_/150мм | F12: пог. м | G12: 1.1 | I12: 3826.9
A13: 1.1.1.1.1.2.1.2.2 | C13: Шпатлевка гипсовая_ / белая / Унифицированная по ПИК-СТАНДАРТ, 30кг | F13: кг | G13: 0.3 | I13: 1043.7
A14: 1.1.1.1.1.2.1.3 | B14: 6.3.1.5.2.1.2.3 | C14: Штукатурка стен сухими смесями с установкой маяков с предварительной огрунтовкой / толщ. от 16,5 мм до 21 мм | E14: 2 этаж | F14: м2 | G14: 1 | I14: 0
A15: 1.1.1.1.1.2.1.3.1 | C15: Штукатурка гипсовая_ / Унифицированная по ПИК-СТАНДАРТ, 30кг | E15: Штукатурка гипсовая Старатели Старт 30 кг | F15: кг | G15: 1 | I15: 0
A16: 1.1.1.1.1.2.1.3.2 | C16: Грунтовка БЕТОН-КОНТАКТ_/ | F16: кг | G16: 0.25 | I16: 0
A17: 1.1.1.1.1.2.1.3.3 | C17: Профиль маячковый_/ПМ6 | F17: пог. м | G17: 1.05 | I17: 0
A18: 1.1.1.1.1.2.1.4 | B18: 6.3.1.5.2.1.4.2 | C18: Выравнивание стен с предварительной огрунтовкой / по оштукатуренной поверхности / толщ. 2 мм | E18: 2 этаж. Шпатлёвка базовая | F18: м2 | G18: 1 | I18: 0
A19: 1.1.1.1.1.2.1.4.1 | C19: Шпатлевка гипсовая_ / белая / Унифицированная по ПИК-СТАНДАРТ, 30кг | E19: Шпаклевка гипсовая Старатели базовая белая 20 кг | F19: кг | G19: 1.8 | I19: 0
A20: 1.1.1.1.1.2.1.4.2 | C20: Уголок малярный_ / L=3м /25х25 мм | F20: шт | G20: 0.3 | I20: 0
A21: 1.1.1.1.1.2.1.4.3 | C21: Лента армированная Серпянка 150мм | F21: пог. м | G21: 1 | I21: 0
A22: 1.1.1.1.1.2.1.4.4 | C22: Грунтовка универсальный ЛАСТИМИН_ / LP-51 А | F22: кг | G22: 0.15 | I22: 0
A23: 1.1.1.1.1.2.1.5 | B23: 6.3.1.5.2.1.4.2 | C23: Выравнивание стен с предварительной огрунтовкой / по оштукатуренной поверхности / толщ. 2 мм | E23: 2 этаж. Шпатлёвка финишная | F23: м2 | G23: 1 | I23: 0
A24: 1.1.1.1.1.2.1.5.1 | C24: Грунтовка универсальный ЛАСТИМИН_ / LP-51 А | F24: кг | G24: 0.15 | I24: 0
A25: 1.1.1.1.1.2.1.5.2 | C25: Шпатлевка гипсовая_ / белая / Унифицированная по ПИК-СТАНДАРТ, 30кг | E25: Шпаклевка гипсовая Старатели финишная 20 кг | F25: кг | G25: 1.8 | I25: 0
A26: 1.1.1.1.1.2.1.6 | B26: 6.3.1.5.2.1.8.5 | C26: Подготовка поверхности СКБ / стен / по штукатурке / 2мм | E26: 2 этаж. Шпаклевка финишная для высококачественной отделки. | F26: м2 | G26: 1 | I26: 0
A27: 1.1.1.1.1.2.1.6.1 | C27: Шпатлевка финишная TERRACO HANDYCOAT ALL PURPOSE | F27: кг | G27: 1 | I27: 0
A28: 1.1.1.1.1.2.1.6.2 | C28: Грунтовка универсальный ЛАСТИМИН_ / LP-51 А | F28: кг | G28: 0.15 | I28: 0
A29: 1.1.1.1.1.2.1.7 | B29: 6.3.1.5.2.1.8.5 | C29: Подготовка поверхности СКБ / стен / по штукатурке / 2мм | E29: 3 этаж. Шпаклевка финишная для высококачественной отделки. | F29: м2 | G29: 1 | I29: 0
A30: 1.1.1.1.1.2.1.7.1 | C30: Грунтовка универсальный ЛАСТИМИН_ / LP-51 А | F30: кг | G30: 0.15 | I30: 0
A31: 1.1.1.1.1.2.1.7.2 | C31: Шпатлевка финишная TERRACO HANDYCOAT ALL PURPOSE | F31: кг | G31: 1 | I31: 0
A32: 1.1.1.1.1.2.1.8 | B32: 6.3.1.5.2.1.8.5 | C32: Подготовка поверхности СКБ / стен / по штукатурке / 2мм | E32: 2 этаж. Шпаклевка базовая. | F32: м2 | G32: 1 | I32: 0
A33: 1.1.1.1.1.2.1.8.1 | C33: Шпатлевка гипсовая_ / белая / Унифицированная по ПИК-СТАНДАРТ, 30кг | F33: кг | G33: 1.8 | I33: 0
A34: 1.1.1.1.1.2.1.8.2 | C34: Грунтовка универсальный ЛАСТИМИН_ / LP-51 А | F34: кг | G34: 0.15 | I34: 0
A35: 1.1.1.1.1.2.1.9 | B35: 6.3.1.5.2.1.8.5 | C35: Подготовка поверхности СКБ / стен / по штукатурке / 2мм | E35: 3 этаж. Шпаклевка базовая. | F35: м2 | G35: 1 | I35: 0
A36: 1.1.1.1.1.2.1.9.1 | C36: Грунтовка универсальный ЛАСТИМИН_ / LP-51 А | F36: кг | G36: 0.15 | I36: 0
A37: 1.1.1.1.1.2.1.9.2 | C37: Шпатлевка гипсовая_ / белая / Унифицированная по ПИК-СТАНДАРТ, 30кг | F37: кг | G37: 1.8 | I37: 0
A38: 1.1.1.1.1.2.1.10 | B38: 6.3.1.5.2.1.8.5 | C38: Подготовка поверхности СКБ / стен / по штукатурке / 2мм | E38: 2 этаж. Шпаклевка финишная для высококачественной отделки. | F38: м2 | G38: 1 | I38: 8128.4
A39: 1.1.1.1.1.2.1.10.1 | C39: Шпатлевка гипсовая_ / белая / Унифицированная по ПИК-СТАНДАРТ, 30кг | F39: кг | G39: 1.8 | I39: 14631.12
A40: 1.1.1.1.1.2.1.10.2 | C40: Грунтовка универсальный ЛАСТИМИН_ / LP-51 А | F40: кг | G40: 0.15 | I40: 1219.26
A41: 1.1.1.1.1.2.1.11 | B41: 6.3.1.5.2.1.8.5 | C41: Подготовка поверхности СКБ / стен / по штукатурке / 2мм | E41: 3 этаж. Шпаклевка финишная для высококачественной отделки. | F41: м2 | G41: 1 | I41: 7374
A42: 1.1.1.1.1.2.1.11.1 | C42: Грунтовка универсальный ЛАСТИМИН_ / LP-51 А | F42: кг | G42: 0.15 | I42: 1106.1
A43: 1.1.1.1.1.2.1.11.2 | C43: Шпатлевка гипсовая_ / белая / Унифицированная по ПИК-СТАНДАРТ, 30кг | F43: кг | G43: 1.8 | I43: 13273.2
A44: 1.1.1.1.1.2.1.12 | B44: 6.3.1.5.2.1.8.5 | C44: Подготовка поверхности СКБ / стен / по штукатурке / 2мм | E44: 2 этаж. Шпаклевка базовая. | F44: м2 | G44: 1 | I44: 8128.4
A45: 1.1.1.1.1.2.1.12.1 | C45: Шпатлевка гипсовая_ / белая / Унифицированная по ПИК-СТАНДАРТ, 30кг | F45: кг | G45: 1.8 | I45: 14631.12
A46: 1.1.1.1.1.2.1.12.2 | C46: Грунтовка универсальный ЛАСТИМИН_ / LP-51 А | F46: кг | G46: 0.15 | I46: 1219.26
A47: 1.1.1.1.1.2.1.13 | B47: 6.3.1.5.2.1.8.5 | C47: Подготовка поверхности СКБ / стен / по штукатурке / 2мм | E47: 3 этаж. Шпаклевка базовая. | F47: м2 | G47: 1 | I47: 7374
A48: 1.1.1.1.1.2.1.13.1 | C48: Грунтовка универсальный ЛАСТИМИН_ / LP-51 А | F48: кг | G48: 0.15 | I48: 1106.1
A49: 1.1.1.1.1.2.1.13.2 | C49: Шпатлевка гипсовая_ / белая / Унифицированная по ПИК-СТАНДАРТ, 30кг | F49: кг | G49: 1.8 | I49: 13273.2
A50: 1.1.1.1.1.2.1.14 | B50: 6.3.1.5.2.1.10.1 | C50: Штукатурка стен цементным, цементно-песчаным раствором с предварительной огрунтовкой / толщ. до 20 мм / высотой до 4 метров | E50: 2 этаж | F50: м2 | G50: 1 | I50: 0
A51: 1.1.1.1.1.2.1.14.1 | C51: Штукатурка цементная | E51: Штукатурка цементная Основит Техно РС21 M 25 кг | F51: кг | G51: 1.3 | I51: 0
A52: 1.1.1.1.1.2.1.14.2 | C52: Сетка штукатурная_/пластиковая/5*5 | F52: м2 | G52: 1.1 | I52: 0
A53: 1.1.1.1.1.2.1.14.3 | C53: Профиль маячковый_/ПМ6 | F53: пог. м | G53: 1 | I53: 0
A54: 1.1.1.1.1.2.1.14.4 | C54: Грунтовка БЕТОН-КОНТАКТ_/ | F54: кг | G54: 0.25 | I54: 0
A55: 1.1.1.1.1.2.1.15 | B55: 6.3.1.5.2.1.10.2 | C55: Штукатурка стен цементным, цементно-песчаным раствором с предварительной огрунтовкой / толщ. от 21 до 40 мм / высотой до 4 метров | E55: 2 этаж. Штукатурка по ЖБ. Толщина слоя согласованна с ПГ. | F55: м2 | G55: 1 | I55: 0
A56: 1.1.1.1.1.2.1.15.1 | C56: Штукатурка цементная | F56: кг | G56: 1.3 | I56: 0
A57: 1.1.1.1.1.2.1.15.2 | C57: Сетка штукатурная_/пластиковая/5*5 | F57: м2 | G57: 1.1 | I57: 0
A58: 1.1.1.1.1.2.1.15.3 | C58: Профиль маячковый_/ПМ6 | F58: пог. м | G58: 1 | I58: 0
A59: 1.1.1.1.1.2.1.15.4 | C59: Грунтовка БЕТОН-КОНТАКТ_/ | F59: кг | G59: 0.25 | I59: 0
A60: 1.1.1.1.1.2.1.16 | B60: 6.3.1.5.2.1.10.2 | C60: Штукатурка стен цементным, цементно-песчаным раствором с предварительной огрунтовкой / толщ. от 21 до 40 мм / высотой до 4 метров | E60: 2 этаж. Штукатурка по блоку, ГСП, ПГП. Толщина слоя согласованна с ПГ | F60: м2 | G60: 1 | I60: 0
A61: 1.1.1.1.1.2.1.16.1 | C61: Грунтовка универсальный ЛАСТИМИН_ / LP-51 А | F61: кг | G61: 0.15 | I61: 0
A62: 1.1.1.1.1.2.1.16.2 | C62: Профиль маячковый_/ПМ6 | F62: пог. м | G62: 1 | I62: 0
A63: 1.1.1.1.1.2.1.16.3 | C63: Сетка штукатурная_/пластиковая/5*5 | F63: м2 | G63: 1.1 | I63: 0
A64: 1.1.1.1.1.2.1.16.4 | C64: Штукатурка цементная | F64: кг | G64: 1.3 | I64: 0
A65: 1.1.1.1.1.2.1.17 | B65: 6.3.1.5.2.1.10.2 | C65: Штукатурка стен цементным, цементно-песчаным раствором с предварительной огрунтовкой / толщ. от 21 до 40 мм / высотой до 4 метров | E65: 3 этаж. Штукатурка по ЖБ. Толщина слоя согласованна с ПГ. | F65: м2 | G65: 1 | I65: 0
A66: 1.1.1.1.1.2.1.17.1 | C66: Штукатурка цементная | F66: кг | G66: 1.3 | I66: 0
A67: 1.1.1.1.1.2.1.17.2 | C67: Сетка штукатурная_/пластиковая/5*5 | F67: м2 | G67: 1.1 | I67: 0
A68: 1.1.1.1.1.2.1.17.3 | C68: Профиль маячковый_/ПМ6 | F68: пог. м | G68: 1 | I68: 0
A69: 1.1.1.1.1.2.1.17.4 | C69: Грунтовка БЕТОН-КОНТАКТ_/ | F69: кг | G69: 0.25 | I69: 0
A70: 1.1.1.1.1.2.1.18 | B70: 6.3.1.5.2.1.10.2 | C70: Штукатурка стен цементным, цементно-песчаным раствором с предварительной огрунтовкой / толщ. от 21 до 40 мм / высотой до 4 метров | E70: 3 этаж. Штукатурка по блоку, ГСП, ПГП. Толщина слоя согласованна с ПГ | F70: м2 | G70: 1 | I70: 0
A71: 1.1.1.1.1.2.1.18.1 | C71: Грунтовка универсальный ЛАСТИМИН_ / LP-51 А | F71: кг | G71: 0.15 | I71: 0
A72: 1.1.1.1.1.2.1.18.2 | C72: Профиль маячковый_/ПМ6 | F72: пог. м | G72: 1 | I72: 0
A73: 1.1.1.1.1.2.1.18.3 | C73: Сетка штукатурная_/пластиковая/5*5 | F73: м2 | G73: 1.1 | I73: 0
A74: 1.1.1.1.1.2.1.18.4 | C74: Штукатурка цементная | F74: кг | G74: 1.3 | I74: 0
A75: 1.1.1.1.1.2.1.19 | B75: 6.3.1.5.2.1.10.2 | C75: Штукатурка стен цементным, цементно-песчаным раствором с предварительной огрунтовкой / толщ. от 21 до 40 мм / высотой до 4 метров | E75: 2 этаж. Штукатурка по ЖБ. Толщина слоя согласованна с ПГ. | F75: м2 | G75: 1 | I75: 174.8
A76: 1.1.1.1.1.2.1.19.1 | C76: Штукатурка цементная | F76: кг | G76: 1.3 | I76: 7953.4
A77: 1.1.1.1.1.2.1.19.2 | C77: Сетка штукатурная_/пластиковая/5*5 | F77: м2 | G77: 1.1 | I77: 192.28
A78: 1.1.1.1.1.2.1.19.3 | C78: Профиль маячковый_/ПМ6 | F78: пог. м | G78: 1 | I78: 174.8
A79: 1.1.1.1.1.2.1.19.4 | C79: Грунтовка БЕТОН-КОНТАКТ_/ | F79: кг | G79: 0.25 | I79: 43.7
A80: 1.1.1.1.1.2.1.20 | B80: 6.3.1.5.2.1.10.2 | C80: Штукатурка стен цементным, цементно-песчаным раствором с предварительной огрунтовкой / толщ. от 21 до 40 мм / высотой до 4 метров | E80: 2 этаж. Штукатурка по блоку, ГСП, ПГП. Толщина слоя согласованна с ПГ | F80: м2 | G80: 1 | I80: 808
A81: 1.1.1.1.1.2.1.20.1 | C81: Грунтовка универсальный ЛАСТИМИН_ / LP-51 А | F81: кг | G81: 0.15 | I81: 121.2
A82: 1.1.1.1.1.2.1.20.2 | C82: Профиль маячковый_/ПМ6 | F82: пог. м | G82: 1 | I82: 808
A83: 1.1.1.1.1.2.1.20.3 | C83: Сетка штукатурная_/пластиковая/5*5 | F83: м2 | G83: 1.1 | I83: 888.8
A84: 1.1.1.1.1.2.1.20.4 | C84: Штукатурка цементная | F84: кг | G84: 1.3 | I84: 36764
A85: 1.1.1.1.1.2.1.21 | B85: 6.3.1.5.2.1.10.2 | C85: Штукатурка стен цементным, цементно-песчаным раствором с предварительной огрунтовкой / толщ. от 21 до 40 мм / высотой до 4 метров | E85: 3 этаж. Штукатурка по ЖБ. Толщина слоя согласованна с ПГ. | F85: м2 | G85: 1 | I85: 154.2
A86: 1.1.1.1.1.2.1.21.1 | C86: Штукатурка цементная | F86: кг | G86: 1.3 | I86: 7016.1
A87: 1.1.1.1.1.2.1.21.2 | C87: Сетка штукатурная_/пластиковая/5*5 | F87: м2 | G87: 1.1 | I87: 169.62
A88: 1.1.1.1.1.2.1.21.3 | C88: Профиль маячковый_/ПМ6 | F88: пог. м | G88: 1 | I88: 154.2
A89: 1.1.1.1.1.2.1.21.4 | C89: Грунтовка БЕТОН-КОНТАКТ_/ | F89: кг | G89: 0.25 | I89: 38.55
A90: 1.1.1.1.1.2.1.22 | B90: 6.3.1.5.2.1.10.2 | C90: Штукатурка стен цементным, цементно-песчаным раствором с предварительной огрунтовкой / толщ. от 21 до 40 мм / высотой до 4 метров | E90: 3 этаж. Штукатурка по блоку, ГСП, ПГП. Толщина слоя согласованна с ПГ | F90: м2 | G90: 1 | I90: 572.4
A91: 1.1.1.1.1.2.1.22.1 | C91: Грунтовка универсальный ЛАСТИМИН_ / LP-51 А | F91: кг | G91: 0.15 | I91: 85.86
A92: 1.1.1.1.1.2.1.22.2 | C92: Профиль маячковый_/ПМ6 | F92: пог. м | G92: 1 | I92: 572.4
A93: 1.1.1.1.1.2.1.22.3 | C93: Сетка штукатурная_/пластиковая/5*5 | F93: м2 | G93: 1.1 | I93: 629.64
A94: 1.1.1.1.1.2.1.22.4 | C94: Штукатурка цементная | F94: кг | G94: 1.3 | I94: 26044.2
A95: 1.1.1.1.1.2.1.23 | B95: 6.3.1.5.2.1.12.2 | C95: Штукатурка стен гипсовыми смесями с предварительной огрунтовкой СКБ / толщ. от 21 до 40 мм / высотой от 4,01 до 8 метров | E95: 2 этаж. Штукатурка по ЖБ. Толщина слоя согласованна с ПГ. | F95: м2 | G95: 1 | I95: 0
A96: 1.1.1.1.1.2.1.23.1 | C96: Штукатурка гипсовая_ / Унифицированная по ПИК-СТАНДАРТ, 30кг | F96: кг | G96: 1 | I96: 0
A97: 1.1.1.1.1.2.1.23.2 | C97: Профиль маячковый_/ПМ6 | F97: пог. м | G97: 1 | I97: 0
A98: 1.1.1.1.1.2.1.23.3 | C98: Грунтовка БЕТОН-КОНТАКТ_/ | F98: кг | G98: 0.25 | I98: 0
A99: 1.1.1.1.1.2.1.24 | B99: 6.3.1.5.2.1.12.2 | C99: Штукатурка стен гипсовыми смесями с предварительной огрунтовкой СКБ / толщ. от 21 до 40 мм / высотой от 4,01 до 8 метров | E99: 2 этаж. Штукатурка по блоку и ПГП. Толщина слоя согласованна с ПГ | F99: м2 | G99: 1 | I99: 0
A100: 1.1.1.1.1.2.1.24.1 | C100: Грунтовка универсальный ЛАСТИМИН_ / LP-51 А | F100: кг | G100: 0.15 | I100: 0
...

Sheet Плитки
A1: Марка | B1: Тип отделки | C1: Этаж -1 | D1: Этаж 01 | E1: Этаж 02 | F1: Этаж 03 | G1: Общий | N1: Старое РД
A2: СТ-1.1 | E2: 5092.4 | F2: 4104.6 | G2: =E2+F2 -> 9197 | I2: 2 и 3 этажи. СТ-1.1 | J2: 9197 | L2: =G2-J2 -> 0 | N2: 9779.3 | P2: =J2-N2 -> -582.3
A3: СТ-1.2 | B3: Краска матовая, моющаяся, влагостойкая, водно-дисперсионная на основе акриловой дисперсии, BRAVO PROFI FW-55, NCS S 2030-R80B, 1 класс истирания. Класс ПБ: Г1, В1, Д1 (КМ1) | C3: 0 | D3: 0 | E3: 7 | F3: 7 | G3: =E3+F3 -> 14 | I3: 2 и 3 этажи. СТ-1.2 | J3: 14 | L3: =G3-J3 -> 0 | N3: 8.4 | P3: =J3-N3 -> 5.6
A4: СТ-1.3 | B4: Краска матовая, моющаяся, влагостойкая, водно-дисперсионная на основе акриловой дисперсии, BRAVO PROFI FW-55, NCS S 5030-R90B, 1 класс истирания. Класс ПБ: Г1, В1, Д1 (КМ1) | C4: 0 | D4: 16.4 | E4: 18.7 | F4: 30.7 | G4: =E4+F4 -> 49.4 | I4: 2 и 3 этажи. СТ-1.3 | J4: 49.4 | L4: =G4-J4 -> 0 | N4: 55.3 | P4: =J4-N4 -> -5.9
A5: СТ-1.4 | B5: Краска матовая, моющаяся, влагостойкая, водно-дисперсионная на основе акриловой дисперсии, BRAVO PROFI FW-55, NCS S 1070-Y30R, 1 класс истирания. Класс ПБ: Г1, В1, Д1 (КМ1) | C5: 0 | D5: 0 | E5: 8.4 | F5: 24.4 | G5: =E5+F5 -> 32.8 | I5: 2 и 3 этажи. СТ-1.4 | J5: 32.8 | L5: =G5-J5 -> 0 | N5: 34.8 | P5: =J5-N5 -> -2
A6: СТ-1.5 | B6: Краска матовая, моющаяся, влагостойкая, водно-дисперсионная на основе акриловой дисперсии, BRAVO PROFI FW-55, NCS S 5020-R70B, 1 класс истирания. Класс ПБ: Г1, В1, Д1 (КМ1) | C6: 0 | D6: 0 | E6: 4 | F6: 3.9 | G6: =E6+F6 -> 7.9 | I6: 2 и 3 этажи. СТ-1.5 | J6: 7.9 | L6: =G6-J6 -> 0 | N6: 10.1 | P6: =J6-N6 -> -2.2
A7: СТ-1.7 | B7: Краска матовая, моющаяся, влагостойкая, водно-дисперсионная на основе акриловой дисперсии, BRAVO PROFI FW-55, NCS S 3040-R20B, 1 класс истирания. Класс ПБ: Г1, В1, Д1 (КМ1) | C7: 0 | D7: 9.6 | E7: 8.8 | F7: 9.3 | G7: =E7+F7 -> 18.1 | I7: 2 и 3 этажи. СТ-1.7 | J7: 18.1 | L7: =G7-J7 -> 0 | N7: 23.4 | P7: =J7-N7 -> -5.3
A8: СТ-1.8 | B8: Краска матовая, моющаяся, влагостойкая, водно-дисперсионная на основе акриловой дисперсии, BRAVO PROFI FW-55, NCS S 2060-G40Y, 1 класс истирания. Класс ПБ: Г1, В1, Д1 (КМ1) | C8: 0 | D8: 16.7 | E8: 15.9 | F8: 16.9 | G8: =E8+F8 -> 32.8 | I8: 2 и 3 этажи. СТ-1.8 | J8: 32.8 | L8: =G8-J8 -> 0 | N8: 43.7 | P8: =J8-N8 -> -10.9
A9: СТ-1.11 | N9: 78.4 | P9: =J9-N9 -> -78.4
A10: СТ-1.13 | N10: 742.1 | P10: =J10-N10 -> -742.1
A11: СТ-1.14 | B11: Краска матовая, моющаяся, влагостойкая, водно-дисперсионная на основе акриловой дисперсии, BRAVO PROFI FW-55, NCS S 4020-R90B, 1 класс истирания. Класс ПБ: Г1, В1, Д1 (КМ1) | C11: 0 | D11: 0 | E11: 2.8 | F11: 2.8 | G11: =E11+F11 -> 5.6 | I11: 2 и 3 этажи. СТ-1.14 | J11: 5.6 | L11: =G11-J11 -> 0 | P11: =J11-N11 -> 5.6
A12: СТ-1.16 | B12: Краска матовая, моющаяся, влагостойкая, водно-дисперсионная на основе акриловой дисперсии, BRAVO PROFI FW-55, NCS S 1502-Y, 1 класс истирания. Класс ПБ: Г1, В1, Д1 (КМ1) | C12: 0 | D12: 229.6 | E12: 355.8 | F12: 388.9 | G12: =E12+F12 -> 744.7 | I12: 2 и 3 этажи. СТ-1.16 | J12: 744.7 | L12: =G12-J12 -> 0 | P12: =J12-N12 -> 744.7
A13: СТ-2.1 | B13: Краска огнестойкая, матовая, моющаяся, влагостойкая водно-дисперсионная, силикатная BRAVO PROFI W-200 или аналог, белая RAL 9003, 2 класс истирания, НГ | C13: 1208 | D13: 2697.6 | E13: 1957.3 | F13: 1990.5 | G13: =E13+F13 -> 3947.8 | I13: 2 и 3 этажи. СТ-2.1 | J13: 3947.8 | L13: =G13-J13 -> 0 | N13: 4000.3 | P13: =J13-N13 -> -52.5
A14: СТ-2.2 | B14: Краска огнестойкая, матовая, моющаяся, влагостойкая водно-дисперсионная, силикатная BRAVO PROFI W-200 или аналог, NCS S 2030-R80B, 2 класс истирания, класс ПБ: НГ | C14: 0 | D14: 6.8 | E14: 0 | F14: 0 | G14: =E14+F14 -> 0 | L14: =G14-J14 -> 0 | P14: =J14-N14 -> 0
A15: СТ-2.3 | B15: Краска огнестойкая, матовая, моющаяся, влагостойкая водно-дисперсионная, силикатная BRAVO PROFI W-200 или аналог, RAL 7044, 2 класс истирания, класс ПБ: НГ | C15: 0 | D15: 89.4 | E15: 94.4 | F15: 0 | G15: =E15+F15 -> 94.4 | I15: 2 и 3 этажи. СТ-2.3 | J15: 94.4 | L15: =G15-J15 -> 0 | P15: =J15-N15 -> 94.4
A16: СТ-2.8 | B16: Краска огнестойкая, матовая, моющаяся, влагостойкая водно-дисперсионная, силикатная BRAVO PROFI W-200 или аналог, NCS S 4020-R90B, 2 класс истирания, НГ | C16: 0 | D16: 21.1 | E16: 0 | F16: 0 | G16: =E16+F16 -> 0
A17: СТ-2.10 | B17: Краска огнестойкая, матовая, моющаяся, влагостойкая водно-дисперсионная, силикатная BRAVO PROFI W-200 или аналог, NCS S 1502-Y, 2 класс истирания, НГ | C17: 0 | D17: 0 | E17: 0 | F17: 24.9 | G17: =E17+F17 -> 24.9 | I17: 2 и 3 этажи. СТ-2.10 | J17: 24.9 | L17: =G17-J17 -> 0 | N17: 23.2 | P17: =J17-N17 -> 1.7
A18: СТ-2.16 | B18: Краска огнестойкая, матовая, моющаяся, влагостойкая водно-дисперсионная, силикатная BRAVO PROFI W-200 или аналог, RAL 7016, 2 класс истирания, НГ | C18: 0 | D18: 671.4 | E18: 458.6 | F18: 191.2 | G18: =E18+F18 -> 649.8 | I18: 2 и 3 этажи. СТ-2.16 | J18: 649.8 | L18: =G18-J18 -> 0 | N18: 239.5 | P18: =J18-N18 -> 410.3
A19: СТ-2.17 | B19: Краска огнестойкая, матовая, моющаяся, влагостойкая водно-дисперсионная, силикатная BRAVO PROFI W-200 или аналог, NCS S 2060-Y30R, 2 класс истирания, НГ | C19: 0 | D19: 22 | E19: 0 | F19: 0 | G19: =E19+F19 -> 0
A20: СТ-6.1 | B20: Керамическая плитка Kerama Marazzi Калейдоскоп белый 5009 200х200х6,9мм. Затирка Ceresit CE 33, 04 серебристо-серый, крестик 2мм. Класс ПБ: НГ | C20: 0 | D20: 382.5 | E20: 201.8 | F20: 152 | G20: =E20+F20 -> 353.8 | I20: 2 и 3 этажи. СТ-6.1 | J20: 353.8 | L20: =G20-J20 -> 0 | N20: 365.8 | P20: =J20-N20 -> -12
A21: СТ-6.2 | B21: Керамическая плитка KERAMA MARAZZI мозаика Таделакт KM3030M0161N синий светлый матовый, 298х298х3,5 мм. Класс ПБ: НГ. Крестик: 2 мм | C21: 0 | D21: 34.7 | E21: 38.7 | F21: 21 | G21: =E21+F21 -> 59.7 | I21: 2 и 3 этажи. СТ-6.2 | J21: 59.7 | L21: =G21-J21 -> 0 | N21: 48.3 | P21: =J21-N21 -> 11.4
A22: СТ-6.3 | B22: Керамическая плитка KERAMA MARAZZI мозаика Таделакт KM3030M0181N красный матовый, 298х298х3.5 мм. Класс ПБ: НГ. Крестик: 2 мм | C22: 0 | D22: 86.2 | E22: 64 | F22: 43.8 | G22: =E22+F22 -> 107.8 | I22: 2 и 3 этажи. СТ-6.3 | J22: 107.8 | L22: =G22-J22 -> 0 | N22: 91.8 | P22: =J22-N22 -> 16
A23: СТ-6.4 | N23: 11.5 | P23: =J23-N23 -> -11.5
A24: СТ-6.5 | N24: 16.3 | P24: =J24-N24 -> -16.3
A25: СТ-7 | B25: Керамическая плитка Керама Марацци арт. 11037TR (1,8м 10пл) Парус белый матовый обрезной 300x600x9 мм. Затирка Ceresit CE 33, 04 серебристо-серый, крестик 2мм, НГ | C25: 0 | D25: 169.5 | E25: 0 | F25: 0 | G25: =E25+F25 -> 0
A26: СТ-8 | B26: Керамическая плитка, Kerama Marazzi Белое солнце 8000, 300х200х6,9мм, затирка Ceresit CE 33, 04 серебристо-серая, крестик 2мм. Класс ПБ: НГ | C26: 0 | D26: 1784.9 | E26: 171.1 | F26: 125.1 | G26: =E26+F26 -> 296.2 | I26: 2 и 3 этажи. СТ-8 | J26: 296.2 | L26: =G26-J26 -> 0 | N26: 302.8 | P26: =J26-N26 -> -6.6
A27: СТ-10 | B27: Керамическая плитка, Kerama Marazzi Про Матрикс серый светлый OS\C314\11259R, 300х600х9мм, затирка Ceresit 07 серый, НГ | C27: 0 | D27: 204.1 | E27: 0 | F27: 0 | G27: =E27+F27 -> 0 | L27: =G27-J27 -> 0 | P27: =J27-N27 -> 0
A28: СТ-11 | B28: Керамическая плитка, 300х600х9мм, Kerama Marazzi Про Матрикс 11259R, серый светлый, НГ. Затирка Ceresit СЕ 33, 04 серебристо-серый; крестик 2 мм | C28: 0 | D28: 397.1 | E28: 400.4 | F28: 351.3 | G28: =E28+F28 -> 751.7 | I28: 2 и 3 этажи. СТ-11 | J28: 751.7 | L28: =G28-J28 -> 0 | N28: 751.5 | P28: =J28-N28 -> 0.2
A29: СТ-12 | B29: Зеркало (заподлицо с плиткой), толщина 4 мм, подготовка: шпаклевка+грунт | C29: 0 | D29: 24 | E29: 11.6 | F29: 12.8 | G29: =E29+F29 -> 24.4 | L29: =G29-J29 -> 24.4 | N29: 24.5 | P29: =J29-N29 -> -24.5
A30: СТ-14 | B30: Плитка керамическая Kerama Marazzi, Аккорд 9010, 85х285х9,2 мм, белый; крестик 2 мм, затирка Ceresit CE33 04 Серебристо-серый, НГ | C30: 0 | D30: 4.3 | E30: 3.9 | F30: 3.9 | G30: =E30+F30 -> 7.8 | I30: 2 и 3 этажи. СТ-14 | J30: 7.8 | L30: =G30-J30 -> 0 | N30: 8.3 | P30: =J30-N30 -> -0.5
A31: СТ-15 | B31: Магнитно-маркерное покрытие, белый RAL 9003 | C31: 0 | D31: 0 | E31: 0 | F31: 3.8 | G31: =E31+F31 -> 3.8 | L31: =G31-J31 -> 3.8

Sheet Пом
A1: Этаж | B1: Пом | C1: Тип | D1: Объем
A2: 2 | B2: 2.001 | C2: СТ-1.1 | D2: 136.6
A3: 2 | B3: 2.001 | C3: СТ-1.13 | D3: 64.4
A4: 2 | B4: 2.001 | C4: СТ-6.1 | D4: 1.3
A5: 2 | B5: 2.002 | C5: СТ-6.1 | D5: 1
A6: 2 | B6: 2.003 | C6: СТ-1.1 | D6: 299.8
A7: 2 | B7: 2.003 | C7: СТ-1.2 | D7: 8.4
A8: 2 | B8: 2.004 | C8: СТ-1.1 | D8: 115.2
A9: 2 | B9: 2.005 | C9: СТ-1.1 | D9: 56.4
A10: 2 | B10: 2.006 | C10: СТ-0 | D10: 0
A11: 2 | B11: 2.007 | C11: СТ-2.1 | D11: 73.5
A12: 2 | B12: 2.008 | C12: СТ-2.1 | D12: 104
A13: 2 | B13: 2.009 | C13: СТ-2.1 | D13: 49.3
... A160: 3 | B160: 3.010 | C160: СТ-6.1 | D160: 2.5
A161: 3 | B161: 3.011 | C161: СТ-1.1 | D161: 134,4
A162: 3 | B162: 3.011 | C162: СТ-6.1 | D162: 3,5
A163: 3 | B163: 3.012 | C163: СТ-1.1 | D163: 336.5
A164: 3 | B164: 3.012 | C164: СТ-1.3 | D164: 34.7
A165: 3 | B165: 3.012 | C165: СТ-14 | D165: 1.8
A166: 3 | B166: 3.013 | C166: СТ-1.1 | D166: 91.2
A167: 3 | B167: 3.013 | C167: СТ-1.13 | D167: 16.4
A168: 3 | B168: 3.013 | C168: СТ-6.1 | D168: 3.8
A169: 3 | B169: 3.014 | C169: СТ-1.1 | D169: 80.9
A170: 3 | B170: 3.014 | C170: СТ-1.13 | D170: 28.3
A171: 3 | B171: 3.014 | C171: СТ-6.1 | D171: 1.7
A172: 3 | B172: 3.015 | C172: СТ-2.16 | D172: 13.6
A173: 3 | B173: 3.015 | C173: СТ-6.4 | D173: 5.8
A174: 3 | B174: 3.015 | C174: СТ-11 | D174: 67.8
... A269: 3 | B269: 3.067 | C269: СТ-2.1 | D269: 24.3

Sheet 7.4Блок
A1: Ведомость работ
A2: № п.п. | B2: Наименование затрат | F2: Ед. изм. | G2: Объем
A3: 1 | B3: Кладка внутренних стен из блоков ячеистого бетона без устройства перемычек, включая армирование, устройство примыканий | F3: м3 | G3: 30.4
A4: 2 | B4: Кладка внутренних стен из блоков ячеистого бетона без устройства перемычек, включая армирование, устройство примыканий | F4: м3 | G4: 0.7
A5: 3 | B5: Кладка внутренних стен из блоков ячеистого бетона без устройства перемычек, включая армирование, устройство примыканий | F5: м3 | G5: 61.3
A6: 4 | B6: Кладка внутренних стен из блоков ячеистого бетона без устройства перемычек, включая армирование, устройство примыканий | F6: м3 | G6: 30.9

Sheet 7.3Кирп1э
A1: Ведомость работ
A2: № п.п. | B2: Наименование затрат | F2: Ед. изм. | G2: Объем
A3: 1 | B3: Кладка стен из кирпича без устройства перемычек, включая армирование, крепление к стенам, заделку примыканий, зачеканку швов | F3: м3 | G3: 1.3
A4: 2 | B4: Кладка стен из кирпича без устройства перемычек, включая армирование, крепление к стенам, заделку примыканий, зачеканку швов | F4: м3 | G4: 0.2

Sheet 7.2КирпПодв
A1: Ведомость работ
A2: № п.п. | B2: Наименование затрат | F2: Ед. изм. | G2: Объем
A3: 1 | B3: Кладка стен из кирпича без устройства перемычек, включая армирование, крепление к стенам, заделку примыканий, зачеканку швов | F3: м3 | G3: =B17 -> 21.897842
A4: 2 | B4: Устройство перемычек металлических с огрунтовкой и окраской | F4: т | G4: 0.023
A6: № п.п. | B6: Объем, м3.
A7: 1 | B7: =7.72-0.525 -> 7.195
A8: 2 | B8: =0.6125*3.15-1.8821*1.1*0.25 -> 1.4117975
A9: 3 | B9: =0.696*3.15-0.7*2.1*0.12*4 -> 1.4868
A10: 4 | B10: =0.5625*3.15-0.156 -> 1.615875
A11: 5 | B11: =0.4188*3.15--0.7*2.1*0.12*2 -> 1.67202
A12: 6 | B12: =0.45*3.15-1*2.2*0.25 -> 0.8675
A13: 7 | B13: =0.125*3.15+0.0375*3.15 -> 0.511875
A14: 8 | B14: =0.45*3.15-1*2.2*0.25 -> 0.8675
A15: 9 | B15: =3.9*3.15*0.25-0.25*2.1 -> 2.54625
A16: 10 | B16: =0.9875*3.15-0.294*2.1+0.4*3.15-0.03 -> 3.723225
A17: сумм | B17: =SUM(B7:B16) -> 21.897842

Sheet 7.1ПГП
A1: Ведомость работ
A2: № п.п. | B2: № поз. | C2: Наименование затрат | G2: Описание | J2: Ед. изм. | K2: Объем
A3: 1 | B3: 72 | C3: Устройство перегородок из ПГП без устройства перемычек, включая проклейку углов примыкания армирующей лентой, толщ. до 115 мм | G3: АРОР от 19.02.2026г. ООО "Транс-Групп" - ООО "МФ-СТРОЙ" | J3: м2 | K3: 128.3
A4: 2 | B4: 78 | C4: Устройство перегородок из ПГП без устройства перемычек, включая проклейку углов примыкания армирующей лентой, толщ. до 115 мм | G4: ПГП-влагостойкий. АРОР от 19.02.2026г. ООО "Транс-Групп" - ООО "МФ-СТРОЙ" | J4: м2 | K4: 317.6
A5: 3 | B5: 84 | C5: Устройство перегородок из ПГП без устройства перемычек, включая проклейку углов примыкания армирующей лентой, толщ. до 115 мм | G5: АРОР от 19.02.2026г. ООО "Транс-Групп" - ООО "МФ-СТРОЙ" | J5: м2 | K5: 350.5
A6: 4 | B6: 90 | C6: Устройство перегородок из ПГП без устройства перемычек, включая проклейку углов примыкания армирующей лентой, толщ. до 115 мм | G6: ПГП-влагостойкий. АРОР от 19.02.2026г. ООО "Транс-Групп" - ООО "МФ-СТРОЙ" | J6: м2 | K6: 543.3
A7: 5 | B7: 96 | C7: Устройство перегородок из ПГП без устройства перемычек, включая проклейку углов примыкания армирующей лентой, толщ. до 115 мм | G7: АРОР от 19.02.2026г. ООО "Транс-Групп" - ООО "МФ-СТРОЙ" | J7: м2 | K7: 814.7
A8: 6 | B8: 102 | C8: Устройство перегородок из ПГП без устройства перемычек, включая проклейку углов примыкания армирующей лентой, толщ. до 115 мм | G8: ПГП-влагостойкий. АРОР от 19.02.2026г. ООО "Транс-Групп" - ООО "МФ-СТРОЙ" | J8: м2 | K8: 200.8
A10: № п.п. | B10: № пом. | C10: ОбЪем, м2 (Влагост.). | E10: № п.п. | F10: № пом. | G10: ОбЪем, м2 (Влагост.).
A11: 1 | B11: 1002 | C11: 3.24 | E11: 28 | F11: 1058 | G11: 19.4
A12: 2 | B12: 1003 | C12: 34.08 | E12: 29 | F12: 1059 | G12: 19.4
A13: 5 | B13: 1010 | C13: 7.68 | E13: 30 | F13: 1061 | G13: 48.2
A14: 6 | B14: 1013 | C14: 17.16 | E14: 31 | F14: 1063 | G14: 35
A15: 7 | B15: 1014 | C15: 32.4 | E15: 32 | F15: 1064 | G15: 18.2
A16: 8 | B16: 1015 | C16: 19.2 | E16: 33 | F16: 1065 | G16: 9.2
A17: 10 | B17: 1019 | C17: 32.4 | E17: 34 | F17: 1066 | G17: 21.8
A18: 11 | B18: 1022 | C18: 49.2 | E18: 35 | F18: 1069 | G18: 24.2
A19: 12 | B19: 1025 | C19: 15.6 | E19: 36 | F19: 1070 | G19: 42.2
A20: 13 | B20: 1027 | C20: 21.6 | E20: 37 | F20: 1072 | G20: 1.76
A21: 14 | B21: 1028 | C21: 8.4 | E21: 38 | F21: 1076 | G21: 29
A22: 15 | B22: 1029 | C22: 4.8 | E22: 39 | F22: 1077 | G22: 23
... A33: 26 | B33: 1054 | C33: 36 | E33: 50 | F33: 1102 | G33: 9.8
C34: =SUM(C11:C33) -> 570.24 | E34: 51 | F34: 1104 | G34: 20.6
E35: 52 | F35: 1105 | G35: 8.6
E36: 54 | F36: 1109 | G36: 9.8
E37: 55 | F37: 1112 | G37: 7.64
G38: =SUM(G11:G37) -> 491.46
A39: ПГП-влагостойкий. | D39: =C34+G38 -> 1061.7

Sheet 6.1ГКЛ
A1: Ведомость работ
A2: № п.п. | B2: Наименование затрат | H2: Описание | J2: Ед. изм. | K2: Объем
A3: 1 | H3: 2 этаж | J3: м2
A4: 2 | B4: 2 | H4: 3 этаж | J4: м2
A6: № пом. | B6: Тип пола | C6: Площадь, м2. | E6: № пом. | F6: Тип пола | G6: Площадь, м2.
F11: Итог: | G11: =SUM(G7:G10) -> 0
B42: Итог: | C42: =SUM(C7:C41) -> 0

Sheet 5.3_остаток
A1: Ведомость работ
A2: № п.п | B2: Наименование затрат | G2: Описание | H2: Ед. изм. | I2: Объем | L2: Надо закрыть
A3: 1 | B3: Облицовка поверхности стен СКБ с затиркой швов / керамической, керамогранитной плиткой до 0,2м2/шт | G3: СТ-6.1 | H3: м2 | I3: =SUM(SUMIF($C$11:$C$36, G3, $D$11:$D$36), SUMIF($H$11:$H$38, G3, $I$11:$I$38)) -> 143.34 | K3: СТ-6.1 | L3: 145.2 | N3: =I3-L3 -> -1.86
A4: 2 | B4: Облицовка поверхности стен СКБ с затиркой швов / керамической, керамогранитной плиткой до 0,2м2/шт | G4: СТ-6.2 | H4: м2 | I4: =SUM(SUMIF($C$11:$C$36, G4, $D$11:$D$36), SUMIF($H$11:$H$38, G4, $I$11:$I$38)) -> 47.6 | K4: СТ-6.2 | L4: 48.2 | N4: =I4-L4 -> -0.6
A5: 3 | B5: Облицовка поверхности стен СКБ с затиркой швов / керамической, керамогранитной плиткой до 0,2м2/шт | G5: СТ-6.3 | H5: м2 | I5: =SUM(SUMIF($C$11:$C$36, G5, $D$11:$D$36), SUMIF($H$11:$H$38, G5, $I$11:$I$38)) -> 78.015 | K5: СТ-6.3 | L5: 79.7 | N5: =I5-L5 -> -1.685
A6: 4 | B6: Облицовка поверхности стен СКБ с затиркой швов / керамической, керамогранитной плиткой до 0,2м2/шт | G6: СТ-8 | H6: м2 | I6: =SUM(SUMIF($C$11:$C$36, G6, $D$11:$D$36), SUMIF($H$11:$H$38, G6, $I$11:$I$38)) -> 78.84 | K6: СТ-8 | L6: 85.8 | N6: =I6-L6 -> -6.96
A7: 5 | B7: Облицовка поверхности стен СКБ с затиркой швов / керамической, керамогранитной плиткой до 0,2м2/шт | G7: СТ-11 | H7: м2 | I7: =SUM(SUMIF($C$11:$C$36, G7, $D$11:$D$36), SUMIF($H$11:$H$38, G7, $I$11:$I$38)) -> 486.008 | K7: СТ-11 | L7: 486.6 | N7: =I7-L7 -> -0.592
A8: 6 | B8: Облицовка поверхности стен СКБ с затиркой швов / керамической, керамогранитной плиткой до 0,2м2/шт | G8: СТ-14 | H8: м2 | I8: =SUM(SUMIF($C$11:$C$36, G8, $D$11:$D$36), SUMIF($H$11:$H$38, G8, $I$11:$I$38)) -> 7.8 | K8: СТ-14 | L8: 7.8 | N8: =I8-L8 -> 0
A10: Этаж | B10: Пом | C10: Тип | D10: Объем | F10: Этаж | G10: Пом | H10: Тип | I10: Объем
A11: 2 | B11: 2.026 | C11: СТ-6.3 | D11: =L11*3 -> 13.8 | F11: 3 | G11: 3.064 | H11: СТ-6.2 | I11: =N11*2.9 -> 7.105 | L11: 4.6 | N11: 2.45
A12: 2 | B12: 2.026 | C12: СТ-11 | D12: =L12*3.8 -> 44.84 | F12: 3 | G12: 3.064 | H12: СТ-11 | I12: =N12*3.5 -> 50.225 | L12: 11.8 | N12: 14.35
A13: 2 | B13: 2.027 | C13: СТ-6.3 | D13: =L13*3 -> 10.5 | F13: 3 | G13: 3.055 | H13: СТ-6.3 | I13: =N13*3 -> 8.1 | L13: 3.5 | N13: 2.7
A14: 2 | B14: 2.027 | C14: СТ-11 | D14: =L14*3.7 -> 32.005 | F14: 3 | G14: 3.055 | H14: СТ-11 | I14: =N14*3.7 -> 50.912 | L14: 8.65 | N14: 13.76
A15: 2 | B15: 2.031 | C15: СТ-6.1 | D15: =L15*1.8 -> 22.68 | F15: 3 | G15: 3.057 | H15: СТ-6.3 | I15: =N15*3 -> 9.45 | L15: 12.6 | N15: 3.15
A16: 2 | B16: 2.032 | C16: СТ-6.3 | D16: =L16*2 -> 7.6 | F16: 3 | G16: 3.057 | H16: СТ-11 | I16: =N16*3.7 -> 33.855 | L16: 3.8 | N16: 9.15
A17: 2 | B17: 2.032 | C17: СТ-11 | D17: =L17*3.7 -> 32.93 | F17: 3 | G17: 3.042 | H17: СТ-6.1 | I17: =N17*1.3 -> 26.975 | L17: 8.9 | N17: 20.75
A18: 2 | B18: 2.065 | C18: СТ-8 | D18: =L18*3 -> 24.6 | F18: 3 | G18: 3.042 | H18: СТ-6.2 | I18: =N18*2.9 -> 8.265 | L18: 8.2 | N18: 2.85
A19: 2 | B19: 2.029 | C19: СТ-6.2 | D19: =L19*2 -> 7 | F19: 3 | G19: 3.044 | H19: СТ-8 | I19: =N19*3.2 -> 27.84 | L19: 3.5 | N19: 8.7
A20: 2 | B20: 2.029 | C20: СТ-11 | D20: =L20*3.7 -> 30.636 | F20: 3 | G20: 3.045 | H20: СТ-6.1 | I20: =N20*2.9 -> 20.735 | L20: 8.28 | N20: 7.15
A21: 2 | B21: 2.028 | C21: СТ-6.2 | D21: =L21*2.9 -> 16.965 | F21: 3 | G21: 3.045 | H21: СТ-6.3 | I21: =N21*3 -> 7.05 | L21: 5.85 | N21: 2.35
A22: 2 | B22: 2.028 | C22: СТ-11 | D22: =L22*3.7 -> 59.755 | F22: 3 | G22: 3.043 | H22: СТ-6.1 | I22: =N22*1.2 -> 26.82 | L22: 16.15 | N22: 22.35
A23: 2 | B23: 2.051 | C23: СТ-6.2 | D23: =L23*2.9 -> 8.265 | F23: 3 | G23: 3.043 | H23: СТ-6.3 | I23: =N23*3 -> 8.55 | L23: 2.85 | N23: 2.85
A24: 2 | B24: 2.051 | C24: СТ-11 | D24: =L24*3.5 -> 72.625 | F24: 3 | G24: 3.012 | H24: СТ-14 | I24: 2 | L24: 20.75
A25: 2 | B25: .2.052 | C25: СТ-8 | D25: =L25*3 -> 26.4 | F25: 3 | G25: 3.041 | H25: СТ-14 | I25: 1.9 | L25: 8.8
A26: 2 | B26: 2.053 | C26: СТ-6.1 | D26: =L26*2 -> 14.3 | F26: 3 | G26: Классы | H26: СТ-6.1 | I26: =26.633*0.6 -> 15.9798 | L26: 7.15
A27: 2 | B27: 2.053 | C27: СТ-6.3 | D27: =L27*2 -> 4.7 | L27: 2.35
A28: 2 | B28: 2.054 | C28: СТ-6.3 | D28: =L28*2.9 -> 8.265 | L28: 2.85
A29: 2 | B29: 2.054 | C29: СТ-11 | D29: =L29*3.5 -> 78.225 | L29: 22.35
A30: 2 | B30: 2.017 | C30: СТ-14 | D30: 2
A31: 2 | B31: 2.049 | C31: СТ-14 | D31: 1.9
A32: 2 | B32: Классы | C32: СТ-6.1 | D32: =26.417*0.6 -> 15.8502
K34: СТ-12 | L34: 11.64 | M34: 12.8
K38: Марка | L38: Расход | M38: Расход
K39: СТ-6.1 | L39: 201.83 | M39: 152.3 | O39: =SUM(L39:N39) -> 354.13 | P39: 353.8 | Q39: =O39-P39 -> 0.33 | R39: 2 и 3 этажи. СТ-6.1 | S39: 208.6 | U39: =P39-S39 -> 145.2
K40: СТ-6.2 | L40: 38.68 | M40: 21 | O40: =SUM(L40:N40) -> 59.68 | P40: 59.7 | Q40: =O40-P40 -> -0.02 | R40: 2 и 3 этажи. СТ-6.2 | S40: 11.5 | U40: =P40-S40 -> 48.2
K41: СТ-6.3 | L41: 69.02 | M41: 43.8 | O41: =SUM(L41:N41) -> 112.82 | P41: 107.8 | Q41: =O41-P41 -> 5.02 | R41: 2 и 3 этажи. СТ-6.3 | S41: 28.1 | U41: =P41-S41 -> 79.7
K42: СТ-8 | L42: 171.07 | M42: 125.1 | O42: =SUM(L42:N42) -> 296.17 | P42: 296.2 | Q42: =O42-P42 -> -0.03 | R42: 2 и 3 этажи. СТ-8 | S42: 210.4 | U42: =P42-S42 -> 85.8
K43: СТ-11 | L43: 405.15 | M43: 351.3 | O43: =SUM(L43:N43) -> 756.45 | P43: 751.7 | Q43: =O43-P43 -> 4.75 | R43: 2 и 3 этажи. СТ-11 | S43: 265.1 | U43: =P43-S43 -> 486.6
K44: СТ-14 | L44: 3.94 | M44: 4 | O44: =SUM(L44:N44) -> 7.94 | P44: 7.8 | Q44: =O44-P44 -> 0.14 | U44: =P44-S44 -> 7.8
K45: РД | L45: =SUM(L39:L44) -> 889.69 | M45: =SUM(M39:M44) -> 697.5
K46: 1 вып | L46: =SUM(L63:L73) -> 369.5
K47: 2 вып
J49: Пом | K49: Тип | L49: Объем | N49: Этаж | O49: Пом | P49: Тип | Q49: Объем
J50: 2.010 | K50: СТ-11 | N50: 3 | O50: 3.009 | P50: СТ-11
J51: 2.018 | K51: СТ-11 | N51: 3 | O51: 3.015 | P51: СТ-11
J52: 2.020 | K52: СТ-6.1 | N52: 3 | O52: 3.017 | P52: СТ-6.1
J53: 2.021 | K53: СТ-6.1 | N53: 3 | O53: 3.018 | P53: СТ-6.1
J54: 2.034 | K54: СТ-6.1 | N54: 3 | O54: 3.025 | P54: СТ-6.1
J55: 2.018 | K55: СТ-6.2 | N55: 3 | O55: 3.015 | P55: СТ-6.2
J56: 2.010 | K56: СТ-6.3 | N56: 3 | O56: 3.009 | P56: СТ-6.3
J57: 2.020 | K57: СТ-6.3 | N57: 3 | O57: 3.017 | P57: СТ-6.3
J58: 2.011 | K58: СТ-8 | N58: 3 | O58: 3.008 | P58: СТ-8
J59: 2.059 | K59: СТ-8 | N59: 3 | O59: 3.026 | P59: СТ-8
J60: 2.035 | K60: СТ-8 | N60: 3 | O60: 3.029 | P60: СТ-8
J62: Пом | K62: Тип | L62: Объем | N62: Этаж | O62: Пом | P62: Тип | Q62: Объем
J63: 2.010 | K63: СТ-11 | L63: 66.4 | N63: 3 | O63: 3.009 | P63: СТ-11 | Q63: 65.8
J64: 2.018 | K64: СТ-11 | L64: 65.1 | N64: 3 | O64: 3.015 | P64: СТ-11 | Q64: 67.8
J65: 2.020 | K65: СТ-6.1 | L65: 31.6 | N65: 3 | O65: 3.017 | P65: СТ-6.1 | Q65: 35.4
J66: 2.021 | K66: СТ-6.1 | L66: 36.9 | N66: 3 | O66: 3.018 | P66: СТ-6.1 | Q66: 29.5
J67: 2.034 | K67: СТ-6.1 | L67: 38.3 | N67: 3 | O67: 3.025 | P67: СТ-6.1 | Q67: 36.9
J68: 2.018 | K68: СТ-6.2 | L68: 5.7 | N68: 3 | O68: 3.015 | P68: СТ-6.2 | Q68: 5.8
J69: 2.010 | K69: СТ-6.3 | L69: 8.2 | N69: 3 | O69: 3.009 | P69: СТ-6.3 | Q69: 8.1
J70: 2.020 | K70: СТ-6.3 | L70: 5.9 | N70: 3 | O70: 3.017 | P70: СТ-6.3 | Q70: 5.9
J71: 2.011 | K71: СТ-8 | L71: 33.3 | N71: 3 | O71: 3.008 | P71: СТ-8 | Q71: 33
J72: 2.059 | K72: СТ-8 | L72: 33.9 | N72: 3 | O72: 3.026 | P72: СТ-8 | Q72: 36.5
J73: 2.035 | K73: СТ-8 | L73: 44.2 | N73: 3 | O73: 3.029 | P73: СТ-8 | Q73: 29.5

Sheet 5.2Плт
A1: Ведомость работ
A2: № п.п | B2: Наименование затрат | G2: Описание | H2: Ед. изм. | I2: Объем
A3: 1 | B3: Облицовка поверхности стен СКБ с затиркой швов / керамической, керамогранитной плиткой до 0,2м2/шт | G3: СТ-6.1 | H3: м2 | I3: =SUM(SUMIF($C$11:$C$32, G3, $D$11:$D$32), SUMIF($H$11:$H$32, G3, $I$11:$I$32)) -> 143.34
A4: 2 | B4: Облицовка поверхности стен СКБ с затиркой швов / керамической, керамогранитной плиткой до 0,2м2/шт | G4: СТ-6.2 | H4: м2 | I4: =SUM(SUMIF($C$11:$C$32, G4, $D$11:$D$32), SUMIF($H$11:$H$32, G4, $I$11:$I$32)) -> 47.6
A5: 3 | B5: Облицовка поверхности стен СКБ с затиркой швов / керамической, керамогранитной плиткой до 0,2м2/шт | G5: СТ-6.3 | H5: м2 | I5: =SUM(SUMIF($C$11:$C$32, G5, $D$11:$D$32), SUMIF($H$11:$H$32, G5, $I$11:$I$32)) -> 78.015
A6: 4 | B6: Облицовка поверхности стен СКБ с затиркой швов / керамической, керамогранитной плиткой до 0,2м2/шт | G6: СТ-8 | H6: м2 | I6: =SUM(SUMIF($C$11:$C$32, G6, $D$11:$D$32), SUMIF($H$11:$H$32, G6, $I$11:$I$32)) -> 78.84
A7: 5 | B7: Облицовка поверхности стен СКБ с затиркой швов / керамической, керамогранитной плиткой до 0,2м2/шт | G7: СТ-11 | H7: м2 | I7: =SUM(SUMIF($C$11:$C$32, G7, $D$11:$D$32), SUMIF($H$11:$H$32, G7, $I$11:$I$32)) -> 486.008
A8: 6 | B8: Облицовка поверхности стен СКБ с затиркой швов / керамической, керамогранитной плиткой до 0,2м2/шт | G8: СТ-14 | H8: м2 | I8: =SUM(SUMIF($C$11:$C$32, G8, $D$11:$D$32), SUMIF($H$11:$H$32, G8, $I$11:$I$32)) -> 7.8
A10: Этаж | B10: Пом | C10: Тип | D10: Объем | F10: Этаж | G10: Пом | H10: Тип | I10: Объем
A11: 2 | B11: 2.026 | C11: СТ-6.3 | D11: 13.8 | F11: 3 | G11: 3.064 | H11: СТ-6.2 | I11: 7.105
A12: 2 | B12: 2.026 | C12: СТ-11 | D12: 44.84 | F12: 3 | G12: 3.064 | H12: СТ-11 | I12: 50.225
A13: 2 | B13: 2.027 | C13: СТ-6.3 | D13: 10.5 | F13: 3 | G13: 3.055 | H13: СТ-6.3 | I13: 8.1
A14: 2 | B14: 2.027 | C14: СТ-11 | D14: 32.005 | F14: 3 | G14: 3.055 | H14: СТ-11 | I14: 50.912
A15: 2 | B15: 2.031 | C15: СТ-6.1 | D15: 22.68 | F15: 3 | G15: 3.057 | H15: СТ-6.3 | I15: 9.45
A16: 2 | B16: 2.032 | C16: СТ-6.3 | D16: 7.6 | F16: 3 | G16: 3.057 | H16: СТ-11 | I16: 33.855
A17: 2 | B17: 2.032 | C17: СТ-11 | D17: 32.93 | F17: 3 | G17: 3.042 | H17: СТ-6.1 | I17: 26.975
A18: 2 | B18: 2.065 | C18: СТ-8 | D18: 24.6 | F18: 3 | G18: 3.042 | H18: СТ-6.2 | I18: 8.265
A19: 2 | B19: 2.029 | C19: СТ-6.2 | D19: 7 | F19: 3 | G19: 3.044 | H19: СТ-8 | I19: 27.84
A20: 2 | B20: 2.029 | C20: СТ-11 | D20: 30.636 | F20: 3 | G20: 3.045 | H20: СТ-6.1 | I20: 20.735
A21: 2 | B21: 2.028 | C21: СТ-6.2 | D21: 16.965 | F21: 3 | G21: 3.045 | H21: СТ-6.3 | I21: 7.05
A22: 2 | B22: 2.028 | C22: СТ-11 | D22: 59.755 | F22: 3 | G22: 3.043 | H22: СТ-6.1 | I22: 26.82
... A26: 2 | B26: 2.053 | C26: СТ-6.1 | D26: 14.3 | F26: 3 | G26: Классы | H26: СТ-6.1 | I26: 15.9798
A27: 2 | B27: 2.053 | C27: СТ-6.3 | D27: 4.7
A28: 2 | B28: 2.054 | C28: СТ-6.3 | D28: 8.265
A29: 2 | B29: 2.054 | C29: СТ-11 | D29: 78.225
A30: 2 | B30: 2.017 | C30: СТ-14 | D30: 2
A31: 2 | B31: 2.049 | C31: СТ-14 | D31: 1.9
A32: 2 | B32: Классы | C32: СТ-6.1 | D32: 15.8502

Sheet 5.1_плтк
A1: Ведомость работ
A2: № п.п | B2: Наименование затрат | G2: Описание | H2: Ед. изм. | I2: Объем
A3: 1 | B3: Облицовка поверхности стен СКБ с затиркой швов / керамической, керамогранитной плиткой до 0,2м2/шт | G3: 2 и 3 этажи. СТ-6.1 | H3: м2 | I3: 208.6
A4: 2 | B4: Облицовка поверхности стен СКБ с затиркой швов / керамической, керамогранитной плиткой до 0,2м2/шт | G4: 2 и 3 этажи. СТ-6.2 | H4: м2 | I4: 11.5
A5: 3 | B5: Облицовка поверхности стен СКБ с затиркой швов / керамической, керамогранитной плиткой до 0,2м2/шт | G5: 2 и 3 этажи. СТ-6.3 | H5: м2 | I5: 28.1
A6: 4 | B6: Облицовка поверхности стен СКБ с затиркой швов / керамической, керамогранитной плиткой до 0,2м2/шт | G6: 2 и 3 этажи. СТ-8 | H6: м2 | I6: 210.4
A7: 5 | B7: Облицовка поверхности стен СКБ с затиркой швов / керамической, керамогранитной плиткой до 0,2м2/шт | G7: 2 и 3 этажи. СТ-11 | H7: м2 | I7: 265.1
A9: Этаж | B9: Пом | C9: Тип | D9: Объем | F9: Этаж | G9: Пом | H9: Тип | I9: Объем
A10: 2 | B10: 2.010 | C10: СТ-6.3 | D10: 8.2 | F10: 3 | G10: 3.008 | H10: СТ-8 | I10: 33
A11: 2 | B11: 2.010 | C11: СТ-11 | D11: 66.4 | F11: 3 | G11: 3.009 | H11: СТ-11 | I11: 65.8
A12: 2 | B12: 2.011 | C12: СТ-8 | D12: 33.3 | F12: 3 | G12: 3.009 | H12: СТ-6.3 | I12: 8.1
A13: 2 | B13: 2.018 | C13: СТ-6.2 | D13: 5.7 | F13: 3 | G13: 3.015 | H13: СТ-11 | I13: 67.8
A14: 2 | B14: 2.018 | C14: СТ-11 | D14: 65.1 | F14: 3 | G14: 3.015 | H14: СТ-6.2 | I14: 5.8
A15: 2 | B15: 2.020 | C15: СТ-6.3 | D15: 5.9 | F15: 3 | G15: 3.017 | H15: СТ-6.1 | I15: 35.4
A16: 2 | B16: 2.020 | C16: СТ-6.1 | D16: 31.6 | F16: 3 | G16: 3.017 | H16: СТ-6.3 | I16: 5.9
A17: 2 | B17: 2.021 | C17: СТ-6.1 | D17: 36.9 | F17: 3 | G17: 3.018 | H17: СТ-6.1 | I17: 29.5
A18: 2 | B18: 2.034 | C18: СТ-6.1 | D18: 38.3 | F18: 3 | G18: 3.025 | H18: СТ-6.1 | I18: 36.9
A19: 2 | B19: 2.035 | C19: СТ-8 | D19: 44.2 | F19: 3 | G19: 3.026 | H19: СТ-8 | I19: 36.5
A20: 2 | B20: 2.059 | C20: СТ-8 | D20: 33.9 | F20: 3 | G20: 3.029 | H20: СТ-8 | I20: 29.5

Sheet 3.2-Ок-Ш2
A1: № п.п | B1: Наименование | C1: Описание | D1: Ед. изм. | E1: Объем
A2: 1 | B2: Штукатурка поверхностей откосов сухими смесями с предварительной огрунтовкой поверхности / толщ. 70 мм | C2: Черновая отделка под подоконники на 2 и 3 этажах СОШ2 | D2: м2 | E2: 180

Sheet 4.1-Ст
A1: Ведомость работ
A2: № п.п. | B2: Наименование затрат | H2: Описание | J2: Ед. изм. | K2: Объем
A3: 1 | H3: 2 этаж | J3: м2
A5: № пом. | B5: Тип пола | C5: Площадь, м2. | E5: № пом. | F5: Тип пола | G5: Площадь, м2.
F10: Итог: | G10: =SUM(G6:G9) -> 0
B41: Итог: | C41: =SUM(C6:C40) -> 0

Sheet 3.1-Ок-Ш2_НЗ
A1: № п.п | B1: Наименование | C1: Описание | D1: Ед. изм. | E1: Объем, (0.3) | F1: Объем, (0.34)
A2: 1 | B2: Утеплитель | C2: Утеплитель минераловатный негорючий | D2: м3 | E2: =E4*0.06 -> 39.27 | F2: =F4*0.06 -> 44.506
A3: 2 | B3: Пожарная пена | D3: м3 | E3: =E4*0.033 -> 21.5985 | F3: =F4*0.033 -> 24.4783
A4: 3 | B4: Устройство оконных откосов из ГЛВ В 2 слоя | C4: Профиль, 28х27х0.6 мм | D4: м2 | E4: =E6+E7 -> 654.5 | F4: =F6+F7 -> 741.76667
A5: 4 | B5: Подоконная заливка | C5: 7-8 см, 177.8 м2 | D5: м3 | E5: 12.4 | F5: 12.4
A6: 5 | B6: Выравнивание поверхностей откосов толщ. до 5 мм с предварительной огрунтовкой поверхности | C6: 2 этаж. Шпаклевка оконных откосов базовая. | D6: м2 | E6: =383.4 -> 383.4 | F6: =383.4/0.3*0.34 -> 434.52
A7: 6 | B7: Выравнивание поверхностей откосов толщ. до 5 мм с предварительной огрунтовкой поверхности | C7: 3 этаж. Шпаклевка оконных откосов базовая. | D7: м2 | E7: 271.1 | F7: =271.1/0.3*0.34 -> 307.24667
A8: 7 | B8: Выравнивание поверхностей откосов толщ. до 5 мм с предварительной огрунтовкой поверхности | C8: 2 этаж. Шпаклевка оконных откосов финишная. | D8: м2 | E8: =E6 -> 383.4 | F8: =F6 -> 434.52
A9: 8 | B9: Выравнивание поверхностей откосов толщ. до 5 мм с предварительной огрунтовкой поверхности | C9: 3 этаж. Шпаклевка оконных откосов финишная. | D9: м2 | E9: =E7 -> 271.1 | F9: =F7 -> 307.24667
A10: 9 | B10: Окраска поверхности откосов с предварительной огрунтовкой поверхности / в 2 слоя | C10: 2 этаж | D10: м2 | E10: =E6 -> 383.4 | F10: =F6 -> 434.52
A11: 10 | B11: Окраска поверхности откосов с предварительной огрунтовкой поверхности / в 2 слоя | C11: 3 этаж | D11: м2 | E11: =E7 -> 271.1 | F11: =F7 -> 307.24667

Sheet 3.1-Ок-Ш2
A1: № п.п | B1: Наименование | C1: Описание | D1: Ед. изм. | E1: Объем, (0.3)
A2: 1 | B2: Утеплитель | C2: Утеплитель минераловатный негорючий | D2: м3 | E2: =E4*0.06 -> 39.27
A3: 2 | B3: Пожарная пена | D3: м3 | E3: =E4*0.033 -> 21.5985
A4: 3 | B4: Устройство оконных откосов из ГЛВ В 2 слоя | C4: Профиль, 28х27х0.6 мм | D4: м2 | E4: =E6+E7 -> 654.5
A5: 4 | B5: Подоконная заливка | C5: 7-8 см, 177.8 м2 | D5: м3 | E5: 12.4
A6: 5 | B6: Выравнивание поверхностей откосов толщ. до 5 мм с предварительной огрунтовкой поверхности | C6: 2 этаж. Шпаклевка оконных откосов базовая. | D6: м2 | E6: =383.4 -> 383.4
A7: 6 | B7: Выравнивание поверхностей откосов толщ. до 5 мм с предварительной огрунтовкой поверхности | C7: 3 этаж. Шпаклевка оконных откосов базовая. | D7: м2 | E7: 271.1
A8: 7 | B8: Выравнивание поверхностей откосов толщ. до 5 мм с предварительной огрунтовкой поверхности | C8: 2 этаж. Шпаклевка оконных откосов финишная. | D8: м2 | E8: =E6 -> 383.4
A9: 8 | B9: Выравнивание поверхностей откосов толщ. до 5 мм с предварительной огрунтовкой поверхности | C9: 3 этаж. Шпаклевка оконных откосов финишная. | D9: м2 | E9: =E7 -> 271.1
A10: 9 | B10: Окраска поверхности откосов с предварительной огрунтовкой поверхности / в 2 слоя | C10: 2 этаж | D10: м2 | E10: =E6 -> 383.4
A11: 10 | B11: Окраска поверхности откосов с предварительной огрунтовкой поверхности / в 2 слоя | C11: 3 этаж | D11: м2 | E11: =E7 -> 271.1

Sheet Лист2
C6: ЗШ-1 | D6: 186.9 | E6: 35.4 | G6: ЗШ-1 | H6: 187.4 | I6: 8
C7: ЗШ-3 | D7: 2.7 | E7: 10.8 | G7: ЗШ-4 | H7: 16.7
C8: ЗШ-4 | D8: 13.8 | E8: 25.7
C10: ЗШ-2 | D10: 60.3 | E10: 0 | G10: ЗШ-2 | H10: 55.1
C12: ПО-4 | D12: 73.9 | E12: 71.9 | G12: ПО-4 | H12: 73.9 | I12: 71.9
F21: помещения | G21: ПО-4 | H21: ЗШ-1
F24: 3.005 | G24: 2.9
F25: 3.019 | G25: 15
F26: 3.011 | H26: 1
F27: 3.027 | H27: 2.9
F28: 3.038 | H28: 1.1
F29: 3.039 | H29: 3
F30: 3.054 | G30: 12,3
F31: 3.059 | G31: 5.9
